package com.millennialmedia.android;

import java.text.SimpleDateFormat;
import java.util.Map;

class BridgeMMCalendar
        extends MMJSObject {
    private static final String a = BridgeMMCalendar.class.getName();
    private static final String[] d = {"yyyy-MM-dd'T'HH:mmZZZ", "yyyy-MM-dd'T'HH:mm:ssZZZ"};
    private static final SimpleDateFormat e = new SimpleDateFormat("yyyyMMdd'T'HHmmss");

    private String a(int paramInt) {
        switch (paramInt) {
            default:
                return null;
            case 1:
                return "MO";
            case 2:
                return "TU";
            case 3:
                return "WE";
            case 4:
                return "TH";
            case 5:
                return "FR";
            case 6:
                return "SA";
        }
        return "SU";
    }

    /* Error */
    private String a(org.json.JSONObject paramJSONObject) {
        // Byte code:
        //   0: new 63	java/lang/StringBuilder
        //   3: dup
        //   4: invokespecial 64	java/lang/StringBuilder:<init>	()V
        //   7: astore_3
        //   8: aload_1
        //   9: ldc 66
        //   11: invokevirtual 72	org/json/JSONObject:getString	(Ljava/lang/String;)Ljava/lang/String;
        //   14: astore 4
        //   16: aload_3
        //   17: ldc 74
        //   19: invokevirtual 78	java/lang/StringBuilder:append	(Ljava/lang/String;)Ljava/lang/StringBuilder;
        //   22: aload 4
        //   24: invokevirtual 78	java/lang/StringBuilder:append	(Ljava/lang/String;)Ljava/lang/StringBuilder;
        //   27: ldc 80
        //   29: invokevirtual 78	java/lang/StringBuilder:append	(Ljava/lang/String;)Ljava/lang/StringBuilder;
        //   32: pop
        //   33: getstatic 38	com/millennialmedia/android/BridgeMMCalendar:e	Ljava/text/SimpleDateFormat;
        //   36: aload_1
        //   37: ldc 82
        //   39: invokevirtual 72	org/json/JSONObject:getString	(Ljava/lang/String;)Ljava/lang/String;
        //   42: getstatic 28	com/millennialmedia/android/BridgeMMCalendar:d	[Ljava/lang/String;
        //   45: invokestatic 88	org/apache/http/impl/cookie/DateUtils:parseDate	(Ljava/lang/String;[Ljava/lang/String;)Ljava/util/Date;
        //   48: invokevirtual 92	java/text/SimpleDateFormat:format	(Ljava/util/Date;)Ljava/lang/String;
        //   51: astore 4
        //   53: aload_3
        //   54: ldc 94
        //   56: invokevirtual 78	java/lang/StringBuilder:append	(Ljava/lang/String;)Ljava/lang/StringBuilder;
        //   59: aload 4
        //   61: invokevirtual 78	java/lang/StringBuilder:append	(Ljava/lang/String;)Ljava/lang/StringBuilder;
        //   64: ldc 80
        //   66: invokevirtual 78	java/lang/StringBuilder:append	(Ljava/lang/String;)Ljava/lang/StringBuilder;
        //   69: pop
        //   70: aload_1
        //   71: ldc 96
        //   73: invokevirtual 100	org/json/JSONObject:getJSONArray	(Ljava/lang/String;)Lorg/json/JSONArray;
        //   76: astore 4
        //   78: new 63	java/lang/StringBuilder
        //   81: dup
        //   82: invokespecial 64	java/lang/StringBuilder:<init>	()V
        //   85: astore 5
        //   87: iconst_0
        //   88: istore_2
        //   89: iload_2
        //   90: aload 4
        //   92: invokevirtual 106	org/json/JSONArray:length	()I
        //   95: if_icmpge +70 -> 165
        //   98: aload 5
        //   100: aload_0
        //   101: aload 4
        //   103: iload_2
        //   104: invokevirtual 110	org/json/JSONArray:getInt	(I)I
        //   107: invokespecial 112	com/millennialmedia/android/BridgeMMCalendar:a	(I)Ljava/lang/String;
        //   110: invokevirtual 78	java/lang/StringBuilder:append	(Ljava/lang/String;)Ljava/lang/StringBuilder;
        //   113: ldc 114
        //   115: invokevirtual 78	java/lang/StringBuilder:append	(Ljava/lang/String;)Ljava/lang/StringBuilder;
        //   118: pop
        //   119: iload_2
        //   120: iconst_1
        //   121: iadd
        //   122: istore_2
        //   123: goto -34 -> 89
        //   126: astore 4
        //   128: getstatic 20	com/millennialmedia/android/BridgeMMCalendar:a	Ljava/lang/String;
        //   131: ldc 116
        //   133: invokestatic 122	com/millennialmedia/android/MMLog:b	(Ljava/lang/String;Ljava/lang/String;)V
        //   136: goto -103 -> 33
        //   139: astore 4
        //   141: getstatic 20	com/millennialmedia/android/BridgeMMCalendar:a	Ljava/lang/String;
        //   144: ldc 124
        //   146: invokestatic 126	com/millennialmedia/android/MMLog:e	(Ljava/lang/String;Ljava/lang/String;)V
        //   149: goto -79 -> 70
        //   152: astore 4
        //   154: getstatic 20	com/millennialmedia/android/BridgeMMCalendar:a	Ljava/lang/String;
        //   157: ldc -128
        //   159: invokestatic 122	com/millennialmedia/android/MMLog:b	(Ljava/lang/String;Ljava/lang/String;)V
        //   162: goto -92 -> 70
        //   165: aload_3
        //   166: ldc -126
        //   168: invokevirtual 78	java/lang/StringBuilder:append	(Ljava/lang/String;)Ljava/lang/StringBuilder;
        //   171: aload 5
        //   173: invokevirtual 133	java/lang/StringBuilder:append	(Ljava/lang/CharSequence;)Ljava/lang/StringBuilder;
        //   176: ldc 80
        //   178: invokevirtual 78	java/lang/StringBuilder:append	(Ljava/lang/String;)Ljava/lang/StringBuilder;
        //   181: pop
        //   182: aload_1
        //   183: ldc -121
        //   185: invokevirtual 72	org/json/JSONObject:getString	(Ljava/lang/String;)Ljava/lang/String;
        //   188: ldc -119
        //   190: ldc -117
        //   192: invokevirtual 143	java/lang/String:replaceAll	(Ljava/lang/String;Ljava/lang/String;)Ljava/lang/String;
        //   195: ldc -111
        //   197: ldc -117
        //   199: invokevirtual 143	java/lang/String:replaceAll	(Ljava/lang/String;Ljava/lang/String;)Ljava/lang/String;
        //   202: astore 4
        //   204: aload_3
        //   205: ldc -109
        //   207: invokevirtual 78	java/lang/StringBuilder:append	(Ljava/lang/String;)Ljava/lang/StringBuilder;
        //   210: aload 4
        //   212: invokevirtual 78	java/lang/StringBuilder:append	(Ljava/lang/String;)Ljava/lang/StringBuilder;
        //   215: ldc 80
        //   217: invokevirtual 78	java/lang/StringBuilder:append	(Ljava/lang/String;)Ljava/lang/StringBuilder;
        //   220: pop
        //   221: aload_1
        //   222: ldc -107
        //   224: invokevirtual 72	org/json/JSONObject:getString	(Ljava/lang/String;)Ljava/lang/String;
        //   227: ldc -119
        //   229: ldc -117
        //   231: invokevirtual 143	java/lang/String:replaceAll	(Ljava/lang/String;Ljava/lang/String;)Ljava/lang/String;
        //   234: ldc -111
        //   236: ldc -117
        //   238: invokevirtual 143	java/lang/String:replaceAll	(Ljava/lang/String;Ljava/lang/String;)Ljava/lang/String;
        //   241: astore 4
        //   243: aload_3
        //   244: ldc -105
        //   246: invokevirtual 78	java/lang/StringBuilder:append	(Ljava/lang/String;)Ljava/lang/StringBuilder;
        //   249: aload 4
        //   251: invokevirtual 78	java/lang/StringBuilder:append	(Ljava/lang/String;)Ljava/lang/StringBuilder;
        //   254: ldc 80
        //   256: invokevirtual 78	java/lang/StringBuilder:append	(Ljava/lang/String;)Ljava/lang/StringBuilder;
        //   259: pop
        //   260: aload_1
        //   261: ldc -103
        //   263: invokevirtual 72	org/json/JSONObject:getString	(Ljava/lang/String;)Ljava/lang/String;
        //   266: astore_1
        //   267: aload_3
        //   268: ldc -101
        //   270: invokevirtual 78	java/lang/StringBuilder:append	(Ljava/lang/String;)Ljava/lang/StringBuilder;
        //   273: aload_1
        //   274: invokevirtual 78	java/lang/StringBuilder:append	(Ljava/lang/String;)Ljava/lang/StringBuilder;
        //   277: ldc 80
        //   279: invokevirtual 78	java/lang/StringBuilder:append	(Ljava/lang/String;)Ljava/lang/StringBuilder;
        //   282: pop
        //   283: aload_3
        //   284: invokevirtual 158	java/lang/StringBuilder:toString	()Ljava/lang/String;
        //   287: invokevirtual 161	java/lang/String:toUpperCase	()Ljava/lang/String;
        //   290: areturn
        //   291: astore 4
        //   293: getstatic 20	com/millennialmedia/android/BridgeMMCalendar:a	Ljava/lang/String;
        //   296: ldc -93
        //   298: invokestatic 122	com/millennialmedia/android/MMLog:b	(Ljava/lang/String;Ljava/lang/String;)V
        //   301: goto -119 -> 182
        //   304: astore 4
        //   306: getstatic 20	com/millennialmedia/android/BridgeMMCalendar:a	Ljava/lang/String;
        //   309: ldc -91
        //   311: invokestatic 122	com/millennialmedia/android/MMLog:b	(Ljava/lang/String;Ljava/lang/String;)V
        //   314: goto -93 -> 221
        //   317: astore 4
        //   319: getstatic 20	com/millennialmedia/android/BridgeMMCalendar:a	Ljava/lang/String;
        //   322: ldc -89
        //   324: invokestatic 122	com/millennialmedia/android/MMLog:b	(Ljava/lang/String;Ljava/lang/String;)V
        //   327: goto -67 -> 260
        //   330: astore_1
        //   331: getstatic 20	com/millennialmedia/android/BridgeMMCalendar:a	Ljava/lang/String;
        //   334: ldc -87
        //   336: invokestatic 122	com/millennialmedia/android/MMLog:b	(Ljava/lang/String;Ljava/lang/String;)V
        //   339: goto -56 -> 283
        // Local variable table:
        //   start	length	slot	name	signature
        //   0	342	0	this	BridgeMMCalendar
        //   0	342	1	paramJSONObject	org.json.JSONObject
        //   88	35	2	i	int
        //   7	277	3	localStringBuilder1	StringBuilder
        //   14	88	4	localObject	Object
        //   126	1	4	localJSONException1	org.json.JSONException
        //   139	1	4	localDateParseException	org.apache.http.impl.cookie.DateParseException
        //   152	1	4	localJSONException2	org.json.JSONException
        //   202	48	4	str	String
        //   291	1	4	localJSONException3	org.json.JSONException
        //   304	1	4	localJSONException4	org.json.JSONException
        //   317	1	4	localJSONException5	org.json.JSONException
        //   85	87	5	localStringBuilder2	StringBuilder
        // Exception table:
        //   from	to	target	type
        //   8	33	126	org/json/JSONException
        //   33	70	139	org/apache/http/impl/cookie/DateParseException
        //   33	70	152	org/json/JSONException
        //   70	87	291	org/json/JSONException
        //   89	119	291	org/json/JSONException
        //   165	182	291	org/json/JSONException
        //   182	221	304	org/json/JSONException
        //   221	260	317	org/json/JSONException
        //   260	283	330	org/json/JSONException
    }

    MMJSResponse a(String paramString, Map<String, String> paramMap) {
        MMJSResponse localMMJSResponse = null;
        if ("addEvent".equals(paramString)) {
            localMMJSResponse = addEvent(paramMap);
        }
        return localMMJSResponse;
    }

    /* Error */
    @android.annotation.TargetApi(14)
    public MMJSResponse addEvent(Map<String, String> paramMap) {
        // Byte code:
        //   0: getstatic 20	com/millennialmedia/android/BridgeMMCalendar:a	Ljava/lang/String;
        //   3: new 63	java/lang/StringBuilder
        //   6: dup
        //   7: invokespecial 64	java/lang/StringBuilder:<init>	()V
        //   10: ldc -70
        //   12: invokevirtual 78	java/lang/StringBuilder:append	(Ljava/lang/String;)Ljava/lang/StringBuilder;
        //   15: aload_1
        //   16: invokevirtual 189	java/lang/StringBuilder:append	(Ljava/lang/Object;)Ljava/lang/StringBuilder;
        //   19: invokevirtual 158	java/lang/StringBuilder:toString	()Ljava/lang/String;
        //   22: invokestatic 122	com/millennialmedia/android/MMLog:b	(Ljava/lang/String;Ljava/lang/String;)V
        //   25: getstatic 195	android/os/Build$VERSION:SDK_INT	I
        //   28: bipush 14
        //   30: if_icmplt +589 -> 619
        //   33: aload_1
        //   34: ifnull +583 -> 617
        //   37: aload_1
        //   38: ldc -59
        //   40: invokeinterface 203 2 0
        //   45: ifnull +572 -> 617
        //   48: new 68	org/json/JSONObject
        //   51: dup
        //   52: aload_1
        //   53: ldc -59
        //   55: invokeinterface 203 2 0
        //   60: checkcast 22	java/lang/String
        //   63: invokespecial 204	org/json/JSONObject:<init>	(Ljava/lang/String;)V
        //   66: astore_3
        //   67: aload_3
        //   68: ldc -50
        //   70: invokevirtual 72	org/json/JSONObject:getString	(Ljava/lang/String;)Ljava/lang/String;
        //   73: astore 4
        //   75: aload_3
        //   76: ldc -48
        //   78: invokevirtual 72	org/json/JSONObject:getString	(Ljava/lang/String;)Ljava/lang/String;
        //   81: astore 5
        //   83: aload_3
        //   84: ldc -46
        //   86: invokevirtual 72	org/json/JSONObject:getString	(Ljava/lang/String;)Ljava/lang/String;
        //   89: astore 6
        //   91: aload_3
        //   92: ldc -44
        //   94: invokevirtual 72	org/json/JSONObject:getString	(Ljava/lang/String;)Ljava/lang/String;
        //   97: astore 7
        //   99: aload_3
        //   100: ldc -42
        //   102: invokevirtual 72	org/json/JSONObject:getString	(Ljava/lang/String;)Ljava/lang/String;
        //   105: astore 8
        //   107: aload_3
        //   108: ldc -40
        //   110: invokevirtual 72	org/json/JSONObject:getString	(Ljava/lang/String;)Ljava/lang/String;
        //   113: astore 9
        //   115: aload_0
        //   116: aload_3
        //   117: ldc -38
        //   119: invokevirtual 222	org/json/JSONObject:getJSONObject	(Ljava/lang/String;)Lorg/json/JSONObject;
        //   122: invokespecial 224	com/millennialmedia/android/BridgeMMCalendar:a	(Lorg/json/JSONObject;)Ljava/lang/String;
        //   125: astore 10
        //   127: aload_3
        //   128: ldc -30
        //   130: invokevirtual 72	org/json/JSONObject:getString	(Ljava/lang/String;)Ljava/lang/String;
        //   133: getstatic 28	com/millennialmedia/android/BridgeMMCalendar:d	[Ljava/lang/String;
        //   136: invokestatic 88	org/apache/http/impl/cookie/DateUtils:parseDate	(Ljava/lang/String;[Ljava/lang/String;)Ljava/util/Date;
        //   139: astore_2
        //   140: aload_3
        //   141: ldc -28
        //   143: invokevirtual 72	org/json/JSONObject:getString	(Ljava/lang/String;)Ljava/lang/String;
        //   146: getstatic 28	com/millennialmedia/android/BridgeMMCalendar:d	[Ljava/lang/String;
        //   149: invokestatic 88	org/apache/http/impl/cookie/DateUtils:parseDate	(Ljava/lang/String;[Ljava/lang/String;)Ljava/util/Date;
        //   152: astore_3
        //   153: getstatic 20	com/millennialmedia/android/BridgeMMCalendar:a	Ljava/lang/String;
        //   156: ldc -26
        //   158: bipush 7
        //   160: anewarray 232	java/lang/Object
        //   163: dup
        //   164: iconst_0
        //   165: aload 4
        //   167: aastore
        //   168: dup
        //   169: iconst_1
        //   170: aload 8
        //   172: aastore
        //   173: dup
        //   174: iconst_2
        //   175: aload_2
        //   176: aastore
        //   177: dup
        //   178: iconst_3
        //   179: aload_3
        //   180: aastore
        //   181: dup
        //   182: iconst_4
        //   183: aload 9
        //   185: aastore
        //   186: dup
        //   187: iconst_5
        //   188: aload 5
        //   190: aastore
        //   191: dup
        //   192: bipush 6
        //   194: aload 10
        //   196: aastore
        //   197: invokestatic 235	java/lang/String:format	(Ljava/lang/String;[Ljava/lang/Object;)Ljava/lang/String;
        //   200: invokestatic 122	com/millennialmedia/android/MMLog:b	(Ljava/lang/String;Ljava/lang/String;)V
        //   203: aload 4
        //   205: ifnull +7 -> 212
        //   208: aload_2
        //   209: ifnonnull +200 -> 409
        //   212: getstatic 20	com/millennialmedia/android/BridgeMMCalendar:a	Ljava/lang/String;
        //   215: ldc -19
        //   217: invokestatic 126	com/millennialmedia/android/MMLog:e	(Ljava/lang/String;Ljava/lang/String;)V
        //   220: ldc -17
        //   222: invokestatic 244	com/millennialmedia/android/MMJSResponse:b	(Ljava/lang/String;)Lcom/millennialmedia/android/MMJSResponse;
        //   225: areturn
        //   226: astore_2
        //   227: getstatic 20	com/millennialmedia/android/BridgeMMCalendar:a	Ljava/lang/String;
        //   230: ldc -10
        //   232: invokestatic 126	com/millennialmedia/android/MMLog:e	(Ljava/lang/String;Ljava/lang/String;)V
        //   235: aconst_null
        //   236: astore 4
        //   238: goto -163 -> 75
        //   241: astore_2
        //   242: getstatic 20	com/millennialmedia/android/BridgeMMCalendar:a	Ljava/lang/String;
        //   245: ldc -10
        //   247: invokestatic 122	com/millennialmedia/android/MMLog:b	(Ljava/lang/String;Ljava/lang/String;)V
        //   250: aconst_null
        //   251: astore 5
        //   253: goto -170 -> 83
        //   256: astore_2
        //   257: getstatic 20	com/millennialmedia/android/BridgeMMCalendar:a	Ljava/lang/String;
        //   260: ldc -8
        //   262: invokestatic 122	com/millennialmedia/android/MMLog:b	(Ljava/lang/String;Ljava/lang/String;)V
        //   265: aconst_null
        //   266: astore 6
        //   268: goto -177 -> 91
        //   271: astore_2
        //   272: getstatic 20	com/millennialmedia/android/BridgeMMCalendar:a	Ljava/lang/String;
        //   275: ldc -6
        //   277: invokestatic 122	com/millennialmedia/android/MMLog:b	(Ljava/lang/String;Ljava/lang/String;)V
        //   280: aconst_null
        //   281: astore 7
        //   283: goto -184 -> 99
        //   286: astore_2
        //   287: getstatic 20	com/millennialmedia/android/BridgeMMCalendar:a	Ljava/lang/String;
        //   290: ldc -4
        //   292: invokestatic 122	com/millennialmedia/android/MMLog:b	(Ljava/lang/String;Ljava/lang/String;)V
        //   295: aconst_null
        //   296: astore 8
        //   298: goto -191 -> 107
        //   301: astore_2
        //   302: getstatic 20	com/millennialmedia/android/BridgeMMCalendar:a	Ljava/lang/String;
        //   305: ldc -2
        //   307: invokestatic 122	com/millennialmedia/android/MMLog:b	(Ljava/lang/String;Ljava/lang/String;)V
        //   310: aconst_null
        //   311: astore 9
        //   313: goto -198 -> 115
        //   316: astore_2
        //   317: getstatic 20	com/millennialmedia/android/BridgeMMCalendar:a	Ljava/lang/String;
        //   320: ldc_w 256
        //   323: invokestatic 122	com/millennialmedia/android/MMLog:b	(Ljava/lang/String;Ljava/lang/String;)V
        //   326: aconst_null
        //   327: astore 10
        //   329: goto -202 -> 127
        //   332: astore_2
        //   333: getstatic 20	com/millennialmedia/android/BridgeMMCalendar:a	Ljava/lang/String;
        //   336: ldc_w 258
        //   339: invokestatic 126	com/millennialmedia/android/MMLog:e	(Ljava/lang/String;Ljava/lang/String;)V
        //   342: aconst_null
        //   343: astore_2
        //   344: goto -204 -> 140
        //   347: astore_2
        //   348: getstatic 20	com/millennialmedia/android/BridgeMMCalendar:a	Ljava/lang/String;
        //   351: ldc_w 260
        //   354: invokestatic 126	com/millennialmedia/android/MMLog:e	(Ljava/lang/String;Ljava/lang/String;)V
        //   357: aconst_null
        //   358: astore_2
        //   359: goto -219 -> 140
        //   362: astore_3
        //   363: getstatic 20	com/millennialmedia/android/BridgeMMCalendar:a	Ljava/lang/String;
        //   366: ldc_w 262
        //   369: invokestatic 126	com/millennialmedia/android/MMLog:e	(Ljava/lang/String;Ljava/lang/String;)V
        //   372: aconst_null
        //   373: astore_3
        //   374: goto -221 -> 153
        //   377: astore_3
        //   378: getstatic 20	com/millennialmedia/android/BridgeMMCalendar:a	Ljava/lang/String;
        //   381: ldc_w 264
        //   384: invokestatic 122	com/millennialmedia/android/MMLog:b	(Ljava/lang/String;Ljava/lang/String;)V
        //   387: aconst_null
        //   388: astore_3
        //   389: goto -236 -> 153
        //   392: astore_1
        //   393: getstatic 20	com/millennialmedia/android/BridgeMMCalendar:a	Ljava/lang/String;
        //   396: ldc_w 266
        //   399: invokestatic 126	com/millennialmedia/android/MMLog:e	(Ljava/lang/String;Ljava/lang/String;)V
        //   402: ldc_w 268
        //   405: invokestatic 244	com/millennialmedia/android/MMJSResponse:b	(Ljava/lang/String;)Lcom/millennialmedia/android/MMJSResponse;
        //   408: areturn
        //   409: new 270	android/content/Intent
        //   412: dup
        //   413: ldc_w 272
        //   416: invokespecial 273	android/content/Intent:<init>	(Ljava/lang/String;)V
        //   419: getstatic 279	android/provider/CalendarContract$Events:CONTENT_URI	Landroid/net/Uri;
        //   422: invokevirtual 283	android/content/Intent:setData	(Landroid/net/Uri;)Landroid/content/Intent;
        //   425: astore 11
        //   427: aload_2
        //   428: ifnull +16 -> 444
        //   431: aload 11
        //   433: ldc_w 285
        //   436: aload_2
        //   437: invokevirtual 291	java/util/Date:getTime	()J
        //   440: invokevirtual 295	android/content/Intent:putExtra	(Ljava/lang/String;J)Landroid/content/Intent;
        //   443: pop
        //   444: aload_3
        //   445: ifnull +16 -> 461
        //   448: aload 11
        //   450: ldc_w 297
        //   453: aload_3
        //   454: invokevirtual 291	java/util/Date:getTime	()J
        //   457: invokevirtual 295	android/content/Intent:putExtra	(Ljava/lang/String;J)Landroid/content/Intent;
        //   460: pop
        //   461: aload 4
        //   463: ifnull +14 -> 477
        //   466: aload 11
        //   468: ldc_w 299
        //   471: aload 4
        //   473: invokevirtual 302	android/content/Intent:putExtra	(Ljava/lang/String;Ljava/lang/String;)Landroid/content/Intent;
        //   476: pop
        //   477: aload 5
        //   479: ifnull +13 -> 492
        //   482: aload 11
        //   484: ldc -50
        //   486: aload 5
        //   488: invokevirtual 302	android/content/Intent:putExtra	(Ljava/lang/String;Ljava/lang/String;)Landroid/content/Intent;
        //   491: pop
        //   492: aload 8
        //   494: ifnull +14 -> 508
        //   497: aload 11
        //   499: ldc_w 304
        //   502: aload 8
        //   504: invokevirtual 302	android/content/Intent:putExtra	(Ljava/lang/String;Ljava/lang/String;)Landroid/content/Intent;
        //   507: pop
        //   508: aload 10
        //   510: ifnull +14 -> 524
        //   513: aload 11
        //   515: ldc_w 306
        //   518: aload 10
        //   520: invokevirtual 302	android/content/Intent:putExtra	(Ljava/lang/String;Ljava/lang/String;)Landroid/content/Intent;
        //   523: pop
        //   524: aload 9
        //   526: ifnull +12 -> 538
        //   529: getstatic 20	com/millennialmedia/android/BridgeMMCalendar:a	Ljava/lang/String;
        //   532: ldc_w 308
        //   535: invokestatic 310	com/millennialmedia/android/MMLog:d	(Ljava/lang/String;Ljava/lang/String;)V
        //   538: aload 6
        //   540: ifnull +12 -> 552
        //   543: getstatic 20	com/millennialmedia/android/BridgeMMCalendar:a	Ljava/lang/String;
        //   546: ldc_w 312
        //   549: invokestatic 310	com/millennialmedia/android/MMLog:d	(Ljava/lang/String;Ljava/lang/String;)V
        //   552: aload 7
        //   554: ifnull +12 -> 566
        //   557: getstatic 20	com/millennialmedia/android/BridgeMMCalendar:a	Ljava/lang/String;
        //   560: ldc_w 314
        //   563: invokestatic 310	com/millennialmedia/android/MMLog:d	(Ljava/lang/String;Ljava/lang/String;)V
        //   566: aload_0
        //   567: getfield 317	com/millennialmedia/android/BridgeMMCalendar:b	Ljava/lang/ref/WeakReference;
        //   570: invokevirtual 322	java/lang/ref/WeakReference:get	()Ljava/lang/Object;
        //   573: checkcast 324	android/content/Context
        //   576: astore_2
        //   577: aload_2
        //   578: ifnull +39 -> 617
        //   581: aload_2
        //   582: aload 11
        //   584: invokestatic 330	com/millennialmedia/android/Utils$IntentUtils:c	(Landroid/content/Context;Landroid/content/Intent;)V
        //   587: aload_2
        //   588: ldc_w 332
        //   591: aload_0
        //   592: aload_1
        //   593: ldc_w 334
        //   596: invokeinterface 203 2 0
        //   601: checkcast 22	java/lang/String
        //   604: invokevirtual 337	com/millennialmedia/android/BridgeMMCalendar:b	(Ljava/lang/String;)J
        //   607: invokestatic 342	com/millennialmedia/android/MMSDK$Event:a	(Landroid/content/Context;Ljava/lang/String;J)V
        //   610: ldc_w 344
        //   613: invokestatic 346	com/millennialmedia/android/MMJSResponse:a	(Ljava/lang/String;)Lcom/millennialmedia/android/MMJSResponse;
        //   616: areturn
        //   617: aconst_null
        //   618: areturn
        //   619: ldc_w 348
        //   622: invokestatic 244	com/millennialmedia/android/MMJSResponse:b	(Ljava/lang/String;)Lcom/millennialmedia/android/MMJSResponse;
        //   625: areturn
        // Local variable table:
        //   start	length	slot	name	signature
        //   0	626	0	this	BridgeMMCalendar
        //   0	626	1	paramMap	Map<String, String>
        //   139	70	2	localDate	java.util.Date
        //   226	1	2	localJSONException1	org.json.JSONException
        //   241	1	2	localJSONException2	org.json.JSONException
        //   256	1	2	localJSONException3	org.json.JSONException
        //   271	1	2	localJSONException4	org.json.JSONException
        //   286	1	2	localJSONException5	org.json.JSONException
        //   301	1	2	localJSONException6	org.json.JSONException
        //   316	1	2	localJSONException7	org.json.JSONException
        //   332	1	2	localDateParseException1	org.apache.http.impl.cookie.DateParseException
        //   343	1	2	localObject1	Object
        //   347	1	2	localJSONException8	org.json.JSONException
        //   358	230	2	localContext	android.content.Context
        //   66	114	3	localObject2	Object
        //   362	1	3	localDateParseException2	org.apache.http.impl.cookie.DateParseException
        //   373	1	3	localObject3	Object
        //   377	1	3	localJSONException9	org.json.JSONException
        //   388	66	3	localObject4	Object
        //   73	399	4	str1	String
        //   81	406	5	str2	String
        //   89	450	6	str3	String
        //   97	456	7	str4	String
        //   105	398	8	str5	String
        //   113	412	9	str6	String
        //   125	394	10	str7	String
        //   425	158	11	localIntent	android.content.Intent
        // Exception table:
        //   from	to	target	type
        //   67	75	226	org/json/JSONException
        //   75	83	241	org/json/JSONException
        //   83	91	256	org/json/JSONException
        //   91	99	271	org/json/JSONException
        //   99	107	286	org/json/JSONException
        //   107	115	301	org/json/JSONException
        //   115	127	316	org/json/JSONException
        //   127	140	332	org/apache/http/impl/cookie/DateParseException
        //   127	140	347	org/json/JSONException
        //   140	153	362	org/apache/http/impl/cookie/DateParseException
        //   140	153	377	org/json/JSONException
        //   48	67	392	org/json/JSONException
        //   153	203	392	org/json/JSONException
        //   227	235	392	org/json/JSONException
        //   242	250	392	org/json/JSONException
        //   257	265	392	org/json/JSONException
        //   272	280	392	org/json/JSONException
        //   287	295	392	org/json/JSONException
        //   302	310	392	org/json/JSONException
        //   317	326	392	org/json/JSONException
        //   333	342	392	org/json/JSONException
        //   348	357	392	org/json/JSONException
        //   363	372	392	org/json/JSONException
        //   378	387	392	org/json/JSONException
    }
}


/* Location:              /Users/amaurremi/uw/stringoid stuff/static vs dynamic/ifunny/mobi.ifunny-2447-dex2jar.jar!/com/millennialmedia/android/BridgeMMCalendar.class
 * Java compiler version: 6 (50.0)
 * JD-Core Version:       0.7.1
 */