package com.google.android.gms.internal;

import android.os.Binder;
import android.os.IBinder;
import android.os.IInterface;
import android.os.Parcel;
import android.os.RemoteException;

public abstract interface gz
  extends IInterface
{
  public abstract void a(int paramInt, hb paramhb)
    throws RemoteException;
  
  public static abstract class a
    extends Binder
    implements gz
  {
    public static gz N(IBinder paramIBinder)
    {
      if (paramIBinder == null) {
        return null;
      }
      IInterface localIInterface = paramIBinder.queryLocalInterface("com.google.android.gms.location.places.internal.IPlacesCallbacks");
      if ((localIInterface != null) && ((localIInterface instanceof gz))) {
        return (gz)localIInterface;
      }
      return new a(paramIBinder);
    }
    
    public IBinder asBinder()
    {
      return this;
    }
    
    public boolean onTransact(int paramInt1, Parcel paramParcel1, Parcel paramParcel2, int paramInt2)
      throws RemoteException
    {
      switch (paramInt1)
      {
      default: 
        return super.onTransact(paramInt1, paramParcel1, paramParcel2, paramInt2);
      case 1598968902: 
        paramParcel2.writeString("com.google.android.gms.location.places.internal.IPlacesCallbacks");
        return true;
      }
      paramParcel1.enforceInterface("com.google.android.gms.location.places.internal.IPlacesCallbacks");
      paramInt1 = paramParcel1.readInt();
      if (paramParcel1.readInt() != 0) {}
      for (paramParcel1 = hb.CREATOR.an(paramParcel1);; paramParcel1 = null)
      {
        a(paramInt1, paramParcel1);
        return true;
      }
    }
    
    private static class a
      implements gz
    {
      private IBinder dU;
      
      a(IBinder paramIBinder)
      {
        this.dU = paramIBinder;
      }
      
      /* Error */
      public void a(int paramInt, hb paramhb)
        throws RemoteException
      {
        // Byte code:
        //   0: invokestatic 28	android/os/Parcel:obtain	()Landroid/os/Parcel;
        //   3: astore_3
        //   4: aload_3
        //   5: ldc 30
        //   7: invokevirtual 34	android/os/Parcel:writeInterfaceToken	(Ljava/lang/String;)V
        //   10: aload_3
        //   11: iload_1
        //   12: invokevirtual 38	android/os/Parcel:writeInt	(I)V
        //   15: aload_2
        //   16: ifnull +33 -> 49
        //   19: aload_3
        //   20: iconst_1
        //   21: invokevirtual 38	android/os/Parcel:writeInt	(I)V
        //   24: aload_2
        //   25: aload_3
        //   26: iconst_0
        //   27: invokevirtual 44	com/google/android/gms/internal/hb:writeToParcel	(Landroid/os/Parcel;I)V
        //   30: aload_0
        //   31: getfield 18	com/google/android/gms/internal/gz$a$a:dU	Landroid/os/IBinder;
        //   34: iconst_1
        //   35: aload_3
        //   36: aconst_null
        //   37: iconst_1
        //   38: invokeinterface 50 5 0
        //   43: pop
        //   44: aload_3
        //   45: invokevirtual 53	android/os/Parcel:recycle	()V
        //   48: return
        //   49: aload_3
        //   50: iconst_0
        //   51: invokevirtual 38	android/os/Parcel:writeInt	(I)V
        //   54: goto -24 -> 30
        //   57: astore_2
        //   58: aload_3
        //   59: invokevirtual 53	android/os/Parcel:recycle	()V
        //   62: aload_2
        //   63: athrow
        // Local variable table:
        //   start	length	slot	name	signature
        //   0	64	0	this	a
        //   0	64	1	paramInt	int
        //   0	64	2	paramhb	hb
        //   3	56	3	localParcel	Parcel
        // Exception table:
        //   from	to	target	type
        //   4	15	57	finally
        //   19	30	57	finally
        //   30	44	57	finally
        //   49	54	57	finally
      }
      
      public IBinder asBinder()
      {
        return this.dU;
      }
    }
  }
}


/* Location:              /Users/amaurremi/uw/stringoid/static-dynamic-comparison/apps/beyondpod/mobi.beyondpod-3368-dex2jar.jar!/com/google/android/gms/internal/gz.class
 * Java compiler version: 6 (50.0)
 * JD-Core Version:       0.7.1
 */