package com.google.android.gms.internal;

import android.os.Binder;
import android.os.IBinder;
import android.os.IInterface;
import android.os.Parcel;
import android.os.RemoteException;
import com.google.android.gms.dynamic.d;
import com.google.android.gms.dynamic.d.a;

public abstract interface ar
  extends IInterface
{
  public abstract d P()
    throws RemoteException;
  
  public abstract am Q()
    throws RemoteException;
  
  public abstract void a(am paramam)
    throws RemoteException;
  
  public abstract void a(aq paramaq)
    throws RemoteException;
  
  public abstract void a(at paramat)
    throws RemoteException;
  
  public abstract void a(dd paramdd)
    throws RemoteException;
  
  public abstract void a(dh paramdh, String paramString)
    throws RemoteException;
  
  public abstract boolean a(aj paramaj)
    throws RemoteException;
  
  public abstract void ab()
    throws RemoteException;
  
  public abstract void destroy()
    throws RemoteException;
  
  public abstract boolean isReady()
    throws RemoteException;
  
  public abstract void pause()
    throws RemoteException;
  
  public abstract void resume()
    throws RemoteException;
  
  public abstract void showInterstitial()
    throws RemoteException;
  
  public abstract void stopLoading()
    throws RemoteException;
  
  public static abstract class a
    extends Binder
    implements ar
  {
    public a()
    {
      attachInterface(this, "com.google.android.gms.ads.internal.client.IAdManager");
    }
    
    public static ar f(IBinder paramIBinder)
    {
      if (paramIBinder == null) {
        return null;
      }
      IInterface localIInterface = paramIBinder.queryLocalInterface("com.google.android.gms.ads.internal.client.IAdManager");
      if ((localIInterface != null) && ((localIInterface instanceof ar))) {
        return (ar)localIInterface;
      }
      return new a(paramIBinder);
    }
    
    public IBinder asBinder()
    {
      return this;
    }
    
    public boolean onTransact(int paramInt1, Parcel paramParcel1, Parcel paramParcel2, int paramInt2)
      throws RemoteException
    {
      d locald = null;
      Object localObject2 = null;
      Object localObject1 = null;
      int i = 0;
      boolean bool;
      switch (paramInt1)
      {
      default: 
        return super.onTransact(paramInt1, paramParcel1, paramParcel2, paramInt2);
      case 1598968902: 
        paramParcel2.writeString("com.google.android.gms.ads.internal.client.IAdManager");
        return true;
      case 1: 
        paramParcel1.enforceInterface("com.google.android.gms.ads.internal.client.IAdManager");
        locald = P();
        paramParcel2.writeNoException();
        paramParcel1 = (Parcel)localObject1;
        if (locald != null) {
          paramParcel1 = locald.asBinder();
        }
        paramParcel2.writeStrongBinder(paramParcel1);
        return true;
      case 2: 
        paramParcel1.enforceInterface("com.google.android.gms.ads.internal.client.IAdManager");
        destroy();
        paramParcel2.writeNoException();
        return true;
      case 3: 
        paramParcel1.enforceInterface("com.google.android.gms.ads.internal.client.IAdManager");
        bool = isReady();
        paramParcel2.writeNoException();
        if (bool) {}
        for (paramInt1 = 1;; paramInt1 = 0)
        {
          paramParcel2.writeInt(paramInt1);
          return true;
        }
      case 4: 
        paramParcel1.enforceInterface("com.google.android.gms.ads.internal.client.IAdManager");
        localObject1 = locald;
        if (paramParcel1.readInt() != 0) {
          localObject1 = aj.CREATOR.b(paramParcel1);
        }
        bool = a((aj)localObject1);
        paramParcel2.writeNoException();
        paramInt1 = i;
        if (bool) {
          paramInt1 = 1;
        }
        paramParcel2.writeInt(paramInt1);
        return true;
      case 5: 
        paramParcel1.enforceInterface("com.google.android.gms.ads.internal.client.IAdManager");
        pause();
        paramParcel2.writeNoException();
        return true;
      case 6: 
        paramParcel1.enforceInterface("com.google.android.gms.ads.internal.client.IAdManager");
        resume();
        paramParcel2.writeNoException();
        return true;
      case 7: 
        paramParcel1.enforceInterface("com.google.android.gms.ads.internal.client.IAdManager");
        a(aq.a.e(paramParcel1.readStrongBinder()));
        paramParcel2.writeNoException();
        return true;
      case 8: 
        paramParcel1.enforceInterface("com.google.android.gms.ads.internal.client.IAdManager");
        a(at.a.h(paramParcel1.readStrongBinder()));
        paramParcel2.writeNoException();
        return true;
      case 9: 
        paramParcel1.enforceInterface("com.google.android.gms.ads.internal.client.IAdManager");
        showInterstitial();
        paramParcel2.writeNoException();
        return true;
      case 10: 
        paramParcel1.enforceInterface("com.google.android.gms.ads.internal.client.IAdManager");
        stopLoading();
        paramParcel2.writeNoException();
        return true;
      case 11: 
        paramParcel1.enforceInterface("com.google.android.gms.ads.internal.client.IAdManager");
        ab();
        paramParcel2.writeNoException();
        return true;
      case 12: 
        paramParcel1.enforceInterface("com.google.android.gms.ads.internal.client.IAdManager");
        paramParcel1 = Q();
        paramParcel2.writeNoException();
        if (paramParcel1 != null)
        {
          paramParcel2.writeInt(1);
          paramParcel1.writeToParcel(paramParcel2, 1);
          return true;
        }
        paramParcel2.writeInt(0);
        return true;
      case 13: 
        paramParcel1.enforceInterface("com.google.android.gms.ads.internal.client.IAdManager");
        localObject1 = localObject2;
        if (paramParcel1.readInt() != 0) {
          localObject1 = am.CREATOR.c(paramParcel1);
        }
        a((am)localObject1);
        paramParcel2.writeNoException();
        return true;
      case 14: 
        paramParcel1.enforceInterface("com.google.android.gms.ads.internal.client.IAdManager");
        a(dd.a.q(paramParcel1.readStrongBinder()));
        paramParcel2.writeNoException();
        return true;
      }
      paramParcel1.enforceInterface("com.google.android.gms.ads.internal.client.IAdManager");
      a(dh.a.u(paramParcel1.readStrongBinder()), paramParcel1.readString());
      paramParcel2.writeNoException();
      return true;
    }
    
    private static class a
      implements ar
    {
      private IBinder ko;
      
      a(IBinder paramIBinder)
      {
        this.ko = paramIBinder;
      }
      
      public d P()
        throws RemoteException
      {
        Parcel localParcel1 = Parcel.obtain();
        Parcel localParcel2 = Parcel.obtain();
        try
        {
          localParcel1.writeInterfaceToken("com.google.android.gms.ads.internal.client.IAdManager");
          this.ko.transact(1, localParcel1, localParcel2, 0);
          localParcel2.readException();
          d locald = d.a.ag(localParcel2.readStrongBinder());
          return locald;
        }
        finally
        {
          localParcel2.recycle();
          localParcel1.recycle();
        }
      }
      
      /* Error */
      public am Q()
        throws RemoteException
      {
        // Byte code:
        //   0: invokestatic 29	android/os/Parcel:obtain	()Landroid/os/Parcel;
        //   3: astore_2
        //   4: invokestatic 29	android/os/Parcel:obtain	()Landroid/os/Parcel;
        //   7: astore_3
        //   8: aload_2
        //   9: ldc 31
        //   11: invokevirtual 35	android/os/Parcel:writeInterfaceToken	(Ljava/lang/String;)V
        //   14: aload_0
        //   15: getfield 18	com/google/android/gms/internal/ar$a$a:ko	Landroid/os/IBinder;
        //   18: bipush 12
        //   20: aload_2
        //   21: aload_3
        //   22: iconst_0
        //   23: invokeinterface 41 5 0
        //   28: pop
        //   29: aload_3
        //   30: invokevirtual 44	android/os/Parcel:readException	()V
        //   33: aload_3
        //   34: invokevirtual 64	android/os/Parcel:readInt	()I
        //   37: ifeq +21 -> 58
        //   40: getstatic 70	com/google/android/gms/internal/am:CREATOR	Lcom/google/android/gms/internal/an;
        //   43: aload_3
        //   44: invokevirtual 76	com/google/android/gms/internal/an:c	(Landroid/os/Parcel;)Lcom/google/android/gms/internal/am;
        //   47: astore_1
        //   48: aload_3
        //   49: invokevirtual 57	android/os/Parcel:recycle	()V
        //   52: aload_2
        //   53: invokevirtual 57	android/os/Parcel:recycle	()V
        //   56: aload_1
        //   57: areturn
        //   58: aconst_null
        //   59: astore_1
        //   60: goto -12 -> 48
        //   63: astore_1
        //   64: aload_3
        //   65: invokevirtual 57	android/os/Parcel:recycle	()V
        //   68: aload_2
        //   69: invokevirtual 57	android/os/Parcel:recycle	()V
        //   72: aload_1
        //   73: athrow
        // Local variable table:
        //   start	length	slot	name	signature
        //   0	74	0	this	a
        //   47	13	1	localam	am
        //   63	10	1	localObject	Object
        //   3	66	2	localParcel1	Parcel
        //   7	58	3	localParcel2	Parcel
        // Exception table:
        //   from	to	target	type
        //   8	48	63	finally
      }
      
      /* Error */
      public void a(am paramam)
        throws RemoteException
      {
        // Byte code:
        //   0: invokestatic 29	android/os/Parcel:obtain	()Landroid/os/Parcel;
        //   3: astore_2
        //   4: invokestatic 29	android/os/Parcel:obtain	()Landroid/os/Parcel;
        //   7: astore_3
        //   8: aload_2
        //   9: ldc 31
        //   11: invokevirtual 35	android/os/Parcel:writeInterfaceToken	(Ljava/lang/String;)V
        //   14: aload_1
        //   15: ifnull +42 -> 57
        //   18: aload_2
        //   19: iconst_1
        //   20: invokevirtual 81	android/os/Parcel:writeInt	(I)V
        //   23: aload_1
        //   24: aload_2
        //   25: iconst_0
        //   26: invokevirtual 85	com/google/android/gms/internal/am:writeToParcel	(Landroid/os/Parcel;I)V
        //   29: aload_0
        //   30: getfield 18	com/google/android/gms/internal/ar$a$a:ko	Landroid/os/IBinder;
        //   33: bipush 13
        //   35: aload_2
        //   36: aload_3
        //   37: iconst_0
        //   38: invokeinterface 41 5 0
        //   43: pop
        //   44: aload_3
        //   45: invokevirtual 44	android/os/Parcel:readException	()V
        //   48: aload_3
        //   49: invokevirtual 57	android/os/Parcel:recycle	()V
        //   52: aload_2
        //   53: invokevirtual 57	android/os/Parcel:recycle	()V
        //   56: return
        //   57: aload_2
        //   58: iconst_0
        //   59: invokevirtual 81	android/os/Parcel:writeInt	(I)V
        //   62: goto -33 -> 29
        //   65: astore_1
        //   66: aload_3
        //   67: invokevirtual 57	android/os/Parcel:recycle	()V
        //   70: aload_2
        //   71: invokevirtual 57	android/os/Parcel:recycle	()V
        //   74: aload_1
        //   75: athrow
        // Local variable table:
        //   start	length	slot	name	signature
        //   0	76	0	this	a
        //   0	76	1	paramam	am
        //   3	68	2	localParcel1	Parcel
        //   7	60	3	localParcel2	Parcel
        // Exception table:
        //   from	to	target	type
        //   8	14	65	finally
        //   18	29	65	finally
        //   29	48	65	finally
        //   57	62	65	finally
      }
      
      /* Error */
      public void a(aq paramaq)
        throws RemoteException
      {
        // Byte code:
        //   0: invokestatic 29	android/os/Parcel:obtain	()Landroid/os/Parcel;
        //   3: astore_2
        //   4: invokestatic 29	android/os/Parcel:obtain	()Landroid/os/Parcel;
        //   7: astore_3
        //   8: aload_2
        //   9: ldc 31
        //   11: invokevirtual 35	android/os/Parcel:writeInterfaceToken	(Ljava/lang/String;)V
        //   14: aload_1
        //   15: ifnull +43 -> 58
        //   18: aload_1
        //   19: invokeinterface 91 1 0
        //   24: astore_1
        //   25: aload_2
        //   26: aload_1
        //   27: invokevirtual 94	android/os/Parcel:writeStrongBinder	(Landroid/os/IBinder;)V
        //   30: aload_0
        //   31: getfield 18	com/google/android/gms/internal/ar$a$a:ko	Landroid/os/IBinder;
        //   34: bipush 7
        //   36: aload_2
        //   37: aload_3
        //   38: iconst_0
        //   39: invokeinterface 41 5 0
        //   44: pop
        //   45: aload_3
        //   46: invokevirtual 44	android/os/Parcel:readException	()V
        //   49: aload_3
        //   50: invokevirtual 57	android/os/Parcel:recycle	()V
        //   53: aload_2
        //   54: invokevirtual 57	android/os/Parcel:recycle	()V
        //   57: return
        //   58: aconst_null
        //   59: astore_1
        //   60: goto -35 -> 25
        //   63: astore_1
        //   64: aload_3
        //   65: invokevirtual 57	android/os/Parcel:recycle	()V
        //   68: aload_2
        //   69: invokevirtual 57	android/os/Parcel:recycle	()V
        //   72: aload_1
        //   73: athrow
        // Local variable table:
        //   start	length	slot	name	signature
        //   0	74	0	this	a
        //   0	74	1	paramaq	aq
        //   3	66	2	localParcel1	Parcel
        //   7	58	3	localParcel2	Parcel
        // Exception table:
        //   from	to	target	type
        //   8	14	63	finally
        //   18	25	63	finally
        //   25	49	63	finally
      }
      
      /* Error */
      public void a(at paramat)
        throws RemoteException
      {
        // Byte code:
        //   0: invokestatic 29	android/os/Parcel:obtain	()Landroid/os/Parcel;
        //   3: astore_2
        //   4: invokestatic 29	android/os/Parcel:obtain	()Landroid/os/Parcel;
        //   7: astore_3
        //   8: aload_2
        //   9: ldc 31
        //   11: invokevirtual 35	android/os/Parcel:writeInterfaceToken	(Ljava/lang/String;)V
        //   14: aload_1
        //   15: ifnull +43 -> 58
        //   18: aload_1
        //   19: invokeinterface 98 1 0
        //   24: astore_1
        //   25: aload_2
        //   26: aload_1
        //   27: invokevirtual 94	android/os/Parcel:writeStrongBinder	(Landroid/os/IBinder;)V
        //   30: aload_0
        //   31: getfield 18	com/google/android/gms/internal/ar$a$a:ko	Landroid/os/IBinder;
        //   34: bipush 8
        //   36: aload_2
        //   37: aload_3
        //   38: iconst_0
        //   39: invokeinterface 41 5 0
        //   44: pop
        //   45: aload_3
        //   46: invokevirtual 44	android/os/Parcel:readException	()V
        //   49: aload_3
        //   50: invokevirtual 57	android/os/Parcel:recycle	()V
        //   53: aload_2
        //   54: invokevirtual 57	android/os/Parcel:recycle	()V
        //   57: return
        //   58: aconst_null
        //   59: astore_1
        //   60: goto -35 -> 25
        //   63: astore_1
        //   64: aload_3
        //   65: invokevirtual 57	android/os/Parcel:recycle	()V
        //   68: aload_2
        //   69: invokevirtual 57	android/os/Parcel:recycle	()V
        //   72: aload_1
        //   73: athrow
        // Local variable table:
        //   start	length	slot	name	signature
        //   0	74	0	this	a
        //   0	74	1	paramat	at
        //   3	66	2	localParcel1	Parcel
        //   7	58	3	localParcel2	Parcel
        // Exception table:
        //   from	to	target	type
        //   8	14	63	finally
        //   18	25	63	finally
        //   25	49	63	finally
      }
      
      /* Error */
      public void a(dd paramdd)
        throws RemoteException
      {
        // Byte code:
        //   0: invokestatic 29	android/os/Parcel:obtain	()Landroid/os/Parcel;
        //   3: astore_2
        //   4: invokestatic 29	android/os/Parcel:obtain	()Landroid/os/Parcel;
        //   7: astore_3
        //   8: aload_2
        //   9: ldc 31
        //   11: invokevirtual 35	android/os/Parcel:writeInterfaceToken	(Ljava/lang/String;)V
        //   14: aload_1
        //   15: ifnull +43 -> 58
        //   18: aload_1
        //   19: invokeinterface 102 1 0
        //   24: astore_1
        //   25: aload_2
        //   26: aload_1
        //   27: invokevirtual 94	android/os/Parcel:writeStrongBinder	(Landroid/os/IBinder;)V
        //   30: aload_0
        //   31: getfield 18	com/google/android/gms/internal/ar$a$a:ko	Landroid/os/IBinder;
        //   34: bipush 14
        //   36: aload_2
        //   37: aload_3
        //   38: iconst_0
        //   39: invokeinterface 41 5 0
        //   44: pop
        //   45: aload_3
        //   46: invokevirtual 44	android/os/Parcel:readException	()V
        //   49: aload_3
        //   50: invokevirtual 57	android/os/Parcel:recycle	()V
        //   53: aload_2
        //   54: invokevirtual 57	android/os/Parcel:recycle	()V
        //   57: return
        //   58: aconst_null
        //   59: astore_1
        //   60: goto -35 -> 25
        //   63: astore_1
        //   64: aload_3
        //   65: invokevirtual 57	android/os/Parcel:recycle	()V
        //   68: aload_2
        //   69: invokevirtual 57	android/os/Parcel:recycle	()V
        //   72: aload_1
        //   73: athrow
        // Local variable table:
        //   start	length	slot	name	signature
        //   0	74	0	this	a
        //   0	74	1	paramdd	dd
        //   3	66	2	localParcel1	Parcel
        //   7	58	3	localParcel2	Parcel
        // Exception table:
        //   from	to	target	type
        //   8	14	63	finally
        //   18	25	63	finally
        //   25	49	63	finally
      }
      
      /* Error */
      public void a(dh paramdh, String paramString)
        throws RemoteException
      {
        // Byte code:
        //   0: invokestatic 29	android/os/Parcel:obtain	()Landroid/os/Parcel;
        //   3: astore_3
        //   4: invokestatic 29	android/os/Parcel:obtain	()Landroid/os/Parcel;
        //   7: astore 4
        //   9: aload_3
        //   10: ldc 31
        //   12: invokevirtual 35	android/os/Parcel:writeInterfaceToken	(Ljava/lang/String;)V
        //   15: aload_1
        //   16: ifnull +51 -> 67
        //   19: aload_1
        //   20: invokeinterface 106 1 0
        //   25: astore_1
        //   26: aload_3
        //   27: aload_1
        //   28: invokevirtual 94	android/os/Parcel:writeStrongBinder	(Landroid/os/IBinder;)V
        //   31: aload_3
        //   32: aload_2
        //   33: invokevirtual 109	android/os/Parcel:writeString	(Ljava/lang/String;)V
        //   36: aload_0
        //   37: getfield 18	com/google/android/gms/internal/ar$a$a:ko	Landroid/os/IBinder;
        //   40: bipush 15
        //   42: aload_3
        //   43: aload 4
        //   45: iconst_0
        //   46: invokeinterface 41 5 0
        //   51: pop
        //   52: aload 4
        //   54: invokevirtual 44	android/os/Parcel:readException	()V
        //   57: aload 4
        //   59: invokevirtual 57	android/os/Parcel:recycle	()V
        //   62: aload_3
        //   63: invokevirtual 57	android/os/Parcel:recycle	()V
        //   66: return
        //   67: aconst_null
        //   68: astore_1
        //   69: goto -43 -> 26
        //   72: astore_1
        //   73: aload 4
        //   75: invokevirtual 57	android/os/Parcel:recycle	()V
        //   78: aload_3
        //   79: invokevirtual 57	android/os/Parcel:recycle	()V
        //   82: aload_1
        //   83: athrow
        // Local variable table:
        //   start	length	slot	name	signature
        //   0	84	0	this	a
        //   0	84	1	paramdh	dh
        //   0	84	2	paramString	String
        //   3	76	3	localParcel1	Parcel
        //   7	67	4	localParcel2	Parcel
        // Exception table:
        //   from	to	target	type
        //   9	15	72	finally
        //   19	26	72	finally
        //   26	57	72	finally
      }
      
      public boolean a(aj paramaj)
        throws RemoteException
      {
        boolean bool = true;
        Parcel localParcel1 = Parcel.obtain();
        Parcel localParcel2 = Parcel.obtain();
        for (;;)
        {
          try
          {
            localParcel1.writeInterfaceToken("com.google.android.gms.ads.internal.client.IAdManager");
            if (paramaj != null)
            {
              localParcel1.writeInt(1);
              paramaj.writeToParcel(localParcel1, 0);
              this.ko.transact(4, localParcel1, localParcel2, 0);
              localParcel2.readException();
              int i = localParcel2.readInt();
              if (i != 0) {
                return bool;
              }
            }
            else
            {
              localParcel1.writeInt(0);
              continue;
            }
            bool = false;
          }
          finally
          {
            localParcel2.recycle();
            localParcel1.recycle();
          }
        }
      }
      
      public void ab()
        throws RemoteException
      {
        Parcel localParcel1 = Parcel.obtain();
        Parcel localParcel2 = Parcel.obtain();
        try
        {
          localParcel1.writeInterfaceToken("com.google.android.gms.ads.internal.client.IAdManager");
          this.ko.transact(11, localParcel1, localParcel2, 0);
          localParcel2.readException();
          return;
        }
        finally
        {
          localParcel2.recycle();
          localParcel1.recycle();
        }
      }
      
      public IBinder asBinder()
      {
        return this.ko;
      }
      
      public void destroy()
        throws RemoteException
      {
        Parcel localParcel1 = Parcel.obtain();
        Parcel localParcel2 = Parcel.obtain();
        try
        {
          localParcel1.writeInterfaceToken("com.google.android.gms.ads.internal.client.IAdManager");
          this.ko.transact(2, localParcel1, localParcel2, 0);
          localParcel2.readException();
          return;
        }
        finally
        {
          localParcel2.recycle();
          localParcel1.recycle();
        }
      }
      
      public boolean isReady()
        throws RemoteException
      {
        boolean bool = false;
        Parcel localParcel1 = Parcel.obtain();
        Parcel localParcel2 = Parcel.obtain();
        try
        {
          localParcel1.writeInterfaceToken("com.google.android.gms.ads.internal.client.IAdManager");
          this.ko.transact(3, localParcel1, localParcel2, 0);
          localParcel2.readException();
          int i = localParcel2.readInt();
          if (i != 0) {
            bool = true;
          }
          return bool;
        }
        finally
        {
          localParcel2.recycle();
          localParcel1.recycle();
        }
      }
      
      public void pause()
        throws RemoteException
      {
        Parcel localParcel1 = Parcel.obtain();
        Parcel localParcel2 = Parcel.obtain();
        try
        {
          localParcel1.writeInterfaceToken("com.google.android.gms.ads.internal.client.IAdManager");
          this.ko.transact(5, localParcel1, localParcel2, 0);
          localParcel2.readException();
          return;
        }
        finally
        {
          localParcel2.recycle();
          localParcel1.recycle();
        }
      }
      
      public void resume()
        throws RemoteException
      {
        Parcel localParcel1 = Parcel.obtain();
        Parcel localParcel2 = Parcel.obtain();
        try
        {
          localParcel1.writeInterfaceToken("com.google.android.gms.ads.internal.client.IAdManager");
          this.ko.transact(6, localParcel1, localParcel2, 0);
          localParcel2.readException();
          return;
        }
        finally
        {
          localParcel2.recycle();
          localParcel1.recycle();
        }
      }
      
      public void showInterstitial()
        throws RemoteException
      {
        Parcel localParcel1 = Parcel.obtain();
        Parcel localParcel2 = Parcel.obtain();
        try
        {
          localParcel1.writeInterfaceToken("com.google.android.gms.ads.internal.client.IAdManager");
          this.ko.transact(9, localParcel1, localParcel2, 0);
          localParcel2.readException();
          return;
        }
        finally
        {
          localParcel2.recycle();
          localParcel1.recycle();
        }
      }
      
      public void stopLoading()
        throws RemoteException
      {
        Parcel localParcel1 = Parcel.obtain();
        Parcel localParcel2 = Parcel.obtain();
        try
        {
          localParcel1.writeInterfaceToken("com.google.android.gms.ads.internal.client.IAdManager");
          this.ko.transact(10, localParcel1, localParcel2, 0);
          localParcel2.readException();
          return;
        }
        finally
        {
          localParcel2.recycle();
          localParcel1.recycle();
        }
      }
    }
  }
}


/* Location:              /Users/amaurremi/uw/stringoid/static-dynamic-comparison/apps/broken screen/mobi.borken.android.brokenscreen-20-dex2jar.jar!/com/google/android/gms/internal/ar.class
 * Java compiler version: 6 (50.0)
 * JD-Core Version:       0.7.1
 */