package com.google.android.gms.games.internal;

import android.os.IBinder;
import android.os.Parcel;
import com.google.android.gms.common.data.DataHolder;
import com.google.android.gms.drive.Contents;

class dl
  implements IGamesCallbacks
{
  private IBinder a;
  
  dl(IBinder paramIBinder)
  {
    this.a = paramIBinder;
  }
  
  /* Error */
  public void A(DataHolder paramDataHolder)
  {
    // Byte code:
    //   0: invokestatic 24	android/os/Parcel:obtain	()Landroid/os/Parcel;
    //   3: astore_2
    //   4: invokestatic 24	android/os/Parcel:obtain	()Landroid/os/Parcel;
    //   7: astore_3
    //   8: aload_2
    //   9: ldc 26
    //   11: invokevirtual 30	android/os/Parcel:writeInterfaceToken	(Ljava/lang/String;)V
    //   14: aload_1
    //   15: ifnull +43 -> 58
    //   18: aload_2
    //   19: iconst_1
    //   20: invokevirtual 34	android/os/Parcel:writeInt	(I)V
    //   23: aload_1
    //   24: aload_2
    //   25: iconst_0
    //   26: invokevirtual 40	com/google/android/gms/common/data/DataHolder:writeToParcel	(Landroid/os/Parcel;I)V
    //   29: aload_0
    //   30: getfield 15	com/google/android/gms/games/internal/dl:a	Landroid/os/IBinder;
    //   33: sipush 5025
    //   36: aload_2
    //   37: aload_3
    //   38: iconst_0
    //   39: invokeinterface 46 5 0
    //   44: pop
    //   45: aload_3
    //   46: invokevirtual 49	android/os/Parcel:readException	()V
    //   49: aload_3
    //   50: invokevirtual 52	android/os/Parcel:recycle	()V
    //   53: aload_2
    //   54: invokevirtual 52	android/os/Parcel:recycle	()V
    //   57: return
    //   58: aload_2
    //   59: iconst_0
    //   60: invokevirtual 34	android/os/Parcel:writeInt	(I)V
    //   63: goto -34 -> 29
    //   66: astore_1
    //   67: aload_3
    //   68: invokevirtual 52	android/os/Parcel:recycle	()V
    //   71: aload_2
    //   72: invokevirtual 52	android/os/Parcel:recycle	()V
    //   75: aload_1
    //   76: athrow
    // Local variable table:
    //   start	length	slot	name	signature
    //   0	77	0	this	dl
    //   0	77	1	paramDataHolder	DataHolder
    //   3	69	2	localParcel1	Parcel
    //   7	61	3	localParcel2	Parcel
    // Exception table:
    //   from	to	target	type
    //   8	14	66	finally
    //   18	29	66	finally
    //   29	49	66	finally
    //   58	63	66	finally
  }
  
  /* Error */
  public void B(DataHolder paramDataHolder)
  {
    // Byte code:
    //   0: invokestatic 24	android/os/Parcel:obtain	()Landroid/os/Parcel;
    //   3: astore_2
    //   4: invokestatic 24	android/os/Parcel:obtain	()Landroid/os/Parcel;
    //   7: astore_3
    //   8: aload_2
    //   9: ldc 26
    //   11: invokevirtual 30	android/os/Parcel:writeInterfaceToken	(Ljava/lang/String;)V
    //   14: aload_1
    //   15: ifnull +43 -> 58
    //   18: aload_2
    //   19: iconst_1
    //   20: invokevirtual 34	android/os/Parcel:writeInt	(I)V
    //   23: aload_1
    //   24: aload_2
    //   25: iconst_0
    //   26: invokevirtual 40	com/google/android/gms/common/data/DataHolder:writeToParcel	(Landroid/os/Parcel;I)V
    //   29: aload_0
    //   30: getfield 15	com/google/android/gms/games/internal/dl:a	Landroid/os/IBinder;
    //   33: sipush 5038
    //   36: aload_2
    //   37: aload_3
    //   38: iconst_0
    //   39: invokeinterface 46 5 0
    //   44: pop
    //   45: aload_3
    //   46: invokevirtual 49	android/os/Parcel:readException	()V
    //   49: aload_3
    //   50: invokevirtual 52	android/os/Parcel:recycle	()V
    //   53: aload_2
    //   54: invokevirtual 52	android/os/Parcel:recycle	()V
    //   57: return
    //   58: aload_2
    //   59: iconst_0
    //   60: invokevirtual 34	android/os/Parcel:writeInt	(I)V
    //   63: goto -34 -> 29
    //   66: astore_1
    //   67: aload_3
    //   68: invokevirtual 52	android/os/Parcel:recycle	()V
    //   71: aload_2
    //   72: invokevirtual 52	android/os/Parcel:recycle	()V
    //   75: aload_1
    //   76: athrow
    // Local variable table:
    //   start	length	slot	name	signature
    //   0	77	0	this	dl
    //   0	77	1	paramDataHolder	DataHolder
    //   3	69	2	localParcel1	Parcel
    //   7	61	3	localParcel2	Parcel
    // Exception table:
    //   from	to	target	type
    //   8	14	66	finally
    //   18	29	66	finally
    //   29	49	66	finally
    //   58	63	66	finally
  }
  
  /* Error */
  public void C(DataHolder paramDataHolder)
  {
    // Byte code:
    //   0: invokestatic 24	android/os/Parcel:obtain	()Landroid/os/Parcel;
    //   3: astore_2
    //   4: invokestatic 24	android/os/Parcel:obtain	()Landroid/os/Parcel;
    //   7: astore_3
    //   8: aload_2
    //   9: ldc 26
    //   11: invokevirtual 30	android/os/Parcel:writeInterfaceToken	(Ljava/lang/String;)V
    //   14: aload_1
    //   15: ifnull +43 -> 58
    //   18: aload_2
    //   19: iconst_1
    //   20: invokevirtual 34	android/os/Parcel:writeInt	(I)V
    //   23: aload_1
    //   24: aload_2
    //   25: iconst_0
    //   26: invokevirtual 40	com/google/android/gms/common/data/DataHolder:writeToParcel	(Landroid/os/Parcel;I)V
    //   29: aload_0
    //   30: getfield 15	com/google/android/gms/games/internal/dl:a	Landroid/os/IBinder;
    //   33: sipush 5035
    //   36: aload_2
    //   37: aload_3
    //   38: iconst_0
    //   39: invokeinterface 46 5 0
    //   44: pop
    //   45: aload_3
    //   46: invokevirtual 49	android/os/Parcel:readException	()V
    //   49: aload_3
    //   50: invokevirtual 52	android/os/Parcel:recycle	()V
    //   53: aload_2
    //   54: invokevirtual 52	android/os/Parcel:recycle	()V
    //   57: return
    //   58: aload_2
    //   59: iconst_0
    //   60: invokevirtual 34	android/os/Parcel:writeInt	(I)V
    //   63: goto -34 -> 29
    //   66: astore_1
    //   67: aload_3
    //   68: invokevirtual 52	android/os/Parcel:recycle	()V
    //   71: aload_2
    //   72: invokevirtual 52	android/os/Parcel:recycle	()V
    //   75: aload_1
    //   76: athrow
    // Local variable table:
    //   start	length	slot	name	signature
    //   0	77	0	this	dl
    //   0	77	1	paramDataHolder	DataHolder
    //   3	69	2	localParcel1	Parcel
    //   7	61	3	localParcel2	Parcel
    // Exception table:
    //   from	to	target	type
    //   8	14	66	finally
    //   18	29	66	finally
    //   29	49	66	finally
    //   58	63	66	finally
  }
  
  /* Error */
  public void D(DataHolder paramDataHolder)
  {
    // Byte code:
    //   0: invokestatic 24	android/os/Parcel:obtain	()Landroid/os/Parcel;
    //   3: astore_2
    //   4: invokestatic 24	android/os/Parcel:obtain	()Landroid/os/Parcel;
    //   7: astore_3
    //   8: aload_2
    //   9: ldc 26
    //   11: invokevirtual 30	android/os/Parcel:writeInterfaceToken	(Ljava/lang/String;)V
    //   14: aload_1
    //   15: ifnull +43 -> 58
    //   18: aload_2
    //   19: iconst_1
    //   20: invokevirtual 34	android/os/Parcel:writeInt	(I)V
    //   23: aload_1
    //   24: aload_2
    //   25: iconst_0
    //   26: invokevirtual 40	com/google/android/gms/common/data/DataHolder:writeToParcel	(Landroid/os/Parcel;I)V
    //   29: aload_0
    //   30: getfield 15	com/google/android/gms/games/internal/dl:a	Landroid/os/IBinder;
    //   33: sipush 5039
    //   36: aload_2
    //   37: aload_3
    //   38: iconst_0
    //   39: invokeinterface 46 5 0
    //   44: pop
    //   45: aload_3
    //   46: invokevirtual 49	android/os/Parcel:readException	()V
    //   49: aload_3
    //   50: invokevirtual 52	android/os/Parcel:recycle	()V
    //   53: aload_2
    //   54: invokevirtual 52	android/os/Parcel:recycle	()V
    //   57: return
    //   58: aload_2
    //   59: iconst_0
    //   60: invokevirtual 34	android/os/Parcel:writeInt	(I)V
    //   63: goto -34 -> 29
    //   66: astore_1
    //   67: aload_3
    //   68: invokevirtual 52	android/os/Parcel:recycle	()V
    //   71: aload_2
    //   72: invokevirtual 52	android/os/Parcel:recycle	()V
    //   75: aload_1
    //   76: athrow
    // Local variable table:
    //   start	length	slot	name	signature
    //   0	77	0	this	dl
    //   0	77	1	paramDataHolder	DataHolder
    //   3	69	2	localParcel1	Parcel
    //   7	61	3	localParcel2	Parcel
    // Exception table:
    //   from	to	target	type
    //   8	14	66	finally
    //   18	29	66	finally
    //   29	49	66	finally
    //   58	63	66	finally
  }
  
  /* Error */
  public void E(DataHolder paramDataHolder)
  {
    // Byte code:
    //   0: invokestatic 24	android/os/Parcel:obtain	()Landroid/os/Parcel;
    //   3: astore_2
    //   4: invokestatic 24	android/os/Parcel:obtain	()Landroid/os/Parcel;
    //   7: astore_3
    //   8: aload_2
    //   9: ldc 26
    //   11: invokevirtual 30	android/os/Parcel:writeInterfaceToken	(Ljava/lang/String;)V
    //   14: aload_1
    //   15: ifnull +43 -> 58
    //   18: aload_2
    //   19: iconst_1
    //   20: invokevirtual 34	android/os/Parcel:writeInt	(I)V
    //   23: aload_1
    //   24: aload_2
    //   25: iconst_0
    //   26: invokevirtual 40	com/google/android/gms/common/data/DataHolder:writeToParcel	(Landroid/os/Parcel;I)V
    //   29: aload_0
    //   30: getfield 15	com/google/android/gms/games/internal/dl:a	Landroid/os/IBinder;
    //   33: sipush 8001
    //   36: aload_2
    //   37: aload_3
    //   38: iconst_0
    //   39: invokeinterface 46 5 0
    //   44: pop
    //   45: aload_3
    //   46: invokevirtual 49	android/os/Parcel:readException	()V
    //   49: aload_3
    //   50: invokevirtual 52	android/os/Parcel:recycle	()V
    //   53: aload_2
    //   54: invokevirtual 52	android/os/Parcel:recycle	()V
    //   57: return
    //   58: aload_2
    //   59: iconst_0
    //   60: invokevirtual 34	android/os/Parcel:writeInt	(I)V
    //   63: goto -34 -> 29
    //   66: astore_1
    //   67: aload_3
    //   68: invokevirtual 52	android/os/Parcel:recycle	()V
    //   71: aload_2
    //   72: invokevirtual 52	android/os/Parcel:recycle	()V
    //   75: aload_1
    //   76: athrow
    // Local variable table:
    //   start	length	slot	name	signature
    //   0	77	0	this	dl
    //   0	77	1	paramDataHolder	DataHolder
    //   3	69	2	localParcel1	Parcel
    //   7	61	3	localParcel2	Parcel
    // Exception table:
    //   from	to	target	type
    //   8	14	66	finally
    //   18	29	66	finally
    //   29	49	66	finally
    //   58	63	66	finally
  }
  
  /* Error */
  public void F(DataHolder paramDataHolder)
  {
    // Byte code:
    //   0: invokestatic 24	android/os/Parcel:obtain	()Landroid/os/Parcel;
    //   3: astore_2
    //   4: invokestatic 24	android/os/Parcel:obtain	()Landroid/os/Parcel;
    //   7: astore_3
    //   8: aload_2
    //   9: ldc 26
    //   11: invokevirtual 30	android/os/Parcel:writeInterfaceToken	(Ljava/lang/String;)V
    //   14: aload_1
    //   15: ifnull +43 -> 58
    //   18: aload_2
    //   19: iconst_1
    //   20: invokevirtual 34	android/os/Parcel:writeInt	(I)V
    //   23: aload_1
    //   24: aload_2
    //   25: iconst_0
    //   26: invokevirtual 40	com/google/android/gms/common/data/DataHolder:writeToParcel	(Landroid/os/Parcel;I)V
    //   29: aload_0
    //   30: getfield 15	com/google/android/gms/games/internal/dl:a	Landroid/os/IBinder;
    //   33: sipush 10003
    //   36: aload_2
    //   37: aload_3
    //   38: iconst_0
    //   39: invokeinterface 46 5 0
    //   44: pop
    //   45: aload_3
    //   46: invokevirtual 49	android/os/Parcel:readException	()V
    //   49: aload_3
    //   50: invokevirtual 52	android/os/Parcel:recycle	()V
    //   53: aload_2
    //   54: invokevirtual 52	android/os/Parcel:recycle	()V
    //   57: return
    //   58: aload_2
    //   59: iconst_0
    //   60: invokevirtual 34	android/os/Parcel:writeInt	(I)V
    //   63: goto -34 -> 29
    //   66: astore_1
    //   67: aload_3
    //   68: invokevirtual 52	android/os/Parcel:recycle	()V
    //   71: aload_2
    //   72: invokevirtual 52	android/os/Parcel:recycle	()V
    //   75: aload_1
    //   76: athrow
    // Local variable table:
    //   start	length	slot	name	signature
    //   0	77	0	this	dl
    //   0	77	1	paramDataHolder	DataHolder
    //   3	69	2	localParcel1	Parcel
    //   7	61	3	localParcel2	Parcel
    // Exception table:
    //   from	to	target	type
    //   8	14	66	finally
    //   18	29	66	finally
    //   29	49	66	finally
    //   58	63	66	finally
  }
  
  /* Error */
  public void G(DataHolder paramDataHolder)
  {
    // Byte code:
    //   0: invokestatic 24	android/os/Parcel:obtain	()Landroid/os/Parcel;
    //   3: astore_2
    //   4: invokestatic 24	android/os/Parcel:obtain	()Landroid/os/Parcel;
    //   7: astore_3
    //   8: aload_2
    //   9: ldc 26
    //   11: invokevirtual 30	android/os/Parcel:writeInterfaceToken	(Ljava/lang/String;)V
    //   14: aload_1
    //   15: ifnull +43 -> 58
    //   18: aload_2
    //   19: iconst_1
    //   20: invokevirtual 34	android/os/Parcel:writeInt	(I)V
    //   23: aload_1
    //   24: aload_2
    //   25: iconst_0
    //   26: invokevirtual 40	com/google/android/gms/common/data/DataHolder:writeToParcel	(Landroid/os/Parcel;I)V
    //   29: aload_0
    //   30: getfield 15	com/google/android/gms/games/internal/dl:a	Landroid/os/IBinder;
    //   33: sipush 10004
    //   36: aload_2
    //   37: aload_3
    //   38: iconst_0
    //   39: invokeinterface 46 5 0
    //   44: pop
    //   45: aload_3
    //   46: invokevirtual 49	android/os/Parcel:readException	()V
    //   49: aload_3
    //   50: invokevirtual 52	android/os/Parcel:recycle	()V
    //   53: aload_2
    //   54: invokevirtual 52	android/os/Parcel:recycle	()V
    //   57: return
    //   58: aload_2
    //   59: iconst_0
    //   60: invokevirtual 34	android/os/Parcel:writeInt	(I)V
    //   63: goto -34 -> 29
    //   66: astore_1
    //   67: aload_3
    //   68: invokevirtual 52	android/os/Parcel:recycle	()V
    //   71: aload_2
    //   72: invokevirtual 52	android/os/Parcel:recycle	()V
    //   75: aload_1
    //   76: athrow
    // Local variable table:
    //   start	length	slot	name	signature
    //   0	77	0	this	dl
    //   0	77	1	paramDataHolder	DataHolder
    //   3	69	2	localParcel1	Parcel
    //   7	61	3	localParcel2	Parcel
    // Exception table:
    //   from	to	target	type
    //   8	14	66	finally
    //   18	29	66	finally
    //   29	49	66	finally
    //   58	63	66	finally
  }
  
  /* Error */
  public void H(DataHolder paramDataHolder)
  {
    // Byte code:
    //   0: invokestatic 24	android/os/Parcel:obtain	()Landroid/os/Parcel;
    //   3: astore_2
    //   4: invokestatic 24	android/os/Parcel:obtain	()Landroid/os/Parcel;
    //   7: astore_3
    //   8: aload_2
    //   9: ldc 26
    //   11: invokevirtual 30	android/os/Parcel:writeInterfaceToken	(Ljava/lang/String;)V
    //   14: aload_1
    //   15: ifnull +43 -> 58
    //   18: aload_2
    //   19: iconst_1
    //   20: invokevirtual 34	android/os/Parcel:writeInt	(I)V
    //   23: aload_1
    //   24: aload_2
    //   25: iconst_0
    //   26: invokevirtual 40	com/google/android/gms/common/data/DataHolder:writeToParcel	(Landroid/os/Parcel;I)V
    //   29: aload_0
    //   30: getfield 15	com/google/android/gms/games/internal/dl:a	Landroid/os/IBinder;
    //   33: sipush 10006
    //   36: aload_2
    //   37: aload_3
    //   38: iconst_0
    //   39: invokeinterface 46 5 0
    //   44: pop
    //   45: aload_3
    //   46: invokevirtual 49	android/os/Parcel:readException	()V
    //   49: aload_3
    //   50: invokevirtual 52	android/os/Parcel:recycle	()V
    //   53: aload_2
    //   54: invokevirtual 52	android/os/Parcel:recycle	()V
    //   57: return
    //   58: aload_2
    //   59: iconst_0
    //   60: invokevirtual 34	android/os/Parcel:writeInt	(I)V
    //   63: goto -34 -> 29
    //   66: astore_1
    //   67: aload_3
    //   68: invokevirtual 52	android/os/Parcel:recycle	()V
    //   71: aload_2
    //   72: invokevirtual 52	android/os/Parcel:recycle	()V
    //   75: aload_1
    //   76: athrow
    // Local variable table:
    //   start	length	slot	name	signature
    //   0	77	0	this	dl
    //   0	77	1	paramDataHolder	DataHolder
    //   3	69	2	localParcel1	Parcel
    //   7	61	3	localParcel2	Parcel
    // Exception table:
    //   from	to	target	type
    //   8	14	66	finally
    //   18	29	66	finally
    //   29	49	66	finally
    //   58	63	66	finally
  }
  
  /* Error */
  public void I(DataHolder paramDataHolder)
  {
    // Byte code:
    //   0: invokestatic 24	android/os/Parcel:obtain	()Landroid/os/Parcel;
    //   3: astore_2
    //   4: invokestatic 24	android/os/Parcel:obtain	()Landroid/os/Parcel;
    //   7: astore_3
    //   8: aload_2
    //   9: ldc 26
    //   11: invokevirtual 30	android/os/Parcel:writeInterfaceToken	(Ljava/lang/String;)V
    //   14: aload_1
    //   15: ifnull +43 -> 58
    //   18: aload_2
    //   19: iconst_1
    //   20: invokevirtual 34	android/os/Parcel:writeInt	(I)V
    //   23: aload_1
    //   24: aload_2
    //   25: iconst_0
    //   26: invokevirtual 40	com/google/android/gms/common/data/DataHolder:writeToParcel	(Landroid/os/Parcel;I)V
    //   29: aload_0
    //   30: getfield 15	com/google/android/gms/games/internal/dl:a	Landroid/os/IBinder;
    //   33: sipush 12001
    //   36: aload_2
    //   37: aload_3
    //   38: iconst_0
    //   39: invokeinterface 46 5 0
    //   44: pop
    //   45: aload_3
    //   46: invokevirtual 49	android/os/Parcel:readException	()V
    //   49: aload_3
    //   50: invokevirtual 52	android/os/Parcel:recycle	()V
    //   53: aload_2
    //   54: invokevirtual 52	android/os/Parcel:recycle	()V
    //   57: return
    //   58: aload_2
    //   59: iconst_0
    //   60: invokevirtual 34	android/os/Parcel:writeInt	(I)V
    //   63: goto -34 -> 29
    //   66: astore_1
    //   67: aload_3
    //   68: invokevirtual 52	android/os/Parcel:recycle	()V
    //   71: aload_2
    //   72: invokevirtual 52	android/os/Parcel:recycle	()V
    //   75: aload_1
    //   76: athrow
    // Local variable table:
    //   start	length	slot	name	signature
    //   0	77	0	this	dl
    //   0	77	1	paramDataHolder	DataHolder
    //   3	69	2	localParcel1	Parcel
    //   7	61	3	localParcel2	Parcel
    // Exception table:
    //   from	to	target	type
    //   8	14	66	finally
    //   18	29	66	finally
    //   29	49	66	finally
    //   58	63	66	finally
  }
  
  /* Error */
  public void J(DataHolder paramDataHolder)
  {
    // Byte code:
    //   0: invokestatic 24	android/os/Parcel:obtain	()Landroid/os/Parcel;
    //   3: astore_2
    //   4: invokestatic 24	android/os/Parcel:obtain	()Landroid/os/Parcel;
    //   7: astore_3
    //   8: aload_2
    //   9: ldc 26
    //   11: invokevirtual 30	android/os/Parcel:writeInterfaceToken	(Ljava/lang/String;)V
    //   14: aload_1
    //   15: ifnull +43 -> 58
    //   18: aload_2
    //   19: iconst_1
    //   20: invokevirtual 34	android/os/Parcel:writeInt	(I)V
    //   23: aload_1
    //   24: aload_2
    //   25: iconst_0
    //   26: invokevirtual 40	com/google/android/gms/common/data/DataHolder:writeToParcel	(Landroid/os/Parcel;I)V
    //   29: aload_0
    //   30: getfield 15	com/google/android/gms/games/internal/dl:a	Landroid/os/IBinder;
    //   33: sipush 12005
    //   36: aload_2
    //   37: aload_3
    //   38: iconst_0
    //   39: invokeinterface 46 5 0
    //   44: pop
    //   45: aload_3
    //   46: invokevirtual 49	android/os/Parcel:readException	()V
    //   49: aload_3
    //   50: invokevirtual 52	android/os/Parcel:recycle	()V
    //   53: aload_2
    //   54: invokevirtual 52	android/os/Parcel:recycle	()V
    //   57: return
    //   58: aload_2
    //   59: iconst_0
    //   60: invokevirtual 34	android/os/Parcel:writeInt	(I)V
    //   63: goto -34 -> 29
    //   66: astore_1
    //   67: aload_3
    //   68: invokevirtual 52	android/os/Parcel:recycle	()V
    //   71: aload_2
    //   72: invokevirtual 52	android/os/Parcel:recycle	()V
    //   75: aload_1
    //   76: athrow
    // Local variable table:
    //   start	length	slot	name	signature
    //   0	77	0	this	dl
    //   0	77	1	paramDataHolder	DataHolder
    //   3	69	2	localParcel1	Parcel
    //   7	61	3	localParcel2	Parcel
    // Exception table:
    //   from	to	target	type
    //   8	14	66	finally
    //   18	29	66	finally
    //   29	49	66	finally
    //   58	63	66	finally
  }
  
  /* Error */
  public void K(DataHolder paramDataHolder)
  {
    // Byte code:
    //   0: invokestatic 24	android/os/Parcel:obtain	()Landroid/os/Parcel;
    //   3: astore_2
    //   4: invokestatic 24	android/os/Parcel:obtain	()Landroid/os/Parcel;
    //   7: astore_3
    //   8: aload_2
    //   9: ldc 26
    //   11: invokevirtual 30	android/os/Parcel:writeInterfaceToken	(Ljava/lang/String;)V
    //   14: aload_1
    //   15: ifnull +43 -> 58
    //   18: aload_2
    //   19: iconst_1
    //   20: invokevirtual 34	android/os/Parcel:writeInt	(I)V
    //   23: aload_1
    //   24: aload_2
    //   25: iconst_0
    //   26: invokevirtual 40	com/google/android/gms/common/data/DataHolder:writeToParcel	(Landroid/os/Parcel;I)V
    //   29: aload_0
    //   30: getfield 15	com/google/android/gms/games/internal/dl:a	Landroid/os/IBinder;
    //   33: sipush 12006
    //   36: aload_2
    //   37: aload_3
    //   38: iconst_0
    //   39: invokeinterface 46 5 0
    //   44: pop
    //   45: aload_3
    //   46: invokevirtual 49	android/os/Parcel:readException	()V
    //   49: aload_3
    //   50: invokevirtual 52	android/os/Parcel:recycle	()V
    //   53: aload_2
    //   54: invokevirtual 52	android/os/Parcel:recycle	()V
    //   57: return
    //   58: aload_2
    //   59: iconst_0
    //   60: invokevirtual 34	android/os/Parcel:writeInt	(I)V
    //   63: goto -34 -> 29
    //   66: astore_1
    //   67: aload_3
    //   68: invokevirtual 52	android/os/Parcel:recycle	()V
    //   71: aload_2
    //   72: invokevirtual 52	android/os/Parcel:recycle	()V
    //   75: aload_1
    //   76: athrow
    // Local variable table:
    //   start	length	slot	name	signature
    //   0	77	0	this	dl
    //   0	77	1	paramDataHolder	DataHolder
    //   3	69	2	localParcel1	Parcel
    //   7	61	3	localParcel2	Parcel
    // Exception table:
    //   from	to	target	type
    //   8	14	66	finally
    //   18	29	66	finally
    //   29	49	66	finally
    //   58	63	66	finally
  }
  
  /* Error */
  public void L(DataHolder paramDataHolder)
  {
    // Byte code:
    //   0: invokestatic 24	android/os/Parcel:obtain	()Landroid/os/Parcel;
    //   3: astore_2
    //   4: invokestatic 24	android/os/Parcel:obtain	()Landroid/os/Parcel;
    //   7: astore_3
    //   8: aload_2
    //   9: ldc 26
    //   11: invokevirtual 30	android/os/Parcel:writeInterfaceToken	(Ljava/lang/String;)V
    //   14: aload_1
    //   15: ifnull +43 -> 58
    //   18: aload_2
    //   19: iconst_1
    //   20: invokevirtual 34	android/os/Parcel:writeInt	(I)V
    //   23: aload_1
    //   24: aload_2
    //   25: iconst_0
    //   26: invokevirtual 40	com/google/android/gms/common/data/DataHolder:writeToParcel	(Landroid/os/Parcel;I)V
    //   29: aload_0
    //   30: getfield 15	com/google/android/gms/games/internal/dl:a	Landroid/os/IBinder;
    //   33: sipush 12007
    //   36: aload_2
    //   37: aload_3
    //   38: iconst_0
    //   39: invokeinterface 46 5 0
    //   44: pop
    //   45: aload_3
    //   46: invokevirtual 49	android/os/Parcel:readException	()V
    //   49: aload_3
    //   50: invokevirtual 52	android/os/Parcel:recycle	()V
    //   53: aload_2
    //   54: invokevirtual 52	android/os/Parcel:recycle	()V
    //   57: return
    //   58: aload_2
    //   59: iconst_0
    //   60: invokevirtual 34	android/os/Parcel:writeInt	(I)V
    //   63: goto -34 -> 29
    //   66: astore_1
    //   67: aload_3
    //   68: invokevirtual 52	android/os/Parcel:recycle	()V
    //   71: aload_2
    //   72: invokevirtual 52	android/os/Parcel:recycle	()V
    //   75: aload_1
    //   76: athrow
    // Local variable table:
    //   start	length	slot	name	signature
    //   0	77	0	this	dl
    //   0	77	1	paramDataHolder	DataHolder
    //   3	69	2	localParcel1	Parcel
    //   7	61	3	localParcel2	Parcel
    // Exception table:
    //   from	to	target	type
    //   8	14	66	finally
    //   18	29	66	finally
    //   29	49	66	finally
    //   58	63	66	finally
  }
  
  /* Error */
  public void M(DataHolder paramDataHolder)
  {
    // Byte code:
    //   0: invokestatic 24	android/os/Parcel:obtain	()Landroid/os/Parcel;
    //   3: astore_2
    //   4: invokestatic 24	android/os/Parcel:obtain	()Landroid/os/Parcel;
    //   7: astore_3
    //   8: aload_2
    //   9: ldc 26
    //   11: invokevirtual 30	android/os/Parcel:writeInterfaceToken	(Ljava/lang/String;)V
    //   14: aload_1
    //   15: ifnull +43 -> 58
    //   18: aload_2
    //   19: iconst_1
    //   20: invokevirtual 34	android/os/Parcel:writeInt	(I)V
    //   23: aload_1
    //   24: aload_2
    //   25: iconst_0
    //   26: invokevirtual 40	com/google/android/gms/common/data/DataHolder:writeToParcel	(Landroid/os/Parcel;I)V
    //   29: aload_0
    //   30: getfield 15	com/google/android/gms/games/internal/dl:a	Landroid/os/IBinder;
    //   33: sipush 12014
    //   36: aload_2
    //   37: aload_3
    //   38: iconst_0
    //   39: invokeinterface 46 5 0
    //   44: pop
    //   45: aload_3
    //   46: invokevirtual 49	android/os/Parcel:readException	()V
    //   49: aload_3
    //   50: invokevirtual 52	android/os/Parcel:recycle	()V
    //   53: aload_2
    //   54: invokevirtual 52	android/os/Parcel:recycle	()V
    //   57: return
    //   58: aload_2
    //   59: iconst_0
    //   60: invokevirtual 34	android/os/Parcel:writeInt	(I)V
    //   63: goto -34 -> 29
    //   66: astore_1
    //   67: aload_3
    //   68: invokevirtual 52	android/os/Parcel:recycle	()V
    //   71: aload_2
    //   72: invokevirtual 52	android/os/Parcel:recycle	()V
    //   75: aload_1
    //   76: athrow
    // Local variable table:
    //   start	length	slot	name	signature
    //   0	77	0	this	dl
    //   0	77	1	paramDataHolder	DataHolder
    //   3	69	2	localParcel1	Parcel
    //   7	61	3	localParcel2	Parcel
    // Exception table:
    //   from	to	target	type
    //   8	14	66	finally
    //   18	29	66	finally
    //   29	49	66	finally
    //   58	63	66	finally
  }
  
  /* Error */
  public void N(DataHolder paramDataHolder)
  {
    // Byte code:
    //   0: invokestatic 24	android/os/Parcel:obtain	()Landroid/os/Parcel;
    //   3: astore_2
    //   4: invokestatic 24	android/os/Parcel:obtain	()Landroid/os/Parcel;
    //   7: astore_3
    //   8: aload_2
    //   9: ldc 26
    //   11: invokevirtual 30	android/os/Parcel:writeInterfaceToken	(Ljava/lang/String;)V
    //   14: aload_1
    //   15: ifnull +43 -> 58
    //   18: aload_2
    //   19: iconst_1
    //   20: invokevirtual 34	android/os/Parcel:writeInt	(I)V
    //   23: aload_1
    //   24: aload_2
    //   25: iconst_0
    //   26: invokevirtual 40	com/google/android/gms/common/data/DataHolder:writeToParcel	(Landroid/os/Parcel;I)V
    //   29: aload_0
    //   30: getfield 15	com/google/android/gms/games/internal/dl:a	Landroid/os/IBinder;
    //   33: sipush 12016
    //   36: aload_2
    //   37: aload_3
    //   38: iconst_0
    //   39: invokeinterface 46 5 0
    //   44: pop
    //   45: aload_3
    //   46: invokevirtual 49	android/os/Parcel:readException	()V
    //   49: aload_3
    //   50: invokevirtual 52	android/os/Parcel:recycle	()V
    //   53: aload_2
    //   54: invokevirtual 52	android/os/Parcel:recycle	()V
    //   57: return
    //   58: aload_2
    //   59: iconst_0
    //   60: invokevirtual 34	android/os/Parcel:writeInt	(I)V
    //   63: goto -34 -> 29
    //   66: astore_1
    //   67: aload_3
    //   68: invokevirtual 52	android/os/Parcel:recycle	()V
    //   71: aload_2
    //   72: invokevirtual 52	android/os/Parcel:recycle	()V
    //   75: aload_1
    //   76: athrow
    // Local variable table:
    //   start	length	slot	name	signature
    //   0	77	0	this	dl
    //   0	77	1	paramDataHolder	DataHolder
    //   3	69	2	localParcel1	Parcel
    //   7	61	3	localParcel2	Parcel
    // Exception table:
    //   from	to	target	type
    //   8	14	66	finally
    //   18	29	66	finally
    //   29	49	66	finally
    //   58	63	66	finally
  }
  
  /* Error */
  public void O(DataHolder paramDataHolder)
  {
    // Byte code:
    //   0: invokestatic 24	android/os/Parcel:obtain	()Landroid/os/Parcel;
    //   3: astore_2
    //   4: invokestatic 24	android/os/Parcel:obtain	()Landroid/os/Parcel;
    //   7: astore_3
    //   8: aload_2
    //   9: ldc 26
    //   11: invokevirtual 30	android/os/Parcel:writeInterfaceToken	(Ljava/lang/String;)V
    //   14: aload_1
    //   15: ifnull +43 -> 58
    //   18: aload_2
    //   19: iconst_1
    //   20: invokevirtual 34	android/os/Parcel:writeInt	(I)V
    //   23: aload_1
    //   24: aload_2
    //   25: iconst_0
    //   26: invokevirtual 40	com/google/android/gms/common/data/DataHolder:writeToParcel	(Landroid/os/Parcel;I)V
    //   29: aload_0
    //   30: getfield 15	com/google/android/gms/games/internal/dl:a	Landroid/os/IBinder;
    //   33: sipush 12008
    //   36: aload_2
    //   37: aload_3
    //   38: iconst_0
    //   39: invokeinterface 46 5 0
    //   44: pop
    //   45: aload_3
    //   46: invokevirtual 49	android/os/Parcel:readException	()V
    //   49: aload_3
    //   50: invokevirtual 52	android/os/Parcel:recycle	()V
    //   53: aload_2
    //   54: invokevirtual 52	android/os/Parcel:recycle	()V
    //   57: return
    //   58: aload_2
    //   59: iconst_0
    //   60: invokevirtual 34	android/os/Parcel:writeInt	(I)V
    //   63: goto -34 -> 29
    //   66: astore_1
    //   67: aload_3
    //   68: invokevirtual 52	android/os/Parcel:recycle	()V
    //   71: aload_2
    //   72: invokevirtual 52	android/os/Parcel:recycle	()V
    //   75: aload_1
    //   76: athrow
    // Local variable table:
    //   start	length	slot	name	signature
    //   0	77	0	this	dl
    //   0	77	1	paramDataHolder	DataHolder
    //   3	69	2	localParcel1	Parcel
    //   7	61	3	localParcel2	Parcel
    // Exception table:
    //   from	to	target	type
    //   8	14	66	finally
    //   18	29	66	finally
    //   29	49	66	finally
    //   58	63	66	finally
  }
  
  /* Error */
  public void P(DataHolder paramDataHolder)
  {
    // Byte code:
    //   0: invokestatic 24	android/os/Parcel:obtain	()Landroid/os/Parcel;
    //   3: astore_2
    //   4: invokestatic 24	android/os/Parcel:obtain	()Landroid/os/Parcel;
    //   7: astore_3
    //   8: aload_2
    //   9: ldc 26
    //   11: invokevirtual 30	android/os/Parcel:writeInterfaceToken	(Ljava/lang/String;)V
    //   14: aload_1
    //   15: ifnull +43 -> 58
    //   18: aload_2
    //   19: iconst_1
    //   20: invokevirtual 34	android/os/Parcel:writeInt	(I)V
    //   23: aload_1
    //   24: aload_2
    //   25: iconst_0
    //   26: invokevirtual 40	com/google/android/gms/common/data/DataHolder:writeToParcel	(Landroid/os/Parcel;I)V
    //   29: aload_0
    //   30: getfield 15	com/google/android/gms/games/internal/dl:a	Landroid/os/IBinder;
    //   33: sipush 12013
    //   36: aload_2
    //   37: aload_3
    //   38: iconst_0
    //   39: invokeinterface 46 5 0
    //   44: pop
    //   45: aload_3
    //   46: invokevirtual 49	android/os/Parcel:readException	()V
    //   49: aload_3
    //   50: invokevirtual 52	android/os/Parcel:recycle	()V
    //   53: aload_2
    //   54: invokevirtual 52	android/os/Parcel:recycle	()V
    //   57: return
    //   58: aload_2
    //   59: iconst_0
    //   60: invokevirtual 34	android/os/Parcel:writeInt	(I)V
    //   63: goto -34 -> 29
    //   66: astore_1
    //   67: aload_3
    //   68: invokevirtual 52	android/os/Parcel:recycle	()V
    //   71: aload_2
    //   72: invokevirtual 52	android/os/Parcel:recycle	()V
    //   75: aload_1
    //   76: athrow
    // Local variable table:
    //   start	length	slot	name	signature
    //   0	77	0	this	dl
    //   0	77	1	paramDataHolder	DataHolder
    //   3	69	2	localParcel1	Parcel
    //   7	61	3	localParcel2	Parcel
    // Exception table:
    //   from	to	target	type
    //   8	14	66	finally
    //   18	29	66	finally
    //   29	49	66	finally
    //   58	63	66	finally
  }
  
  public void a(int paramInt, String paramString, boolean paramBoolean)
  {
    int i = 0;
    Parcel localParcel1 = Parcel.obtain();
    Parcel localParcel2 = Parcel.obtain();
    try
    {
      localParcel1.writeInterfaceToken("com.google.android.gms.games.internal.IGamesCallbacks");
      localParcel1.writeInt(paramInt);
      localParcel1.writeString(paramString);
      paramInt = i;
      if (paramBoolean) {
        paramInt = 1;
      }
      localParcel1.writeInt(paramInt);
      this.a.transact(5034, localParcel1, localParcel2, 0);
      localParcel2.readException();
      return;
    }
    finally
    {
      localParcel2.recycle();
      localParcel1.recycle();
    }
  }
  
  public void a(DataHolder paramDataHolder1, DataHolder paramDataHolder2)
  {
    Parcel localParcel1 = Parcel.obtain();
    Parcel localParcel2 = Parcel.obtain();
    for (;;)
    {
      try
      {
        localParcel1.writeInterfaceToken("com.google.android.gms.games.internal.IGamesCallbacks");
        if (paramDataHolder1 != null)
        {
          localParcel1.writeInt(1);
          paramDataHolder1.writeToParcel(localParcel1, 0);
          if (paramDataHolder2 != null)
          {
            localParcel1.writeInt(1);
            paramDataHolder2.writeToParcel(localParcel1, 0);
            this.a.transact(5005, localParcel1, localParcel2, 0);
            localParcel2.readException();
          }
        }
        else
        {
          localParcel1.writeInt(0);
          continue;
        }
        localParcel1.writeInt(0);
      }
      finally
      {
        localParcel2.recycle();
        localParcel1.recycle();
      }
    }
  }
  
  public void a(DataHolder paramDataHolder, Contents paramContents)
  {
    Parcel localParcel1 = Parcel.obtain();
    Parcel localParcel2 = Parcel.obtain();
    for (;;)
    {
      try
      {
        localParcel1.writeInterfaceToken("com.google.android.gms.games.internal.IGamesCallbacks");
        if (paramDataHolder != null)
        {
          localParcel1.writeInt(1);
          paramDataHolder.writeToParcel(localParcel1, 0);
          if (paramContents != null)
          {
            localParcel1.writeInt(1);
            paramContents.writeToParcel(localParcel1, 0);
            this.a.transact(12004, localParcel1, localParcel2, 0);
            localParcel2.readException();
          }
        }
        else
        {
          localParcel1.writeInt(0);
          continue;
        }
        localParcel1.writeInt(0);
      }
      finally
      {
        localParcel2.recycle();
        localParcel1.recycle();
      }
    }
  }
  
  public void a(DataHolder paramDataHolder, String paramString, Contents paramContents1, Contents paramContents2, Contents paramContents3)
  {
    Parcel localParcel1 = Parcel.obtain();
    Parcel localParcel2 = Parcel.obtain();
    for (;;)
    {
      try
      {
        localParcel1.writeInterfaceToken("com.google.android.gms.games.internal.IGamesCallbacks");
        if (paramDataHolder != null)
        {
          localParcel1.writeInt(1);
          paramDataHolder.writeToParcel(localParcel1, 0);
          localParcel1.writeString(paramString);
          if (paramContents1 != null)
          {
            localParcel1.writeInt(1);
            paramContents1.writeToParcel(localParcel1, 0);
            if (paramContents2 == null) {
              break label160;
            }
            localParcel1.writeInt(1);
            paramContents2.writeToParcel(localParcel1, 0);
            if (paramContents3 == null) {
              break label169;
            }
            localParcel1.writeInt(1);
            paramContents3.writeToParcel(localParcel1, 0);
            this.a.transact(12017, localParcel1, localParcel2, 0);
            localParcel2.readException();
          }
        }
        else
        {
          localParcel1.writeInt(0);
          continue;
        }
        localParcel1.writeInt(0);
      }
      finally
      {
        localParcel2.recycle();
        localParcel1.recycle();
      }
      continue;
      label160:
      localParcel1.writeInt(0);
      continue;
      label169:
      localParcel1.writeInt(0);
    }
  }
  
  /* Error */
  public void a(DataHolder paramDataHolder, String[] paramArrayOfString)
  {
    // Byte code:
    //   0: invokestatic 24	android/os/Parcel:obtain	()Landroid/os/Parcel;
    //   3: astore_3
    //   4: invokestatic 24	android/os/Parcel:obtain	()Landroid/os/Parcel;
    //   7: astore 4
    //   9: aload_3
    //   10: ldc 26
    //   12: invokevirtual 30	android/os/Parcel:writeInterfaceToken	(Ljava/lang/String;)V
    //   15: aload_1
    //   16: ifnull +51 -> 67
    //   19: aload_3
    //   20: iconst_1
    //   21: invokevirtual 34	android/os/Parcel:writeInt	(I)V
    //   24: aload_1
    //   25: aload_3
    //   26: iconst_0
    //   27: invokevirtual 40	com/google/android/gms/common/data/DataHolder:writeToParcel	(Landroid/os/Parcel;I)V
    //   30: aload_3
    //   31: aload_2
    //   32: invokevirtual 82	android/os/Parcel:writeStringArray	([Ljava/lang/String;)V
    //   35: aload_0
    //   36: getfield 15	com/google/android/gms/games/internal/dl:a	Landroid/os/IBinder;
    //   39: sipush 5026
    //   42: aload_3
    //   43: aload 4
    //   45: iconst_0
    //   46: invokeinterface 46 5 0
    //   51: pop
    //   52: aload 4
    //   54: invokevirtual 49	android/os/Parcel:readException	()V
    //   57: aload 4
    //   59: invokevirtual 52	android/os/Parcel:recycle	()V
    //   62: aload_3
    //   63: invokevirtual 52	android/os/Parcel:recycle	()V
    //   66: return
    //   67: aload_3
    //   68: iconst_0
    //   69: invokevirtual 34	android/os/Parcel:writeInt	(I)V
    //   72: goto -42 -> 30
    //   75: astore_1
    //   76: aload 4
    //   78: invokevirtual 52	android/os/Parcel:recycle	()V
    //   81: aload_3
    //   82: invokevirtual 52	android/os/Parcel:recycle	()V
    //   85: aload_1
    //   86: athrow
    // Local variable table:
    //   start	length	slot	name	signature
    //   0	87	0	this	dl
    //   0	87	1	paramDataHolder	DataHolder
    //   0	87	2	paramArrayOfString	String[]
    //   3	79	3	localParcel1	Parcel
    //   7	70	4	localParcel2	Parcel
    // Exception table:
    //   from	to	target	type
    //   9	15	75	finally
    //   19	30	75	finally
    //   30	57	75	finally
    //   67	72	75	finally
  }
  
  public IBinder asBinder()
  {
    return this.a;
  }
  
  public void b(int paramInt1, int paramInt2, String paramString)
  {
    Parcel localParcel1 = Parcel.obtain();
    Parcel localParcel2 = Parcel.obtain();
    try
    {
      localParcel1.writeInterfaceToken("com.google.android.gms.games.internal.IGamesCallbacks");
      localParcel1.writeInt(paramInt1);
      localParcel1.writeInt(paramInt2);
      localParcel1.writeString(paramString);
      this.a.transact(5033, localParcel1, localParcel2, 0);
      localParcel2.readException();
      return;
    }
    finally
    {
      localParcel2.recycle();
      localParcel1.recycle();
    }
  }
  
  /* Error */
  public void b(int paramInt, android.os.Bundle paramBundle)
  {
    // Byte code:
    //   0: invokestatic 24	android/os/Parcel:obtain	()Landroid/os/Parcel;
    //   3: astore_3
    //   4: invokestatic 24	android/os/Parcel:obtain	()Landroid/os/Parcel;
    //   7: astore 4
    //   9: aload_3
    //   10: ldc 26
    //   12: invokevirtual 30	android/os/Parcel:writeInterfaceToken	(Ljava/lang/String;)V
    //   15: aload_3
    //   16: iload_1
    //   17: invokevirtual 34	android/os/Parcel:writeInt	(I)V
    //   20: aload_2
    //   21: ifnull +46 -> 67
    //   24: aload_3
    //   25: iconst_1
    //   26: invokevirtual 34	android/os/Parcel:writeInt	(I)V
    //   29: aload_2
    //   30: aload_3
    //   31: iconst_0
    //   32: invokevirtual 90	android/os/Bundle:writeToParcel	(Landroid/os/Parcel;I)V
    //   35: aload_0
    //   36: getfield 15	com/google/android/gms/games/internal/dl:a	Landroid/os/IBinder;
    //   39: sipush 8002
    //   42: aload_3
    //   43: aload 4
    //   45: iconst_0
    //   46: invokeinterface 46 5 0
    //   51: pop
    //   52: aload 4
    //   54: invokevirtual 49	android/os/Parcel:readException	()V
    //   57: aload 4
    //   59: invokevirtual 52	android/os/Parcel:recycle	()V
    //   62: aload_3
    //   63: invokevirtual 52	android/os/Parcel:recycle	()V
    //   66: return
    //   67: aload_3
    //   68: iconst_0
    //   69: invokevirtual 34	android/os/Parcel:writeInt	(I)V
    //   72: goto -37 -> 35
    //   75: astore_2
    //   76: aload 4
    //   78: invokevirtual 52	android/os/Parcel:recycle	()V
    //   81: aload_3
    //   82: invokevirtual 52	android/os/Parcel:recycle	()V
    //   85: aload_2
    //   86: athrow
    // Local variable table:
    //   start	length	slot	name	signature
    //   0	87	0	this	dl
    //   0	87	1	paramInt	int
    //   0	87	2	paramBundle	android.os.Bundle
    //   3	79	3	localParcel1	Parcel
    //   7	70	4	localParcel2	Parcel
    // Exception table:
    //   from	to	target	type
    //   9	20	75	finally
    //   24	35	75	finally
    //   35	57	75	finally
    //   67	72	75	finally
  }
  
  /* Error */
  public void b(DataHolder paramDataHolder, String[] paramArrayOfString)
  {
    // Byte code:
    //   0: invokestatic 24	android/os/Parcel:obtain	()Landroid/os/Parcel;
    //   3: astore_3
    //   4: invokestatic 24	android/os/Parcel:obtain	()Landroid/os/Parcel;
    //   7: astore 4
    //   9: aload_3
    //   10: ldc 26
    //   12: invokevirtual 30	android/os/Parcel:writeInterfaceToken	(Ljava/lang/String;)V
    //   15: aload_1
    //   16: ifnull +51 -> 67
    //   19: aload_3
    //   20: iconst_1
    //   21: invokevirtual 34	android/os/Parcel:writeInt	(I)V
    //   24: aload_1
    //   25: aload_3
    //   26: iconst_0
    //   27: invokevirtual 40	com/google/android/gms/common/data/DataHolder:writeToParcel	(Landroid/os/Parcel;I)V
    //   30: aload_3
    //   31: aload_2
    //   32: invokevirtual 82	android/os/Parcel:writeStringArray	([Ljava/lang/String;)V
    //   35: aload_0
    //   36: getfield 15	com/google/android/gms/games/internal/dl:a	Landroid/os/IBinder;
    //   39: sipush 5027
    //   42: aload_3
    //   43: aload 4
    //   45: iconst_0
    //   46: invokeinterface 46 5 0
    //   51: pop
    //   52: aload 4
    //   54: invokevirtual 49	android/os/Parcel:readException	()V
    //   57: aload 4
    //   59: invokevirtual 52	android/os/Parcel:recycle	()V
    //   62: aload_3
    //   63: invokevirtual 52	android/os/Parcel:recycle	()V
    //   66: return
    //   67: aload_3
    //   68: iconst_0
    //   69: invokevirtual 34	android/os/Parcel:writeInt	(I)V
    //   72: goto -42 -> 30
    //   75: astore_1
    //   76: aload 4
    //   78: invokevirtual 52	android/os/Parcel:recycle	()V
    //   81: aload_3
    //   82: invokevirtual 52	android/os/Parcel:recycle	()V
    //   85: aload_1
    //   86: athrow
    // Local variable table:
    //   start	length	slot	name	signature
    //   0	87	0	this	dl
    //   0	87	1	paramDataHolder	DataHolder
    //   0	87	2	paramArrayOfString	String[]
    //   3	79	3	localParcel1	Parcel
    //   7	70	4	localParcel2	Parcel
    // Exception table:
    //   from	to	target	type
    //   9	15	75	finally
    //   19	30	75	finally
    //   30	57	75	finally
    //   67	72	75	finally
  }
  
  /* Error */
  public void c(int paramInt, android.os.Bundle paramBundle)
  {
    // Byte code:
    //   0: invokestatic 24	android/os/Parcel:obtain	()Landroid/os/Parcel;
    //   3: astore_3
    //   4: invokestatic 24	android/os/Parcel:obtain	()Landroid/os/Parcel;
    //   7: astore 4
    //   9: aload_3
    //   10: ldc 26
    //   12: invokevirtual 30	android/os/Parcel:writeInterfaceToken	(Ljava/lang/String;)V
    //   15: aload_3
    //   16: iload_1
    //   17: invokevirtual 34	android/os/Parcel:writeInt	(I)V
    //   20: aload_2
    //   21: ifnull +46 -> 67
    //   24: aload_3
    //   25: iconst_1
    //   26: invokevirtual 34	android/os/Parcel:writeInt	(I)V
    //   29: aload_2
    //   30: aload_3
    //   31: iconst_0
    //   32: invokevirtual 90	android/os/Bundle:writeToParcel	(Landroid/os/Parcel;I)V
    //   35: aload_0
    //   36: getfield 15	com/google/android/gms/games/internal/dl:a	Landroid/os/IBinder;
    //   39: sipush 10005
    //   42: aload_3
    //   43: aload 4
    //   45: iconst_0
    //   46: invokeinterface 46 5 0
    //   51: pop
    //   52: aload 4
    //   54: invokevirtual 49	android/os/Parcel:readException	()V
    //   57: aload 4
    //   59: invokevirtual 52	android/os/Parcel:recycle	()V
    //   62: aload_3
    //   63: invokevirtual 52	android/os/Parcel:recycle	()V
    //   66: return
    //   67: aload_3
    //   68: iconst_0
    //   69: invokevirtual 34	android/os/Parcel:writeInt	(I)V
    //   72: goto -37 -> 35
    //   75: astore_2
    //   76: aload 4
    //   78: invokevirtual 52	android/os/Parcel:recycle	()V
    //   81: aload_3
    //   82: invokevirtual 52	android/os/Parcel:recycle	()V
    //   85: aload_2
    //   86: athrow
    // Local variable table:
    //   start	length	slot	name	signature
    //   0	87	0	this	dl
    //   0	87	1	paramInt	int
    //   0	87	2	paramBundle	android.os.Bundle
    //   3	79	3	localParcel1	Parcel
    //   7	70	4	localParcel2	Parcel
    // Exception table:
    //   from	to	target	type
    //   9	20	75	finally
    //   24	35	75	finally
    //   35	57	75	finally
    //   67	72	75	finally
  }
  
  /* Error */
  public void c(DataHolder paramDataHolder)
  {
    // Byte code:
    //   0: invokestatic 24	android/os/Parcel:obtain	()Landroid/os/Parcel;
    //   3: astore_2
    //   4: invokestatic 24	android/os/Parcel:obtain	()Landroid/os/Parcel;
    //   7: astore_3
    //   8: aload_2
    //   9: ldc 26
    //   11: invokevirtual 30	android/os/Parcel:writeInterfaceToken	(Ljava/lang/String;)V
    //   14: aload_1
    //   15: ifnull +43 -> 58
    //   18: aload_2
    //   19: iconst_1
    //   20: invokevirtual 34	android/os/Parcel:writeInt	(I)V
    //   23: aload_1
    //   24: aload_2
    //   25: iconst_0
    //   26: invokevirtual 40	com/google/android/gms/common/data/DataHolder:writeToParcel	(Landroid/os/Parcel;I)V
    //   29: aload_0
    //   30: getfield 15	com/google/android/gms/games/internal/dl:a	Landroid/os/IBinder;
    //   33: sipush 5002
    //   36: aload_2
    //   37: aload_3
    //   38: iconst_0
    //   39: invokeinterface 46 5 0
    //   44: pop
    //   45: aload_3
    //   46: invokevirtual 49	android/os/Parcel:readException	()V
    //   49: aload_3
    //   50: invokevirtual 52	android/os/Parcel:recycle	()V
    //   53: aload_2
    //   54: invokevirtual 52	android/os/Parcel:recycle	()V
    //   57: return
    //   58: aload_2
    //   59: iconst_0
    //   60: invokevirtual 34	android/os/Parcel:writeInt	(I)V
    //   63: goto -34 -> 29
    //   66: astore_1
    //   67: aload_3
    //   68: invokevirtual 52	android/os/Parcel:recycle	()V
    //   71: aload_2
    //   72: invokevirtual 52	android/os/Parcel:recycle	()V
    //   75: aload_1
    //   76: athrow
    // Local variable table:
    //   start	length	slot	name	signature
    //   0	77	0	this	dl
    //   0	77	1	paramDataHolder	DataHolder
    //   3	69	2	localParcel1	Parcel
    //   7	61	3	localParcel2	Parcel
    // Exception table:
    //   from	to	target	type
    //   8	14	66	finally
    //   18	29	66	finally
    //   29	49	66	finally
    //   58	63	66	finally
  }
  
  /* Error */
  public void c(DataHolder paramDataHolder, String[] paramArrayOfString)
  {
    // Byte code:
    //   0: invokestatic 24	android/os/Parcel:obtain	()Landroid/os/Parcel;
    //   3: astore_3
    //   4: invokestatic 24	android/os/Parcel:obtain	()Landroid/os/Parcel;
    //   7: astore 4
    //   9: aload_3
    //   10: ldc 26
    //   12: invokevirtual 30	android/os/Parcel:writeInterfaceToken	(Ljava/lang/String;)V
    //   15: aload_1
    //   16: ifnull +51 -> 67
    //   19: aload_3
    //   20: iconst_1
    //   21: invokevirtual 34	android/os/Parcel:writeInt	(I)V
    //   24: aload_1
    //   25: aload_3
    //   26: iconst_0
    //   27: invokevirtual 40	com/google/android/gms/common/data/DataHolder:writeToParcel	(Landroid/os/Parcel;I)V
    //   30: aload_3
    //   31: aload_2
    //   32: invokevirtual 82	android/os/Parcel:writeStringArray	([Ljava/lang/String;)V
    //   35: aload_0
    //   36: getfield 15	com/google/android/gms/games/internal/dl:a	Landroid/os/IBinder;
    //   39: sipush 5028
    //   42: aload_3
    //   43: aload 4
    //   45: iconst_0
    //   46: invokeinterface 46 5 0
    //   51: pop
    //   52: aload 4
    //   54: invokevirtual 49	android/os/Parcel:readException	()V
    //   57: aload 4
    //   59: invokevirtual 52	android/os/Parcel:recycle	()V
    //   62: aload_3
    //   63: invokevirtual 52	android/os/Parcel:recycle	()V
    //   66: return
    //   67: aload_3
    //   68: iconst_0
    //   69: invokevirtual 34	android/os/Parcel:writeInt	(I)V
    //   72: goto -42 -> 30
    //   75: astore_1
    //   76: aload 4
    //   78: invokevirtual 52	android/os/Parcel:recycle	()V
    //   81: aload_3
    //   82: invokevirtual 52	android/os/Parcel:recycle	()V
    //   85: aload_1
    //   86: athrow
    // Local variable table:
    //   start	length	slot	name	signature
    //   0	87	0	this	dl
    //   0	87	1	paramDataHolder	DataHolder
    //   0	87	2	paramArrayOfString	String[]
    //   3	79	3	localParcel1	Parcel
    //   7	70	4	localParcel2	Parcel
    // Exception table:
    //   from	to	target	type
    //   9	15	75	finally
    //   19	30	75	finally
    //   30	57	75	finally
    //   67	72	75	finally
  }
  
  public void cd(int paramInt)
  {
    Parcel localParcel1 = Parcel.obtain();
    Parcel localParcel2 = Parcel.obtain();
    try
    {
      localParcel1.writeInterfaceToken("com.google.android.gms.games.internal.IGamesCallbacks");
      localParcel1.writeInt(paramInt);
      this.a.transact(5036, localParcel1, localParcel2, 0);
      localParcel2.readException();
      return;
    }
    finally
    {
      localParcel2.recycle();
      localParcel1.recycle();
    }
  }
  
  public void ce(int paramInt)
  {
    Parcel localParcel1 = Parcel.obtain();
    Parcel localParcel2 = Parcel.obtain();
    try
    {
      localParcel1.writeInterfaceToken("com.google.android.gms.games.internal.IGamesCallbacks");
      localParcel1.writeInt(paramInt);
      this.a.transact(5040, localParcel1, localParcel2, 0);
      localParcel2.readException();
      return;
    }
    finally
    {
      localParcel2.recycle();
      localParcel1.recycle();
    }
  }
  
  /* Error */
  public void d(int paramInt, android.os.Bundle paramBundle)
  {
    // Byte code:
    //   0: invokestatic 24	android/os/Parcel:obtain	()Landroid/os/Parcel;
    //   3: astore_3
    //   4: invokestatic 24	android/os/Parcel:obtain	()Landroid/os/Parcel;
    //   7: astore 4
    //   9: aload_3
    //   10: ldc 26
    //   12: invokevirtual 30	android/os/Parcel:writeInterfaceToken	(Ljava/lang/String;)V
    //   15: aload_3
    //   16: iload_1
    //   17: invokevirtual 34	android/os/Parcel:writeInt	(I)V
    //   20: aload_2
    //   21: ifnull +46 -> 67
    //   24: aload_3
    //   25: iconst_1
    //   26: invokevirtual 34	android/os/Parcel:writeInt	(I)V
    //   29: aload_2
    //   30: aload_3
    //   31: iconst_0
    //   32: invokevirtual 90	android/os/Bundle:writeToParcel	(Landroid/os/Parcel;I)V
    //   35: aload_0
    //   36: getfield 15	com/google/android/gms/games/internal/dl:a	Landroid/os/IBinder;
    //   39: sipush 11001
    //   42: aload_3
    //   43: aload 4
    //   45: iconst_0
    //   46: invokeinterface 46 5 0
    //   51: pop
    //   52: aload 4
    //   54: invokevirtual 49	android/os/Parcel:readException	()V
    //   57: aload 4
    //   59: invokevirtual 52	android/os/Parcel:recycle	()V
    //   62: aload_3
    //   63: invokevirtual 52	android/os/Parcel:recycle	()V
    //   66: return
    //   67: aload_3
    //   68: iconst_0
    //   69: invokevirtual 34	android/os/Parcel:writeInt	(I)V
    //   72: goto -37 -> 35
    //   75: astore_2
    //   76: aload 4
    //   78: invokevirtual 52	android/os/Parcel:recycle	()V
    //   81: aload_3
    //   82: invokevirtual 52	android/os/Parcel:recycle	()V
    //   85: aload_2
    //   86: athrow
    // Local variable table:
    //   start	length	slot	name	signature
    //   0	87	0	this	dl
    //   0	87	1	paramInt	int
    //   0	87	2	paramBundle	android.os.Bundle
    //   3	79	3	localParcel1	Parcel
    //   7	70	4	localParcel2	Parcel
    // Exception table:
    //   from	to	target	type
    //   9	20	75	finally
    //   24	35	75	finally
    //   35	57	75	finally
    //   67	72	75	finally
  }
  
  public void d(int paramInt, String paramString)
  {
    Parcel localParcel1 = Parcel.obtain();
    Parcel localParcel2 = Parcel.obtain();
    try
    {
      localParcel1.writeInterfaceToken("com.google.android.gms.games.internal.IGamesCallbacks");
      localParcel1.writeInt(paramInt);
      localParcel1.writeString(paramString);
      this.a.transact(5001, localParcel1, localParcel2, 0);
      localParcel2.readException();
      return;
    }
    finally
    {
      localParcel2.recycle();
      localParcel1.recycle();
    }
  }
  
  /* Error */
  public void d(DataHolder paramDataHolder)
  {
    // Byte code:
    //   0: invokestatic 24	android/os/Parcel:obtain	()Landroid/os/Parcel;
    //   3: astore_2
    //   4: invokestatic 24	android/os/Parcel:obtain	()Landroid/os/Parcel;
    //   7: astore_3
    //   8: aload_2
    //   9: ldc 26
    //   11: invokevirtual 30	android/os/Parcel:writeInterfaceToken	(Ljava/lang/String;)V
    //   14: aload_1
    //   15: ifnull +43 -> 58
    //   18: aload_2
    //   19: iconst_1
    //   20: invokevirtual 34	android/os/Parcel:writeInt	(I)V
    //   23: aload_1
    //   24: aload_2
    //   25: iconst_0
    //   26: invokevirtual 40	com/google/android/gms/common/data/DataHolder:writeToParcel	(Landroid/os/Parcel;I)V
    //   29: aload_0
    //   30: getfield 15	com/google/android/gms/games/internal/dl:a	Landroid/os/IBinder;
    //   33: sipush 12011
    //   36: aload_2
    //   37: aload_3
    //   38: iconst_0
    //   39: invokeinterface 46 5 0
    //   44: pop
    //   45: aload_3
    //   46: invokevirtual 49	android/os/Parcel:readException	()V
    //   49: aload_3
    //   50: invokevirtual 52	android/os/Parcel:recycle	()V
    //   53: aload_2
    //   54: invokevirtual 52	android/os/Parcel:recycle	()V
    //   57: return
    //   58: aload_2
    //   59: iconst_0
    //   60: invokevirtual 34	android/os/Parcel:writeInt	(I)V
    //   63: goto -34 -> 29
    //   66: astore_1
    //   67: aload_3
    //   68: invokevirtual 52	android/os/Parcel:recycle	()V
    //   71: aload_2
    //   72: invokevirtual 52	android/os/Parcel:recycle	()V
    //   75: aload_1
    //   76: athrow
    // Local variable table:
    //   start	length	slot	name	signature
    //   0	77	0	this	dl
    //   0	77	1	paramDataHolder	DataHolder
    //   3	69	2	localParcel1	Parcel
    //   7	61	3	localParcel2	Parcel
    // Exception table:
    //   from	to	target	type
    //   8	14	66	finally
    //   18	29	66	finally
    //   29	49	66	finally
    //   58	63	66	finally
  }
  
  /* Error */
  public void d(DataHolder paramDataHolder, String[] paramArrayOfString)
  {
    // Byte code:
    //   0: invokestatic 24	android/os/Parcel:obtain	()Landroid/os/Parcel;
    //   3: astore_3
    //   4: invokestatic 24	android/os/Parcel:obtain	()Landroid/os/Parcel;
    //   7: astore 4
    //   9: aload_3
    //   10: ldc 26
    //   12: invokevirtual 30	android/os/Parcel:writeInterfaceToken	(Ljava/lang/String;)V
    //   15: aload_1
    //   16: ifnull +51 -> 67
    //   19: aload_3
    //   20: iconst_1
    //   21: invokevirtual 34	android/os/Parcel:writeInt	(I)V
    //   24: aload_1
    //   25: aload_3
    //   26: iconst_0
    //   27: invokevirtual 40	com/google/android/gms/common/data/DataHolder:writeToParcel	(Landroid/os/Parcel;I)V
    //   30: aload_3
    //   31: aload_2
    //   32: invokevirtual 82	android/os/Parcel:writeStringArray	([Ljava/lang/String;)V
    //   35: aload_0
    //   36: getfield 15	com/google/android/gms/games/internal/dl:a	Landroid/os/IBinder;
    //   39: sipush 5029
    //   42: aload_3
    //   43: aload 4
    //   45: iconst_0
    //   46: invokeinterface 46 5 0
    //   51: pop
    //   52: aload 4
    //   54: invokevirtual 49	android/os/Parcel:readException	()V
    //   57: aload 4
    //   59: invokevirtual 52	android/os/Parcel:recycle	()V
    //   62: aload_3
    //   63: invokevirtual 52	android/os/Parcel:recycle	()V
    //   66: return
    //   67: aload_3
    //   68: iconst_0
    //   69: invokevirtual 34	android/os/Parcel:writeInt	(I)V
    //   72: goto -42 -> 30
    //   75: astore_1
    //   76: aload 4
    //   78: invokevirtual 52	android/os/Parcel:recycle	()V
    //   81: aload_3
    //   82: invokevirtual 52	android/os/Parcel:recycle	()V
    //   85: aload_1
    //   86: athrow
    // Local variable table:
    //   start	length	slot	name	signature
    //   0	87	0	this	dl
    //   0	87	1	paramDataHolder	DataHolder
    //   0	87	2	paramArrayOfString	String[]
    //   3	79	3	localParcel1	Parcel
    //   7	70	4	localParcel2	Parcel
    // Exception table:
    //   from	to	target	type
    //   9	15	75	finally
    //   19	30	75	finally
    //   30	57	75	finally
    //   67	72	75	finally
  }
  
  public void dT()
  {
    Parcel localParcel1 = Parcel.obtain();
    Parcel localParcel2 = Parcel.obtain();
    try
    {
      localParcel1.writeInterfaceToken("com.google.android.gms.games.internal.IGamesCallbacks");
      this.a.transact(5016, localParcel1, localParcel2, 0);
      localParcel2.readException();
      return;
    }
    finally
    {
      localParcel2.recycle();
      localParcel1.recycle();
    }
  }
  
  /* Error */
  public void e(int paramInt, android.os.Bundle paramBundle)
  {
    // Byte code:
    //   0: invokestatic 24	android/os/Parcel:obtain	()Landroid/os/Parcel;
    //   3: astore_3
    //   4: invokestatic 24	android/os/Parcel:obtain	()Landroid/os/Parcel;
    //   7: astore 4
    //   9: aload_3
    //   10: ldc 26
    //   12: invokevirtual 30	android/os/Parcel:writeInterfaceToken	(Ljava/lang/String;)V
    //   15: aload_3
    //   16: iload_1
    //   17: invokevirtual 34	android/os/Parcel:writeInt	(I)V
    //   20: aload_2
    //   21: ifnull +46 -> 67
    //   24: aload_3
    //   25: iconst_1
    //   26: invokevirtual 34	android/os/Parcel:writeInt	(I)V
    //   29: aload_2
    //   30: aload_3
    //   31: iconst_0
    //   32: invokevirtual 90	android/os/Bundle:writeToParcel	(Landroid/os/Parcel;I)V
    //   35: aload_0
    //   36: getfield 15	com/google/android/gms/games/internal/dl:a	Landroid/os/IBinder;
    //   39: sipush 12003
    //   42: aload_3
    //   43: aload 4
    //   45: iconst_0
    //   46: invokeinterface 46 5 0
    //   51: pop
    //   52: aload 4
    //   54: invokevirtual 49	android/os/Parcel:readException	()V
    //   57: aload 4
    //   59: invokevirtual 52	android/os/Parcel:recycle	()V
    //   62: aload_3
    //   63: invokevirtual 52	android/os/Parcel:recycle	()V
    //   66: return
    //   67: aload_3
    //   68: iconst_0
    //   69: invokevirtual 34	android/os/Parcel:writeInt	(I)V
    //   72: goto -37 -> 35
    //   75: astore_2
    //   76: aload 4
    //   78: invokevirtual 52	android/os/Parcel:recycle	()V
    //   81: aload_3
    //   82: invokevirtual 52	android/os/Parcel:recycle	()V
    //   85: aload_2
    //   86: athrow
    // Local variable table:
    //   start	length	slot	name	signature
    //   0	87	0	this	dl
    //   0	87	1	paramInt	int
    //   0	87	2	paramBundle	android.os.Bundle
    //   3	79	3	localParcel1	Parcel
    //   7	70	4	localParcel2	Parcel
    // Exception table:
    //   from	to	target	type
    //   9	20	75	finally
    //   24	35	75	finally
    //   35	57	75	finally
    //   67	72	75	finally
  }
  
  public void e(int paramInt, String paramString)
  {
    Parcel localParcel1 = Parcel.obtain();
    Parcel localParcel2 = Parcel.obtain();
    try
    {
      localParcel1.writeInterfaceToken("com.google.android.gms.games.internal.IGamesCallbacks");
      localParcel1.writeInt(paramInt);
      localParcel1.writeString(paramString);
      this.a.transact(5003, localParcel1, localParcel2, 0);
      localParcel2.readException();
      return;
    }
    finally
    {
      localParcel2.recycle();
      localParcel1.recycle();
    }
  }
  
  /* Error */
  public void e(DataHolder paramDataHolder)
  {
    // Byte code:
    //   0: invokestatic 24	android/os/Parcel:obtain	()Landroid/os/Parcel;
    //   3: astore_2
    //   4: invokestatic 24	android/os/Parcel:obtain	()Landroid/os/Parcel;
    //   7: astore_3
    //   8: aload_2
    //   9: ldc 26
    //   11: invokevirtual 30	android/os/Parcel:writeInterfaceToken	(Ljava/lang/String;)V
    //   14: aload_1
    //   15: ifnull +43 -> 58
    //   18: aload_2
    //   19: iconst_1
    //   20: invokevirtual 34	android/os/Parcel:writeInt	(I)V
    //   23: aload_1
    //   24: aload_2
    //   25: iconst_0
    //   26: invokevirtual 40	com/google/android/gms/common/data/DataHolder:writeToParcel	(Landroid/os/Parcel;I)V
    //   29: aload_0
    //   30: getfield 15	com/google/android/gms/games/internal/dl:a	Landroid/os/IBinder;
    //   33: sipush 5004
    //   36: aload_2
    //   37: aload_3
    //   38: iconst_0
    //   39: invokeinterface 46 5 0
    //   44: pop
    //   45: aload_3
    //   46: invokevirtual 49	android/os/Parcel:readException	()V
    //   49: aload_3
    //   50: invokevirtual 52	android/os/Parcel:recycle	()V
    //   53: aload_2
    //   54: invokevirtual 52	android/os/Parcel:recycle	()V
    //   57: return
    //   58: aload_2
    //   59: iconst_0
    //   60: invokevirtual 34	android/os/Parcel:writeInt	(I)V
    //   63: goto -34 -> 29
    //   66: astore_1
    //   67: aload_3
    //   68: invokevirtual 52	android/os/Parcel:recycle	()V
    //   71: aload_2
    //   72: invokevirtual 52	android/os/Parcel:recycle	()V
    //   75: aload_1
    //   76: athrow
    // Local variable table:
    //   start	length	slot	name	signature
    //   0	77	0	this	dl
    //   0	77	1	paramDataHolder	DataHolder
    //   3	69	2	localParcel1	Parcel
    //   7	61	3	localParcel2	Parcel
    // Exception table:
    //   from	to	target	type
    //   8	14	66	finally
    //   18	29	66	finally
    //   29	49	66	finally
    //   58	63	66	finally
  }
  
  /* Error */
  public void e(DataHolder paramDataHolder, String[] paramArrayOfString)
  {
    // Byte code:
    //   0: invokestatic 24	android/os/Parcel:obtain	()Landroid/os/Parcel;
    //   3: astore_3
    //   4: invokestatic 24	android/os/Parcel:obtain	()Landroid/os/Parcel;
    //   7: astore 4
    //   9: aload_3
    //   10: ldc 26
    //   12: invokevirtual 30	android/os/Parcel:writeInterfaceToken	(Ljava/lang/String;)V
    //   15: aload_1
    //   16: ifnull +51 -> 67
    //   19: aload_3
    //   20: iconst_1
    //   21: invokevirtual 34	android/os/Parcel:writeInt	(I)V
    //   24: aload_1
    //   25: aload_3
    //   26: iconst_0
    //   27: invokevirtual 40	com/google/android/gms/common/data/DataHolder:writeToParcel	(Landroid/os/Parcel;I)V
    //   30: aload_3
    //   31: aload_2
    //   32: invokevirtual 82	android/os/Parcel:writeStringArray	([Ljava/lang/String;)V
    //   35: aload_0
    //   36: getfield 15	com/google/android/gms/games/internal/dl:a	Landroid/os/IBinder;
    //   39: sipush 5030
    //   42: aload_3
    //   43: aload 4
    //   45: iconst_0
    //   46: invokeinterface 46 5 0
    //   51: pop
    //   52: aload 4
    //   54: invokevirtual 49	android/os/Parcel:readException	()V
    //   57: aload 4
    //   59: invokevirtual 52	android/os/Parcel:recycle	()V
    //   62: aload_3
    //   63: invokevirtual 52	android/os/Parcel:recycle	()V
    //   66: return
    //   67: aload_3
    //   68: iconst_0
    //   69: invokevirtual 34	android/os/Parcel:writeInt	(I)V
    //   72: goto -42 -> 30
    //   75: astore_1
    //   76: aload 4
    //   78: invokevirtual 52	android/os/Parcel:recycle	()V
    //   81: aload_3
    //   82: invokevirtual 52	android/os/Parcel:recycle	()V
    //   85: aload_1
    //   86: athrow
    // Local variable table:
    //   start	length	slot	name	signature
    //   0	87	0	this	dl
    //   0	87	1	paramDataHolder	DataHolder
    //   0	87	2	paramArrayOfString	String[]
    //   3	79	3	localParcel1	Parcel
    //   7	70	4	localParcel2	Parcel
    // Exception table:
    //   from	to	target	type
    //   9	15	75	finally
    //   19	30	75	finally
    //   30	57	75	finally
    //   67	72	75	finally
  }
  
  /* Error */
  public void f(int paramInt, android.os.Bundle paramBundle)
  {
    // Byte code:
    //   0: invokestatic 24	android/os/Parcel:obtain	()Landroid/os/Parcel;
    //   3: astore_3
    //   4: invokestatic 24	android/os/Parcel:obtain	()Landroid/os/Parcel;
    //   7: astore 4
    //   9: aload_3
    //   10: ldc 26
    //   12: invokevirtual 30	android/os/Parcel:writeInterfaceToken	(Ljava/lang/String;)V
    //   15: aload_3
    //   16: iload_1
    //   17: invokevirtual 34	android/os/Parcel:writeInt	(I)V
    //   20: aload_2
    //   21: ifnull +46 -> 67
    //   24: aload_3
    //   25: iconst_1
    //   26: invokevirtual 34	android/os/Parcel:writeInt	(I)V
    //   29: aload_2
    //   30: aload_3
    //   31: iconst_0
    //   32: invokevirtual 90	android/os/Bundle:writeToParcel	(Landroid/os/Parcel;I)V
    //   35: aload_0
    //   36: getfield 15	com/google/android/gms/games/internal/dl:a	Landroid/os/IBinder;
    //   39: sipush 12015
    //   42: aload_3
    //   43: aload 4
    //   45: iconst_0
    //   46: invokeinterface 46 5 0
    //   51: pop
    //   52: aload 4
    //   54: invokevirtual 49	android/os/Parcel:readException	()V
    //   57: aload 4
    //   59: invokevirtual 52	android/os/Parcel:recycle	()V
    //   62: aload_3
    //   63: invokevirtual 52	android/os/Parcel:recycle	()V
    //   66: return
    //   67: aload_3
    //   68: iconst_0
    //   69: invokevirtual 34	android/os/Parcel:writeInt	(I)V
    //   72: goto -37 -> 35
    //   75: astore_2
    //   76: aload 4
    //   78: invokevirtual 52	android/os/Parcel:recycle	()V
    //   81: aload_3
    //   82: invokevirtual 52	android/os/Parcel:recycle	()V
    //   85: aload_2
    //   86: athrow
    // Local variable table:
    //   start	length	slot	name	signature
    //   0	87	0	this	dl
    //   0	87	1	paramInt	int
    //   0	87	2	paramBundle	android.os.Bundle
    //   3	79	3	localParcel1	Parcel
    //   7	70	4	localParcel2	Parcel
    // Exception table:
    //   from	to	target	type
    //   9	20	75	finally
    //   24	35	75	finally
    //   35	57	75	finally
    //   67	72	75	finally
  }
  
  public void f(int paramInt, String paramString)
  {
    Parcel localParcel1 = Parcel.obtain();
    Parcel localParcel2 = Parcel.obtain();
    try
    {
      localParcel1.writeInterfaceToken("com.google.android.gms.games.internal.IGamesCallbacks");
      localParcel1.writeInt(paramInt);
      localParcel1.writeString(paramString);
      this.a.transact(8007, localParcel1, localParcel2, 0);
      localParcel2.readException();
      return;
    }
    finally
    {
      localParcel2.recycle();
      localParcel1.recycle();
    }
  }
  
  /* Error */
  public void f(DataHolder paramDataHolder)
  {
    // Byte code:
    //   0: invokestatic 24	android/os/Parcel:obtain	()Landroid/os/Parcel;
    //   3: astore_2
    //   4: invokestatic 24	android/os/Parcel:obtain	()Landroid/os/Parcel;
    //   7: astore_3
    //   8: aload_2
    //   9: ldc 26
    //   11: invokevirtual 30	android/os/Parcel:writeInterfaceToken	(Ljava/lang/String;)V
    //   14: aload_1
    //   15: ifnull +43 -> 58
    //   18: aload_2
    //   19: iconst_1
    //   20: invokevirtual 34	android/os/Parcel:writeInt	(I)V
    //   23: aload_1
    //   24: aload_2
    //   25: iconst_0
    //   26: invokevirtual 40	com/google/android/gms/common/data/DataHolder:writeToParcel	(Landroid/os/Parcel;I)V
    //   29: aload_0
    //   30: getfield 15	com/google/android/gms/games/internal/dl:a	Landroid/os/IBinder;
    //   33: sipush 5006
    //   36: aload_2
    //   37: aload_3
    //   38: iconst_0
    //   39: invokeinterface 46 5 0
    //   44: pop
    //   45: aload_3
    //   46: invokevirtual 49	android/os/Parcel:readException	()V
    //   49: aload_3
    //   50: invokevirtual 52	android/os/Parcel:recycle	()V
    //   53: aload_2
    //   54: invokevirtual 52	android/os/Parcel:recycle	()V
    //   57: return
    //   58: aload_2
    //   59: iconst_0
    //   60: invokevirtual 34	android/os/Parcel:writeInt	(I)V
    //   63: goto -34 -> 29
    //   66: astore_1
    //   67: aload_3
    //   68: invokevirtual 52	android/os/Parcel:recycle	()V
    //   71: aload_2
    //   72: invokevirtual 52	android/os/Parcel:recycle	()V
    //   75: aload_1
    //   76: athrow
    // Local variable table:
    //   start	length	slot	name	signature
    //   0	77	0	this	dl
    //   0	77	1	paramDataHolder	DataHolder
    //   3	69	2	localParcel1	Parcel
    //   7	61	3	localParcel2	Parcel
    // Exception table:
    //   from	to	target	type
    //   8	14	66	finally
    //   18	29	66	finally
    //   29	49	66	finally
    //   58	63	66	finally
  }
  
  /* Error */
  public void f(DataHolder paramDataHolder, String[] paramArrayOfString)
  {
    // Byte code:
    //   0: invokestatic 24	android/os/Parcel:obtain	()Landroid/os/Parcel;
    //   3: astore_3
    //   4: invokestatic 24	android/os/Parcel:obtain	()Landroid/os/Parcel;
    //   7: astore 4
    //   9: aload_3
    //   10: ldc 26
    //   12: invokevirtual 30	android/os/Parcel:writeInterfaceToken	(Ljava/lang/String;)V
    //   15: aload_1
    //   16: ifnull +51 -> 67
    //   19: aload_3
    //   20: iconst_1
    //   21: invokevirtual 34	android/os/Parcel:writeInt	(I)V
    //   24: aload_1
    //   25: aload_3
    //   26: iconst_0
    //   27: invokevirtual 40	com/google/android/gms/common/data/DataHolder:writeToParcel	(Landroid/os/Parcel;I)V
    //   30: aload_3
    //   31: aload_2
    //   32: invokevirtual 82	android/os/Parcel:writeStringArray	([Ljava/lang/String;)V
    //   35: aload_0
    //   36: getfield 15	com/google/android/gms/games/internal/dl:a	Landroid/os/IBinder;
    //   39: sipush 5031
    //   42: aload_3
    //   43: aload 4
    //   45: iconst_0
    //   46: invokeinterface 46 5 0
    //   51: pop
    //   52: aload 4
    //   54: invokevirtual 49	android/os/Parcel:readException	()V
    //   57: aload 4
    //   59: invokevirtual 52	android/os/Parcel:recycle	()V
    //   62: aload_3
    //   63: invokevirtual 52	android/os/Parcel:recycle	()V
    //   66: return
    //   67: aload_3
    //   68: iconst_0
    //   69: invokevirtual 34	android/os/Parcel:writeInt	(I)V
    //   72: goto -42 -> 30
    //   75: astore_1
    //   76: aload 4
    //   78: invokevirtual 52	android/os/Parcel:recycle	()V
    //   81: aload_3
    //   82: invokevirtual 52	android/os/Parcel:recycle	()V
    //   85: aload_1
    //   86: athrow
    // Local variable table:
    //   start	length	slot	name	signature
    //   0	87	0	this	dl
    //   0	87	1	paramDataHolder	DataHolder
    //   0	87	2	paramArrayOfString	String[]
    //   3	79	3	localParcel1	Parcel
    //   7	70	4	localParcel2	Parcel
    // Exception table:
    //   from	to	target	type
    //   9	15	75	finally
    //   19	30	75	finally
    //   30	57	75	finally
    //   67	72	75	finally
  }
  
  public void g(int paramInt, String paramString)
  {
    Parcel localParcel1 = Parcel.obtain();
    Parcel localParcel2 = Parcel.obtain();
    try
    {
      localParcel1.writeInterfaceToken("com.google.android.gms.games.internal.IGamesCallbacks");
      localParcel1.writeInt(paramInt);
      localParcel1.writeString(paramString);
      this.a.transact(12012, localParcel1, localParcel2, 0);
      localParcel2.readException();
      return;
    }
    finally
    {
      localParcel2.recycle();
      localParcel1.recycle();
    }
  }
  
  /* Error */
  public void g(DataHolder paramDataHolder)
  {
    // Byte code:
    //   0: invokestatic 24	android/os/Parcel:obtain	()Landroid/os/Parcel;
    //   3: astore_2
    //   4: invokestatic 24	android/os/Parcel:obtain	()Landroid/os/Parcel;
    //   7: astore_3
    //   8: aload_2
    //   9: ldc 26
    //   11: invokevirtual 30	android/os/Parcel:writeInterfaceToken	(Ljava/lang/String;)V
    //   14: aload_1
    //   15: ifnull +43 -> 58
    //   18: aload_2
    //   19: iconst_1
    //   20: invokevirtual 34	android/os/Parcel:writeInt	(I)V
    //   23: aload_1
    //   24: aload_2
    //   25: iconst_0
    //   26: invokevirtual 40	com/google/android/gms/common/data/DataHolder:writeToParcel	(Landroid/os/Parcel;I)V
    //   29: aload_0
    //   30: getfield 15	com/google/android/gms/games/internal/dl:a	Landroid/os/IBinder;
    //   33: sipush 5007
    //   36: aload_2
    //   37: aload_3
    //   38: iconst_0
    //   39: invokeinterface 46 5 0
    //   44: pop
    //   45: aload_3
    //   46: invokevirtual 49	android/os/Parcel:readException	()V
    //   49: aload_3
    //   50: invokevirtual 52	android/os/Parcel:recycle	()V
    //   53: aload_2
    //   54: invokevirtual 52	android/os/Parcel:recycle	()V
    //   57: return
    //   58: aload_2
    //   59: iconst_0
    //   60: invokevirtual 34	android/os/Parcel:writeInt	(I)V
    //   63: goto -34 -> 29
    //   66: astore_1
    //   67: aload_3
    //   68: invokevirtual 52	android/os/Parcel:recycle	()V
    //   71: aload_2
    //   72: invokevirtual 52	android/os/Parcel:recycle	()V
    //   75: aload_1
    //   76: athrow
    // Local variable table:
    //   start	length	slot	name	signature
    //   0	77	0	this	dl
    //   0	77	1	paramDataHolder	DataHolder
    //   3	69	2	localParcel1	Parcel
    //   7	61	3	localParcel2	Parcel
    // Exception table:
    //   from	to	target	type
    //   8	14	66	finally
    //   18	29	66	finally
    //   29	49	66	finally
    //   58	63	66	finally
  }
  
  /* Error */
  public void h(DataHolder paramDataHolder)
  {
    // Byte code:
    //   0: invokestatic 24	android/os/Parcel:obtain	()Landroid/os/Parcel;
    //   3: astore_2
    //   4: invokestatic 24	android/os/Parcel:obtain	()Landroid/os/Parcel;
    //   7: astore_3
    //   8: aload_2
    //   9: ldc 26
    //   11: invokevirtual 30	android/os/Parcel:writeInterfaceToken	(Ljava/lang/String;)V
    //   14: aload_1
    //   15: ifnull +43 -> 58
    //   18: aload_2
    //   19: iconst_1
    //   20: invokevirtual 34	android/os/Parcel:writeInt	(I)V
    //   23: aload_1
    //   24: aload_2
    //   25: iconst_0
    //   26: invokevirtual 40	com/google/android/gms/common/data/DataHolder:writeToParcel	(Landroid/os/Parcel;I)V
    //   29: aload_0
    //   30: getfield 15	com/google/android/gms/games/internal/dl:a	Landroid/os/IBinder;
    //   33: sipush 5008
    //   36: aload_2
    //   37: aload_3
    //   38: iconst_0
    //   39: invokeinterface 46 5 0
    //   44: pop
    //   45: aload_3
    //   46: invokevirtual 49	android/os/Parcel:readException	()V
    //   49: aload_3
    //   50: invokevirtual 52	android/os/Parcel:recycle	()V
    //   53: aload_2
    //   54: invokevirtual 52	android/os/Parcel:recycle	()V
    //   57: return
    //   58: aload_2
    //   59: iconst_0
    //   60: invokevirtual 34	android/os/Parcel:writeInt	(I)V
    //   63: goto -34 -> 29
    //   66: astore_1
    //   67: aload_3
    //   68: invokevirtual 52	android/os/Parcel:recycle	()V
    //   71: aload_2
    //   72: invokevirtual 52	android/os/Parcel:recycle	()V
    //   75: aload_1
    //   76: athrow
    // Local variable table:
    //   start	length	slot	name	signature
    //   0	77	0	this	dl
    //   0	77	1	paramDataHolder	DataHolder
    //   3	69	2	localParcel1	Parcel
    //   7	61	3	localParcel2	Parcel
    // Exception table:
    //   from	to	target	type
    //   8	14	66	finally
    //   18	29	66	finally
    //   29	49	66	finally
    //   58	63	66	finally
  }
  
  /* Error */
  public void i(DataHolder paramDataHolder)
  {
    // Byte code:
    //   0: invokestatic 24	android/os/Parcel:obtain	()Landroid/os/Parcel;
    //   3: astore_2
    //   4: invokestatic 24	android/os/Parcel:obtain	()Landroid/os/Parcel;
    //   7: astore_3
    //   8: aload_2
    //   9: ldc 26
    //   11: invokevirtual 30	android/os/Parcel:writeInterfaceToken	(Ljava/lang/String;)V
    //   14: aload_1
    //   15: ifnull +43 -> 58
    //   18: aload_2
    //   19: iconst_1
    //   20: invokevirtual 34	android/os/Parcel:writeInt	(I)V
    //   23: aload_1
    //   24: aload_2
    //   25: iconst_0
    //   26: invokevirtual 40	com/google/android/gms/common/data/DataHolder:writeToParcel	(Landroid/os/Parcel;I)V
    //   29: aload_0
    //   30: getfield 15	com/google/android/gms/games/internal/dl:a	Landroid/os/IBinder;
    //   33: sipush 5009
    //   36: aload_2
    //   37: aload_3
    //   38: iconst_0
    //   39: invokeinterface 46 5 0
    //   44: pop
    //   45: aload_3
    //   46: invokevirtual 49	android/os/Parcel:readException	()V
    //   49: aload_3
    //   50: invokevirtual 52	android/os/Parcel:recycle	()V
    //   53: aload_2
    //   54: invokevirtual 52	android/os/Parcel:recycle	()V
    //   57: return
    //   58: aload_2
    //   59: iconst_0
    //   60: invokevirtual 34	android/os/Parcel:writeInt	(I)V
    //   63: goto -34 -> 29
    //   66: astore_1
    //   67: aload_3
    //   68: invokevirtual 52	android/os/Parcel:recycle	()V
    //   71: aload_2
    //   72: invokevirtual 52	android/os/Parcel:recycle	()V
    //   75: aload_1
    //   76: athrow
    // Local variable table:
    //   start	length	slot	name	signature
    //   0	77	0	this	dl
    //   0	77	1	paramDataHolder	DataHolder
    //   3	69	2	localParcel1	Parcel
    //   7	61	3	localParcel2	Parcel
    // Exception table:
    //   from	to	target	type
    //   8	14	66	finally
    //   18	29	66	finally
    //   29	49	66	finally
    //   58	63	66	finally
  }
  
  /* Error */
  public void j(DataHolder paramDataHolder)
  {
    // Byte code:
    //   0: invokestatic 24	android/os/Parcel:obtain	()Landroid/os/Parcel;
    //   3: astore_2
    //   4: invokestatic 24	android/os/Parcel:obtain	()Landroid/os/Parcel;
    //   7: astore_3
    //   8: aload_2
    //   9: ldc 26
    //   11: invokevirtual 30	android/os/Parcel:writeInterfaceToken	(Ljava/lang/String;)V
    //   14: aload_1
    //   15: ifnull +43 -> 58
    //   18: aload_2
    //   19: iconst_1
    //   20: invokevirtual 34	android/os/Parcel:writeInt	(I)V
    //   23: aload_1
    //   24: aload_2
    //   25: iconst_0
    //   26: invokevirtual 40	com/google/android/gms/common/data/DataHolder:writeToParcel	(Landroid/os/Parcel;I)V
    //   29: aload_0
    //   30: getfield 15	com/google/android/gms/games/internal/dl:a	Landroid/os/IBinder;
    //   33: sipush 5010
    //   36: aload_2
    //   37: aload_3
    //   38: iconst_0
    //   39: invokeinterface 46 5 0
    //   44: pop
    //   45: aload_3
    //   46: invokevirtual 49	android/os/Parcel:readException	()V
    //   49: aload_3
    //   50: invokevirtual 52	android/os/Parcel:recycle	()V
    //   53: aload_2
    //   54: invokevirtual 52	android/os/Parcel:recycle	()V
    //   57: return
    //   58: aload_2
    //   59: iconst_0
    //   60: invokevirtual 34	android/os/Parcel:writeInt	(I)V
    //   63: goto -34 -> 29
    //   66: astore_1
    //   67: aload_3
    //   68: invokevirtual 52	android/os/Parcel:recycle	()V
    //   71: aload_2
    //   72: invokevirtual 52	android/os/Parcel:recycle	()V
    //   75: aload_1
    //   76: athrow
    // Local variable table:
    //   start	length	slot	name	signature
    //   0	77	0	this	dl
    //   0	77	1	paramDataHolder	DataHolder
    //   3	69	2	localParcel1	Parcel
    //   7	61	3	localParcel2	Parcel
    // Exception table:
    //   from	to	target	type
    //   8	14	66	finally
    //   18	29	66	finally
    //   29	49	66	finally
    //   58	63	66	finally
  }
  
  /* Error */
  public void k(DataHolder paramDataHolder)
  {
    // Byte code:
    //   0: invokestatic 24	android/os/Parcel:obtain	()Landroid/os/Parcel;
    //   3: astore_2
    //   4: invokestatic 24	android/os/Parcel:obtain	()Landroid/os/Parcel;
    //   7: astore_3
    //   8: aload_2
    //   9: ldc 26
    //   11: invokevirtual 30	android/os/Parcel:writeInterfaceToken	(Ljava/lang/String;)V
    //   14: aload_1
    //   15: ifnull +43 -> 58
    //   18: aload_2
    //   19: iconst_1
    //   20: invokevirtual 34	android/os/Parcel:writeInt	(I)V
    //   23: aload_1
    //   24: aload_2
    //   25: iconst_0
    //   26: invokevirtual 40	com/google/android/gms/common/data/DataHolder:writeToParcel	(Landroid/os/Parcel;I)V
    //   29: aload_0
    //   30: getfield 15	com/google/android/gms/games/internal/dl:a	Landroid/os/IBinder;
    //   33: sipush 5011
    //   36: aload_2
    //   37: aload_3
    //   38: iconst_0
    //   39: invokeinterface 46 5 0
    //   44: pop
    //   45: aload_3
    //   46: invokevirtual 49	android/os/Parcel:readException	()V
    //   49: aload_3
    //   50: invokevirtual 52	android/os/Parcel:recycle	()V
    //   53: aload_2
    //   54: invokevirtual 52	android/os/Parcel:recycle	()V
    //   57: return
    //   58: aload_2
    //   59: iconst_0
    //   60: invokevirtual 34	android/os/Parcel:writeInt	(I)V
    //   63: goto -34 -> 29
    //   66: astore_1
    //   67: aload_3
    //   68: invokevirtual 52	android/os/Parcel:recycle	()V
    //   71: aload_2
    //   72: invokevirtual 52	android/os/Parcel:recycle	()V
    //   75: aload_1
    //   76: athrow
    // Local variable table:
    //   start	length	slot	name	signature
    //   0	77	0	this	dl
    //   0	77	1	paramDataHolder	DataHolder
    //   3	69	2	localParcel1	Parcel
    //   7	61	3	localParcel2	Parcel
    // Exception table:
    //   from	to	target	type
    //   8	14	66	finally
    //   18	29	66	finally
    //   29	49	66	finally
    //   58	63	66	finally
  }
  
  /* Error */
  public void l(DataHolder paramDataHolder)
  {
    // Byte code:
    //   0: invokestatic 24	android/os/Parcel:obtain	()Landroid/os/Parcel;
    //   3: astore_2
    //   4: invokestatic 24	android/os/Parcel:obtain	()Landroid/os/Parcel;
    //   7: astore_3
    //   8: aload_2
    //   9: ldc 26
    //   11: invokevirtual 30	android/os/Parcel:writeInterfaceToken	(Ljava/lang/String;)V
    //   14: aload_1
    //   15: ifnull +43 -> 58
    //   18: aload_2
    //   19: iconst_1
    //   20: invokevirtual 34	android/os/Parcel:writeInt	(I)V
    //   23: aload_1
    //   24: aload_2
    //   25: iconst_0
    //   26: invokevirtual 40	com/google/android/gms/common/data/DataHolder:writeToParcel	(Landroid/os/Parcel;I)V
    //   29: aload_0
    //   30: getfield 15	com/google/android/gms/games/internal/dl:a	Landroid/os/IBinder;
    //   33: sipush 9001
    //   36: aload_2
    //   37: aload_3
    //   38: iconst_0
    //   39: invokeinterface 46 5 0
    //   44: pop
    //   45: aload_3
    //   46: invokevirtual 49	android/os/Parcel:readException	()V
    //   49: aload_3
    //   50: invokevirtual 52	android/os/Parcel:recycle	()V
    //   53: aload_2
    //   54: invokevirtual 52	android/os/Parcel:recycle	()V
    //   57: return
    //   58: aload_2
    //   59: iconst_0
    //   60: invokevirtual 34	android/os/Parcel:writeInt	(I)V
    //   63: goto -34 -> 29
    //   66: astore_1
    //   67: aload_3
    //   68: invokevirtual 52	android/os/Parcel:recycle	()V
    //   71: aload_2
    //   72: invokevirtual 52	android/os/Parcel:recycle	()V
    //   75: aload_1
    //   76: athrow
    // Local variable table:
    //   start	length	slot	name	signature
    //   0	77	0	this	dl
    //   0	77	1	paramDataHolder	DataHolder
    //   3	69	2	localParcel1	Parcel
    //   7	61	3	localParcel2	Parcel
    // Exception table:
    //   from	to	target	type
    //   8	14	66	finally
    //   18	29	66	finally
    //   29	49	66	finally
    //   58	63	66	finally
  }
  
  /* Error */
  public void m(DataHolder paramDataHolder)
  {
    // Byte code:
    //   0: invokestatic 24	android/os/Parcel:obtain	()Landroid/os/Parcel;
    //   3: astore_2
    //   4: invokestatic 24	android/os/Parcel:obtain	()Landroid/os/Parcel;
    //   7: astore_3
    //   8: aload_2
    //   9: ldc 26
    //   11: invokevirtual 30	android/os/Parcel:writeInterfaceToken	(Ljava/lang/String;)V
    //   14: aload_1
    //   15: ifnull +43 -> 58
    //   18: aload_2
    //   19: iconst_1
    //   20: invokevirtual 34	android/os/Parcel:writeInt	(I)V
    //   23: aload_1
    //   24: aload_2
    //   25: iconst_0
    //   26: invokevirtual 40	com/google/android/gms/common/data/DataHolder:writeToParcel	(Landroid/os/Parcel;I)V
    //   29: aload_0
    //   30: getfield 15	com/google/android/gms/games/internal/dl:a	Landroid/os/IBinder;
    //   33: sipush 5017
    //   36: aload_2
    //   37: aload_3
    //   38: iconst_0
    //   39: invokeinterface 46 5 0
    //   44: pop
    //   45: aload_3
    //   46: invokevirtual 49	android/os/Parcel:readException	()V
    //   49: aload_3
    //   50: invokevirtual 52	android/os/Parcel:recycle	()V
    //   53: aload_2
    //   54: invokevirtual 52	android/os/Parcel:recycle	()V
    //   57: return
    //   58: aload_2
    //   59: iconst_0
    //   60: invokevirtual 34	android/os/Parcel:writeInt	(I)V
    //   63: goto -34 -> 29
    //   66: astore_1
    //   67: aload_3
    //   68: invokevirtual 52	android/os/Parcel:recycle	()V
    //   71: aload_2
    //   72: invokevirtual 52	android/os/Parcel:recycle	()V
    //   75: aload_1
    //   76: athrow
    // Local variable table:
    //   start	length	slot	name	signature
    //   0	77	0	this	dl
    //   0	77	1	paramDataHolder	DataHolder
    //   3	69	2	localParcel1	Parcel
    //   7	61	3	localParcel2	Parcel
    // Exception table:
    //   from	to	target	type
    //   8	14	66	finally
    //   18	29	66	finally
    //   29	49	66	finally
    //   58	63	66	finally
  }
  
  /* Error */
  public void n(DataHolder paramDataHolder)
  {
    // Byte code:
    //   0: invokestatic 24	android/os/Parcel:obtain	()Landroid/os/Parcel;
    //   3: astore_2
    //   4: invokestatic 24	android/os/Parcel:obtain	()Landroid/os/Parcel;
    //   7: astore_3
    //   8: aload_2
    //   9: ldc 26
    //   11: invokevirtual 30	android/os/Parcel:writeInterfaceToken	(Ljava/lang/String;)V
    //   14: aload_1
    //   15: ifnull +43 -> 58
    //   18: aload_2
    //   19: iconst_1
    //   20: invokevirtual 34	android/os/Parcel:writeInt	(I)V
    //   23: aload_1
    //   24: aload_2
    //   25: iconst_0
    //   26: invokevirtual 40	com/google/android/gms/common/data/DataHolder:writeToParcel	(Landroid/os/Parcel;I)V
    //   29: aload_0
    //   30: getfield 15	com/google/android/gms/games/internal/dl:a	Landroid/os/IBinder;
    //   33: sipush 5037
    //   36: aload_2
    //   37: aload_3
    //   38: iconst_0
    //   39: invokeinterface 46 5 0
    //   44: pop
    //   45: aload_3
    //   46: invokevirtual 49	android/os/Parcel:readException	()V
    //   49: aload_3
    //   50: invokevirtual 52	android/os/Parcel:recycle	()V
    //   53: aload_2
    //   54: invokevirtual 52	android/os/Parcel:recycle	()V
    //   57: return
    //   58: aload_2
    //   59: iconst_0
    //   60: invokevirtual 34	android/os/Parcel:writeInt	(I)V
    //   63: goto -34 -> 29
    //   66: astore_1
    //   67: aload_3
    //   68: invokevirtual 52	android/os/Parcel:recycle	()V
    //   71: aload_2
    //   72: invokevirtual 52	android/os/Parcel:recycle	()V
    //   75: aload_1
    //   76: athrow
    // Local variable table:
    //   start	length	slot	name	signature
    //   0	77	0	this	dl
    //   0	77	1	paramDataHolder	DataHolder
    //   3	69	2	localParcel1	Parcel
    //   7	61	3	localParcel2	Parcel
    // Exception table:
    //   from	to	target	type
    //   8	14	66	finally
    //   18	29	66	finally
    //   29	49	66	finally
    //   58	63	66	finally
  }
  
  /* Error */
  public void o(DataHolder paramDataHolder)
  {
    // Byte code:
    //   0: invokestatic 24	android/os/Parcel:obtain	()Landroid/os/Parcel;
    //   3: astore_2
    //   4: invokestatic 24	android/os/Parcel:obtain	()Landroid/os/Parcel;
    //   7: astore_3
    //   8: aload_2
    //   9: ldc 26
    //   11: invokevirtual 30	android/os/Parcel:writeInterfaceToken	(Ljava/lang/String;)V
    //   14: aload_1
    //   15: ifnull +43 -> 58
    //   18: aload_2
    //   19: iconst_1
    //   20: invokevirtual 34	android/os/Parcel:writeInt	(I)V
    //   23: aload_1
    //   24: aload_2
    //   25: iconst_0
    //   26: invokevirtual 40	com/google/android/gms/common/data/DataHolder:writeToParcel	(Landroid/os/Parcel;I)V
    //   29: aload_0
    //   30: getfield 15	com/google/android/gms/games/internal/dl:a	Landroid/os/IBinder;
    //   33: sipush 10001
    //   36: aload_2
    //   37: aload_3
    //   38: iconst_0
    //   39: invokeinterface 46 5 0
    //   44: pop
    //   45: aload_3
    //   46: invokevirtual 49	android/os/Parcel:readException	()V
    //   49: aload_3
    //   50: invokevirtual 52	android/os/Parcel:recycle	()V
    //   53: aload_2
    //   54: invokevirtual 52	android/os/Parcel:recycle	()V
    //   57: return
    //   58: aload_2
    //   59: iconst_0
    //   60: invokevirtual 34	android/os/Parcel:writeInt	(I)V
    //   63: goto -34 -> 29
    //   66: astore_1
    //   67: aload_3
    //   68: invokevirtual 52	android/os/Parcel:recycle	()V
    //   71: aload_2
    //   72: invokevirtual 52	android/os/Parcel:recycle	()V
    //   75: aload_1
    //   76: athrow
    // Local variable table:
    //   start	length	slot	name	signature
    //   0	77	0	this	dl
    //   0	77	1	paramDataHolder	DataHolder
    //   3	69	2	localParcel1	Parcel
    //   7	61	3	localParcel2	Parcel
    // Exception table:
    //   from	to	target	type
    //   8	14	66	finally
    //   18	29	66	finally
    //   29	49	66	finally
    //   58	63	66	finally
  }
  
  public void onInvitationRemoved(String paramString)
  {
    Parcel localParcel1 = Parcel.obtain();
    Parcel localParcel2 = Parcel.obtain();
    try
    {
      localParcel1.writeInterfaceToken("com.google.android.gms.games.internal.IGamesCallbacks");
      localParcel1.writeString(paramString);
      this.a.transact(8010, localParcel1, localParcel2, 0);
      localParcel2.readException();
      return;
    }
    finally
    {
      localParcel2.recycle();
      localParcel1.recycle();
    }
  }
  
  public void onLeftRoom(int paramInt, String paramString)
  {
    Parcel localParcel1 = Parcel.obtain();
    Parcel localParcel2 = Parcel.obtain();
    try
    {
      localParcel1.writeInterfaceToken("com.google.android.gms.games.internal.IGamesCallbacks");
      localParcel1.writeInt(paramInt);
      localParcel1.writeString(paramString);
      this.a.transact(5020, localParcel1, localParcel2, 0);
      localParcel2.readException();
      return;
    }
    finally
    {
      localParcel2.recycle();
      localParcel1.recycle();
    }
  }
  
  public void onP2PConnected(String paramString)
  {
    Parcel localParcel1 = Parcel.obtain();
    Parcel localParcel2 = Parcel.obtain();
    try
    {
      localParcel1.writeInterfaceToken("com.google.android.gms.games.internal.IGamesCallbacks");
      localParcel1.writeString(paramString);
      this.a.transact(6001, localParcel1, localParcel2, 0);
      localParcel2.readException();
      return;
    }
    finally
    {
      localParcel2.recycle();
      localParcel1.recycle();
    }
  }
  
  public void onP2PDisconnected(String paramString)
  {
    Parcel localParcel1 = Parcel.obtain();
    Parcel localParcel2 = Parcel.obtain();
    try
    {
      localParcel1.writeInterfaceToken("com.google.android.gms.games.internal.IGamesCallbacks");
      localParcel1.writeString(paramString);
      this.a.transact(6002, localParcel1, localParcel2, 0);
      localParcel2.readException();
      return;
    }
    finally
    {
      localParcel2.recycle();
      localParcel1.recycle();
    }
  }
  
  /* Error */
  public void onRealTimeMessageReceived(com.google.android.gms.games.multiplayer.realtime.RealTimeMessage paramRealTimeMessage)
  {
    // Byte code:
    //   0: invokestatic 24	android/os/Parcel:obtain	()Landroid/os/Parcel;
    //   3: astore_2
    //   4: invokestatic 24	android/os/Parcel:obtain	()Landroid/os/Parcel;
    //   7: astore_3
    //   8: aload_2
    //   9: ldc 26
    //   11: invokevirtual 30	android/os/Parcel:writeInterfaceToken	(Ljava/lang/String;)V
    //   14: aload_1
    //   15: ifnull +43 -> 58
    //   18: aload_2
    //   19: iconst_1
    //   20: invokevirtual 34	android/os/Parcel:writeInt	(I)V
    //   23: aload_1
    //   24: aload_2
    //   25: iconst_0
    //   26: invokevirtual 116	com/google/android/gms/games/multiplayer/realtime/RealTimeMessage:writeToParcel	(Landroid/os/Parcel;I)V
    //   29: aload_0
    //   30: getfield 15	com/google/android/gms/games/internal/dl:a	Landroid/os/IBinder;
    //   33: sipush 5032
    //   36: aload_2
    //   37: aload_3
    //   38: iconst_0
    //   39: invokeinterface 46 5 0
    //   44: pop
    //   45: aload_3
    //   46: invokevirtual 49	android/os/Parcel:readException	()V
    //   49: aload_3
    //   50: invokevirtual 52	android/os/Parcel:recycle	()V
    //   53: aload_2
    //   54: invokevirtual 52	android/os/Parcel:recycle	()V
    //   57: return
    //   58: aload_2
    //   59: iconst_0
    //   60: invokevirtual 34	android/os/Parcel:writeInt	(I)V
    //   63: goto -34 -> 29
    //   66: astore_1
    //   67: aload_3
    //   68: invokevirtual 52	android/os/Parcel:recycle	()V
    //   71: aload_2
    //   72: invokevirtual 52	android/os/Parcel:recycle	()V
    //   75: aload_1
    //   76: athrow
    // Local variable table:
    //   start	length	slot	name	signature
    //   0	77	0	this	dl
    //   0	77	1	paramRealTimeMessage	com.google.android.gms.games.multiplayer.realtime.RealTimeMessage
    //   3	69	2	localParcel1	Parcel
    //   7	61	3	localParcel2	Parcel
    // Exception table:
    //   from	to	target	type
    //   8	14	66	finally
    //   18	29	66	finally
    //   29	49	66	finally
    //   58	63	66	finally
  }
  
  public void onRequestRemoved(String paramString)
  {
    Parcel localParcel1 = Parcel.obtain();
    Parcel localParcel2 = Parcel.obtain();
    try
    {
      localParcel1.writeInterfaceToken("com.google.android.gms.games.internal.IGamesCallbacks");
      localParcel1.writeString(paramString);
      this.a.transact(10002, localParcel1, localParcel2, 0);
      localParcel2.readException();
      return;
    }
    finally
    {
      localParcel2.recycle();
      localParcel1.recycle();
    }
  }
  
  public void onTurnBasedMatchRemoved(String paramString)
  {
    Parcel localParcel1 = Parcel.obtain();
    Parcel localParcel2 = Parcel.obtain();
    try
    {
      localParcel1.writeInterfaceToken("com.google.android.gms.games.internal.IGamesCallbacks");
      localParcel1.writeString(paramString);
      this.a.transact(8009, localParcel1, localParcel2, 0);
      localParcel2.readException();
      return;
    }
    finally
    {
      localParcel2.recycle();
      localParcel1.recycle();
    }
  }
  
  /* Error */
  public void p(DataHolder paramDataHolder)
  {
    // Byte code:
    //   0: invokestatic 24	android/os/Parcel:obtain	()Landroid/os/Parcel;
    //   3: astore_2
    //   4: invokestatic 24	android/os/Parcel:obtain	()Landroid/os/Parcel;
    //   7: astore_3
    //   8: aload_2
    //   9: ldc 26
    //   11: invokevirtual 30	android/os/Parcel:writeInterfaceToken	(Ljava/lang/String;)V
    //   14: aload_1
    //   15: ifnull +43 -> 58
    //   18: aload_2
    //   19: iconst_1
    //   20: invokevirtual 34	android/os/Parcel:writeInt	(I)V
    //   23: aload_1
    //   24: aload_2
    //   25: iconst_0
    //   26: invokevirtual 40	com/google/android/gms/common/data/DataHolder:writeToParcel	(Landroid/os/Parcel;I)V
    //   29: aload_0
    //   30: getfield 15	com/google/android/gms/games/internal/dl:a	Landroid/os/IBinder;
    //   33: sipush 8003
    //   36: aload_2
    //   37: aload_3
    //   38: iconst_0
    //   39: invokeinterface 46 5 0
    //   44: pop
    //   45: aload_3
    //   46: invokevirtual 49	android/os/Parcel:readException	()V
    //   49: aload_3
    //   50: invokevirtual 52	android/os/Parcel:recycle	()V
    //   53: aload_2
    //   54: invokevirtual 52	android/os/Parcel:recycle	()V
    //   57: return
    //   58: aload_2
    //   59: iconst_0
    //   60: invokevirtual 34	android/os/Parcel:writeInt	(I)V
    //   63: goto -34 -> 29
    //   66: astore_1
    //   67: aload_3
    //   68: invokevirtual 52	android/os/Parcel:recycle	()V
    //   71: aload_2
    //   72: invokevirtual 52	android/os/Parcel:recycle	()V
    //   75: aload_1
    //   76: athrow
    // Local variable table:
    //   start	length	slot	name	signature
    //   0	77	0	this	dl
    //   0	77	1	paramDataHolder	DataHolder
    //   3	69	2	localParcel1	Parcel
    //   7	61	3	localParcel2	Parcel
    // Exception table:
    //   from	to	target	type
    //   8	14	66	finally
    //   18	29	66	finally
    //   29	49	66	finally
    //   58	63	66	finally
  }
  
  /* Error */
  public void q(DataHolder paramDataHolder)
  {
    // Byte code:
    //   0: invokestatic 24	android/os/Parcel:obtain	()Landroid/os/Parcel;
    //   3: astore_2
    //   4: invokestatic 24	android/os/Parcel:obtain	()Landroid/os/Parcel;
    //   7: astore_3
    //   8: aload_2
    //   9: ldc 26
    //   11: invokevirtual 30	android/os/Parcel:writeInterfaceToken	(Ljava/lang/String;)V
    //   14: aload_1
    //   15: ifnull +43 -> 58
    //   18: aload_2
    //   19: iconst_1
    //   20: invokevirtual 34	android/os/Parcel:writeInt	(I)V
    //   23: aload_1
    //   24: aload_2
    //   25: iconst_0
    //   26: invokevirtual 40	com/google/android/gms/common/data/DataHolder:writeToParcel	(Landroid/os/Parcel;I)V
    //   29: aload_0
    //   30: getfield 15	com/google/android/gms/games/internal/dl:a	Landroid/os/IBinder;
    //   33: sipush 8004
    //   36: aload_2
    //   37: aload_3
    //   38: iconst_0
    //   39: invokeinterface 46 5 0
    //   44: pop
    //   45: aload_3
    //   46: invokevirtual 49	android/os/Parcel:readException	()V
    //   49: aload_3
    //   50: invokevirtual 52	android/os/Parcel:recycle	()V
    //   53: aload_2
    //   54: invokevirtual 52	android/os/Parcel:recycle	()V
    //   57: return
    //   58: aload_2
    //   59: iconst_0
    //   60: invokevirtual 34	android/os/Parcel:writeInt	(I)V
    //   63: goto -34 -> 29
    //   66: astore_1
    //   67: aload_3
    //   68: invokevirtual 52	android/os/Parcel:recycle	()V
    //   71: aload_2
    //   72: invokevirtual 52	android/os/Parcel:recycle	()V
    //   75: aload_1
    //   76: athrow
    // Local variable table:
    //   start	length	slot	name	signature
    //   0	77	0	this	dl
    //   0	77	1	paramDataHolder	DataHolder
    //   3	69	2	localParcel1	Parcel
    //   7	61	3	localParcel2	Parcel
    // Exception table:
    //   from	to	target	type
    //   8	14	66	finally
    //   18	29	66	finally
    //   29	49	66	finally
    //   58	63	66	finally
  }
  
  /* Error */
  public void r(DataHolder paramDataHolder)
  {
    // Byte code:
    //   0: invokestatic 24	android/os/Parcel:obtain	()Landroid/os/Parcel;
    //   3: astore_2
    //   4: invokestatic 24	android/os/Parcel:obtain	()Landroid/os/Parcel;
    //   7: astore_3
    //   8: aload_2
    //   9: ldc 26
    //   11: invokevirtual 30	android/os/Parcel:writeInterfaceToken	(Ljava/lang/String;)V
    //   14: aload_1
    //   15: ifnull +43 -> 58
    //   18: aload_2
    //   19: iconst_1
    //   20: invokevirtual 34	android/os/Parcel:writeInt	(I)V
    //   23: aload_1
    //   24: aload_2
    //   25: iconst_0
    //   26: invokevirtual 40	com/google/android/gms/common/data/DataHolder:writeToParcel	(Landroid/os/Parcel;I)V
    //   29: aload_0
    //   30: getfield 15	com/google/android/gms/games/internal/dl:a	Landroid/os/IBinder;
    //   33: sipush 8005
    //   36: aload_2
    //   37: aload_3
    //   38: iconst_0
    //   39: invokeinterface 46 5 0
    //   44: pop
    //   45: aload_3
    //   46: invokevirtual 49	android/os/Parcel:readException	()V
    //   49: aload_3
    //   50: invokevirtual 52	android/os/Parcel:recycle	()V
    //   53: aload_2
    //   54: invokevirtual 52	android/os/Parcel:recycle	()V
    //   57: return
    //   58: aload_2
    //   59: iconst_0
    //   60: invokevirtual 34	android/os/Parcel:writeInt	(I)V
    //   63: goto -34 -> 29
    //   66: astore_1
    //   67: aload_3
    //   68: invokevirtual 52	android/os/Parcel:recycle	()V
    //   71: aload_2
    //   72: invokevirtual 52	android/os/Parcel:recycle	()V
    //   75: aload_1
    //   76: athrow
    // Local variable table:
    //   start	length	slot	name	signature
    //   0	77	0	this	dl
    //   0	77	1	paramDataHolder	DataHolder
    //   3	69	2	localParcel1	Parcel
    //   7	61	3	localParcel2	Parcel
    // Exception table:
    //   from	to	target	type
    //   8	14	66	finally
    //   18	29	66	finally
    //   29	49	66	finally
    //   58	63	66	finally
  }
  
  /* Error */
  public void s(DataHolder paramDataHolder)
  {
    // Byte code:
    //   0: invokestatic 24	android/os/Parcel:obtain	()Landroid/os/Parcel;
    //   3: astore_2
    //   4: invokestatic 24	android/os/Parcel:obtain	()Landroid/os/Parcel;
    //   7: astore_3
    //   8: aload_2
    //   9: ldc 26
    //   11: invokevirtual 30	android/os/Parcel:writeInterfaceToken	(Ljava/lang/String;)V
    //   14: aload_1
    //   15: ifnull +43 -> 58
    //   18: aload_2
    //   19: iconst_1
    //   20: invokevirtual 34	android/os/Parcel:writeInt	(I)V
    //   23: aload_1
    //   24: aload_2
    //   25: iconst_0
    //   26: invokevirtual 40	com/google/android/gms/common/data/DataHolder:writeToParcel	(Landroid/os/Parcel;I)V
    //   29: aload_0
    //   30: getfield 15	com/google/android/gms/games/internal/dl:a	Landroid/os/IBinder;
    //   33: sipush 8006
    //   36: aload_2
    //   37: aload_3
    //   38: iconst_0
    //   39: invokeinterface 46 5 0
    //   44: pop
    //   45: aload_3
    //   46: invokevirtual 49	android/os/Parcel:readException	()V
    //   49: aload_3
    //   50: invokevirtual 52	android/os/Parcel:recycle	()V
    //   53: aload_2
    //   54: invokevirtual 52	android/os/Parcel:recycle	()V
    //   57: return
    //   58: aload_2
    //   59: iconst_0
    //   60: invokevirtual 34	android/os/Parcel:writeInt	(I)V
    //   63: goto -34 -> 29
    //   66: astore_1
    //   67: aload_3
    //   68: invokevirtual 52	android/os/Parcel:recycle	()V
    //   71: aload_2
    //   72: invokevirtual 52	android/os/Parcel:recycle	()V
    //   75: aload_1
    //   76: athrow
    // Local variable table:
    //   start	length	slot	name	signature
    //   0	77	0	this	dl
    //   0	77	1	paramDataHolder	DataHolder
    //   3	69	2	localParcel1	Parcel
    //   7	61	3	localParcel2	Parcel
    // Exception table:
    //   from	to	target	type
    //   8	14	66	finally
    //   18	29	66	finally
    //   29	49	66	finally
    //   58	63	66	finally
  }
  
  /* Error */
  public void t(DataHolder paramDataHolder)
  {
    // Byte code:
    //   0: invokestatic 24	android/os/Parcel:obtain	()Landroid/os/Parcel;
    //   3: astore_2
    //   4: invokestatic 24	android/os/Parcel:obtain	()Landroid/os/Parcel;
    //   7: astore_3
    //   8: aload_2
    //   9: ldc 26
    //   11: invokevirtual 30	android/os/Parcel:writeInterfaceToken	(Ljava/lang/String;)V
    //   14: aload_1
    //   15: ifnull +43 -> 58
    //   18: aload_2
    //   19: iconst_1
    //   20: invokevirtual 34	android/os/Parcel:writeInt	(I)V
    //   23: aload_1
    //   24: aload_2
    //   25: iconst_0
    //   26: invokevirtual 40	com/google/android/gms/common/data/DataHolder:writeToParcel	(Landroid/os/Parcel;I)V
    //   29: aload_0
    //   30: getfield 15	com/google/android/gms/games/internal/dl:a	Landroid/os/IBinder;
    //   33: sipush 8008
    //   36: aload_2
    //   37: aload_3
    //   38: iconst_0
    //   39: invokeinterface 46 5 0
    //   44: pop
    //   45: aload_3
    //   46: invokevirtual 49	android/os/Parcel:readException	()V
    //   49: aload_3
    //   50: invokevirtual 52	android/os/Parcel:recycle	()V
    //   53: aload_2
    //   54: invokevirtual 52	android/os/Parcel:recycle	()V
    //   57: return
    //   58: aload_2
    //   59: iconst_0
    //   60: invokevirtual 34	android/os/Parcel:writeInt	(I)V
    //   63: goto -34 -> 29
    //   66: astore_1
    //   67: aload_3
    //   68: invokevirtual 52	android/os/Parcel:recycle	()V
    //   71: aload_2
    //   72: invokevirtual 52	android/os/Parcel:recycle	()V
    //   75: aload_1
    //   76: athrow
    // Local variable table:
    //   start	length	slot	name	signature
    //   0	77	0	this	dl
    //   0	77	1	paramDataHolder	DataHolder
    //   3	69	2	localParcel1	Parcel
    //   7	61	3	localParcel2	Parcel
    // Exception table:
    //   from	to	target	type
    //   8	14	66	finally
    //   18	29	66	finally
    //   29	49	66	finally
    //   58	63	66	finally
  }
  
  /* Error */
  public void u(DataHolder paramDataHolder)
  {
    // Byte code:
    //   0: invokestatic 24	android/os/Parcel:obtain	()Landroid/os/Parcel;
    //   3: astore_2
    //   4: invokestatic 24	android/os/Parcel:obtain	()Landroid/os/Parcel;
    //   7: astore_3
    //   8: aload_2
    //   9: ldc 26
    //   11: invokevirtual 30	android/os/Parcel:writeInterfaceToken	(Ljava/lang/String;)V
    //   14: aload_1
    //   15: ifnull +43 -> 58
    //   18: aload_2
    //   19: iconst_1
    //   20: invokevirtual 34	android/os/Parcel:writeInt	(I)V
    //   23: aload_1
    //   24: aload_2
    //   25: iconst_0
    //   26: invokevirtual 40	com/google/android/gms/common/data/DataHolder:writeToParcel	(Landroid/os/Parcel;I)V
    //   29: aload_0
    //   30: getfield 15	com/google/android/gms/games/internal/dl:a	Landroid/os/IBinder;
    //   33: sipush 5018
    //   36: aload_2
    //   37: aload_3
    //   38: iconst_0
    //   39: invokeinterface 46 5 0
    //   44: pop
    //   45: aload_3
    //   46: invokevirtual 49	android/os/Parcel:readException	()V
    //   49: aload_3
    //   50: invokevirtual 52	android/os/Parcel:recycle	()V
    //   53: aload_2
    //   54: invokevirtual 52	android/os/Parcel:recycle	()V
    //   57: return
    //   58: aload_2
    //   59: iconst_0
    //   60: invokevirtual 34	android/os/Parcel:writeInt	(I)V
    //   63: goto -34 -> 29
    //   66: astore_1
    //   67: aload_3
    //   68: invokevirtual 52	android/os/Parcel:recycle	()V
    //   71: aload_2
    //   72: invokevirtual 52	android/os/Parcel:recycle	()V
    //   75: aload_1
    //   76: athrow
    // Local variable table:
    //   start	length	slot	name	signature
    //   0	77	0	this	dl
    //   0	77	1	paramDataHolder	DataHolder
    //   3	69	2	localParcel1	Parcel
    //   7	61	3	localParcel2	Parcel
    // Exception table:
    //   from	to	target	type
    //   8	14	66	finally
    //   18	29	66	finally
    //   29	49	66	finally
    //   58	63	66	finally
  }
  
  /* Error */
  public void v(DataHolder paramDataHolder)
  {
    // Byte code:
    //   0: invokestatic 24	android/os/Parcel:obtain	()Landroid/os/Parcel;
    //   3: astore_2
    //   4: invokestatic 24	android/os/Parcel:obtain	()Landroid/os/Parcel;
    //   7: astore_3
    //   8: aload_2
    //   9: ldc 26
    //   11: invokevirtual 30	android/os/Parcel:writeInterfaceToken	(Ljava/lang/String;)V
    //   14: aload_1
    //   15: ifnull +43 -> 58
    //   18: aload_2
    //   19: iconst_1
    //   20: invokevirtual 34	android/os/Parcel:writeInt	(I)V
    //   23: aload_1
    //   24: aload_2
    //   25: iconst_0
    //   26: invokevirtual 40	com/google/android/gms/common/data/DataHolder:writeToParcel	(Landroid/os/Parcel;I)V
    //   29: aload_0
    //   30: getfield 15	com/google/android/gms/games/internal/dl:a	Landroid/os/IBinder;
    //   33: sipush 5019
    //   36: aload_2
    //   37: aload_3
    //   38: iconst_0
    //   39: invokeinterface 46 5 0
    //   44: pop
    //   45: aload_3
    //   46: invokevirtual 49	android/os/Parcel:readException	()V
    //   49: aload_3
    //   50: invokevirtual 52	android/os/Parcel:recycle	()V
    //   53: aload_2
    //   54: invokevirtual 52	android/os/Parcel:recycle	()V
    //   57: return
    //   58: aload_2
    //   59: iconst_0
    //   60: invokevirtual 34	android/os/Parcel:writeInt	(I)V
    //   63: goto -34 -> 29
    //   66: astore_1
    //   67: aload_3
    //   68: invokevirtual 52	android/os/Parcel:recycle	()V
    //   71: aload_2
    //   72: invokevirtual 52	android/os/Parcel:recycle	()V
    //   75: aload_1
    //   76: athrow
    // Local variable table:
    //   start	length	slot	name	signature
    //   0	77	0	this	dl
    //   0	77	1	paramDataHolder	DataHolder
    //   3	69	2	localParcel1	Parcel
    //   7	61	3	localParcel2	Parcel
    // Exception table:
    //   from	to	target	type
    //   8	14	66	finally
    //   18	29	66	finally
    //   29	49	66	finally
    //   58	63	66	finally
  }
  
  /* Error */
  public void w(DataHolder paramDataHolder)
  {
    // Byte code:
    //   0: invokestatic 24	android/os/Parcel:obtain	()Landroid/os/Parcel;
    //   3: astore_2
    //   4: invokestatic 24	android/os/Parcel:obtain	()Landroid/os/Parcel;
    //   7: astore_3
    //   8: aload_2
    //   9: ldc 26
    //   11: invokevirtual 30	android/os/Parcel:writeInterfaceToken	(Ljava/lang/String;)V
    //   14: aload_1
    //   15: ifnull +43 -> 58
    //   18: aload_2
    //   19: iconst_1
    //   20: invokevirtual 34	android/os/Parcel:writeInt	(I)V
    //   23: aload_1
    //   24: aload_2
    //   25: iconst_0
    //   26: invokevirtual 40	com/google/android/gms/common/data/DataHolder:writeToParcel	(Landroid/os/Parcel;I)V
    //   29: aload_0
    //   30: getfield 15	com/google/android/gms/games/internal/dl:a	Landroid/os/IBinder;
    //   33: sipush 5021
    //   36: aload_2
    //   37: aload_3
    //   38: iconst_0
    //   39: invokeinterface 46 5 0
    //   44: pop
    //   45: aload_3
    //   46: invokevirtual 49	android/os/Parcel:readException	()V
    //   49: aload_3
    //   50: invokevirtual 52	android/os/Parcel:recycle	()V
    //   53: aload_2
    //   54: invokevirtual 52	android/os/Parcel:recycle	()V
    //   57: return
    //   58: aload_2
    //   59: iconst_0
    //   60: invokevirtual 34	android/os/Parcel:writeInt	(I)V
    //   63: goto -34 -> 29
    //   66: astore_1
    //   67: aload_3
    //   68: invokevirtual 52	android/os/Parcel:recycle	()V
    //   71: aload_2
    //   72: invokevirtual 52	android/os/Parcel:recycle	()V
    //   75: aload_1
    //   76: athrow
    // Local variable table:
    //   start	length	slot	name	signature
    //   0	77	0	this	dl
    //   0	77	1	paramDataHolder	DataHolder
    //   3	69	2	localParcel1	Parcel
    //   7	61	3	localParcel2	Parcel
    // Exception table:
    //   from	to	target	type
    //   8	14	66	finally
    //   18	29	66	finally
    //   29	49	66	finally
    //   58	63	66	finally
  }
  
  /* Error */
  public void x(DataHolder paramDataHolder)
  {
    // Byte code:
    //   0: invokestatic 24	android/os/Parcel:obtain	()Landroid/os/Parcel;
    //   3: astore_2
    //   4: invokestatic 24	android/os/Parcel:obtain	()Landroid/os/Parcel;
    //   7: astore_3
    //   8: aload_2
    //   9: ldc 26
    //   11: invokevirtual 30	android/os/Parcel:writeInterfaceToken	(Ljava/lang/String;)V
    //   14: aload_1
    //   15: ifnull +43 -> 58
    //   18: aload_2
    //   19: iconst_1
    //   20: invokevirtual 34	android/os/Parcel:writeInt	(I)V
    //   23: aload_1
    //   24: aload_2
    //   25: iconst_0
    //   26: invokevirtual 40	com/google/android/gms/common/data/DataHolder:writeToParcel	(Landroid/os/Parcel;I)V
    //   29: aload_0
    //   30: getfield 15	com/google/android/gms/games/internal/dl:a	Landroid/os/IBinder;
    //   33: sipush 5022
    //   36: aload_2
    //   37: aload_3
    //   38: iconst_0
    //   39: invokeinterface 46 5 0
    //   44: pop
    //   45: aload_3
    //   46: invokevirtual 49	android/os/Parcel:readException	()V
    //   49: aload_3
    //   50: invokevirtual 52	android/os/Parcel:recycle	()V
    //   53: aload_2
    //   54: invokevirtual 52	android/os/Parcel:recycle	()V
    //   57: return
    //   58: aload_2
    //   59: iconst_0
    //   60: invokevirtual 34	android/os/Parcel:writeInt	(I)V
    //   63: goto -34 -> 29
    //   66: astore_1
    //   67: aload_3
    //   68: invokevirtual 52	android/os/Parcel:recycle	()V
    //   71: aload_2
    //   72: invokevirtual 52	android/os/Parcel:recycle	()V
    //   75: aload_1
    //   76: athrow
    // Local variable table:
    //   start	length	slot	name	signature
    //   0	77	0	this	dl
    //   0	77	1	paramDataHolder	DataHolder
    //   3	69	2	localParcel1	Parcel
    //   7	61	3	localParcel2	Parcel
    // Exception table:
    //   from	to	target	type
    //   8	14	66	finally
    //   18	29	66	finally
    //   29	49	66	finally
    //   58	63	66	finally
  }
  
  /* Error */
  public void y(DataHolder paramDataHolder)
  {
    // Byte code:
    //   0: invokestatic 24	android/os/Parcel:obtain	()Landroid/os/Parcel;
    //   3: astore_2
    //   4: invokestatic 24	android/os/Parcel:obtain	()Landroid/os/Parcel;
    //   7: astore_3
    //   8: aload_2
    //   9: ldc 26
    //   11: invokevirtual 30	android/os/Parcel:writeInterfaceToken	(Ljava/lang/String;)V
    //   14: aload_1
    //   15: ifnull +43 -> 58
    //   18: aload_2
    //   19: iconst_1
    //   20: invokevirtual 34	android/os/Parcel:writeInt	(I)V
    //   23: aload_1
    //   24: aload_2
    //   25: iconst_0
    //   26: invokevirtual 40	com/google/android/gms/common/data/DataHolder:writeToParcel	(Landroid/os/Parcel;I)V
    //   29: aload_0
    //   30: getfield 15	com/google/android/gms/games/internal/dl:a	Landroid/os/IBinder;
    //   33: sipush 5023
    //   36: aload_2
    //   37: aload_3
    //   38: iconst_0
    //   39: invokeinterface 46 5 0
    //   44: pop
    //   45: aload_3
    //   46: invokevirtual 49	android/os/Parcel:readException	()V
    //   49: aload_3
    //   50: invokevirtual 52	android/os/Parcel:recycle	()V
    //   53: aload_2
    //   54: invokevirtual 52	android/os/Parcel:recycle	()V
    //   57: return
    //   58: aload_2
    //   59: iconst_0
    //   60: invokevirtual 34	android/os/Parcel:writeInt	(I)V
    //   63: goto -34 -> 29
    //   66: astore_1
    //   67: aload_3
    //   68: invokevirtual 52	android/os/Parcel:recycle	()V
    //   71: aload_2
    //   72: invokevirtual 52	android/os/Parcel:recycle	()V
    //   75: aload_1
    //   76: athrow
    // Local variable table:
    //   start	length	slot	name	signature
    //   0	77	0	this	dl
    //   0	77	1	paramDataHolder	DataHolder
    //   3	69	2	localParcel1	Parcel
    //   7	61	3	localParcel2	Parcel
    // Exception table:
    //   from	to	target	type
    //   8	14	66	finally
    //   18	29	66	finally
    //   29	49	66	finally
    //   58	63	66	finally
  }
  
  /* Error */
  public void z(DataHolder paramDataHolder)
  {
    // Byte code:
    //   0: invokestatic 24	android/os/Parcel:obtain	()Landroid/os/Parcel;
    //   3: astore_2
    //   4: invokestatic 24	android/os/Parcel:obtain	()Landroid/os/Parcel;
    //   7: astore_3
    //   8: aload_2
    //   9: ldc 26
    //   11: invokevirtual 30	android/os/Parcel:writeInterfaceToken	(Ljava/lang/String;)V
    //   14: aload_1
    //   15: ifnull +43 -> 58
    //   18: aload_2
    //   19: iconst_1
    //   20: invokevirtual 34	android/os/Parcel:writeInt	(I)V
    //   23: aload_1
    //   24: aload_2
    //   25: iconst_0
    //   26: invokevirtual 40	com/google/android/gms/common/data/DataHolder:writeToParcel	(Landroid/os/Parcel;I)V
    //   29: aload_0
    //   30: getfield 15	com/google/android/gms/games/internal/dl:a	Landroid/os/IBinder;
    //   33: sipush 5024
    //   36: aload_2
    //   37: aload_3
    //   38: iconst_0
    //   39: invokeinterface 46 5 0
    //   44: pop
    //   45: aload_3
    //   46: invokevirtual 49	android/os/Parcel:readException	()V
    //   49: aload_3
    //   50: invokevirtual 52	android/os/Parcel:recycle	()V
    //   53: aload_2
    //   54: invokevirtual 52	android/os/Parcel:recycle	()V
    //   57: return
    //   58: aload_2
    //   59: iconst_0
    //   60: invokevirtual 34	android/os/Parcel:writeInt	(I)V
    //   63: goto -34 -> 29
    //   66: astore_1
    //   67: aload_3
    //   68: invokevirtual 52	android/os/Parcel:recycle	()V
    //   71: aload_2
    //   72: invokevirtual 52	android/os/Parcel:recycle	()V
    //   75: aload_1
    //   76: athrow
    // Local variable table:
    //   start	length	slot	name	signature
    //   0	77	0	this	dl
    //   0	77	1	paramDataHolder	DataHolder
    //   3	69	2	localParcel1	Parcel
    //   7	61	3	localParcel2	Parcel
    // Exception table:
    //   from	to	target	type
    //   8	14	66	finally
    //   18	29	66	finally
    //   29	49	66	finally
    //   58	63	66	finally
  }
}


/* Location:              /Users/amaurremi/uw/stringoid/static-dynamic-comparison/apps/retrica/com.venticake.retrica-21-dex2jar.jar!/com/google/android/gms/games/internal/dl.class
 * Java compiler version: 6 (50.0)
 * JD-Core Version:       0.7.1
 */