package com.skplanet.tad.videoplayer.manager;

public class a
{
  /* Error */
  public static String a(String paramString1, String paramString2, String paramString3)
  {
    // Byte code:
    //   0: aconst_null
    //   1: astore 5
    //   3: aconst_null
    //   4: astore 4
    //   6: new 12	java/net/URL
    //   9: dup
    //   10: aload_0
    //   11: invokespecial 16	java/net/URL:<init>	(Ljava/lang/String;)V
    //   14: astore 6
    //   16: ldc 18
    //   18: invokestatic 22	com/skplanet/tad/videoplayer/util/b:a	(Ljava/lang/String;)V
    //   21: new 24	java/lang/StringBuilder
    //   24: dup
    //   25: ldc 26
    //   27: invokespecial 27	java/lang/StringBuilder:<init>	(Ljava/lang/String;)V
    //   30: aload_0
    //   31: invokevirtual 31	java/lang/StringBuilder:append	(Ljava/lang/String;)Ljava/lang/StringBuilder;
    //   34: invokevirtual 35	java/lang/StringBuilder:toString	()Ljava/lang/String;
    //   37: invokestatic 22	com/skplanet/tad/videoplayer/util/b:a	(Ljava/lang/String;)V
    //   40: aload 6
    //   42: invokevirtual 39	java/net/URL:openConnection	()Ljava/net/URLConnection;
    //   45: checkcast 41	java/net/HttpURLConnection
    //   48: astore_0
    //   49: aload_0
    //   50: iconst_1
    //   51: invokevirtual 45	java/net/HttpURLConnection:setDoOutput	(Z)V
    //   54: aload_0
    //   55: iconst_1
    //   56: invokevirtual 48	java/net/HttpURLConnection:setDoInput	(Z)V
    //   59: aload_0
    //   60: iconst_0
    //   61: invokevirtual 51	java/net/HttpURLConnection:setUseCaches	(Z)V
    //   64: aload_0
    //   65: aload_1
    //   66: invokevirtual 54	java/net/HttpURLConnection:setRequestMethod	(Ljava/lang/String;)V
    //   69: aload_0
    //   70: sipush 10000
    //   73: invokevirtual 58	java/net/HttpURLConnection:setConnectTimeout	(I)V
    //   76: aload_2
    //   77: ifnull +37 -> 114
    //   80: aload_2
    //   81: ldc 60
    //   83: invokevirtual 66	java/lang/String:equals	(Ljava/lang/Object;)Z
    //   86: ifne +28 -> 114
    //   89: new 68	java/io/OutputStreamWriter
    //   92: dup
    //   93: aload_0
    //   94: invokevirtual 72	java/net/HttpURLConnection:getOutputStream	()Ljava/io/OutputStream;
    //   97: invokespecial 75	java/io/OutputStreamWriter:<init>	(Ljava/io/OutputStream;)V
    //   100: astore_1
    //   101: aload_1
    //   102: aload_2
    //   103: invokevirtual 78	java/io/OutputStreamWriter:write	(Ljava/lang/String;)V
    //   106: aload_1
    //   107: invokevirtual 82	java/io/OutputStreamWriter:flush	()V
    //   110: aload_1
    //   111: invokevirtual 85	java/io/OutputStreamWriter:close	()V
    //   114: aload_0
    //   115: invokevirtual 89	java/net/HttpURLConnection:getResponseCode	()I
    //   118: istore_3
    //   119: new 24	java/lang/StringBuilder
    //   122: dup
    //   123: ldc 91
    //   125: invokespecial 27	java/lang/StringBuilder:<init>	(Ljava/lang/String;)V
    //   128: iload_3
    //   129: invokevirtual 94	java/lang/StringBuilder:append	(I)Ljava/lang/StringBuilder;
    //   132: invokevirtual 35	java/lang/StringBuilder:toString	()Ljava/lang/String;
    //   135: invokestatic 22	com/skplanet/tad/videoplayer/util/b:a	(Ljava/lang/String;)V
    //   138: iload_3
    //   139: sipush 200
    //   142: if_icmpne +110 -> 252
    //   145: aload_0
    //   146: invokevirtual 98	java/net/HttpURLConnection:getInputStream	()Ljava/io/InputStream;
    //   149: astore_1
    //   150: new 100	java/io/BufferedReader
    //   153: dup
    //   154: new 102	java/io/InputStreamReader
    //   157: dup
    //   158: aload_1
    //   159: invokespecial 105	java/io/InputStreamReader:<init>	(Ljava/io/InputStream;)V
    //   162: invokespecial 108	java/io/BufferedReader:<init>	(Ljava/io/Reader;)V
    //   165: astore 4
    //   167: new 24	java/lang/StringBuilder
    //   170: dup
    //   171: invokespecial 110	java/lang/StringBuilder:<init>	()V
    //   174: astore_1
    //   175: aload 4
    //   177: invokevirtual 113	java/io/BufferedReader:readLine	()Ljava/lang/String;
    //   180: astore_2
    //   181: aload_2
    //   182: ifnonnull +78 -> 260
    //   185: aload_1
    //   186: invokevirtual 116	java/lang/StringBuilder:length	()I
    //   189: ifle +119 -> 308
    //   192: aload_1
    //   193: invokevirtual 35	java/lang/StringBuilder:toString	()Ljava/lang/String;
    //   196: astore_1
    //   197: new 24	java/lang/StringBuilder
    //   200: dup
    //   201: ldc 118
    //   203: invokespecial 27	java/lang/StringBuilder:<init>	(Ljava/lang/String;)V
    //   206: aload_1
    //   207: invokevirtual 31	java/lang/StringBuilder:append	(Ljava/lang/String;)Ljava/lang/StringBuilder;
    //   210: invokevirtual 35	java/lang/StringBuilder:toString	()Ljava/lang/String;
    //   213: invokestatic 22	com/skplanet/tad/videoplayer/util/b:a	(Ljava/lang/String;)V
    //   216: aload 4
    //   218: ifnull +8 -> 226
    //   221: aload 4
    //   223: invokevirtual 119	java/io/BufferedReader:close	()V
    //   226: aload_0
    //   227: ifnull +7 -> 234
    //   230: aload_0
    //   231: invokevirtual 122	java/net/HttpURLConnection:disconnect	()V
    //   234: aload_1
    //   235: astore_2
    //   236: aload_2
    //   237: astore_0
    //   238: aload_2
    //   239: ldc 60
    //   241: invokevirtual 66	java/lang/String:equals	(Ljava/lang/Object;)Z
    //   244: ifeq +6 -> 250
    //   247: ldc 124
    //   249: astore_0
    //   250: aload_0
    //   251: areturn
    //   252: aload_0
    //   253: invokevirtual 127	java/net/HttpURLConnection:getErrorStream	()Ljava/io/InputStream;
    //   256: astore_1
    //   257: goto -107 -> 150
    //   260: aload_1
    //   261: aload_2
    //   262: invokevirtual 31	java/lang/StringBuilder:append	(Ljava/lang/String;)Ljava/lang/StringBuilder;
    //   265: pop
    //   266: goto -91 -> 175
    //   269: astore_2
    //   270: ldc 60
    //   272: astore 5
    //   274: aload_0
    //   275: astore_1
    //   276: aload 5
    //   278: astore_0
    //   279: aload_2
    //   280: invokevirtual 130	java/lang/Exception:printStackTrace	()V
    //   283: aload 4
    //   285: ifnull +8 -> 293
    //   288: aload 4
    //   290: invokevirtual 119	java/io/BufferedReader:close	()V
    //   293: aload_0
    //   294: astore_2
    //   295: aload_1
    //   296: ifnull -60 -> 236
    //   299: aload_1
    //   300: invokevirtual 122	java/net/HttpURLConnection:disconnect	()V
    //   303: aload_0
    //   304: astore_2
    //   305: goto -69 -> 236
    //   308: iload_3
    //   309: invokestatic 134	java/lang/String:valueOf	(I)Ljava/lang/String;
    //   312: astore_1
    //   313: goto -116 -> 197
    //   316: astore_2
    //   317: aload_2
    //   318: invokevirtual 135	java/io/IOException:printStackTrace	()V
    //   321: goto -28 -> 293
    //   324: astore_0
    //   325: aconst_null
    //   326: astore 4
    //   328: aload 5
    //   330: astore_1
    //   331: aload 4
    //   333: ifnull +8 -> 341
    //   336: aload 4
    //   338: invokevirtual 119	java/io/BufferedReader:close	()V
    //   341: aload_1
    //   342: ifnull +7 -> 349
    //   345: aload_1
    //   346: invokevirtual 122	java/net/HttpURLConnection:disconnect	()V
    //   349: aload_0
    //   350: athrow
    //   351: astore_2
    //   352: aload_2
    //   353: invokevirtual 135	java/io/IOException:printStackTrace	()V
    //   356: goto -15 -> 341
    //   359: astore_2
    //   360: aload_2
    //   361: invokevirtual 135	java/io/IOException:printStackTrace	()V
    //   364: goto -138 -> 226
    //   367: astore_2
    //   368: aconst_null
    //   369: astore 4
    //   371: aload_0
    //   372: astore_1
    //   373: aload_2
    //   374: astore_0
    //   375: goto -44 -> 331
    //   378: astore_2
    //   379: aload_0
    //   380: astore_1
    //   381: aload_2
    //   382: astore_0
    //   383: goto -52 -> 331
    //   386: astore_0
    //   387: goto -56 -> 331
    //   390: astore_2
    //   391: aconst_null
    //   392: astore 5
    //   394: ldc 60
    //   396: astore_0
    //   397: aload 4
    //   399: astore_1
    //   400: aload 5
    //   402: astore 4
    //   404: goto -125 -> 279
    //   407: astore_2
    //   408: aconst_null
    //   409: astore 4
    //   411: aload_0
    //   412: astore_1
    //   413: ldc 60
    //   415: astore_0
    //   416: goto -137 -> 279
    //   419: astore_2
    //   420: aload_0
    //   421: astore 5
    //   423: aload_1
    //   424: astore_0
    //   425: aload 5
    //   427: astore_1
    //   428: goto -149 -> 279
    // Local variable table:
    //   start	length	slot	name	signature
    //   0	431	0	paramString1	String
    //   0	431	1	paramString2	String
    //   0	431	2	paramString3	String
    //   118	191	3	i	int
    //   4	406	4	localObject	Object
    //   1	425	5	str	String
    //   14	27	6	localURL	java.net.URL
    // Exception table:
    //   from	to	target	type
    //   167	175	269	java/lang/Exception
    //   175	181	269	java/lang/Exception
    //   185	197	269	java/lang/Exception
    //   260	266	269	java/lang/Exception
    //   288	293	316	java/io/IOException
    //   6	49	324	finally
    //   336	341	351	java/io/IOException
    //   221	226	359	java/io/IOException
    //   49	76	367	finally
    //   80	114	367	finally
    //   114	138	367	finally
    //   145	150	367	finally
    //   150	167	367	finally
    //   252	257	367	finally
    //   167	175	378	finally
    //   175	181	378	finally
    //   185	197	378	finally
    //   197	216	378	finally
    //   260	266	378	finally
    //   279	283	386	finally
    //   6	49	390	java/lang/Exception
    //   49	76	407	java/lang/Exception
    //   80	114	407	java/lang/Exception
    //   114	138	407	java/lang/Exception
    //   145	150	407	java/lang/Exception
    //   150	167	407	java/lang/Exception
    //   252	257	407	java/lang/Exception
    //   197	216	419	java/lang/Exception
  }
}


/* Location:              /Users/amaurremi/uw/stringoid/static-dynamic-comparison/apps/randomchat/com.pioong-93-dex2jar.jar!/com/skplanet/tad/videoplayer/manager/a.class
 * Java compiler version: 6 (50.0)
 * JD-Core Version:       0.7.1
 */