package com.flurry.sdk;

public class dc {
    private static final String a = dc.class.getSimpleName();
    private byte[] b;

    /* Error */
    public dc(String paramString1, String paramString2, boolean paramBoolean1, boolean paramBoolean2, long paramLong1, long paramLong2, java.util.List<dh> paramList, java.util.Map<dr, java.nio.ByteBuffer> paramMap, java.util.Map<String, java.util.List<String>> paramMap1, java.util.Map<String, java.util.List<String>> paramMap2, java.util.Map<String, java.util.Map<String, String>> paramMap3, long paramLong3)
            throws java.io.IOException {
        // Byte code:
        //   0: aload_0
        //   1: invokespecial 27	java/lang/Object:<init>	()V
        //   4: aload_0
        //   5: aconst_null
        //   6: putfield 29	com/flurry/sdk/dc:b	[B
        //   9: aconst_null
        //   10: astore 19
        //   12: new 31	com/flurry/sdk/ed
        //   15: dup
        //   16: invokespecial 32	com/flurry/sdk/ed:<init>	()V
        //   19: astore 20
        //   21: new 34	java/io/ByteArrayOutputStream
        //   24: dup
        //   25: invokespecial 35	java/io/ByteArrayOutputStream:<init>	()V
        //   28: astore 21
        //   30: new 37	java/security/DigestOutputStream
        //   33: dup
        //   34: aload 21
        //   36: aload 20
        //   38: invokespecial 40	java/security/DigestOutputStream:<init>	(Ljava/io/OutputStream;Ljava/security/MessageDigest;)V
        //   41: astore 22
        //   43: new 42	java/io/DataOutputStream
        //   46: dup
        //   47: aload 22
        //   49: invokespecial 45	java/io/DataOutputStream:<init>	(Ljava/io/OutputStream;)V
        //   52: astore 18
        //   54: aload 18
        //   56: bipush 29
        //   58: invokevirtual 49	java/io/DataOutputStream:writeShort	(I)V
        //   61: aload 18
        //   63: iconst_0
        //   64: invokevirtual 49	java/io/DataOutputStream:writeShort	(I)V
        //   67: aload 18
        //   69: lconst_0
        //   70: invokevirtual 53	java/io/DataOutputStream:writeLong	(J)V
        //   73: aload 18
        //   75: iconst_0
        //   76: invokevirtual 49	java/io/DataOutputStream:writeShort	(I)V
        //   79: aload 18
        //   81: iconst_3
        //   82: invokevirtual 49	java/io/DataOutputStream:writeShort	(I)V
        //   85: aload 18
        //   87: invokestatic 59	com/flurry/android/FlurryAgent:getAgentVersion	()I
        //   90: invokevirtual 49	java/io/DataOutputStream:writeShort	(I)V
        //   93: aload 18
        //   95: lload 14
        //   97: invokevirtual 53	java/io/DataOutputStream:writeLong	(J)V
        //   100: aload 18
        //   102: aload_1
        //   103: invokevirtual 63	java/io/DataOutputStream:writeUTF	(Ljava/lang/String;)V
        //   106: aload 18
        //   108: aload_2
        //   109: invokevirtual 63	java/io/DataOutputStream:writeUTF	(Ljava/lang/String;)V
        //   112: aload 18
        //   114: aload 10
        //   116: invokeinterface 68 1 0
        //   121: invokevirtual 49	java/io/DataOutputStream:writeShort	(I)V
        //   124: aload 10
        //   126: invokeinterface 72 1 0
        //   131: invokeinterface 78 1 0
        //   136: astore_1
        //   137: aload_1
        //   138: invokeinterface 84 1 0
        //   143: ifeq +86 -> 229
        //   146: aload_1
        //   147: invokeinterface 88 1 0
        //   152: checkcast 90	java/util/Map$Entry
        //   155: astore_2
        //   156: aload 18
        //   158: aload_2
        //   159: invokeinterface 93 1 0
        //   164: checkcast 95	com/flurry/sdk/dr
        //   167: getfield 99	com/flurry/sdk/dr:d	I
        //   170: invokevirtual 49	java/io/DataOutputStream:writeShort	(I)V
        //   173: aload_2
        //   174: invokeinterface 102 1 0
        //   179: checkcast 104	java/nio/ByteBuffer
        //   182: invokevirtual 108	java/nio/ByteBuffer:array	()[B
        //   185: astore_2
        //   186: aload 18
        //   188: aload_2
        //   189: arraylength
        //   190: invokevirtual 49	java/io/DataOutputStream:writeShort	(I)V
        //   193: aload 18
        //   195: aload_2
        //   196: invokevirtual 112	java/io/DataOutputStream:write	([B)V
        //   199: goto -62 -> 137
        //   202: astore_2
        //   203: aload 18
        //   205: astore_1
        //   206: bipush 6
        //   208: getstatic 18	com/flurry/sdk/dc:a	Ljava/lang/String;
        //   211: ldc 114
        //   213: aload_2
        //   214: invokestatic 119	com/flurry/sdk/eo:a	(ILjava/lang/String;Ljava/lang/String;Ljava/lang/Throwable;)V
        //   217: aload_1
        //   218: invokestatic 124	com/flurry/sdk/fe:a	(Ljava/io/Closeable;)V
        //   221: aconst_null
        //   222: astore_1
        //   223: aload_0
        //   224: aload_1
        //   225: putfield 29	com/flurry/sdk/dc:b	[B
        //   228: return
        //   229: aload 18
        //   231: iconst_0
        //   232: invokevirtual 127	java/io/DataOutputStream:writeByte	(I)V
        //   235: aload 18
        //   237: iload_3
        //   238: invokevirtual 131	java/io/DataOutputStream:writeBoolean	(Z)V
        //   241: aload 18
        //   243: iload 4
        //   245: invokevirtual 131	java/io/DataOutputStream:writeBoolean	(Z)V
        //   248: aload 18
        //   250: lload 5
        //   252: invokevirtual 53	java/io/DataOutputStream:writeLong	(J)V
        //   255: aload 18
        //   257: lload 7
        //   259: invokevirtual 53	java/io/DataOutputStream:writeLong	(J)V
        //   262: aload 18
        //   264: bipush 6
        //   266: invokevirtual 49	java/io/DataOutputStream:writeShort	(I)V
        //   269: aload 18
        //   271: ldc -123
        //   273: invokevirtual 63	java/io/DataOutputStream:writeUTF	(Ljava/lang/String;)V
        //   276: aload 18
        //   278: getstatic 138	android/os/Build:MODEL	Ljava/lang/String;
        //   281: invokevirtual 63	java/io/DataOutputStream:writeUTF	(Ljava/lang/String;)V
        //   284: aload 18
        //   286: iconst_0
        //   287: invokevirtual 127	java/io/DataOutputStream:writeByte	(I)V
        //   290: aload 18
        //   292: ldc -116
        //   294: invokevirtual 63	java/io/DataOutputStream:writeUTF	(Ljava/lang/String;)V
        //   297: aload 18
        //   299: getstatic 143	android/os/Build:BRAND	Ljava/lang/String;
        //   302: invokevirtual 63	java/io/DataOutputStream:writeUTF	(Ljava/lang/String;)V
        //   305: aload 18
        //   307: iconst_0
        //   308: invokevirtual 127	java/io/DataOutputStream:writeByte	(I)V
        //   311: aload 18
        //   313: ldc -111
        //   315: invokevirtual 63	java/io/DataOutputStream:writeUTF	(Ljava/lang/String;)V
        //   318: aload 18
        //   320: getstatic 148	android/os/Build:ID	Ljava/lang/String;
        //   323: invokevirtual 63	java/io/DataOutputStream:writeUTF	(Ljava/lang/String;)V
        //   326: aload 18
        //   328: iconst_0
        //   329: invokevirtual 127	java/io/DataOutputStream:writeByte	(I)V
        //   332: aload 18
        //   334: ldc -106
        //   336: invokevirtual 63	java/io/DataOutputStream:writeUTF	(Ljava/lang/String;)V
        //   339: aload 18
        //   341: getstatic 155	android/os/Build$VERSION:RELEASE	Ljava/lang/String;
        //   344: invokevirtual 63	java/io/DataOutputStream:writeUTF	(Ljava/lang/String;)V
        //   347: aload 18
        //   349: iconst_0
        //   350: invokevirtual 127	java/io/DataOutputStream:writeByte	(I)V
        //   353: aload 18
        //   355: ldc -99
        //   357: invokevirtual 63	java/io/DataOutputStream:writeUTF	(Ljava/lang/String;)V
        //   360: aload 18
        //   362: getstatic 160	android/os/Build:DEVICE	Ljava/lang/String;
        //   365: invokevirtual 63	java/io/DataOutputStream:writeUTF	(Ljava/lang/String;)V
        //   368: aload 18
        //   370: iconst_0
        //   371: invokevirtual 127	java/io/DataOutputStream:writeByte	(I)V
        //   374: aload 18
        //   376: ldc -94
        //   378: invokevirtual 63	java/io/DataOutputStream:writeUTF	(Ljava/lang/String;)V
        //   381: aload 18
        //   383: getstatic 165	android/os/Build:PRODUCT	Ljava/lang/String;
        //   386: invokevirtual 63	java/io/DataOutputStream:writeUTF	(Ljava/lang/String;)V
        //   389: aload 18
        //   391: iconst_0
        //   392: invokevirtual 127	java/io/DataOutputStream:writeByte	(I)V
        //   395: aload 11
        //   397: ifnull +267 -> 664
        //   400: aload 11
        //   402: invokeinterface 168 1 0
        //   407: invokeinterface 169 1 0
        //   412: istore 16
        //   414: aload 18
        //   416: iload 16
        //   418: invokevirtual 49	java/io/DataOutputStream:writeShort	(I)V
        //   421: aload 11
        //   423: ifnull +247 -> 670
        //   426: iconst_3
        //   427: getstatic 18	com/flurry/sdk/dc:a	Ljava/lang/String;
        //   430: ldc -85
        //   432: invokestatic 174	com/flurry/sdk/eo:a	(ILjava/lang/String;Ljava/lang/String;)V
        //   435: aload 11
        //   437: invokeinterface 72 1 0
        //   442: invokeinterface 78 1 0
        //   447: astore_1
        //   448: aload_1
        //   449: invokeinterface 84 1 0
        //   454: ifeq +216 -> 670
        //   457: aload_1
        //   458: invokeinterface 88 1 0
        //   463: checkcast 90	java/util/Map$Entry
        //   466: astore_2
        //   467: iconst_3
        //   468: getstatic 18	com/flurry/sdk/dc:a	Ljava/lang/String;
        //   471: new 176	java/lang/StringBuilder
        //   474: dup
        //   475: invokespecial 177	java/lang/StringBuilder:<init>	()V
        //   478: ldc -77
        //   480: invokevirtual 183	java/lang/StringBuilder:append	(Ljava/lang/String;)Ljava/lang/StringBuilder;
        //   483: aload_2
        //   484: invokeinterface 93 1 0
        //   489: checkcast 185	java/lang/String
        //   492: invokevirtual 183	java/lang/StringBuilder:append	(Ljava/lang/String;)Ljava/lang/StringBuilder;
        //   495: ldc -69
        //   497: invokevirtual 183	java/lang/StringBuilder:append	(Ljava/lang/String;)Ljava/lang/StringBuilder;
        //   500: aload_2
        //   501: invokeinterface 102 1 0
        //   506: invokevirtual 190	java/lang/StringBuilder:append	(Ljava/lang/Object;)Ljava/lang/StringBuilder;
        //   509: invokevirtual 193	java/lang/StringBuilder:toString	()Ljava/lang/String;
        //   512: invokestatic 174	com/flurry/sdk/eo:a	(ILjava/lang/String;Ljava/lang/String;)V
        //   515: aload 18
        //   517: aload_2
        //   518: invokeinterface 93 1 0
        //   523: checkcast 185	java/lang/String
        //   526: invokevirtual 63	java/io/DataOutputStream:writeUTF	(Ljava/lang/String;)V
        //   529: iconst_3
        //   530: getstatic 18	com/flurry/sdk/dc:a	Ljava/lang/String;
        //   533: new 176	java/lang/StringBuilder
        //   536: dup
        //   537: invokespecial 177	java/lang/StringBuilder:<init>	()V
        //   540: ldc -61
        //   542: invokevirtual 183	java/lang/StringBuilder:append	(Ljava/lang/String;)Ljava/lang/StringBuilder;
        //   545: aload_2
        //   546: invokeinterface 93 1 0
        //   551: checkcast 185	java/lang/String
        //   554: invokevirtual 183	java/lang/StringBuilder:append	(Ljava/lang/String;)Ljava/lang/StringBuilder;
        //   557: invokevirtual 193	java/lang/StringBuilder:toString	()Ljava/lang/String;
        //   560: invokestatic 174	com/flurry/sdk/eo:a	(ILjava/lang/String;Ljava/lang/String;)V
        //   563: aload 18
        //   565: aload_2
        //   566: invokeinterface 102 1 0
        //   571: checkcast 197	java/util/List
        //   574: invokeinterface 198 1 0
        //   579: invokevirtual 49	java/io/DataOutputStream:writeShort	(I)V
        //   582: aload_2
        //   583: invokeinterface 102 1 0
        //   588: checkcast 197	java/util/List
        //   591: invokeinterface 199 1 0
        //   596: astore_2
        //   597: aload_2
        //   598: invokeinterface 84 1 0
        //   603: ifeq -155 -> 448
        //   606: aload_2
        //   607: invokeinterface 88 1 0
        //   612: checkcast 185	java/lang/String
        //   615: astore 10
        //   617: aload 18
        //   619: aload 10
        //   621: invokevirtual 63	java/io/DataOutputStream:writeUTF	(Ljava/lang/String;)V
        //   624: iconst_3
        //   625: getstatic 18	com/flurry/sdk/dc:a	Ljava/lang/String;
        //   628: new 176	java/lang/StringBuilder
        //   631: dup
        //   632: invokespecial 177	java/lang/StringBuilder:<init>	()V
        //   635: ldc -55
        //   637: invokevirtual 183	java/lang/StringBuilder:append	(Ljava/lang/String;)Ljava/lang/StringBuilder;
        //   640: aload 10
        //   642: invokevirtual 183	java/lang/StringBuilder:append	(Ljava/lang/String;)Ljava/lang/StringBuilder;
        //   645: invokevirtual 193	java/lang/StringBuilder:toString	()Ljava/lang/String;
        //   648: invokestatic 174	com/flurry/sdk/eo:a	(ILjava/lang/String;Ljava/lang/String;)V
        //   651: goto -54 -> 597
        //   654: astore_1
        //   655: aload 18
        //   657: astore_2
        //   658: aload_2
        //   659: invokestatic 124	com/flurry/sdk/fe:a	(Ljava/io/Closeable;)V
        //   662: aload_1
        //   663: athrow
        //   664: iconst_0
        //   665: istore 16
        //   667: goto -253 -> 414
        //   670: aload 18
        //   672: iconst_0
        //   673: invokevirtual 131	java/io/DataOutputStream:writeBoolean	(Z)V
        //   676: aload 12
        //   678: ifnull +746 -> 1424
        //   681: aload 12
        //   683: invokeinterface 168 1 0
        //   688: invokeinterface 169 1 0
        //   693: istore 16
        //   695: iconst_3
        //   696: getstatic 18	com/flurry/sdk/dc:a	Ljava/lang/String;
        //   699: new 176	java/lang/StringBuilder
        //   702: dup
        //   703: invokespecial 177	java/lang/StringBuilder:<init>	()V
        //   706: ldc -53
        //   708: invokevirtual 183	java/lang/StringBuilder:append	(Ljava/lang/String;)Ljava/lang/StringBuilder;
        //   711: iload 16
        //   713: invokevirtual 206	java/lang/StringBuilder:append	(I)Ljava/lang/StringBuilder;
        //   716: invokevirtual 193	java/lang/StringBuilder:toString	()Ljava/lang/String;
        //   719: invokestatic 174	com/flurry/sdk/eo:a	(ILjava/lang/String;Ljava/lang/String;)V
        //   722: aload 18
        //   724: iload 16
        //   726: invokevirtual 49	java/io/DataOutputStream:writeShort	(I)V
        //   729: aload 12
        //   731: ifnull +183 -> 914
        //   734: iconst_3
        //   735: getstatic 18	com/flurry/sdk/dc:a	Ljava/lang/String;
        //   738: ldc -48
        //   740: invokestatic 174	com/flurry/sdk/eo:a	(ILjava/lang/String;Ljava/lang/String;)V
        //   743: aload 12
        //   745: invokeinterface 72 1 0
        //   750: invokeinterface 78 1 0
        //   755: astore_1
        //   756: aload_1
        //   757: invokeinterface 84 1 0
        //   762: ifeq +152 -> 914
        //   765: aload_1
        //   766: invokeinterface 88 1 0
        //   771: checkcast 90	java/util/Map$Entry
        //   774: astore_2
        //   775: iconst_3
        //   776: getstatic 18	com/flurry/sdk/dc:a	Ljava/lang/String;
        //   779: new 176	java/lang/StringBuilder
        //   782: dup
        //   783: invokespecial 177	java/lang/StringBuilder:<init>	()V
        //   786: ldc -46
        //   788: invokevirtual 183	java/lang/StringBuilder:append	(Ljava/lang/String;)Ljava/lang/StringBuilder;
        //   791: aload_2
        //   792: invokeinterface 93 1 0
        //   797: checkcast 185	java/lang/String
        //   800: invokevirtual 183	java/lang/StringBuilder:append	(Ljava/lang/String;)Ljava/lang/StringBuilder;
        //   803: invokevirtual 193	java/lang/StringBuilder:toString	()Ljava/lang/String;
        //   806: invokestatic 174	com/flurry/sdk/eo:a	(ILjava/lang/String;Ljava/lang/String;)V
        //   809: aload 18
        //   811: aload_2
        //   812: invokeinterface 93 1 0
        //   817: checkcast 185	java/lang/String
        //   820: invokevirtual 63	java/io/DataOutputStream:writeUTF	(Ljava/lang/String;)V
        //   823: aload 18
        //   825: aload_2
        //   826: invokeinterface 102 1 0
        //   831: checkcast 197	java/util/List
        //   834: invokeinterface 198 1 0
        //   839: invokevirtual 49	java/io/DataOutputStream:writeShort	(I)V
        //   842: aload_2
        //   843: invokeinterface 102 1 0
        //   848: checkcast 197	java/util/List
        //   851: invokeinterface 199 1 0
        //   856: astore_2
        //   857: aload_2
        //   858: invokeinterface 84 1 0
        //   863: ifeq -107 -> 756
        //   866: aload_2
        //   867: invokeinterface 88 1 0
        //   872: checkcast 185	java/lang/String
        //   875: astore 10
        //   877: aload 18
        //   879: aload 10
        //   881: invokevirtual 63	java/io/DataOutputStream:writeUTF	(Ljava/lang/String;)V
        //   884: iconst_3
        //   885: getstatic 18	com/flurry/sdk/dc:a	Ljava/lang/String;
        //   888: new 176	java/lang/StringBuilder
        //   891: dup
        //   892: invokespecial 177	java/lang/StringBuilder:<init>	()V
        //   895: ldc -44
        //   897: invokevirtual 183	java/lang/StringBuilder:append	(Ljava/lang/String;)Ljava/lang/StringBuilder;
        //   900: aload 10
        //   902: invokevirtual 183	java/lang/StringBuilder:append	(Ljava/lang/String;)Ljava/lang/StringBuilder;
        //   905: invokevirtual 193	java/lang/StringBuilder:toString	()Ljava/lang/String;
        //   908: invokestatic 174	com/flurry/sdk/eo:a	(ILjava/lang/String;Ljava/lang/String;)V
        //   911: goto -54 -> 857
        //   914: aload 13
        //   916: ifnull +514 -> 1430
        //   919: aload 13
        //   921: invokeinterface 168 1 0
        //   926: invokeinterface 169 1 0
        //   931: istore 17
        //   933: iconst_3
        //   934: getstatic 18	com/flurry/sdk/dc:a	Ljava/lang/String;
        //   937: new 176	java/lang/StringBuilder
        //   940: dup
        //   941: invokespecial 177	java/lang/StringBuilder:<init>	()V
        //   944: ldc -42
        //   946: invokevirtual 183	java/lang/StringBuilder:append	(Ljava/lang/String;)Ljava/lang/StringBuilder;
        //   949: iload 16
        //   951: invokevirtual 206	java/lang/StringBuilder:append	(I)Ljava/lang/StringBuilder;
        //   954: invokevirtual 193	java/lang/StringBuilder:toString	()Ljava/lang/String;
        //   957: invokestatic 174	com/flurry/sdk/eo:a	(ILjava/lang/String;Ljava/lang/String;)V
        //   960: aload 18
        //   962: iload 17
        //   964: invokevirtual 49	java/io/DataOutputStream:writeShort	(I)V
        //   967: aload 13
        //   969: ifnull +336 -> 1305
        //   972: aload 13
        //   974: invokeinterface 72 1 0
        //   979: invokeinterface 78 1 0
        //   984: astore_2
        //   985: aload_2
        //   986: invokeinterface 84 1 0
        //   991: ifeq +314 -> 1305
        //   994: aload_2
        //   995: invokeinterface 88 1 0
        //   1000: checkcast 90	java/util/Map$Entry
        //   1003: astore 10
        //   1005: iconst_3
        //   1006: getstatic 18	com/flurry/sdk/dc:a	Ljava/lang/String;
        //   1009: new 176	java/lang/StringBuilder
        //   1012: dup
        //   1013: invokespecial 177	java/lang/StringBuilder:<init>	()V
        //   1016: ldc -40
        //   1018: invokevirtual 183	java/lang/StringBuilder:append	(Ljava/lang/String;)Ljava/lang/StringBuilder;
        //   1021: aload 10
        //   1023: invokeinterface 93 1 0
        //   1028: checkcast 185	java/lang/String
        //   1031: invokevirtual 183	java/lang/StringBuilder:append	(Ljava/lang/String;)Ljava/lang/StringBuilder;
        //   1034: invokevirtual 193	java/lang/StringBuilder:toString	()Ljava/lang/String;
        //   1037: invokestatic 174	com/flurry/sdk/eo:a	(ILjava/lang/String;Ljava/lang/String;)V
        //   1040: aload 18
        //   1042: aload 10
        //   1044: invokeinterface 93 1 0
        //   1049: checkcast 185	java/lang/String
        //   1052: invokevirtual 63	java/io/DataOutputStream:writeUTF	(Ljava/lang/String;)V
        //   1055: aload 18
        //   1057: aload 10
        //   1059: invokeinterface 102 1 0
        //   1064: checkcast 65	java/util/Map
        //   1067: invokeinterface 68 1 0
        //   1072: invokevirtual 49	java/io/DataOutputStream:writeShort	(I)V
        //   1075: iconst_3
        //   1076: getstatic 18	com/flurry/sdk/dc:a	Ljava/lang/String;
        //   1079: new 176	java/lang/StringBuilder
        //   1082: dup
        //   1083: invokespecial 177	java/lang/StringBuilder:<init>	()V
        //   1086: ldc -38
        //   1088: invokevirtual 183	java/lang/StringBuilder:append	(Ljava/lang/String;)Ljava/lang/StringBuilder;
        //   1091: aload 10
        //   1093: invokeinterface 93 1 0
        //   1098: checkcast 185	java/lang/String
        //   1101: invokevirtual 183	java/lang/StringBuilder:append	(Ljava/lang/String;)Ljava/lang/StringBuilder;
        //   1104: ldc -36
        //   1106: invokevirtual 183	java/lang/StringBuilder:append	(Ljava/lang/String;)Ljava/lang/StringBuilder;
        //   1109: aload 10
        //   1111: invokeinterface 102 1 0
        //   1116: checkcast 65	java/util/Map
        //   1119: invokeinterface 68 1 0
        //   1124: invokevirtual 206	java/lang/StringBuilder:append	(I)Ljava/lang/StringBuilder;
        //   1127: invokevirtual 193	java/lang/StringBuilder:toString	()Ljava/lang/String;
        //   1130: invokestatic 174	com/flurry/sdk/eo:a	(ILjava/lang/String;Ljava/lang/String;)V
        //   1133: aload 10
        //   1135: invokeinterface 102 1 0
        //   1140: checkcast 65	java/util/Map
        //   1143: invokeinterface 72 1 0
        //   1148: invokeinterface 78 1 0
        //   1153: astore 11
        //   1155: aload 11
        //   1157: invokeinterface 84 1 0
        //   1162: ifeq -177 -> 985
        //   1165: aload 11
        //   1167: invokeinterface 88 1 0
        //   1172: checkcast 90	java/util/Map$Entry
        //   1175: astore 12
        //   1177: iconst_3
        //   1178: getstatic 18	com/flurry/sdk/dc:a	Ljava/lang/String;
        //   1181: new 176	java/lang/StringBuilder
        //   1184: dup
        //   1185: invokespecial 177	java/lang/StringBuilder:<init>	()V
        //   1188: ldc -34
        //   1190: invokevirtual 183	java/lang/StringBuilder:append	(Ljava/lang/String;)Ljava/lang/StringBuilder;
        //   1193: aload 10
        //   1195: invokeinterface 93 1 0
        //   1200: checkcast 185	java/lang/String
        //   1203: invokevirtual 183	java/lang/StringBuilder:append	(Ljava/lang/String;)Ljava/lang/StringBuilder;
        //   1206: ldc -36
        //   1208: invokevirtual 183	java/lang/StringBuilder:append	(Ljava/lang/String;)Ljava/lang/StringBuilder;
        //   1211: aload 12
        //   1213: invokeinterface 93 1 0
        //   1218: checkcast 185	java/lang/String
        //   1221: invokevirtual 183	java/lang/StringBuilder:append	(Ljava/lang/String;)Ljava/lang/StringBuilder;
        //   1224: ldc -32
        //   1226: invokevirtual 183	java/lang/StringBuilder:append	(Ljava/lang/String;)Ljava/lang/StringBuilder;
        //   1229: aload 12
        //   1231: invokeinterface 102 1 0
        //   1236: checkcast 185	java/lang/String
        //   1239: invokevirtual 183	java/lang/StringBuilder:append	(Ljava/lang/String;)Ljava/lang/StringBuilder;
        //   1242: invokevirtual 193	java/lang/StringBuilder:toString	()Ljava/lang/String;
        //   1245: invokestatic 174	com/flurry/sdk/eo:a	(ILjava/lang/String;Ljava/lang/String;)V
        //   1248: aload 12
        //   1250: invokeinterface 93 1 0
        //   1255: ifnull +181 -> 1436
        //   1258: aload 12
        //   1260: invokeinterface 93 1 0
        //   1265: checkcast 185	java/lang/String
        //   1268: astore_1
        //   1269: aload 18
        //   1271: aload_1
        //   1272: invokevirtual 63	java/io/DataOutputStream:writeUTF	(Ljava/lang/String;)V
        //   1275: aload 12
        //   1277: invokeinterface 102 1 0
        //   1282: ifnull +160 -> 1442
        //   1285: aload 12
        //   1287: invokeinterface 102 1 0
        //   1292: checkcast 185	java/lang/String
        //   1295: astore_1
        //   1296: aload 18
        //   1298: aload_1
        //   1299: invokevirtual 63	java/io/DataOutputStream:writeUTF	(Ljava/lang/String;)V
        //   1302: goto -147 -> 1155
        //   1305: aload 9
        //   1307: invokeinterface 198 1 0
        //   1312: istore 17
        //   1314: aload 18
        //   1316: iload 17
        //   1318: invokevirtual 49	java/io/DataOutputStream:writeShort	(I)V
        //   1321: iconst_0
        //   1322: istore 16
        //   1324: iload 16
        //   1326: iload 17
        //   1328: if_icmpge +32 -> 1360
        //   1331: aload 18
        //   1333: aload 9
        //   1335: iload 16
        //   1337: invokeinterface 228 2 0
        //   1342: checkcast 230	com/flurry/sdk/dh
        //   1345: invokevirtual 232	com/flurry/sdk/dh:a	()[B
        //   1348: invokevirtual 112	java/io/DataOutputStream:write	([B)V
        //   1351: iload 16
        //   1353: iconst_1
        //   1354: iadd
        //   1355: istore 16
        //   1357: goto -33 -> 1324
        //   1360: aload 18
        //   1362: iconst_0
        //   1363: invokevirtual 49	java/io/DataOutputStream:writeShort	(I)V
        //   1366: aload 22
        //   1368: iconst_0
        //   1369: invokevirtual 235	java/security/DigestOutputStream:on	(Z)V
        //   1372: aload 18
        //   1374: aload 20
        //   1376: invokevirtual 236	com/flurry/sdk/ed:a	()[B
        //   1379: invokevirtual 112	java/io/DataOutputStream:write	([B)V
        //   1382: aload 18
        //   1384: invokevirtual 239	java/io/DataOutputStream:close	()V
        //   1387: aload 21
        //   1389: invokevirtual 242	java/io/ByteArrayOutputStream:toByteArray	()[B
        //   1392: astore_1
        //   1393: aload 18
        //   1395: invokestatic 124	com/flurry/sdk/fe:a	(Ljava/io/Closeable;)V
        //   1398: goto -1175 -> 223
        //   1401: astore_1
        //   1402: aconst_null
        //   1403: astore_2
        //   1404: goto -746 -> 658
        //   1407: astore 9
        //   1409: aload_1
        //   1410: astore_2
        //   1411: aload 9
        //   1413: astore_1
        //   1414: goto -756 -> 658
        //   1417: astore_2
        //   1418: aload 19
        //   1420: astore_1
        //   1421: goto -1215 -> 206
        //   1424: iconst_0
        //   1425: istore 16
        //   1427: goto -732 -> 695
        //   1430: iconst_0
        //   1431: istore 17
        //   1433: goto -500 -> 933
        //   1436: ldc -12
        //   1438: astore_1
        //   1439: goto -170 -> 1269
        //   1442: ldc -12
        //   1444: astore_1
        //   1445: goto -149 -> 1296
        // Local variable table:
        //   start	length	slot	name	signature
        //   0	1448	0	this	dc
        //   0	1448	1	paramString1	String
        //   0	1448	2	paramString2	String
        //   0	1448	3	paramBoolean1	boolean
        //   0	1448	4	paramBoolean2	boolean
        //   0	1448	5	paramLong1	long
        //   0	1448	7	paramLong2	long
        //   0	1448	9	paramList	java.util.List<dh>
        //   0	1448	10	paramMap	java.util.Map<dr, java.nio.ByteBuffer>
        //   0	1448	11	paramMap1	java.util.Map<String, java.util.List<String>>
        //   0	1448	12	paramMap2	java.util.Map<String, java.util.List<String>>
        //   0	1448	13	paramMap3	java.util.Map<String, java.util.Map<String, String>>
        //   0	1448	14	paramLong3	long
        //   412	1014	16	i	int
        //   931	501	17	j	int
        //   52	1342	18	localDataOutputStream	java.io.DataOutputStream
        //   10	1409	19	localObject	Object
        //   19	1356	20	localed	ed
        //   28	1360	21	localByteArrayOutputStream	java.io.ByteArrayOutputStream
        //   41	1326	22	localDigestOutputStream	java.security.DigestOutputStream
        // Exception table:
        //   from	to	target	type
        //   54	137	202	java/lang/Throwable
        //   137	199	202	java/lang/Throwable
        //   229	395	202	java/lang/Throwable
        //   400	414	202	java/lang/Throwable
        //   414	421	202	java/lang/Throwable
        //   426	448	202	java/lang/Throwable
        //   448	597	202	java/lang/Throwable
        //   597	651	202	java/lang/Throwable
        //   670	676	202	java/lang/Throwable
        //   681	695	202	java/lang/Throwable
        //   695	729	202	java/lang/Throwable
        //   734	756	202	java/lang/Throwable
        //   756	857	202	java/lang/Throwable
        //   857	911	202	java/lang/Throwable
        //   919	933	202	java/lang/Throwable
        //   933	967	202	java/lang/Throwable
        //   972	985	202	java/lang/Throwable
        //   985	1155	202	java/lang/Throwable
        //   1155	1269	202	java/lang/Throwable
        //   1269	1296	202	java/lang/Throwable
        //   1296	1302	202	java/lang/Throwable
        //   1305	1321	202	java/lang/Throwable
        //   1331	1351	202	java/lang/Throwable
        //   1360	1393	202	java/lang/Throwable
        //   54	137	654	finally
        //   137	199	654	finally
        //   229	395	654	finally
        //   400	414	654	finally
        //   414	421	654	finally
        //   426	448	654	finally
        //   448	597	654	finally
        //   597	651	654	finally
        //   670	676	654	finally
        //   681	695	654	finally
        //   695	729	654	finally
        //   734	756	654	finally
        //   756	857	654	finally
        //   857	911	654	finally
        //   919	933	654	finally
        //   933	967	654	finally
        //   972	985	654	finally
        //   985	1155	654	finally
        //   1155	1269	654	finally
        //   1269	1296	654	finally
        //   1296	1302	654	finally
        //   1305	1321	654	finally
        //   1331	1351	654	finally
        //   1360	1393	654	finally
        //   12	54	1401	finally
        //   206	217	1407	finally
        //   12	54	1417	java/lang/Throwable
    }

    public byte[] a() {
        return this.b;
    }
}


/* Location:              /Users/amaurremi/uw/stringoid stuff/static vs dynamic/fotor/com.everimaging.photoeffectstudio-85-dex2jar.jar!/com/flurry/sdk/dc.class
 * Java compiler version: 6 (50.0)
 * JD-Core Version:       0.7.1
 */