package com.flurry.android.monolithic.sdk.impl;

class p
  extends jf
{
  p(o paramo, String paramString) {}
  
  /* Error */
  public void a()
  {
    // Byte code:
    //   0: invokestatic 28	com/flurry/android/impl/ads/FlurryAdModule:getInstance	()Lcom/flurry/android/impl/ads/FlurryAdModule;
    //   3: invokevirtual 32	com/flurry/android/impl/ads/FlurryAdModule:I	()Z
    //   6: ifne +51 -> 57
    //   9: aload_0
    //   10: getfield 12	com/flurry/android/monolithic/sdk/impl/p:b	Lcom/flurry/android/monolithic/sdk/impl/o;
    //   13: invokestatic 38	com/flurry/android/monolithic/sdk/impl/o:l	(Lcom/flurry/android/monolithic/sdk/impl/o;)Landroid/app/ProgressDialog;
    //   16: ifnull +26 -> 42
    //   19: aload_0
    //   20: getfield 12	com/flurry/android/monolithic/sdk/impl/p:b	Lcom/flurry/android/monolithic/sdk/impl/o;
    //   23: invokestatic 38	com/flurry/android/monolithic/sdk/impl/o:l	(Lcom/flurry/android/monolithic/sdk/impl/o;)Landroid/app/ProgressDialog;
    //   26: invokevirtual 43	android/app/ProgressDialog:isShowing	()Z
    //   29: ifeq +13 -> 42
    //   32: aload_0
    //   33: getfield 12	com/flurry/android/monolithic/sdk/impl/p:b	Lcom/flurry/android/monolithic/sdk/impl/o;
    //   36: invokestatic 38	com/flurry/android/monolithic/sdk/impl/o:l	(Lcom/flurry/android/monolithic/sdk/impl/o;)Landroid/app/ProgressDialog;
    //   39: invokevirtual 46	android/app/ProgressDialog:dismiss	()V
    //   42: invokestatic 51	com/flurry/android/monolithic/sdk/impl/ia:a	()Lcom/flurry/android/monolithic/sdk/impl/ia;
    //   45: new 53	com/flurry/android/monolithic/sdk/impl/q
    //   48: dup
    //   49: aload_0
    //   50: invokespecial 56	com/flurry/android/monolithic/sdk/impl/q:<init>	(Lcom/flurry/android/monolithic/sdk/impl/p;)V
    //   53: invokevirtual 59	com/flurry/android/monolithic/sdk/impl/ia:a	(Ljava/lang/Runnable;)V
    //   56: return
    //   57: aconst_null
    //   58: astore_2
    //   59: new 61	org/apache/http/params/BasicHttpParams
    //   62: dup
    //   63: invokespecial 62	org/apache/http/params/BasicHttpParams:<init>	()V
    //   66: invokestatic 67	com/flurry/android/monolithic/sdk/impl/iz:a	(Lorg/apache/http/params/HttpParams;)Lorg/apache/http/client/HttpClient;
    //   69: astore_3
    //   70: aload_3
    //   71: astore_2
    //   72: aload_2
    //   73: astore_3
    //   74: aload_2
    //   75: new 69	org/apache/http/client/methods/HttpGet
    //   78: dup
    //   79: aload_0
    //   80: getfield 14	com/flurry/android/monolithic/sdk/impl/p:a	Ljava/lang/String;
    //   83: invokespecial 72	org/apache/http/client/methods/HttpGet:<init>	(Ljava/lang/String;)V
    //   86: invokeinterface 78 2 0
    //   91: astore 4
    //   93: aload_2
    //   94: astore_3
    //   95: aload 4
    //   97: invokeinterface 84 1 0
    //   102: invokeinterface 90 1 0
    //   107: istore_1
    //   108: aload_2
    //   109: astore_3
    //   110: aload 4
    //   112: invokeinterface 84 1 0
    //   117: invokeinterface 90 1 0
    //   122: sipush 200
    //   125: if_icmpne +71 -> 196
    //   128: aload_2
    //   129: astore_3
    //   130: aload_0
    //   131: getfield 12	com/flurry/android/monolithic/sdk/impl/p:b	Lcom/flurry/android/monolithic/sdk/impl/o;
    //   134: ldc 92
    //   136: invokestatic 98	java/util/Collections:emptyMap	()Ljava/util/Map;
    //   139: aload_0
    //   140: getfield 12	com/flurry/android/monolithic/sdk/impl/p:b	Lcom/flurry/android/monolithic/sdk/impl/o;
    //   143: getfield 102	com/flurry/android/monolithic/sdk/impl/o:d	Lcom/flurry/android/impl/ads/avro/protocol/v6/AdUnit;
    //   146: aload_0
    //   147: getfield 12	com/flurry/android/monolithic/sdk/impl/p:b	Lcom/flurry/android/monolithic/sdk/impl/o;
    //   150: getfield 106	com/flurry/android/monolithic/sdk/impl/o:c	Lcom/flurry/android/monolithic/sdk/impl/m;
    //   153: aload_0
    //   154: getfield 12	com/flurry/android/monolithic/sdk/impl/p:b	Lcom/flurry/android/monolithic/sdk/impl/o;
    //   157: getfield 109	com/flurry/android/monolithic/sdk/impl/o:e	I
    //   160: iconst_0
    //   161: invokevirtual 112	com/flurry/android/monolithic/sdk/impl/o:a	(Ljava/lang/String;Ljava/util/Map;Lcom/flurry/android/impl/ads/avro/protocol/v6/AdUnit;Lcom/flurry/android/monolithic/sdk/impl/m;II)V
    //   164: aload_2
    //   165: astore_3
    //   166: invokestatic 51	com/flurry/android/monolithic/sdk/impl/ia:a	()Lcom/flurry/android/monolithic/sdk/impl/ia;
    //   169: new 114	com/flurry/android/monolithic/sdk/impl/r
    //   172: dup
    //   173: aload_0
    //   174: invokespecial 115	com/flurry/android/monolithic/sdk/impl/r:<init>	(Lcom/flurry/android/monolithic/sdk/impl/p;)V
    //   177: invokevirtual 59	com/flurry/android/monolithic/sdk/impl/ia:a	(Ljava/lang/Runnable;)V
    //   180: aload_2
    //   181: ifnull -125 -> 56
    //   184: aload_2
    //   185: invokeinterface 119 1 0
    //   190: invokeinterface 124 1 0
    //   195: return
    //   196: aload_2
    //   197: astore_3
    //   198: iconst_4
    //   199: aload_0
    //   200: getfield 12	com/flurry/android/monolithic/sdk/impl/p:b	Lcom/flurry/android/monolithic/sdk/impl/o;
    //   203: invokestatic 127	com/flurry/android/monolithic/sdk/impl/o:a	(Lcom/flurry/android/monolithic/sdk/impl/o;)Ljava/lang/String;
    //   206: new 129	java/lang/StringBuilder
    //   209: dup
    //   210: invokespecial 130	java/lang/StringBuilder:<init>	()V
    //   213: ldc -124
    //   215: invokevirtual 136	java/lang/StringBuilder:append	(Ljava/lang/String;)Ljava/lang/StringBuilder;
    //   218: iload_1
    //   219: invokevirtual 139	java/lang/StringBuilder:append	(I)Ljava/lang/StringBuilder;
    //   222: invokevirtual 143	java/lang/StringBuilder:toString	()Ljava/lang/String;
    //   225: invokestatic 148	com/flurry/android/monolithic/sdk/impl/ja:a	(ILjava/lang/String;Ljava/lang/String;)V
    //   228: aload_2
    //   229: ifnull +14 -> 243
    //   232: aload_2
    //   233: invokeinterface 119 1 0
    //   238: invokeinterface 124 1 0
    //   243: aload_0
    //   244: getfield 12	com/flurry/android/monolithic/sdk/impl/p:b	Lcom/flurry/android/monolithic/sdk/impl/o;
    //   247: invokestatic 38	com/flurry/android/monolithic/sdk/impl/o:l	(Lcom/flurry/android/monolithic/sdk/impl/o;)Landroid/app/ProgressDialog;
    //   250: ifnull +26 -> 276
    //   253: aload_0
    //   254: getfield 12	com/flurry/android/monolithic/sdk/impl/p:b	Lcom/flurry/android/monolithic/sdk/impl/o;
    //   257: invokestatic 38	com/flurry/android/monolithic/sdk/impl/o:l	(Lcom/flurry/android/monolithic/sdk/impl/o;)Landroid/app/ProgressDialog;
    //   260: invokevirtual 43	android/app/ProgressDialog:isShowing	()Z
    //   263: ifeq +13 -> 276
    //   266: aload_0
    //   267: getfield 12	com/flurry/android/monolithic/sdk/impl/p:b	Lcom/flurry/android/monolithic/sdk/impl/o;
    //   270: invokestatic 38	com/flurry/android/monolithic/sdk/impl/o:l	(Lcom/flurry/android/monolithic/sdk/impl/o;)Landroid/app/ProgressDialog;
    //   273: invokevirtual 46	android/app/ProgressDialog:dismiss	()V
    //   276: invokestatic 51	com/flurry/android/monolithic/sdk/impl/ia:a	()Lcom/flurry/android/monolithic/sdk/impl/ia;
    //   279: new 150	com/flurry/android/monolithic/sdk/impl/s
    //   282: dup
    //   283: aload_0
    //   284: invokespecial 151	com/flurry/android/monolithic/sdk/impl/s:<init>	(Lcom/flurry/android/monolithic/sdk/impl/p;)V
    //   287: invokevirtual 59	com/flurry/android/monolithic/sdk/impl/ia:a	(Ljava/lang/Runnable;)V
    //   290: return
    //   291: astore_3
    //   292: iconst_4
    //   293: aload_0
    //   294: getfield 12	com/flurry/android/monolithic/sdk/impl/p:b	Lcom/flurry/android/monolithic/sdk/impl/o;
    //   297: invokestatic 127	com/flurry/android/monolithic/sdk/impl/o:a	(Lcom/flurry/android/monolithic/sdk/impl/o;)Ljava/lang/String;
    //   300: ldc -103
    //   302: invokestatic 148	com/flurry/android/monolithic/sdk/impl/ja:a	(ILjava/lang/String;Ljava/lang/String;)V
    //   305: aload_2
    //   306: ifnull -63 -> 243
    //   309: aload_2
    //   310: invokeinterface 119 1 0
    //   315: invokeinterface 124 1 0
    //   320: goto -77 -> 243
    //   323: astore_2
    //   324: aconst_null
    //   325: astore_2
    //   326: aload_2
    //   327: astore_3
    //   328: iconst_4
    //   329: aload_0
    //   330: getfield 12	com/flurry/android/monolithic/sdk/impl/p:b	Lcom/flurry/android/monolithic/sdk/impl/o;
    //   333: invokestatic 127	com/flurry/android/monolithic/sdk/impl/o:a	(Lcom/flurry/android/monolithic/sdk/impl/o;)Ljava/lang/String;
    //   336: ldc -101
    //   338: invokestatic 148	com/flurry/android/monolithic/sdk/impl/ja:a	(ILjava/lang/String;Ljava/lang/String;)V
    //   341: aload_2
    //   342: ifnull -99 -> 243
    //   345: aload_2
    //   346: invokeinterface 119 1 0
    //   351: invokeinterface 124 1 0
    //   356: goto -113 -> 243
    //   359: astore_2
    //   360: aconst_null
    //   361: astore_3
    //   362: aload_3
    //   363: ifnull +14 -> 377
    //   366: aload_3
    //   367: invokeinterface 119 1 0
    //   372: invokeinterface 124 1 0
    //   377: aload_2
    //   378: athrow
    //   379: astore_2
    //   380: goto -18 -> 362
    //   383: astore 4
    //   385: aload_2
    //   386: astore_3
    //   387: aload 4
    //   389: astore_2
    //   390: goto -28 -> 362
    //   393: astore_3
    //   394: goto -68 -> 326
    //   397: astore_3
    //   398: goto -106 -> 292
    // Local variable table:
    //   start	length	slot	name	signature
    //   0	401	0	this	p
    //   107	112	1	i	int
    //   58	252	2	localObject1	Object
    //   323	1	2	localIOException1	java.io.IOException
    //   325	21	2	localObject2	Object
    //   359	19	2	localObject3	Object
    //   379	7	2	localObject4	Object
    //   389	1	2	localObject5	Object
    //   69	129	3	localObject6	Object
    //   291	1	3	localClientProtocolException1	org.apache.http.client.ClientProtocolException
    //   327	60	3	localObject7	Object
    //   393	1	3	localIOException2	java.io.IOException
    //   397	1	3	localClientProtocolException2	org.apache.http.client.ClientProtocolException
    //   91	20	4	localHttpResponse	org.apache.http.HttpResponse
    //   383	5	4	localObject8	Object
    // Exception table:
    //   from	to	target	type
    //   59	70	291	org/apache/http/client/ClientProtocolException
    //   59	70	323	java/io/IOException
    //   59	70	359	finally
    //   74	93	379	finally
    //   95	108	379	finally
    //   110	128	379	finally
    //   130	164	379	finally
    //   166	180	379	finally
    //   198	228	379	finally
    //   328	341	379	finally
    //   292	305	383	finally
    //   74	93	393	java/io/IOException
    //   95	108	393	java/io/IOException
    //   110	128	393	java/io/IOException
    //   130	164	393	java/io/IOException
    //   166	180	393	java/io/IOException
    //   198	228	393	java/io/IOException
    //   74	93	397	org/apache/http/client/ClientProtocolException
    //   95	108	397	org/apache/http/client/ClientProtocolException
    //   110	128	397	org/apache/http/client/ClientProtocolException
    //   130	164	397	org/apache/http/client/ClientProtocolException
    //   166	180	397	org/apache/http/client/ClientProtocolException
    //   198	228	397	org/apache/http/client/ClientProtocolException
  }
}


/* Location:              /Users/amaurremi/uw/stringoid/static-dynamic-comparison/apps/logo quiz/logo.quiz.game.category-48-dex2jar.jar!/com/flurry/android/monolithic/sdk/impl/p.class
 * Java compiler version: 6 (50.0)
 * JD-Core Version:       0.7.1
 */