package com.inmobi.commons.analytics.iat.impl.net;

final class AdTrackerNetworkInterface$b
        implements Runnable {
    AdTrackerNetworkInterface$b(String paramString) {
    }

    /* Error */
    public void run() {
        // Byte code:
        //   0: invokestatic 25	com/inmobi/commons/analytics/iat/impl/net/AdTrackerNetworkInterface:c	()Ljava/util/concurrent/atomic/AtomicBoolean;
        //   3: invokevirtual 31	java/util/concurrent/atomic/AtomicBoolean:get	()Z
        //   6: ifne +86 -> 92
        //   9: invokestatic 35	com/inmobi/commons/analytics/iat/impl/net/AdTrackerNetworkInterface:d	()Lcom/inmobi/commons/analytics/iat/impl/GoalList;
        //   12: invokevirtual 40	com/inmobi/commons/analytics/iat/impl/GoalList:saveGoals	()V
        //   15: invokestatic 25	com/inmobi/commons/analytics/iat/impl/net/AdTrackerNetworkInterface:c	()Ljava/util/concurrent/atomic/AtomicBoolean;
        //   18: iconst_1
        //   19: invokevirtual 44	java/util/concurrent/atomic/AtomicBoolean:set	(Z)V
        //   22: invokestatic 35	com/inmobi/commons/analytics/iat/impl/net/AdTrackerNetworkInterface:d	()Lcom/inmobi/commons/analytics/iat/impl/GoalList;
        //   25: ifnull +12 -> 37
        //   28: invokestatic 35	com/inmobi/commons/analytics/iat/impl/net/AdTrackerNetworkInterface:d	()Lcom/inmobi/commons/analytics/iat/impl/GoalList;
        //   31: invokevirtual 47	com/inmobi/commons/analytics/iat/impl/GoalList:isEmpty	()Z
        //   34: ifeq +14 -> 48
        //   37: ldc 49
        //   39: ldc 51
        //   41: invokestatic 57	com/inmobi/commons/internal/Log:internal	(Ljava/lang/String;Ljava/lang/String;)V
        //   44: invokestatic 60	com/inmobi/commons/analytics/iat/impl/net/AdTrackerNetworkInterface:deinit	()V
        //   47: return
        //   48: invokestatic 35	com/inmobi/commons/analytics/iat/impl/net/AdTrackerNetworkInterface:d	()Lcom/inmobi/commons/analytics/iat/impl/GoalList;
        //   51: invokevirtual 47	com/inmobi/commons/analytics/iat/impl/GoalList:isEmpty	()Z
        //   54: ifne +28 -> 82
        //   57: aload_0
        //   58: getfield 12	com/inmobi/commons/analytics/iat/impl/net/AdTrackerNetworkInterface$b:a	Ljava/lang/String;
        //   61: invokestatic 62	com/inmobi/commons/analytics/iat/impl/net/AdTrackerNetworkInterface:a	(Ljava/lang/String;)V
        //   64: goto -16 -> 48
        //   67: astore_1
        //   68: invokestatic 60	com/inmobi/commons/analytics/iat/impl/net/AdTrackerNetworkInterface:deinit	()V
        //   71: return
        //   72: astore_1
        //   73: ldc 49
        //   75: ldc 64
        //   77: aload_1
        //   78: invokestatic 67	com/inmobi/commons/internal/Log:internal	(Ljava/lang/String;Ljava/lang/String;Ljava/lang/Throwable;)V
        //   81: return
        //   82: invokestatic 70	com/inmobi/commons/analytics/iat/impl/net/AdTrackerNetworkInterface:e	()Ljava/util/concurrent/atomic/AtomicBoolean;
        //   85: iconst_0
        //   86: invokevirtual 44	java/util/concurrent/atomic/AtomicBoolean:set	(Z)V
        //   89: goto -89 -> 0
        //   92: invokestatic 60	com/inmobi/commons/analytics/iat/impl/net/AdTrackerNetworkInterface:deinit	()V
        //   95: return
        // Local variable table:
        //   start	length	slot	name	signature
        //   0	96	0	this	b
        //   67	1	1	localException1	Exception
        //   72	6	1	localException2	Exception
        // Exception table:
        //   from	to	target	type
        //   48	64	67	java/lang/Exception
        //   0	37	72	java/lang/Exception
        //   37	47	72	java/lang/Exception
        //   68	71	72	java/lang/Exception
        //   82	89	72	java/lang/Exception
        //   92	95	72	java/lang/Exception
    }
}


/* Location:              /Users/amaurremi/uw/stringoid stuff/static vs dynamic/ifunny/mobi.ifunny-2447-dex2jar.jar!/com/inmobi/commons/analytics/iat/impl/net/AdTrackerNetworkInterface$b.class
 * Java compiler version: 6 (50.0)
 * JD-Core Version:       0.7.1
 */