package com.vungle.sdk;

import java.io.IOException;
import java.net.HttpURLConnection;
import java.net.URL;

final class at
{
  /* Error */
  public static String a(String paramString1, String paramString2)
  {
    // Byte code:
    //   0: aconst_null
    //   1: astore 6
    //   3: aconst_null
    //   4: astore 5
    //   6: aconst_null
    //   7: astore 4
    //   9: iconst_1
    //   10: istore_2
    //   11: getstatic 16	com/vungle/sdk/e:t	Ljava/lang/String;
    //   14: astore_3
    //   15: getstatic 16	com/vungle/sdk/e:t	Ljava/lang/String;
    //   18: astore_3
    //   19: new 18	java/net/URL
    //   22: dup
    //   23: aload_0
    //   24: invokespecial 22	java/net/URL:<init>	(Ljava/lang/String;)V
    //   27: invokestatic 25	com/vungle/sdk/at:a	(Ljava/net/URL;)Ljava/net/HttpURLConnection;
    //   30: astore_0
    //   31: aload_0
    //   32: astore_3
    //   33: aload_0
    //   34: getstatic 31	com/vungle/sdk/a/a/g$a:c	Lcom/vungle/sdk/a/a/g$a;
    //   37: invokevirtual 35	com/vungle/sdk/a/a/g$a:toString	()Ljava/lang/String;
    //   40: invokevirtual 40	java/net/HttpURLConnection:setRequestMethod	(Ljava/lang/String;)V
    //   43: aload_1
    //   44: ifnull +269 -> 313
    //   47: aload_0
    //   48: astore_3
    //   49: aload_1
    //   50: invokevirtual 46	java/lang/String:length	()I
    //   53: ifle +260 -> 313
    //   56: iload_2
    //   57: ifeq +13 -> 70
    //   60: aload_0
    //   61: astore_3
    //   62: aload_0
    //   63: ldc 48
    //   65: ldc 50
    //   67: invokevirtual 54	java/net/HttpURLConnection:setRequestProperty	(Ljava/lang/String;Ljava/lang/String;)V
    //   70: aload_0
    //   71: astore_3
    //   72: aload_0
    //   73: ldc 56
    //   75: ldc 58
    //   77: invokevirtual 54	java/net/HttpURLConnection:setRequestProperty	(Ljava/lang/String;Ljava/lang/String;)V
    //   80: aload_0
    //   81: astore_3
    //   82: aload_0
    //   83: ldc 60
    //   85: invokestatic 64	com/vungle/sdk/ba:c	()Ljava/lang/String;
    //   88: invokevirtual 54	java/net/HttpURLConnection:setRequestProperty	(Ljava/lang/String;Ljava/lang/String;)V
    //   91: aload_0
    //   92: astore_3
    //   93: aload_0
    //   94: ldc 66
    //   96: invokestatic 69	com/vungle/sdk/ba:b	()Ljava/lang/String;
    //   99: invokevirtual 54	java/net/HttpURLConnection:setRequestProperty	(Ljava/lang/String;Ljava/lang/String;)V
    //   102: aload_0
    //   103: astore_3
    //   104: aload_0
    //   105: ldc 71
    //   107: invokestatic 77	com/vungle/sdk/ak:e	()Landroid/content/Context;
    //   110: invokevirtual 82	android/content/Context:getPackageName	()Ljava/lang/String;
    //   113: invokevirtual 54	java/net/HttpURLConnection:setRequestProperty	(Ljava/lang/String;Ljava/lang/String;)V
    //   116: aload_0
    //   117: astore_3
    //   118: invokestatic 77	com/vungle/sdk/ak:e	()Landroid/content/Context;
    //   121: invokevirtual 82	android/content/Context:getPackageName	()Ljava/lang/String;
    //   124: pop
    //   125: iload_2
    //   126: ifeq +23 -> 149
    //   129: aload_0
    //   130: astore_3
    //   131: aload_0
    //   132: iconst_1
    //   133: invokevirtual 86	java/net/HttpURLConnection:setDoOutput	(Z)V
    //   136: aload_0
    //   137: astore_3
    //   138: aload_0
    //   139: invokevirtual 90	java/net/HttpURLConnection:getOutputStream	()Ljava/io/OutputStream;
    //   142: aload_1
    //   143: invokevirtual 94	java/lang/String:getBytes	()[B
    //   146: invokevirtual 100	java/io/OutputStream:write	([B)V
    //   149: aload_0
    //   150: astore_3
    //   151: getstatic 16	com/vungle/sdk/e:t	Ljava/lang/String;
    //   154: astore_1
    //   155: aload_0
    //   156: astore_3
    //   157: new 102	java/lang/StringBuilder
    //   160: dup
    //   161: ldc 104
    //   163: invokespecial 105	java/lang/StringBuilder:<init>	(Ljava/lang/String;)V
    //   166: aload_0
    //   167: invokevirtual 108	java/net/HttpURLConnection:getResponseCode	()I
    //   170: invokevirtual 112	java/lang/StringBuilder:append	(I)Ljava/lang/StringBuilder;
    //   173: pop
    //   174: aload 6
    //   176: astore_1
    //   177: aload_0
    //   178: astore_3
    //   179: aload_0
    //   180: invokevirtual 108	java/net/HttpURLConnection:getResponseCode	()I
    //   183: sipush 200
    //   186: if_icmpne +168 -> 354
    //   189: aload_0
    //   190: astore_3
    //   191: aload_0
    //   192: invokevirtual 116	java/net/HttpURLConnection:getContent	()Ljava/lang/Object;
    //   195: checkcast 118	java/io/InputStream
    //   198: astore 4
    //   200: aload_0
    //   201: astore_3
    //   202: new 102	java/lang/StringBuilder
    //   205: dup
    //   206: invokespecial 121	java/lang/StringBuilder:<init>	()V
    //   209: astore_1
    //   210: aload_0
    //   211: astore_3
    //   212: sipush 1024
    //   215: newarray <illegal type>
    //   217: astore 5
    //   219: new 123	java/io/BufferedReader
    //   222: dup
    //   223: new 125	java/io/InputStreamReader
    //   226: dup
    //   227: aload 4
    //   229: ldc 127
    //   231: invokespecial 130	java/io/InputStreamReader:<init>	(Ljava/io/InputStream;Ljava/lang/String;)V
    //   234: invokespecial 133	java/io/BufferedReader:<init>	(Ljava/io/Reader;)V
    //   237: astore_3
    //   238: aload_3
    //   239: aload 5
    //   241: invokevirtual 137	java/io/BufferedReader:read	([C)I
    //   244: istore_2
    //   245: iload_2
    //   246: iconst_m1
    //   247: if_icmpeq +71 -> 318
    //   250: aload_1
    //   251: aload 5
    //   253: iconst_0
    //   254: iload_2
    //   255: invokevirtual 140	java/lang/StringBuilder:append	([CII)Ljava/lang/StringBuilder;
    //   258: pop
    //   259: goto -21 -> 238
    //   262: astore 5
    //   264: aload 4
    //   266: ifnull +10 -> 276
    //   269: aload_0
    //   270: astore_3
    //   271: aload 4
    //   273: invokevirtual 143	java/io/InputStream:close	()V
    //   276: aload_0
    //   277: astore_3
    //   278: aload 5
    //   280: athrow
    //   281: astore_3
    //   282: getstatic 146	com/vungle/sdk/e:u	Ljava/lang/String;
    //   285: aload_3
    //   286: invokevirtual 149	java/net/MalformedURLException:getMessage	()Ljava/lang/String;
    //   289: aload_3
    //   290: invokestatic 154	com/vungle/sdk/av:a	(Ljava/lang/String;Ljava/lang/String;Ljava/lang/Throwable;)V
    //   293: aload_1
    //   294: astore_3
    //   295: aload_0
    //   296: ifnull +9 -> 305
    //   299: aload_0
    //   300: invokevirtual 157	java/net/HttpURLConnection:disconnect	()V
    //   303: aload_1
    //   304: astore_3
    //   305: aload_3
    //   306: ifnonnull +113 -> 419
    //   309: getstatic 160	com/vungle/sdk/e:B	Ljava/lang/String;
    //   312: areturn
    //   313: iconst_0
    //   314: istore_2
    //   315: goto -259 -> 56
    //   318: getstatic 16	com/vungle/sdk/e:t	Ljava/lang/String;
    //   321: astore_3
    //   322: new 102	java/lang/StringBuilder
    //   325: dup
    //   326: ldc -94
    //   328: invokespecial 105	java/lang/StringBuilder:<init>	(Ljava/lang/String;)V
    //   331: aload_1
    //   332: invokevirtual 163	java/lang/StringBuilder:toString	()Ljava/lang/String;
    //   335: invokevirtual 166	java/lang/String:trim	()Ljava/lang/String;
    //   338: invokevirtual 169	java/lang/StringBuilder:append	(Ljava/lang/String;)Ljava/lang/StringBuilder;
    //   341: pop
    //   342: aload 4
    //   344: ifnull +123 -> 467
    //   347: aload_0
    //   348: astore_3
    //   349: aload 4
    //   351: invokevirtual 143	java/io/InputStream:close	()V
    //   354: aload_1
    //   355: astore_3
    //   356: aload_0
    //   357: ifnull +107 -> 464
    //   360: aload_0
    //   361: invokevirtual 157	java/net/HttpURLConnection:disconnect	()V
    //   364: aload_1
    //   365: astore_3
    //   366: goto -61 -> 305
    //   369: astore 4
    //   371: aconst_null
    //   372: astore_0
    //   373: aload 5
    //   375: astore_1
    //   376: aload_0
    //   377: astore_3
    //   378: getstatic 146	com/vungle/sdk/e:u	Ljava/lang/String;
    //   381: aload 4
    //   383: invokevirtual 170	java/io/IOException:getMessage	()Ljava/lang/String;
    //   386: aload 4
    //   388: invokestatic 154	com/vungle/sdk/av:a	(Ljava/lang/String;Ljava/lang/String;Ljava/lang/Throwable;)V
    //   391: aload_1
    //   392: astore_3
    //   393: aload_0
    //   394: ifnull +70 -> 464
    //   397: aload_0
    //   398: invokevirtual 157	java/net/HttpURLConnection:disconnect	()V
    //   401: aload_1
    //   402: astore_3
    //   403: goto -98 -> 305
    //   406: astore_0
    //   407: aconst_null
    //   408: astore_3
    //   409: aload_3
    //   410: ifnull +7 -> 417
    //   413: aload_3
    //   414: invokevirtual 157	java/net/HttpURLConnection:disconnect	()V
    //   417: aload_0
    //   418: athrow
    //   419: aload_3
    //   420: invokevirtual 163	java/lang/StringBuilder:toString	()Ljava/lang/String;
    //   423: areturn
    //   424: astore_0
    //   425: goto -16 -> 409
    //   428: astore_1
    //   429: aload_0
    //   430: astore_3
    //   431: aload_1
    //   432: astore_0
    //   433: goto -24 -> 409
    //   436: astore 4
    //   438: aload 5
    //   440: astore_1
    //   441: goto -65 -> 376
    //   444: astore 4
    //   446: goto -70 -> 376
    //   449: astore_3
    //   450: aconst_null
    //   451: astore_1
    //   452: aload 4
    //   454: astore_0
    //   455: goto -173 -> 282
    //   458: astore_3
    //   459: aconst_null
    //   460: astore_1
    //   461: goto -179 -> 282
    //   464: goto -159 -> 305
    //   467: goto -113 -> 354
    // Local variable table:
    //   start	length	slot	name	signature
    //   0	470	0	paramString1	String
    //   0	470	1	paramString2	String
    //   10	305	2	i	int
    //   14	264	3	localObject1	Object
    //   281	9	3	localMalformedURLException1	java.net.MalformedURLException
    //   294	137	3	str	String
    //   449	1	3	localMalformedURLException2	java.net.MalformedURLException
    //   458	1	3	localMalformedURLException3	java.net.MalformedURLException
    //   7	343	4	localInputStream	java.io.InputStream
    //   369	18	4	localIOException1	IOException
    //   436	1	4	localIOException2	IOException
    //   444	9	4	localIOException3	IOException
    //   4	248	5	arrayOfChar	char[]
    //   262	177	5	localObject2	Object
    //   1	174	6	localObject3	Object
    // Exception table:
    //   from	to	target	type
    //   219	238	262	finally
    //   238	245	262	finally
    //   250	259	262	finally
    //   318	342	262	finally
    //   212	219	281	java/net/MalformedURLException
    //   271	276	281	java/net/MalformedURLException
    //   278	281	281	java/net/MalformedURLException
    //   349	354	281	java/net/MalformedURLException
    //   11	31	369	java/io/IOException
    //   11	31	406	finally
    //   33	43	424	finally
    //   49	56	424	finally
    //   62	70	424	finally
    //   72	80	424	finally
    //   82	91	424	finally
    //   93	102	424	finally
    //   104	116	424	finally
    //   118	125	424	finally
    //   131	136	424	finally
    //   138	149	424	finally
    //   151	155	424	finally
    //   157	174	424	finally
    //   179	189	424	finally
    //   191	200	424	finally
    //   202	210	424	finally
    //   212	219	424	finally
    //   271	276	424	finally
    //   278	281	424	finally
    //   349	354	424	finally
    //   378	391	424	finally
    //   282	293	428	finally
    //   33	43	436	java/io/IOException
    //   49	56	436	java/io/IOException
    //   62	70	436	java/io/IOException
    //   72	80	436	java/io/IOException
    //   82	91	436	java/io/IOException
    //   93	102	436	java/io/IOException
    //   104	116	436	java/io/IOException
    //   118	125	436	java/io/IOException
    //   131	136	436	java/io/IOException
    //   138	149	436	java/io/IOException
    //   151	155	436	java/io/IOException
    //   157	174	436	java/io/IOException
    //   179	189	436	java/io/IOException
    //   191	200	436	java/io/IOException
    //   202	210	436	java/io/IOException
    //   212	219	444	java/io/IOException
    //   271	276	444	java/io/IOException
    //   278	281	444	java/io/IOException
    //   349	354	444	java/io/IOException
    //   11	31	449	java/net/MalformedURLException
    //   33	43	458	java/net/MalformedURLException
    //   49	56	458	java/net/MalformedURLException
    //   62	70	458	java/net/MalformedURLException
    //   72	80	458	java/net/MalformedURLException
    //   82	91	458	java/net/MalformedURLException
    //   93	102	458	java/net/MalformedURLException
    //   104	116	458	java/net/MalformedURLException
    //   118	125	458	java/net/MalformedURLException
    //   131	136	458	java/net/MalformedURLException
    //   138	149	458	java/net/MalformedURLException
    //   151	155	458	java/net/MalformedURLException
    //   157	174	458	java/net/MalformedURLException
    //   179	189	458	java/net/MalformedURLException
    //   191	200	458	java/net/MalformedURLException
    //   202	210	458	java/net/MalformedURLException
  }
  
  private static HttpURLConnection a(URL paramURL)
    throws IOException
  {
    paramURL = (HttpURLConnection)paramURL.openConnection();
    paramURL.setConnectTimeout(30000);
    paramURL.setReadTimeout(30000);
    paramURL.setUseCaches(false);
    return paramURL;
  }
  
  /* Error */
  public static java.util.ArrayList<String> a(String paramString)
  {
    // Byte code:
    //   0: new 189	java/util/ArrayList
    //   3: dup
    //   4: invokespecial 190	java/util/ArrayList:<init>	()V
    //   7: astore 5
    //   9: aconst_null
    //   10: astore 4
    //   12: aconst_null
    //   13: astore_2
    //   14: aconst_null
    //   15: astore_3
    //   16: new 18	java/net/URL
    //   19: dup
    //   20: aload_0
    //   21: invokespecial 22	java/net/URL:<init>	(Ljava/lang/String;)V
    //   24: invokestatic 25	com/vungle/sdk/at:a	(Ljava/net/URL;)Ljava/net/HttpURLConnection;
    //   27: astore_0
    //   28: aload_0
    //   29: astore_3
    //   30: aload_0
    //   31: astore 4
    //   33: aload_0
    //   34: astore_2
    //   35: aload_0
    //   36: getstatic 192	com/vungle/sdk/a/a/g$a:a	Lcom/vungle/sdk/a/a/g$a;
    //   39: invokevirtual 35	com/vungle/sdk/a/a/g$a:toString	()Ljava/lang/String;
    //   42: invokevirtual 40	java/net/HttpURLConnection:setRequestMethod	(Ljava/lang/String;)V
    //   45: aload_0
    //   46: astore_3
    //   47: aload_0
    //   48: astore 4
    //   50: aload_0
    //   51: astore_2
    //   52: aload_0
    //   53: invokevirtual 195	java/net/HttpURLConnection:connect	()V
    //   56: aload_0
    //   57: astore_3
    //   58: aload_0
    //   59: astore 4
    //   61: aload_0
    //   62: astore_2
    //   63: getstatic 16	com/vungle/sdk/e:t	Ljava/lang/String;
    //   66: astore 6
    //   68: aload_0
    //   69: astore_3
    //   70: aload_0
    //   71: astore 4
    //   73: aload_0
    //   74: astore_2
    //   75: new 102	java/lang/StringBuilder
    //   78: dup
    //   79: ldc -59
    //   81: invokespecial 105	java/lang/StringBuilder:<init>	(Ljava/lang/String;)V
    //   84: aload_0
    //   85: invokevirtual 108	java/net/HttpURLConnection:getResponseCode	()I
    //   88: invokevirtual 112	java/lang/StringBuilder:append	(I)Ljava/lang/StringBuilder;
    //   91: pop
    //   92: aload_0
    //   93: astore_3
    //   94: aload_0
    //   95: astore 4
    //   97: aload_0
    //   98: astore_2
    //   99: aload 5
    //   101: iconst_0
    //   102: aload_0
    //   103: invokevirtual 200	java/net/HttpURLConnection:getResponseMessage	()Ljava/lang/String;
    //   106: invokevirtual 204	java/util/ArrayList:add	(ILjava/lang/Object;)V
    //   109: aload_0
    //   110: astore_3
    //   111: aload_0
    //   112: astore 4
    //   114: aload_0
    //   115: astore_2
    //   116: aload_0
    //   117: invokevirtual 108	java/net/HttpURLConnection:getResponseCode	()I
    //   120: sipush 200
    //   123: if_icmpne +194 -> 317
    //   126: aload_0
    //   127: astore_3
    //   128: aload_0
    //   129: astore 4
    //   131: aload_0
    //   132: astore_2
    //   133: aload_0
    //   134: invokevirtual 208	java/net/HttpURLConnection:getInputStream	()Ljava/io/InputStream;
    //   137: astore 6
    //   139: aload_0
    //   140: astore_3
    //   141: aload_0
    //   142: astore 4
    //   144: aload_0
    //   145: astore_2
    //   146: new 102	java/lang/StringBuilder
    //   149: dup
    //   150: invokespecial 121	java/lang/StringBuilder:<init>	()V
    //   153: astore 7
    //   155: aload_0
    //   156: astore_3
    //   157: aload_0
    //   158: astore 4
    //   160: aload_0
    //   161: astore_2
    //   162: sipush 1024
    //   165: newarray <illegal type>
    //   167: astore 8
    //   169: new 123	java/io/BufferedReader
    //   172: dup
    //   173: new 125	java/io/InputStreamReader
    //   176: dup
    //   177: aload 6
    //   179: ldc 127
    //   181: invokespecial 130	java/io/InputStreamReader:<init>	(Ljava/io/InputStream;Ljava/lang/String;)V
    //   184: invokespecial 133	java/io/BufferedReader:<init>	(Ljava/io/Reader;)V
    //   187: astore_2
    //   188: aload_2
    //   189: aload 8
    //   191: invokevirtual 137	java/io/BufferedReader:read	([C)I
    //   194: istore_1
    //   195: iload_1
    //   196: iconst_m1
    //   197: if_icmpeq +70 -> 267
    //   200: aload 7
    //   202: aload 8
    //   204: iconst_0
    //   205: iload_1
    //   206: invokevirtual 140	java/lang/StringBuilder:append	([CII)Ljava/lang/StringBuilder;
    //   209: pop
    //   210: goto -22 -> 188
    //   213: astore 7
    //   215: aload 6
    //   217: ifnull +15 -> 232
    //   220: aload_0
    //   221: astore_3
    //   222: aload_0
    //   223: astore 4
    //   225: aload_0
    //   226: astore_2
    //   227: aload 6
    //   229: invokevirtual 143	java/io/InputStream:close	()V
    //   232: aload_0
    //   233: astore_3
    //   234: aload_0
    //   235: astore 4
    //   237: aload_0
    //   238: astore_2
    //   239: aload 7
    //   241: athrow
    //   242: astore_0
    //   243: aload_3
    //   244: astore_2
    //   245: getstatic 146	com/vungle/sdk/e:u	Ljava/lang/String;
    //   248: aload_0
    //   249: invokevirtual 149	java/net/MalformedURLException:getMessage	()Ljava/lang/String;
    //   252: aload_0
    //   253: invokestatic 154	com/vungle/sdk/av:a	(Ljava/lang/String;Ljava/lang/String;Ljava/lang/Throwable;)V
    //   256: aload_3
    //   257: ifnull +7 -> 264
    //   260: aload_3
    //   261: invokevirtual 157	java/net/HttpURLConnection:disconnect	()V
    //   264: aload 5
    //   266: areturn
    //   267: aload 5
    //   269: iconst_1
    //   270: aload 7
    //   272: invokevirtual 163	java/lang/StringBuilder:toString	()Ljava/lang/String;
    //   275: invokevirtual 204	java/util/ArrayList:add	(ILjava/lang/Object;)V
    //   278: getstatic 16	com/vungle/sdk/e:t	Ljava/lang/String;
    //   281: astore_2
    //   282: new 102	java/lang/StringBuilder
    //   285: dup
    //   286: ldc -46
    //   288: invokespecial 105	java/lang/StringBuilder:<init>	(Ljava/lang/String;)V
    //   291: aload 7
    //   293: invokevirtual 163	java/lang/StringBuilder:toString	()Ljava/lang/String;
    //   296: invokevirtual 169	java/lang/StringBuilder:append	(Ljava/lang/String;)Ljava/lang/StringBuilder;
    //   299: pop
    //   300: aload 6
    //   302: ifnull +15 -> 317
    //   305: aload_0
    //   306: astore_3
    //   307: aload_0
    //   308: astore 4
    //   310: aload_0
    //   311: astore_2
    //   312: aload 6
    //   314: invokevirtual 143	java/io/InputStream:close	()V
    //   317: aload_0
    //   318: ifnull -54 -> 264
    //   321: aload_0
    //   322: invokevirtual 157	java/net/HttpURLConnection:disconnect	()V
    //   325: aload 5
    //   327: areturn
    //   328: astore_0
    //   329: aload 4
    //   331: astore_2
    //   332: getstatic 146	com/vungle/sdk/e:u	Ljava/lang/String;
    //   335: aload_0
    //   336: invokevirtual 170	java/io/IOException:getMessage	()Ljava/lang/String;
    //   339: aload_0
    //   340: invokestatic 154	com/vungle/sdk/av:a	(Ljava/lang/String;Ljava/lang/String;Ljava/lang/Throwable;)V
    //   343: aload 4
    //   345: ifnull -81 -> 264
    //   348: aload 4
    //   350: invokevirtual 157	java/net/HttpURLConnection:disconnect	()V
    //   353: aload 5
    //   355: areturn
    //   356: astore_0
    //   357: aload_2
    //   358: ifnull +7 -> 365
    //   361: aload_2
    //   362: invokevirtual 157	java/net/HttpURLConnection:disconnect	()V
    //   365: aload_0
    //   366: athrow
    // Local variable table:
    //   start	length	slot	name	signature
    //   0	367	0	paramString	String
    //   194	12	1	i	int
    //   13	349	2	localObject1	Object
    //   15	292	3	str1	String
    //   10	339	4	str2	String
    //   7	347	5	localArrayList	java.util.ArrayList
    //   66	247	6	localObject2	Object
    //   153	48	7	localStringBuilder	StringBuilder
    //   213	79	7	localObject3	Object
    //   167	36	8	arrayOfChar	char[]
    // Exception table:
    //   from	to	target	type
    //   169	188	213	finally
    //   188	195	213	finally
    //   200	210	213	finally
    //   267	300	213	finally
    //   16	28	242	java/net/MalformedURLException
    //   35	45	242	java/net/MalformedURLException
    //   52	56	242	java/net/MalformedURLException
    //   63	68	242	java/net/MalformedURLException
    //   75	92	242	java/net/MalformedURLException
    //   99	109	242	java/net/MalformedURLException
    //   116	126	242	java/net/MalformedURLException
    //   133	139	242	java/net/MalformedURLException
    //   146	155	242	java/net/MalformedURLException
    //   162	169	242	java/net/MalformedURLException
    //   227	232	242	java/net/MalformedURLException
    //   239	242	242	java/net/MalformedURLException
    //   312	317	242	java/net/MalformedURLException
    //   16	28	328	java/io/IOException
    //   35	45	328	java/io/IOException
    //   52	56	328	java/io/IOException
    //   63	68	328	java/io/IOException
    //   75	92	328	java/io/IOException
    //   99	109	328	java/io/IOException
    //   116	126	328	java/io/IOException
    //   133	139	328	java/io/IOException
    //   146	155	328	java/io/IOException
    //   162	169	328	java/io/IOException
    //   227	232	328	java/io/IOException
    //   239	242	328	java/io/IOException
    //   312	317	328	java/io/IOException
    //   16	28	356	finally
    //   35	45	356	finally
    //   52	56	356	finally
    //   63	68	356	finally
    //   75	92	356	finally
    //   99	109	356	finally
    //   116	126	356	finally
    //   133	139	356	finally
    //   146	155	356	finally
    //   162	169	356	finally
    //   227	232	356	finally
    //   239	242	356	finally
    //   245	256	356	finally
    //   312	317	356	finally
    //   332	343	356	finally
  }
}


/* Location:              /Users/amaurremi/uw/stringoid/static-dynamic-comparison/apps/where is that/com.jaysquared.games.whereishd.releasefree-72-dex2jar.jar!/com/vungle/sdk/at.class
 * Java compiler version: 6 (50.0)
 * JD-Core Version:       0.7.1
 */