package com.flurry.android.monolithic.sdk.impl;

public class ev
  extends jf
{
  static int a = 15000;
  private String b;
  private String c;
  private String d;
  private byte[] e;
  private ex f;
  
  public ev(String paramString1, String paramString2, String paramString3, byte[] paramArrayOfByte, ex paramex)
  {
    this.b = paramString1;
    this.c = paramString2;
    this.d = paramString3;
    this.e = paramArrayOfByte;
    this.f = paramex;
  }
  
  /* Error */
  public void a()
  {
    // Byte code:
    //   0: aconst_null
    //   1: astore 5
    //   3: aconst_null
    //   4: astore 7
    //   6: invokestatic 41	java/lang/Thread:currentThread	()Ljava/lang/Thread;
    //   9: invokevirtual 45	java/lang/Thread:getId	()J
    //   12: lstore_2
    //   13: invokestatic 41	java/lang/Thread:currentThread	()Ljava/lang/Thread;
    //   16: new 47	java/lang/StringBuilder
    //   19: dup
    //   20: invokespecial 48	java/lang/StringBuilder:<init>	()V
    //   23: ldc 50
    //   25: invokevirtual 54	java/lang/StringBuilder:append	(Ljava/lang/String;)Ljava/lang/StringBuilder;
    //   28: lload_2
    //   29: invokestatic 60	java/lang/Long:valueOf	(J)Ljava/lang/Long;
    //   32: invokevirtual 63	java/lang/StringBuilder:append	(Ljava/lang/Object;)Ljava/lang/StringBuilder;
    //   35: invokevirtual 67	java/lang/StringBuilder:toString	()Ljava/lang/String;
    //   38: invokevirtual 71	java/lang/Thread:setName	(Ljava/lang/String;)V
    //   41: new 73	org/apache/http/entity/ByteArrayEntity
    //   44: dup
    //   45: aload_0
    //   46: getfield 31	com/flurry/android/monolithic/sdk/impl/ev:e	[B
    //   49: invokespecial 76	org/apache/http/entity/ByteArrayEntity:<init>	([B)V
    //   52: astore 4
    //   54: aload 4
    //   56: ldc 78
    //   58: invokevirtual 81	org/apache/http/entity/ByteArrayEntity:setContentType	(Ljava/lang/String;)V
    //   61: new 83	org/apache/http/client/methods/HttpPost
    //   64: dup
    //   65: aload_0
    //   66: getfield 25	com/flurry/android/monolithic/sdk/impl/ev:b	Ljava/lang/String;
    //   69: invokespecial 85	org/apache/http/client/methods/HttpPost:<init>	(Ljava/lang/String;)V
    //   72: astore 6
    //   74: aload 6
    //   76: aload 4
    //   78: invokevirtual 89	org/apache/http/client/methods/HttpPost:setEntity	(Lorg/apache/http/HttpEntity;)V
    //   81: new 91	org/apache/http/params/BasicHttpParams
    //   84: dup
    //   85: invokespecial 92	org/apache/http/params/BasicHttpParams:<init>	()V
    //   88: astore 4
    //   90: aload 4
    //   92: sipush 10000
    //   95: invokestatic 98	org/apache/http/params/HttpConnectionParams:setConnectionTimeout	(Lorg/apache/http/params/HttpParams;I)V
    //   98: aload 4
    //   100: getstatic 18	com/flurry/android/monolithic/sdk/impl/ev:a	I
    //   103: invokestatic 101	org/apache/http/params/HttpConnectionParams:setSoTimeout	(Lorg/apache/http/params/HttpParams;I)V
    //   106: aload 6
    //   108: invokevirtual 105	org/apache/http/client/methods/HttpPost:getParams	()Lorg/apache/http/params/HttpParams;
    //   111: ldc 107
    //   113: iconst_0
    //   114: invokeinterface 113 3 0
    //   119: pop
    //   120: aload 4
    //   122: invokestatic 118	com/flurry/android/monolithic/sdk/impl/iz:b	(Lorg/apache/http/params/HttpParams;)Lorg/apache/http/client/HttpClient;
    //   125: astore 4
    //   127: aload 4
    //   129: astore 5
    //   131: aload 4
    //   133: aload 6
    //   135: invokeinterface 124 2 0
    //   140: astore 6
    //   142: aload 6
    //   144: astore 5
    //   146: aload 4
    //   148: ifnull +19 -> 167
    //   151: aload 4
    //   153: invokeinterface 128 1 0
    //   158: invokeinterface 133 1 0
    //   163: aload 6
    //   165: astore 5
    //   167: aload 5
    //   169: ifnull +13 -> 182
    //   172: aload 5
    //   174: invokeinterface 139 1 0
    //   179: ifnonnull +85 -> 264
    //   182: aload_0
    //   183: getfield 33	com/flurry/android/monolithic/sdk/impl/ev:f	Lcom/flurry/android/monolithic/sdk/impl/ex;
    //   186: aload_0
    //   187: getfield 27	com/flurry/android/monolithic/sdk/impl/ev:c	Ljava/lang/String;
    //   190: aload_0
    //   191: getfield 29	com/flurry/android/monolithic/sdk/impl/ev:d	Ljava/lang/String;
    //   194: invokeinterface 144 3 0
    //   199: return
    //   200: astore 6
    //   202: aconst_null
    //   203: astore 4
    //   205: aload 4
    //   207: astore 5
    //   209: aload 6
    //   211: invokevirtual 147	java/lang/Exception:printStackTrace	()V
    //   214: aload 7
    //   216: astore 5
    //   218: aload 4
    //   220: ifnull -53 -> 167
    //   223: aload 4
    //   225: invokeinterface 128 1 0
    //   230: invokeinterface 133 1 0
    //   235: aload 7
    //   237: astore 5
    //   239: goto -72 -> 167
    //   242: astore 4
    //   244: aload 5
    //   246: ifnull +15 -> 261
    //   249: aload 5
    //   251: invokeinterface 128 1 0
    //   256: invokeinterface 133 1 0
    //   261: aload 4
    //   263: athrow
    //   264: aload 5
    //   266: invokeinterface 139 1 0
    //   271: astore 4
    //   273: aload 4
    //   275: invokeinterface 153 1 0
    //   280: istore_1
    //   281: aload 4
    //   283: invokeinterface 156 1 0
    //   288: astore 4
    //   290: aload_0
    //   291: getfield 33	com/flurry/android/monolithic/sdk/impl/ev:f	Lcom/flurry/android/monolithic/sdk/impl/ex;
    //   294: iload_1
    //   295: aload 4
    //   297: aload_0
    //   298: getfield 27	com/flurry/android/monolithic/sdk/impl/ev:c	Ljava/lang/String;
    //   301: aload_0
    //   302: getfield 29	com/flurry/android/monolithic/sdk/impl/ev:d	Ljava/lang/String;
    //   305: invokeinterface 159 5 0
    //   310: return
    //   311: astore 4
    //   313: aload 4
    //   315: invokevirtual 147	java/lang/Exception:printStackTrace	()V
    //   318: return
    //   319: astore 4
    //   321: goto -77 -> 244
    //   324: astore 6
    //   326: goto -121 -> 205
    // Local variable table:
    //   start	length	slot	name	signature
    //   0	329	0	this	ev
    //   280	15	1	i	int
    //   12	17	2	l	long
    //   52	172	4	localObject1	Object
    //   242	20	4	localObject2	Object
    //   271	25	4	localObject3	Object
    //   311	3	4	localException1	Exception
    //   319	1	4	localObject4	Object
    //   1	264	5	localObject5	Object
    //   72	92	6	localObject6	Object
    //   200	10	6	localException2	Exception
    //   324	1	6	localException3	Exception
    //   4	232	7	localObject7	Object
    // Exception table:
    //   from	to	target	type
    //   41	127	200	java/lang/Exception
    //   41	127	242	finally
    //   172	182	311	java/lang/Exception
    //   182	199	311	java/lang/Exception
    //   264	310	311	java/lang/Exception
    //   131	142	319	finally
    //   209	214	319	finally
    //   131	142	324	java/lang/Exception
  }
}


/* Location:              /Users/amaurremi/uw/stringoid/static-dynamic-comparison/apps/logo quiz/logo.quiz.game.category-48-dex2jar.jar!/com/flurry/android/monolithic/sdk/impl/ev.class
 * Java compiler version: 6 (50.0)
 * JD-Core Version:       0.7.1
 */