package com.flurry.android.monolithic.sdk.impl;

import com.flurry.android.InstallReceiver;

public class h
  extends jf
{
  public h(InstallReceiver paramInstallReceiver, String paramString) {}
  
  /* Error */
  public void a()
  {
    // Byte code:
    //   0: aconst_null
    //   1: astore_1
    //   2: iconst_3
    //   3: ldc 22
    //   5: ldc 24
    //   7: invokestatic 29	com/flurry/android/monolithic/sdk/impl/ja:a	(ILjava/lang/String;Ljava/lang/String;)V
    //   10: aload_0
    //   11: getfield 12	com/flurry/android/monolithic/sdk/impl/h:b	Lcom/flurry/android/InstallReceiver;
    //   14: invokestatic 34	com/flurry/android/InstallReceiver:a	(Lcom/flurry/android/InstallReceiver;)Ljava/io/File;
    //   17: invokevirtual 40	java/io/File:getParentFile	()Ljava/io/File;
    //   20: astore_2
    //   21: iconst_3
    //   22: ldc 22
    //   24: new 42	java/lang/StringBuilder
    //   27: dup
    //   28: invokespecial 43	java/lang/StringBuilder:<init>	()V
    //   31: ldc 45
    //   33: invokevirtual 49	java/lang/StringBuilder:append	(Ljava/lang/String;)Ljava/lang/StringBuilder;
    //   36: aload_2
    //   37: invokevirtual 53	java/io/File:toString	()Ljava/lang/String;
    //   40: invokevirtual 49	java/lang/StringBuilder:append	(Ljava/lang/String;)Ljava/lang/StringBuilder;
    //   43: invokevirtual 54	java/lang/StringBuilder:toString	()Ljava/lang/String;
    //   46: invokestatic 29	com/flurry/android/monolithic/sdk/impl/ja:a	(ILjava/lang/String;Ljava/lang/String;)V
    //   49: aload_2
    //   50: invokevirtual 58	java/io/File:mkdirs	()Z
    //   53: ifne +41 -> 94
    //   56: aload_2
    //   57: invokevirtual 61	java/io/File:exists	()Z
    //   60: ifne +34 -> 94
    //   63: bipush 6
    //   65: ldc 22
    //   67: new 42	java/lang/StringBuilder
    //   70: dup
    //   71: invokespecial 43	java/lang/StringBuilder:<init>	()V
    //   74: ldc 63
    //   76: invokevirtual 49	java/lang/StringBuilder:append	(Ljava/lang/String;)Ljava/lang/StringBuilder;
    //   79: aload_2
    //   80: invokevirtual 66	java/lang/StringBuilder:append	(Ljava/lang/Object;)Ljava/lang/StringBuilder;
    //   83: invokevirtual 54	java/lang/StringBuilder:toString	()Ljava/lang/String;
    //   86: invokestatic 29	com/flurry/android/monolithic/sdk/impl/ja:a	(ILjava/lang/String;Ljava/lang/String;)V
    //   89: aconst_null
    //   90: invokestatic 71	com/flurry/android/monolithic/sdk/impl/je:a	(Ljava/io/Closeable;)V
    //   93: return
    //   94: new 73	java/io/FileOutputStream
    //   97: dup
    //   98: aload_0
    //   99: getfield 12	com/flurry/android/monolithic/sdk/impl/h:b	Lcom/flurry/android/InstallReceiver;
    //   102: invokestatic 34	com/flurry/android/InstallReceiver:a	(Lcom/flurry/android/InstallReceiver;)Ljava/io/File;
    //   105: invokespecial 76	java/io/FileOutputStream:<init>	(Ljava/io/File;)V
    //   108: astore_2
    //   109: iconst_3
    //   110: ldc 22
    //   112: ldc 78
    //   114: invokestatic 29	com/flurry/android/monolithic/sdk/impl/ja:a	(ILjava/lang/String;Ljava/lang/String;)V
    //   117: aload_2
    //   118: aload_0
    //   119: getfield 14	com/flurry/android/monolithic/sdk/impl/h:a	Ljava/lang/String;
    //   122: invokevirtual 84	java/lang/String:getBytes	()[B
    //   125: invokevirtual 88	java/io/FileOutputStream:write	([B)V
    //   128: aload_0
    //   129: getfield 12	com/flurry/android/monolithic/sdk/impl/h:b	Lcom/flurry/android/InstallReceiver;
    //   132: aload_0
    //   133: getfield 12	com/flurry/android/monolithic/sdk/impl/h:b	Lcom/flurry/android/InstallReceiver;
    //   136: invokestatic 34	com/flurry/android/InstallReceiver:a	(Lcom/flurry/android/InstallReceiver;)Ljava/io/File;
    //   139: invokestatic 91	com/flurry/android/InstallReceiver:a	(Lcom/flurry/android/InstallReceiver;Ljava/io/File;)Ljava/lang/String;
    //   142: invokestatic 94	com/flurry/android/InstallReceiver:a	(Ljava/lang/String;)Ljava/util/Map;
    //   145: astore_1
    //   146: aload_1
    //   147: ifnull +104 -> 251
    //   150: aload_1
    //   151: invokeinterface 100 1 0
    //   156: invokeinterface 106 1 0
    //   161: astore_1
    //   162: aload_1
    //   163: invokeinterface 111 1 0
    //   168: ifeq +83 -> 251
    //   171: aload_1
    //   172: invokeinterface 115 1 0
    //   177: checkcast 117	java/util/Map$Entry
    //   180: astore_3
    //   181: iconst_3
    //   182: ldc 22
    //   184: new 42	java/lang/StringBuilder
    //   187: dup
    //   188: invokespecial 43	java/lang/StringBuilder:<init>	()V
    //   191: ldc 119
    //   193: invokevirtual 49	java/lang/StringBuilder:append	(Ljava/lang/String;)Ljava/lang/StringBuilder;
    //   196: aload_3
    //   197: invokeinterface 122 1 0
    //   202: checkcast 80	java/lang/String
    //   205: invokevirtual 49	java/lang/StringBuilder:append	(Ljava/lang/String;)Ljava/lang/StringBuilder;
    //   208: ldc 124
    //   210: invokevirtual 49	java/lang/StringBuilder:append	(Ljava/lang/String;)Ljava/lang/StringBuilder;
    //   213: aload_3
    //   214: invokeinterface 127 1 0
    //   219: invokevirtual 66	java/lang/StringBuilder:append	(Ljava/lang/Object;)Ljava/lang/StringBuilder;
    //   222: invokevirtual 54	java/lang/StringBuilder:toString	()Ljava/lang/String;
    //   225: invokestatic 29	com/flurry/android/monolithic/sdk/impl/ja:a	(ILjava/lang/String;Ljava/lang/String;)V
    //   228: goto -66 -> 162
    //   231: astore_3
    //   232: aload_2
    //   233: astore_1
    //   234: aload_3
    //   235: astore_2
    //   236: bipush 6
    //   238: ldc 22
    //   240: ldc -127
    //   242: aload_2
    //   243: invokestatic 132	com/flurry/android/monolithic/sdk/impl/ja:a	(ILjava/lang/String;Ljava/lang/String;Ljava/lang/Throwable;)V
    //   246: aload_1
    //   247: invokestatic 71	com/flurry/android/monolithic/sdk/impl/je:a	(Ljava/io/Closeable;)V
    //   250: return
    //   251: aload_2
    //   252: invokestatic 71	com/flurry/android/monolithic/sdk/impl/je:a	(Ljava/io/Closeable;)V
    //   255: return
    //   256: astore_1
    //   257: aconst_null
    //   258: astore_2
    //   259: aload_2
    //   260: invokestatic 71	com/flurry/android/monolithic/sdk/impl/je:a	(Ljava/io/Closeable;)V
    //   263: aload_1
    //   264: athrow
    //   265: astore_1
    //   266: goto -7 -> 259
    //   269: astore_3
    //   270: aload_1
    //   271: astore_2
    //   272: aload_3
    //   273: astore_1
    //   274: goto -15 -> 259
    //   277: astore_2
    //   278: goto -42 -> 236
    // Local variable table:
    //   start	length	slot	name	signature
    //   0	281	0	this	h
    //   1	246	1	localObject1	Object
    //   256	8	1	localObject2	Object
    //   265	6	1	localObject3	Object
    //   273	1	1	localObject4	Object
    //   20	252	2	localObject5	Object
    //   277	1	2	localThrowable1	Throwable
    //   180	34	3	localEntry	java.util.Map.Entry
    //   231	4	3	localThrowable2	Throwable
    //   269	4	3	localObject6	Object
    // Exception table:
    //   from	to	target	type
    //   109	146	231	java/lang/Throwable
    //   150	162	231	java/lang/Throwable
    //   162	228	231	java/lang/Throwable
    //   10	89	256	finally
    //   94	109	256	finally
    //   109	146	265	finally
    //   150	162	265	finally
    //   162	228	265	finally
    //   236	246	269	finally
    //   10	89	277	java/lang/Throwable
    //   94	109	277	java/lang/Throwable
  }
}


/* Location:              /Users/amaurremi/uw/stringoid/static-dynamic-comparison/apps/logo quiz/logo.quiz.game.category-48-dex2jar.jar!/com/flurry/android/monolithic/sdk/impl/h.class
 * Java compiler version: 6 (50.0)
 * JD-Core Version:       0.7.1
 */