package com.flurry.android.monolithic.sdk.impl;

class ho
{
  private hn a;
  private String b;
  private Object c = new Object();
  
  /* Error */
  private hn c(hm arg1)
  {
    // Byte code:
    //   0: aload_0
    //   1: new 31	com/flurry/android/monolithic/sdk/impl/hn
    //   4: dup
    //   5: sipush 721
    //   8: aconst_null
    //   9: invokespecial 34	com/flurry/android/monolithic/sdk/impl/hn:<init>	(ILcom/flurry/android/monolithic/sdk/impl/fq;)V
    //   12: putfield 20	com/flurry/android/monolithic/sdk/impl/ho:a	Lcom/flurry/android/monolithic/sdk/impl/hn;
    //   15: new 36	java/util/ArrayList
    //   18: dup
    //   19: aload_1
    //   20: invokevirtual 41	com/flurry/android/monolithic/sdk/impl/hm:a	()Ljava/util/Vector;
    //   23: invokespecial 44	java/util/ArrayList:<init>	(Ljava/util/Collection;)V
    //   26: astore 5
    //   28: aload_0
    //   29: aload_1
    //   30: invokevirtual 47	com/flurry/android/monolithic/sdk/impl/hm:c	()Ljava/lang/String;
    //   33: putfield 23	com/flurry/android/monolithic/sdk/impl/ho:b	Ljava/lang/String;
    //   36: aload_1
    //   37: invokevirtual 49	com/flurry/android/monolithic/sdk/impl/hm:b	()Ljava/lang/String;
    //   40: astore 6
    //   42: ldc 51
    //   44: astore 4
    //   46: iconst_0
    //   47: istore_3
    //   48: aload_1
    //   49: invokevirtual 55	com/flurry/android/monolithic/sdk/impl/hm:g	()Lcom/flurry/android/monolithic/sdk/impl/hl;
    //   52: getstatic 60	com/flurry/android/monolithic/sdk/impl/hl:b	Lcom/flurry/android/monolithic/sdk/impl/hl;
    //   55: if_acmpne +74 -> 129
    //   58: iconst_1
    //   59: istore_2
    //   60: new 62	java/lang/StringBuilder
    //   63: dup
    //   64: invokespecial 63	java/lang/StringBuilder:<init>	()V
    //   67: ldc 51
    //   69: invokevirtual 67	java/lang/StringBuilder:append	(Ljava/lang/String;)Ljava/lang/StringBuilder;
    //   72: ldc 69
    //   74: invokevirtual 67	java/lang/StringBuilder:append	(Ljava/lang/String;)Ljava/lang/StringBuilder;
    //   77: invokevirtual 72	java/lang/StringBuilder:toString	()Ljava/lang/String;
    //   80: astore 4
    //   82: aload_0
    //   83: getfield 23	com/flurry/android/monolithic/sdk/impl/ho:b	Ljava/lang/String;
    //   86: ifnonnull +19 -> 105
    //   89: iload_2
    //   90: aload 4
    //   92: aload 5
    //   94: new 74	com/flurry/android/monolithic/sdk/impl/hp
    //   97: dup
    //   98: aload_0
    //   99: invokespecial 77	com/flurry/android/monolithic/sdk/impl/hp:<init>	(Lcom/flurry/android/monolithic/sdk/impl/ho;)V
    //   102: invokestatic 82	com/flurry/android/monolithic/sdk/impl/gr:a	(ZLjava/lang/String;Ljava/util/List;Lcom/flurry/android/monolithic/sdk/impl/fr;)V
    //   105: aload_0
    //   106: getfield 16	com/flurry/android/monolithic/sdk/impl/ho:c	Ljava/lang/Object;
    //   109: astore_1
    //   110: aload_1
    //   111: monitorenter
    //   112: aload_0
    //   113: getfield 16	com/flurry/android/monolithic/sdk/impl/ho:c	Ljava/lang/Object;
    //   116: ldc2_w 83
    //   119: invokevirtual 88	java/lang/Object:wait	(J)V
    //   122: aload_1
    //   123: monitorexit
    //   124: aload_0
    //   125: getfield 20	com/flurry/android/monolithic/sdk/impl/ho:a	Lcom/flurry/android/monolithic/sdk/impl/hn;
    //   128: areturn
    //   129: iload_3
    //   130: istore_2
    //   131: aload_1
    //   132: invokevirtual 55	com/flurry/android/monolithic/sdk/impl/hm:g	()Lcom/flurry/android/monolithic/sdk/impl/hl;
    //   135: getstatic 90	com/flurry/android/monolithic/sdk/impl/hl:a	Lcom/flurry/android/monolithic/sdk/impl/hl;
    //   138: if_acmpne -56 -> 82
    //   141: new 62	java/lang/StringBuilder
    //   144: dup
    //   145: invokespecial 63	java/lang/StringBuilder:<init>	()V
    //   148: ldc 51
    //   150: invokevirtual 67	java/lang/StringBuilder:append	(Ljava/lang/String;)Ljava/lang/StringBuilder;
    //   153: ldc 92
    //   155: invokevirtual 67	java/lang/StringBuilder:append	(Ljava/lang/String;)Ljava/lang/StringBuilder;
    //   158: aload 6
    //   160: invokevirtual 67	java/lang/StringBuilder:append	(Ljava/lang/String;)Ljava/lang/StringBuilder;
    //   163: invokevirtual 72	java/lang/StringBuilder:toString	()Ljava/lang/String;
    //   166: astore 4
    //   168: iload_3
    //   169: istore_2
    //   170: goto -88 -> 82
    //   173: astore_1
    //   174: aload_1
    //   175: invokevirtual 95	java/lang/Exception:printStackTrace	()V
    //   178: goto -73 -> 105
    //   181: astore 4
    //   183: aload_1
    //   184: monitorexit
    //   185: aload 4
    //   187: athrow
    //   188: astore_1
    //   189: aload_1
    //   190: invokevirtual 96	java/lang/InterruptedException:printStackTrace	()V
    //   193: goto -69 -> 124
    // Local variable table:
    //   start	length	slot	name	signature
    //   0	196	0	this	ho
    //   59	111	2	bool1	boolean
    //   47	122	3	bool2	boolean
    //   44	123	4	str1	String
    //   181	5	4	localObject	Object
    //   26	67	5	localArrayList	java.util.ArrayList
    //   40	119	6	str2	String
    // Exception table:
    //   from	to	target	type
    //   15	42	173	java/lang/Exception
    //   48	58	173	java/lang/Exception
    //   60	82	173	java/lang/Exception
    //   82	105	173	java/lang/Exception
    //   131	168	173	java/lang/Exception
    //   112	124	181	finally
    //   183	185	181	finally
    //   105	112	188	java/lang/InterruptedException
    //   185	188	188	java/lang/InterruptedException
  }
  
  /* Error */
  private hn d(hm arg1)
  {
    // Byte code:
    //   0: aload_0
    //   1: new 31	com/flurry/android/monolithic/sdk/impl/hn
    //   4: dup
    //   5: sipush 721
    //   8: aconst_null
    //   9: invokespecial 34	com/flurry/android/monolithic/sdk/impl/hn:<init>	(ILcom/flurry/android/monolithic/sdk/impl/fq;)V
    //   12: putfield 20	com/flurry/android/monolithic/sdk/impl/ho:a	Lcom/flurry/android/monolithic/sdk/impl/hn;
    //   15: aload_0
    //   16: aload_1
    //   17: invokevirtual 47	com/flurry/android/monolithic/sdk/impl/hm:c	()Ljava/lang/String;
    //   20: putfield 23	com/flurry/android/monolithic/sdk/impl/ho:b	Ljava/lang/String;
    //   23: aload_1
    //   24: invokevirtual 49	com/flurry/android/monolithic/sdk/impl/hm:b	()Ljava/lang/String;
    //   27: astore 5
    //   29: ldc 51
    //   31: astore 4
    //   33: iconst_0
    //   34: istore_3
    //   35: aload_1
    //   36: invokevirtual 55	com/flurry/android/monolithic/sdk/impl/hm:g	()Lcom/flurry/android/monolithic/sdk/impl/hl;
    //   39: getstatic 60	com/flurry/android/monolithic/sdk/impl/hl:b	Lcom/flurry/android/monolithic/sdk/impl/hl;
    //   42: if_acmpne +91 -> 133
    //   45: iconst_1
    //   46: istore_2
    //   47: new 62	java/lang/StringBuilder
    //   50: dup
    //   51: invokespecial 63	java/lang/StringBuilder:<init>	()V
    //   54: ldc 51
    //   56: invokevirtual 67	java/lang/StringBuilder:append	(Ljava/lang/String;)Ljava/lang/StringBuilder;
    //   59: ldc 69
    //   61: invokevirtual 67	java/lang/StringBuilder:append	(Ljava/lang/String;)Ljava/lang/StringBuilder;
    //   64: invokevirtual 72	java/lang/StringBuilder:toString	()Ljava/lang/String;
    //   67: astore 4
    //   69: iload_2
    //   70: new 62	java/lang/StringBuilder
    //   73: dup
    //   74: invokespecial 63	java/lang/StringBuilder:<init>	()V
    //   77: aload 4
    //   79: invokevirtual 67	java/lang/StringBuilder:append	(Ljava/lang/String;)Ljava/lang/StringBuilder;
    //   82: ldc 99
    //   84: invokevirtual 67	java/lang/StringBuilder:append	(Ljava/lang/String;)Ljava/lang/StringBuilder;
    //   87: aload_0
    //   88: getfield 23	com/flurry/android/monolithic/sdk/impl/ho:b	Ljava/lang/String;
    //   91: invokevirtual 67	java/lang/StringBuilder:append	(Ljava/lang/String;)Ljava/lang/StringBuilder;
    //   94: invokevirtual 72	java/lang/StringBuilder:toString	()Ljava/lang/String;
    //   97: aconst_null
    //   98: new 101	com/flurry/android/monolithic/sdk/impl/hq
    //   101: dup
    //   102: aload_0
    //   103: invokespecial 102	com/flurry/android/monolithic/sdk/impl/hq:<init>	(Lcom/flurry/android/monolithic/sdk/impl/ho;)V
    //   106: invokestatic 104	com/flurry/android/monolithic/sdk/impl/gr:c	(ZLjava/lang/String;Ljava/util/List;Lcom/flurry/android/monolithic/sdk/impl/fr;)V
    //   109: aload_0
    //   110: getfield 16	com/flurry/android/monolithic/sdk/impl/ho:c	Ljava/lang/Object;
    //   113: astore_1
    //   114: aload_1
    //   115: monitorenter
    //   116: aload_0
    //   117: getfield 16	com/flurry/android/monolithic/sdk/impl/ho:c	Ljava/lang/Object;
    //   120: ldc2_w 83
    //   123: invokevirtual 88	java/lang/Object:wait	(J)V
    //   126: aload_1
    //   127: monitorexit
    //   128: aload_0
    //   129: getfield 20	com/flurry/android/monolithic/sdk/impl/ho:a	Lcom/flurry/android/monolithic/sdk/impl/hn;
    //   132: areturn
    //   133: iload_3
    //   134: istore_2
    //   135: aload_1
    //   136: invokevirtual 55	com/flurry/android/monolithic/sdk/impl/hm:g	()Lcom/flurry/android/monolithic/sdk/impl/hl;
    //   139: getstatic 90	com/flurry/android/monolithic/sdk/impl/hl:a	Lcom/flurry/android/monolithic/sdk/impl/hl;
    //   142: if_acmpne -73 -> 69
    //   145: new 62	java/lang/StringBuilder
    //   148: dup
    //   149: invokespecial 63	java/lang/StringBuilder:<init>	()V
    //   152: ldc 51
    //   154: invokevirtual 67	java/lang/StringBuilder:append	(Ljava/lang/String;)Ljava/lang/StringBuilder;
    //   157: ldc 92
    //   159: invokevirtual 67	java/lang/StringBuilder:append	(Ljava/lang/String;)Ljava/lang/StringBuilder;
    //   162: aload 5
    //   164: invokevirtual 67	java/lang/StringBuilder:append	(Ljava/lang/String;)Ljava/lang/StringBuilder;
    //   167: invokevirtual 72	java/lang/StringBuilder:toString	()Ljava/lang/String;
    //   170: astore 4
    //   172: iload_3
    //   173: istore_2
    //   174: goto -105 -> 69
    //   177: astore_1
    //   178: aload_1
    //   179: invokevirtual 95	java/lang/Exception:printStackTrace	()V
    //   182: goto -73 -> 109
    //   185: astore 4
    //   187: aload_1
    //   188: monitorexit
    //   189: aload 4
    //   191: athrow
    //   192: astore_1
    //   193: aload_1
    //   194: invokevirtual 96	java/lang/InterruptedException:printStackTrace	()V
    //   197: goto -69 -> 128
    // Local variable table:
    //   start	length	slot	name	signature
    //   0	200	0	this	ho
    //   46	128	2	bool1	boolean
    //   34	139	3	bool2	boolean
    //   31	140	4	str1	String
    //   185	5	4	localObject	Object
    //   27	136	5	str2	String
    // Exception table:
    //   from	to	target	type
    //   69	109	177	java/lang/Exception
    //   116	128	185	finally
    //   187	189	185	finally
    //   109	116	192	java/lang/InterruptedException
    //   189	192	192	java/lang/InterruptedException
  }
  
  public hn a(hm paramhm)
  {
    switch (paramhm.h())
    {
    default: 
      return null;
    case 1: 
      return c(paramhm);
    case 2: 
      return d(paramhm);
    }
    return b(paramhm);
  }
  
  /* Error */
  public hn b(hm arg1)
  {
    // Byte code:
    //   0: aload_0
    //   1: new 31	com/flurry/android/monolithic/sdk/impl/hn
    //   4: dup
    //   5: sipush 721
    //   8: aconst_null
    //   9: invokespecial 34	com/flurry/android/monolithic/sdk/impl/hn:<init>	(ILcom/flurry/android/monolithic/sdk/impl/fq;)V
    //   12: putfield 20	com/flurry/android/monolithic/sdk/impl/ho:a	Lcom/flurry/android/monolithic/sdk/impl/hn;
    //   15: aload_1
    //   16: invokevirtual 41	com/flurry/android/monolithic/sdk/impl/hm:a	()Ljava/util/Vector;
    //   19: iconst_0
    //   20: invokevirtual 120	java/util/Vector:get	(I)Ljava/lang/Object;
    //   23: checkcast 122	org/apache/http/NameValuePair
    //   26: invokeinterface 125 1 0
    //   31: astore 4
    //   33: aload_1
    //   34: invokevirtual 41	com/flurry/android/monolithic/sdk/impl/hm:a	()Ljava/util/Vector;
    //   37: iconst_0
    //   38: invokevirtual 120	java/util/Vector:get	(I)Ljava/lang/Object;
    //   41: checkcast 122	org/apache/http/NameValuePair
    //   44: invokeinterface 128 1 0
    //   49: astore 5
    //   51: aload_0
    //   52: aload_1
    //   53: invokevirtual 47	com/flurry/android/monolithic/sdk/impl/hm:c	()Ljava/lang/String;
    //   56: putfield 23	com/flurry/android/monolithic/sdk/impl/ho:b	Ljava/lang/String;
    //   59: aload_1
    //   60: invokevirtual 49	com/flurry/android/monolithic/sdk/impl/hm:b	()Ljava/lang/String;
    //   63: astore 6
    //   65: new 36	java/util/ArrayList
    //   68: dup
    //   69: invokespecial 129	java/util/ArrayList:<init>	()V
    //   72: astore_3
    //   73: aload 4
    //   75: ifnull +49 -> 124
    //   78: aload 4
    //   80: ldc -125
    //   82: invokevirtual 137	java/lang/String:equals	(Ljava/lang/Object;)Z
    //   85: ifne +39 -> 124
    //   88: aload_3
    //   89: new 139	org/apache/http/message/BasicNameValuePair
    //   92: dup
    //   93: aload 4
    //   95: new 62	java/lang/StringBuilder
    //   98: dup
    //   99: invokespecial 63	java/lang/StringBuilder:<init>	()V
    //   102: ldc -115
    //   104: invokevirtual 67	java/lang/StringBuilder:append	(Ljava/lang/String;)Ljava/lang/StringBuilder;
    //   107: aload 5
    //   109: invokevirtual 67	java/lang/StringBuilder:append	(Ljava/lang/String;)Ljava/lang/StringBuilder;
    //   112: invokevirtual 72	java/lang/StringBuilder:toString	()Ljava/lang/String;
    //   115: invokespecial 144	org/apache/http/message/BasicNameValuePair:<init>	(Ljava/lang/String;Ljava/lang/String;)V
    //   118: invokeinterface 149 2 0
    //   123: pop
    //   124: aload_1
    //   125: invokevirtual 55	com/flurry/android/monolithic/sdk/impl/hm:g	()Lcom/flurry/android/monolithic/sdk/impl/hl;
    //   128: getstatic 60	com/flurry/android/monolithic/sdk/impl/hl:b	Lcom/flurry/android/monolithic/sdk/impl/hl;
    //   131: if_acmpne +89 -> 220
    //   134: iconst_1
    //   135: istore_2
    //   136: new 62	java/lang/StringBuilder
    //   139: dup
    //   140: invokespecial 63	java/lang/StringBuilder:<init>	()V
    //   143: ldc -125
    //   145: invokevirtual 67	java/lang/StringBuilder:append	(Ljava/lang/String;)Ljava/lang/StringBuilder;
    //   148: ldc 69
    //   150: invokevirtual 67	java/lang/StringBuilder:append	(Ljava/lang/String;)Ljava/lang/StringBuilder;
    //   153: invokevirtual 72	java/lang/StringBuilder:toString	()Ljava/lang/String;
    //   156: astore_1
    //   157: iload_2
    //   158: new 62	java/lang/StringBuilder
    //   161: dup
    //   162: invokespecial 63	java/lang/StringBuilder:<init>	()V
    //   165: aload_1
    //   166: invokevirtual 67	java/lang/StringBuilder:append	(Ljava/lang/String;)Ljava/lang/StringBuilder;
    //   169: ldc 99
    //   171: invokevirtual 67	java/lang/StringBuilder:append	(Ljava/lang/String;)Ljava/lang/StringBuilder;
    //   174: aload_0
    //   175: getfield 23	com/flurry/android/monolithic/sdk/impl/ho:b	Ljava/lang/String;
    //   178: invokevirtual 67	java/lang/StringBuilder:append	(Ljava/lang/String;)Ljava/lang/StringBuilder;
    //   181: invokevirtual 72	java/lang/StringBuilder:toString	()Ljava/lang/String;
    //   184: aload_3
    //   185: new 151	com/flurry/android/monolithic/sdk/impl/hr
    //   188: dup
    //   189: aload_0
    //   190: invokespecial 152	com/flurry/android/monolithic/sdk/impl/hr:<init>	(Lcom/flurry/android/monolithic/sdk/impl/ho;)V
    //   193: invokestatic 154	com/flurry/android/monolithic/sdk/impl/gr:b	(ZLjava/lang/String;Ljava/util/List;Lcom/flurry/android/monolithic/sdk/impl/fr;)V
    //   196: aload_0
    //   197: getfield 16	com/flurry/android/monolithic/sdk/impl/ho:c	Ljava/lang/Object;
    //   200: astore_1
    //   201: aload_1
    //   202: monitorenter
    //   203: aload_0
    //   204: getfield 16	com/flurry/android/monolithic/sdk/impl/ho:c	Ljava/lang/Object;
    //   207: ldc2_w 83
    //   210: invokevirtual 88	java/lang/Object:wait	(J)V
    //   213: aload_1
    //   214: monitorexit
    //   215: aload_0
    //   216: getfield 20	com/flurry/android/monolithic/sdk/impl/ho:a	Lcom/flurry/android/monolithic/sdk/impl/hn;
    //   219: areturn
    //   220: aload_1
    //   221: invokevirtual 55	com/flurry/android/monolithic/sdk/impl/hm:g	()Lcom/flurry/android/monolithic/sdk/impl/hl;
    //   224: getstatic 90	com/flurry/android/monolithic/sdk/impl/hl:a	Lcom/flurry/android/monolithic/sdk/impl/hl;
    //   227: if_acmpne +55 -> 282
    //   230: new 62	java/lang/StringBuilder
    //   233: dup
    //   234: invokespecial 63	java/lang/StringBuilder:<init>	()V
    //   237: ldc -125
    //   239: invokevirtual 67	java/lang/StringBuilder:append	(Ljava/lang/String;)Ljava/lang/StringBuilder;
    //   242: ldc 92
    //   244: invokevirtual 67	java/lang/StringBuilder:append	(Ljava/lang/String;)Ljava/lang/StringBuilder;
    //   247: aload 6
    //   249: invokevirtual 67	java/lang/StringBuilder:append	(Ljava/lang/String;)Ljava/lang/StringBuilder;
    //   252: invokevirtual 72	java/lang/StringBuilder:toString	()Ljava/lang/String;
    //   255: astore_1
    //   256: iconst_0
    //   257: istore_2
    //   258: goto -101 -> 157
    //   261: astore_1
    //   262: aload_1
    //   263: invokevirtual 95	java/lang/Exception:printStackTrace	()V
    //   266: goto -70 -> 196
    //   269: astore_3
    //   270: aload_1
    //   271: monitorexit
    //   272: aload_3
    //   273: athrow
    //   274: astore_1
    //   275: aload_1
    //   276: invokevirtual 96	java/lang/InterruptedException:printStackTrace	()V
    //   279: goto -64 -> 215
    //   282: iconst_0
    //   283: istore_2
    //   284: ldc -125
    //   286: astore_1
    //   287: goto -130 -> 157
    // Local variable table:
    //   start	length	slot	name	signature
    //   0	290	0	this	ho
    //   135	149	2	bool	boolean
    //   72	113	3	localArrayList	java.util.ArrayList
    //   269	4	3	localObject	Object
    //   31	63	4	str1	String
    //   49	59	5	str2	String
    //   63	185	6	str3	String
    // Exception table:
    //   from	to	target	type
    //   157	196	261	java/lang/Exception
    //   203	215	269	finally
    //   270	272	269	finally
    //   196	203	274	java/lang/InterruptedException
    //   272	274	274	java/lang/InterruptedException
  }
}


/* Location:              /Users/amaurremi/uw/stringoid/static-dynamic-comparison/apps/logo quiz/logo.quiz.game.category-48-dex2jar.jar!/com/flurry/android/monolithic/sdk/impl/ho.class
 * Java compiler version: 6 (50.0)
 * JD-Core Version:       0.7.1
 */