package com.gau.go.launcherex.gowidget.messagecenter.util;

import java.util.ArrayList;

public class a
{
  private ArrayList a;
  
  /* Error */
  public void a(int paramInt1, int paramInt2, Object paramObject, java.util.List paramList)
  {
    // Byte code:
    //   0: aload_0
    //   1: monitorenter
    //   2: aload_0
    //   3: getfield 14	com/gau/go/launcherex/gowidget/messagecenter/util/a:a	Ljava/util/ArrayList;
    //   6: astore 6
    //   8: aload 6
    //   10: ifnonnull +6 -> 16
    //   13: aload_0
    //   14: monitorexit
    //   15: return
    //   16: iconst_0
    //   17: istore 5
    //   19: iload 5
    //   21: aload_0
    //   22: getfield 14	com/gau/go/launcherex/gowidget/messagecenter/util/a:a	Ljava/util/ArrayList;
    //   25: invokevirtual 20	java/util/ArrayList:size	()I
    //   28: if_icmpge -15 -> 13
    //   31: aload_0
    //   32: getfield 14	com/gau/go/launcherex/gowidget/messagecenter/util/a:a	Ljava/util/ArrayList;
    //   35: iload 5
    //   37: invokevirtual 24	java/util/ArrayList:get	(I)Ljava/lang/Object;
    //   40: checkcast 26	com/gau/go/launcherex/gowidget/messagecenter/util/b
    //   43: astore 6
    //   45: aload 6
    //   47: ifnull +15 -> 62
    //   50: aload 6
    //   52: iload_1
    //   53: iload_2
    //   54: aload_3
    //   55: aload 4
    //   57: invokeinterface 28 5 0
    //   62: iload 5
    //   64: iconst_1
    //   65: iadd
    //   66: istore 5
    //   68: goto -49 -> 19
    //   71: astore_3
    //   72: aload_0
    //   73: monitorexit
    //   74: aload_3
    //   75: athrow
    // Local variable table:
    //   start	length	slot	name	signature
    //   0	76	0	this	a
    //   0	76	1	paramInt1	int
    //   0	76	2	paramInt2	int
    //   0	76	3	paramObject	Object
    //   0	76	4	paramList	java.util.List
    //   17	50	5	i	int
    //   6	45	6	localObject	Object
    // Exception table:
    //   from	to	target	type
    //   2	8	71	finally
    //   19	45	71	finally
    //   50	62	71	finally
  }
  
  /* Error */
  public void a(b paramb)
  {
    // Byte code:
    //   0: aload_0
    //   1: monitorenter
    //   2: aload_1
    //   3: ifnonnull +6 -> 9
    //   6: aload_0
    //   7: monitorexit
    //   8: return
    //   9: aload_0
    //   10: getfield 14	com/gau/go/launcherex/gowidget/messagecenter/util/a:a	Ljava/util/ArrayList;
    //   13: ifnonnull +14 -> 27
    //   16: aload_0
    //   17: new 16	java/util/ArrayList
    //   20: dup
    //   21: invokespecial 34	java/util/ArrayList:<init>	()V
    //   24: putfield 14	com/gau/go/launcherex/gowidget/messagecenter/util/a:a	Ljava/util/ArrayList;
    //   27: aload_0
    //   28: getfield 14	com/gau/go/launcherex/gowidget/messagecenter/util/a:a	Ljava/util/ArrayList;
    //   31: aload_1
    //   32: invokevirtual 38	java/util/ArrayList:indexOf	(Ljava/lang/Object;)I
    //   35: ifge -29 -> 6
    //   38: aload_0
    //   39: getfield 14	com/gau/go/launcherex/gowidget/messagecenter/util/a:a	Ljava/util/ArrayList;
    //   42: aload_1
    //   43: invokevirtual 42	java/util/ArrayList:add	(Ljava/lang/Object;)Z
    //   46: pop
    //   47: goto -41 -> 6
    //   50: astore_1
    //   51: aload_1
    //   52: invokevirtual 45	java/lang/Exception:printStackTrace	()V
    //   55: goto -49 -> 6
    //   58: astore_1
    //   59: aload_0
    //   60: monitorexit
    //   61: aload_1
    //   62: athrow
    //   63: astore_1
    //   64: invokestatic 50	com/gau/go/launcherex/gowidget/messagecenter/util/ah:b	()V
    //   67: goto -61 -> 6
    // Local variable table:
    //   start	length	slot	name	signature
    //   0	70	0	this	a
    //   0	70	1	paramb	b
    // Exception table:
    //   from	to	target	type
    //   27	47	50	java/lang/Exception
    //   9	27	58	finally
    //   27	47	58	finally
    //   51	55	58	finally
    //   64	67	58	finally
    //   27	47	63	java/lang/OutOfMemoryError
  }
  
  /* Error */
  public boolean b(b paramb)
  {
    // Byte code:
    //   0: aload_0
    //   1: monitorenter
    //   2: aload_0
    //   3: getfield 14	com/gau/go/launcherex/gowidget/messagecenter/util/a:a	Ljava/util/ArrayList;
    //   6: astore_3
    //   7: aload_3
    //   8: ifnonnull +9 -> 17
    //   11: iconst_0
    //   12: istore_2
    //   13: aload_0
    //   14: monitorexit
    //   15: iload_2
    //   16: ireturn
    //   17: aload_0
    //   18: getfield 14	com/gau/go/launcherex/gowidget/messagecenter/util/a:a	Ljava/util/ArrayList;
    //   21: aload_1
    //   22: invokevirtual 54	java/util/ArrayList:remove	(Ljava/lang/Object;)Z
    //   25: istore_2
    //   26: goto -13 -> 13
    //   29: astore_1
    //   30: aload_0
    //   31: monitorexit
    //   32: aload_1
    //   33: athrow
    // Local variable table:
    //   start	length	slot	name	signature
    //   0	34	0	this	a
    //   0	34	1	paramb	b
    //   12	14	2	bool	boolean
    //   6	2	3	localArrayList	ArrayList
    // Exception table:
    //   from	to	target	type
    //   2	7	29	finally
    //   17	26	29	finally
  }
}


/* Location:              /Users/amaurremi/uw/stringoid/static-dynamic-comparison/apps/go weather ex/com.gau.go.launcherex.gowidget.weatherwidget-124-dex2jar.jar!/com/gau/go/launcherex/gowidget/messagecenter/util/a.class
 * Java compiler version: 6 (50.0)
 * JD-Core Version:       0.7.1
 */