package com.badlogic.gdx.graphics;

class o
{
  private static final byte[] a = new byte['紀'];
  private static final byte[] b = new byte['紀'];
  
  /* Error */
  public static k a(com.badlogic.gdx.c.a parama)
  {
    // Byte code:
    //   0: new 19	java/io/DataInputStream
    //   3: dup
    //   4: new 21	java/util/zip/InflaterInputStream
    //   7: dup
    //   8: new 23	java/io/BufferedInputStream
    //   11: dup
    //   12: aload_0
    //   13: invokevirtual 28	com/badlogic/gdx/c/a:a	()Ljava/io/InputStream;
    //   16: invokespecial 32	java/io/BufferedInputStream:<init>	(Ljava/io/InputStream;)V
    //   19: invokespecial 33	java/util/zip/InflaterInputStream:<init>	(Ljava/io/InputStream;)V
    //   22: invokespecial 34	java/io/DataInputStream:<init>	(Ljava/io/InputStream;)V
    //   25: astore_3
    //   26: aload_3
    //   27: astore_2
    //   28: new 36	com/badlogic/gdx/graphics/k
    //   31: dup
    //   32: aload_3
    //   33: invokevirtual 40	java/io/DataInputStream:readInt	()I
    //   36: aload_3
    //   37: invokevirtual 40	java/io/DataInputStream:readInt	()I
    //   40: aload_3
    //   41: invokevirtual 40	java/io/DataInputStream:readInt	()I
    //   44: invokestatic 45	com/badlogic/gdx/graphics/m:a	(I)Lcom/badlogic/gdx/graphics/m;
    //   47: invokespecial 48	com/badlogic/gdx/graphics/k:<init>	(IILcom/badlogic/gdx/graphics/m;)V
    //   50: astore 5
    //   52: aload_3
    //   53: astore_2
    //   54: aload 5
    //   56: invokevirtual 52	com/badlogic/gdx/graphics/k:h	()Ljava/nio/ByteBuffer;
    //   59: astore 6
    //   61: aload_3
    //   62: astore_2
    //   63: aload 6
    //   65: iconst_0
    //   66: invokevirtual 58	java/nio/ByteBuffer:position	(I)Ljava/nio/Buffer;
    //   69: pop
    //   70: aload_3
    //   71: astore_2
    //   72: aload 6
    //   74: aload 6
    //   76: invokevirtual 61	java/nio/ByteBuffer:capacity	()I
    //   79: invokevirtual 64	java/nio/ByteBuffer:limit	(I)Ljava/nio/Buffer;
    //   82: pop
    //   83: aload_3
    //   84: astore_2
    //   85: getstatic 13	com/badlogic/gdx/graphics/o:b	[B
    //   88: astore 4
    //   90: aload_3
    //   91: astore_2
    //   92: aload 4
    //   94: monitorenter
    //   95: aload_3
    //   96: getstatic 13	com/badlogic/gdx/graphics/o:b	[B
    //   99: invokevirtual 68	java/io/DataInputStream:read	([B)I
    //   102: istore_1
    //   103: iload_1
    //   104: ifle +74 -> 178
    //   107: aload 6
    //   109: getstatic 13	com/badlogic/gdx/graphics/o:b	[B
    //   112: iconst_0
    //   113: iload_1
    //   114: invokevirtual 72	java/nio/ByteBuffer:put	([BII)Ljava/nio/ByteBuffer;
    //   117: pop
    //   118: goto -23 -> 95
    //   121: astore 5
    //   123: aload 4
    //   125: monitorexit
    //   126: aload_3
    //   127: astore_2
    //   128: aload 5
    //   130: athrow
    //   131: astore 4
    //   133: aload_3
    //   134: astore_2
    //   135: aload 4
    //   137: astore_3
    //   138: new 74	com/badlogic/gdx/utils/f
    //   141: dup
    //   142: new 76	java/lang/StringBuilder
    //   145: dup
    //   146: invokespecial 78	java/lang/StringBuilder:<init>	()V
    //   149: ldc 80
    //   151: invokevirtual 84	java/lang/StringBuilder:append	(Ljava/lang/String;)Ljava/lang/StringBuilder;
    //   154: aload_0
    //   155: invokevirtual 87	java/lang/StringBuilder:append	(Ljava/lang/Object;)Ljava/lang/StringBuilder;
    //   158: ldc 89
    //   160: invokevirtual 84	java/lang/StringBuilder:append	(Ljava/lang/String;)Ljava/lang/StringBuilder;
    //   163: invokevirtual 93	java/lang/StringBuilder:toString	()Ljava/lang/String;
    //   166: aload_3
    //   167: invokespecial 96	com/badlogic/gdx/utils/f:<init>	(Ljava/lang/String;Ljava/lang/Throwable;)V
    //   170: athrow
    //   171: astore_0
    //   172: aload_2
    //   173: invokestatic 101	com/badlogic/gdx/utils/s:a	(Ljava/io/Closeable;)V
    //   176: aload_0
    //   177: athrow
    //   178: aload 4
    //   180: monitorexit
    //   181: aload_3
    //   182: astore_2
    //   183: aload 6
    //   185: iconst_0
    //   186: invokevirtual 58	java/nio/ByteBuffer:position	(I)Ljava/nio/Buffer;
    //   189: pop
    //   190: aload_3
    //   191: astore_2
    //   192: aload 6
    //   194: aload 6
    //   196: invokevirtual 61	java/nio/ByteBuffer:capacity	()I
    //   199: invokevirtual 64	java/nio/ByteBuffer:limit	(I)Ljava/nio/Buffer;
    //   202: pop
    //   203: aload_3
    //   204: invokestatic 101	com/badlogic/gdx/utils/s:a	(Ljava/io/Closeable;)V
    //   207: aload 5
    //   209: areturn
    //   210: astore_0
    //   211: aconst_null
    //   212: astore_2
    //   213: goto -41 -> 172
    //   216: astore_3
    //   217: aconst_null
    //   218: astore_2
    //   219: goto -81 -> 138
    // Local variable table:
    //   start	length	slot	name	signature
    //   0	222	0	parama	com.badlogic.gdx.c.a
    //   102	12	1	i	int
    //   27	192	2	localObject1	Object
    //   25	179	3	localObject2	Object
    //   216	1	3	localException1	Exception
    //   88	36	4	arrayOfByte	byte[]
    //   131	48	4	localException2	Exception
    //   50	5	5	localk1	k
    //   121	87	5	localk2	k
    //   59	136	6	localByteBuffer	java.nio.ByteBuffer
    // Exception table:
    //   from	to	target	type
    //   95	103	121	finally
    //   107	118	121	finally
    //   123	126	121	finally
    //   178	181	121	finally
    //   28	52	131	java/lang/Exception
    //   54	61	131	java/lang/Exception
    //   63	70	131	java/lang/Exception
    //   72	83	131	java/lang/Exception
    //   85	90	131	java/lang/Exception
    //   92	95	131	java/lang/Exception
    //   128	131	131	java/lang/Exception
    //   183	190	131	java/lang/Exception
    //   192	203	131	java/lang/Exception
    //   28	52	171	finally
    //   54	61	171	finally
    //   63	70	171	finally
    //   72	83	171	finally
    //   85	90	171	finally
    //   92	95	171	finally
    //   128	131	171	finally
    //   138	171	171	finally
    //   183	190	171	finally
    //   192	203	171	finally
    //   0	26	210	finally
    //   0	26	216	java/lang/Exception
  }
}


/* Location:              /Users/amaurremi/uw/stringoid/static-dynamic-comparison/apps/xperia z/com.androidwasabi.livewallpaper.xperiaz-13-dex2jar.jar!/com/badlogic/gdx/graphics/o.class
 * Java compiler version: 6 (50.0)
 * JD-Core Version:       0.7.1
 */