package com.gau.go.launcherex.gowidget.weather.provider;

public class b
{
  /* Error */
  public static java.util.List a(android.content.Context paramContext, String paramString)
  {
    // Byte code:
    //   0: aconst_null
    //   1: astore_3
    //   2: aconst_null
    //   3: astore 4
    //   5: aconst_null
    //   6: astore 7
    //   8: aconst_null
    //   9: astore 5
    //   11: aconst_null
    //   12: astore 6
    //   14: new 10	java/util/ArrayList
    //   17: dup
    //   18: invokespecial 14	java/util/ArrayList:<init>	()V
    //   21: astore 8
    //   23: aload_0
    //   24: ldc 16
    //   26: ldc 17
    //   28: invokestatic 23	com/gau/go/launcherex/gowidget/weather/util/r:b	(Landroid/content/Context;Ljava/lang/String;I)Landroid/database/sqlite/SQLiteDatabase;
    //   31: astore_0
    //   32: aload_0
    //   33: astore_3
    //   34: aload_3
    //   35: ifnull +455 -> 490
    //   38: aload_3
    //   39: astore 4
    //   41: aload 7
    //   43: astore_0
    //   44: aload_3
    //   45: ldc 25
    //   47: iconst_1
    //   48: anewarray 27	java/lang/String
    //   51: dup
    //   52: iconst_0
    //   53: new 29	java/lang/StringBuilder
    //   56: dup
    //   57: invokespecial 30	java/lang/StringBuilder:<init>	()V
    //   60: aload_1
    //   61: invokevirtual 34	java/lang/StringBuilder:append	(Ljava/lang/String;)Ljava/lang/StringBuilder;
    //   64: ldc 36
    //   66: invokevirtual 34	java/lang/StringBuilder:append	(Ljava/lang/String;)Ljava/lang/StringBuilder;
    //   69: invokevirtual 40	java/lang/StringBuilder:toString	()Ljava/lang/String;
    //   72: aastore
    //   73: invokevirtual 46	android/database/sqlite/SQLiteDatabase:rawQuery	(Ljava/lang/String;[Ljava/lang/String;)Landroid/database/Cursor;
    //   76: astore_1
    //   77: aload_1
    //   78: astore 6
    //   80: aload_1
    //   81: ifnull +409 -> 490
    //   84: aload_1
    //   85: astore 6
    //   87: aload_3
    //   88: astore 4
    //   90: aload_1
    //   91: astore_0
    //   92: aload_1
    //   93: astore 5
    //   95: aload_1
    //   96: invokeinterface 52 1 0
    //   101: ifeq +389 -> 490
    //   104: aload_3
    //   105: astore 4
    //   107: aload_1
    //   108: astore_0
    //   109: aload_1
    //   110: astore 5
    //   112: new 54	com/gau/go/launcherex/gowidget/weather/model/b
    //   115: dup
    //   116: invokespecial 55	com/gau/go/launcherex/gowidget/weather/model/b:<init>	()V
    //   119: astore 6
    //   121: aload_3
    //   122: astore 4
    //   124: aload_1
    //   125: astore_0
    //   126: aload_1
    //   127: astore 5
    //   129: aload 6
    //   131: aload_1
    //   132: aload_1
    //   133: ldc 16
    //   135: invokeinterface 59 2 0
    //   140: invokeinterface 63 2 0
    //   145: invokevirtual 66	com/gau/go/launcherex/gowidget/weather/model/b:b	(Ljava/lang/String;)V
    //   148: aload_3
    //   149: astore 4
    //   151: aload_1
    //   152: astore_0
    //   153: aload_1
    //   154: astore 5
    //   156: aload 6
    //   158: aload_1
    //   159: aload_1
    //   160: ldc 68
    //   162: invokeinterface 59 2 0
    //   167: invokeinterface 63 2 0
    //   172: invokevirtual 70	com/gau/go/launcherex/gowidget/weather/model/b:a	(Ljava/lang/String;)V
    //   175: aload_3
    //   176: astore 4
    //   178: aload_1
    //   179: astore_0
    //   180: aload_1
    //   181: astore 5
    //   183: aload 6
    //   185: aload_1
    //   186: aload_1
    //   187: ldc 72
    //   189: invokeinterface 59 2 0
    //   194: invokeinterface 63 2 0
    //   199: invokevirtual 75	com/gau/go/launcherex/gowidget/weather/model/b:d	(Ljava/lang/String;)V
    //   202: aload_3
    //   203: astore 4
    //   205: aload_1
    //   206: astore_0
    //   207: aload_1
    //   208: astore 5
    //   210: aload 6
    //   212: aload_1
    //   213: aload_1
    //   214: ldc 77
    //   216: invokeinterface 59 2 0
    //   221: invokeinterface 63 2 0
    //   226: invokevirtual 80	com/gau/go/launcherex/gowidget/weather/model/b:c	(Ljava/lang/String;)V
    //   229: aload_3
    //   230: astore 4
    //   232: aload_1
    //   233: astore_0
    //   234: aload_1
    //   235: astore 5
    //   237: aload 6
    //   239: aload_1
    //   240: aload_1
    //   241: ldc 82
    //   243: invokeinterface 59 2 0
    //   248: invokeinterface 63 2 0
    //   253: invokevirtual 85	com/gau/go/launcherex/gowidget/weather/model/b:e	(Ljava/lang/String;)V
    //   256: aload_3
    //   257: astore 4
    //   259: aload_1
    //   260: astore_0
    //   261: aload_1
    //   262: astore 5
    //   264: new 29	java/lang/StringBuilder
    //   267: dup
    //   268: invokespecial 30	java/lang/StringBuilder:<init>	()V
    //   271: astore 7
    //   273: aload_3
    //   274: astore 4
    //   276: aload_1
    //   277: astore_0
    //   278: aload_1
    //   279: astore 5
    //   281: aload 7
    //   283: aload 6
    //   285: invokevirtual 87	com/gau/go/launcherex/gowidget/weather/model/b:b	()Ljava/lang/String;
    //   288: invokevirtual 34	java/lang/StringBuilder:append	(Ljava/lang/String;)Ljava/lang/StringBuilder;
    //   291: pop
    //   292: aload_3
    //   293: astore 4
    //   295: aload_1
    //   296: astore_0
    //   297: aload_1
    //   298: astore 5
    //   300: aload 6
    //   302: invokevirtual 89	com/gau/go/launcherex/gowidget/weather/model/b:d	()Ljava/lang/String;
    //   305: invokestatic 95	android/text/TextUtils:isEmpty	(Ljava/lang/CharSequence;)Z
    //   308: ifne +38 -> 346
    //   311: aload_3
    //   312: astore 4
    //   314: aload_1
    //   315: astore_0
    //   316: aload_1
    //   317: astore 5
    //   319: aload 7
    //   321: ldc 97
    //   323: invokevirtual 34	java/lang/StringBuilder:append	(Ljava/lang/String;)Ljava/lang/StringBuilder;
    //   326: pop
    //   327: aload_3
    //   328: astore 4
    //   330: aload_1
    //   331: astore_0
    //   332: aload_1
    //   333: astore 5
    //   335: aload 7
    //   337: aload 6
    //   339: invokevirtual 89	com/gau/go/launcherex/gowidget/weather/model/b:d	()Ljava/lang/String;
    //   342: invokevirtual 34	java/lang/StringBuilder:append	(Ljava/lang/String;)Ljava/lang/StringBuilder;
    //   345: pop
    //   346: aload_3
    //   347: astore 4
    //   349: aload_1
    //   350: astore_0
    //   351: aload_1
    //   352: astore 5
    //   354: aload 6
    //   356: invokevirtual 99	com/gau/go/launcherex/gowidget/weather/model/b:c	()Ljava/lang/String;
    //   359: invokestatic 95	android/text/TextUtils:isEmpty	(Ljava/lang/CharSequence;)Z
    //   362: ifne +70 -> 432
    //   365: aload_3
    //   366: astore 4
    //   368: aload_1
    //   369: astore_0
    //   370: aload_1
    //   371: astore 5
    //   373: aload 7
    //   375: ldc 97
    //   377: invokevirtual 34	java/lang/StringBuilder:append	(Ljava/lang/String;)Ljava/lang/StringBuilder;
    //   380: pop
    //   381: aload_3
    //   382: astore 4
    //   384: aload_1
    //   385: astore_0
    //   386: aload_1
    //   387: astore 5
    //   389: aload 7
    //   391: ldc 101
    //   393: invokevirtual 34	java/lang/StringBuilder:append	(Ljava/lang/String;)Ljava/lang/StringBuilder;
    //   396: pop
    //   397: aload_3
    //   398: astore 4
    //   400: aload_1
    //   401: astore_0
    //   402: aload_1
    //   403: astore 5
    //   405: aload 7
    //   407: aload 6
    //   409: invokevirtual 99	com/gau/go/launcherex/gowidget/weather/model/b:c	()Ljava/lang/String;
    //   412: invokevirtual 34	java/lang/StringBuilder:append	(Ljava/lang/String;)Ljava/lang/StringBuilder;
    //   415: pop
    //   416: aload_3
    //   417: astore 4
    //   419: aload_1
    //   420: astore_0
    //   421: aload_1
    //   422: astore 5
    //   424: aload 7
    //   426: ldc 103
    //   428: invokevirtual 34	java/lang/StringBuilder:append	(Ljava/lang/String;)Ljava/lang/StringBuilder;
    //   431: pop
    //   432: aload_3
    //   433: astore 4
    //   435: aload_1
    //   436: astore_0
    //   437: aload_1
    //   438: astore 5
    //   440: aload 6
    //   442: aload 7
    //   444: invokevirtual 40	java/lang/StringBuilder:toString	()Ljava/lang/String;
    //   447: invokevirtual 106	com/gau/go/launcherex/gowidget/weather/model/b:f	(Ljava/lang/String;)V
    //   450: aload_3
    //   451: astore 4
    //   453: aload_1
    //   454: astore_0
    //   455: aload_1
    //   456: astore 5
    //   458: aload 8
    //   460: aload 6
    //   462: invokeinterface 112 2 0
    //   467: pop
    //   468: aload_3
    //   469: astore 4
    //   471: aload_1
    //   472: astore_0
    //   473: aload_1
    //   474: astore 5
    //   476: aload_1
    //   477: invokeinterface 115 1 0
    //   482: istore_2
    //   483: iload_2
    //   484: ifne -380 -> 104
    //   487: aload_1
    //   488: astore 6
    //   490: aload 6
    //   492: ifnull +10 -> 502
    //   495: aload 6
    //   497: invokeinterface 118 1 0
    //   502: aload_3
    //   503: ifnull +14 -> 517
    //   506: aload_3
    //   507: invokevirtual 121	android/database/sqlite/SQLiteDatabase:isOpen	()Z
    //   510: ifeq +7 -> 517
    //   513: aload_3
    //   514: invokevirtual 122	android/database/sqlite/SQLiteDatabase:close	()V
    //   517: aload 8
    //   519: areturn
    //   520: astore_1
    //   521: aconst_null
    //   522: astore_0
    //   523: aload_3
    //   524: astore 5
    //   526: aload_0
    //   527: astore_3
    //   528: aload_3
    //   529: astore 4
    //   531: aload 5
    //   533: astore_0
    //   534: aload_1
    //   535: invokevirtual 125	java/lang/Exception:printStackTrace	()V
    //   538: aload 5
    //   540: ifnull +10 -> 550
    //   543: aload 5
    //   545: invokeinterface 118 1 0
    //   550: aload_3
    //   551: ifnull -34 -> 517
    //   554: aload_3
    //   555: invokevirtual 121	android/database/sqlite/SQLiteDatabase:isOpen	()Z
    //   558: ifeq -41 -> 517
    //   561: goto -48 -> 513
    //   564: astore_1
    //   565: aconst_null
    //   566: astore_3
    //   567: aload 4
    //   569: astore_0
    //   570: aload_3
    //   571: astore 4
    //   573: aload_0
    //   574: ifnull +9 -> 583
    //   577: aload_0
    //   578: invokeinterface 118 1 0
    //   583: aload 4
    //   585: ifnull +16 -> 601
    //   588: aload 4
    //   590: invokevirtual 121	android/database/sqlite/SQLiteDatabase:isOpen	()Z
    //   593: ifeq +8 -> 601
    //   596: aload 4
    //   598: invokevirtual 122	android/database/sqlite/SQLiteDatabase:close	()V
    //   601: aload_1
    //   602: athrow
    //   603: astore_1
    //   604: goto -31 -> 573
    //   607: astore_1
    //   608: goto -80 -> 528
    // Local variable table:
    //   start	length	slot	name	signature
    //   0	611	0	paramContext	android.content.Context
    //   0	611	1	paramString	String
    //   482	2	2	bool	boolean
    //   1	570	3	localContext1	android.content.Context
    //   3	594	4	localContext2	android.content.Context
    //   9	535	5	localObject1	Object
    //   12	484	6	localObject2	Object
    //   6	437	7	localStringBuilder	StringBuilder
    //   21	497	8	localArrayList	java.util.ArrayList
    // Exception table:
    //   from	to	target	type
    //   23	32	520	java/lang/Exception
    //   23	32	564	finally
    //   44	77	603	finally
    //   95	104	603	finally
    //   112	121	603	finally
    //   129	148	603	finally
    //   156	175	603	finally
    //   183	202	603	finally
    //   210	229	603	finally
    //   237	256	603	finally
    //   264	273	603	finally
    //   281	292	603	finally
    //   300	311	603	finally
    //   319	327	603	finally
    //   335	346	603	finally
    //   354	365	603	finally
    //   373	381	603	finally
    //   389	397	603	finally
    //   405	416	603	finally
    //   424	432	603	finally
    //   440	450	603	finally
    //   458	468	603	finally
    //   476	483	603	finally
    //   534	538	603	finally
    //   44	77	607	java/lang/Exception
    //   95	104	607	java/lang/Exception
    //   112	121	607	java/lang/Exception
    //   129	148	607	java/lang/Exception
    //   156	175	607	java/lang/Exception
    //   183	202	607	java/lang/Exception
    //   210	229	607	java/lang/Exception
    //   237	256	607	java/lang/Exception
    //   264	273	607	java/lang/Exception
    //   281	292	607	java/lang/Exception
    //   300	311	607	java/lang/Exception
    //   319	327	607	java/lang/Exception
    //   335	346	607	java/lang/Exception
    //   354	365	607	java/lang/Exception
    //   373	381	607	java/lang/Exception
    //   389	397	607	java/lang/Exception
    //   405	416	607	java/lang/Exception
    //   424	432	607	java/lang/Exception
    //   440	450	607	java/lang/Exception
    //   458	468	607	java/lang/Exception
    //   476	483	607	java/lang/Exception
  }
}


/* Location:              /Users/amaurremi/uw/stringoid/static-dynamic-comparison/apps/go weather ex/com.gau.go.launcherex.gowidget.weatherwidget-124-dex2jar.jar!/com/gau/go/launcherex/gowidget/weather/provider/b.class
 * Java compiler version: 6 (50.0)
 * JD-Core Version:       0.7.1
 */