package com.google.analytics.containertag.proto;

import com.google.analytics.midtier.proto.containertag.TypeSystem.Value;
import com.google.tagmanager.protobuf.CodedOutputStream;
import com.google.tagmanager.protobuf.GeneratedMessageLite;
import com.google.tagmanager.protobuf.GeneratedMessageLite.a;
import com.google.tagmanager.protobuf.c;
import com.google.tagmanager.protobuf.e;
import com.google.tagmanager.protobuf.f;
import com.google.tagmanager.protobuf.g;
import com.google.tagmanager.protobuf.i;
import com.google.tagmanager.protobuf.i.a;
import com.google.tagmanager.protobuf.i.b;
import com.google.tagmanager.protobuf.k;
import com.google.tagmanager.protobuf.l;
import com.google.tagmanager.protobuf.n;
import com.google.tagmanager.protobuf.o;
import com.google.tagmanager.protobuf.p;
import com.google.tagmanager.protobuf.q;
import com.google.tagmanager.protobuf.t;
import java.util.ArrayList;
import java.util.Collections;
import java.util.List;

public final class Serving
{
  public static final class CacheOption
    extends GeneratedMessageLite
    implements Serving.a
  {
    private static final CacheOption gV;
    public static q<CacheOption> gW = new c()
    {
      public Serving.CacheOption a(f paramAnonymousf, g paramAnonymousg)
      {
        return new Serving.CacheOption(paramAnonymousf, paramAnonymousg, null);
      }
    };
    private static volatile p gX = null;
    private static final long serialVersionUID = 0L;
    private int bitField0_;
    private int expirationSeconds_;
    private int gcacheExpirationSeconds_;
    private CacheLevel level_;
    private byte memoizedIsInitialized = -1;
    private int memoizedSerializedSize = -1;
    private final e unknownFields;
    
    static
    {
      gV = new CacheOption(true);
      gV.fH();
    }
    
    private CacheOption(GeneratedMessageLite.a parama)
    {
      super();
      this.unknownFields = parama.BE();
    }
    
    /* Error */
    private CacheOption(f paramf, g paramg)
    {
      // Byte code:
      //   0: aload_0
      //   1: invokespecial 82	com/google/tagmanager/protobuf/GeneratedMessageLite:<init>	()V
      //   4: aload_0
      //   5: iconst_m1
      //   6: putfield 64	com/google/analytics/containertag/proto/Serving$CacheOption:memoizedIsInitialized	B
      //   9: aload_0
      //   10: iconst_m1
      //   11: putfield 66	com/google/analytics/containertag/proto/Serving$CacheOption:memoizedSerializedSize	I
      //   14: aload_0
      //   15: invokespecial 58	com/google/analytics/containertag/proto/Serving$CacheOption:fH	()V
      //   18: invokestatic 88	com/google/tagmanager/protobuf/e:AN	()Lcom/google/tagmanager/protobuf/e$b;
      //   21: astore 6
      //   23: aload 6
      //   25: invokestatic 93	com/google/tagmanager/protobuf/CodedOutputStream:a	(Ljava/io/OutputStream;)Lcom/google/tagmanager/protobuf/CodedOutputStream;
      //   28: astore 7
      //   30: iconst_0
      //   31: istore_3
      //   32: iload_3
      //   33: ifne +214 -> 247
      //   36: aload_1
      //   37: invokevirtual 99	com/google/tagmanager/protobuf/f:AT	()I
      //   40: istore 4
      //   42: iload 4
      //   44: lookupswitch	default:+272->316, 0:+275->319, 8:+62->106, 16:+161->205, 24:+182->226
      //   88: aload_0
      //   89: aload_1
      //   90: aload 7
      //   92: aload_2
      //   93: iload 4
      //   95: invokevirtual 102	com/google/analytics/containertag/proto/Serving$CacheOption:a	(Lcom/google/tagmanager/protobuf/f;Lcom/google/tagmanager/protobuf/CodedOutputStream;Lcom/google/tagmanager/protobuf/g;I)Z
      //   98: ifne -66 -> 32
      //   101: iconst_1
      //   102: istore_3
      //   103: goto -71 -> 32
      //   106: aload_1
      //   107: invokevirtual 105	com/google/tagmanager/protobuf/f:Bd	()I
      //   110: istore 5
      //   112: iload 5
      //   114: invokestatic 109	com/google/analytics/containertag/proto/Serving$CacheOption$CacheLevel:aC	(I)Lcom/google/analytics/containertag/proto/Serving$CacheOption$CacheLevel;
      //   117: astore 8
      //   119: aload 8
      //   121: ifnonnull +48 -> 169
      //   124: aload 7
      //   126: iload 4
      //   128: invokevirtual 113	com/google/tagmanager/protobuf/CodedOutputStream:fn	(I)V
      //   131: aload 7
      //   133: iload 5
      //   135: invokevirtual 113	com/google/tagmanager/protobuf/CodedOutputStream:fn	(I)V
      //   138: goto -106 -> 32
      //   141: astore_1
      //   142: aload_1
      //   143: aload_0
      //   144: invokevirtual 117	com/google/tagmanager/protobuf/InvalidProtocolBufferException:h	(Lcom/google/tagmanager/protobuf/n;)Lcom/google/tagmanager/protobuf/InvalidProtocolBufferException;
      //   147: athrow
      //   148: astore_1
      //   149: aload 7
      //   151: invokevirtual 120	com/google/tagmanager/protobuf/CodedOutputStream:flush	()V
      //   154: aload_0
      //   155: aload 6
      //   157: invokevirtual 125	com/google/tagmanager/protobuf/e$b:AR	()Lcom/google/tagmanager/protobuf/e;
      //   160: putfield 74	com/google/analytics/containertag/proto/Serving$CacheOption:unknownFields	Lcom/google/tagmanager/protobuf/e;
      //   163: aload_0
      //   164: invokevirtual 128	com/google/analytics/containertag/proto/Serving$CacheOption:BD	()V
      //   167: aload_1
      //   168: athrow
      //   169: aload_0
      //   170: aload_0
      //   171: getfield 130	com/google/analytics/containertag/proto/Serving$CacheOption:bitField0_	I
      //   174: iconst_1
      //   175: ior
      //   176: putfield 130	com/google/analytics/containertag/proto/Serving$CacheOption:bitField0_	I
      //   179: aload_0
      //   180: aload 8
      //   182: putfield 132	com/google/analytics/containertag/proto/Serving$CacheOption:level_	Lcom/google/analytics/containertag/proto/Serving$CacheOption$CacheLevel;
      //   185: goto -153 -> 32
      //   188: astore_1
      //   189: new 79	com/google/tagmanager/protobuf/InvalidProtocolBufferException
      //   192: dup
      //   193: aload_1
      //   194: invokevirtual 136	java/io/IOException:getMessage	()Ljava/lang/String;
      //   197: invokespecial 139	com/google/tagmanager/protobuf/InvalidProtocolBufferException:<init>	(Ljava/lang/String;)V
      //   200: aload_0
      //   201: invokevirtual 117	com/google/tagmanager/protobuf/InvalidProtocolBufferException:h	(Lcom/google/tagmanager/protobuf/n;)Lcom/google/tagmanager/protobuf/InvalidProtocolBufferException;
      //   204: athrow
      //   205: aload_0
      //   206: aload_0
      //   207: getfield 130	com/google/analytics/containertag/proto/Serving$CacheOption:bitField0_	I
      //   210: iconst_2
      //   211: ior
      //   212: putfield 130	com/google/analytics/containertag/proto/Serving$CacheOption:bitField0_	I
      //   215: aload_0
      //   216: aload_1
      //   217: invokevirtual 142	com/google/tagmanager/protobuf/f:AW	()I
      //   220: putfield 144	com/google/analytics/containertag/proto/Serving$CacheOption:expirationSeconds_	I
      //   223: goto -191 -> 32
      //   226: aload_0
      //   227: aload_0
      //   228: getfield 130	com/google/analytics/containertag/proto/Serving$CacheOption:bitField0_	I
      //   231: iconst_4
      //   232: ior
      //   233: putfield 130	com/google/analytics/containertag/proto/Serving$CacheOption:bitField0_	I
      //   236: aload_0
      //   237: aload_1
      //   238: invokevirtual 142	com/google/tagmanager/protobuf/f:AW	()I
      //   241: putfield 146	com/google/analytics/containertag/proto/Serving$CacheOption:gcacheExpirationSeconds_	I
      //   244: goto -212 -> 32
      //   247: aload 7
      //   249: invokevirtual 120	com/google/tagmanager/protobuf/CodedOutputStream:flush	()V
      //   252: aload_0
      //   253: aload 6
      //   255: invokevirtual 125	com/google/tagmanager/protobuf/e$b:AR	()Lcom/google/tagmanager/protobuf/e;
      //   258: putfield 74	com/google/analytics/containertag/proto/Serving$CacheOption:unknownFields	Lcom/google/tagmanager/protobuf/e;
      //   261: aload_0
      //   262: invokevirtual 128	com/google/analytics/containertag/proto/Serving$CacheOption:BD	()V
      //   265: return
      //   266: astore_1
      //   267: aload_0
      //   268: aload 6
      //   270: invokevirtual 125	com/google/tagmanager/protobuf/e$b:AR	()Lcom/google/tagmanager/protobuf/e;
      //   273: putfield 74	com/google/analytics/containertag/proto/Serving$CacheOption:unknownFields	Lcom/google/tagmanager/protobuf/e;
      //   276: goto -15 -> 261
      //   279: astore_1
      //   280: aload_0
      //   281: aload 6
      //   283: invokevirtual 125	com/google/tagmanager/protobuf/e$b:AR	()Lcom/google/tagmanager/protobuf/e;
      //   286: putfield 74	com/google/analytics/containertag/proto/Serving$CacheOption:unknownFields	Lcom/google/tagmanager/protobuf/e;
      //   289: aload_1
      //   290: athrow
      //   291: astore_2
      //   292: aload_0
      //   293: aload 6
      //   295: invokevirtual 125	com/google/tagmanager/protobuf/e$b:AR	()Lcom/google/tagmanager/protobuf/e;
      //   298: putfield 74	com/google/analytics/containertag/proto/Serving$CacheOption:unknownFields	Lcom/google/tagmanager/protobuf/e;
      //   301: goto -138 -> 163
      //   304: astore_1
      //   305: aload_0
      //   306: aload 6
      //   308: invokevirtual 125	com/google/tagmanager/protobuf/e$b:AR	()Lcom/google/tagmanager/protobuf/e;
      //   311: putfield 74	com/google/analytics/containertag/proto/Serving$CacheOption:unknownFields	Lcom/google/tagmanager/protobuf/e;
      //   314: aload_1
      //   315: athrow
      //   316: goto -228 -> 88
      //   319: iconst_1
      //   320: istore_3
      //   321: goto -289 -> 32
      // Local variable table:
      //   start	length	slot	name	signature
      //   0	324	0	this	CacheOption
      //   0	324	1	paramf	f
      //   0	324	2	paramg	g
      //   31	290	3	i	int
      //   40	87	4	j	int
      //   110	24	5	k	int
      //   21	286	6	localb	com.google.tagmanager.protobuf.e.b
      //   28	220	7	localCodedOutputStream	CodedOutputStream
      //   117	64	8	localCacheLevel	CacheLevel
      // Exception table:
      //   from	to	target	type
      //   36	42	141	com/google/tagmanager/protobuf/InvalidProtocolBufferException
      //   88	101	141	com/google/tagmanager/protobuf/InvalidProtocolBufferException
      //   106	119	141	com/google/tagmanager/protobuf/InvalidProtocolBufferException
      //   124	138	141	com/google/tagmanager/protobuf/InvalidProtocolBufferException
      //   169	185	141	com/google/tagmanager/protobuf/InvalidProtocolBufferException
      //   205	223	141	com/google/tagmanager/protobuf/InvalidProtocolBufferException
      //   226	244	141	com/google/tagmanager/protobuf/InvalidProtocolBufferException
      //   36	42	148	finally
      //   88	101	148	finally
      //   106	119	148	finally
      //   124	138	148	finally
      //   142	148	148	finally
      //   169	185	148	finally
      //   189	205	148	finally
      //   205	223	148	finally
      //   226	244	148	finally
      //   36	42	188	java/io/IOException
      //   88	101	188	java/io/IOException
      //   106	119	188	java/io/IOException
      //   124	138	188	java/io/IOException
      //   169	185	188	java/io/IOException
      //   205	223	188	java/io/IOException
      //   226	244	188	java/io/IOException
      //   247	252	266	java/io/IOException
      //   247	252	279	finally
      //   149	154	291	java/io/IOException
      //   149	154	304	finally
    }
    
    private CacheOption(boolean paramBoolean)
    {
      this.unknownFields = e.ajf;
    }
    
    public static a a(CacheOption paramCacheOption)
    {
      return fJ().c(paramCacheOption);
    }
    
    private void fH()
    {
      this.level_ = CacheLevel.gY;
      this.expirationSeconds_ = 0;
      this.gcacheExpirationSeconds_ = 0;
    }
    
    public static a fJ()
    {
      return a.fZ();
    }
    
    public static CacheOption fy()
    {
      return gV;
    }
    
    public void a(CodedOutputStream paramCodedOutputStream)
    {
      fI();
      if ((this.bitField0_ & 0x1) == 1) {
        paramCodedOutputStream.y(1, this.level_.ga());
      }
      if ((this.bitField0_ & 0x2) == 2) {
        paramCodedOutputStream.w(2, this.expirationSeconds_);
      }
      if ((this.bitField0_ & 0x4) == 4) {
        paramCodedOutputStream.w(3, this.gcacheExpirationSeconds_);
      }
      paramCodedOutputStream.d(this.unknownFields);
    }
    
    public boolean equals(Object paramObject)
    {
      if (paramObject == this) {
        return true;
      }
      if (!(paramObject instanceof CacheOption)) {
        return super.equals(paramObject);
      }
      paramObject = (CacheOption)paramObject;
      int i;
      label38:
      int j;
      if (fB() == ((CacheOption)paramObject).fB())
      {
        i = 1;
        j = i;
        if (fB())
        {
          if ((i == 0) || (fC() != ((CacheOption)paramObject).fC())) {
            break label155;
          }
          j = 1;
        }
        label64:
        if ((j == 0) || (fD() != ((CacheOption)paramObject).fD())) {
          break label160;
        }
        i = 1;
        label81:
        j = i;
        if (fD())
        {
          if ((i == 0) || (fE() != ((CacheOption)paramObject).fE())) {
            break label165;
          }
          j = 1;
        }
        label107:
        if ((j == 0) || (fF() != ((CacheOption)paramObject).fF())) {
          break label170;
        }
      }
      label155:
      label160:
      label165:
      label170:
      for (boolean bool = true;; bool = false)
      {
        if (!fF()) {
          break label176;
        }
        if ((bool) && (fG() == ((CacheOption)paramObject).fG())) {
          break;
        }
        return false;
        i = 0;
        break label38;
        j = 0;
        break label64;
        i = 0;
        break label81;
        j = 0;
        break label107;
      }
      label176:
      return bool;
    }
    
    public q<CacheOption> fA()
    {
      return gW;
    }
    
    public boolean fB()
    {
      return (this.bitField0_ & 0x1) == 1;
    }
    
    public CacheLevel fC()
    {
      return this.level_;
    }
    
    public boolean fD()
    {
      return (this.bitField0_ & 0x2) == 2;
    }
    
    public int fE()
    {
      return this.expirationSeconds_;
    }
    
    public boolean fF()
    {
      return (this.bitField0_ & 0x4) == 4;
    }
    
    public int fG()
    {
      return this.gcacheExpirationSeconds_;
    }
    
    public int fI()
    {
      int i = this.memoizedSerializedSize;
      if (i != -1) {
        return i;
      }
      int j = 0;
      if ((this.bitField0_ & 0x1) == 1) {
        j = 0 + CodedOutputStream.A(1, this.level_.ga());
      }
      i = j;
      if ((this.bitField0_ & 0x2) == 2) {
        i = j + CodedOutputStream.z(2, this.expirationSeconds_);
      }
      j = i;
      if ((this.bitField0_ & 0x4) == 4) {
        j = i + CodedOutputStream.z(3, this.gcacheExpirationSeconds_);
      }
      i = j + this.unknownFields.size();
      this.memoizedSerializedSize = i;
      return i;
    }
    
    public a fK()
    {
      return fJ();
    }
    
    public a fL()
    {
      return a(this);
    }
    
    public CacheOption fz()
    {
      return gV;
    }
    
    public int hashCode()
    {
      if (this.memoizedHashCode != 0) {
        return this.memoizedHashCode;
      }
      int j = CacheOption.class.hashCode() + 779;
      int i = j;
      if (fB()) {
        i = (j * 37 + 1) * 53 + i.a(fC());
      }
      j = i;
      if (fD()) {
        j = (i * 37 + 2) * 53 + fE();
      }
      i = j;
      if (fF()) {
        i = (j * 37 + 3) * 53 + fG();
      }
      i = i * 29 + this.unknownFields.hashCode();
      this.memoizedHashCode = i;
      return i;
    }
    
    public final boolean isInitialized()
    {
      int i = this.memoizedIsInitialized;
      if (i != -1) {
        return i == 1;
      }
      this.memoizedIsInitialized = 1;
      return true;
    }
    
    protected Object writeReplace()
    {
      return super.writeReplace();
    }
    
    public static enum CacheLevel
      implements i.a
    {
      private static i.b<CacheLevel> hb = new i.b()
      {
        public Serving.CacheOption.CacheLevel aD(int paramAnonymousInt)
        {
          return Serving.CacheOption.CacheLevel.aC(paramAnonymousInt);
        }
      };
      private final int value;
      
      private CacheLevel(int paramInt1, int paramInt2)
      {
        this.value = paramInt2;
      }
      
      public static CacheLevel aC(int paramInt)
      {
        switch (paramInt)
        {
        default: 
          return null;
        case 1: 
          return gY;
        case 2: 
          return gZ;
        }
        return ha;
      }
      
      public final int ga()
      {
        return this.value;
      }
    }
    
    public static final class a
      extends GeneratedMessageLite.a<Serving.CacheOption, a>
      implements Serving.a
    {
      private int bitField0_;
      private int expirationSeconds_;
      private int gcacheExpirationSeconds_;
      private Serving.CacheOption.CacheLevel level_ = Serving.CacheOption.CacheLevel.gY;
      
      private a()
      {
        fP();
      }
      
      private void fP() {}
      
      private static a fQ()
      {
        return new a();
      }
      
      public a a(Serving.CacheOption.CacheLevel paramCacheLevel)
      {
        if (paramCacheLevel == null) {
          throw new NullPointerException();
        }
        this.bitField0_ |= 0x1;
        this.level_ = paramCacheLevel;
        return this;
      }
      
      public a aA(int paramInt)
      {
        this.bitField0_ |= 0x2;
        this.expirationSeconds_ = paramInt;
        return this;
      }
      
      public a aB(int paramInt)
      {
        this.bitField0_ |= 0x4;
        this.gcacheExpirationSeconds_ = paramInt;
        return this;
      }
      
      public a c(Serving.CacheOption paramCacheOption)
      {
        if (paramCacheOption == Serving.CacheOption.fy()) {
          return this;
        }
        if (paramCacheOption.fB()) {
          a(paramCacheOption.fC());
        }
        if (paramCacheOption.fD()) {
          aA(paramCacheOption.fE());
        }
        if (paramCacheOption.fF()) {
          aB(paramCacheOption.fG());
        }
        e(BE().a(Serving.CacheOption.b(paramCacheOption)));
        return this;
      }
      
      /* Error */
      public a c(f paramf, g paramg)
      {
        // Byte code:
        //   0: getstatic 113	com/google/analytics/containertag/proto/Serving$CacheOption:gW	Lcom/google/tagmanager/protobuf/q;
        //   3: aload_1
        //   4: aload_2
        //   5: invokeinterface 118 3 0
        //   10: checkcast 9	com/google/analytics/containertag/proto/Serving$CacheOption
        //   13: astore_1
        //   14: aload_1
        //   15: ifnull +9 -> 24
        //   18: aload_0
        //   19: aload_1
        //   20: invokevirtual 51	com/google/analytics/containertag/proto/Serving$CacheOption$a:c	(Lcom/google/analytics/containertag/proto/Serving$CacheOption;)Lcom/google/analytics/containertag/proto/Serving$CacheOption$a;
        //   23: pop
        //   24: aload_0
        //   25: areturn
        //   26: astore_2
        //   27: aload_2
        //   28: invokevirtual 122	com/google/tagmanager/protobuf/InvalidProtocolBufferException:BN	()Lcom/google/tagmanager/protobuf/n;
        //   31: checkcast 9	com/google/analytics/containertag/proto/Serving$CacheOption
        //   34: astore_1
        //   35: aload_2
        //   36: athrow
        //   37: astore_2
        //   38: aload_1
        //   39: ifnull +9 -> 48
        //   42: aload_0
        //   43: aload_1
        //   44: invokevirtual 51	com/google/analytics/containertag/proto/Serving$CacheOption$a:c	(Lcom/google/analytics/containertag/proto/Serving$CacheOption;)Lcom/google/analytics/containertag/proto/Serving$CacheOption$a;
        //   47: pop
        //   48: aload_2
        //   49: athrow
        //   50: astore_2
        //   51: aconst_null
        //   52: astore_1
        //   53: goto -15 -> 38
        // Local variable table:
        //   start	length	slot	name	signature
        //   0	56	0	this	a
        //   0	56	1	paramf	f
        //   0	56	2	paramg	g
        // Exception table:
        //   from	to	target	type
        //   0	14	26	com/google/tagmanager/protobuf/InvalidProtocolBufferException
        //   35	37	37	finally
        //   0	14	50	finally
        //   27	35	50	finally
      }
      
      public a fR()
      {
        return fQ().c(fT());
      }
      
      public Serving.CacheOption fS()
      {
        Serving.CacheOption localCacheOption = fT();
        if (!localCacheOption.isInitialized()) {
          throw a(localCacheOption);
        }
        return localCacheOption;
      }
      
      public Serving.CacheOption fT()
      {
        int j = 1;
        Serving.CacheOption localCacheOption = new Serving.CacheOption(this, null);
        int k = this.bitField0_;
        if ((k & 0x1) == 1) {}
        for (;;)
        {
          Serving.CacheOption.a(localCacheOption, this.level_);
          int i = j;
          if ((k & 0x2) == 2) {
            i = j | 0x2;
          }
          Serving.CacheOption.a(localCacheOption, this.expirationSeconds_);
          j = i;
          if ((k & 0x4) == 4) {
            j = i | 0x4;
          }
          Serving.CacheOption.b(localCacheOption, this.gcacheExpirationSeconds_);
          Serving.CacheOption.c(localCacheOption, j);
          return localCacheOption;
          j = 0;
        }
      }
      
      public Serving.CacheOption fz()
      {
        return Serving.CacheOption.fy();
      }
      
      public final boolean isInitialized()
      {
        return true;
      }
    }
  }
  
  public static final class FunctionCall
    extends GeneratedMessageLite
    implements Serving.b
  {
    public static q<FunctionCall> gW = new c()
    {
      public Serving.FunctionCall f(f paramAnonymousf, g paramAnonymousg)
      {
        return new Serving.FunctionCall(paramAnonymousf, paramAnonymousg, null);
      }
    };
    private static volatile p gX = null;
    private static final FunctionCall hd = new FunctionCall(true);
    private static final long serialVersionUID = 0L;
    private int bitField0_;
    private int function_;
    private boolean liveOnly_;
    private byte memoizedIsInitialized = -1;
    private int memoizedSerializedSize = -1;
    private int name_;
    private List<Integer> property_;
    private boolean serverSide_;
    private final e unknownFields;
    
    static
    {
      hd.fH();
    }
    
    private FunctionCall(GeneratedMessageLite.a parama)
    {
      super();
      this.unknownFields = parama.BE();
    }
    
    /* Error */
    private FunctionCall(f paramf, g paramg)
    {
      // Byte code:
      //   0: iconst_0
      //   1: istore 8
      //   3: aload_0
      //   4: invokespecial 81	com/google/tagmanager/protobuf/GeneratedMessageLite:<init>	()V
      //   7: aload_0
      //   8: iconst_m1
      //   9: putfield 63	com/google/analytics/containertag/proto/Serving$FunctionCall:memoizedIsInitialized	B
      //   12: aload_0
      //   13: iconst_m1
      //   14: putfield 65	com/google/analytics/containertag/proto/Serving$FunctionCall:memoizedSerializedSize	I
      //   17: aload_0
      //   18: invokespecial 57	com/google/analytics/containertag/proto/Serving$FunctionCall:fH	()V
      //   21: invokestatic 87	com/google/tagmanager/protobuf/e:AN	()Lcom/google/tagmanager/protobuf/e$b;
      //   24: astore 10
      //   26: aload 10
      //   28: invokestatic 92	com/google/tagmanager/protobuf/CodedOutputStream:a	(Ljava/io/OutputStream;)Lcom/google/tagmanager/protobuf/CodedOutputStream;
      //   31: astore 11
      //   33: iconst_0
      //   34: istore_3
      //   35: iload 8
      //   37: ifne +562 -> 599
      //   40: iload_3
      //   41: istore 6
      //   43: iload_3
      //   44: istore 4
      //   46: iload_3
      //   47: istore 7
      //   49: aload_1
      //   50: invokevirtual 98	com/google/tagmanager/protobuf/f:AT	()I
      //   53: istore 5
      //   55: iload 5
      //   57: lookupswitch	default:+629->686, 0:+632->689, 8:+95->152, 16:+186->243, 24:+246->303, 26:+316->373, 32:+464->521, 48:+503->560
      //   124: iload_3
      //   125: istore 6
      //   127: iload_3
      //   128: istore 4
      //   130: iload_3
      //   131: istore 7
      //   133: aload_0
      //   134: aload_1
      //   135: aload 11
      //   137: aload_2
      //   138: iload 5
      //   140: invokevirtual 101	com/google/analytics/containertag/proto/Serving$FunctionCall:a	(Lcom/google/tagmanager/protobuf/f;Lcom/google/tagmanager/protobuf/CodedOutputStream;Lcom/google/tagmanager/protobuf/g;I)Z
      //   143: ifne -108 -> 35
      //   146: iconst_1
      //   147: istore 8
      //   149: goto -114 -> 35
      //   152: iload_3
      //   153: istore 6
      //   155: iload_3
      //   156: istore 4
      //   158: iload_3
      //   159: istore 7
      //   161: aload_0
      //   162: aload_0
      //   163: getfield 103	com/google/analytics/containertag/proto/Serving$FunctionCall:bitField0_	I
      //   166: bipush 8
      //   168: ior
      //   169: putfield 103	com/google/analytics/containertag/proto/Serving$FunctionCall:bitField0_	I
      //   172: iload_3
      //   173: istore 6
      //   175: iload_3
      //   176: istore 4
      //   178: iload_3
      //   179: istore 7
      //   181: aload_0
      //   182: aload_1
      //   183: invokevirtual 107	com/google/tagmanager/protobuf/f:AZ	()Z
      //   186: putfield 109	com/google/analytics/containertag/proto/Serving$FunctionCall:serverSide_	Z
      //   189: goto -154 -> 35
      //   192: astore_1
      //   193: iload 6
      //   195: istore 4
      //   197: aload_1
      //   198: aload_0
      //   199: invokevirtual 113	com/google/tagmanager/protobuf/InvalidProtocolBufferException:h	(Lcom/google/tagmanager/protobuf/n;)Lcom/google/tagmanager/protobuf/InvalidProtocolBufferException;
      //   202: athrow
      //   203: astore_1
      //   204: iload 4
      //   206: iconst_1
      //   207: iand
      //   208: iconst_1
      //   209: if_icmpne +14 -> 223
      //   212: aload_0
      //   213: aload_0
      //   214: getfield 115	com/google/analytics/containertag/proto/Serving$FunctionCall:property_	Ljava/util/List;
      //   217: invokestatic 121	java/util/Collections:unmodifiableList	(Ljava/util/List;)Ljava/util/List;
      //   220: putfield 115	com/google/analytics/containertag/proto/Serving$FunctionCall:property_	Ljava/util/List;
      //   223: aload 11
      //   225: invokevirtual 124	com/google/tagmanager/protobuf/CodedOutputStream:flush	()V
      //   228: aload_0
      //   229: aload 10
      //   231: invokevirtual 129	com/google/tagmanager/protobuf/e$b:AR	()Lcom/google/tagmanager/protobuf/e;
      //   234: putfield 73	com/google/analytics/containertag/proto/Serving$FunctionCall:unknownFields	Lcom/google/tagmanager/protobuf/e;
      //   237: aload_0
      //   238: invokevirtual 132	com/google/analytics/containertag/proto/Serving$FunctionCall:BD	()V
      //   241: aload_1
      //   242: athrow
      //   243: iload_3
      //   244: istore 6
      //   246: iload_3
      //   247: istore 4
      //   249: iload_3
      //   250: istore 7
      //   252: aload_0
      //   253: aload_0
      //   254: getfield 103	com/google/analytics/containertag/proto/Serving$FunctionCall:bitField0_	I
      //   257: iconst_1
      //   258: ior
      //   259: putfield 103	com/google/analytics/containertag/proto/Serving$FunctionCall:bitField0_	I
      //   262: iload_3
      //   263: istore 6
      //   265: iload_3
      //   266: istore 4
      //   268: iload_3
      //   269: istore 7
      //   271: aload_0
      //   272: aload_1
      //   273: invokevirtual 135	com/google/tagmanager/protobuf/f:AW	()I
      //   276: putfield 137	com/google/analytics/containertag/proto/Serving$FunctionCall:function_	I
      //   279: goto -244 -> 35
      //   282: astore_1
      //   283: iload 7
      //   285: istore 4
      //   287: new 78	com/google/tagmanager/protobuf/InvalidProtocolBufferException
      //   290: dup
      //   291: aload_1
      //   292: invokevirtual 141	java/io/IOException:getMessage	()Ljava/lang/String;
      //   295: invokespecial 144	com/google/tagmanager/protobuf/InvalidProtocolBufferException:<init>	(Ljava/lang/String;)V
      //   298: aload_0
      //   299: invokevirtual 113	com/google/tagmanager/protobuf/InvalidProtocolBufferException:h	(Lcom/google/tagmanager/protobuf/n;)Lcom/google/tagmanager/protobuf/InvalidProtocolBufferException;
      //   302: athrow
      //   303: iload_3
      //   304: istore 5
      //   306: iload_3
      //   307: iconst_1
      //   308: iand
      //   309: iconst_1
      //   310: if_icmpeq +28 -> 338
      //   313: iload_3
      //   314: istore 6
      //   316: iload_3
      //   317: istore 4
      //   319: iload_3
      //   320: istore 7
      //   322: aload_0
      //   323: new 146	java/util/ArrayList
      //   326: dup
      //   327: invokespecial 147	java/util/ArrayList:<init>	()V
      //   330: putfield 115	com/google/analytics/containertag/proto/Serving$FunctionCall:property_	Ljava/util/List;
      //   333: iload_3
      //   334: iconst_1
      //   335: ior
      //   336: istore 5
      //   338: iload 5
      //   340: istore 6
      //   342: iload 5
      //   344: istore 4
      //   346: iload 5
      //   348: istore 7
      //   350: aload_0
      //   351: getfield 115	com/google/analytics/containertag/proto/Serving$FunctionCall:property_	Ljava/util/List;
      //   354: aload_1
      //   355: invokevirtual 135	com/google/tagmanager/protobuf/f:AW	()I
      //   358: invokestatic 153	java/lang/Integer:valueOf	(I)Ljava/lang/Integer;
      //   361: invokeinterface 159 2 0
      //   366: pop
      //   367: iload 5
      //   369: istore_3
      //   370: goto -335 -> 35
      //   373: iload_3
      //   374: istore 6
      //   376: iload_3
      //   377: istore 4
      //   379: iload_3
      //   380: istore 7
      //   382: aload_1
      //   383: aload_1
      //   384: invokevirtual 162	com/google/tagmanager/protobuf/f:Bi	()I
      //   387: invokevirtual 166	com/google/tagmanager/protobuf/f:eV	(I)I
      //   390: istore 9
      //   392: iload_3
      //   393: istore 5
      //   395: iload_3
      //   396: iconst_1
      //   397: iand
      //   398: iconst_1
      //   399: if_icmpeq +47 -> 446
      //   402: iload_3
      //   403: istore 6
      //   405: iload_3
      //   406: istore 4
      //   408: iload_3
      //   409: istore 7
      //   411: iload_3
      //   412: istore 5
      //   414: aload_1
      //   415: invokevirtual 169	com/google/tagmanager/protobuf/f:Bn	()I
      //   418: ifle +28 -> 446
      //   421: iload_3
      //   422: istore 6
      //   424: iload_3
      //   425: istore 4
      //   427: iload_3
      //   428: istore 7
      //   430: aload_0
      //   431: new 146	java/util/ArrayList
      //   434: dup
      //   435: invokespecial 147	java/util/ArrayList:<init>	()V
      //   438: putfield 115	com/google/analytics/containertag/proto/Serving$FunctionCall:property_	Ljava/util/List;
      //   441: iload_3
      //   442: iconst_1
      //   443: ior
      //   444: istore 5
      //   446: iload 5
      //   448: istore 6
      //   450: iload 5
      //   452: istore 4
      //   454: iload 5
      //   456: istore 7
      //   458: aload_1
      //   459: invokevirtual 169	com/google/tagmanager/protobuf/f:Bn	()I
      //   462: ifle +35 -> 497
      //   465: iload 5
      //   467: istore 6
      //   469: iload 5
      //   471: istore 4
      //   473: iload 5
      //   475: istore 7
      //   477: aload_0
      //   478: getfield 115	com/google/analytics/containertag/proto/Serving$FunctionCall:property_	Ljava/util/List;
      //   481: aload_1
      //   482: invokevirtual 135	com/google/tagmanager/protobuf/f:AW	()I
      //   485: invokestatic 153	java/lang/Integer:valueOf	(I)Ljava/lang/Integer;
      //   488: invokeinterface 159 2 0
      //   493: pop
      //   494: goto -48 -> 446
      //   497: iload 5
      //   499: istore 6
      //   501: iload 5
      //   503: istore 4
      //   505: iload 5
      //   507: istore 7
      //   509: aload_1
      //   510: iload 9
      //   512: invokevirtual 173	com/google/tagmanager/protobuf/f:eW	(I)V
      //   515: iload 5
      //   517: istore_3
      //   518: goto -483 -> 35
      //   521: iload_3
      //   522: istore 6
      //   524: iload_3
      //   525: istore 4
      //   527: iload_3
      //   528: istore 7
      //   530: aload_0
      //   531: aload_0
      //   532: getfield 103	com/google/analytics/containertag/proto/Serving$FunctionCall:bitField0_	I
      //   535: iconst_2
      //   536: ior
      //   537: putfield 103	com/google/analytics/containertag/proto/Serving$FunctionCall:bitField0_	I
      //   540: iload_3
      //   541: istore 6
      //   543: iload_3
      //   544: istore 4
      //   546: iload_3
      //   547: istore 7
      //   549: aload_0
      //   550: aload_1
      //   551: invokevirtual 135	com/google/tagmanager/protobuf/f:AW	()I
      //   554: putfield 175	com/google/analytics/containertag/proto/Serving$FunctionCall:name_	I
      //   557: goto -522 -> 35
      //   560: iload_3
      //   561: istore 6
      //   563: iload_3
      //   564: istore 4
      //   566: iload_3
      //   567: istore 7
      //   569: aload_0
      //   570: aload_0
      //   571: getfield 103	com/google/analytics/containertag/proto/Serving$FunctionCall:bitField0_	I
      //   574: iconst_4
      //   575: ior
      //   576: putfield 103	com/google/analytics/containertag/proto/Serving$FunctionCall:bitField0_	I
      //   579: iload_3
      //   580: istore 6
      //   582: iload_3
      //   583: istore 4
      //   585: iload_3
      //   586: istore 7
      //   588: aload_0
      //   589: aload_1
      //   590: invokevirtual 107	com/google/tagmanager/protobuf/f:AZ	()Z
      //   593: putfield 177	com/google/analytics/containertag/proto/Serving$FunctionCall:liveOnly_	Z
      //   596: goto -561 -> 35
      //   599: iload_3
      //   600: iconst_1
      //   601: iand
      //   602: iconst_1
      //   603: if_icmpne +14 -> 617
      //   606: aload_0
      //   607: aload_0
      //   608: getfield 115	com/google/analytics/containertag/proto/Serving$FunctionCall:property_	Ljava/util/List;
      //   611: invokestatic 121	java/util/Collections:unmodifiableList	(Ljava/util/List;)Ljava/util/List;
      //   614: putfield 115	com/google/analytics/containertag/proto/Serving$FunctionCall:property_	Ljava/util/List;
      //   617: aload 11
      //   619: invokevirtual 124	com/google/tagmanager/protobuf/CodedOutputStream:flush	()V
      //   622: aload_0
      //   623: aload 10
      //   625: invokevirtual 129	com/google/tagmanager/protobuf/e$b:AR	()Lcom/google/tagmanager/protobuf/e;
      //   628: putfield 73	com/google/analytics/containertag/proto/Serving$FunctionCall:unknownFields	Lcom/google/tagmanager/protobuf/e;
      //   631: aload_0
      //   632: invokevirtual 132	com/google/analytics/containertag/proto/Serving$FunctionCall:BD	()V
      //   635: return
      //   636: astore_1
      //   637: aload_0
      //   638: aload 10
      //   640: invokevirtual 129	com/google/tagmanager/protobuf/e$b:AR	()Lcom/google/tagmanager/protobuf/e;
      //   643: putfield 73	com/google/analytics/containertag/proto/Serving$FunctionCall:unknownFields	Lcom/google/tagmanager/protobuf/e;
      //   646: goto -15 -> 631
      //   649: astore_1
      //   650: aload_0
      //   651: aload 10
      //   653: invokevirtual 129	com/google/tagmanager/protobuf/e$b:AR	()Lcom/google/tagmanager/protobuf/e;
      //   656: putfield 73	com/google/analytics/containertag/proto/Serving$FunctionCall:unknownFields	Lcom/google/tagmanager/protobuf/e;
      //   659: aload_1
      //   660: athrow
      //   661: astore_2
      //   662: aload_0
      //   663: aload 10
      //   665: invokevirtual 129	com/google/tagmanager/protobuf/e$b:AR	()Lcom/google/tagmanager/protobuf/e;
      //   668: putfield 73	com/google/analytics/containertag/proto/Serving$FunctionCall:unknownFields	Lcom/google/tagmanager/protobuf/e;
      //   671: goto -434 -> 237
      //   674: astore_1
      //   675: aload_0
      //   676: aload 10
      //   678: invokevirtual 129	com/google/tagmanager/protobuf/e$b:AR	()Lcom/google/tagmanager/protobuf/e;
      //   681: putfield 73	com/google/analytics/containertag/proto/Serving$FunctionCall:unknownFields	Lcom/google/tagmanager/protobuf/e;
      //   684: aload_1
      //   685: athrow
      //   686: goto -562 -> 124
      //   689: iconst_1
      //   690: istore 8
      //   692: goto -657 -> 35
      // Local variable table:
      //   start	length	slot	name	signature
      //   0	695	0	this	FunctionCall
      //   0	695	1	paramf	f
      //   0	695	2	paramg	g
      //   34	568	3	i	int
      //   44	540	4	j	int
      //   53	463	5	k	int
      //   41	540	6	m	int
      //   47	540	7	n	int
      //   1	690	8	i1	int
      //   390	121	9	i2	int
      //   24	653	10	localb	com.google.tagmanager.protobuf.e.b
      //   31	587	11	localCodedOutputStream	CodedOutputStream
      // Exception table:
      //   from	to	target	type
      //   49	55	192	com/google/tagmanager/protobuf/InvalidProtocolBufferException
      //   133	146	192	com/google/tagmanager/protobuf/InvalidProtocolBufferException
      //   161	172	192	com/google/tagmanager/protobuf/InvalidProtocolBufferException
      //   181	189	192	com/google/tagmanager/protobuf/InvalidProtocolBufferException
      //   252	262	192	com/google/tagmanager/protobuf/InvalidProtocolBufferException
      //   271	279	192	com/google/tagmanager/protobuf/InvalidProtocolBufferException
      //   322	333	192	com/google/tagmanager/protobuf/InvalidProtocolBufferException
      //   350	367	192	com/google/tagmanager/protobuf/InvalidProtocolBufferException
      //   382	392	192	com/google/tagmanager/protobuf/InvalidProtocolBufferException
      //   414	421	192	com/google/tagmanager/protobuf/InvalidProtocolBufferException
      //   430	441	192	com/google/tagmanager/protobuf/InvalidProtocolBufferException
      //   458	465	192	com/google/tagmanager/protobuf/InvalidProtocolBufferException
      //   477	494	192	com/google/tagmanager/protobuf/InvalidProtocolBufferException
      //   509	515	192	com/google/tagmanager/protobuf/InvalidProtocolBufferException
      //   530	540	192	com/google/tagmanager/protobuf/InvalidProtocolBufferException
      //   549	557	192	com/google/tagmanager/protobuf/InvalidProtocolBufferException
      //   569	579	192	com/google/tagmanager/protobuf/InvalidProtocolBufferException
      //   588	596	192	com/google/tagmanager/protobuf/InvalidProtocolBufferException
      //   49	55	203	finally
      //   133	146	203	finally
      //   161	172	203	finally
      //   181	189	203	finally
      //   197	203	203	finally
      //   252	262	203	finally
      //   271	279	203	finally
      //   287	303	203	finally
      //   322	333	203	finally
      //   350	367	203	finally
      //   382	392	203	finally
      //   414	421	203	finally
      //   430	441	203	finally
      //   458	465	203	finally
      //   477	494	203	finally
      //   509	515	203	finally
      //   530	540	203	finally
      //   549	557	203	finally
      //   569	579	203	finally
      //   588	596	203	finally
      //   49	55	282	java/io/IOException
      //   133	146	282	java/io/IOException
      //   161	172	282	java/io/IOException
      //   181	189	282	java/io/IOException
      //   252	262	282	java/io/IOException
      //   271	279	282	java/io/IOException
      //   322	333	282	java/io/IOException
      //   350	367	282	java/io/IOException
      //   382	392	282	java/io/IOException
      //   414	421	282	java/io/IOException
      //   430	441	282	java/io/IOException
      //   458	465	282	java/io/IOException
      //   477	494	282	java/io/IOException
      //   509	515	282	java/io/IOException
      //   530	540	282	java/io/IOException
      //   549	557	282	java/io/IOException
      //   569	579	282	java/io/IOException
      //   588	596	282	java/io/IOException
      //   617	622	636	java/io/IOException
      //   617	622	649	finally
      //   223	228	661	java/io/IOException
      //   223	228	674	finally
    }
    
    private FunctionCall(boolean paramBoolean)
    {
      this.unknownFields = e.ajf;
    }
    
    public static a a(FunctionCall paramFunctionCall)
    {
      return go().d(paramFunctionCall);
    }
    
    private void fH()
    {
      this.property_ = Collections.emptyList();
      this.function_ = 0;
      this.name_ = 0;
      this.liveOnly_ = false;
      this.serverSide_ = false;
    }
    
    public static FunctionCall gb()
    {
      return hd;
    }
    
    public static a go()
    {
      return a.gw();
    }
    
    public void a(CodedOutputStream paramCodedOutputStream)
    {
      fI();
      if ((this.bitField0_ & 0x8) == 8) {
        paramCodedOutputStream.d(1, this.serverSide_);
      }
      if ((this.bitField0_ & 0x1) == 1) {
        paramCodedOutputStream.w(2, this.function_);
      }
      int i = 0;
      while (i < this.property_.size())
      {
        paramCodedOutputStream.w(3, ((Integer)this.property_.get(i)).intValue());
        i += 1;
      }
      if ((this.bitField0_ & 0x2) == 2) {
        paramCodedOutputStream.w(4, this.name_);
      }
      if ((this.bitField0_ & 0x4) == 4) {
        paramCodedOutputStream.d(6, this.liveOnly_);
      }
      paramCodedOutputStream.d(this.unknownFields);
    }
    
    public boolean equals(Object paramObject)
    {
      if (paramObject == this) {
        return true;
      }
      if (!(paramObject instanceof FunctionCall)) {
        return super.equals(paramObject);
      }
      paramObject = (FunctionCall)paramObject;
      int i;
      label43:
      label60:
      int j;
      if (ge().equals(((FunctionCall)paramObject).ge()))
      {
        i = 1;
        if ((i == 0) || (gg() != ((FunctionCall)paramObject).gg())) {
          break label220;
        }
        i = 1;
        j = i;
        if (gg())
        {
          if ((i == 0) || (gh() != ((FunctionCall)paramObject).gh())) {
            break label225;
          }
          j = 1;
        }
        label86:
        if ((j == 0) || (gi() != ((FunctionCall)paramObject).gi())) {
          break label230;
        }
        i = 1;
        label103:
        j = i;
        if (gi())
        {
          if ((i == 0) || (gj() != ((FunctionCall)paramObject).gj())) {
            break label235;
          }
          j = 1;
        }
        label129:
        if ((j == 0) || (gk() != ((FunctionCall)paramObject).gk())) {
          break label240;
        }
        i = 1;
        label146:
        j = i;
        if (gk())
        {
          if ((i == 0) || (gl() != ((FunctionCall)paramObject).gl())) {
            break label245;
          }
          j = 1;
        }
        label172:
        if ((j == 0) || (gm() != ((FunctionCall)paramObject).gm())) {
          break label250;
        }
      }
      label220:
      label225:
      label230:
      label235:
      label240:
      label245:
      label250:
      for (boolean bool = true;; bool = false)
      {
        if (!gm()) {
          break label256;
        }
        if ((bool) && (gn() == ((FunctionCall)paramObject).gn())) {
          break;
        }
        return false;
        i = 0;
        break label43;
        i = 0;
        break label60;
        j = 0;
        break label86;
        i = 0;
        break label103;
        j = 0;
        break label129;
        i = 0;
        break label146;
        j = 0;
        break label172;
      }
      label256:
      return bool;
    }
    
    public q<FunctionCall> fA()
    {
      return gW;
    }
    
    public int fI()
    {
      int k = 0;
      int i = this.memoizedSerializedSize;
      if (i != -1) {
        return i;
      }
      if ((this.bitField0_ & 0x8) == 8) {}
      for (i = CodedOutputStream.e(1, this.serverSide_) + 0;; i = 0)
      {
        if ((this.bitField0_ & 0x1) == 1) {
          i += CodedOutputStream.z(2, this.function_);
        }
        for (;;)
        {
          int m;
          for (int j = 0; k < this.property_.size(); j = m + j)
          {
            m = CodedOutputStream.ff(((Integer)this.property_.get(k)).intValue());
            k += 1;
          }
          j = i + j + ge().size() * 1;
          i = j;
          if ((this.bitField0_ & 0x2) == 2) {
            i = j + CodedOutputStream.z(4, this.name_);
          }
          j = i;
          if ((this.bitField0_ & 0x4) == 4) {
            j = i + CodedOutputStream.e(6, this.liveOnly_);
          }
          i = j + this.unknownFields.size();
          this.memoizedSerializedSize = i;
          return i;
        }
      }
    }
    
    public FunctionCall gd()
    {
      return hd;
    }
    
    public List<Integer> ge()
    {
      return this.property_;
    }
    
    public int gf()
    {
      return this.property_.size();
    }
    
    public boolean gg()
    {
      return (this.bitField0_ & 0x1) == 1;
    }
    
    public int gh()
    {
      return this.function_;
    }
    
    public boolean gi()
    {
      return (this.bitField0_ & 0x2) == 2;
    }
    
    public int gj()
    {
      return this.name_;
    }
    
    public boolean gk()
    {
      return (this.bitField0_ & 0x4) == 4;
    }
    
    public boolean gl()
    {
      return this.liveOnly_;
    }
    
    public boolean gm()
    {
      return (this.bitField0_ & 0x8) == 8;
    }
    
    public boolean gn()
    {
      return this.serverSide_;
    }
    
    public a gp()
    {
      return go();
    }
    
    public a gq()
    {
      return a(this);
    }
    
    public int hashCode()
    {
      if (this.memoizedHashCode != 0) {
        return this.memoizedHashCode;
      }
      int j = FunctionCall.class.hashCode() + 779;
      int i = j;
      if (gf() > 0) {
        i = (j * 37 + 3) * 53 + ge().hashCode();
      }
      j = i;
      if (gg()) {
        j = (i * 37 + 2) * 53 + gh();
      }
      i = j;
      if (gi()) {
        i = (j * 37 + 4) * 53 + gj();
      }
      j = i;
      if (gk()) {
        j = (i * 37 + 6) * 53 + i.aK(gl());
      }
      i = j;
      if (gm()) {
        i = (j * 37 + 1) * 53 + i.aK(gn());
      }
      i = i * 29 + this.unknownFields.hashCode();
      this.memoizedHashCode = i;
      return i;
    }
    
    public final boolean isInitialized()
    {
      int i = this.memoizedIsInitialized;
      if (i != -1) {
        return i == 1;
      }
      if (!gg())
      {
        this.memoizedIsInitialized = 0;
        return false;
      }
      this.memoizedIsInitialized = 1;
      return true;
    }
    
    protected Object writeReplace()
    {
      return super.writeReplace();
    }
    
    public static final class a
      extends GeneratedMessageLite.a<Serving.FunctionCall, a>
      implements Serving.b
    {
      private int bitField0_;
      private int function_;
      private boolean liveOnly_;
      private int name_;
      private List<Integer> property_ = Collections.emptyList();
      private boolean serverSide_;
      
      private a()
      {
        fP();
      }
      
      private void fP() {}
      
      private static a gr()
      {
        return new a();
      }
      
      private void gv()
      {
        if ((this.bitField0_ & 0x1) != 1)
        {
          this.property_ = new ArrayList(this.property_);
          this.bitField0_ |= 0x1;
        }
      }
      
      public a aF(int paramInt)
      {
        this.bitField0_ |= 0x2;
        this.function_ = paramInt;
        return this;
      }
      
      public a aG(int paramInt)
      {
        this.bitField0_ |= 0x4;
        this.name_ = paramInt;
        return this;
      }
      
      public a d(Serving.FunctionCall paramFunctionCall)
      {
        if (paramFunctionCall == Serving.FunctionCall.gb()) {
          return this;
        }
        if (!Serving.FunctionCall.b(paramFunctionCall).isEmpty())
        {
          if (!this.property_.isEmpty()) {
            break label134;
          }
          this.property_ = Serving.FunctionCall.b(paramFunctionCall);
          this.bitField0_ &= 0xFFFFFFFE;
        }
        for (;;)
        {
          if (paramFunctionCall.gg()) {
            aF(paramFunctionCall.gh());
          }
          if (paramFunctionCall.gi()) {
            aG(paramFunctionCall.gj());
          }
          if (paramFunctionCall.gk()) {
            h(paramFunctionCall.gl());
          }
          if (paramFunctionCall.gm()) {
            i(paramFunctionCall.gn());
          }
          e(BE().a(Serving.FunctionCall.c(paramFunctionCall)));
          return this;
          label134:
          gv();
          this.property_.addAll(Serving.FunctionCall.b(paramFunctionCall));
        }
      }
      
      /* Error */
      public a g(f paramf, g paramg)
      {
        // Byte code:
        //   0: getstatic 174	com/google/analytics/containertag/proto/Serving$FunctionCall:gW	Lcom/google/tagmanager/protobuf/q;
        //   3: aload_1
        //   4: aload_2
        //   5: invokeinterface 179 3 0
        //   10: checkcast 9	com/google/analytics/containertag/proto/Serving$FunctionCall
        //   13: astore_1
        //   14: aload_1
        //   15: ifnull +9 -> 24
        //   18: aload_0
        //   19: aload_1
        //   20: invokevirtual 58	com/google/analytics/containertag/proto/Serving$FunctionCall$a:d	(Lcom/google/analytics/containertag/proto/Serving$FunctionCall;)Lcom/google/analytics/containertag/proto/Serving$FunctionCall$a;
        //   23: pop
        //   24: aload_0
        //   25: areturn
        //   26: astore_2
        //   27: aload_2
        //   28: invokevirtual 182	com/google/tagmanager/protobuf/InvalidProtocolBufferException:BN	()Lcom/google/tagmanager/protobuf/n;
        //   31: checkcast 9	com/google/analytics/containertag/proto/Serving$FunctionCall
        //   34: astore_1
        //   35: aload_2
        //   36: athrow
        //   37: astore_2
        //   38: aload_1
        //   39: ifnull +9 -> 48
        //   42: aload_0
        //   43: aload_1
        //   44: invokevirtual 58	com/google/analytics/containertag/proto/Serving$FunctionCall$a:d	(Lcom/google/analytics/containertag/proto/Serving$FunctionCall;)Lcom/google/analytics/containertag/proto/Serving$FunctionCall$a;
        //   47: pop
        //   48: aload_2
        //   49: athrow
        //   50: astore_2
        //   51: aconst_null
        //   52: astore_1
        //   53: goto -15 -> 38
        // Local variable table:
        //   start	length	slot	name	signature
        //   0	56	0	this	a
        //   0	56	1	paramf	f
        //   0	56	2	paramg	g
        // Exception table:
        //   from	to	target	type
        //   0	14	26	com/google/tagmanager/protobuf/InvalidProtocolBufferException
        //   35	37	37	finally
        //   0	14	50	finally
        //   27	35	50	finally
      }
      
      public Serving.FunctionCall gd()
      {
        return Serving.FunctionCall.gb();
      }
      
      public boolean gg()
      {
        return (this.bitField0_ & 0x2) == 2;
      }
      
      public a gs()
      {
        return gr().d(gu());
      }
      
      public Serving.FunctionCall gt()
      {
        Serving.FunctionCall localFunctionCall = gu();
        if (!localFunctionCall.isInitialized()) {
          throw a(localFunctionCall);
        }
        return localFunctionCall;
      }
      
      public Serving.FunctionCall gu()
      {
        int j = 1;
        Serving.FunctionCall localFunctionCall = new Serving.FunctionCall(this, null);
        int k = this.bitField0_;
        if ((this.bitField0_ & 0x1) == 1)
        {
          this.property_ = Collections.unmodifiableList(this.property_);
          this.bitField0_ &= 0xFFFFFFFE;
        }
        Serving.FunctionCall.a(localFunctionCall, this.property_);
        if ((k & 0x2) == 2) {}
        for (;;)
        {
          Serving.FunctionCall.a(localFunctionCall, this.function_);
          int i = j;
          if ((k & 0x4) == 4) {
            i = j | 0x2;
          }
          Serving.FunctionCall.b(localFunctionCall, this.name_);
          j = i;
          if ((k & 0x8) == 8) {
            j = i | 0x4;
          }
          Serving.FunctionCall.a(localFunctionCall, this.liveOnly_);
          i = j;
          if ((k & 0x10) == 16) {
            i = j | 0x8;
          }
          Serving.FunctionCall.b(localFunctionCall, this.serverSide_);
          Serving.FunctionCall.c(localFunctionCall, i);
          return localFunctionCall;
          j = 0;
        }
      }
      
      public a h(boolean paramBoolean)
      {
        this.bitField0_ |= 0x8;
        this.liveOnly_ = paramBoolean;
        return this;
      }
      
      public a i(boolean paramBoolean)
      {
        this.bitField0_ |= 0x10;
        this.serverSide_ = paramBoolean;
        return this;
      }
      
      public final boolean isInitialized()
      {
        return gg();
      }
    }
  }
  
  public static final class Property
    extends GeneratedMessageLite
    implements Serving.c
  {
    public static q<Property> gW = new c()
    {
      public Serving.Property h(f paramAnonymousf, g paramAnonymousg)
      {
        return new Serving.Property(paramAnonymousf, paramAnonymousg, null);
      }
    };
    private static volatile p gX = null;
    private static final Property he = new Property(true);
    private static final long serialVersionUID = 0L;
    private int bitField0_;
    private int key_;
    private byte memoizedIsInitialized = -1;
    private int memoizedSerializedSize = -1;
    private final e unknownFields;
    private int value_;
    
    static
    {
      he.fH();
    }
    
    private Property(GeneratedMessageLite.a parama)
    {
      super();
      this.unknownFields = parama.BE();
    }
    
    /* Error */
    private Property(f paramf, g paramg)
    {
      // Byte code:
      //   0: aload_0
      //   1: invokespecial 75	com/google/tagmanager/protobuf/GeneratedMessageLite:<init>	()V
      //   4: aload_0
      //   5: iconst_m1
      //   6: putfield 57	com/google/analytics/containertag/proto/Serving$Property:memoizedIsInitialized	B
      //   9: aload_0
      //   10: iconst_m1
      //   11: putfield 59	com/google/analytics/containertag/proto/Serving$Property:memoizedSerializedSize	I
      //   14: aload_0
      //   15: invokespecial 51	com/google/analytics/containertag/proto/Serving$Property:fH	()V
      //   18: invokestatic 81	com/google/tagmanager/protobuf/e:AN	()Lcom/google/tagmanager/protobuf/e$b;
      //   21: astore 5
      //   23: aload 5
      //   25: invokestatic 86	com/google/tagmanager/protobuf/CodedOutputStream:a	(Ljava/io/OutputStream;)Lcom/google/tagmanager/protobuf/CodedOutputStream;
      //   28: astore 6
      //   30: iconst_0
      //   31: istore_3
      //   32: iload_3
      //   33: ifne +152 -> 185
      //   36: aload_1
      //   37: invokevirtual 92	com/google/tagmanager/protobuf/f:AT	()I
      //   40: istore 4
      //   42: iload 4
      //   44: lookupswitch	default:+210->254, 0:+213->257, 8:+54->98, 16:+103->147
      //   80: aload_0
      //   81: aload_1
      //   82: aload 6
      //   84: aload_2
      //   85: iload 4
      //   87: invokevirtual 95	com/google/analytics/containertag/proto/Serving$Property:a	(Lcom/google/tagmanager/protobuf/f;Lcom/google/tagmanager/protobuf/CodedOutputStream;Lcom/google/tagmanager/protobuf/g;I)Z
      //   90: ifne -58 -> 32
      //   93: iconst_1
      //   94: istore_3
      //   95: goto -63 -> 32
      //   98: aload_0
      //   99: aload_0
      //   100: getfield 97	com/google/analytics/containertag/proto/Serving$Property:bitField0_	I
      //   103: iconst_1
      //   104: ior
      //   105: putfield 97	com/google/analytics/containertag/proto/Serving$Property:bitField0_	I
      //   108: aload_0
      //   109: aload_1
      //   110: invokevirtual 100	com/google/tagmanager/protobuf/f:AW	()I
      //   113: putfield 102	com/google/analytics/containertag/proto/Serving$Property:key_	I
      //   116: goto -84 -> 32
      //   119: astore_1
      //   120: aload_1
      //   121: aload_0
      //   122: invokevirtual 106	com/google/tagmanager/protobuf/InvalidProtocolBufferException:h	(Lcom/google/tagmanager/protobuf/n;)Lcom/google/tagmanager/protobuf/InvalidProtocolBufferException;
      //   125: athrow
      //   126: astore_1
      //   127: aload 6
      //   129: invokevirtual 109	com/google/tagmanager/protobuf/CodedOutputStream:flush	()V
      //   132: aload_0
      //   133: aload 5
      //   135: invokevirtual 114	com/google/tagmanager/protobuf/e$b:AR	()Lcom/google/tagmanager/protobuf/e;
      //   138: putfield 67	com/google/analytics/containertag/proto/Serving$Property:unknownFields	Lcom/google/tagmanager/protobuf/e;
      //   141: aload_0
      //   142: invokevirtual 117	com/google/analytics/containertag/proto/Serving$Property:BD	()V
      //   145: aload_1
      //   146: athrow
      //   147: aload_0
      //   148: aload_0
      //   149: getfield 97	com/google/analytics/containertag/proto/Serving$Property:bitField0_	I
      //   152: iconst_2
      //   153: ior
      //   154: putfield 97	com/google/analytics/containertag/proto/Serving$Property:bitField0_	I
      //   157: aload_0
      //   158: aload_1
      //   159: invokevirtual 100	com/google/tagmanager/protobuf/f:AW	()I
      //   162: putfield 119	com/google/analytics/containertag/proto/Serving$Property:value_	I
      //   165: goto -133 -> 32
      //   168: astore_1
      //   169: new 72	com/google/tagmanager/protobuf/InvalidProtocolBufferException
      //   172: dup
      //   173: aload_1
      //   174: invokevirtual 123	java/io/IOException:getMessage	()Ljava/lang/String;
      //   177: invokespecial 126	com/google/tagmanager/protobuf/InvalidProtocolBufferException:<init>	(Ljava/lang/String;)V
      //   180: aload_0
      //   181: invokevirtual 106	com/google/tagmanager/protobuf/InvalidProtocolBufferException:h	(Lcom/google/tagmanager/protobuf/n;)Lcom/google/tagmanager/protobuf/InvalidProtocolBufferException;
      //   184: athrow
      //   185: aload 6
      //   187: invokevirtual 109	com/google/tagmanager/protobuf/CodedOutputStream:flush	()V
      //   190: aload_0
      //   191: aload 5
      //   193: invokevirtual 114	com/google/tagmanager/protobuf/e$b:AR	()Lcom/google/tagmanager/protobuf/e;
      //   196: putfield 67	com/google/analytics/containertag/proto/Serving$Property:unknownFields	Lcom/google/tagmanager/protobuf/e;
      //   199: aload_0
      //   200: invokevirtual 117	com/google/analytics/containertag/proto/Serving$Property:BD	()V
      //   203: return
      //   204: astore_1
      //   205: aload_0
      //   206: aload 5
      //   208: invokevirtual 114	com/google/tagmanager/protobuf/e$b:AR	()Lcom/google/tagmanager/protobuf/e;
      //   211: putfield 67	com/google/analytics/containertag/proto/Serving$Property:unknownFields	Lcom/google/tagmanager/protobuf/e;
      //   214: goto -15 -> 199
      //   217: astore_1
      //   218: aload_0
      //   219: aload 5
      //   221: invokevirtual 114	com/google/tagmanager/protobuf/e$b:AR	()Lcom/google/tagmanager/protobuf/e;
      //   224: putfield 67	com/google/analytics/containertag/proto/Serving$Property:unknownFields	Lcom/google/tagmanager/protobuf/e;
      //   227: aload_1
      //   228: athrow
      //   229: astore_2
      //   230: aload_0
      //   231: aload 5
      //   233: invokevirtual 114	com/google/tagmanager/protobuf/e$b:AR	()Lcom/google/tagmanager/protobuf/e;
      //   236: putfield 67	com/google/analytics/containertag/proto/Serving$Property:unknownFields	Lcom/google/tagmanager/protobuf/e;
      //   239: goto -98 -> 141
      //   242: astore_1
      //   243: aload_0
      //   244: aload 5
      //   246: invokevirtual 114	com/google/tagmanager/protobuf/e$b:AR	()Lcom/google/tagmanager/protobuf/e;
      //   249: putfield 67	com/google/analytics/containertag/proto/Serving$Property:unknownFields	Lcom/google/tagmanager/protobuf/e;
      //   252: aload_1
      //   253: athrow
      //   254: goto -174 -> 80
      //   257: iconst_1
      //   258: istore_3
      //   259: goto -227 -> 32
      // Local variable table:
      //   start	length	slot	name	signature
      //   0	262	0	this	Property
      //   0	262	1	paramf	f
      //   0	262	2	paramg	g
      //   31	228	3	i	int
      //   40	46	4	j	int
      //   21	224	5	localb	com.google.tagmanager.protobuf.e.b
      //   28	158	6	localCodedOutputStream	CodedOutputStream
      // Exception table:
      //   from	to	target	type
      //   36	42	119	com/google/tagmanager/protobuf/InvalidProtocolBufferException
      //   80	93	119	com/google/tagmanager/protobuf/InvalidProtocolBufferException
      //   98	116	119	com/google/tagmanager/protobuf/InvalidProtocolBufferException
      //   147	165	119	com/google/tagmanager/protobuf/InvalidProtocolBufferException
      //   36	42	126	finally
      //   80	93	126	finally
      //   98	116	126	finally
      //   120	126	126	finally
      //   147	165	126	finally
      //   169	185	126	finally
      //   36	42	168	java/io/IOException
      //   80	93	168	java/io/IOException
      //   98	116	168	java/io/IOException
      //   147	165	168	java/io/IOException
      //   185	190	204	java/io/IOException
      //   185	190	217	finally
      //   127	132	229	java/io/IOException
      //   127	132	242	finally
    }
    
    private Property(boolean paramBoolean)
    {
      this.unknownFields = e.ajf;
    }
    
    public static a a(Property paramProperty)
    {
      return gA().c(paramProperty);
    }
    
    private void fH()
    {
      this.key_ = 0;
      this.value_ = 0;
    }
    
    public static a gA()
    {
      return a.gH();
    }
    
    public static Property gx()
    {
      return he;
    }
    
    public void a(CodedOutputStream paramCodedOutputStream)
    {
      fI();
      if ((this.bitField0_ & 0x1) == 1) {
        paramCodedOutputStream.w(1, this.key_);
      }
      if ((this.bitField0_ & 0x2) == 2) {
        paramCodedOutputStream.w(2, this.value_);
      }
      paramCodedOutputStream.d(this.unknownFields);
    }
    
    public boolean equals(Object paramObject)
    {
      if (paramObject == this) {
        return true;
      }
      if (!(paramObject instanceof Property)) {
        return super.equals(paramObject);
      }
      paramObject = (Property)paramObject;
      int i;
      label38:
      int j;
      if (hasKey() == ((Property)paramObject).hasKey())
      {
        i = 1;
        j = i;
        if (hasKey())
        {
          if ((i == 0) || (gz() != ((Property)paramObject).gz())) {
            break label112;
          }
          j = 1;
        }
        label64:
        if ((j == 0) || (hasValue() != ((Property)paramObject).hasValue())) {
          break label117;
        }
      }
      label112:
      label117:
      for (boolean bool = true;; bool = false)
      {
        if (!hasValue()) {
          break label123;
        }
        if ((bool) && (getValue() == ((Property)paramObject).getValue())) {
          break;
        }
        return false;
        i = 0;
        break label38;
        j = 0;
        break label64;
      }
      label123:
      return bool;
    }
    
    public q<Property> fA()
    {
      return gW;
    }
    
    public int fI()
    {
      int i = this.memoizedSerializedSize;
      if (i != -1) {
        return i;
      }
      i = 0;
      if ((this.bitField0_ & 0x1) == 1) {
        i = 0 + CodedOutputStream.z(1, this.key_);
      }
      int j = i;
      if ((this.bitField0_ & 0x2) == 2) {
        j = i + CodedOutputStream.z(2, this.value_);
      }
      i = j + this.unknownFields.size();
      this.memoizedSerializedSize = i;
      return i;
    }
    
    public a gB()
    {
      return gA();
    }
    
    public a gC()
    {
      return a(this);
    }
    
    public int getValue()
    {
      return this.value_;
    }
    
    public Property gy()
    {
      return he;
    }
    
    public int gz()
    {
      return this.key_;
    }
    
    public boolean hasKey()
    {
      return (this.bitField0_ & 0x1) == 1;
    }
    
    public boolean hasValue()
    {
      return (this.bitField0_ & 0x2) == 2;
    }
    
    public int hashCode()
    {
      if (this.memoizedHashCode != 0) {
        return this.memoizedHashCode;
      }
      int j = Property.class.hashCode() + 779;
      int i = j;
      if (hasKey()) {
        i = (j * 37 + 1) * 53 + gz();
      }
      j = i;
      if (hasValue()) {
        j = (i * 37 + 2) * 53 + getValue();
      }
      i = j * 29 + this.unknownFields.hashCode();
      this.memoizedHashCode = i;
      return i;
    }
    
    public final boolean isInitialized()
    {
      int i = this.memoizedIsInitialized;
      if (i != -1) {
        return i == 1;
      }
      if (!hasKey())
      {
        this.memoizedIsInitialized = 0;
        return false;
      }
      if (!hasValue())
      {
        this.memoizedIsInitialized = 0;
        return false;
      }
      this.memoizedIsInitialized = 1;
      return true;
    }
    
    protected Object writeReplace()
    {
      return super.writeReplace();
    }
    
    public static final class a
      extends GeneratedMessageLite.a<Serving.Property, a>
      implements Serving.c
    {
      private int bitField0_;
      private int key_;
      private int value_;
      
      private a()
      {
        fP();
      }
      
      private void fP() {}
      
      private static a gD()
      {
        return new a();
      }
      
      public a aH(int paramInt)
      {
        this.bitField0_ |= 0x1;
        this.key_ = paramInt;
        return this;
      }
      
      public a aI(int paramInt)
      {
        this.bitField0_ |= 0x2;
        this.value_ = paramInt;
        return this;
      }
      
      public a c(Serving.Property paramProperty)
      {
        if (paramProperty == Serving.Property.gx()) {
          return this;
        }
        if (paramProperty.hasKey()) {
          aH(paramProperty.gz());
        }
        if (paramProperty.hasValue()) {
          aI(paramProperty.getValue());
        }
        e(BE().a(Serving.Property.b(paramProperty)));
        return this;
      }
      
      public a gE()
      {
        return gD().c(gG());
      }
      
      public Serving.Property gF()
      {
        Serving.Property localProperty = gG();
        if (!localProperty.isInitialized()) {
          throw a(localProperty);
        }
        return localProperty;
      }
      
      public Serving.Property gG()
      {
        int i = 1;
        Serving.Property localProperty = new Serving.Property(this, null);
        int k = this.bitField0_;
        if ((k & 0x1) == 1) {}
        for (;;)
        {
          Serving.Property.a(localProperty, this.key_);
          int j = i;
          if ((k & 0x2) == 2) {
            j = i | 0x2;
          }
          Serving.Property.b(localProperty, this.value_);
          Serving.Property.c(localProperty, j);
          return localProperty;
          i = 0;
        }
      }
      
      public Serving.Property gy()
      {
        return Serving.Property.gx();
      }
      
      public boolean hasKey()
      {
        return (this.bitField0_ & 0x1) == 1;
      }
      
      public boolean hasValue()
      {
        return (this.bitField0_ & 0x2) == 2;
      }
      
      /* Error */
      public a i(f paramf, g paramg)
      {
        // Byte code:
        //   0: getstatic 137	com/google/analytics/containertag/proto/Serving$Property:gW	Lcom/google/tagmanager/protobuf/q;
        //   3: aload_1
        //   4: aload_2
        //   5: invokeinterface 142 3 0
        //   10: checkcast 9	com/google/analytics/containertag/proto/Serving$Property
        //   13: astore_1
        //   14: aload_1
        //   15: ifnull +9 -> 24
        //   18: aload_0
        //   19: aload_1
        //   20: invokevirtual 36	com/google/analytics/containertag/proto/Serving$Property$a:c	(Lcom/google/analytics/containertag/proto/Serving$Property;)Lcom/google/analytics/containertag/proto/Serving$Property$a;
        //   23: pop
        //   24: aload_0
        //   25: areturn
        //   26: astore_2
        //   27: aload_2
        //   28: invokevirtual 145	com/google/tagmanager/protobuf/InvalidProtocolBufferException:BN	()Lcom/google/tagmanager/protobuf/n;
        //   31: checkcast 9	com/google/analytics/containertag/proto/Serving$Property
        //   34: astore_1
        //   35: aload_2
        //   36: athrow
        //   37: astore_2
        //   38: aload_1
        //   39: ifnull +9 -> 48
        //   42: aload_0
        //   43: aload_1
        //   44: invokevirtual 36	com/google/analytics/containertag/proto/Serving$Property$a:c	(Lcom/google/analytics/containertag/proto/Serving$Property;)Lcom/google/analytics/containertag/proto/Serving$Property$a;
        //   47: pop
        //   48: aload_2
        //   49: athrow
        //   50: astore_2
        //   51: aconst_null
        //   52: astore_1
        //   53: goto -15 -> 38
        // Local variable table:
        //   start	length	slot	name	signature
        //   0	56	0	this	a
        //   0	56	1	paramf	f
        //   0	56	2	paramg	g
        // Exception table:
        //   from	to	target	type
        //   0	14	26	com/google/tagmanager/protobuf/InvalidProtocolBufferException
        //   35	37	37	finally
        //   0	14	50	finally
        //   27	35	50	finally
      }
      
      public final boolean isInitialized()
      {
        if (!hasKey()) {}
        while (!hasValue()) {
          return false;
        }
        return true;
      }
    }
  }
  
  public static final class Resource
    extends GeneratedMessageLite
    implements Serving.d
  {
    public static q<Resource> gW = new c()
    {
      public Serving.Resource j(f paramAnonymousf, g paramAnonymousg)
      {
        return new Serving.Resource(paramAnonymousf, paramAnonymousg, null);
      }
    };
    private static volatile p gX = null;
    private static final Resource hf = new Resource(true);
    private static final long serialVersionUID = 0L;
    private int bitField0_;
    private boolean enableAutoEventTracking_;
    private l key_;
    private Serving.CacheOption liveJsCacheOption_;
    private List<Serving.FunctionCall> macro_;
    private Object malwareScanAuthCode_;
    private byte memoizedIsInitialized = -1;
    private int memoizedSerializedSize = -1;
    private List<Serving.FunctionCall> predicate_;
    private Object previewAuthCode_;
    private List<Serving.Property> property_;
    private float reportingSampleRate_;
    private int resourceFormatVersion_;
    private List<Serving.Rule> rule_;
    private List<Serving.FunctionCall> tag_;
    private Object templateVersionSet_;
    private final e unknownFields;
    private l usageContext_;
    private List<TypeSystem.Value> value_;
    private Object version_;
    
    static
    {
      hf.fH();
    }
    
    private Resource(GeneratedMessageLite.a parama)
    {
      super();
      this.unknownFields = parama.BE();
    }
    
    /* Error */
    private Resource(f paramf, g paramg)
    {
      // Byte code:
      //   0: aload_0
      //   1: invokespecial 99	com/google/tagmanager/protobuf/GeneratedMessageLite:<init>	()V
      //   4: aload_0
      //   5: iconst_m1
      //   6: putfield 81	com/google/analytics/containertag/proto/Serving$Resource:memoizedIsInitialized	B
      //   9: aload_0
      //   10: iconst_m1
      //   11: putfield 83	com/google/analytics/containertag/proto/Serving$Resource:memoizedSerializedSize	I
      //   14: aload_0
      //   15: invokespecial 75	com/google/analytics/containertag/proto/Serving$Resource:fH	()V
      //   18: iconst_0
      //   19: istore_3
      //   20: invokestatic 105	com/google/tagmanager/protobuf/e:AN	()Lcom/google/tagmanager/protobuf/e$b;
      //   23: astore 9
      //   25: aload 9
      //   27: invokestatic 110	com/google/tagmanager/protobuf/CodedOutputStream:a	(Ljava/io/OutputStream;)Lcom/google/tagmanager/protobuf/CodedOutputStream;
      //   30: astore 10
      //   32: iconst_0
      //   33: istore 4
      //   35: iload 4
      //   37: ifne +1123 -> 1160
      //   40: iload_3
      //   41: istore 5
      //   43: aload_1
      //   44: invokevirtual 116	com/google/tagmanager/protobuf/f:AT	()I
      //   47: istore 6
      //   49: iload 6
      //   51: lookupswitch	default:+1640->1691, 0:+1656->1707, 10:+173->224, 18:+240->291, 26:+305->356, 34:+370->421, 42:+438->489, 50:+506->557, 58:+574->625, 74:+642->693, 82:+686->737, 98:+730->781, 106:+774->825, 114:+819->870, 125:+921->972, 130:+959->1010, 136:+1032->1083, 144:+1071->1122
      //   196: iload_3
      //   197: istore 5
      //   199: aload_0
      //   200: aload_1
      //   201: aload 10
      //   203: aload_2
      //   204: iload 6
      //   206: invokevirtual 119	com/google/analytics/containertag/proto/Serving$Resource:a	(Lcom/google/tagmanager/protobuf/f;Lcom/google/tagmanager/protobuf/CodedOutputStream;Lcom/google/tagmanager/protobuf/g;I)Z
      //   209: ifne +938 -> 1147
      //   212: iconst_1
      //   213: istore 5
      //   215: iload_3
      //   216: istore 4
      //   218: iload 5
      //   220: istore_3
      //   221: goto +1473 -> 1694
      //   224: iload_3
      //   225: istore 5
      //   227: aload_1
      //   228: invokevirtual 122	com/google/tagmanager/protobuf/f:Bb	()Lcom/google/tagmanager/protobuf/e;
      //   231: astore 8
      //   233: iload_3
      //   234: iconst_1
      //   235: iand
      //   236: iconst_1
      //   237: if_icmpeq +1448 -> 1685
      //   240: iload_3
      //   241: istore 5
      //   243: aload_0
      //   244: new 124	com/google/tagmanager/protobuf/k
      //   247: dup
      //   248: invokespecial 125	com/google/tagmanager/protobuf/k:<init>	()V
      //   251: putfield 127	com/google/analytics/containertag/proto/Serving$Resource:key_	Lcom/google/tagmanager/protobuf/l;
      //   254: iload_3
      //   255: iconst_1
      //   256: ior
      //   257: istore 7
      //   259: iload 7
      //   261: istore_3
      //   262: iload 7
      //   264: istore 5
      //   266: iload 7
      //   268: istore 6
      //   270: aload_0
      //   271: getfield 127	com/google/analytics/containertag/proto/Serving$Resource:key_	Lcom/google/tagmanager/protobuf/l;
      //   274: aload 8
      //   276: invokeinterface 133 2 0
      //   281: iload 4
      //   283: istore_3
      //   284: iload 7
      //   286: istore 4
      //   288: goto +1406 -> 1694
      //   291: iload_3
      //   292: iconst_2
      //   293: iand
      //   294: iconst_2
      //   295: if_icmpeq +1384 -> 1679
      //   298: iload_3
      //   299: istore 5
      //   301: aload_0
      //   302: new 135	java/util/ArrayList
      //   305: dup
      //   306: invokespecial 136	java/util/ArrayList:<init>	()V
      //   309: putfield 138	com/google/analytics/containertag/proto/Serving$Resource:value_	Ljava/util/List;
      //   312: iload_3
      //   313: iconst_2
      //   314: ior
      //   315: istore 7
      //   317: iload 7
      //   319: istore_3
      //   320: iload 7
      //   322: istore 5
      //   324: iload 7
      //   326: istore 6
      //   328: aload_0
      //   329: getfield 138	com/google/analytics/containertag/proto/Serving$Resource:value_	Ljava/util/List;
      //   332: aload_1
      //   333: getstatic 141	com/google/analytics/midtier/proto/containertag/TypeSystem$Value:gW	Lcom/google/tagmanager/protobuf/q;
      //   336: aload_2
      //   337: invokevirtual 144	com/google/tagmanager/protobuf/f:a	(Lcom/google/tagmanager/protobuf/q;Lcom/google/tagmanager/protobuf/g;)Lcom/google/tagmanager/protobuf/n;
      //   340: invokeinterface 150 2 0
      //   345: pop
      //   346: iload 4
      //   348: istore_3
      //   349: iload 7
      //   351: istore 4
      //   353: goto +1341 -> 1694
      //   356: iload_3
      //   357: iconst_4
      //   358: iand
      //   359: iconst_4
      //   360: if_icmpeq +1313 -> 1673
      //   363: iload_3
      //   364: istore 5
      //   366: aload_0
      //   367: new 135	java/util/ArrayList
      //   370: dup
      //   371: invokespecial 136	java/util/ArrayList:<init>	()V
      //   374: putfield 152	com/google/analytics/containertag/proto/Serving$Resource:property_	Ljava/util/List;
      //   377: iload_3
      //   378: iconst_4
      //   379: ior
      //   380: istore 7
      //   382: iload 7
      //   384: istore_3
      //   385: iload 7
      //   387: istore 5
      //   389: iload 7
      //   391: istore 6
      //   393: aload_0
      //   394: getfield 152	com/google/analytics/containertag/proto/Serving$Resource:property_	Ljava/util/List;
      //   397: aload_1
      //   398: getstatic 155	com/google/analytics/containertag/proto/Serving$Property:gW	Lcom/google/tagmanager/protobuf/q;
      //   401: aload_2
      //   402: invokevirtual 144	com/google/tagmanager/protobuf/f:a	(Lcom/google/tagmanager/protobuf/q;Lcom/google/tagmanager/protobuf/g;)Lcom/google/tagmanager/protobuf/n;
      //   405: invokeinterface 150 2 0
      //   410: pop
      //   411: iload 4
      //   413: istore_3
      //   414: iload 7
      //   416: istore 4
      //   418: goto +1276 -> 1694
      //   421: iload_3
      //   422: bipush 8
      //   424: iand
      //   425: bipush 8
      //   427: if_icmpeq +1240 -> 1667
      //   430: iload_3
      //   431: istore 5
      //   433: aload_0
      //   434: new 135	java/util/ArrayList
      //   437: dup
      //   438: invokespecial 136	java/util/ArrayList:<init>	()V
      //   441: putfield 157	com/google/analytics/containertag/proto/Serving$Resource:macro_	Ljava/util/List;
      //   444: iload_3
      //   445: bipush 8
      //   447: ior
      //   448: istore 7
      //   450: iload 7
      //   452: istore_3
      //   453: iload 7
      //   455: istore 5
      //   457: iload 7
      //   459: istore 6
      //   461: aload_0
      //   462: getfield 157	com/google/analytics/containertag/proto/Serving$Resource:macro_	Ljava/util/List;
      //   465: aload_1
      //   466: getstatic 160	com/google/analytics/containertag/proto/Serving$FunctionCall:gW	Lcom/google/tagmanager/protobuf/q;
      //   469: aload_2
      //   470: invokevirtual 144	com/google/tagmanager/protobuf/f:a	(Lcom/google/tagmanager/protobuf/q;Lcom/google/tagmanager/protobuf/g;)Lcom/google/tagmanager/protobuf/n;
      //   473: invokeinterface 150 2 0
      //   478: pop
      //   479: iload 4
      //   481: istore_3
      //   482: iload 7
      //   484: istore 4
      //   486: goto +1208 -> 1694
      //   489: iload_3
      //   490: bipush 16
      //   492: iand
      //   493: bipush 16
      //   495: if_icmpeq +1166 -> 1661
      //   498: iload_3
      //   499: istore 5
      //   501: aload_0
      //   502: new 135	java/util/ArrayList
      //   505: dup
      //   506: invokespecial 136	java/util/ArrayList:<init>	()V
      //   509: putfield 162	com/google/analytics/containertag/proto/Serving$Resource:tag_	Ljava/util/List;
      //   512: iload_3
      //   513: bipush 16
      //   515: ior
      //   516: istore 7
      //   518: iload 7
      //   520: istore_3
      //   521: iload 7
      //   523: istore 5
      //   525: iload 7
      //   527: istore 6
      //   529: aload_0
      //   530: getfield 162	com/google/analytics/containertag/proto/Serving$Resource:tag_	Ljava/util/List;
      //   533: aload_1
      //   534: getstatic 160	com/google/analytics/containertag/proto/Serving$FunctionCall:gW	Lcom/google/tagmanager/protobuf/q;
      //   537: aload_2
      //   538: invokevirtual 144	com/google/tagmanager/protobuf/f:a	(Lcom/google/tagmanager/protobuf/q;Lcom/google/tagmanager/protobuf/g;)Lcom/google/tagmanager/protobuf/n;
      //   541: invokeinterface 150 2 0
      //   546: pop
      //   547: iload 4
      //   549: istore_3
      //   550: iload 7
      //   552: istore 4
      //   554: goto +1140 -> 1694
      //   557: iload_3
      //   558: bipush 32
      //   560: iand
      //   561: bipush 32
      //   563: if_icmpeq +1092 -> 1655
      //   566: iload_3
      //   567: istore 5
      //   569: aload_0
      //   570: new 135	java/util/ArrayList
      //   573: dup
      //   574: invokespecial 136	java/util/ArrayList:<init>	()V
      //   577: putfield 164	com/google/analytics/containertag/proto/Serving$Resource:predicate_	Ljava/util/List;
      //   580: iload_3
      //   581: bipush 32
      //   583: ior
      //   584: istore 7
      //   586: iload 7
      //   588: istore_3
      //   589: iload 7
      //   591: istore 5
      //   593: iload 7
      //   595: istore 6
      //   597: aload_0
      //   598: getfield 164	com/google/analytics/containertag/proto/Serving$Resource:predicate_	Ljava/util/List;
      //   601: aload_1
      //   602: getstatic 160	com/google/analytics/containertag/proto/Serving$FunctionCall:gW	Lcom/google/tagmanager/protobuf/q;
      //   605: aload_2
      //   606: invokevirtual 144	com/google/tagmanager/protobuf/f:a	(Lcom/google/tagmanager/protobuf/q;Lcom/google/tagmanager/protobuf/g;)Lcom/google/tagmanager/protobuf/n;
      //   609: invokeinterface 150 2 0
      //   614: pop
      //   615: iload 4
      //   617: istore_3
      //   618: iload 7
      //   620: istore 4
      //   622: goto +1072 -> 1694
      //   625: iload_3
      //   626: bipush 64
      //   628: iand
      //   629: bipush 64
      //   631: if_icmpeq +1018 -> 1649
      //   634: iload_3
      //   635: istore 5
      //   637: aload_0
      //   638: new 135	java/util/ArrayList
      //   641: dup
      //   642: invokespecial 136	java/util/ArrayList:<init>	()V
      //   645: putfield 166	com/google/analytics/containertag/proto/Serving$Resource:rule_	Ljava/util/List;
      //   648: iload_3
      //   649: bipush 64
      //   651: ior
      //   652: istore 7
      //   654: iload 7
      //   656: istore_3
      //   657: iload 7
      //   659: istore 5
      //   661: iload 7
      //   663: istore 6
      //   665: aload_0
      //   666: getfield 166	com/google/analytics/containertag/proto/Serving$Resource:rule_	Ljava/util/List;
      //   669: aload_1
      //   670: getstatic 169	com/google/analytics/containertag/proto/Serving$Rule:gW	Lcom/google/tagmanager/protobuf/q;
      //   673: aload_2
      //   674: invokevirtual 144	com/google/tagmanager/protobuf/f:a	(Lcom/google/tagmanager/protobuf/q;Lcom/google/tagmanager/protobuf/g;)Lcom/google/tagmanager/protobuf/n;
      //   677: invokeinterface 150 2 0
      //   682: pop
      //   683: iload 4
      //   685: istore_3
      //   686: iload 7
      //   688: istore 4
      //   690: goto +1004 -> 1694
      //   693: iload_3
      //   694: istore 5
      //   696: aload_1
      //   697: invokevirtual 122	com/google/tagmanager/protobuf/f:Bb	()Lcom/google/tagmanager/protobuf/e;
      //   700: astore 8
      //   702: iload_3
      //   703: istore 5
      //   705: aload_0
      //   706: aload_0
      //   707: getfield 171	com/google/analytics/containertag/proto/Serving$Resource:bitField0_	I
      //   710: iconst_1
      //   711: ior
      //   712: putfield 171	com/google/analytics/containertag/proto/Serving$Resource:bitField0_	I
      //   715: iload_3
      //   716: istore 5
      //   718: aload_0
      //   719: aload 8
      //   721: putfield 173	com/google/analytics/containertag/proto/Serving$Resource:previewAuthCode_	Ljava/lang/Object;
      //   724: iload_3
      //   725: istore 5
      //   727: iload 4
      //   729: istore_3
      //   730: iload 5
      //   732: istore 4
      //   734: goto +960 -> 1694
      //   737: iload_3
      //   738: istore 5
      //   740: aload_1
      //   741: invokevirtual 122	com/google/tagmanager/protobuf/f:Bb	()Lcom/google/tagmanager/protobuf/e;
      //   744: astore 8
      //   746: iload_3
      //   747: istore 5
      //   749: aload_0
      //   750: aload_0
      //   751: getfield 171	com/google/analytics/containertag/proto/Serving$Resource:bitField0_	I
      //   754: iconst_2
      //   755: ior
      //   756: putfield 171	com/google/analytics/containertag/proto/Serving$Resource:bitField0_	I
      //   759: iload_3
      //   760: istore 5
      //   762: aload_0
      //   763: aload 8
      //   765: putfield 175	com/google/analytics/containertag/proto/Serving$Resource:malwareScanAuthCode_	Ljava/lang/Object;
      //   768: iload_3
      //   769: istore 5
      //   771: iload 4
      //   773: istore_3
      //   774: iload 5
      //   776: istore 4
      //   778: goto +916 -> 1694
      //   781: iload_3
      //   782: istore 5
      //   784: aload_1
      //   785: invokevirtual 122	com/google/tagmanager/protobuf/f:Bb	()Lcom/google/tagmanager/protobuf/e;
      //   788: astore 8
      //   790: iload_3
      //   791: istore 5
      //   793: aload_0
      //   794: aload_0
      //   795: getfield 171	com/google/analytics/containertag/proto/Serving$Resource:bitField0_	I
      //   798: iconst_4
      //   799: ior
      //   800: putfield 171	com/google/analytics/containertag/proto/Serving$Resource:bitField0_	I
      //   803: iload_3
      //   804: istore 5
      //   806: aload_0
      //   807: aload 8
      //   809: putfield 177	com/google/analytics/containertag/proto/Serving$Resource:templateVersionSet_	Ljava/lang/Object;
      //   812: iload_3
      //   813: istore 5
      //   815: iload 4
      //   817: istore_3
      //   818: iload 5
      //   820: istore 4
      //   822: goto +872 -> 1694
      //   825: iload_3
      //   826: istore 5
      //   828: aload_1
      //   829: invokevirtual 122	com/google/tagmanager/protobuf/f:Bb	()Lcom/google/tagmanager/protobuf/e;
      //   832: astore 8
      //   834: iload_3
      //   835: istore 5
      //   837: aload_0
      //   838: aload_0
      //   839: getfield 171	com/google/analytics/containertag/proto/Serving$Resource:bitField0_	I
      //   842: bipush 8
      //   844: ior
      //   845: putfield 171	com/google/analytics/containertag/proto/Serving$Resource:bitField0_	I
      //   848: iload_3
      //   849: istore 5
      //   851: aload_0
      //   852: aload 8
      //   854: putfield 179	com/google/analytics/containertag/proto/Serving$Resource:version_	Ljava/lang/Object;
      //   857: iload_3
      //   858: istore 5
      //   860: iload 4
      //   862: istore_3
      //   863: iload 5
      //   865: istore 4
      //   867: goto +827 -> 1694
      //   870: iload_3
      //   871: istore 5
      //   873: aload_0
      //   874: getfield 171	com/google/analytics/containertag/proto/Serving$Resource:bitField0_	I
      //   877: bipush 16
      //   879: iand
      //   880: bipush 16
      //   882: if_icmpne +761 -> 1643
      //   885: iload_3
      //   886: istore 5
      //   888: aload_0
      //   889: getfield 181	com/google/analytics/containertag/proto/Serving$Resource:liveJsCacheOption_	Lcom/google/analytics/containertag/proto/Serving$CacheOption;
      //   892: invokevirtual 187	com/google/analytics/containertag/proto/Serving$CacheOption:fL	()Lcom/google/analytics/containertag/proto/Serving$CacheOption$a;
      //   895: astore 8
      //   897: iload_3
      //   898: istore 5
      //   900: aload_0
      //   901: aload_1
      //   902: getstatic 188	com/google/analytics/containertag/proto/Serving$CacheOption:gW	Lcom/google/tagmanager/protobuf/q;
      //   905: aload_2
      //   906: invokevirtual 144	com/google/tagmanager/protobuf/f:a	(Lcom/google/tagmanager/protobuf/q;Lcom/google/tagmanager/protobuf/g;)Lcom/google/tagmanager/protobuf/n;
      //   909: checkcast 183	com/google/analytics/containertag/proto/Serving$CacheOption
      //   912: putfield 181	com/google/analytics/containertag/proto/Serving$Resource:liveJsCacheOption_	Lcom/google/analytics/containertag/proto/Serving$CacheOption;
      //   915: aload 8
      //   917: ifnull +28 -> 945
      //   920: iload_3
      //   921: istore 5
      //   923: aload 8
      //   925: aload_0
      //   926: getfield 181	com/google/analytics/containertag/proto/Serving$Resource:liveJsCacheOption_	Lcom/google/analytics/containertag/proto/Serving$CacheOption;
      //   929: invokevirtual 194	com/google/analytics/containertag/proto/Serving$CacheOption$a:c	(Lcom/google/analytics/containertag/proto/Serving$CacheOption;)Lcom/google/analytics/containertag/proto/Serving$CacheOption$a;
      //   932: pop
      //   933: iload_3
      //   934: istore 5
      //   936: aload_0
      //   937: aload 8
      //   939: invokevirtual 198	com/google/analytics/containertag/proto/Serving$CacheOption$a:fT	()Lcom/google/analytics/containertag/proto/Serving$CacheOption;
      //   942: putfield 181	com/google/analytics/containertag/proto/Serving$Resource:liveJsCacheOption_	Lcom/google/analytics/containertag/proto/Serving$CacheOption;
      //   945: iload_3
      //   946: istore 5
      //   948: aload_0
      //   949: aload_0
      //   950: getfield 171	com/google/analytics/containertag/proto/Serving$Resource:bitField0_	I
      //   953: bipush 16
      //   955: ior
      //   956: putfield 171	com/google/analytics/containertag/proto/Serving$Resource:bitField0_	I
      //   959: iload_3
      //   960: istore 5
      //   962: iload 4
      //   964: istore_3
      //   965: iload 5
      //   967: istore 4
      //   969: goto +725 -> 1694
      //   972: iload_3
      //   973: istore 5
      //   975: aload_0
      //   976: aload_0
      //   977: getfield 171	com/google/analytics/containertag/proto/Serving$Resource:bitField0_	I
      //   980: bipush 32
      //   982: ior
      //   983: putfield 171	com/google/analytics/containertag/proto/Serving$Resource:bitField0_	I
      //   986: iload_3
      //   987: istore 5
      //   989: aload_0
      //   990: aload_1
      //   991: invokevirtual 202	com/google/tagmanager/protobuf/f:readFloat	()F
      //   994: putfield 204	com/google/analytics/containertag/proto/Serving$Resource:reportingSampleRate_	F
      //   997: iload_3
      //   998: istore 5
      //   1000: iload 4
      //   1002: istore_3
      //   1003: iload 5
      //   1005: istore 4
      //   1007: goto +687 -> 1694
      //   1010: iload_3
      //   1011: istore 5
      //   1013: aload_1
      //   1014: invokevirtual 122	com/google/tagmanager/protobuf/f:Bb	()Lcom/google/tagmanager/protobuf/e;
      //   1017: astore 8
      //   1019: iload_3
      //   1020: sipush 16384
      //   1023: iand
      //   1024: sipush 16384
      //   1027: if_icmpeq +610 -> 1637
      //   1030: iload_3
      //   1031: istore 5
      //   1033: aload_0
      //   1034: new 124	com/google/tagmanager/protobuf/k
      //   1037: dup
      //   1038: invokespecial 125	com/google/tagmanager/protobuf/k:<init>	()V
      //   1041: putfield 206	com/google/analytics/containertag/proto/Serving$Resource:usageContext_	Lcom/google/tagmanager/protobuf/l;
      //   1044: iload_3
      //   1045: sipush 16384
      //   1048: ior
      //   1049: istore 7
      //   1051: iload 7
      //   1053: istore_3
      //   1054: iload 7
      //   1056: istore 5
      //   1058: iload 7
      //   1060: istore 6
      //   1062: aload_0
      //   1063: getfield 206	com/google/analytics/containertag/proto/Serving$Resource:usageContext_	Lcom/google/tagmanager/protobuf/l;
      //   1066: aload 8
      //   1068: invokeinterface 133 2 0
      //   1073: iload 4
      //   1075: istore_3
      //   1076: iload 7
      //   1078: istore 4
      //   1080: goto +614 -> 1694
      //   1083: iload_3
      //   1084: istore 5
      //   1086: aload_0
      //   1087: aload_0
      //   1088: getfield 171	com/google/analytics/containertag/proto/Serving$Resource:bitField0_	I
      //   1091: sipush 128
      //   1094: ior
      //   1095: putfield 171	com/google/analytics/containertag/proto/Serving$Resource:bitField0_	I
      //   1098: iload_3
      //   1099: istore 5
      //   1101: aload_0
      //   1102: aload_1
      //   1103: invokevirtual 209	com/google/tagmanager/protobuf/f:AW	()I
      //   1106: putfield 211	com/google/analytics/containertag/proto/Serving$Resource:resourceFormatVersion_	I
      //   1109: iload_3
      //   1110: istore 5
      //   1112: iload 4
      //   1114: istore_3
      //   1115: iload 5
      //   1117: istore 4
      //   1119: goto +575 -> 1694
      //   1122: iload_3
      //   1123: istore 5
      //   1125: aload_0
      //   1126: aload_0
      //   1127: getfield 171	com/google/analytics/containertag/proto/Serving$Resource:bitField0_	I
      //   1130: bipush 64
      //   1132: ior
      //   1133: putfield 171	com/google/analytics/containertag/proto/Serving$Resource:bitField0_	I
      //   1136: iload_3
      //   1137: istore 5
      //   1139: aload_0
      //   1140: aload_1
      //   1141: invokevirtual 215	com/google/tagmanager/protobuf/f:AZ	()Z
      //   1144: putfield 217	com/google/analytics/containertag/proto/Serving$Resource:enableAutoEventTracking_	Z
      //   1147: iload_3
      //   1148: istore 5
      //   1150: iload 4
      //   1152: istore_3
      //   1153: iload 5
      //   1155: istore 4
      //   1157: goto +537 -> 1694
      //   1160: iload_3
      //   1161: iconst_1
      //   1162: iand
      //   1163: iconst_1
      //   1164: if_icmpne +18 -> 1182
      //   1167: aload_0
      //   1168: new 219	com/google/tagmanager/protobuf/t
      //   1171: dup
      //   1172: aload_0
      //   1173: getfield 127	com/google/analytics/containertag/proto/Serving$Resource:key_	Lcom/google/tagmanager/protobuf/l;
      //   1176: invokespecial 222	com/google/tagmanager/protobuf/t:<init>	(Lcom/google/tagmanager/protobuf/l;)V
      //   1179: putfield 127	com/google/analytics/containertag/proto/Serving$Resource:key_	Lcom/google/tagmanager/protobuf/l;
      //   1182: iload_3
      //   1183: iconst_2
      //   1184: iand
      //   1185: iconst_2
      //   1186: if_icmpne +14 -> 1200
      //   1189: aload_0
      //   1190: aload_0
      //   1191: getfield 138	com/google/analytics/containertag/proto/Serving$Resource:value_	Ljava/util/List;
      //   1194: invokestatic 228	java/util/Collections:unmodifiableList	(Ljava/util/List;)Ljava/util/List;
      //   1197: putfield 138	com/google/analytics/containertag/proto/Serving$Resource:value_	Ljava/util/List;
      //   1200: iload_3
      //   1201: iconst_4
      //   1202: iand
      //   1203: iconst_4
      //   1204: if_icmpne +14 -> 1218
      //   1207: aload_0
      //   1208: aload_0
      //   1209: getfield 152	com/google/analytics/containertag/proto/Serving$Resource:property_	Ljava/util/List;
      //   1212: invokestatic 228	java/util/Collections:unmodifiableList	(Ljava/util/List;)Ljava/util/List;
      //   1215: putfield 152	com/google/analytics/containertag/proto/Serving$Resource:property_	Ljava/util/List;
      //   1218: iload_3
      //   1219: bipush 8
      //   1221: iand
      //   1222: bipush 8
      //   1224: if_icmpne +14 -> 1238
      //   1227: aload_0
      //   1228: aload_0
      //   1229: getfield 157	com/google/analytics/containertag/proto/Serving$Resource:macro_	Ljava/util/List;
      //   1232: invokestatic 228	java/util/Collections:unmodifiableList	(Ljava/util/List;)Ljava/util/List;
      //   1235: putfield 157	com/google/analytics/containertag/proto/Serving$Resource:macro_	Ljava/util/List;
      //   1238: iload_3
      //   1239: bipush 16
      //   1241: iand
      //   1242: bipush 16
      //   1244: if_icmpne +14 -> 1258
      //   1247: aload_0
      //   1248: aload_0
      //   1249: getfield 162	com/google/analytics/containertag/proto/Serving$Resource:tag_	Ljava/util/List;
      //   1252: invokestatic 228	java/util/Collections:unmodifiableList	(Ljava/util/List;)Ljava/util/List;
      //   1255: putfield 162	com/google/analytics/containertag/proto/Serving$Resource:tag_	Ljava/util/List;
      //   1258: iload_3
      //   1259: bipush 32
      //   1261: iand
      //   1262: bipush 32
      //   1264: if_icmpne +14 -> 1278
      //   1267: aload_0
      //   1268: aload_0
      //   1269: getfield 164	com/google/analytics/containertag/proto/Serving$Resource:predicate_	Ljava/util/List;
      //   1272: invokestatic 228	java/util/Collections:unmodifiableList	(Ljava/util/List;)Ljava/util/List;
      //   1275: putfield 164	com/google/analytics/containertag/proto/Serving$Resource:predicate_	Ljava/util/List;
      //   1278: iload_3
      //   1279: bipush 64
      //   1281: iand
      //   1282: bipush 64
      //   1284: if_icmpne +14 -> 1298
      //   1287: aload_0
      //   1288: aload_0
      //   1289: getfield 166	com/google/analytics/containertag/proto/Serving$Resource:rule_	Ljava/util/List;
      //   1292: invokestatic 228	java/util/Collections:unmodifiableList	(Ljava/util/List;)Ljava/util/List;
      //   1295: putfield 166	com/google/analytics/containertag/proto/Serving$Resource:rule_	Ljava/util/List;
      //   1298: iload_3
      //   1299: sipush 16384
      //   1302: iand
      //   1303: sipush 16384
      //   1306: if_icmpne +18 -> 1324
      //   1309: aload_0
      //   1310: new 219	com/google/tagmanager/protobuf/t
      //   1313: dup
      //   1314: aload_0
      //   1315: getfield 206	com/google/analytics/containertag/proto/Serving$Resource:usageContext_	Lcom/google/tagmanager/protobuf/l;
      //   1318: invokespecial 222	com/google/tagmanager/protobuf/t:<init>	(Lcom/google/tagmanager/protobuf/l;)V
      //   1321: putfield 206	com/google/analytics/containertag/proto/Serving$Resource:usageContext_	Lcom/google/tagmanager/protobuf/l;
      //   1324: aload 10
      //   1326: invokevirtual 231	com/google/tagmanager/protobuf/CodedOutputStream:flush	()V
      //   1329: aload_0
      //   1330: aload 9
      //   1332: invokevirtual 236	com/google/tagmanager/protobuf/e$b:AR	()Lcom/google/tagmanager/protobuf/e;
      //   1335: putfield 91	com/google/analytics/containertag/proto/Serving$Resource:unknownFields	Lcom/google/tagmanager/protobuf/e;
      //   1338: aload_0
      //   1339: invokevirtual 239	com/google/analytics/containertag/proto/Serving$Resource:BD	()V
      //   1342: return
      //   1343: astore_1
      //   1344: aload_0
      //   1345: aload 9
      //   1347: invokevirtual 236	com/google/tagmanager/protobuf/e$b:AR	()Lcom/google/tagmanager/protobuf/e;
      //   1350: putfield 91	com/google/analytics/containertag/proto/Serving$Resource:unknownFields	Lcom/google/tagmanager/protobuf/e;
      //   1353: goto -15 -> 1338
      //   1356: astore_1
      //   1357: aload_0
      //   1358: aload 9
      //   1360: invokevirtual 236	com/google/tagmanager/protobuf/e$b:AR	()Lcom/google/tagmanager/protobuf/e;
      //   1363: putfield 91	com/google/analytics/containertag/proto/Serving$Resource:unknownFields	Lcom/google/tagmanager/protobuf/e;
      //   1366: aload_1
      //   1367: athrow
      //   1368: astore_1
      //   1369: iload_3
      //   1370: istore 5
      //   1372: aload_1
      //   1373: aload_0
      //   1374: invokevirtual 243	com/google/tagmanager/protobuf/InvalidProtocolBufferException:h	(Lcom/google/tagmanager/protobuf/n;)Lcom/google/tagmanager/protobuf/InvalidProtocolBufferException;
      //   1377: athrow
      //   1378: astore_1
      //   1379: iload 5
      //   1381: iconst_1
      //   1382: iand
      //   1383: iconst_1
      //   1384: if_icmpne +18 -> 1402
      //   1387: aload_0
      //   1388: new 219	com/google/tagmanager/protobuf/t
      //   1391: dup
      //   1392: aload_0
      //   1393: getfield 127	com/google/analytics/containertag/proto/Serving$Resource:key_	Lcom/google/tagmanager/protobuf/l;
      //   1396: invokespecial 222	com/google/tagmanager/protobuf/t:<init>	(Lcom/google/tagmanager/protobuf/l;)V
      //   1399: putfield 127	com/google/analytics/containertag/proto/Serving$Resource:key_	Lcom/google/tagmanager/protobuf/l;
      //   1402: iload 5
      //   1404: iconst_2
      //   1405: iand
      //   1406: iconst_2
      //   1407: if_icmpne +14 -> 1421
      //   1410: aload_0
      //   1411: aload_0
      //   1412: getfield 138	com/google/analytics/containertag/proto/Serving$Resource:value_	Ljava/util/List;
      //   1415: invokestatic 228	java/util/Collections:unmodifiableList	(Ljava/util/List;)Ljava/util/List;
      //   1418: putfield 138	com/google/analytics/containertag/proto/Serving$Resource:value_	Ljava/util/List;
      //   1421: iload 5
      //   1423: iconst_4
      //   1424: iand
      //   1425: iconst_4
      //   1426: if_icmpne +14 -> 1440
      //   1429: aload_0
      //   1430: aload_0
      //   1431: getfield 152	com/google/analytics/containertag/proto/Serving$Resource:property_	Ljava/util/List;
      //   1434: invokestatic 228	java/util/Collections:unmodifiableList	(Ljava/util/List;)Ljava/util/List;
      //   1437: putfield 152	com/google/analytics/containertag/proto/Serving$Resource:property_	Ljava/util/List;
      //   1440: iload 5
      //   1442: bipush 8
      //   1444: iand
      //   1445: bipush 8
      //   1447: if_icmpne +14 -> 1461
      //   1450: aload_0
      //   1451: aload_0
      //   1452: getfield 157	com/google/analytics/containertag/proto/Serving$Resource:macro_	Ljava/util/List;
      //   1455: invokestatic 228	java/util/Collections:unmodifiableList	(Ljava/util/List;)Ljava/util/List;
      //   1458: putfield 157	com/google/analytics/containertag/proto/Serving$Resource:macro_	Ljava/util/List;
      //   1461: iload 5
      //   1463: bipush 16
      //   1465: iand
      //   1466: bipush 16
      //   1468: if_icmpne +14 -> 1482
      //   1471: aload_0
      //   1472: aload_0
      //   1473: getfield 162	com/google/analytics/containertag/proto/Serving$Resource:tag_	Ljava/util/List;
      //   1476: invokestatic 228	java/util/Collections:unmodifiableList	(Ljava/util/List;)Ljava/util/List;
      //   1479: putfield 162	com/google/analytics/containertag/proto/Serving$Resource:tag_	Ljava/util/List;
      //   1482: iload 5
      //   1484: bipush 32
      //   1486: iand
      //   1487: bipush 32
      //   1489: if_icmpne +14 -> 1503
      //   1492: aload_0
      //   1493: aload_0
      //   1494: getfield 164	com/google/analytics/containertag/proto/Serving$Resource:predicate_	Ljava/util/List;
      //   1497: invokestatic 228	java/util/Collections:unmodifiableList	(Ljava/util/List;)Ljava/util/List;
      //   1500: putfield 164	com/google/analytics/containertag/proto/Serving$Resource:predicate_	Ljava/util/List;
      //   1503: iload 5
      //   1505: bipush 64
      //   1507: iand
      //   1508: bipush 64
      //   1510: if_icmpne +14 -> 1524
      //   1513: aload_0
      //   1514: aload_0
      //   1515: getfield 166	com/google/analytics/containertag/proto/Serving$Resource:rule_	Ljava/util/List;
      //   1518: invokestatic 228	java/util/Collections:unmodifiableList	(Ljava/util/List;)Ljava/util/List;
      //   1521: putfield 166	com/google/analytics/containertag/proto/Serving$Resource:rule_	Ljava/util/List;
      //   1524: iload 5
      //   1526: sipush 16384
      //   1529: iand
      //   1530: sipush 16384
      //   1533: if_icmpne +18 -> 1551
      //   1536: aload_0
      //   1537: new 219	com/google/tagmanager/protobuf/t
      //   1540: dup
      //   1541: aload_0
      //   1542: getfield 206	com/google/analytics/containertag/proto/Serving$Resource:usageContext_	Lcom/google/tagmanager/protobuf/l;
      //   1545: invokespecial 222	com/google/tagmanager/protobuf/t:<init>	(Lcom/google/tagmanager/protobuf/l;)V
      //   1548: putfield 206	com/google/analytics/containertag/proto/Serving$Resource:usageContext_	Lcom/google/tagmanager/protobuf/l;
      //   1551: aload 10
      //   1553: invokevirtual 231	com/google/tagmanager/protobuf/CodedOutputStream:flush	()V
      //   1556: aload_0
      //   1557: aload 9
      //   1559: invokevirtual 236	com/google/tagmanager/protobuf/e$b:AR	()Lcom/google/tagmanager/protobuf/e;
      //   1562: putfield 91	com/google/analytics/containertag/proto/Serving$Resource:unknownFields	Lcom/google/tagmanager/protobuf/e;
      //   1565: aload_0
      //   1566: invokevirtual 239	com/google/analytics/containertag/proto/Serving$Resource:BD	()V
      //   1569: aload_1
      //   1570: athrow
      //   1571: astore_1
      //   1572: iload_3
      //   1573: istore 5
      //   1575: new 96	com/google/tagmanager/protobuf/InvalidProtocolBufferException
      //   1578: dup
      //   1579: aload_1
      //   1580: invokevirtual 247	java/io/IOException:getMessage	()Ljava/lang/String;
      //   1583: invokespecial 250	com/google/tagmanager/protobuf/InvalidProtocolBufferException:<init>	(Ljava/lang/String;)V
      //   1586: aload_0
      //   1587: invokevirtual 243	com/google/tagmanager/protobuf/InvalidProtocolBufferException:h	(Lcom/google/tagmanager/protobuf/n;)Lcom/google/tagmanager/protobuf/InvalidProtocolBufferException;
      //   1590: athrow
      //   1591: astore_2
      //   1592: aload_0
      //   1593: aload 9
      //   1595: invokevirtual 236	com/google/tagmanager/protobuf/e$b:AR	()Lcom/google/tagmanager/protobuf/e;
      //   1598: putfield 91	com/google/analytics/containertag/proto/Serving$Resource:unknownFields	Lcom/google/tagmanager/protobuf/e;
      //   1601: goto -36 -> 1565
      //   1604: astore_1
      //   1605: aload_0
      //   1606: aload 9
      //   1608: invokevirtual 236	com/google/tagmanager/protobuf/e$b:AR	()Lcom/google/tagmanager/protobuf/e;
      //   1611: putfield 91	com/google/analytics/containertag/proto/Serving$Resource:unknownFields	Lcom/google/tagmanager/protobuf/e;
      //   1614: aload_1
      //   1615: athrow
      //   1616: astore_1
      //   1617: iload_3
      //   1618: istore 5
      //   1620: goto -241 -> 1379
      //   1623: astore_1
      //   1624: iload 5
      //   1626: istore_3
      //   1627: goto -55 -> 1572
      //   1630: astore_1
      //   1631: iload 6
      //   1633: istore_3
      //   1634: goto -265 -> 1369
      //   1637: iload_3
      //   1638: istore 7
      //   1640: goto -589 -> 1051
      //   1643: aconst_null
      //   1644: astore 8
      //   1646: goto -749 -> 897
      //   1649: iload_3
      //   1650: istore 7
      //   1652: goto -998 -> 654
      //   1655: iload_3
      //   1656: istore 7
      //   1658: goto -1072 -> 586
      //   1661: iload_3
      //   1662: istore 7
      //   1664: goto -1146 -> 518
      //   1667: iload_3
      //   1668: istore 7
      //   1670: goto -1220 -> 450
      //   1673: iload_3
      //   1674: istore 7
      //   1676: goto -1294 -> 382
      //   1679: iload_3
      //   1680: istore 7
      //   1682: goto -1365 -> 317
      //   1685: iload_3
      //   1686: istore 7
      //   1688: goto -1429 -> 259
      //   1691: goto -1495 -> 196
      //   1694: iload 4
      //   1696: istore 5
      //   1698: iload_3
      //   1699: istore 4
      //   1701: iload 5
      //   1703: istore_3
      //   1704: goto -1669 -> 35
      //   1707: iconst_1
      //   1708: istore 5
      //   1710: iload_3
      //   1711: istore 4
      //   1713: iload 5
      //   1715: istore_3
      //   1716: goto -22 -> 1694
      // Local variable table:
      //   start	length	slot	name	signature
      //   0	1719	0	this	Resource
      //   0	1719	1	paramf	f
      //   0	1719	2	paramg	g
      //   19	1697	3	i	int
      //   33	1679	4	j	int
      //   41	1673	5	k	int
      //   47	1585	6	m	int
      //   257	1430	7	n	int
      //   231	1414	8	localObject	Object
      //   23	1584	9	localb	com.google.tagmanager.protobuf.e.b
      //   30	1522	10	localCodedOutputStream	CodedOutputStream
      // Exception table:
      //   from	to	target	type
      //   1324	1329	1343	java/io/IOException
      //   1324	1329	1356	finally
      //   43	49	1368	com/google/tagmanager/protobuf/InvalidProtocolBufferException
      //   199	212	1368	com/google/tagmanager/protobuf/InvalidProtocolBufferException
      //   227	233	1368	com/google/tagmanager/protobuf/InvalidProtocolBufferException
      //   243	254	1368	com/google/tagmanager/protobuf/InvalidProtocolBufferException
      //   301	312	1368	com/google/tagmanager/protobuf/InvalidProtocolBufferException
      //   366	377	1368	com/google/tagmanager/protobuf/InvalidProtocolBufferException
      //   433	444	1368	com/google/tagmanager/protobuf/InvalidProtocolBufferException
      //   501	512	1368	com/google/tagmanager/protobuf/InvalidProtocolBufferException
      //   569	580	1368	com/google/tagmanager/protobuf/InvalidProtocolBufferException
      //   637	648	1368	com/google/tagmanager/protobuf/InvalidProtocolBufferException
      //   696	702	1368	com/google/tagmanager/protobuf/InvalidProtocolBufferException
      //   705	715	1368	com/google/tagmanager/protobuf/InvalidProtocolBufferException
      //   718	724	1368	com/google/tagmanager/protobuf/InvalidProtocolBufferException
      //   740	746	1368	com/google/tagmanager/protobuf/InvalidProtocolBufferException
      //   749	759	1368	com/google/tagmanager/protobuf/InvalidProtocolBufferException
      //   762	768	1368	com/google/tagmanager/protobuf/InvalidProtocolBufferException
      //   784	790	1368	com/google/tagmanager/protobuf/InvalidProtocolBufferException
      //   793	803	1368	com/google/tagmanager/protobuf/InvalidProtocolBufferException
      //   806	812	1368	com/google/tagmanager/protobuf/InvalidProtocolBufferException
      //   828	834	1368	com/google/tagmanager/protobuf/InvalidProtocolBufferException
      //   837	848	1368	com/google/tagmanager/protobuf/InvalidProtocolBufferException
      //   851	857	1368	com/google/tagmanager/protobuf/InvalidProtocolBufferException
      //   873	885	1368	com/google/tagmanager/protobuf/InvalidProtocolBufferException
      //   888	897	1368	com/google/tagmanager/protobuf/InvalidProtocolBufferException
      //   900	915	1368	com/google/tagmanager/protobuf/InvalidProtocolBufferException
      //   923	933	1368	com/google/tagmanager/protobuf/InvalidProtocolBufferException
      //   936	945	1368	com/google/tagmanager/protobuf/InvalidProtocolBufferException
      //   948	959	1368	com/google/tagmanager/protobuf/InvalidProtocolBufferException
      //   975	986	1368	com/google/tagmanager/protobuf/InvalidProtocolBufferException
      //   989	997	1368	com/google/tagmanager/protobuf/InvalidProtocolBufferException
      //   1013	1019	1368	com/google/tagmanager/protobuf/InvalidProtocolBufferException
      //   1033	1044	1368	com/google/tagmanager/protobuf/InvalidProtocolBufferException
      //   1086	1098	1368	com/google/tagmanager/protobuf/InvalidProtocolBufferException
      //   1101	1109	1368	com/google/tagmanager/protobuf/InvalidProtocolBufferException
      //   1125	1136	1368	com/google/tagmanager/protobuf/InvalidProtocolBufferException
      //   1139	1147	1368	com/google/tagmanager/protobuf/InvalidProtocolBufferException
      //   43	49	1378	finally
      //   199	212	1378	finally
      //   227	233	1378	finally
      //   243	254	1378	finally
      //   301	312	1378	finally
      //   366	377	1378	finally
      //   433	444	1378	finally
      //   501	512	1378	finally
      //   569	580	1378	finally
      //   637	648	1378	finally
      //   696	702	1378	finally
      //   705	715	1378	finally
      //   718	724	1378	finally
      //   740	746	1378	finally
      //   749	759	1378	finally
      //   762	768	1378	finally
      //   784	790	1378	finally
      //   793	803	1378	finally
      //   806	812	1378	finally
      //   828	834	1378	finally
      //   837	848	1378	finally
      //   851	857	1378	finally
      //   873	885	1378	finally
      //   888	897	1378	finally
      //   900	915	1378	finally
      //   923	933	1378	finally
      //   936	945	1378	finally
      //   948	959	1378	finally
      //   975	986	1378	finally
      //   989	997	1378	finally
      //   1013	1019	1378	finally
      //   1033	1044	1378	finally
      //   1086	1098	1378	finally
      //   1101	1109	1378	finally
      //   1125	1136	1378	finally
      //   1139	1147	1378	finally
      //   1372	1378	1378	finally
      //   1575	1591	1378	finally
      //   43	49	1571	java/io/IOException
      //   199	212	1571	java/io/IOException
      //   227	233	1571	java/io/IOException
      //   243	254	1571	java/io/IOException
      //   301	312	1571	java/io/IOException
      //   366	377	1571	java/io/IOException
      //   433	444	1571	java/io/IOException
      //   501	512	1571	java/io/IOException
      //   569	580	1571	java/io/IOException
      //   637	648	1571	java/io/IOException
      //   696	702	1571	java/io/IOException
      //   705	715	1571	java/io/IOException
      //   718	724	1571	java/io/IOException
      //   740	746	1571	java/io/IOException
      //   749	759	1571	java/io/IOException
      //   762	768	1571	java/io/IOException
      //   784	790	1571	java/io/IOException
      //   793	803	1571	java/io/IOException
      //   806	812	1571	java/io/IOException
      //   828	834	1571	java/io/IOException
      //   837	848	1571	java/io/IOException
      //   851	857	1571	java/io/IOException
      //   873	885	1571	java/io/IOException
      //   888	897	1571	java/io/IOException
      //   900	915	1571	java/io/IOException
      //   923	933	1571	java/io/IOException
      //   936	945	1571	java/io/IOException
      //   948	959	1571	java/io/IOException
      //   975	986	1571	java/io/IOException
      //   989	997	1571	java/io/IOException
      //   1013	1019	1571	java/io/IOException
      //   1033	1044	1571	java/io/IOException
      //   1086	1098	1571	java/io/IOException
      //   1101	1109	1571	java/io/IOException
      //   1125	1136	1571	java/io/IOException
      //   1139	1147	1571	java/io/IOException
      //   1551	1556	1591	java/io/IOException
      //   1551	1556	1604	finally
      //   270	281	1616	finally
      //   328	346	1616	finally
      //   393	411	1616	finally
      //   461	479	1616	finally
      //   529	547	1616	finally
      //   597	615	1616	finally
      //   665	683	1616	finally
      //   1062	1073	1616	finally
      //   270	281	1623	java/io/IOException
      //   328	346	1623	java/io/IOException
      //   393	411	1623	java/io/IOException
      //   461	479	1623	java/io/IOException
      //   529	547	1623	java/io/IOException
      //   597	615	1623	java/io/IOException
      //   665	683	1623	java/io/IOException
      //   1062	1073	1623	java/io/IOException
      //   270	281	1630	com/google/tagmanager/protobuf/InvalidProtocolBufferException
      //   328	346	1630	com/google/tagmanager/protobuf/InvalidProtocolBufferException
      //   393	411	1630	com/google/tagmanager/protobuf/InvalidProtocolBufferException
      //   461	479	1630	com/google/tagmanager/protobuf/InvalidProtocolBufferException
      //   529	547	1630	com/google/tagmanager/protobuf/InvalidProtocolBufferException
      //   597	615	1630	com/google/tagmanager/protobuf/InvalidProtocolBufferException
      //   665	683	1630	com/google/tagmanager/protobuf/InvalidProtocolBufferException
      //   1062	1073	1630	com/google/tagmanager/protobuf/InvalidProtocolBufferException
    }
    
    private Resource(boolean paramBoolean)
    {
      this.unknownFields = e.ajf;
    }
    
    public static a a(Resource paramResource)
    {
      return hp().o(paramResource);
    }
    
    private void fH()
    {
      this.key_ = k.akb;
      this.value_ = Collections.emptyList();
      this.property_ = Collections.emptyList();
      this.macro_ = Collections.emptyList();
      this.tag_ = Collections.emptyList();
      this.predicate_ = Collections.emptyList();
      this.rule_ = Collections.emptyList();
      this.previewAuthCode_ = "";
      this.malwareScanAuthCode_ = "";
      this.templateVersionSet_ = "0";
      this.version_ = "";
      this.liveJsCacheOption_ = Serving.CacheOption.fy();
      this.reportingSampleRate_ = 0.0F;
      this.enableAutoEventTracking_ = false;
      this.usageContext_ = k.akb;
      this.resourceFormatVersion_ = 0;
    }
    
    public static Resource gI()
    {
      return hf;
    }
    
    public static a hp()
    {
      return a.hD();
    }
    
    public void a(CodedOutputStream paramCodedOutputStream)
    {
      int j = 0;
      fI();
      int i = 0;
      while (i < this.key_.size())
      {
        paramCodedOutputStream.a(1, this.key_.ft(i));
        i += 1;
      }
      i = 0;
      while (i < this.value_.size())
      {
        paramCodedOutputStream.b(2, (n)this.value_.get(i));
        i += 1;
      }
      i = 0;
      while (i < this.property_.size())
      {
        paramCodedOutputStream.b(3, (n)this.property_.get(i));
        i += 1;
      }
      i = 0;
      while (i < this.macro_.size())
      {
        paramCodedOutputStream.b(4, (n)this.macro_.get(i));
        i += 1;
      }
      i = 0;
      while (i < this.tag_.size())
      {
        paramCodedOutputStream.b(5, (n)this.tag_.get(i));
        i += 1;
      }
      i = 0;
      while (i < this.predicate_.size())
      {
        paramCodedOutputStream.b(6, (n)this.predicate_.get(i));
        i += 1;
      }
      i = 0;
      while (i < this.rule_.size())
      {
        paramCodedOutputStream.b(7, (n)this.rule_.get(i));
        i += 1;
      }
      if ((this.bitField0_ & 0x1) == 1) {
        paramCodedOutputStream.a(9, gW());
      }
      if ((this.bitField0_ & 0x2) == 2) {
        paramCodedOutputStream.a(10, gZ());
      }
      if ((this.bitField0_ & 0x4) == 4) {
        paramCodedOutputStream.a(12, hc());
      }
      if ((this.bitField0_ & 0x8) == 8) {
        paramCodedOutputStream.a(13, he());
      }
      if ((this.bitField0_ & 0x10) == 16) {
        paramCodedOutputStream.b(14, this.liveJsCacheOption_);
      }
      i = j;
      if ((this.bitField0_ & 0x20) == 32)
      {
        paramCodedOutputStream.a(15, this.reportingSampleRate_);
        i = j;
      }
      while (i < this.usageContext_.size())
      {
        paramCodedOutputStream.a(16, this.usageContext_.ft(i));
        i += 1;
      }
      if ((this.bitField0_ & 0x80) == 128) {
        paramCodedOutputStream.w(17, this.resourceFormatVersion_);
      }
      if ((this.bitField0_ & 0x40) == 64) {
        paramCodedOutputStream.d(18, this.enableAutoEventTracking_);
      }
      paramCodedOutputStream.d(this.unknownFields);
    }
    
    public TypeSystem.Value aJ(int paramInt)
    {
      return (TypeSystem.Value)this.value_.get(paramInt);
    }
    
    public Serving.Property aK(int paramInt)
    {
      return (Serving.Property)this.property_.get(paramInt);
    }
    
    public Serving.FunctionCall aL(int paramInt)
    {
      return (Serving.FunctionCall)this.macro_.get(paramInt);
    }
    
    public Serving.FunctionCall aM(int paramInt)
    {
      return (Serving.FunctionCall)this.tag_.get(paramInt);
    }
    
    public Serving.FunctionCall aN(int paramInt)
    {
      return (Serving.FunctionCall)this.predicate_.get(paramInt);
    }
    
    public boolean equals(Object paramObject)
    {
      if (paramObject == this) {
        return true;
      }
      if (!(paramObject instanceof Resource)) {
        return super.equals(paramObject);
      }
      paramObject = (Resource)paramObject;
      int i;
      label43:
      label65:
      label87:
      label109:
      label131:
      label153:
      label175:
      label192:
      int j;
      if (getKeyList().equals(((Resource)paramObject).getKeyList()))
      {
        i = 1;
        if ((i == 0) || (!gL().equals(((Resource)paramObject).gL()))) {
          break label567;
        }
        i = 1;
        if ((i == 0) || (!ge().equals(((Resource)paramObject).ge()))) {
          break label572;
        }
        i = 1;
        if ((i == 0) || (!gM().equals(((Resource)paramObject).gM()))) {
          break label577;
        }
        i = 1;
        if ((i == 0) || (!gO().equals(((Resource)paramObject).gO()))) {
          break label582;
        }
        i = 1;
        if ((i == 0) || (!gQ().equals(((Resource)paramObject).gQ()))) {
          break label587;
        }
        i = 1;
        if ((i == 0) || (!gS().equals(((Resource)paramObject).gS()))) {
          break label592;
        }
        i = 1;
        if ((i == 0) || (gU() != ((Resource)paramObject).gU())) {
          break label597;
        }
        i = 1;
        j = i;
        if (gU())
        {
          if ((i == 0) || (!gV().equals(((Resource)paramObject).gV()))) {
            break label602;
          }
          j = 1;
        }
        label221:
        if ((j == 0) || (gX() != ((Resource)paramObject).gX())) {
          break label607;
        }
        i = 1;
        label238:
        j = i;
        if (gX())
        {
          if ((i == 0) || (!gY().equals(((Resource)paramObject).gY()))) {
            break label612;
          }
          j = 1;
        }
        label267:
        if ((j == 0) || (ha() != ((Resource)paramObject).ha())) {
          break label617;
        }
        i = 1;
        label284:
        j = i;
        if (ha())
        {
          if ((i == 0) || (!hb().equals(((Resource)paramObject).hb()))) {
            break label622;
          }
          j = 1;
        }
        label313:
        if ((j == 0) || (hd() != ((Resource)paramObject).hd())) {
          break label627;
        }
        i = 1;
        label330:
        j = i;
        if (hd())
        {
          if ((i == 0) || (!getVersion().equals(((Resource)paramObject).getVersion()))) {
            break label632;
          }
          j = 1;
        }
        label359:
        if ((j == 0) || (hf() != ((Resource)paramObject).hf())) {
          break label637;
        }
        i = 1;
        label376:
        j = i;
        if (hf())
        {
          if ((i == 0) || (!hg().equals(((Resource)paramObject).hg()))) {
            break label642;
          }
          j = 1;
        }
        label405:
        if ((j == 0) || (hh() != ((Resource)paramObject).hh())) {
          break label647;
        }
        i = 1;
        label422:
        j = i;
        if (hh())
        {
          if ((i == 0) || (Float.floatToIntBits(hi()) != Float.floatToIntBits(((Resource)paramObject).hi()))) {
            break label652;
          }
          j = 1;
        }
        label454:
        if ((j == 0) || (hj() != ((Resource)paramObject).hj())) {
          break label657;
        }
        i = 1;
        label471:
        j = i;
        if (hj())
        {
          if ((i == 0) || (hk() != ((Resource)paramObject).hk())) {
            break label662;
          }
          j = 1;
        }
        label497:
        if ((j == 0) || (!hl().equals(((Resource)paramObject).hl()))) {
          break label667;
        }
        i = 1;
        label519:
        if ((i == 0) || (hn() != ((Resource)paramObject).hn())) {
          break label672;
        }
      }
      label567:
      label572:
      label577:
      label582:
      label587:
      label592:
      label597:
      label602:
      label607:
      label612:
      label617:
      label622:
      label627:
      label632:
      label637:
      label642:
      label647:
      label652:
      label657:
      label662:
      label667:
      label672:
      for (boolean bool = true;; bool = false)
      {
        if (!hn()) {
          break label678;
        }
        if ((bool) && (ho() == ((Resource)paramObject).ho())) {
          break;
        }
        return false;
        i = 0;
        break label43;
        i = 0;
        break label65;
        i = 0;
        break label87;
        i = 0;
        break label109;
        i = 0;
        break label131;
        i = 0;
        break label153;
        i = 0;
        break label175;
        i = 0;
        break label192;
        j = 0;
        break label221;
        i = 0;
        break label238;
        j = 0;
        break label267;
        i = 0;
        break label284;
        j = 0;
        break label313;
        i = 0;
        break label330;
        j = 0;
        break label359;
        i = 0;
        break label376;
        j = 0;
        break label405;
        i = 0;
        break label422;
        j = 0;
        break label454;
        i = 0;
        break label471;
        j = 0;
        break label497;
        i = 0;
        break label519;
      }
      label678:
      return bool;
    }
    
    public q<Resource> fA()
    {
      return gW;
    }
    
    public int fI()
    {
      int k = 0;
      int i = this.memoizedSerializedSize;
      if (i != -1) {
        return i;
      }
      int j = 0;
      i = 0;
      while (j < this.key_.size())
      {
        i += CodedOutputStream.c(this.key_.ft(j));
        j += 1;
      }
      int m = getKeyList().size();
      j = 0;
      i = 0 + i + m * 1;
      while (j < this.value_.size())
      {
        i += CodedOutputStream.d(2, (n)this.value_.get(j));
        j += 1;
      }
      j = 0;
      while (j < this.property_.size())
      {
        i += CodedOutputStream.d(3, (n)this.property_.get(j));
        j += 1;
      }
      j = 0;
      while (j < this.macro_.size())
      {
        i += CodedOutputStream.d(4, (n)this.macro_.get(j));
        j += 1;
      }
      j = 0;
      while (j < this.tag_.size())
      {
        i += CodedOutputStream.d(5, (n)this.tag_.get(j));
        j += 1;
      }
      j = 0;
      while (j < this.predicate_.size())
      {
        i += CodedOutputStream.d(6, (n)this.predicate_.get(j));
        j += 1;
      }
      j = 0;
      while (j < this.rule_.size())
      {
        i += CodedOutputStream.d(7, (n)this.rule_.get(j));
        j += 1;
      }
      j = i;
      if ((this.bitField0_ & 0x1) == 1) {
        j = i + CodedOutputStream.b(9, gW());
      }
      i = j;
      if ((this.bitField0_ & 0x2) == 2) {
        i = j + CodedOutputStream.b(10, gZ());
      }
      j = i;
      if ((this.bitField0_ & 0x4) == 4) {
        j = i + CodedOutputStream.b(12, hc());
      }
      i = j;
      if ((this.bitField0_ & 0x8) == 8) {
        i = j + CodedOutputStream.b(13, he());
      }
      j = i;
      if ((this.bitField0_ & 0x10) == 16) {
        j = i + CodedOutputStream.d(14, this.liveJsCacheOption_);
      }
      i = j;
      if ((this.bitField0_ & 0x20) == 32) {
        i = j + CodedOutputStream.b(15, this.reportingSampleRate_);
      }
      m = 0;
      j = k;
      k = m;
      while (j < this.usageContext_.size())
      {
        k += CodedOutputStream.c(this.usageContext_.ft(j));
        j += 1;
      }
      j = k + i + hl().size() * 2;
      i = j;
      if ((this.bitField0_ & 0x80) == 128) {
        i = j + CodedOutputStream.z(17, this.resourceFormatVersion_);
      }
      j = i;
      if ((this.bitField0_ & 0x40) == 64) {
        j = i + CodedOutputStream.e(18, this.enableAutoEventTracking_);
      }
      i = j + this.unknownFields.size();
      this.memoizedSerializedSize = i;
      return i;
    }
    
    public Resource gJ()
    {
      return hf;
    }
    
    public int gK()
    {
      return this.key_.size();
    }
    
    public List<TypeSystem.Value> gL()
    {
      return this.value_;
    }
    
    public List<Serving.FunctionCall> gM()
    {
      return this.macro_;
    }
    
    public int gN()
    {
      return this.macro_.size();
    }
    
    public List<Serving.FunctionCall> gO()
    {
      return this.tag_;
    }
    
    public int gP()
    {
      return this.tag_.size();
    }
    
    public List<Serving.FunctionCall> gQ()
    {
      return this.predicate_;
    }
    
    public int gR()
    {
      return this.predicate_.size();
    }
    
    public List<Serving.Rule> gS()
    {
      return this.rule_;
    }
    
    public int gT()
    {
      return this.rule_.size();
    }
    
    public boolean gU()
    {
      return (this.bitField0_ & 0x1) == 1;
    }
    
    public String gV()
    {
      Object localObject = this.previewAuthCode_;
      if ((localObject instanceof String)) {
        return (String)localObject;
      }
      localObject = (e)localObject;
      String str = ((e)localObject).AK();
      if (((e)localObject).AL()) {
        this.previewAuthCode_ = str;
      }
      return str;
    }
    
    public e gW()
    {
      Object localObject = this.previewAuthCode_;
      if ((localObject instanceof String))
      {
        localObject = e.cU((String)localObject);
        this.previewAuthCode_ = localObject;
        return (e)localObject;
      }
      return (e)localObject;
    }
    
    public boolean gX()
    {
      return (this.bitField0_ & 0x2) == 2;
    }
    
    public String gY()
    {
      Object localObject = this.malwareScanAuthCode_;
      if ((localObject instanceof String)) {
        return (String)localObject;
      }
      localObject = (e)localObject;
      String str = ((e)localObject).AK();
      if (((e)localObject).AL()) {
        this.malwareScanAuthCode_ = str;
      }
      return str;
    }
    
    public e gZ()
    {
      Object localObject = this.malwareScanAuthCode_;
      if ((localObject instanceof String))
      {
        localObject = e.cU((String)localObject);
        this.malwareScanAuthCode_ = localObject;
        return (e)localObject;
      }
      return (e)localObject;
    }
    
    public List<Serving.Property> ge()
    {
      return this.property_;
    }
    
    public List<String> getKeyList()
    {
      return this.key_;
    }
    
    public int getValueCount()
    {
      return this.value_.size();
    }
    
    public String getVersion()
    {
      Object localObject = this.version_;
      if ((localObject instanceof String)) {
        return (String)localObject;
      }
      localObject = (e)localObject;
      String str = ((e)localObject).AK();
      if (((e)localObject).AL()) {
        this.version_ = str;
      }
      return str;
    }
    
    public int gf()
    {
      return this.property_.size();
    }
    
    public boolean ha()
    {
      return (this.bitField0_ & 0x4) == 4;
    }
    
    public int hashCode()
    {
      if (this.memoizedHashCode != 0) {
        return this.memoizedHashCode;
      }
      int j = Resource.class.hashCode() + 779;
      int i = j;
      if (gK() > 0) {
        i = (j * 37 + 1) * 53 + getKeyList().hashCode();
      }
      j = i;
      if (getValueCount() > 0) {
        j = (i * 37 + 2) * 53 + gL().hashCode();
      }
      i = j;
      if (gf() > 0) {
        i = (j * 37 + 3) * 53 + ge().hashCode();
      }
      j = i;
      if (gN() > 0) {
        j = (i * 37 + 4) * 53 + gM().hashCode();
      }
      i = j;
      if (gP() > 0) {
        i = (j * 37 + 5) * 53 + gO().hashCode();
      }
      j = i;
      if (gR() > 0) {
        j = (i * 37 + 6) * 53 + gQ().hashCode();
      }
      i = j;
      if (gT() > 0) {
        i = (j * 37 + 7) * 53 + gS().hashCode();
      }
      j = i;
      if (gU()) {
        j = (i * 37 + 9) * 53 + gV().hashCode();
      }
      i = j;
      if (gX()) {
        i = (j * 37 + 10) * 53 + gY().hashCode();
      }
      j = i;
      if (ha()) {
        j = (i * 37 + 12) * 53 + hb().hashCode();
      }
      i = j;
      if (hd()) {
        i = (j * 37 + 13) * 53 + getVersion().hashCode();
      }
      j = i;
      if (hf()) {
        j = (i * 37 + 14) * 53 + hg().hashCode();
      }
      i = j;
      if (hh()) {
        i = (j * 37 + 15) * 53 + Float.floatToIntBits(hi());
      }
      j = i;
      if (hj()) {
        j = (i * 37 + 18) * 53 + i.aK(hk());
      }
      i = j;
      if (hm() > 0) {
        i = (j * 37 + 16) * 53 + hl().hashCode();
      }
      j = i;
      if (hn()) {
        j = (i * 37 + 17) * 53 + ho();
      }
      i = j * 29 + this.unknownFields.hashCode();
      this.memoizedHashCode = i;
      return i;
    }
    
    public String hb()
    {
      Object localObject = this.templateVersionSet_;
      if ((localObject instanceof String)) {
        return (String)localObject;
      }
      localObject = (e)localObject;
      String str = ((e)localObject).AK();
      if (((e)localObject).AL()) {
        this.templateVersionSet_ = str;
      }
      return str;
    }
    
    public e hc()
    {
      Object localObject = this.templateVersionSet_;
      if ((localObject instanceof String))
      {
        localObject = e.cU((String)localObject);
        this.templateVersionSet_ = localObject;
        return (e)localObject;
      }
      return (e)localObject;
    }
    
    public boolean hd()
    {
      return (this.bitField0_ & 0x8) == 8;
    }
    
    public e he()
    {
      Object localObject = this.version_;
      if ((localObject instanceof String))
      {
        localObject = e.cU((String)localObject);
        this.version_ = localObject;
        return (e)localObject;
      }
      return (e)localObject;
    }
    
    public boolean hf()
    {
      return (this.bitField0_ & 0x10) == 16;
    }
    
    public Serving.CacheOption hg()
    {
      return this.liveJsCacheOption_;
    }
    
    public boolean hh()
    {
      return (this.bitField0_ & 0x20) == 32;
    }
    
    public float hi()
    {
      return this.reportingSampleRate_;
    }
    
    public boolean hj()
    {
      return (this.bitField0_ & 0x40) == 64;
    }
    
    public boolean hk()
    {
      return this.enableAutoEventTracking_;
    }
    
    public List<String> hl()
    {
      return this.usageContext_;
    }
    
    public int hm()
    {
      return this.usageContext_.size();
    }
    
    public boolean hn()
    {
      return (this.bitField0_ & 0x80) == 128;
    }
    
    public int ho()
    {
      return this.resourceFormatVersion_;
    }
    
    public a hq()
    {
      return hp();
    }
    
    public a hr()
    {
      return a(this);
    }
    
    public final boolean isInitialized()
    {
      boolean bool = true;
      int i = this.memoizedIsInitialized;
      if (i != -1)
      {
        if (i == 1) {}
        for (;;)
        {
          return bool;
          bool = false;
        }
      }
      i = 0;
      while (i < getValueCount())
      {
        if (!aJ(i).isInitialized())
        {
          this.memoizedIsInitialized = 0;
          return false;
        }
        i += 1;
      }
      i = 0;
      while (i < gf())
      {
        if (!aK(i).isInitialized())
        {
          this.memoizedIsInitialized = 0;
          return false;
        }
        i += 1;
      }
      i = 0;
      while (i < gN())
      {
        if (!aL(i).isInitialized())
        {
          this.memoizedIsInitialized = 0;
          return false;
        }
        i += 1;
      }
      i = 0;
      while (i < gP())
      {
        if (!aM(i).isInitialized())
        {
          this.memoizedIsInitialized = 0;
          return false;
        }
        i += 1;
      }
      i = 0;
      while (i < gR())
      {
        if (!aN(i).isInitialized())
        {
          this.memoizedIsInitialized = 0;
          return false;
        }
        i += 1;
      }
      this.memoizedIsInitialized = 1;
      return true;
    }
    
    protected Object writeReplace()
    {
      return super.writeReplace();
    }
    
    public static final class a
      extends GeneratedMessageLite.a<Serving.Resource, a>
      implements Serving.d
    {
      private int bitField0_;
      private boolean enableAutoEventTracking_;
      private l key_ = k.akb;
      private Serving.CacheOption liveJsCacheOption_ = Serving.CacheOption.fy();
      private List<Serving.FunctionCall> macro_ = Collections.emptyList();
      private Object malwareScanAuthCode_ = "";
      private List<Serving.FunctionCall> predicate_ = Collections.emptyList();
      private Object previewAuthCode_ = "";
      private List<Serving.Property> property_ = Collections.emptyList();
      private float reportingSampleRate_;
      private int resourceFormatVersion_;
      private List<Serving.Rule> rule_ = Collections.emptyList();
      private List<Serving.FunctionCall> tag_ = Collections.emptyList();
      private Object templateVersionSet_ = "0";
      private l usageContext_ = k.akb;
      private List<TypeSystem.Value> value_ = Collections.emptyList();
      private Object version_ = "";
      
      private a()
      {
        fP();
      }
      
      private void fP() {}
      
      private void gv()
      {
        if ((this.bitField0_ & 0x4) != 4)
        {
          this.property_ = new ArrayList(this.property_);
          this.bitField0_ |= 0x4;
        }
      }
      
      private void hA()
      {
        if ((this.bitField0_ & 0x20) != 32)
        {
          this.predicate_ = new ArrayList(this.predicate_);
          this.bitField0_ |= 0x20;
        }
      }
      
      private void hB()
      {
        if ((this.bitField0_ & 0x40) != 64)
        {
          this.rule_ = new ArrayList(this.rule_);
          this.bitField0_ |= 0x40;
        }
      }
      
      private void hC()
      {
        if ((this.bitField0_ & 0x4000) != 16384)
        {
          this.usageContext_ = new k(this.usageContext_);
          this.bitField0_ |= 0x4000;
        }
      }
      
      private static a hs()
      {
        return new a();
      }
      
      private void hw()
      {
        if ((this.bitField0_ & 0x1) != 1)
        {
          this.key_ = new k(this.key_);
          this.bitField0_ |= 0x1;
        }
      }
      
      private void hx()
      {
        if ((this.bitField0_ & 0x2) != 2)
        {
          this.value_ = new ArrayList(this.value_);
          this.bitField0_ |= 0x2;
        }
      }
      
      private void hy()
      {
        if ((this.bitField0_ & 0x8) != 8)
        {
          this.macro_ = new ArrayList(this.macro_);
          this.bitField0_ |= 0x8;
        }
      }
      
      private void hz()
      {
        if ((this.bitField0_ & 0x10) != 16)
        {
          this.tag_ = new ArrayList(this.tag_);
          this.bitField0_ |= 0x10;
        }
      }
      
      public TypeSystem.Value aJ(int paramInt)
      {
        return (TypeSystem.Value)this.value_.get(paramInt);
      }
      
      public Serving.Property aK(int paramInt)
      {
        return (Serving.Property)this.property_.get(paramInt);
      }
      
      public Serving.FunctionCall aL(int paramInt)
      {
        return (Serving.FunctionCall)this.macro_.get(paramInt);
      }
      
      public Serving.FunctionCall aM(int paramInt)
      {
        return (Serving.FunctionCall)this.tag_.get(paramInt);
      }
      
      public Serving.FunctionCall aN(int paramInt)
      {
        return (Serving.FunctionCall)this.predicate_.get(paramInt);
      }
      
      public a aO(int paramInt)
      {
        this.bitField0_ |= 0x8000;
        this.resourceFormatVersion_ = paramInt;
        return this;
      }
      
      public a d(Serving.CacheOption paramCacheOption)
      {
        if (((this.bitField0_ & 0x800) == 2048) && (this.liveJsCacheOption_ != Serving.CacheOption.fy())) {}
        for (this.liveJsCacheOption_ = Serving.CacheOption.a(this.liveJsCacheOption_).c(paramCacheOption).fT();; this.liveJsCacheOption_ = paramCacheOption)
        {
          this.bitField0_ |= 0x800;
          return this;
        }
      }
      
      public a g(float paramFloat)
      {
        this.bitField0_ |= 0x1000;
        this.reportingSampleRate_ = paramFloat;
        return this;
      }
      
      public Serving.Resource gJ()
      {
        return Serving.Resource.gI();
      }
      
      public int gN()
      {
        return this.macro_.size();
      }
      
      public int gP()
      {
        return this.tag_.size();
      }
      
      public int gR()
      {
        return this.predicate_.size();
      }
      
      public int getValueCount()
      {
        return this.value_.size();
      }
      
      public int gf()
      {
        return this.property_.size();
      }
      
      public a ht()
      {
        return hs().o(hv());
      }
      
      public Serving.Resource hu()
      {
        Serving.Resource localResource = hv();
        if (!localResource.isInitialized()) {
          throw a(localResource);
        }
        return localResource;
      }
      
      public Serving.Resource hv()
      {
        int j = 1;
        Serving.Resource localResource = new Serving.Resource(this, null);
        int k = this.bitField0_;
        if ((this.bitField0_ & 0x1) == 1)
        {
          this.key_ = new t(this.key_);
          this.bitField0_ &= 0xFFFFFFFE;
        }
        Serving.Resource.a(localResource, this.key_);
        if ((this.bitField0_ & 0x2) == 2)
        {
          this.value_ = Collections.unmodifiableList(this.value_);
          this.bitField0_ &= 0xFFFFFFFD;
        }
        Serving.Resource.a(localResource, this.value_);
        if ((this.bitField0_ & 0x4) == 4)
        {
          this.property_ = Collections.unmodifiableList(this.property_);
          this.bitField0_ &= 0xFFFFFFFB;
        }
        Serving.Resource.b(localResource, this.property_);
        if ((this.bitField0_ & 0x8) == 8)
        {
          this.macro_ = Collections.unmodifiableList(this.macro_);
          this.bitField0_ &= 0xFFFFFFF7;
        }
        Serving.Resource.c(localResource, this.macro_);
        if ((this.bitField0_ & 0x10) == 16)
        {
          this.tag_ = Collections.unmodifiableList(this.tag_);
          this.bitField0_ &= 0xFFFFFFEF;
        }
        Serving.Resource.d(localResource, this.tag_);
        if ((this.bitField0_ & 0x20) == 32)
        {
          this.predicate_ = Collections.unmodifiableList(this.predicate_);
          this.bitField0_ &= 0xFFFFFFDF;
        }
        Serving.Resource.e(localResource, this.predicate_);
        if ((this.bitField0_ & 0x40) == 64)
        {
          this.rule_ = Collections.unmodifiableList(this.rule_);
          this.bitField0_ &= 0xFFFFFFBF;
        }
        Serving.Resource.f(localResource, this.rule_);
        if ((k & 0x80) == 128) {}
        for (;;)
        {
          Serving.Resource.a(localResource, this.previewAuthCode_);
          int i = j;
          if ((k & 0x100) == 256) {
            i = j | 0x2;
          }
          Serving.Resource.b(localResource, this.malwareScanAuthCode_);
          j = i;
          if ((k & 0x200) == 512) {
            j = i | 0x4;
          }
          Serving.Resource.c(localResource, this.templateVersionSet_);
          i = j;
          if ((k & 0x400) == 1024) {
            i = j | 0x8;
          }
          Serving.Resource.d(localResource, this.version_);
          j = i;
          if ((k & 0x800) == 2048) {
            j = i | 0x10;
          }
          Serving.Resource.a(localResource, this.liveJsCacheOption_);
          i = j;
          if ((k & 0x1000) == 4096) {
            i = j | 0x20;
          }
          Serving.Resource.a(localResource, this.reportingSampleRate_);
          j = i;
          if ((k & 0x2000) == 8192) {
            j = i | 0x40;
          }
          Serving.Resource.a(localResource, this.enableAutoEventTracking_);
          if ((this.bitField0_ & 0x4000) == 16384)
          {
            this.usageContext_ = new t(this.usageContext_);
            this.bitField0_ &= 0xBFFF;
          }
          Serving.Resource.b(localResource, this.usageContext_);
          i = j;
          if ((k & 0x8000) == 32768) {
            i = j | 0x80;
          }
          Serving.Resource.a(localResource, this.resourceFormatVersion_);
          Serving.Resource.b(localResource, i);
          return localResource;
          j = 0;
        }
      }
      
      public final boolean isInitialized()
      {
        int i = 0;
        while (i < getValueCount())
        {
          if (!aJ(i).isInitialized()) {
            return false;
          }
          i += 1;
        }
        i = 0;
        for (;;)
        {
          if (i >= gf()) {
            break label58;
          }
          if (!aK(i).isInitialized()) {
            break;
          }
          i += 1;
        }
        label58:
        i = 0;
        for (;;)
        {
          if (i >= gN()) {
            break label86;
          }
          if (!aL(i).isInitialized()) {
            break;
          }
          i += 1;
        }
        label86:
        i = 0;
        for (;;)
        {
          if (i >= gP()) {
            break label114;
          }
          if (!aM(i).isInitialized()) {
            break;
          }
          i += 1;
        }
        label114:
        i = 0;
        for (;;)
        {
          if (i >= gR()) {
            break label142;
          }
          if (!aN(i).isInitialized()) {
            break;
          }
          i += 1;
        }
        label142:
        return true;
      }
      
      public a j(boolean paramBoolean)
      {
        this.bitField0_ |= 0x2000;
        this.enableAutoEventTracking_ = paramBoolean;
        return this;
      }
      
      /* Error */
      public a k(f paramf, g paramg)
      {
        // Byte code:
        //   0: getstatic 304	com/google/analytics/containertag/proto/Serving$Resource:gW	Lcom/google/tagmanager/protobuf/q;
        //   3: aload_1
        //   4: aload_2
        //   5: invokeinterface 309 3 0
        //   10: checkcast 9	com/google/analytics/containertag/proto/Serving$Resource
        //   13: astore_1
        //   14: aload_1
        //   15: ifnull +9 -> 24
        //   18: aload_0
        //   19: aload_1
        //   20: invokevirtual 125	com/google/analytics/containertag/proto/Serving$Resource$a:o	(Lcom/google/analytics/containertag/proto/Serving$Resource;)Lcom/google/analytics/containertag/proto/Serving$Resource$a;
        //   23: pop
        //   24: aload_0
        //   25: areturn
        //   26: astore_2
        //   27: aload_2
        //   28: invokevirtual 312	com/google/tagmanager/protobuf/InvalidProtocolBufferException:BN	()Lcom/google/tagmanager/protobuf/n;
        //   31: checkcast 9	com/google/analytics/containertag/proto/Serving$Resource
        //   34: astore_1
        //   35: aload_2
        //   36: athrow
        //   37: astore_2
        //   38: aload_1
        //   39: ifnull +9 -> 48
        //   42: aload_0
        //   43: aload_1
        //   44: invokevirtual 125	com/google/analytics/containertag/proto/Serving$Resource$a:o	(Lcom/google/analytics/containertag/proto/Serving$Resource;)Lcom/google/analytics/containertag/proto/Serving$Resource$a;
        //   47: pop
        //   48: aload_2
        //   49: athrow
        //   50: astore_2
        //   51: aconst_null
        //   52: astore_1
        //   53: goto -15 -> 38
        // Local variable table:
        //   start	length	slot	name	signature
        //   0	56	0	this	a
        //   0	56	1	paramf	f
        //   0	56	2	paramg	g
        // Exception table:
        //   from	to	target	type
        //   0	14	26	com/google/tagmanager/protobuf/InvalidProtocolBufferException
        //   35	37	37	finally
        //   0	14	50	finally
        //   27	35	50	finally
      }
      
      public a o(Serving.Resource paramResource)
      {
        if (paramResource == Serving.Resource.gI()) {
          return this;
        }
        if (!Serving.Resource.b(paramResource).isEmpty())
        {
          if (this.key_.isEmpty())
          {
            this.key_ = Serving.Resource.b(paramResource);
            this.bitField0_ &= 0xFFFFFFFE;
          }
        }
        else
        {
          if (!Serving.Resource.c(paramResource).isEmpty())
          {
            if (!this.value_.isEmpty()) {
              break label565;
            }
            this.value_ = Serving.Resource.c(paramResource);
            this.bitField0_ &= 0xFFFFFFFD;
          }
          label95:
          if (!Serving.Resource.d(paramResource).isEmpty())
          {
            if (!this.property_.isEmpty()) {
              break label586;
            }
            this.property_ = Serving.Resource.d(paramResource);
            this.bitField0_ &= 0xFFFFFFFB;
          }
          label138:
          if (!Serving.Resource.e(paramResource).isEmpty())
          {
            if (!this.macro_.isEmpty()) {
              break label607;
            }
            this.macro_ = Serving.Resource.e(paramResource);
            this.bitField0_ &= 0xFFFFFFF7;
          }
          label181:
          if (!Serving.Resource.f(paramResource).isEmpty())
          {
            if (!this.tag_.isEmpty()) {
              break label628;
            }
            this.tag_ = Serving.Resource.f(paramResource);
            this.bitField0_ &= 0xFFFFFFEF;
          }
          label224:
          if (!Serving.Resource.g(paramResource).isEmpty())
          {
            if (!this.predicate_.isEmpty()) {
              break label649;
            }
            this.predicate_ = Serving.Resource.g(paramResource);
            this.bitField0_ &= 0xFFFFFFDF;
          }
          label267:
          if (!Serving.Resource.h(paramResource).isEmpty())
          {
            if (!this.rule_.isEmpty()) {
              break label670;
            }
            this.rule_ = Serving.Resource.h(paramResource);
            this.bitField0_ &= 0xFFFFFFBF;
          }
          label310:
          if (paramResource.gU())
          {
            this.bitField0_ |= 0x80;
            this.previewAuthCode_ = Serving.Resource.i(paramResource);
          }
          if (paramResource.gX())
          {
            this.bitField0_ |= 0x100;
            this.malwareScanAuthCode_ = Serving.Resource.j(paramResource);
          }
          if (paramResource.ha())
          {
            this.bitField0_ |= 0x200;
            this.templateVersionSet_ = Serving.Resource.k(paramResource);
          }
          if (paramResource.hd())
          {
            this.bitField0_ |= 0x400;
            this.version_ = Serving.Resource.l(paramResource);
          }
          if (paramResource.hf()) {
            d(paramResource.hg());
          }
          if (paramResource.hh()) {
            g(paramResource.hi());
          }
          if (paramResource.hj()) {
            j(paramResource.hk());
          }
          if (!Serving.Resource.m(paramResource).isEmpty())
          {
            if (!this.usageContext_.isEmpty()) {
              break label691;
            }
            this.usageContext_ = Serving.Resource.m(paramResource);
            this.bitField0_ &= 0xBFFF;
          }
        }
        for (;;)
        {
          if (paramResource.hn()) {
            aO(paramResource.ho());
          }
          e(BE().a(Serving.Resource.n(paramResource)));
          return this;
          hw();
          this.key_.addAll(Serving.Resource.b(paramResource));
          break;
          label565:
          hx();
          this.value_.addAll(Serving.Resource.c(paramResource));
          break label95;
          label586:
          gv();
          this.property_.addAll(Serving.Resource.d(paramResource));
          break label138;
          label607:
          hy();
          this.macro_.addAll(Serving.Resource.e(paramResource));
          break label181;
          label628:
          hz();
          this.tag_.addAll(Serving.Resource.f(paramResource));
          break label224;
          label649:
          hA();
          this.predicate_.addAll(Serving.Resource.g(paramResource));
          break label267;
          label670:
          hB();
          this.rule_.addAll(Serving.Resource.h(paramResource));
          break label310;
          label691:
          hC();
          this.usageContext_.addAll(Serving.Resource.m(paramResource));
        }
      }
    }
  }
  
  public static final class Rule
    extends GeneratedMessageLite
    implements Serving.e
  {
    public static q<Rule> gW = new c()
    {
      public Serving.Rule l(f paramAnonymousf, g paramAnonymousg)
      {
        return new Serving.Rule(paramAnonymousf, paramAnonymousg, null);
      }
    };
    private static volatile p gX = null;
    private static final Rule hg = new Rule(true);
    private static final long serialVersionUID = 0L;
    private List<Integer> addMacroRuleName_;
    private List<Integer> addMacro_;
    private List<Integer> addTagRuleName_;
    private List<Integer> addTag_;
    private byte memoizedIsInitialized = -1;
    private int memoizedSerializedSize = -1;
    private List<Integer> negativePredicate_;
    private List<Integer> positivePredicate_;
    private List<Integer> removeMacroRuleName_;
    private List<Integer> removeMacro_;
    private List<Integer> removeTagRuleName_;
    private List<Integer> removeTag_;
    private final e unknownFields;
    
    static
    {
      hg.fH();
    }
    
    private Rule(GeneratedMessageLite.a parama)
    {
      super();
      this.unknownFields = parama.BE();
    }
    
    /* Error */
    private Rule(f paramf, g paramg)
    {
      // Byte code:
      //   0: aload_0
      //   1: invokespecial 84	com/google/tagmanager/protobuf/GeneratedMessageLite:<init>	()V
      //   4: aload_0
      //   5: iconst_m1
      //   6: putfield 66	com/google/analytics/containertag/proto/Serving$Rule:memoizedIsInitialized	B
      //   9: aload_0
      //   10: iconst_m1
      //   11: putfield 68	com/google/analytics/containertag/proto/Serving$Rule:memoizedSerializedSize	I
      //   14: aload_0
      //   15: invokespecial 60	com/google/analytics/containertag/proto/Serving$Rule:fH	()V
      //   18: iconst_0
      //   19: istore_3
      //   20: invokestatic 90	com/google/tagmanager/protobuf/e:AN	()Lcom/google/tagmanager/protobuf/e$b;
      //   23: astore 10
      //   25: aload 10
      //   27: invokestatic 95	com/google/tagmanager/protobuf/CodedOutputStream:a	(Ljava/io/OutputStream;)Lcom/google/tagmanager/protobuf/CodedOutputStream;
      //   30: astore 11
      //   32: iconst_0
      //   33: istore 8
      //   35: iload 8
      //   37: ifne +2730 -> 2767
      //   40: iload_3
      //   41: istore 5
      //   43: iload_3
      //   44: istore 4
      //   46: iload_3
      //   47: istore 6
      //   49: aload_1
      //   50: invokevirtual 101	com/google/tagmanager/protobuf/f:AT	()I
      //   53: istore 7
      //   55: iload 7
      //   57: lookupswitch	default:+2979->3036, 0:+2982->3039, 8:+207->264, 10:+519->576, 16:+688->745, 18:+758->815, 24:+906->963, 26:+976->1033, 32:+1124->1181, 34:+1197->1254, 40:+1348->1405, 42:+1421->1478, 48:+1572->1629, 50:+1645->1702, 56:+1796->1853, 58:+1869->1926, 64:+2020->2077, 66:+2096->2153, 72:+2250->2307, 74:+2326->2383, 80:+2480->2537, 82:+2556->2613
      //   236: iload_3
      //   237: istore 5
      //   239: iload_3
      //   240: istore 4
      //   242: iload_3
      //   243: istore 6
      //   245: aload_0
      //   246: aload_1
      //   247: aload 11
      //   249: aload_2
      //   250: iload 7
      //   252: invokevirtual 104	com/google/analytics/containertag/proto/Serving$Rule:a	(Lcom/google/tagmanager/protobuf/f;Lcom/google/tagmanager/protobuf/CodedOutputStream;Lcom/google/tagmanager/protobuf/g;I)Z
      //   255: ifne -220 -> 35
      //   258: iconst_1
      //   259: istore 8
      //   261: goto -226 -> 35
      //   264: iload_3
      //   265: istore 7
      //   267: iload_3
      //   268: iconst_1
      //   269: iand
      //   270: iconst_1
      //   271: if_icmpeq +28 -> 299
      //   274: iload_3
      //   275: istore 5
      //   277: iload_3
      //   278: istore 4
      //   280: iload_3
      //   281: istore 6
      //   283: aload_0
      //   284: new 106	java/util/ArrayList
      //   287: dup
      //   288: invokespecial 107	java/util/ArrayList:<init>	()V
      //   291: putfield 109	com/google/analytics/containertag/proto/Serving$Rule:positivePredicate_	Ljava/util/List;
      //   294: iload_3
      //   295: iconst_1
      //   296: ior
      //   297: istore 7
      //   299: iload 7
      //   301: istore 5
      //   303: iload 7
      //   305: istore 4
      //   307: iload 7
      //   309: istore 6
      //   311: aload_0
      //   312: getfield 109	com/google/analytics/containertag/proto/Serving$Rule:positivePredicate_	Ljava/util/List;
      //   315: aload_1
      //   316: invokevirtual 112	com/google/tagmanager/protobuf/f:AW	()I
      //   319: invokestatic 118	java/lang/Integer:valueOf	(I)Ljava/lang/Integer;
      //   322: invokeinterface 124 2 0
      //   327: pop
      //   328: iload 7
      //   330: istore_3
      //   331: goto -296 -> 35
      //   334: astore_1
      //   335: iload 5
      //   337: istore 4
      //   339: aload_1
      //   340: aload_0
      //   341: invokevirtual 128	com/google/tagmanager/protobuf/InvalidProtocolBufferException:h	(Lcom/google/tagmanager/protobuf/n;)Lcom/google/tagmanager/protobuf/InvalidProtocolBufferException;
      //   344: athrow
      //   345: astore_1
      //   346: iload 4
      //   348: iconst_1
      //   349: iand
      //   350: iconst_1
      //   351: if_icmpne +14 -> 365
      //   354: aload_0
      //   355: aload_0
      //   356: getfield 109	com/google/analytics/containertag/proto/Serving$Rule:positivePredicate_	Ljava/util/List;
      //   359: invokestatic 134	java/util/Collections:unmodifiableList	(Ljava/util/List;)Ljava/util/List;
      //   362: putfield 109	com/google/analytics/containertag/proto/Serving$Rule:positivePredicate_	Ljava/util/List;
      //   365: iload 4
      //   367: iconst_2
      //   368: iand
      //   369: iconst_2
      //   370: if_icmpne +14 -> 384
      //   373: aload_0
      //   374: aload_0
      //   375: getfield 136	com/google/analytics/containertag/proto/Serving$Rule:negativePredicate_	Ljava/util/List;
      //   378: invokestatic 134	java/util/Collections:unmodifiableList	(Ljava/util/List;)Ljava/util/List;
      //   381: putfield 136	com/google/analytics/containertag/proto/Serving$Rule:negativePredicate_	Ljava/util/List;
      //   384: iload 4
      //   386: iconst_4
      //   387: iand
      //   388: iconst_4
      //   389: if_icmpne +14 -> 403
      //   392: aload_0
      //   393: aload_0
      //   394: getfield 138	com/google/analytics/containertag/proto/Serving$Rule:addTag_	Ljava/util/List;
      //   397: invokestatic 134	java/util/Collections:unmodifiableList	(Ljava/util/List;)Ljava/util/List;
      //   400: putfield 138	com/google/analytics/containertag/proto/Serving$Rule:addTag_	Ljava/util/List;
      //   403: iload 4
      //   405: bipush 8
      //   407: iand
      //   408: bipush 8
      //   410: if_icmpne +14 -> 424
      //   413: aload_0
      //   414: aload_0
      //   415: getfield 140	com/google/analytics/containertag/proto/Serving$Rule:removeTag_	Ljava/util/List;
      //   418: invokestatic 134	java/util/Collections:unmodifiableList	(Ljava/util/List;)Ljava/util/List;
      //   421: putfield 140	com/google/analytics/containertag/proto/Serving$Rule:removeTag_	Ljava/util/List;
      //   424: iload 4
      //   426: bipush 16
      //   428: iand
      //   429: bipush 16
      //   431: if_icmpne +14 -> 445
      //   434: aload_0
      //   435: aload_0
      //   436: getfield 142	com/google/analytics/containertag/proto/Serving$Rule:addTagRuleName_	Ljava/util/List;
      //   439: invokestatic 134	java/util/Collections:unmodifiableList	(Ljava/util/List;)Ljava/util/List;
      //   442: putfield 142	com/google/analytics/containertag/proto/Serving$Rule:addTagRuleName_	Ljava/util/List;
      //   445: iload 4
      //   447: bipush 32
      //   449: iand
      //   450: bipush 32
      //   452: if_icmpne +14 -> 466
      //   455: aload_0
      //   456: aload_0
      //   457: getfield 144	com/google/analytics/containertag/proto/Serving$Rule:removeTagRuleName_	Ljava/util/List;
      //   460: invokestatic 134	java/util/Collections:unmodifiableList	(Ljava/util/List;)Ljava/util/List;
      //   463: putfield 144	com/google/analytics/containertag/proto/Serving$Rule:removeTagRuleName_	Ljava/util/List;
      //   466: iload 4
      //   468: bipush 64
      //   470: iand
      //   471: bipush 64
      //   473: if_icmpne +14 -> 487
      //   476: aload_0
      //   477: aload_0
      //   478: getfield 146	com/google/analytics/containertag/proto/Serving$Rule:addMacro_	Ljava/util/List;
      //   481: invokestatic 134	java/util/Collections:unmodifiableList	(Ljava/util/List;)Ljava/util/List;
      //   484: putfield 146	com/google/analytics/containertag/proto/Serving$Rule:addMacro_	Ljava/util/List;
      //   487: iload 4
      //   489: sipush 128
      //   492: iand
      //   493: sipush 128
      //   496: if_icmpne +14 -> 510
      //   499: aload_0
      //   500: aload_0
      //   501: getfield 148	com/google/analytics/containertag/proto/Serving$Rule:removeMacro_	Ljava/util/List;
      //   504: invokestatic 134	java/util/Collections:unmodifiableList	(Ljava/util/List;)Ljava/util/List;
      //   507: putfield 148	com/google/analytics/containertag/proto/Serving$Rule:removeMacro_	Ljava/util/List;
      //   510: iload 4
      //   512: sipush 256
      //   515: iand
      //   516: sipush 256
      //   519: if_icmpne +14 -> 533
      //   522: aload_0
      //   523: aload_0
      //   524: getfield 150	com/google/analytics/containertag/proto/Serving$Rule:addMacroRuleName_	Ljava/util/List;
      //   527: invokestatic 134	java/util/Collections:unmodifiableList	(Ljava/util/List;)Ljava/util/List;
      //   530: putfield 150	com/google/analytics/containertag/proto/Serving$Rule:addMacroRuleName_	Ljava/util/List;
      //   533: iload 4
      //   535: sipush 512
      //   538: iand
      //   539: sipush 512
      //   542: if_icmpne +14 -> 556
      //   545: aload_0
      //   546: aload_0
      //   547: getfield 152	com/google/analytics/containertag/proto/Serving$Rule:removeMacroRuleName_	Ljava/util/List;
      //   550: invokestatic 134	java/util/Collections:unmodifiableList	(Ljava/util/List;)Ljava/util/List;
      //   553: putfield 152	com/google/analytics/containertag/proto/Serving$Rule:removeMacroRuleName_	Ljava/util/List;
      //   556: aload 11
      //   558: invokevirtual 155	com/google/tagmanager/protobuf/CodedOutputStream:flush	()V
      //   561: aload_0
      //   562: aload 10
      //   564: invokevirtual 160	com/google/tagmanager/protobuf/e$b:AR	()Lcom/google/tagmanager/protobuf/e;
      //   567: putfield 76	com/google/analytics/containertag/proto/Serving$Rule:unknownFields	Lcom/google/tagmanager/protobuf/e;
      //   570: aload_0
      //   571: invokevirtual 163	com/google/analytics/containertag/proto/Serving$Rule:BD	()V
      //   574: aload_1
      //   575: athrow
      //   576: iload_3
      //   577: istore 5
      //   579: iload_3
      //   580: istore 4
      //   582: iload_3
      //   583: istore 6
      //   585: aload_1
      //   586: aload_1
      //   587: invokevirtual 166	com/google/tagmanager/protobuf/f:Bi	()I
      //   590: invokevirtual 170	com/google/tagmanager/protobuf/f:eV	(I)I
      //   593: istore 9
      //   595: iload_3
      //   596: istore 7
      //   598: iload_3
      //   599: iconst_1
      //   600: iand
      //   601: iconst_1
      //   602: if_icmpeq +47 -> 649
      //   605: iload_3
      //   606: istore 5
      //   608: iload_3
      //   609: istore 4
      //   611: iload_3
      //   612: istore 7
      //   614: iload_3
      //   615: istore 6
      //   617: aload_1
      //   618: invokevirtual 173	com/google/tagmanager/protobuf/f:Bn	()I
      //   621: ifle +28 -> 649
      //   624: iload_3
      //   625: istore 5
      //   627: iload_3
      //   628: istore 4
      //   630: iload_3
      //   631: istore 6
      //   633: aload_0
      //   634: new 106	java/util/ArrayList
      //   637: dup
      //   638: invokespecial 107	java/util/ArrayList:<init>	()V
      //   641: putfield 109	com/google/analytics/containertag/proto/Serving$Rule:positivePredicate_	Ljava/util/List;
      //   644: iload_3
      //   645: iconst_1
      //   646: ior
      //   647: istore 7
      //   649: iload 7
      //   651: istore 5
      //   653: iload 7
      //   655: istore 4
      //   657: iload 7
      //   659: istore 6
      //   661: aload_1
      //   662: invokevirtual 173	com/google/tagmanager/protobuf/f:Bn	()I
      //   665: ifle +56 -> 721
      //   668: iload 7
      //   670: istore 5
      //   672: iload 7
      //   674: istore 4
      //   676: iload 7
      //   678: istore 6
      //   680: aload_0
      //   681: getfield 109	com/google/analytics/containertag/proto/Serving$Rule:positivePredicate_	Ljava/util/List;
      //   684: aload_1
      //   685: invokevirtual 112	com/google/tagmanager/protobuf/f:AW	()I
      //   688: invokestatic 118	java/lang/Integer:valueOf	(I)Ljava/lang/Integer;
      //   691: invokeinterface 124 2 0
      //   696: pop
      //   697: goto -48 -> 649
      //   700: astore_1
      //   701: iload 6
      //   703: istore 4
      //   705: new 81	com/google/tagmanager/protobuf/InvalidProtocolBufferException
      //   708: dup
      //   709: aload_1
      //   710: invokevirtual 177	java/io/IOException:getMessage	()Ljava/lang/String;
      //   713: invokespecial 180	com/google/tagmanager/protobuf/InvalidProtocolBufferException:<init>	(Ljava/lang/String;)V
      //   716: aload_0
      //   717: invokevirtual 128	com/google/tagmanager/protobuf/InvalidProtocolBufferException:h	(Lcom/google/tagmanager/protobuf/n;)Lcom/google/tagmanager/protobuf/InvalidProtocolBufferException;
      //   720: athrow
      //   721: iload 7
      //   723: istore 5
      //   725: iload 7
      //   727: istore 4
      //   729: iload 7
      //   731: istore 6
      //   733: aload_1
      //   734: iload 9
      //   736: invokevirtual 184	com/google/tagmanager/protobuf/f:eW	(I)V
      //   739: iload 7
      //   741: istore_3
      //   742: goto -707 -> 35
      //   745: iload_3
      //   746: istore 7
      //   748: iload_3
      //   749: iconst_2
      //   750: iand
      //   751: iconst_2
      //   752: if_icmpeq +28 -> 780
      //   755: iload_3
      //   756: istore 5
      //   758: iload_3
      //   759: istore 4
      //   761: iload_3
      //   762: istore 6
      //   764: aload_0
      //   765: new 106	java/util/ArrayList
      //   768: dup
      //   769: invokespecial 107	java/util/ArrayList:<init>	()V
      //   772: putfield 136	com/google/analytics/containertag/proto/Serving$Rule:negativePredicate_	Ljava/util/List;
      //   775: iload_3
      //   776: iconst_2
      //   777: ior
      //   778: istore 7
      //   780: iload 7
      //   782: istore 5
      //   784: iload 7
      //   786: istore 4
      //   788: iload 7
      //   790: istore 6
      //   792: aload_0
      //   793: getfield 136	com/google/analytics/containertag/proto/Serving$Rule:negativePredicate_	Ljava/util/List;
      //   796: aload_1
      //   797: invokevirtual 112	com/google/tagmanager/protobuf/f:AW	()I
      //   800: invokestatic 118	java/lang/Integer:valueOf	(I)Ljava/lang/Integer;
      //   803: invokeinterface 124 2 0
      //   808: pop
      //   809: iload 7
      //   811: istore_3
      //   812: goto -777 -> 35
      //   815: iload_3
      //   816: istore 5
      //   818: iload_3
      //   819: istore 4
      //   821: iload_3
      //   822: istore 6
      //   824: aload_1
      //   825: aload_1
      //   826: invokevirtual 166	com/google/tagmanager/protobuf/f:Bi	()I
      //   829: invokevirtual 170	com/google/tagmanager/protobuf/f:eV	(I)I
      //   832: istore 9
      //   834: iload_3
      //   835: istore 7
      //   837: iload_3
      //   838: iconst_2
      //   839: iand
      //   840: iconst_2
      //   841: if_icmpeq +47 -> 888
      //   844: iload_3
      //   845: istore 5
      //   847: iload_3
      //   848: istore 4
      //   850: iload_3
      //   851: istore 6
      //   853: iload_3
      //   854: istore 7
      //   856: aload_1
      //   857: invokevirtual 173	com/google/tagmanager/protobuf/f:Bn	()I
      //   860: ifle +28 -> 888
      //   863: iload_3
      //   864: istore 5
      //   866: iload_3
      //   867: istore 4
      //   869: iload_3
      //   870: istore 6
      //   872: aload_0
      //   873: new 106	java/util/ArrayList
      //   876: dup
      //   877: invokespecial 107	java/util/ArrayList:<init>	()V
      //   880: putfield 136	com/google/analytics/containertag/proto/Serving$Rule:negativePredicate_	Ljava/util/List;
      //   883: iload_3
      //   884: iconst_2
      //   885: ior
      //   886: istore 7
      //   888: iload 7
      //   890: istore 5
      //   892: iload 7
      //   894: istore 4
      //   896: iload 7
      //   898: istore 6
      //   900: aload_1
      //   901: invokevirtual 173	com/google/tagmanager/protobuf/f:Bn	()I
      //   904: ifle +35 -> 939
      //   907: iload 7
      //   909: istore 5
      //   911: iload 7
      //   913: istore 4
      //   915: iload 7
      //   917: istore 6
      //   919: aload_0
      //   920: getfield 136	com/google/analytics/containertag/proto/Serving$Rule:negativePredicate_	Ljava/util/List;
      //   923: aload_1
      //   924: invokevirtual 112	com/google/tagmanager/protobuf/f:AW	()I
      //   927: invokestatic 118	java/lang/Integer:valueOf	(I)Ljava/lang/Integer;
      //   930: invokeinterface 124 2 0
      //   935: pop
      //   936: goto -48 -> 888
      //   939: iload 7
      //   941: istore 5
      //   943: iload 7
      //   945: istore 4
      //   947: iload 7
      //   949: istore 6
      //   951: aload_1
      //   952: iload 9
      //   954: invokevirtual 184	com/google/tagmanager/protobuf/f:eW	(I)V
      //   957: iload 7
      //   959: istore_3
      //   960: goto -925 -> 35
      //   963: iload_3
      //   964: istore 7
      //   966: iload_3
      //   967: iconst_4
      //   968: iand
      //   969: iconst_4
      //   970: if_icmpeq +28 -> 998
      //   973: iload_3
      //   974: istore 5
      //   976: iload_3
      //   977: istore 4
      //   979: iload_3
      //   980: istore 6
      //   982: aload_0
      //   983: new 106	java/util/ArrayList
      //   986: dup
      //   987: invokespecial 107	java/util/ArrayList:<init>	()V
      //   990: putfield 138	com/google/analytics/containertag/proto/Serving$Rule:addTag_	Ljava/util/List;
      //   993: iload_3
      //   994: iconst_4
      //   995: ior
      //   996: istore 7
      //   998: iload 7
      //   1000: istore 5
      //   1002: iload 7
      //   1004: istore 4
      //   1006: iload 7
      //   1008: istore 6
      //   1010: aload_0
      //   1011: getfield 138	com/google/analytics/containertag/proto/Serving$Rule:addTag_	Ljava/util/List;
      //   1014: aload_1
      //   1015: invokevirtual 112	com/google/tagmanager/protobuf/f:AW	()I
      //   1018: invokestatic 118	java/lang/Integer:valueOf	(I)Ljava/lang/Integer;
      //   1021: invokeinterface 124 2 0
      //   1026: pop
      //   1027: iload 7
      //   1029: istore_3
      //   1030: goto -995 -> 35
      //   1033: iload_3
      //   1034: istore 5
      //   1036: iload_3
      //   1037: istore 4
      //   1039: iload_3
      //   1040: istore 6
      //   1042: aload_1
      //   1043: aload_1
      //   1044: invokevirtual 166	com/google/tagmanager/protobuf/f:Bi	()I
      //   1047: invokevirtual 170	com/google/tagmanager/protobuf/f:eV	(I)I
      //   1050: istore 9
      //   1052: iload_3
      //   1053: istore 7
      //   1055: iload_3
      //   1056: iconst_4
      //   1057: iand
      //   1058: iconst_4
      //   1059: if_icmpeq +47 -> 1106
      //   1062: iload_3
      //   1063: istore 5
      //   1065: iload_3
      //   1066: istore 4
      //   1068: iload_3
      //   1069: istore 6
      //   1071: iload_3
      //   1072: istore 7
      //   1074: aload_1
      //   1075: invokevirtual 173	com/google/tagmanager/protobuf/f:Bn	()I
      //   1078: ifle +28 -> 1106
      //   1081: iload_3
      //   1082: istore 5
      //   1084: iload_3
      //   1085: istore 4
      //   1087: iload_3
      //   1088: istore 6
      //   1090: aload_0
      //   1091: new 106	java/util/ArrayList
      //   1094: dup
      //   1095: invokespecial 107	java/util/ArrayList:<init>	()V
      //   1098: putfield 138	com/google/analytics/containertag/proto/Serving$Rule:addTag_	Ljava/util/List;
      //   1101: iload_3
      //   1102: iconst_4
      //   1103: ior
      //   1104: istore 7
      //   1106: iload 7
      //   1108: istore 5
      //   1110: iload 7
      //   1112: istore 4
      //   1114: iload 7
      //   1116: istore 6
      //   1118: aload_1
      //   1119: invokevirtual 173	com/google/tagmanager/protobuf/f:Bn	()I
      //   1122: ifle +35 -> 1157
      //   1125: iload 7
      //   1127: istore 5
      //   1129: iload 7
      //   1131: istore 4
      //   1133: iload 7
      //   1135: istore 6
      //   1137: aload_0
      //   1138: getfield 138	com/google/analytics/containertag/proto/Serving$Rule:addTag_	Ljava/util/List;
      //   1141: aload_1
      //   1142: invokevirtual 112	com/google/tagmanager/protobuf/f:AW	()I
      //   1145: invokestatic 118	java/lang/Integer:valueOf	(I)Ljava/lang/Integer;
      //   1148: invokeinterface 124 2 0
      //   1153: pop
      //   1154: goto -48 -> 1106
      //   1157: iload 7
      //   1159: istore 5
      //   1161: iload 7
      //   1163: istore 4
      //   1165: iload 7
      //   1167: istore 6
      //   1169: aload_1
      //   1170: iload 9
      //   1172: invokevirtual 184	com/google/tagmanager/protobuf/f:eW	(I)V
      //   1175: iload 7
      //   1177: istore_3
      //   1178: goto -1143 -> 35
      //   1181: iload_3
      //   1182: istore 7
      //   1184: iload_3
      //   1185: bipush 8
      //   1187: iand
      //   1188: bipush 8
      //   1190: if_icmpeq +29 -> 1219
      //   1193: iload_3
      //   1194: istore 5
      //   1196: iload_3
      //   1197: istore 4
      //   1199: iload_3
      //   1200: istore 6
      //   1202: aload_0
      //   1203: new 106	java/util/ArrayList
      //   1206: dup
      //   1207: invokespecial 107	java/util/ArrayList:<init>	()V
      //   1210: putfield 140	com/google/analytics/containertag/proto/Serving$Rule:removeTag_	Ljava/util/List;
      //   1213: iload_3
      //   1214: bipush 8
      //   1216: ior
      //   1217: istore 7
      //   1219: iload 7
      //   1221: istore 5
      //   1223: iload 7
      //   1225: istore 4
      //   1227: iload 7
      //   1229: istore 6
      //   1231: aload_0
      //   1232: getfield 140	com/google/analytics/containertag/proto/Serving$Rule:removeTag_	Ljava/util/List;
      //   1235: aload_1
      //   1236: invokevirtual 112	com/google/tagmanager/protobuf/f:AW	()I
      //   1239: invokestatic 118	java/lang/Integer:valueOf	(I)Ljava/lang/Integer;
      //   1242: invokeinterface 124 2 0
      //   1247: pop
      //   1248: iload 7
      //   1250: istore_3
      //   1251: goto -1216 -> 35
      //   1254: iload_3
      //   1255: istore 5
      //   1257: iload_3
      //   1258: istore 4
      //   1260: iload_3
      //   1261: istore 6
      //   1263: aload_1
      //   1264: aload_1
      //   1265: invokevirtual 166	com/google/tagmanager/protobuf/f:Bi	()I
      //   1268: invokevirtual 170	com/google/tagmanager/protobuf/f:eV	(I)I
      //   1271: istore 9
      //   1273: iload_3
      //   1274: istore 7
      //   1276: iload_3
      //   1277: bipush 8
      //   1279: iand
      //   1280: bipush 8
      //   1282: if_icmpeq +48 -> 1330
      //   1285: iload_3
      //   1286: istore 5
      //   1288: iload_3
      //   1289: istore 4
      //   1291: iload_3
      //   1292: istore 6
      //   1294: iload_3
      //   1295: istore 7
      //   1297: aload_1
      //   1298: invokevirtual 173	com/google/tagmanager/protobuf/f:Bn	()I
      //   1301: ifle +29 -> 1330
      //   1304: iload_3
      //   1305: istore 5
      //   1307: iload_3
      //   1308: istore 4
      //   1310: iload_3
      //   1311: istore 6
      //   1313: aload_0
      //   1314: new 106	java/util/ArrayList
      //   1317: dup
      //   1318: invokespecial 107	java/util/ArrayList:<init>	()V
      //   1321: putfield 140	com/google/analytics/containertag/proto/Serving$Rule:removeTag_	Ljava/util/List;
      //   1324: iload_3
      //   1325: bipush 8
      //   1327: ior
      //   1328: istore 7
      //   1330: iload 7
      //   1332: istore 5
      //   1334: iload 7
      //   1336: istore 4
      //   1338: iload 7
      //   1340: istore 6
      //   1342: aload_1
      //   1343: invokevirtual 173	com/google/tagmanager/protobuf/f:Bn	()I
      //   1346: ifle +35 -> 1381
      //   1349: iload 7
      //   1351: istore 5
      //   1353: iload 7
      //   1355: istore 4
      //   1357: iload 7
      //   1359: istore 6
      //   1361: aload_0
      //   1362: getfield 140	com/google/analytics/containertag/proto/Serving$Rule:removeTag_	Ljava/util/List;
      //   1365: aload_1
      //   1366: invokevirtual 112	com/google/tagmanager/protobuf/f:AW	()I
      //   1369: invokestatic 118	java/lang/Integer:valueOf	(I)Ljava/lang/Integer;
      //   1372: invokeinterface 124 2 0
      //   1377: pop
      //   1378: goto -48 -> 1330
      //   1381: iload 7
      //   1383: istore 5
      //   1385: iload 7
      //   1387: istore 4
      //   1389: iload 7
      //   1391: istore 6
      //   1393: aload_1
      //   1394: iload 9
      //   1396: invokevirtual 184	com/google/tagmanager/protobuf/f:eW	(I)V
      //   1399: iload 7
      //   1401: istore_3
      //   1402: goto -1367 -> 35
      //   1405: iload_3
      //   1406: istore 7
      //   1408: iload_3
      //   1409: bipush 16
      //   1411: iand
      //   1412: bipush 16
      //   1414: if_icmpeq +29 -> 1443
      //   1417: iload_3
      //   1418: istore 5
      //   1420: iload_3
      //   1421: istore 4
      //   1423: iload_3
      //   1424: istore 6
      //   1426: aload_0
      //   1427: new 106	java/util/ArrayList
      //   1430: dup
      //   1431: invokespecial 107	java/util/ArrayList:<init>	()V
      //   1434: putfield 142	com/google/analytics/containertag/proto/Serving$Rule:addTagRuleName_	Ljava/util/List;
      //   1437: iload_3
      //   1438: bipush 16
      //   1440: ior
      //   1441: istore 7
      //   1443: iload 7
      //   1445: istore 5
      //   1447: iload 7
      //   1449: istore 4
      //   1451: iload 7
      //   1453: istore 6
      //   1455: aload_0
      //   1456: getfield 142	com/google/analytics/containertag/proto/Serving$Rule:addTagRuleName_	Ljava/util/List;
      //   1459: aload_1
      //   1460: invokevirtual 112	com/google/tagmanager/protobuf/f:AW	()I
      //   1463: invokestatic 118	java/lang/Integer:valueOf	(I)Ljava/lang/Integer;
      //   1466: invokeinterface 124 2 0
      //   1471: pop
      //   1472: iload 7
      //   1474: istore_3
      //   1475: goto -1440 -> 35
      //   1478: iload_3
      //   1479: istore 5
      //   1481: iload_3
      //   1482: istore 4
      //   1484: iload_3
      //   1485: istore 6
      //   1487: aload_1
      //   1488: aload_1
      //   1489: invokevirtual 166	com/google/tagmanager/protobuf/f:Bi	()I
      //   1492: invokevirtual 170	com/google/tagmanager/protobuf/f:eV	(I)I
      //   1495: istore 9
      //   1497: iload_3
      //   1498: istore 7
      //   1500: iload_3
      //   1501: bipush 16
      //   1503: iand
      //   1504: bipush 16
      //   1506: if_icmpeq +48 -> 1554
      //   1509: iload_3
      //   1510: istore 5
      //   1512: iload_3
      //   1513: istore 4
      //   1515: iload_3
      //   1516: istore 6
      //   1518: iload_3
      //   1519: istore 7
      //   1521: aload_1
      //   1522: invokevirtual 173	com/google/tagmanager/protobuf/f:Bn	()I
      //   1525: ifle +29 -> 1554
      //   1528: iload_3
      //   1529: istore 5
      //   1531: iload_3
      //   1532: istore 4
      //   1534: iload_3
      //   1535: istore 6
      //   1537: aload_0
      //   1538: new 106	java/util/ArrayList
      //   1541: dup
      //   1542: invokespecial 107	java/util/ArrayList:<init>	()V
      //   1545: putfield 142	com/google/analytics/containertag/proto/Serving$Rule:addTagRuleName_	Ljava/util/List;
      //   1548: iload_3
      //   1549: bipush 16
      //   1551: ior
      //   1552: istore 7
      //   1554: iload 7
      //   1556: istore 5
      //   1558: iload 7
      //   1560: istore 4
      //   1562: iload 7
      //   1564: istore 6
      //   1566: aload_1
      //   1567: invokevirtual 173	com/google/tagmanager/protobuf/f:Bn	()I
      //   1570: ifle +35 -> 1605
      //   1573: iload 7
      //   1575: istore 5
      //   1577: iload 7
      //   1579: istore 4
      //   1581: iload 7
      //   1583: istore 6
      //   1585: aload_0
      //   1586: getfield 142	com/google/analytics/containertag/proto/Serving$Rule:addTagRuleName_	Ljava/util/List;
      //   1589: aload_1
      //   1590: invokevirtual 112	com/google/tagmanager/protobuf/f:AW	()I
      //   1593: invokestatic 118	java/lang/Integer:valueOf	(I)Ljava/lang/Integer;
      //   1596: invokeinterface 124 2 0
      //   1601: pop
      //   1602: goto -48 -> 1554
      //   1605: iload 7
      //   1607: istore 5
      //   1609: iload 7
      //   1611: istore 4
      //   1613: iload 7
      //   1615: istore 6
      //   1617: aload_1
      //   1618: iload 9
      //   1620: invokevirtual 184	com/google/tagmanager/protobuf/f:eW	(I)V
      //   1623: iload 7
      //   1625: istore_3
      //   1626: goto -1591 -> 35
      //   1629: iload_3
      //   1630: istore 7
      //   1632: iload_3
      //   1633: bipush 32
      //   1635: iand
      //   1636: bipush 32
      //   1638: if_icmpeq +29 -> 1667
      //   1641: iload_3
      //   1642: istore 5
      //   1644: iload_3
      //   1645: istore 4
      //   1647: iload_3
      //   1648: istore 6
      //   1650: aload_0
      //   1651: new 106	java/util/ArrayList
      //   1654: dup
      //   1655: invokespecial 107	java/util/ArrayList:<init>	()V
      //   1658: putfield 144	com/google/analytics/containertag/proto/Serving$Rule:removeTagRuleName_	Ljava/util/List;
      //   1661: iload_3
      //   1662: bipush 32
      //   1664: ior
      //   1665: istore 7
      //   1667: iload 7
      //   1669: istore 5
      //   1671: iload 7
      //   1673: istore 4
      //   1675: iload 7
      //   1677: istore 6
      //   1679: aload_0
      //   1680: getfield 144	com/google/analytics/containertag/proto/Serving$Rule:removeTagRuleName_	Ljava/util/List;
      //   1683: aload_1
      //   1684: invokevirtual 112	com/google/tagmanager/protobuf/f:AW	()I
      //   1687: invokestatic 118	java/lang/Integer:valueOf	(I)Ljava/lang/Integer;
      //   1690: invokeinterface 124 2 0
      //   1695: pop
      //   1696: iload 7
      //   1698: istore_3
      //   1699: goto -1664 -> 35
      //   1702: iload_3
      //   1703: istore 5
      //   1705: iload_3
      //   1706: istore 4
      //   1708: iload_3
      //   1709: istore 6
      //   1711: aload_1
      //   1712: aload_1
      //   1713: invokevirtual 166	com/google/tagmanager/protobuf/f:Bi	()I
      //   1716: invokevirtual 170	com/google/tagmanager/protobuf/f:eV	(I)I
      //   1719: istore 9
      //   1721: iload_3
      //   1722: istore 7
      //   1724: iload_3
      //   1725: bipush 32
      //   1727: iand
      //   1728: bipush 32
      //   1730: if_icmpeq +48 -> 1778
      //   1733: iload_3
      //   1734: istore 5
      //   1736: iload_3
      //   1737: istore 4
      //   1739: iload_3
      //   1740: istore 6
      //   1742: iload_3
      //   1743: istore 7
      //   1745: aload_1
      //   1746: invokevirtual 173	com/google/tagmanager/protobuf/f:Bn	()I
      //   1749: ifle +29 -> 1778
      //   1752: iload_3
      //   1753: istore 5
      //   1755: iload_3
      //   1756: istore 4
      //   1758: iload_3
      //   1759: istore 6
      //   1761: aload_0
      //   1762: new 106	java/util/ArrayList
      //   1765: dup
      //   1766: invokespecial 107	java/util/ArrayList:<init>	()V
      //   1769: putfield 144	com/google/analytics/containertag/proto/Serving$Rule:removeTagRuleName_	Ljava/util/List;
      //   1772: iload_3
      //   1773: bipush 32
      //   1775: ior
      //   1776: istore 7
      //   1778: iload 7
      //   1780: istore 5
      //   1782: iload 7
      //   1784: istore 4
      //   1786: iload 7
      //   1788: istore 6
      //   1790: aload_1
      //   1791: invokevirtual 173	com/google/tagmanager/protobuf/f:Bn	()I
      //   1794: ifle +35 -> 1829
      //   1797: iload 7
      //   1799: istore 5
      //   1801: iload 7
      //   1803: istore 4
      //   1805: iload 7
      //   1807: istore 6
      //   1809: aload_0
      //   1810: getfield 144	com/google/analytics/containertag/proto/Serving$Rule:removeTagRuleName_	Ljava/util/List;
      //   1813: aload_1
      //   1814: invokevirtual 112	com/google/tagmanager/protobuf/f:AW	()I
      //   1817: invokestatic 118	java/lang/Integer:valueOf	(I)Ljava/lang/Integer;
      //   1820: invokeinterface 124 2 0
      //   1825: pop
      //   1826: goto -48 -> 1778
      //   1829: iload 7
      //   1831: istore 5
      //   1833: iload 7
      //   1835: istore 4
      //   1837: iload 7
      //   1839: istore 6
      //   1841: aload_1
      //   1842: iload 9
      //   1844: invokevirtual 184	com/google/tagmanager/protobuf/f:eW	(I)V
      //   1847: iload 7
      //   1849: istore_3
      //   1850: goto -1815 -> 35
      //   1853: iload_3
      //   1854: istore 7
      //   1856: iload_3
      //   1857: bipush 64
      //   1859: iand
      //   1860: bipush 64
      //   1862: if_icmpeq +29 -> 1891
      //   1865: iload_3
      //   1866: istore 5
      //   1868: iload_3
      //   1869: istore 4
      //   1871: iload_3
      //   1872: istore 6
      //   1874: aload_0
      //   1875: new 106	java/util/ArrayList
      //   1878: dup
      //   1879: invokespecial 107	java/util/ArrayList:<init>	()V
      //   1882: putfield 146	com/google/analytics/containertag/proto/Serving$Rule:addMacro_	Ljava/util/List;
      //   1885: iload_3
      //   1886: bipush 64
      //   1888: ior
      //   1889: istore 7
      //   1891: iload 7
      //   1893: istore 5
      //   1895: iload 7
      //   1897: istore 4
      //   1899: iload 7
      //   1901: istore 6
      //   1903: aload_0
      //   1904: getfield 146	com/google/analytics/containertag/proto/Serving$Rule:addMacro_	Ljava/util/List;
      //   1907: aload_1
      //   1908: invokevirtual 112	com/google/tagmanager/protobuf/f:AW	()I
      //   1911: invokestatic 118	java/lang/Integer:valueOf	(I)Ljava/lang/Integer;
      //   1914: invokeinterface 124 2 0
      //   1919: pop
      //   1920: iload 7
      //   1922: istore_3
      //   1923: goto -1888 -> 35
      //   1926: iload_3
      //   1927: istore 5
      //   1929: iload_3
      //   1930: istore 4
      //   1932: iload_3
      //   1933: istore 6
      //   1935: aload_1
      //   1936: aload_1
      //   1937: invokevirtual 166	com/google/tagmanager/protobuf/f:Bi	()I
      //   1940: invokevirtual 170	com/google/tagmanager/protobuf/f:eV	(I)I
      //   1943: istore 9
      //   1945: iload_3
      //   1946: istore 7
      //   1948: iload_3
      //   1949: bipush 64
      //   1951: iand
      //   1952: bipush 64
      //   1954: if_icmpeq +48 -> 2002
      //   1957: iload_3
      //   1958: istore 5
      //   1960: iload_3
      //   1961: istore 4
      //   1963: iload_3
      //   1964: istore 6
      //   1966: iload_3
      //   1967: istore 7
      //   1969: aload_1
      //   1970: invokevirtual 173	com/google/tagmanager/protobuf/f:Bn	()I
      //   1973: ifle +29 -> 2002
      //   1976: iload_3
      //   1977: istore 5
      //   1979: iload_3
      //   1980: istore 4
      //   1982: iload_3
      //   1983: istore 6
      //   1985: aload_0
      //   1986: new 106	java/util/ArrayList
      //   1989: dup
      //   1990: invokespecial 107	java/util/ArrayList:<init>	()V
      //   1993: putfield 146	com/google/analytics/containertag/proto/Serving$Rule:addMacro_	Ljava/util/List;
      //   1996: iload_3
      //   1997: bipush 64
      //   1999: ior
      //   2000: istore 7
      //   2002: iload 7
      //   2004: istore 5
      //   2006: iload 7
      //   2008: istore 4
      //   2010: iload 7
      //   2012: istore 6
      //   2014: aload_1
      //   2015: invokevirtual 173	com/google/tagmanager/protobuf/f:Bn	()I
      //   2018: ifle +35 -> 2053
      //   2021: iload 7
      //   2023: istore 5
      //   2025: iload 7
      //   2027: istore 4
      //   2029: iload 7
      //   2031: istore 6
      //   2033: aload_0
      //   2034: getfield 146	com/google/analytics/containertag/proto/Serving$Rule:addMacro_	Ljava/util/List;
      //   2037: aload_1
      //   2038: invokevirtual 112	com/google/tagmanager/protobuf/f:AW	()I
      //   2041: invokestatic 118	java/lang/Integer:valueOf	(I)Ljava/lang/Integer;
      //   2044: invokeinterface 124 2 0
      //   2049: pop
      //   2050: goto -48 -> 2002
      //   2053: iload 7
      //   2055: istore 5
      //   2057: iload 7
      //   2059: istore 4
      //   2061: iload 7
      //   2063: istore 6
      //   2065: aload_1
      //   2066: iload 9
      //   2068: invokevirtual 184	com/google/tagmanager/protobuf/f:eW	(I)V
      //   2071: iload 7
      //   2073: istore_3
      //   2074: goto -2039 -> 35
      //   2077: iload_3
      //   2078: istore 7
      //   2080: iload_3
      //   2081: sipush 128
      //   2084: iand
      //   2085: sipush 128
      //   2088: if_icmpeq +30 -> 2118
      //   2091: iload_3
      //   2092: istore 5
      //   2094: iload_3
      //   2095: istore 4
      //   2097: iload_3
      //   2098: istore 6
      //   2100: aload_0
      //   2101: new 106	java/util/ArrayList
      //   2104: dup
      //   2105: invokespecial 107	java/util/ArrayList:<init>	()V
      //   2108: putfield 148	com/google/analytics/containertag/proto/Serving$Rule:removeMacro_	Ljava/util/List;
      //   2111: iload_3
      //   2112: sipush 128
      //   2115: ior
      //   2116: istore 7
      //   2118: iload 7
      //   2120: istore 5
      //   2122: iload 7
      //   2124: istore 4
      //   2126: iload 7
      //   2128: istore 6
      //   2130: aload_0
      //   2131: getfield 148	com/google/analytics/containertag/proto/Serving$Rule:removeMacro_	Ljava/util/List;
      //   2134: aload_1
      //   2135: invokevirtual 112	com/google/tagmanager/protobuf/f:AW	()I
      //   2138: invokestatic 118	java/lang/Integer:valueOf	(I)Ljava/lang/Integer;
      //   2141: invokeinterface 124 2 0
      //   2146: pop
      //   2147: iload 7
      //   2149: istore_3
      //   2150: goto -2115 -> 35
      //   2153: iload_3
      //   2154: istore 5
      //   2156: iload_3
      //   2157: istore 4
      //   2159: iload_3
      //   2160: istore 6
      //   2162: aload_1
      //   2163: aload_1
      //   2164: invokevirtual 166	com/google/tagmanager/protobuf/f:Bi	()I
      //   2167: invokevirtual 170	com/google/tagmanager/protobuf/f:eV	(I)I
      //   2170: istore 9
      //   2172: iload_3
      //   2173: istore 7
      //   2175: iload_3
      //   2176: sipush 128
      //   2179: iand
      //   2180: sipush 128
      //   2183: if_icmpeq +49 -> 2232
      //   2186: iload_3
      //   2187: istore 5
      //   2189: iload_3
      //   2190: istore 4
      //   2192: iload_3
      //   2193: istore 6
      //   2195: iload_3
      //   2196: istore 7
      //   2198: aload_1
      //   2199: invokevirtual 173	com/google/tagmanager/protobuf/f:Bn	()I
      //   2202: ifle +30 -> 2232
      //   2205: iload_3
      //   2206: istore 5
      //   2208: iload_3
      //   2209: istore 4
      //   2211: iload_3
      //   2212: istore 6
      //   2214: aload_0
      //   2215: new 106	java/util/ArrayList
      //   2218: dup
      //   2219: invokespecial 107	java/util/ArrayList:<init>	()V
      //   2222: putfield 148	com/google/analytics/containertag/proto/Serving$Rule:removeMacro_	Ljava/util/List;
      //   2225: iload_3
      //   2226: sipush 128
      //   2229: ior
      //   2230: istore 7
      //   2232: iload 7
      //   2234: istore 5
      //   2236: iload 7
      //   2238: istore 4
      //   2240: iload 7
      //   2242: istore 6
      //   2244: aload_1
      //   2245: invokevirtual 173	com/google/tagmanager/protobuf/f:Bn	()I
      //   2248: ifle +35 -> 2283
      //   2251: iload 7
      //   2253: istore 5
      //   2255: iload 7
      //   2257: istore 4
      //   2259: iload 7
      //   2261: istore 6
      //   2263: aload_0
      //   2264: getfield 148	com/google/analytics/containertag/proto/Serving$Rule:removeMacro_	Ljava/util/List;
      //   2267: aload_1
      //   2268: invokevirtual 112	com/google/tagmanager/protobuf/f:AW	()I
      //   2271: invokestatic 118	java/lang/Integer:valueOf	(I)Ljava/lang/Integer;
      //   2274: invokeinterface 124 2 0
      //   2279: pop
      //   2280: goto -48 -> 2232
      //   2283: iload 7
      //   2285: istore 5
      //   2287: iload 7
      //   2289: istore 4
      //   2291: iload 7
      //   2293: istore 6
      //   2295: aload_1
      //   2296: iload 9
      //   2298: invokevirtual 184	com/google/tagmanager/protobuf/f:eW	(I)V
      //   2301: iload 7
      //   2303: istore_3
      //   2304: goto -2269 -> 35
      //   2307: iload_3
      //   2308: istore 7
      //   2310: iload_3
      //   2311: sipush 256
      //   2314: iand
      //   2315: sipush 256
      //   2318: if_icmpeq +30 -> 2348
      //   2321: iload_3
      //   2322: istore 5
      //   2324: iload_3
      //   2325: istore 4
      //   2327: iload_3
      //   2328: istore 6
      //   2330: aload_0
      //   2331: new 106	java/util/ArrayList
      //   2334: dup
      //   2335: invokespecial 107	java/util/ArrayList:<init>	()V
      //   2338: putfield 150	com/google/analytics/containertag/proto/Serving$Rule:addMacroRuleName_	Ljava/util/List;
      //   2341: iload_3
      //   2342: sipush 256
      //   2345: ior
      //   2346: istore 7
      //   2348: iload 7
      //   2350: istore 5
      //   2352: iload 7
      //   2354: istore 4
      //   2356: iload 7
      //   2358: istore 6
      //   2360: aload_0
      //   2361: getfield 150	com/google/analytics/containertag/proto/Serving$Rule:addMacroRuleName_	Ljava/util/List;
      //   2364: aload_1
      //   2365: invokevirtual 112	com/google/tagmanager/protobuf/f:AW	()I
      //   2368: invokestatic 118	java/lang/Integer:valueOf	(I)Ljava/lang/Integer;
      //   2371: invokeinterface 124 2 0
      //   2376: pop
      //   2377: iload 7
      //   2379: istore_3
      //   2380: goto -2345 -> 35
      //   2383: iload_3
      //   2384: istore 5
      //   2386: iload_3
      //   2387: istore 4
      //   2389: iload_3
      //   2390: istore 6
      //   2392: aload_1
      //   2393: aload_1
      //   2394: invokevirtual 166	com/google/tagmanager/protobuf/f:Bi	()I
      //   2397: invokevirtual 170	com/google/tagmanager/protobuf/f:eV	(I)I
      //   2400: istore 9
      //   2402: iload_3
      //   2403: istore 7
      //   2405: iload_3
      //   2406: sipush 256
      //   2409: iand
      //   2410: sipush 256
      //   2413: if_icmpeq +49 -> 2462
      //   2416: iload_3
      //   2417: istore 5
      //   2419: iload_3
      //   2420: istore 4
      //   2422: iload_3
      //   2423: istore 6
      //   2425: iload_3
      //   2426: istore 7
      //   2428: aload_1
      //   2429: invokevirtual 173	com/google/tagmanager/protobuf/f:Bn	()I
      //   2432: ifle +30 -> 2462
      //   2435: iload_3
      //   2436: istore 5
      //   2438: iload_3
      //   2439: istore 4
      //   2441: iload_3
      //   2442: istore 6
      //   2444: aload_0
      //   2445: new 106	java/util/ArrayList
      //   2448: dup
      //   2449: invokespecial 107	java/util/ArrayList:<init>	()V
      //   2452: putfield 150	com/google/analytics/containertag/proto/Serving$Rule:addMacroRuleName_	Ljava/util/List;
      //   2455: iload_3
      //   2456: sipush 256
      //   2459: ior
      //   2460: istore 7
      //   2462: iload 7
      //   2464: istore 5
      //   2466: iload 7
      //   2468: istore 4
      //   2470: iload 7
      //   2472: istore 6
      //   2474: aload_1
      //   2475: invokevirtual 173	com/google/tagmanager/protobuf/f:Bn	()I
      //   2478: ifle +35 -> 2513
      //   2481: iload 7
      //   2483: istore 5
      //   2485: iload 7
      //   2487: istore 4
      //   2489: iload 7
      //   2491: istore 6
      //   2493: aload_0
      //   2494: getfield 150	com/google/analytics/containertag/proto/Serving$Rule:addMacroRuleName_	Ljava/util/List;
      //   2497: aload_1
      //   2498: invokevirtual 112	com/google/tagmanager/protobuf/f:AW	()I
      //   2501: invokestatic 118	java/lang/Integer:valueOf	(I)Ljava/lang/Integer;
      //   2504: invokeinterface 124 2 0
      //   2509: pop
      //   2510: goto -48 -> 2462
      //   2513: iload 7
      //   2515: istore 5
      //   2517: iload 7
      //   2519: istore 4
      //   2521: iload 7
      //   2523: istore 6
      //   2525: aload_1
      //   2526: iload 9
      //   2528: invokevirtual 184	com/google/tagmanager/protobuf/f:eW	(I)V
      //   2531: iload 7
      //   2533: istore_3
      //   2534: goto -2499 -> 35
      //   2537: iload_3
      //   2538: istore 7
      //   2540: iload_3
      //   2541: sipush 512
      //   2544: iand
      //   2545: sipush 512
      //   2548: if_icmpeq +30 -> 2578
      //   2551: iload_3
      //   2552: istore 5
      //   2554: iload_3
      //   2555: istore 4
      //   2557: iload_3
      //   2558: istore 6
      //   2560: aload_0
      //   2561: new 106	java/util/ArrayList
      //   2564: dup
      //   2565: invokespecial 107	java/util/ArrayList:<init>	()V
      //   2568: putfield 152	com/google/analytics/containertag/proto/Serving$Rule:removeMacroRuleName_	Ljava/util/List;
      //   2571: iload_3
      //   2572: sipush 512
      //   2575: ior
      //   2576: istore 7
      //   2578: iload 7
      //   2580: istore 5
      //   2582: iload 7
      //   2584: istore 4
      //   2586: iload 7
      //   2588: istore 6
      //   2590: aload_0
      //   2591: getfield 152	com/google/analytics/containertag/proto/Serving$Rule:removeMacroRuleName_	Ljava/util/List;
      //   2594: aload_1
      //   2595: invokevirtual 112	com/google/tagmanager/protobuf/f:AW	()I
      //   2598: invokestatic 118	java/lang/Integer:valueOf	(I)Ljava/lang/Integer;
      //   2601: invokeinterface 124 2 0
      //   2606: pop
      //   2607: iload 7
      //   2609: istore_3
      //   2610: goto -2575 -> 35
      //   2613: iload_3
      //   2614: istore 5
      //   2616: iload_3
      //   2617: istore 4
      //   2619: iload_3
      //   2620: istore 6
      //   2622: aload_1
      //   2623: aload_1
      //   2624: invokevirtual 166	com/google/tagmanager/protobuf/f:Bi	()I
      //   2627: invokevirtual 170	com/google/tagmanager/protobuf/f:eV	(I)I
      //   2630: istore 9
      //   2632: iload_3
      //   2633: istore 7
      //   2635: iload_3
      //   2636: sipush 512
      //   2639: iand
      //   2640: sipush 512
      //   2643: if_icmpeq +49 -> 2692
      //   2646: iload_3
      //   2647: istore 5
      //   2649: iload_3
      //   2650: istore 4
      //   2652: iload_3
      //   2653: istore 6
      //   2655: iload_3
      //   2656: istore 7
      //   2658: aload_1
      //   2659: invokevirtual 173	com/google/tagmanager/protobuf/f:Bn	()I
      //   2662: ifle +30 -> 2692
      //   2665: iload_3
      //   2666: istore 5
      //   2668: iload_3
      //   2669: istore 4
      //   2671: iload_3
      //   2672: istore 6
      //   2674: aload_0
      //   2675: new 106	java/util/ArrayList
      //   2678: dup
      //   2679: invokespecial 107	java/util/ArrayList:<init>	()V
      //   2682: putfield 152	com/google/analytics/containertag/proto/Serving$Rule:removeMacroRuleName_	Ljava/util/List;
      //   2685: iload_3
      //   2686: sipush 512
      //   2689: ior
      //   2690: istore 7
      //   2692: iload 7
      //   2694: istore 5
      //   2696: iload 7
      //   2698: istore 4
      //   2700: iload 7
      //   2702: istore 6
      //   2704: aload_1
      //   2705: invokevirtual 173	com/google/tagmanager/protobuf/f:Bn	()I
      //   2708: ifle +35 -> 2743
      //   2711: iload 7
      //   2713: istore 5
      //   2715: iload 7
      //   2717: istore 4
      //   2719: iload 7
      //   2721: istore 6
      //   2723: aload_0
      //   2724: getfield 152	com/google/analytics/containertag/proto/Serving$Rule:removeMacroRuleName_	Ljava/util/List;
      //   2727: aload_1
      //   2728: invokevirtual 112	com/google/tagmanager/protobuf/f:AW	()I
      //   2731: invokestatic 118	java/lang/Integer:valueOf	(I)Ljava/lang/Integer;
      //   2734: invokeinterface 124 2 0
      //   2739: pop
      //   2740: goto -48 -> 2692
      //   2743: iload 7
      //   2745: istore 5
      //   2747: iload 7
      //   2749: istore 4
      //   2751: iload 7
      //   2753: istore 6
      //   2755: aload_1
      //   2756: iload 9
      //   2758: invokevirtual 184	com/google/tagmanager/protobuf/f:eW	(I)V
      //   2761: iload 7
      //   2763: istore_3
      //   2764: goto -2729 -> 35
      //   2767: iload_3
      //   2768: iconst_1
      //   2769: iand
      //   2770: iconst_1
      //   2771: if_icmpne +14 -> 2785
      //   2774: aload_0
      //   2775: aload_0
      //   2776: getfield 109	com/google/analytics/containertag/proto/Serving$Rule:positivePredicate_	Ljava/util/List;
      //   2779: invokestatic 134	java/util/Collections:unmodifiableList	(Ljava/util/List;)Ljava/util/List;
      //   2782: putfield 109	com/google/analytics/containertag/proto/Serving$Rule:positivePredicate_	Ljava/util/List;
      //   2785: iload_3
      //   2786: iconst_2
      //   2787: iand
      //   2788: iconst_2
      //   2789: if_icmpne +14 -> 2803
      //   2792: aload_0
      //   2793: aload_0
      //   2794: getfield 136	com/google/analytics/containertag/proto/Serving$Rule:negativePredicate_	Ljava/util/List;
      //   2797: invokestatic 134	java/util/Collections:unmodifiableList	(Ljava/util/List;)Ljava/util/List;
      //   2800: putfield 136	com/google/analytics/containertag/proto/Serving$Rule:negativePredicate_	Ljava/util/List;
      //   2803: iload_3
      //   2804: iconst_4
      //   2805: iand
      //   2806: iconst_4
      //   2807: if_icmpne +14 -> 2821
      //   2810: aload_0
      //   2811: aload_0
      //   2812: getfield 138	com/google/analytics/containertag/proto/Serving$Rule:addTag_	Ljava/util/List;
      //   2815: invokestatic 134	java/util/Collections:unmodifiableList	(Ljava/util/List;)Ljava/util/List;
      //   2818: putfield 138	com/google/analytics/containertag/proto/Serving$Rule:addTag_	Ljava/util/List;
      //   2821: iload_3
      //   2822: bipush 8
      //   2824: iand
      //   2825: bipush 8
      //   2827: if_icmpne +14 -> 2841
      //   2830: aload_0
      //   2831: aload_0
      //   2832: getfield 140	com/google/analytics/containertag/proto/Serving$Rule:removeTag_	Ljava/util/List;
      //   2835: invokestatic 134	java/util/Collections:unmodifiableList	(Ljava/util/List;)Ljava/util/List;
      //   2838: putfield 140	com/google/analytics/containertag/proto/Serving$Rule:removeTag_	Ljava/util/List;
      //   2841: iload_3
      //   2842: bipush 16
      //   2844: iand
      //   2845: bipush 16
      //   2847: if_icmpne +14 -> 2861
      //   2850: aload_0
      //   2851: aload_0
      //   2852: getfield 142	com/google/analytics/containertag/proto/Serving$Rule:addTagRuleName_	Ljava/util/List;
      //   2855: invokestatic 134	java/util/Collections:unmodifiableList	(Ljava/util/List;)Ljava/util/List;
      //   2858: putfield 142	com/google/analytics/containertag/proto/Serving$Rule:addTagRuleName_	Ljava/util/List;
      //   2861: iload_3
      //   2862: bipush 32
      //   2864: iand
      //   2865: bipush 32
      //   2867: if_icmpne +14 -> 2881
      //   2870: aload_0
      //   2871: aload_0
      //   2872: getfield 144	com/google/analytics/containertag/proto/Serving$Rule:removeTagRuleName_	Ljava/util/List;
      //   2875: invokestatic 134	java/util/Collections:unmodifiableList	(Ljava/util/List;)Ljava/util/List;
      //   2878: putfield 144	com/google/analytics/containertag/proto/Serving$Rule:removeTagRuleName_	Ljava/util/List;
      //   2881: iload_3
      //   2882: bipush 64
      //   2884: iand
      //   2885: bipush 64
      //   2887: if_icmpne +14 -> 2901
      //   2890: aload_0
      //   2891: aload_0
      //   2892: getfield 146	com/google/analytics/containertag/proto/Serving$Rule:addMacro_	Ljava/util/List;
      //   2895: invokestatic 134	java/util/Collections:unmodifiableList	(Ljava/util/List;)Ljava/util/List;
      //   2898: putfield 146	com/google/analytics/containertag/proto/Serving$Rule:addMacro_	Ljava/util/List;
      //   2901: iload_3
      //   2902: sipush 128
      //   2905: iand
      //   2906: sipush 128
      //   2909: if_icmpne +14 -> 2923
      //   2912: aload_0
      //   2913: aload_0
      //   2914: getfield 148	com/google/analytics/containertag/proto/Serving$Rule:removeMacro_	Ljava/util/List;
      //   2917: invokestatic 134	java/util/Collections:unmodifiableList	(Ljava/util/List;)Ljava/util/List;
      //   2920: putfield 148	com/google/analytics/containertag/proto/Serving$Rule:removeMacro_	Ljava/util/List;
      //   2923: iload_3
      //   2924: sipush 256
      //   2927: iand
      //   2928: sipush 256
      //   2931: if_icmpne +14 -> 2945
      //   2934: aload_0
      //   2935: aload_0
      //   2936: getfield 150	com/google/analytics/containertag/proto/Serving$Rule:addMacroRuleName_	Ljava/util/List;
      //   2939: invokestatic 134	java/util/Collections:unmodifiableList	(Ljava/util/List;)Ljava/util/List;
      //   2942: putfield 150	com/google/analytics/containertag/proto/Serving$Rule:addMacroRuleName_	Ljava/util/List;
      //   2945: iload_3
      //   2946: sipush 512
      //   2949: iand
      //   2950: sipush 512
      //   2953: if_icmpne +14 -> 2967
      //   2956: aload_0
      //   2957: aload_0
      //   2958: getfield 152	com/google/analytics/containertag/proto/Serving$Rule:removeMacroRuleName_	Ljava/util/List;
      //   2961: invokestatic 134	java/util/Collections:unmodifiableList	(Ljava/util/List;)Ljava/util/List;
      //   2964: putfield 152	com/google/analytics/containertag/proto/Serving$Rule:removeMacroRuleName_	Ljava/util/List;
      //   2967: aload 11
      //   2969: invokevirtual 155	com/google/tagmanager/protobuf/CodedOutputStream:flush	()V
      //   2972: aload_0
      //   2973: aload 10
      //   2975: invokevirtual 160	com/google/tagmanager/protobuf/e$b:AR	()Lcom/google/tagmanager/protobuf/e;
      //   2978: putfield 76	com/google/analytics/containertag/proto/Serving$Rule:unknownFields	Lcom/google/tagmanager/protobuf/e;
      //   2981: aload_0
      //   2982: invokevirtual 163	com/google/analytics/containertag/proto/Serving$Rule:BD	()V
      //   2985: return
      //   2986: astore_1
      //   2987: aload_0
      //   2988: aload 10
      //   2990: invokevirtual 160	com/google/tagmanager/protobuf/e$b:AR	()Lcom/google/tagmanager/protobuf/e;
      //   2993: putfield 76	com/google/analytics/containertag/proto/Serving$Rule:unknownFields	Lcom/google/tagmanager/protobuf/e;
      //   2996: goto -15 -> 2981
      //   2999: astore_1
      //   3000: aload_0
      //   3001: aload 10
      //   3003: invokevirtual 160	com/google/tagmanager/protobuf/e$b:AR	()Lcom/google/tagmanager/protobuf/e;
      //   3006: putfield 76	com/google/analytics/containertag/proto/Serving$Rule:unknownFields	Lcom/google/tagmanager/protobuf/e;
      //   3009: aload_1
      //   3010: athrow
      //   3011: astore_2
      //   3012: aload_0
      //   3013: aload 10
      //   3015: invokevirtual 160	com/google/tagmanager/protobuf/e$b:AR	()Lcom/google/tagmanager/protobuf/e;
      //   3018: putfield 76	com/google/analytics/containertag/proto/Serving$Rule:unknownFields	Lcom/google/tagmanager/protobuf/e;
      //   3021: goto -2451 -> 570
      //   3024: astore_1
      //   3025: aload_0
      //   3026: aload 10
      //   3028: invokevirtual 160	com/google/tagmanager/protobuf/e$b:AR	()Lcom/google/tagmanager/protobuf/e;
      //   3031: putfield 76	com/google/analytics/containertag/proto/Serving$Rule:unknownFields	Lcom/google/tagmanager/protobuf/e;
      //   3034: aload_1
      //   3035: athrow
      //   3036: goto -2800 -> 236
      //   3039: iconst_1
      //   3040: istore 8
      //   3042: goto -3007 -> 35
      // Local variable table:
      //   start	length	slot	name	signature
      //   0	3045	0	this	Rule
      //   0	3045	1	paramf	f
      //   0	3045	2	paramg	g
      //   19	2931	3	i	int
      //   44	2706	4	j	int
      //   41	2705	5	k	int
      //   47	2707	6	m	int
      //   53	2709	7	n	int
      //   33	3008	8	i1	int
      //   593	2164	9	i2	int
      //   23	3004	10	localb	com.google.tagmanager.protobuf.e.b
      //   30	2938	11	localCodedOutputStream	CodedOutputStream
      // Exception table:
      //   from	to	target	type
      //   49	55	334	com/google/tagmanager/protobuf/InvalidProtocolBufferException
      //   245	258	334	com/google/tagmanager/protobuf/InvalidProtocolBufferException
      //   283	294	334	com/google/tagmanager/protobuf/InvalidProtocolBufferException
      //   311	328	334	com/google/tagmanager/protobuf/InvalidProtocolBufferException
      //   585	595	334	com/google/tagmanager/protobuf/InvalidProtocolBufferException
      //   617	624	334	com/google/tagmanager/protobuf/InvalidProtocolBufferException
      //   633	644	334	com/google/tagmanager/protobuf/InvalidProtocolBufferException
      //   661	668	334	com/google/tagmanager/protobuf/InvalidProtocolBufferException
      //   680	697	334	com/google/tagmanager/protobuf/InvalidProtocolBufferException
      //   733	739	334	com/google/tagmanager/protobuf/InvalidProtocolBufferException
      //   764	775	334	com/google/tagmanager/protobuf/InvalidProtocolBufferException
      //   792	809	334	com/google/tagmanager/protobuf/InvalidProtocolBufferException
      //   824	834	334	com/google/tagmanager/protobuf/InvalidProtocolBufferException
      //   856	863	334	com/google/tagmanager/protobuf/InvalidProtocolBufferException
      //   872	883	334	com/google/tagmanager/protobuf/InvalidProtocolBufferException
      //   900	907	334	com/google/tagmanager/protobuf/InvalidProtocolBufferException
      //   919	936	334	com/google/tagmanager/protobuf/InvalidProtocolBufferException
      //   951	957	334	com/google/tagmanager/protobuf/InvalidProtocolBufferException
      //   982	993	334	com/google/tagmanager/protobuf/InvalidProtocolBufferException
      //   1010	1027	334	com/google/tagmanager/protobuf/InvalidProtocolBufferException
      //   1042	1052	334	com/google/tagmanager/protobuf/InvalidProtocolBufferException
      //   1074	1081	334	com/google/tagmanager/protobuf/InvalidProtocolBufferException
      //   1090	1101	334	com/google/tagmanager/protobuf/InvalidProtocolBufferException
      //   1118	1125	334	com/google/tagmanager/protobuf/InvalidProtocolBufferException
      //   1137	1154	334	com/google/tagmanager/protobuf/InvalidProtocolBufferException
      //   1169	1175	334	com/google/tagmanager/protobuf/InvalidProtocolBufferException
      //   1202	1213	334	com/google/tagmanager/protobuf/InvalidProtocolBufferException
      //   1231	1248	334	com/google/tagmanager/protobuf/InvalidProtocolBufferException
      //   1263	1273	334	com/google/tagmanager/protobuf/InvalidProtocolBufferException
      //   1297	1304	334	com/google/tagmanager/protobuf/InvalidProtocolBufferException
      //   1313	1324	334	com/google/tagmanager/protobuf/InvalidProtocolBufferException
      //   1342	1349	334	com/google/tagmanager/protobuf/InvalidProtocolBufferException
      //   1361	1378	334	com/google/tagmanager/protobuf/InvalidProtocolBufferException
      //   1393	1399	334	com/google/tagmanager/protobuf/InvalidProtocolBufferException
      //   1426	1437	334	com/google/tagmanager/protobuf/InvalidProtocolBufferException
      //   1455	1472	334	com/google/tagmanager/protobuf/InvalidProtocolBufferException
      //   1487	1497	334	com/google/tagmanager/protobuf/InvalidProtocolBufferException
      //   1521	1528	334	com/google/tagmanager/protobuf/InvalidProtocolBufferException
      //   1537	1548	334	com/google/tagmanager/protobuf/InvalidProtocolBufferException
      //   1566	1573	334	com/google/tagmanager/protobuf/InvalidProtocolBufferException
      //   1585	1602	334	com/google/tagmanager/protobuf/InvalidProtocolBufferException
      //   1617	1623	334	com/google/tagmanager/protobuf/InvalidProtocolBufferException
      //   1650	1661	334	com/google/tagmanager/protobuf/InvalidProtocolBufferException
      //   1679	1696	334	com/google/tagmanager/protobuf/InvalidProtocolBufferException
      //   1711	1721	334	com/google/tagmanager/protobuf/InvalidProtocolBufferException
      //   1745	1752	334	com/google/tagmanager/protobuf/InvalidProtocolBufferException
      //   1761	1772	334	com/google/tagmanager/protobuf/InvalidProtocolBufferException
      //   1790	1797	334	com/google/tagmanager/protobuf/InvalidProtocolBufferException
      //   1809	1826	334	com/google/tagmanager/protobuf/InvalidProtocolBufferException
      //   1841	1847	334	com/google/tagmanager/protobuf/InvalidProtocolBufferException
      //   1874	1885	334	com/google/tagmanager/protobuf/InvalidProtocolBufferException
      //   1903	1920	334	com/google/tagmanager/protobuf/InvalidProtocolBufferException
      //   1935	1945	334	com/google/tagmanager/protobuf/InvalidProtocolBufferException
      //   1969	1976	334	com/google/tagmanager/protobuf/InvalidProtocolBufferException
      //   1985	1996	334	com/google/tagmanager/protobuf/InvalidProtocolBufferException
      //   2014	2021	334	com/google/tagmanager/protobuf/InvalidProtocolBufferException
      //   2033	2050	334	com/google/tagmanager/protobuf/InvalidProtocolBufferException
      //   2065	2071	334	com/google/tagmanager/protobuf/InvalidProtocolBufferException
      //   2100	2111	334	com/google/tagmanager/protobuf/InvalidProtocolBufferException
      //   2130	2147	334	com/google/tagmanager/protobuf/InvalidProtocolBufferException
      //   2162	2172	334	com/google/tagmanager/protobuf/InvalidProtocolBufferException
      //   2198	2205	334	com/google/tagmanager/protobuf/InvalidProtocolBufferException
      //   2214	2225	334	com/google/tagmanager/protobuf/InvalidProtocolBufferException
      //   2244	2251	334	com/google/tagmanager/protobuf/InvalidProtocolBufferException
      //   2263	2280	334	com/google/tagmanager/protobuf/InvalidProtocolBufferException
      //   2295	2301	334	com/google/tagmanager/protobuf/InvalidProtocolBufferException
      //   2330	2341	334	com/google/tagmanager/protobuf/InvalidProtocolBufferException
      //   2360	2377	334	com/google/tagmanager/protobuf/InvalidProtocolBufferException
      //   2392	2402	334	com/google/tagmanager/protobuf/InvalidProtocolBufferException
      //   2428	2435	334	com/google/tagmanager/protobuf/InvalidProtocolBufferException
      //   2444	2455	334	com/google/tagmanager/protobuf/InvalidProtocolBufferException
      //   2474	2481	334	com/google/tagmanager/protobuf/InvalidProtocolBufferException
      //   2493	2510	334	com/google/tagmanager/protobuf/InvalidProtocolBufferException
      //   2525	2531	334	com/google/tagmanager/protobuf/InvalidProtocolBufferException
      //   2560	2571	334	com/google/tagmanager/protobuf/InvalidProtocolBufferException
      //   2590	2607	334	com/google/tagmanager/protobuf/InvalidProtocolBufferException
      //   2622	2632	334	com/google/tagmanager/protobuf/InvalidProtocolBufferException
      //   2658	2665	334	com/google/tagmanager/protobuf/InvalidProtocolBufferException
      //   2674	2685	334	com/google/tagmanager/protobuf/InvalidProtocolBufferException
      //   2704	2711	334	com/google/tagmanager/protobuf/InvalidProtocolBufferException
      //   2723	2740	334	com/google/tagmanager/protobuf/InvalidProtocolBufferException
      //   2755	2761	334	com/google/tagmanager/protobuf/InvalidProtocolBufferException
      //   49	55	345	finally
      //   245	258	345	finally
      //   283	294	345	finally
      //   311	328	345	finally
      //   339	345	345	finally
      //   585	595	345	finally
      //   617	624	345	finally
      //   633	644	345	finally
      //   661	668	345	finally
      //   680	697	345	finally
      //   705	721	345	finally
      //   733	739	345	finally
      //   764	775	345	finally
      //   792	809	345	finally
      //   824	834	345	finally
      //   856	863	345	finally
      //   872	883	345	finally
      //   900	907	345	finally
      //   919	936	345	finally
      //   951	957	345	finally
      //   982	993	345	finally
      //   1010	1027	345	finally
      //   1042	1052	345	finally
      //   1074	1081	345	finally
      //   1090	1101	345	finally
      //   1118	1125	345	finally
      //   1137	1154	345	finally
      //   1169	1175	345	finally
      //   1202	1213	345	finally
      //   1231	1248	345	finally
      //   1263	1273	345	finally
      //   1297	1304	345	finally
      //   1313	1324	345	finally
      //   1342	1349	345	finally
      //   1361	1378	345	finally
      //   1393	1399	345	finally
      //   1426	1437	345	finally
      //   1455	1472	345	finally
      //   1487	1497	345	finally
      //   1521	1528	345	finally
      //   1537	1548	345	finally
      //   1566	1573	345	finally
      //   1585	1602	345	finally
      //   1617	1623	345	finally
      //   1650	1661	345	finally
      //   1679	1696	345	finally
      //   1711	1721	345	finally
      //   1745	1752	345	finally
      //   1761	1772	345	finally
      //   1790	1797	345	finally
      //   1809	1826	345	finally
      //   1841	1847	345	finally
      //   1874	1885	345	finally
      //   1903	1920	345	finally
      //   1935	1945	345	finally
      //   1969	1976	345	finally
      //   1985	1996	345	finally
      //   2014	2021	345	finally
      //   2033	2050	345	finally
      //   2065	2071	345	finally
      //   2100	2111	345	finally
      //   2130	2147	345	finally
      //   2162	2172	345	finally
      //   2198	2205	345	finally
      //   2214	2225	345	finally
      //   2244	2251	345	finally
      //   2263	2280	345	finally
      //   2295	2301	345	finally
      //   2330	2341	345	finally
      //   2360	2377	345	finally
      //   2392	2402	345	finally
      //   2428	2435	345	finally
      //   2444	2455	345	finally
      //   2474	2481	345	finally
      //   2493	2510	345	finally
      //   2525	2531	345	finally
      //   2560	2571	345	finally
      //   2590	2607	345	finally
      //   2622	2632	345	finally
      //   2658	2665	345	finally
      //   2674	2685	345	finally
      //   2704	2711	345	finally
      //   2723	2740	345	finally
      //   2755	2761	345	finally
      //   49	55	700	java/io/IOException
      //   245	258	700	java/io/IOException
      //   283	294	700	java/io/IOException
      //   311	328	700	java/io/IOException
      //   585	595	700	java/io/IOException
      //   617	624	700	java/io/IOException
      //   633	644	700	java/io/IOException
      //   661	668	700	java/io/IOException
      //   680	697	700	java/io/IOException
      //   733	739	700	java/io/IOException
      //   764	775	700	java/io/IOException
      //   792	809	700	java/io/IOException
      //   824	834	700	java/io/IOException
      //   856	863	700	java/io/IOException
      //   872	883	700	java/io/IOException
      //   900	907	700	java/io/IOException
      //   919	936	700	java/io/IOException
      //   951	957	700	java/io/IOException
      //   982	993	700	java/io/IOException
      //   1010	1027	700	java/io/IOException
      //   1042	1052	700	java/io/IOException
      //   1074	1081	700	java/io/IOException
      //   1090	1101	700	java/io/IOException
      //   1118	1125	700	java/io/IOException
      //   1137	1154	700	java/io/IOException
      //   1169	1175	700	java/io/IOException
      //   1202	1213	700	java/io/IOException
      //   1231	1248	700	java/io/IOException
      //   1263	1273	700	java/io/IOException
      //   1297	1304	700	java/io/IOException
      //   1313	1324	700	java/io/IOException
      //   1342	1349	700	java/io/IOException
      //   1361	1378	700	java/io/IOException
      //   1393	1399	700	java/io/IOException
      //   1426	1437	700	java/io/IOException
      //   1455	1472	700	java/io/IOException
      //   1487	1497	700	java/io/IOException
      //   1521	1528	700	java/io/IOException
      //   1537	1548	700	java/io/IOException
      //   1566	1573	700	java/io/IOException
      //   1585	1602	700	java/io/IOException
      //   1617	1623	700	java/io/IOException
      //   1650	1661	700	java/io/IOException
      //   1679	1696	700	java/io/IOException
      //   1711	1721	700	java/io/IOException
      //   1745	1752	700	java/io/IOException
      //   1761	1772	700	java/io/IOException
      //   1790	1797	700	java/io/IOException
      //   1809	1826	700	java/io/IOException
      //   1841	1847	700	java/io/IOException
      //   1874	1885	700	java/io/IOException
      //   1903	1920	700	java/io/IOException
      //   1935	1945	700	java/io/IOException
      //   1969	1976	700	java/io/IOException
      //   1985	1996	700	java/io/IOException
      //   2014	2021	700	java/io/IOException
      //   2033	2050	700	java/io/IOException
      //   2065	2071	700	java/io/IOException
      //   2100	2111	700	java/io/IOException
      //   2130	2147	700	java/io/IOException
      //   2162	2172	700	java/io/IOException
      //   2198	2205	700	java/io/IOException
      //   2214	2225	700	java/io/IOException
      //   2244	2251	700	java/io/IOException
      //   2263	2280	700	java/io/IOException
      //   2295	2301	700	java/io/IOException
      //   2330	2341	700	java/io/IOException
      //   2360	2377	700	java/io/IOException
      //   2392	2402	700	java/io/IOException
      //   2428	2435	700	java/io/IOException
      //   2444	2455	700	java/io/IOException
      //   2474	2481	700	java/io/IOException
      //   2493	2510	700	java/io/IOException
      //   2525	2531	700	java/io/IOException
      //   2560	2571	700	java/io/IOException
      //   2590	2607	700	java/io/IOException
      //   2622	2632	700	java/io/IOException
      //   2658	2665	700	java/io/IOException
      //   2674	2685	700	java/io/IOException
      //   2704	2711	700	java/io/IOException
      //   2723	2740	700	java/io/IOException
      //   2755	2761	700	java/io/IOException
      //   2967	2972	2986	java/io/IOException
      //   2967	2972	2999	finally
      //   556	561	3011	java/io/IOException
      //   556	561	3024	finally
    }
    
    private Rule(boolean paramBoolean)
    {
      this.unknownFields = e.ajf;
    }
    
    public static a a(Rule paramRule)
    {
      return ia().m(paramRule);
    }
    
    private void fH()
    {
      this.positivePredicate_ = Collections.emptyList();
      this.negativePredicate_ = Collections.emptyList();
      this.addTag_ = Collections.emptyList();
      this.removeTag_ = Collections.emptyList();
      this.addTagRuleName_ = Collections.emptyList();
      this.removeTagRuleName_ = Collections.emptyList();
      this.addMacro_ = Collections.emptyList();
      this.removeMacro_ = Collections.emptyList();
      this.addMacroRuleName_ = Collections.emptyList();
      this.removeMacroRuleName_ = Collections.emptyList();
    }
    
    public static Rule hE()
    {
      return hg;
    }
    
    public static a ia()
    {
      return a.ir();
    }
    
    public void a(CodedOutputStream paramCodedOutputStream)
    {
      int k = 0;
      fI();
      int i = 0;
      while (i < this.positivePredicate_.size())
      {
        paramCodedOutputStream.w(1, ((Integer)this.positivePredicate_.get(i)).intValue());
        i += 1;
      }
      i = 0;
      while (i < this.negativePredicate_.size())
      {
        paramCodedOutputStream.w(2, ((Integer)this.negativePredicate_.get(i)).intValue());
        i += 1;
      }
      i = 0;
      while (i < this.addTag_.size())
      {
        paramCodedOutputStream.w(3, ((Integer)this.addTag_.get(i)).intValue());
        i += 1;
      }
      i = 0;
      while (i < this.removeTag_.size())
      {
        paramCodedOutputStream.w(4, ((Integer)this.removeTag_.get(i)).intValue());
        i += 1;
      }
      i = 0;
      while (i < this.addTagRuleName_.size())
      {
        paramCodedOutputStream.w(5, ((Integer)this.addTagRuleName_.get(i)).intValue());
        i += 1;
      }
      i = 0;
      while (i < this.removeTagRuleName_.size())
      {
        paramCodedOutputStream.w(6, ((Integer)this.removeTagRuleName_.get(i)).intValue());
        i += 1;
      }
      i = 0;
      while (i < this.addMacro_.size())
      {
        paramCodedOutputStream.w(7, ((Integer)this.addMacro_.get(i)).intValue());
        i += 1;
      }
      i = 0;
      while (i < this.removeMacro_.size())
      {
        paramCodedOutputStream.w(8, ((Integer)this.removeMacro_.get(i)).intValue());
        i += 1;
      }
      i = 0;
      int j;
      for (;;)
      {
        j = k;
        if (i >= this.addMacroRuleName_.size()) {
          break;
        }
        paramCodedOutputStream.w(9, ((Integer)this.addMacroRuleName_.get(i)).intValue());
        i += 1;
      }
      while (j < this.removeMacroRuleName_.size())
      {
        paramCodedOutputStream.w(10, ((Integer)this.removeMacroRuleName_.get(j)).intValue());
        j += 1;
      }
      paramCodedOutputStream.d(this.unknownFields);
    }
    
    public boolean equals(Object paramObject)
    {
      if (paramObject == this) {}
      label65:
      label87:
      label109:
      label131:
      label153:
      label175:
      label197:
      label246:
      label251:
      label256:
      label261:
      label266:
      label271:
      label276:
      label281:
      label284:
      for (;;)
      {
        return true;
        if (!(paramObject instanceof Rule)) {
          return super.equals(paramObject);
        }
        paramObject = (Rule)paramObject;
        if (hG().equals(((Rule)paramObject).hG()))
        {
          i = 1;
          if ((i == 0) || (!hI().equals(((Rule)paramObject).hI()))) {
            break label246;
          }
          i = 1;
          if ((i == 0) || (!hK().equals(((Rule)paramObject).hK()))) {
            break label251;
          }
          i = 1;
          if ((i == 0) || (!hM().equals(((Rule)paramObject).hM()))) {
            break label256;
          }
          i = 1;
          if ((i == 0) || (!hO().equals(((Rule)paramObject).hO()))) {
            break label261;
          }
          i = 1;
          if ((i == 0) || (!hQ().equals(((Rule)paramObject).hQ()))) {
            break label266;
          }
          i = 1;
          if ((i == 0) || (!hS().equals(((Rule)paramObject).hS()))) {
            break label271;
          }
          i = 1;
          if ((i == 0) || (!hU().equals(((Rule)paramObject).hU()))) {
            break label276;
          }
          i = 1;
          if ((i == 0) || (!hW().equals(((Rule)paramObject).hW()))) {
            break label281;
          }
        }
        for (int i = 1;; i = 0)
        {
          if ((i != 0) && (hY().equals(((Rule)paramObject).hY()))) {
            break label284;
          }
          return false;
          i = 0;
          break;
          i = 0;
          break label65;
          i = 0;
          break label87;
          i = 0;
          break label109;
          i = 0;
          break label131;
          i = 0;
          break label153;
          i = 0;
          break label175;
          i = 0;
          break label197;
        }
      }
    }
    
    public q<Rule> fA()
    {
      return gW;
    }
    
    public int fI()
    {
      int i6 = 0;
      int i = this.memoizedSerializedSize;
      if (i != -1) {
        return i;
      }
      int j = 0;
      i = 0;
      while (j < this.positivePredicate_.size())
      {
        i += CodedOutputStream.ff(((Integer)this.positivePredicate_.get(j)).intValue());
        j += 1;
      }
      int i7 = hG().size();
      int k = 0;
      j = 0;
      while (k < this.negativePredicate_.size())
      {
        j += CodedOutputStream.ff(((Integer)this.negativePredicate_.get(k)).intValue());
        k += 1;
      }
      int i8 = hI().size();
      int m = 0;
      k = 0;
      while (m < this.addTag_.size())
      {
        k += CodedOutputStream.ff(((Integer)this.addTag_.get(m)).intValue());
        m += 1;
      }
      int i9 = hK().size();
      int n = 0;
      m = 0;
      while (n < this.removeTag_.size())
      {
        m += CodedOutputStream.ff(((Integer)this.removeTag_.get(n)).intValue());
        n += 1;
      }
      int i10 = hM().size();
      int i1 = 0;
      n = 0;
      while (i1 < this.addTagRuleName_.size())
      {
        n += CodedOutputStream.ff(((Integer)this.addTagRuleName_.get(i1)).intValue());
        i1 += 1;
      }
      int i11 = hO().size();
      int i2 = 0;
      i1 = 0;
      while (i2 < this.removeTagRuleName_.size())
      {
        i1 += CodedOutputStream.ff(((Integer)this.removeTagRuleName_.get(i2)).intValue());
        i2 += 1;
      }
      int i12 = hQ().size();
      int i3 = 0;
      i2 = 0;
      while (i3 < this.addMacro_.size())
      {
        i2 += CodedOutputStream.ff(((Integer)this.addMacro_.get(i3)).intValue());
        i3 += 1;
      }
      int i13 = hS().size();
      int i4 = 0;
      i3 = 0;
      while (i4 < this.removeMacro_.size())
      {
        i3 += CodedOutputStream.ff(((Integer)this.removeMacro_.get(i4)).intValue());
        i4 += 1;
      }
      int i14 = hU().size();
      int i5 = 0;
      i4 = 0;
      while (i5 < this.addMacroRuleName_.size())
      {
        i4 += CodedOutputStream.ff(((Integer)this.addMacroRuleName_.get(i5)).intValue());
        i5 += 1;
      }
      int i15 = hW().size();
      int i16;
      for (i5 = 0; i6 < this.removeMacroRuleName_.size(); i5 = i16 + i5)
      {
        i16 = CodedOutputStream.ff(((Integer)this.removeMacroRuleName_.get(i6)).intValue());
        i6 += 1;
      }
      i = 0 + i + i7 * 1 + j + i8 * 1 + k + i9 * 1 + m + i10 * 1 + n + i11 * 1 + i1 + i12 * 1 + i2 + i13 * 1 + i3 + i14 * 1 + i4 + i15 * 1 + i5 + hY().size() * 1 + this.unknownFields.size();
      this.memoizedSerializedSize = i;
      return i;
    }
    
    public Rule hF()
    {
      return hg;
    }
    
    public List<Integer> hG()
    {
      return this.positivePredicate_;
    }
    
    public int hH()
    {
      return this.positivePredicate_.size();
    }
    
    public List<Integer> hI()
    {
      return this.negativePredicate_;
    }
    
    public int hJ()
    {
      return this.negativePredicate_.size();
    }
    
    public List<Integer> hK()
    {
      return this.addTag_;
    }
    
    public int hL()
    {
      return this.addTag_.size();
    }
    
    public List<Integer> hM()
    {
      return this.removeTag_;
    }
    
    public int hN()
    {
      return this.removeTag_.size();
    }
    
    public List<Integer> hO()
    {
      return this.addTagRuleName_;
    }
    
    public int hP()
    {
      return this.addTagRuleName_.size();
    }
    
    public List<Integer> hQ()
    {
      return this.removeTagRuleName_;
    }
    
    public int hR()
    {
      return this.removeTagRuleName_.size();
    }
    
    public List<Integer> hS()
    {
      return this.addMacro_;
    }
    
    public int hT()
    {
      return this.addMacro_.size();
    }
    
    public List<Integer> hU()
    {
      return this.removeMacro_;
    }
    
    public int hV()
    {
      return this.removeMacro_.size();
    }
    
    public List<Integer> hW()
    {
      return this.addMacroRuleName_;
    }
    
    public int hX()
    {
      return this.addMacroRuleName_.size();
    }
    
    public List<Integer> hY()
    {
      return this.removeMacroRuleName_;
    }
    
    public int hZ()
    {
      return this.removeMacroRuleName_.size();
    }
    
    public int hashCode()
    {
      if (this.memoizedHashCode != 0) {
        return this.memoizedHashCode;
      }
      int j = Rule.class.hashCode() + 779;
      int i = j;
      if (hH() > 0) {
        i = (j * 37 + 1) * 53 + hG().hashCode();
      }
      j = i;
      if (hJ() > 0) {
        j = (i * 37 + 2) * 53 + hI().hashCode();
      }
      i = j;
      if (hL() > 0) {
        i = (j * 37 + 3) * 53 + hK().hashCode();
      }
      j = i;
      if (hN() > 0) {
        j = (i * 37 + 4) * 53 + hM().hashCode();
      }
      i = j;
      if (hP() > 0) {
        i = (j * 37 + 5) * 53 + hO().hashCode();
      }
      j = i;
      if (hR() > 0) {
        j = (i * 37 + 6) * 53 + hQ().hashCode();
      }
      i = j;
      if (hT() > 0) {
        i = (j * 37 + 7) * 53 + hS().hashCode();
      }
      j = i;
      if (hV() > 0) {
        j = (i * 37 + 8) * 53 + hU().hashCode();
      }
      i = j;
      if (hX() > 0) {
        i = (j * 37 + 9) * 53 + hW().hashCode();
      }
      j = i;
      if (hZ() > 0) {
        j = (i * 37 + 10) * 53 + hY().hashCode();
      }
      i = j * 29 + this.unknownFields.hashCode();
      this.memoizedHashCode = i;
      return i;
    }
    
    public a ib()
    {
      return ia();
    }
    
    public a ic()
    {
      return a(this);
    }
    
    public final boolean isInitialized()
    {
      int i = this.memoizedIsInitialized;
      if (i != -1) {
        return i == 1;
      }
      this.memoizedIsInitialized = 1;
      return true;
    }
    
    protected Object writeReplace()
    {
      return super.writeReplace();
    }
    
    public static final class a
      extends GeneratedMessageLite.a<Serving.Rule, a>
      implements Serving.e
    {
      private List<Integer> addMacroRuleName_ = Collections.emptyList();
      private List<Integer> addMacro_ = Collections.emptyList();
      private List<Integer> addTagRuleName_ = Collections.emptyList();
      private List<Integer> addTag_ = Collections.emptyList();
      private int bitField0_;
      private List<Integer> negativePredicate_ = Collections.emptyList();
      private List<Integer> positivePredicate_ = Collections.emptyList();
      private List<Integer> removeMacroRuleName_ = Collections.emptyList();
      private List<Integer> removeMacro_ = Collections.emptyList();
      private List<Integer> removeTagRuleName_ = Collections.emptyList();
      private List<Integer> removeTag_ = Collections.emptyList();
      
      private a()
      {
        fP();
      }
      
      private void fP() {}
      
      private static a id()
      {
        return new a();
      }
      
      private void ih()
      {
        if ((this.bitField0_ & 0x1) != 1)
        {
          this.positivePredicate_ = new ArrayList(this.positivePredicate_);
          this.bitField0_ |= 0x1;
        }
      }
      
      private void ii()
      {
        if ((this.bitField0_ & 0x2) != 2)
        {
          this.negativePredicate_ = new ArrayList(this.negativePredicate_);
          this.bitField0_ |= 0x2;
        }
      }
      
      private void ij()
      {
        if ((this.bitField0_ & 0x4) != 4)
        {
          this.addTag_ = new ArrayList(this.addTag_);
          this.bitField0_ |= 0x4;
        }
      }
      
      private void ik()
      {
        if ((this.bitField0_ & 0x8) != 8)
        {
          this.removeTag_ = new ArrayList(this.removeTag_);
          this.bitField0_ |= 0x8;
        }
      }
      
      private void il()
      {
        if ((this.bitField0_ & 0x10) != 16)
        {
          this.addTagRuleName_ = new ArrayList(this.addTagRuleName_);
          this.bitField0_ |= 0x10;
        }
      }
      
      private void im()
      {
        if ((this.bitField0_ & 0x20) != 32)
        {
          this.removeTagRuleName_ = new ArrayList(this.removeTagRuleName_);
          this.bitField0_ |= 0x20;
        }
      }
      
      private void in()
      {
        if ((this.bitField0_ & 0x40) != 64)
        {
          this.addMacro_ = new ArrayList(this.addMacro_);
          this.bitField0_ |= 0x40;
        }
      }
      
      private void io()
      {
        if ((this.bitField0_ & 0x80) != 128)
        {
          this.removeMacro_ = new ArrayList(this.removeMacro_);
          this.bitField0_ |= 0x80;
        }
      }
      
      private void ip()
      {
        if ((this.bitField0_ & 0x100) != 256)
        {
          this.addMacroRuleName_ = new ArrayList(this.addMacroRuleName_);
          this.bitField0_ |= 0x100;
        }
      }
      
      private void iq()
      {
        if ((this.bitField0_ & 0x200) != 512)
        {
          this.removeMacroRuleName_ = new ArrayList(this.removeMacroRuleName_);
          this.bitField0_ |= 0x200;
        }
      }
      
      public Serving.Rule hF()
      {
        return Serving.Rule.hE();
      }
      
      public a ie()
      {
        return id().m(ig());
      }
      
      public Serving.Rule jdMethod_if()
      {
        Serving.Rule localRule = ig();
        if (!localRule.isInitialized()) {
          throw a(localRule);
        }
        return localRule;
      }
      
      public Serving.Rule ig()
      {
        Serving.Rule localRule = new Serving.Rule(this, null);
        int i = this.bitField0_;
        if ((this.bitField0_ & 0x1) == 1)
        {
          this.positivePredicate_ = Collections.unmodifiableList(this.positivePredicate_);
          this.bitField0_ &= 0xFFFFFFFE;
        }
        Serving.Rule.a(localRule, this.positivePredicate_);
        if ((this.bitField0_ & 0x2) == 2)
        {
          this.negativePredicate_ = Collections.unmodifiableList(this.negativePredicate_);
          this.bitField0_ &= 0xFFFFFFFD;
        }
        Serving.Rule.b(localRule, this.negativePredicate_);
        if ((this.bitField0_ & 0x4) == 4)
        {
          this.addTag_ = Collections.unmodifiableList(this.addTag_);
          this.bitField0_ &= 0xFFFFFFFB;
        }
        Serving.Rule.c(localRule, this.addTag_);
        if ((this.bitField0_ & 0x8) == 8)
        {
          this.removeTag_ = Collections.unmodifiableList(this.removeTag_);
          this.bitField0_ &= 0xFFFFFFF7;
        }
        Serving.Rule.d(localRule, this.removeTag_);
        if ((this.bitField0_ & 0x10) == 16)
        {
          this.addTagRuleName_ = Collections.unmodifiableList(this.addTagRuleName_);
          this.bitField0_ &= 0xFFFFFFEF;
        }
        Serving.Rule.e(localRule, this.addTagRuleName_);
        if ((this.bitField0_ & 0x20) == 32)
        {
          this.removeTagRuleName_ = Collections.unmodifiableList(this.removeTagRuleName_);
          this.bitField0_ &= 0xFFFFFFDF;
        }
        Serving.Rule.f(localRule, this.removeTagRuleName_);
        if ((this.bitField0_ & 0x40) == 64)
        {
          this.addMacro_ = Collections.unmodifiableList(this.addMacro_);
          this.bitField0_ &= 0xFFFFFFBF;
        }
        Serving.Rule.g(localRule, this.addMacro_);
        if ((this.bitField0_ & 0x80) == 128)
        {
          this.removeMacro_ = Collections.unmodifiableList(this.removeMacro_);
          this.bitField0_ &= 0xFF7F;
        }
        Serving.Rule.h(localRule, this.removeMacro_);
        if ((this.bitField0_ & 0x100) == 256)
        {
          this.addMacroRuleName_ = Collections.unmodifiableList(this.addMacroRuleName_);
          this.bitField0_ &= 0xFEFF;
        }
        Serving.Rule.i(localRule, this.addMacroRuleName_);
        if ((this.bitField0_ & 0x200) == 512)
        {
          this.removeMacroRuleName_ = Collections.unmodifiableList(this.removeMacroRuleName_);
          this.bitField0_ &= 0xFDFF;
        }
        Serving.Rule.j(localRule, this.removeMacroRuleName_);
        return localRule;
      }
      
      public final boolean isInitialized()
      {
        return true;
      }
      
      public a m(Serving.Rule paramRule)
      {
        if (paramRule == Serving.Rule.hE()) {
          return this;
        }
        if (!Serving.Rule.b(paramRule).isEmpty())
        {
          if (this.positivePredicate_.isEmpty())
          {
            this.positivePredicate_ = Serving.Rule.b(paramRule);
            this.bitField0_ &= 0xFFFFFFFE;
          }
        }
        else
        {
          if (!Serving.Rule.c(paramRule).isEmpty())
          {
            if (!this.negativePredicate_.isEmpty()) {
              break label481;
            }
            this.negativePredicate_ = Serving.Rule.c(paramRule);
            this.bitField0_ &= 0xFFFFFFFD;
          }
          label95:
          if (!Serving.Rule.d(paramRule).isEmpty())
          {
            if (!this.addTag_.isEmpty()) {
              break label502;
            }
            this.addTag_ = Serving.Rule.d(paramRule);
            this.bitField0_ &= 0xFFFFFFFB;
          }
          label138:
          if (!Serving.Rule.e(paramRule).isEmpty())
          {
            if (!this.removeTag_.isEmpty()) {
              break label523;
            }
            this.removeTag_ = Serving.Rule.e(paramRule);
            this.bitField0_ &= 0xFFFFFFF7;
          }
          label181:
          if (!Serving.Rule.f(paramRule).isEmpty())
          {
            if (!this.addTagRuleName_.isEmpty()) {
              break label544;
            }
            this.addTagRuleName_ = Serving.Rule.f(paramRule);
            this.bitField0_ &= 0xFFFFFFEF;
          }
          label224:
          if (!Serving.Rule.g(paramRule).isEmpty())
          {
            if (!this.removeTagRuleName_.isEmpty()) {
              break label565;
            }
            this.removeTagRuleName_ = Serving.Rule.g(paramRule);
            this.bitField0_ &= 0xFFFFFFDF;
          }
          label267:
          if (!Serving.Rule.h(paramRule).isEmpty())
          {
            if (!this.addMacro_.isEmpty()) {
              break label586;
            }
            this.addMacro_ = Serving.Rule.h(paramRule);
            this.bitField0_ &= 0xFFFFFFBF;
          }
          label310:
          if (!Serving.Rule.i(paramRule).isEmpty())
          {
            if (!this.removeMacro_.isEmpty()) {
              break label607;
            }
            this.removeMacro_ = Serving.Rule.i(paramRule);
            this.bitField0_ &= 0xFF7F;
          }
          label354:
          if (!Serving.Rule.j(paramRule).isEmpty())
          {
            if (!this.addMacroRuleName_.isEmpty()) {
              break label628;
            }
            this.addMacroRuleName_ = Serving.Rule.j(paramRule);
            this.bitField0_ &= 0xFEFF;
          }
          label398:
          if (!Serving.Rule.k(paramRule).isEmpty())
          {
            if (!this.removeMacroRuleName_.isEmpty()) {
              break label649;
            }
            this.removeMacroRuleName_ = Serving.Rule.k(paramRule);
            this.bitField0_ &= 0xFDFF;
          }
        }
        for (;;)
        {
          e(BE().a(Serving.Rule.l(paramRule)));
          return this;
          ih();
          this.positivePredicate_.addAll(Serving.Rule.b(paramRule));
          break;
          label481:
          ii();
          this.negativePredicate_.addAll(Serving.Rule.c(paramRule));
          break label95;
          label502:
          ij();
          this.addTag_.addAll(Serving.Rule.d(paramRule));
          break label138;
          label523:
          ik();
          this.removeTag_.addAll(Serving.Rule.e(paramRule));
          break label181;
          label544:
          il();
          this.addTagRuleName_.addAll(Serving.Rule.f(paramRule));
          break label224;
          label565:
          im();
          this.removeTagRuleName_.addAll(Serving.Rule.g(paramRule));
          break label267;
          label586:
          in();
          this.addMacro_.addAll(Serving.Rule.h(paramRule));
          break label310;
          label607:
          io();
          this.removeMacro_.addAll(Serving.Rule.i(paramRule));
          break label354;
          label628:
          ip();
          this.addMacroRuleName_.addAll(Serving.Rule.j(paramRule));
          break label398;
          label649:
          iq();
          this.removeMacroRuleName_.addAll(Serving.Rule.k(paramRule));
        }
      }
      
      /* Error */
      public a m(f paramf, g paramg)
      {
        // Byte code:
        //   0: getstatic 239	com/google/analytics/containertag/proto/Serving$Rule:gW	Lcom/google/tagmanager/protobuf/q;
        //   3: aload_1
        //   4: aload_2
        //   5: invokeinterface 244 3 0
        //   10: checkcast 9	com/google/analytics/containertag/proto/Serving$Rule
        //   13: astore_1
        //   14: aload_1
        //   15: ifnull +9 -> 24
        //   18: aload_0
        //   19: aload_1
        //   20: invokevirtual 89	com/google/analytics/containertag/proto/Serving$Rule$a:m	(Lcom/google/analytics/containertag/proto/Serving$Rule;)Lcom/google/analytics/containertag/proto/Serving$Rule$a;
        //   23: pop
        //   24: aload_0
        //   25: areturn
        //   26: astore_2
        //   27: aload_2
        //   28: invokevirtual 247	com/google/tagmanager/protobuf/InvalidProtocolBufferException:BN	()Lcom/google/tagmanager/protobuf/n;
        //   31: checkcast 9	com/google/analytics/containertag/proto/Serving$Rule
        //   34: astore_1
        //   35: aload_2
        //   36: athrow
        //   37: astore_2
        //   38: aload_1
        //   39: ifnull +9 -> 48
        //   42: aload_0
        //   43: aload_1
        //   44: invokevirtual 89	com/google/analytics/containertag/proto/Serving$Rule$a:m	(Lcom/google/analytics/containertag/proto/Serving$Rule;)Lcom/google/analytics/containertag/proto/Serving$Rule$a;
        //   47: pop
        //   48: aload_2
        //   49: athrow
        //   50: astore_2
        //   51: aconst_null
        //   52: astore_1
        //   53: goto -15 -> 38
        // Local variable table:
        //   start	length	slot	name	signature
        //   0	56	0	this	a
        //   0	56	1	paramf	f
        //   0	56	2	paramg	g
        // Exception table:
        //   from	to	target	type
        //   0	14	26	com/google/tagmanager/protobuf/InvalidProtocolBufferException
        //   35	37	37	finally
        //   0	14	50	finally
        //   27	35	50	finally
      }
    }
  }
  
  public static abstract interface a
    extends o
  {}
  
  public static abstract interface b
    extends o
  {}
  
  public static abstract interface c
    extends o
  {}
  
  public static abstract interface d
    extends o
  {}
  
  public static abstract interface e
    extends o
  {}
}


/* Location:              /Users/amaurremi/uw/stringoid/static-dynamic-comparison/apps/quick pdf scanner/com.mobisystems.mobiscanner-213-dex2jar.jar!/com/google/analytics/containertag/proto/Serving.class
 * Java compiler version: 6 (50.0)
 * JD-Core Version:       0.7.1
 */