package com.mobileapptracker;

public class d
        implements Runnable {
    protected d(b paramb) {
    }

    /* Error */
    public void run() {
        // Byte code:
        //   0: aload_0
        //   1: getfield 12	com/mobileapptracker/d:a	Lcom/mobileapptracker/b;
        //   4: invokevirtual 26	com/mobileapptracker/b:a	()I
        //   7: istore 4
        //   9: iload 4
        //   11: ifne +4 -> 15
        //   14: return
        //   15: aload_0
        //   16: getfield 12	com/mobileapptracker/d:a	Lcom/mobileapptracker/b;
        //   19: invokestatic 29	com/mobileapptracker/b:a	(Lcom/mobileapptracker/b;)Ljava/util/concurrent/Semaphore;
        //   22: invokevirtual 34	java/util/concurrent/Semaphore:acquire	()V
        //   25: iload 4
        //   27: bipush 50
        //   29: if_icmple +521 -> 550
        //   32: iload 4
        //   34: bipush 50
        //   36: isub
        //   37: iconst_1
        //   38: iadd
        //   39: istore_3
        //   40: iload_3
        //   41: iload 4
        //   43: if_icmple +14 -> 57
        //   46: aload_0
        //   47: getfield 12	com/mobileapptracker/d:a	Lcom/mobileapptracker/b;
        //   50: invokestatic 29	com/mobileapptracker/b:a	(Lcom/mobileapptracker/b;)Ljava/util/concurrent/Semaphore;
        //   53: invokevirtual 37	java/util/concurrent/Semaphore:release	()V
        //   56: return
        //   57: iload_3
        //   58: invokestatic 43	java/lang/Integer:toString	(I)Ljava/lang/String;
        //   61: astore 18
        //   63: aload_0
        //   64: getfield 12	com/mobileapptracker/d:a	Lcom/mobileapptracker/b;
        //   67: invokestatic 47	com/mobileapptracker/b:b	(Lcom/mobileapptracker/b;)Landroid/content/SharedPreferences;
        //   70: aload 18
        //   72: aconst_null
        //   73: invokeinterface 53 3 0
        //   78: astore 19
        //   80: aload 19
        //   82: ifnull +428 -> 510
        //   85: aconst_null
        //   86: astore 9
        //   88: aconst_null
        //   89: astore 10
        //   91: aconst_null
        //   92: astore 11
        //   94: aconst_null
        //   95: astore 12
        //   97: aconst_null
        //   98: astore 13
        //   100: aconst_null
        //   101: astore 14
        //   103: aconst_null
        //   104: astore 15
        //   106: aconst_null
        //   107: astore 16
        //   109: aconst_null
        //   110: astore 17
        //   112: new 55	org/json/JSONObject
        //   115: dup
        //   116: aload 19
        //   118: invokespecial 58	org/json/JSONObject:<init>	(Ljava/lang/String;)V
        //   121: astore 22
        //   123: aload 22
        //   125: ldc 60
        //   127: invokevirtual 63	org/json/JSONObject:getString	(Ljava/lang/String;)Ljava/lang/String;
        //   130: astore 19
        //   132: aload 22
        //   134: ldc 65
        //   136: invokevirtual 69	org/json/JSONObject:has	(Ljava/lang/String;)Z
        //   139: ifeq +12 -> 151
        //   142: aload 22
        //   144: ldc 65
        //   146: invokevirtual 63	org/json/JSONObject:getString	(Ljava/lang/String;)Ljava/lang/String;
        //   149: astore 9
        //   151: aload 22
        //   153: ldc 71
        //   155: invokevirtual 63	org/json/JSONObject:getString	(Ljava/lang/String;)Ljava/lang/String;
        //   158: astore 20
        //   160: aload 22
        //   162: ldc 73
        //   164: invokevirtual 77	org/json/JSONObject:getDouble	(Ljava/lang/String;)D
        //   167: dstore_1
        //   168: aload 22
        //   170: ldc 79
        //   172: invokevirtual 63	org/json/JSONObject:getString	(Ljava/lang/String;)Ljava/lang/String;
        //   175: astore 21
        //   177: aload 22
        //   179: ldc 81
        //   181: invokevirtual 69	org/json/JSONObject:has	(Ljava/lang/String;)Z
        //   184: ifeq +12 -> 196
        //   187: aload 22
        //   189: ldc 81
        //   191: invokevirtual 63	org/json/JSONObject:getString	(Ljava/lang/String;)Ljava/lang/String;
        //   194: astore 10
        //   196: aload 22
        //   198: ldc 83
        //   200: invokevirtual 69	org/json/JSONObject:has	(Ljava/lang/String;)Z
        //   203: ifeq +12 -> 215
        //   206: aload 22
        //   208: ldc 83
        //   210: invokevirtual 63	org/json/JSONObject:getString	(Ljava/lang/String;)Ljava/lang/String;
        //   213: astore 11
        //   215: aload 22
        //   217: ldc 85
        //   219: invokevirtual 69	org/json/JSONObject:has	(Ljava/lang/String;)Z
        //   222: ifeq +12 -> 234
        //   225: aload 22
        //   227: ldc 85
        //   229: invokevirtual 63	org/json/JSONObject:getString	(Ljava/lang/String;)Ljava/lang/String;
        //   232: astore 12
        //   234: aload 22
        //   236: ldc 87
        //   238: invokevirtual 69	org/json/JSONObject:has	(Ljava/lang/String;)Z
        //   241: ifeq +12 -> 253
        //   244: aload 22
        //   246: ldc 87
        //   248: invokevirtual 63	org/json/JSONObject:getString	(Ljava/lang/String;)Ljava/lang/String;
        //   251: astore 13
        //   253: aload 22
        //   255: ldc 89
        //   257: invokevirtual 69	org/json/JSONObject:has	(Ljava/lang/String;)Z
        //   260: ifeq +12 -> 272
        //   263: aload 22
        //   265: ldc 89
        //   267: invokevirtual 63	org/json/JSONObject:getString	(Ljava/lang/String;)Ljava/lang/String;
        //   270: astore 14
        //   272: aload 22
        //   274: ldc 91
        //   276: invokevirtual 69	org/json/JSONObject:has	(Ljava/lang/String;)Z
        //   279: ifeq +12 -> 291
        //   282: aload 22
        //   284: ldc 91
        //   286: invokevirtual 63	org/json/JSONObject:getString	(Ljava/lang/String;)Ljava/lang/String;
        //   289: astore 15
        //   291: aload 22
        //   293: ldc 93
        //   295: invokevirtual 69	org/json/JSONObject:has	(Ljava/lang/String;)Z
        //   298: ifeq +12 -> 310
        //   301: aload 22
        //   303: ldc 93
        //   305: invokevirtual 63	org/json/JSONObject:getString	(Ljava/lang/String;)Ljava/lang/String;
        //   308: astore 16
        //   310: aload 22
        //   312: ldc 95
        //   314: invokevirtual 69	org/json/JSONObject:has	(Ljava/lang/String;)Z
        //   317: ifeq +12 -> 329
        //   320: aload 22
        //   322: ldc 95
        //   324: invokevirtual 63	org/json/JSONObject:getString	(Ljava/lang/String;)Ljava/lang/String;
        //   327: astore 17
        //   329: aload 22
        //   331: ldc 97
        //   333: invokevirtual 100	org/json/JSONObject:getBoolean	(Ljava/lang/String;)Z
        //   336: istore 5
        //   338: aload 22
        //   340: ldc 102
        //   342: invokevirtual 106	org/json/JSONObject:getLong	(Ljava/lang/String;)J
        //   345: lstore 7
        //   347: new 108	java/util/Date
        //   350: dup
        //   351: lload 7
        //   353: invokespecial 111	java/util/Date:<init>	(J)V
        //   356: astore 22
        //   358: new 108	java/util/Date
        //   361: dup
        //   362: invokespecial 112	java/util/Date:<init>	()V
        //   365: astore 23
        //   367: aload 22
        //   369: aload 23
        //   371: invokevirtual 116	java/util/Date:after	(Ljava/util/Date;)Z
        //   374: istore 6
        //   376: iload 6
        //   378: ifeq +17 -> 395
        //   381: aload 22
        //   383: invokevirtual 120	java/util/Date:getTime	()J
        //   386: aload 23
        //   388: invokevirtual 120	java/util/Date:getTime	()J
        //   391: lsub
        //   392: invokestatic 125	java/lang/Thread:sleep	(J)V
        //   395: aload_0
        //   396: getfield 12	com/mobileapptracker/d:a	Lcom/mobileapptracker/b;
        //   399: aload 18
        //   401: invokevirtual 127	com/mobileapptracker/b:a	(Ljava/lang/String;)V
        //   404: aload_0
        //   405: getfield 12	com/mobileapptracker/d:a	Lcom/mobileapptracker/b;
        //   408: invokestatic 131	com/mobileapptracker/b:c	(Lcom/mobileapptracker/b;)Lcom/mobileapptracker/g;
        //   411: ifnull +70 -> 481
        //   414: aload_0
        //   415: getfield 12	com/mobileapptracker/d:a	Lcom/mobileapptracker/b;
        //   418: invokestatic 131	com/mobileapptracker/b:c	(Lcom/mobileapptracker/b;)Lcom/mobileapptracker/g;
        //   421: aload 19
        //   423: aload 9
        //   425: aload 20
        //   427: dload_1
        //   428: aload 21
        //   430: aload 10
        //   432: aload 11
        //   434: aload 12
        //   436: aload 13
        //   438: aload 14
        //   440: aload 15
        //   442: aload 16
        //   444: aload 17
        //   446: iload 5
        //   448: invokevirtual 136	com/mobileapptracker/g:a	(Ljava/lang/String;Ljava/lang/String;Ljava/lang/String;DLjava/lang/String;Ljava/lang/String;Ljava/lang/String;Ljava/lang/String;Ljava/lang/String;Ljava/lang/String;Ljava/lang/String;Ljava/lang/String;Ljava/lang/String;Z)V
        //   451: goto +104 -> 555
        //   454: astore 9
        //   456: aload 9
        //   458: invokevirtual 139	org/json/JSONException:printStackTrace	()V
        //   461: aload_0
        //   462: getfield 12	com/mobileapptracker/d:a	Lcom/mobileapptracker/b;
        //   465: aload 18
        //   467: invokevirtual 127	com/mobileapptracker/b:a	(Ljava/lang/String;)V
        //   470: aload_0
        //   471: getfield 12	com/mobileapptracker/d:a	Lcom/mobileapptracker/b;
        //   474: invokestatic 29	com/mobileapptracker/b:a	(Lcom/mobileapptracker/b;)Ljava/util/concurrent/Semaphore;
        //   477: invokevirtual 37	java/util/concurrent/Semaphore:release	()V
        //   480: return
        //   481: ldc -115
        //   483: ldc -113
        //   485: invokestatic 149	android/util/Log:d	(Ljava/lang/String;Ljava/lang/String;)I
        //   488: pop
        //   489: goto +66 -> 555
        //   492: astore 9
        //   494: aload 9
        //   496: invokevirtual 150	java/lang/InterruptedException:printStackTrace	()V
        //   499: aload_0
        //   500: getfield 12	com/mobileapptracker/d:a	Lcom/mobileapptracker/b;
        //   503: invokestatic 29	com/mobileapptracker/b:a	(Lcom/mobileapptracker/b;)Ljava/util/concurrent/Semaphore;
        //   506: invokevirtual 37	java/util/concurrent/Semaphore:release	()V
        //   509: return
        //   510: ldc -115
        //   512: ldc -104
        //   514: invokestatic 149	android/util/Log:d	(Ljava/lang/String;Ljava/lang/String;)I
        //   517: pop
        //   518: aload_0
        //   519: getfield 12	com/mobileapptracker/d:a	Lcom/mobileapptracker/b;
        //   522: aload 18
        //   524: invokevirtual 127	com/mobileapptracker/b:a	(Ljava/lang/String;)V
        //   527: goto +28 -> 555
        //   530: astore 9
        //   532: aload_0
        //   533: getfield 12	com/mobileapptracker/d:a	Lcom/mobileapptracker/b;
        //   536: invokestatic 29	com/mobileapptracker/b:a	(Lcom/mobileapptracker/b;)Ljava/util/concurrent/Semaphore;
        //   539: invokevirtual 37	java/util/concurrent/Semaphore:release	()V
        //   542: aload 9
        //   544: athrow
        //   545: astore 22
        //   547: goto -152 -> 395
        //   550: iconst_1
        //   551: istore_3
        //   552: goto -512 -> 40
        //   555: iload_3
        //   556: iconst_1
        //   557: iadd
        //   558: istore_3
        //   559: goto -519 -> 40
        // Local variable table:
        //   start	length	slot	name	signature
        //   0	562	0	this	d
        //   167	261	1	d	double
        //   39	520	3	i	int
        //   7	37	4	j	int
        //   336	111	5	bool1	boolean
        //   374	3	6	bool2	boolean
        //   345	7	7	l	long
        //   86	338	9	str1	String
        //   454	3	9	localJSONException	org.json.JSONException
        //   492	3	9	localInterruptedException1	InterruptedException
        //   530	13	9	localObject1	Object
        //   89	342	10	str2	String
        //   92	341	11	str3	String
        //   95	340	12	str4	String
        //   98	339	13	str5	String
        //   101	338	14	str6	String
        //   104	337	15	str7	String
        //   107	336	16	str8	String
        //   110	335	17	str9	String
        //   61	462	18	str10	String
        //   78	344	19	str11	String
        //   158	268	20	str12	String
        //   175	254	21	str13	String
        //   121	261	22	localObject2	Object
        //   545	1	22	localInterruptedException2	InterruptedException
        //   365	22	23	localDate	java.util.Date
        // Exception table:
        //   from	to	target	type
        //   112	132	454	org/json/JSONException
        //   132	151	454	org/json/JSONException
        //   151	177	454	org/json/JSONException
        //   177	196	454	org/json/JSONException
        //   196	215	454	org/json/JSONException
        //   215	234	454	org/json/JSONException
        //   234	253	454	org/json/JSONException
        //   253	272	454	org/json/JSONException
        //   272	291	454	org/json/JSONException
        //   291	310	454	org/json/JSONException
        //   310	329	454	org/json/JSONException
        //   329	347	454	org/json/JSONException
        //   15	25	492	java/lang/InterruptedException
        //   57	80	492	java/lang/InterruptedException
        //   112	132	492	java/lang/InterruptedException
        //   132	151	492	java/lang/InterruptedException
        //   151	177	492	java/lang/InterruptedException
        //   177	196	492	java/lang/InterruptedException
        //   196	215	492	java/lang/InterruptedException
        //   215	234	492	java/lang/InterruptedException
        //   234	253	492	java/lang/InterruptedException
        //   253	272	492	java/lang/InterruptedException
        //   272	291	492	java/lang/InterruptedException
        //   291	310	492	java/lang/InterruptedException
        //   310	329	492	java/lang/InterruptedException
        //   329	347	492	java/lang/InterruptedException
        //   347	376	492	java/lang/InterruptedException
        //   395	451	492	java/lang/InterruptedException
        //   456	470	492	java/lang/InterruptedException
        //   481	489	492	java/lang/InterruptedException
        //   510	527	492	java/lang/InterruptedException
        //   15	25	530	finally
        //   57	80	530	finally
        //   112	132	530	finally
        //   132	151	530	finally
        //   151	177	530	finally
        //   177	196	530	finally
        //   196	215	530	finally
        //   215	234	530	finally
        //   234	253	530	finally
        //   253	272	530	finally
        //   272	291	530	finally
        //   291	310	530	finally
        //   310	329	530	finally
        //   329	347	530	finally
        //   347	376	530	finally
        //   381	395	530	finally
        //   395	451	530	finally
        //   456	470	530	finally
        //   481	489	530	finally
        //   494	499	530	finally
        //   510	527	530	finally
        //   381	395	545	java/lang/InterruptedException
    }
}


/* Location:              /Users/amaurremi/uw/stringoid stuff/static vs dynamic/ifunny/mobi.ifunny-2447-dex2jar.jar!/com/mobileapptracker/d.class
 * Java compiler version: 6 (50.0)
 * JD-Core Version:       0.7.1
 */