package com.gtp.go.weather.sharephoto.c;

import android.content.Context;
import com.gau.go.launcherex.gowidget.weather.service.a.a;
import com.gtp.go.weather.sharephoto.b.e;
import com.gtp.go.weather.sharephoto.b.l;
import com.jiubang.goweather.b.f;

public class n
  extends a
{
  private e a;
  private Context b;
  private f c;
  private l d;
  
  public n(Context paramContext, e parame)
  {
    this.b = paramContext.getApplicationContext();
    this.a = parame;
  }
  
  /* Error */
  public void a()
  {
    // Byte code:
    //   0: aload_0
    //   1: getfield 27	com/gtp/go/weather/sharephoto/c/n:a	Lcom/gtp/go/weather/sharephoto/b/e;
    //   4: invokevirtual 38	com/gtp/go/weather/sharephoto/b/e:l	()Z
    //   7: ifne +4 -> 11
    //   10: return
    //   11: aload_0
    //   12: getfield 27	com/gtp/go/weather/sharephoto/c/n:a	Lcom/gtp/go/weather/sharephoto/b/e;
    //   15: invokevirtual 41	com/gtp/go/weather/sharephoto/b/e:e	()Z
    //   18: ifeq +13 -> 31
    //   21: aload_0
    //   22: getfield 27	com/gtp/go/weather/sharephoto/c/n:a	Lcom/gtp/go/weather/sharephoto/b/e;
    //   25: invokevirtual 44	com/gtp/go/weather/sharephoto/b/e:m	()Z
    //   28: ifeq -18 -> 10
    //   31: new 46	java/io/File
    //   34: dup
    //   35: aload_0
    //   36: getfield 27	com/gtp/go/weather/sharephoto/c/n:a	Lcom/gtp/go/weather/sharephoto/b/e;
    //   39: invokevirtual 50	com/gtp/go/weather/sharephoto/b/e:g	()Ljava/lang/String;
    //   42: invokespecial 53	java/io/File:<init>	(Ljava/lang/String;)V
    //   45: astore 13
    //   47: aload_0
    //   48: getfield 27	com/gtp/go/weather/sharephoto/c/n:a	Lcom/gtp/go/weather/sharephoto/b/e;
    //   51: invokevirtual 41	com/gtp/go/weather/sharephoto/b/e:e	()Z
    //   54: ifeq +1933 -> 1987
    //   57: new 46	java/io/File
    //   60: dup
    //   61: aload_0
    //   62: getfield 27	com/gtp/go/weather/sharephoto/c/n:a	Lcom/gtp/go/weather/sharephoto/b/e;
    //   65: invokevirtual 56	com/gtp/go/weather/sharephoto/b/e:h	()Ljava/lang/String;
    //   68: invokespecial 53	java/io/File:<init>	(Ljava/lang/String;)V
    //   71: astore 10
    //   73: aload_0
    //   74: new 58	com/jiubang/goweather/b/f
    //   77: dup
    //   78: invokespecial 59	com/jiubang/goweather/b/f:<init>	()V
    //   81: putfield 61	com/gtp/go/weather/sharephoto/c/n:c	Lcom/jiubang/goweather/b/f;
    //   84: invokestatic 66	com/gtp/a/a/a/a:a	()Lcom/gtp/a/a/a/a;
    //   87: new 68	java/lang/StringBuilder
    //   90: dup
    //   91: invokespecial 69	java/lang/StringBuilder:<init>	()V
    //   94: ldc 71
    //   96: invokevirtual 75	java/lang/StringBuilder:append	(Ljava/lang/String;)Ljava/lang/StringBuilder;
    //   99: aload_0
    //   100: getfield 27	com/gtp/go/weather/sharephoto/c/n:a	Lcom/gtp/go/weather/sharephoto/b/e;
    //   103: invokevirtual 79	com/gtp/go/weather/sharephoto/b/e:f	()J
    //   106: invokevirtual 82	java/lang/StringBuilder:append	(J)Ljava/lang/StringBuilder;
    //   109: ldc 84
    //   111: invokevirtual 75	java/lang/StringBuilder:append	(Ljava/lang/String;)Ljava/lang/StringBuilder;
    //   114: invokevirtual 87	java/lang/StringBuilder:toString	()Ljava/lang/String;
    //   117: ldc 89
    //   119: invokevirtual 92	com/gtp/a/a/a/a:a	(Ljava/lang/String;Ljava/lang/String;)V
    //   122: new 94	com/jiubang/goweather/b/e
    //   125: dup
    //   126: ldc 96
    //   128: invokespecial 97	com/jiubang/goweather/b/e:<init>	(Ljava/lang/String;)V
    //   131: astore 11
    //   133: aload 11
    //   135: ldc 99
    //   137: invokestatic 103	com/gau/go/launcherex/gowidget/statistics/y:c	()Ljava/lang/String;
    //   140: invokevirtual 106	com/jiubang/goweather/b/e:a	(Ljava/lang/String;Ljava/lang/String;)Lcom/jiubang/goweather/b/a;
    //   143: pop
    //   144: aload 11
    //   146: ldc 108
    //   148: invokevirtual 110	com/jiubang/goweather/b/e:a	(Ljava/lang/String;)V
    //   151: aload_0
    //   152: getfield 25	com/gtp/go/weather/sharephoto/c/n:b	Landroid/content/Context;
    //   155: invokestatic 115	com/gtp/go/weather/sharephoto/a/f:a	(Landroid/content/Context;)Lorg/json/JSONObject;
    //   158: astore 8
    //   160: aload 8
    //   162: ifnull -152 -> 10
    //   165: aload 8
    //   167: invokevirtual 118	org/json/JSONObject:toString	()Ljava/lang/String;
    //   170: astore 12
    //   172: new 120	java/util/ArrayList
    //   175: dup
    //   176: invokespecial 121	java/util/ArrayList:<init>	()V
    //   179: astore 8
    //   181: aload 8
    //   183: new 123	org/apache/http/message/BasicNameValuePair
    //   186: dup
    //   187: ldc 125
    //   189: aload 12
    //   191: invokespecial 127	org/apache/http/message/BasicNameValuePair:<init>	(Ljava/lang/String;Ljava/lang/String;)V
    //   194: invokeinterface 133 2 0
    //   199: pop
    //   200: aload 8
    //   202: new 123	org/apache/http/message/BasicNameValuePair
    //   205: dup
    //   206: ldc -121
    //   208: aload_0
    //   209: getfield 27	com/gtp/go/weather/sharephoto/c/n:a	Lcom/gtp/go/weather/sharephoto/b/e;
    //   212: invokevirtual 79	com/gtp/go/weather/sharephoto/b/e:f	()J
    //   215: invokestatic 141	java/lang/String:valueOf	(J)Ljava/lang/String;
    //   218: invokespecial 127	org/apache/http/message/BasicNameValuePair:<init>	(Ljava/lang/String;Ljava/lang/String;)V
    //   221: invokeinterface 133 2 0
    //   226: pop
    //   227: aload 11
    //   229: aload 8
    //   231: invokevirtual 144	com/jiubang/goweather/b/e:a	(Ljava/util/List;)V
    //   234: iconst_1
    //   235: invokestatic 149	com/jiubang/goweather/b/d:a	(Z)Lcom/jiubang/goweather/b/c;
    //   238: astore 14
    //   240: aconst_null
    //   241: astore 9
    //   243: aload 11
    //   245: invokevirtual 152	com/jiubang/goweather/b/e:i	()Ljava/lang/String;
    //   248: astore 8
    //   250: aload 8
    //   252: invokestatic 158	android/text/TextUtils:isEmpty	(Ljava/lang/CharSequence;)Z
    //   255: ifne -245 -> 10
    //   258: aload 14
    //   260: aload 8
    //   262: aload 11
    //   264: aload_0
    //   265: getfield 61	com/gtp/go/weather/sharephoto/c/n:c	Lcom/jiubang/goweather/b/f;
    //   268: invokevirtual 163	com/jiubang/goweather/b/c:b	(Ljava/lang/String;Lcom/jiubang/goweather/b/e;Lcom/jiubang/goweather/b/f;)Ljava/lang/String;
    //   271: astore 9
    //   273: aload_0
    //   274: getfield 61	com/gtp/go/weather/sharephoto/c/n:c	Lcom/jiubang/goweather/b/f;
    //   277: aload 9
    //   279: invokevirtual 165	com/jiubang/goweather/b/f:b	(Ljava/lang/String;)V
    //   282: aload 9
    //   284: invokestatic 158	android/text/TextUtils:isEmpty	(Ljava/lang/CharSequence;)Z
    //   287: ifne -277 -> 10
    //   290: aconst_null
    //   291: astore 8
    //   293: new 117	org/json/JSONObject
    //   296: dup
    //   297: aload 9
    //   299: invokespecial 166	org/json/JSONObject:<init>	(Ljava/lang/String;)V
    //   302: astore 9
    //   304: aload_0
    //   305: aload 9
    //   307: ldc -88
    //   309: invokevirtual 172	org/json/JSONObject:getJSONObject	(Ljava/lang/String;)Lorg/json/JSONObject;
    //   312: invokestatic 177	com/gtp/go/weather/sharephoto/b/l:a	(Lorg/json/JSONObject;)Lcom/gtp/go/weather/sharephoto/b/l;
    //   315: putfield 179	com/gtp/go/weather/sharephoto/c/n:d	Lcom/gtp/go/weather/sharephoto/b/l;
    //   318: aload_0
    //   319: getfield 179	com/gtp/go/weather/sharephoto/c/n:d	Lcom/gtp/go/weather/sharephoto/b/l;
    //   322: getfield 182	com/gtp/go/weather/sharephoto/b/l:a	I
    //   325: iconst_1
    //   326: if_icmpne +436 -> 762
    //   329: aload 9
    //   331: ldc -72
    //   333: invokevirtual 188	org/json/JSONObject:getJSONArray	(Ljava/lang/String;)Lorg/json/JSONArray;
    //   336: invokestatic 193	com/gtp/go/weather/sharephoto/b/m:a	(Lorg/json/JSONArray;)Ljava/util/List;
    //   339: astore 8
    //   341: iconst_0
    //   342: istore_1
    //   343: iconst_0
    //   344: istore_2
    //   345: aload 8
    //   347: invokeinterface 197 1 0
    //   352: astore 9
    //   354: aload 9
    //   356: invokeinterface 202 1 0
    //   361: ifeq +83 -> 444
    //   364: aload 9
    //   366: invokeinterface 206 1 0
    //   371: checkcast 190	com/gtp/go/weather/sharephoto/b/m
    //   374: astore 11
    //   376: aload 11
    //   378: getfield 207	com/gtp/go/weather/sharephoto/b/m:a	I
    //   381: istore_3
    //   382: iload_3
    //   383: iconst_1
    //   384: if_icmpne +42 -> 426
    //   387: iconst_1
    //   388: istore_3
    //   389: iload_2
    //   390: istore_1
    //   391: iload_3
    //   392: istore_2
    //   393: iload_2
    //   394: istore_3
    //   395: iload_1
    //   396: istore_2
    //   397: iload_3
    //   398: istore_1
    //   399: goto -45 -> 354
    //   402: astore 15
    //   404: aload 9
    //   406: astore 8
    //   408: invokestatic 211	com/gtp/a/a/b/c:a	()Z
    //   411: ifeq -161 -> 250
    //   414: aload 15
    //   416: invokevirtual 214	java/io/UnsupportedEncodingException:printStackTrace	()V
    //   419: aload 9
    //   421: astore 8
    //   423: goto -173 -> 250
    //   426: aload 11
    //   428: getfield 207	com/gtp/go/weather/sharephoto/b/m:a	I
    //   431: iconst_2
    //   432: if_icmpne +1546 -> 1978
    //   435: iconst_1
    //   436: istore_3
    //   437: iload_1
    //   438: istore_2
    //   439: iload_3
    //   440: istore_1
    //   441: goto -48 -> 393
    //   444: iload_1
    //   445: ifne +34 -> 479
    //   448: new 190	com/gtp/go/weather/sharephoto/b/m
    //   451: dup
    //   452: invokespecial 215	com/gtp/go/weather/sharephoto/b/m:<init>	()V
    //   455: astore 9
    //   457: aload 9
    //   459: iconst_1
    //   460: putfield 207	com/gtp/go/weather/sharephoto/b/m:a	I
    //   463: aload 9
    //   465: iconst_0
    //   466: putfield 217	com/gtp/go/weather/sharephoto/b/m:b	I
    //   469: aload 8
    //   471: aload 9
    //   473: invokeinterface 133 2 0
    //   478: pop
    //   479: iload_2
    //   480: ifne +34 -> 514
    //   483: new 190	com/gtp/go/weather/sharephoto/b/m
    //   486: dup
    //   487: invokespecial 215	com/gtp/go/weather/sharephoto/b/m:<init>	()V
    //   490: astore 9
    //   492: aload 9
    //   494: iconst_2
    //   495: putfield 207	com/gtp/go/weather/sharephoto/b/m:a	I
    //   498: aload 9
    //   500: iconst_0
    //   501: putfield 217	com/gtp/go/weather/sharephoto/b/m:b	I
    //   504: aload 8
    //   506: aload 9
    //   508: invokeinterface 133 2 0
    //   513: pop
    //   514: aload 8
    //   516: ifnull -506 -> 10
    //   519: aload 8
    //   521: invokeinterface 221 1 0
    //   526: ifeq -516 -> 10
    //   529: aload_0
    //   530: new 58	com/jiubang/goweather/b/f
    //   533: dup
    //   534: invokespecial 59	com/jiubang/goweather/b/f:<init>	()V
    //   537: putfield 61	com/gtp/go/weather/sharephoto/c/n:c	Lcom/jiubang/goweather/b/f;
    //   540: aconst_null
    //   541: astore 11
    //   543: aconst_null
    //   544: astore 9
    //   546: aload 8
    //   548: invokeinterface 197 1 0
    //   553: astore 15
    //   555: aload 11
    //   557: astore 8
    //   559: aload 15
    //   561: invokeinterface 202 1 0
    //   566: ifeq +492 -> 1058
    //   569: aload 15
    //   571: invokeinterface 206 1 0
    //   576: checkcast 190	com/gtp/go/weather/sharephoto/b/m
    //   579: astore 11
    //   581: aload 11
    //   583: getfield 207	com/gtp/go/weather/sharephoto/b/m:a	I
    //   586: iconst_1
    //   587: if_icmpne +278 -> 865
    //   590: aload_0
    //   591: getfield 27	com/gtp/go/weather/sharephoto/c/n:a	Lcom/gtp/go/weather/sharephoto/b/e;
    //   594: aload 11
    //   596: getfield 217	com/gtp/go/weather/sharephoto/b/m:b	I
    //   599: i2l
    //   600: invokevirtual 224	com/gtp/go/weather/sharephoto/b/e:b	(J)V
    //   603: new 46	java/io/File
    //   606: dup
    //   607: aload 13
    //   609: invokevirtual 227	java/io/File:getParent	()Ljava/lang/String;
    //   612: new 68	java/lang/StringBuilder
    //   615: dup
    //   616: invokespecial 69	java/lang/StringBuilder:<init>	()V
    //   619: aload 13
    //   621: invokevirtual 230	java/io/File:getName	()Ljava/lang/String;
    //   624: invokevirtual 75	java/lang/StringBuilder:append	(Ljava/lang/String;)Ljava/lang/StringBuilder;
    //   627: ldc -24
    //   629: invokevirtual 75	java/lang/StringBuilder:append	(Ljava/lang/String;)Ljava/lang/StringBuilder;
    //   632: invokevirtual 87	java/lang/StringBuilder:toString	()Ljava/lang/String;
    //   635: invokespecial 233	java/io/File:<init>	(Ljava/lang/String;Ljava/lang/String;)V
    //   638: astore 8
    //   640: aload 13
    //   642: invokevirtual 236	java/io/File:length	()J
    //   645: lstore 4
    //   647: aload 11
    //   649: getfield 217	com/gtp/go/weather/sharephoto/b/m:b	I
    //   652: i2l
    //   653: lstore 6
    //   655: aload 13
    //   657: aload 8
    //   659: aload 11
    //   661: getfield 217	com/gtp/go/weather/sharephoto/b/m:b	I
    //   664: i2l
    //   665: lload 4
    //   667: lload 6
    //   669: lsub
    //   670: invokestatic 241	com/jiubang/goweather/e/a:a	(Ljava/io/File;Ljava/io/File;JJ)Z
    //   673: pop
    //   674: ldc -13
    //   676: new 68	java/lang/StringBuilder
    //   679: dup
    //   680: invokespecial 69	java/lang/StringBuilder:<init>	()V
    //   683: ldc -11
    //   685: invokevirtual 75	java/lang/StringBuilder:append	(Ljava/lang/String;)Ljava/lang/StringBuilder;
    //   688: aload 13
    //   690: invokevirtual 236	java/io/File:length	()J
    //   693: invokevirtual 82	java/lang/StringBuilder:append	(J)Ljava/lang/StringBuilder;
    //   696: ldc -9
    //   698: invokevirtual 75	java/lang/StringBuilder:append	(Ljava/lang/String;)Ljava/lang/StringBuilder;
    //   701: aload 11
    //   703: getfield 217	com/gtp/go/weather/sharephoto/b/m:b	I
    //   706: invokevirtual 250	java/lang/StringBuilder:append	(I)Ljava/lang/StringBuilder;
    //   709: invokevirtual 87	java/lang/StringBuilder:toString	()Ljava/lang/String;
    //   712: invokestatic 251	com/gtp/a/a/b/c:a	(Ljava/lang/String;Ljava/lang/String;)V
    //   715: invokestatic 66	com/gtp/a/a/a/a:a	()Lcom/gtp/a/a/a/a;
    //   718: new 68	java/lang/StringBuilder
    //   721: dup
    //   722: invokespecial 69	java/lang/StringBuilder:<init>	()V
    //   725: ldc -11
    //   727: invokevirtual 75	java/lang/StringBuilder:append	(Ljava/lang/String;)Ljava/lang/StringBuilder;
    //   730: aload 13
    //   732: invokevirtual 236	java/io/File:length	()J
    //   735: invokevirtual 82	java/lang/StringBuilder:append	(J)Ljava/lang/StringBuilder;
    //   738: ldc -9
    //   740: invokevirtual 75	java/lang/StringBuilder:append	(Ljava/lang/String;)Ljava/lang/StringBuilder;
    //   743: aload 11
    //   745: getfield 217	com/gtp/go/weather/sharephoto/b/m:b	I
    //   748: invokevirtual 250	java/lang/StringBuilder:append	(I)Ljava/lang/StringBuilder;
    //   751: invokevirtual 87	java/lang/StringBuilder:toString	()Ljava/lang/String;
    //   754: ldc 89
    //   756: invokevirtual 92	com/gtp/a/a/a/a:a	(Ljava/lang/String;Ljava/lang/String;)V
    //   759: goto -200 -> 559
    //   762: aload_0
    //   763: getfield 179	com/gtp/go/weather/sharephoto/c/n:d	Lcom/gtp/go/weather/sharephoto/b/l;
    //   766: getfield 182	com/gtp/go/weather/sharephoto/b/l:a	I
    //   769: ifne -255 -> 514
    //   772: new 120	java/util/ArrayList
    //   775: dup
    //   776: invokespecial 121	java/util/ArrayList:<init>	()V
    //   779: astore 8
    //   781: new 190	com/gtp/go/weather/sharephoto/b/m
    //   784: dup
    //   785: invokespecial 215	com/gtp/go/weather/sharephoto/b/m:<init>	()V
    //   788: astore 9
    //   790: aload 9
    //   792: iconst_1
    //   793: putfield 207	com/gtp/go/weather/sharephoto/b/m:a	I
    //   796: aload 9
    //   798: iconst_0
    //   799: putfield 217	com/gtp/go/weather/sharephoto/b/m:b	I
    //   802: aload 8
    //   804: aload 9
    //   806: invokeinterface 133 2 0
    //   811: pop
    //   812: new 190	com/gtp/go/weather/sharephoto/b/m
    //   815: dup
    //   816: invokespecial 215	com/gtp/go/weather/sharephoto/b/m:<init>	()V
    //   819: astore 9
    //   821: aload 9
    //   823: iconst_2
    //   824: putfield 207	com/gtp/go/weather/sharephoto/b/m:a	I
    //   827: aload 9
    //   829: iconst_0
    //   830: putfield 217	com/gtp/go/weather/sharephoto/b/m:b	I
    //   833: aload 8
    //   835: aload 9
    //   837: invokeinterface 133 2 0
    //   842: pop
    //   843: goto -329 -> 514
    //   846: astore 8
    //   848: invokestatic 211	com/gtp/a/a/b/c:a	()Z
    //   851: ifeq +8 -> 859
    //   854: aload 8
    //   856: invokevirtual 252	org/json/JSONException:printStackTrace	()V
    //   859: aconst_null
    //   860: astore 8
    //   862: goto -348 -> 514
    //   865: aload 11
    //   867: getfield 207	com/gtp/go/weather/sharephoto/b/m:a	I
    //   870: iconst_2
    //   871: if_icmpne +1104 -> 1975
    //   874: aload_0
    //   875: getfield 27	com/gtp/go/weather/sharephoto/c/n:a	Lcom/gtp/go/weather/sharephoto/b/e;
    //   878: invokevirtual 41	com/gtp/go/weather/sharephoto/b/e:e	()Z
    //   881: ifeq +1094 -> 1975
    //   884: aload_0
    //   885: getfield 27	com/gtp/go/weather/sharephoto/c/n:a	Lcom/gtp/go/weather/sharephoto/b/e;
    //   888: aload 11
    //   890: getfield 217	com/gtp/go/weather/sharephoto/b/m:b	I
    //   893: i2l
    //   894: invokevirtual 254	com/gtp/go/weather/sharephoto/b/e:c	(J)V
    //   897: new 46	java/io/File
    //   900: dup
    //   901: aload 10
    //   903: invokevirtual 227	java/io/File:getParent	()Ljava/lang/String;
    //   906: new 68	java/lang/StringBuilder
    //   909: dup
    //   910: invokespecial 69	java/lang/StringBuilder:<init>	()V
    //   913: aload 10
    //   915: invokevirtual 230	java/io/File:getName	()Ljava/lang/String;
    //   918: invokevirtual 75	java/lang/StringBuilder:append	(Ljava/lang/String;)Ljava/lang/StringBuilder;
    //   921: ldc -24
    //   923: invokevirtual 75	java/lang/StringBuilder:append	(Ljava/lang/String;)Ljava/lang/StringBuilder;
    //   926: invokevirtual 87	java/lang/StringBuilder:toString	()Ljava/lang/String;
    //   929: invokespecial 233	java/io/File:<init>	(Ljava/lang/String;Ljava/lang/String;)V
    //   932: astore 9
    //   934: aload 10
    //   936: invokevirtual 236	java/io/File:length	()J
    //   939: lstore 4
    //   941: aload 11
    //   943: getfield 217	com/gtp/go/weather/sharephoto/b/m:b	I
    //   946: i2l
    //   947: lstore 6
    //   949: aload 10
    //   951: aload 9
    //   953: aload 11
    //   955: getfield 217	com/gtp/go/weather/sharephoto/b/m:b	I
    //   958: i2l
    //   959: lload 4
    //   961: lload 6
    //   963: lsub
    //   964: invokestatic 241	com/jiubang/goweather/e/a:a	(Ljava/io/File;Ljava/io/File;JJ)Z
    //   967: pop
    //   968: ldc -13
    //   970: new 68	java/lang/StringBuilder
    //   973: dup
    //   974: invokespecial 69	java/lang/StringBuilder:<init>	()V
    //   977: ldc_w 256
    //   980: invokevirtual 75	java/lang/StringBuilder:append	(Ljava/lang/String;)Ljava/lang/StringBuilder;
    //   983: aload 10
    //   985: invokevirtual 236	java/io/File:length	()J
    //   988: invokevirtual 82	java/lang/StringBuilder:append	(J)Ljava/lang/StringBuilder;
    //   991: ldc -9
    //   993: invokevirtual 75	java/lang/StringBuilder:append	(Ljava/lang/String;)Ljava/lang/StringBuilder;
    //   996: aload 11
    //   998: getfield 217	com/gtp/go/weather/sharephoto/b/m:b	I
    //   1001: invokevirtual 250	java/lang/StringBuilder:append	(I)Ljava/lang/StringBuilder;
    //   1004: invokevirtual 87	java/lang/StringBuilder:toString	()Ljava/lang/String;
    //   1007: invokestatic 251	com/gtp/a/a/b/c:a	(Ljava/lang/String;Ljava/lang/String;)V
    //   1010: invokestatic 66	com/gtp/a/a/a/a:a	()Lcom/gtp/a/a/a/a;
    //   1013: new 68	java/lang/StringBuilder
    //   1016: dup
    //   1017: invokespecial 69	java/lang/StringBuilder:<init>	()V
    //   1020: ldc_w 256
    //   1023: invokevirtual 75	java/lang/StringBuilder:append	(Ljava/lang/String;)Ljava/lang/StringBuilder;
    //   1026: aload 10
    //   1028: invokevirtual 236	java/io/File:length	()J
    //   1031: invokevirtual 82	java/lang/StringBuilder:append	(J)Ljava/lang/StringBuilder;
    //   1034: ldc -9
    //   1036: invokevirtual 75	java/lang/StringBuilder:append	(Ljava/lang/String;)Ljava/lang/StringBuilder;
    //   1039: aload 11
    //   1041: getfield 217	com/gtp/go/weather/sharephoto/b/m:b	I
    //   1044: invokevirtual 250	java/lang/StringBuilder:append	(I)Ljava/lang/StringBuilder;
    //   1047: invokevirtual 87	java/lang/StringBuilder:toString	()Ljava/lang/String;
    //   1050: ldc 89
    //   1052: invokevirtual 92	com/gtp/a/a/a/a:a	(Ljava/lang/String;Ljava/lang/String;)V
    //   1055: goto -296 -> 759
    //   1058: aload_0
    //   1059: getfield 27	com/gtp/go/weather/sharephoto/c/n:a	Lcom/gtp/go/weather/sharephoto/b/e;
    //   1062: invokevirtual 259	com/gtp/go/weather/sharephoto/b/e:k	()Z
    //   1065: ifne +595 -> 1660
    //   1068: new 94	com/jiubang/goweather/b/e
    //   1071: dup
    //   1072: ldc_w 261
    //   1075: invokespecial 97	com/jiubang/goweather/b/e:<init>	(Ljava/lang/String;)V
    //   1078: astore 15
    //   1080: aload 15
    //   1082: iconst_0
    //   1083: invokevirtual 264	com/jiubang/goweather/b/e:b	(I)V
    //   1086: aload 15
    //   1088: ldc 99
    //   1090: invokestatic 103	com/gau/go/launcherex/gowidget/statistics/y:c	()Ljava/lang/String;
    //   1093: invokevirtual 106	com/jiubang/goweather/b/e:a	(Ljava/lang/String;Ljava/lang/String;)Lcom/jiubang/goweather/b/a;
    //   1096: pop
    //   1097: aload 15
    //   1099: ldc 108
    //   1101: invokevirtual 110	com/jiubang/goweather/b/e:a	(Ljava/lang/String;)V
    //   1104: new 266	a/a/a/a/a/h
    //   1107: dup
    //   1108: getstatic 271	a/a/a/a/a/e:b	La/a/a/a/a/e;
    //   1111: invokespecial 274	a/a/a/a/a/h:<init>	(La/a/a/a/a/e;)V
    //   1114: astore 11
    //   1116: aload 11
    //   1118: ldc 125
    //   1120: new 276	a/a/a/a/a/a/e
    //   1123: dup
    //   1124: aload 12
    //   1126: invokespecial 277	a/a/a/a/a/a/e:<init>	(Ljava/lang/String;)V
    //   1129: invokevirtual 280	a/a/a/a/a/h:a	(Ljava/lang/String;La/a/a/a/a/a/b;)V
    //   1132: aload 11
    //   1134: ldc -121
    //   1136: new 276	a/a/a/a/a/a/e
    //   1139: dup
    //   1140: aload_0
    //   1141: getfield 27	com/gtp/go/weather/sharephoto/c/n:a	Lcom/gtp/go/weather/sharephoto/b/e;
    //   1144: invokevirtual 79	com/gtp/go/weather/sharephoto/b/e:f	()J
    //   1147: invokestatic 141	java/lang/String:valueOf	(J)Ljava/lang/String;
    //   1150: invokespecial 277	a/a/a/a/a/a/e:<init>	(Ljava/lang/String;)V
    //   1153: invokevirtual 280	a/a/a/a/a/h:a	(Ljava/lang/String;La/a/a/a/a/a/b;)V
    //   1156: aload 11
    //   1158: ldc_w 282
    //   1161: new 276	a/a/a/a/a/a/e
    //   1164: dup
    //   1165: aload 13
    //   1167: invokevirtual 236	java/io/File:length	()J
    //   1170: invokestatic 141	java/lang/String:valueOf	(J)Ljava/lang/String;
    //   1173: invokespecial 277	a/a/a/a/a/a/e:<init>	(Ljava/lang/String;)V
    //   1176: invokevirtual 280	a/a/a/a/a/h:a	(Ljava/lang/String;La/a/a/a/a/a/b;)V
    //   1179: aload 11
    //   1181: ldc_w 284
    //   1184: new 276	a/a/a/a/a/a/e
    //   1187: dup
    //   1188: aload_0
    //   1189: getfield 27	com/gtp/go/weather/sharephoto/c/n:a	Lcom/gtp/go/weather/sharephoto/b/e;
    //   1192: invokevirtual 41	com/gtp/go/weather/sharephoto/b/e:e	()Z
    //   1195: invokestatic 287	java/lang/String:valueOf	(Z)Ljava/lang/String;
    //   1198: invokespecial 277	a/a/a/a/a/a/e:<init>	(Ljava/lang/String;)V
    //   1201: invokevirtual 280	a/a/a/a/a/h:a	(Ljava/lang/String;La/a/a/a/a/a/b;)V
    //   1204: aload_0
    //   1205: getfield 27	com/gtp/go/weather/sharephoto/c/n:a	Lcom/gtp/go/weather/sharephoto/b/e;
    //   1208: invokevirtual 41	com/gtp/go/weather/sharephoto/b/e:e	()Z
    //   1211: ifeq +26 -> 1237
    //   1214: aload 11
    //   1216: ldc_w 289
    //   1219: new 276	a/a/a/a/a/a/e
    //   1222: dup
    //   1223: aload 10
    //   1225: invokevirtual 236	java/io/File:length	()J
    //   1228: invokestatic 141	java/lang/String:valueOf	(J)Ljava/lang/String;
    //   1231: invokespecial 277	a/a/a/a/a/a/e:<init>	(Ljava/lang/String;)V
    //   1234: invokevirtual 280	a/a/a/a/a/h:a	(Ljava/lang/String;La/a/a/a/a/a/b;)V
    //   1237: aload 8
    //   1239: ifnull +91 -> 1330
    //   1242: aload 8
    //   1244: invokevirtual 236	java/io/File:length	()J
    //   1247: lconst_0
    //   1248: lcmp
    //   1249: ifle +81 -> 1330
    //   1252: ldc -13
    //   1254: new 68	java/lang/StringBuilder
    //   1257: dup
    //   1258: invokespecial 69	java/lang/StringBuilder:<init>	()V
    //   1261: ldc_w 291
    //   1264: invokevirtual 75	java/lang/StringBuilder:append	(Ljava/lang/String;)Ljava/lang/StringBuilder;
    //   1267: aload 8
    //   1269: invokevirtual 236	java/io/File:length	()J
    //   1272: invokevirtual 82	java/lang/StringBuilder:append	(J)Ljava/lang/StringBuilder;
    //   1275: invokevirtual 87	java/lang/StringBuilder:toString	()Ljava/lang/String;
    //   1278: invokestatic 251	com/gtp/a/a/b/c:a	(Ljava/lang/String;Ljava/lang/String;)V
    //   1281: invokestatic 66	com/gtp/a/a/a/a:a	()Lcom/gtp/a/a/a/a;
    //   1284: new 68	java/lang/StringBuilder
    //   1287: dup
    //   1288: invokespecial 69	java/lang/StringBuilder:<init>	()V
    //   1291: ldc_w 293
    //   1294: invokevirtual 75	java/lang/StringBuilder:append	(Ljava/lang/String;)Ljava/lang/StringBuilder;
    //   1297: aload 8
    //   1299: invokevirtual 236	java/io/File:length	()J
    //   1302: invokevirtual 82	java/lang/StringBuilder:append	(J)Ljava/lang/StringBuilder;
    //   1305: invokevirtual 87	java/lang/StringBuilder:toString	()Ljava/lang/String;
    //   1308: ldc 89
    //   1310: invokevirtual 92	com/gtp/a/a/a/a:a	(Ljava/lang/String;Ljava/lang/String;)V
    //   1313: aload 11
    //   1315: ldc_w 295
    //   1318: new 297	a/a/a/a/a/a/d
    //   1321: dup
    //   1322: aload 8
    //   1324: invokespecial 300	a/a/a/a/a/a/d:<init>	(Ljava/io/File;)V
    //   1327: invokevirtual 280	a/a/a/a/a/h:a	(Ljava/lang/String;La/a/a/a/a/a/b;)V
    //   1330: aload_0
    //   1331: getfield 27	com/gtp/go/weather/sharephoto/c/n:a	Lcom/gtp/go/weather/sharephoto/b/e;
    //   1334: invokevirtual 41	com/gtp/go/weather/sharephoto/b/e:e	()Z
    //   1337: ifeq +96 -> 1433
    //   1340: aload 9
    //   1342: ifnull +91 -> 1433
    //   1345: aload 9
    //   1347: invokevirtual 236	java/io/File:length	()J
    //   1350: lconst_0
    //   1351: lcmp
    //   1352: ifle +81 -> 1433
    //   1355: ldc -13
    //   1357: new 68	java/lang/StringBuilder
    //   1360: dup
    //   1361: invokespecial 69	java/lang/StringBuilder:<init>	()V
    //   1364: ldc_w 302
    //   1367: invokevirtual 75	java/lang/StringBuilder:append	(Ljava/lang/String;)Ljava/lang/StringBuilder;
    //   1370: aload 9
    //   1372: invokevirtual 236	java/io/File:length	()J
    //   1375: invokevirtual 82	java/lang/StringBuilder:append	(J)Ljava/lang/StringBuilder;
    //   1378: invokevirtual 87	java/lang/StringBuilder:toString	()Ljava/lang/String;
    //   1381: invokestatic 251	com/gtp/a/a/b/c:a	(Ljava/lang/String;Ljava/lang/String;)V
    //   1384: invokestatic 66	com/gtp/a/a/a/a:a	()Lcom/gtp/a/a/a/a;
    //   1387: new 68	java/lang/StringBuilder
    //   1390: dup
    //   1391: invokespecial 69	java/lang/StringBuilder:<init>	()V
    //   1394: ldc_w 304
    //   1397: invokevirtual 75	java/lang/StringBuilder:append	(Ljava/lang/String;)Ljava/lang/StringBuilder;
    //   1400: aload 9
    //   1402: invokevirtual 236	java/io/File:length	()J
    //   1405: invokevirtual 82	java/lang/StringBuilder:append	(J)Ljava/lang/StringBuilder;
    //   1408: invokevirtual 87	java/lang/StringBuilder:toString	()Ljava/lang/String;
    //   1411: ldc 89
    //   1413: invokevirtual 92	com/gtp/a/a/a/a:a	(Ljava/lang/String;Ljava/lang/String;)V
    //   1416: aload 11
    //   1418: ldc_w 306
    //   1421: new 297	a/a/a/a/a/a/d
    //   1424: dup
    //   1425: aload 9
    //   1427: invokespecial 300	a/a/a/a/a/a/d:<init>	(Ljava/io/File;)V
    //   1430: invokevirtual 280	a/a/a/a/a/h:a	(Ljava/lang/String;La/a/a/a/a/a/b;)V
    //   1433: aload 15
    //   1435: aload 11
    //   1437: invokevirtual 309	com/jiubang/goweather/b/e:a	(La/a/a/a/a/h;)V
    //   1440: aconst_null
    //   1441: astore 12
    //   1443: aload 15
    //   1445: invokevirtual 152	com/jiubang/goweather/b/e:i	()Ljava/lang/String;
    //   1448: astore 11
    //   1450: aload 11
    //   1452: invokestatic 158	android/text/TextUtils:isEmpty	(Ljava/lang/CharSequence;)Z
    //   1455: ifne -1445 -> 10
    //   1458: ldc -13
    //   1460: ldc_w 311
    //   1463: invokestatic 251	com/gtp/a/a/b/c:a	(Ljava/lang/String;Ljava/lang/String;)V
    //   1466: aload 14
    //   1468: aload 11
    //   1470: aload 15
    //   1472: aload_0
    //   1473: getfield 61	com/gtp/go/weather/sharephoto/c/n:c	Lcom/jiubang/goweather/b/f;
    //   1476: invokevirtual 163	com/jiubang/goweather/b/c:b	(Ljava/lang/String;Lcom/jiubang/goweather/b/e;Lcom/jiubang/goweather/b/f;)Ljava/lang/String;
    //   1479: astore 11
    //   1481: ldc -13
    //   1483: ldc_w 313
    //   1486: invokestatic 251	com/gtp/a/a/b/c:a	(Ljava/lang/String;Ljava/lang/String;)V
    //   1489: aload 8
    //   1491: ifnull +9 -> 1500
    //   1494: aload 8
    //   1496: invokevirtual 316	java/io/File:delete	()Z
    //   1499: pop
    //   1500: aload 9
    //   1502: ifnull +9 -> 1511
    //   1505: aload 9
    //   1507: invokevirtual 316	java/io/File:delete	()Z
    //   1510: pop
    //   1511: ldc -13
    //   1513: new 68	java/lang/StringBuilder
    //   1516: dup
    //   1517: invokespecial 69	java/lang/StringBuilder:<init>	()V
    //   1520: ldc_w 318
    //   1523: invokevirtual 75	java/lang/StringBuilder:append	(Ljava/lang/String;)Ljava/lang/StringBuilder;
    //   1526: aload 11
    //   1528: invokevirtual 75	java/lang/StringBuilder:append	(Ljava/lang/String;)Ljava/lang/StringBuilder;
    //   1531: ldc_w 320
    //   1534: invokevirtual 75	java/lang/StringBuilder:append	(Ljava/lang/String;)Ljava/lang/StringBuilder;
    //   1537: aload_0
    //   1538: getfield 27	com/gtp/go/weather/sharephoto/c/n:a	Lcom/gtp/go/weather/sharephoto/b/e;
    //   1541: invokevirtual 79	com/gtp/go/weather/sharephoto/b/e:f	()J
    //   1544: invokevirtual 82	java/lang/StringBuilder:append	(J)Ljava/lang/StringBuilder;
    //   1547: invokevirtual 87	java/lang/StringBuilder:toString	()Ljava/lang/String;
    //   1550: invokestatic 251	com/gtp/a/a/b/c:a	(Ljava/lang/String;Ljava/lang/String;)V
    //   1553: aload_0
    //   1554: getfield 61	com/gtp/go/weather/sharephoto/c/n:c	Lcom/jiubang/goweather/b/f;
    //   1557: aload 11
    //   1559: invokevirtual 165	com/jiubang/goweather/b/f:b	(Ljava/lang/String;)V
    //   1562: aload_0
    //   1563: aconst_null
    //   1564: putfield 179	com/gtp/go/weather/sharephoto/c/n:d	Lcom/gtp/go/weather/sharephoto/b/l;
    //   1567: aload 11
    //   1569: invokestatic 158	android/text/TextUtils:isEmpty	(Ljava/lang/CharSequence;)Z
    //   1572: ifne +24 -> 1596
    //   1575: aload_0
    //   1576: new 117	org/json/JSONObject
    //   1579: dup
    //   1580: aload 11
    //   1582: invokespecial 166	org/json/JSONObject:<init>	(Ljava/lang/String;)V
    //   1585: ldc -88
    //   1587: invokevirtual 172	org/json/JSONObject:getJSONObject	(Ljava/lang/String;)Lorg/json/JSONObject;
    //   1590: invokestatic 177	com/gtp/go/weather/sharephoto/b/l:a	(Lorg/json/JSONObject;)Lcom/gtp/go/weather/sharephoto/b/l;
    //   1593: putfield 179	com/gtp/go/weather/sharephoto/c/n:d	Lcom/gtp/go/weather/sharephoto/b/l;
    //   1596: aload_0
    //   1597: getfield 179	com/gtp/go/weather/sharephoto/c/n:d	Lcom/gtp/go/weather/sharephoto/b/l;
    //   1600: ifnull +60 -> 1660
    //   1603: aload_0
    //   1604: getfield 179	com/gtp/go/weather/sharephoto/c/n:d	Lcom/gtp/go/weather/sharephoto/b/l;
    //   1607: getfield 182	com/gtp/go/weather/sharephoto/b/l:a	I
    //   1610: iconst_1
    //   1611: if_icmpeq +15 -> 1626
    //   1614: aload_0
    //   1615: getfield 179	com/gtp/go/weather/sharephoto/c/n:d	Lcom/gtp/go/weather/sharephoto/b/l;
    //   1618: getfield 182	com/gtp/go/weather/sharephoto/b/l:a	I
    //   1621: bipush 11
    //   1623: if_icmpne +37 -> 1660
    //   1626: aload_0
    //   1627: getfield 27	com/gtp/go/weather/sharephoto/c/n:a	Lcom/gtp/go/weather/sharephoto/b/e;
    //   1630: aload 13
    //   1632: invokevirtual 236	java/io/File:length	()J
    //   1635: invokevirtual 224	com/gtp/go/weather/sharephoto/b/e:b	(J)V
    //   1638: aload_0
    //   1639: getfield 27	com/gtp/go/weather/sharephoto/c/n:a	Lcom/gtp/go/weather/sharephoto/b/e;
    //   1642: invokevirtual 41	com/gtp/go/weather/sharephoto/b/e:e	()Z
    //   1645: ifeq +15 -> 1660
    //   1648: aload_0
    //   1649: getfield 27	com/gtp/go/weather/sharephoto/c/n:a	Lcom/gtp/go/weather/sharephoto/b/e;
    //   1652: aload 10
    //   1654: invokevirtual 236	java/io/File:length	()J
    //   1657: invokevirtual 254	com/gtp/go/weather/sharephoto/b/e:c	(J)V
    //   1660: aload_0
    //   1661: getfield 27	com/gtp/go/weather/sharephoto/c/n:a	Lcom/gtp/go/weather/sharephoto/b/e;
    //   1664: invokevirtual 79	com/gtp/go/weather/sharephoto/b/e:f	()J
    //   1667: lstore 4
    //   1669: new 322	android/content/ContentValues
    //   1672: dup
    //   1673: invokespecial 323	android/content/ContentValues:<init>	()V
    //   1676: astore 8
    //   1678: aload 8
    //   1680: ldc_w 325
    //   1683: aload_0
    //   1684: getfield 27	com/gtp/go/weather/sharephoto/c/n:a	Lcom/gtp/go/weather/sharephoto/b/e;
    //   1687: invokevirtual 327	com/gtp/go/weather/sharephoto/b/e:i	()J
    //   1690: invokestatic 332	java/lang/Long:valueOf	(J)Ljava/lang/Long;
    //   1693: invokevirtual 336	android/content/ContentValues:put	(Ljava/lang/String;Ljava/lang/Long;)V
    //   1696: aload 8
    //   1698: ldc_w 338
    //   1701: aload_0
    //   1702: getfield 27	com/gtp/go/weather/sharephoto/c/n:a	Lcom/gtp/go/weather/sharephoto/b/e;
    //   1705: invokevirtual 341	com/gtp/go/weather/sharephoto/b/e:j	()J
    //   1708: invokestatic 332	java/lang/Long:valueOf	(J)Ljava/lang/Long;
    //   1711: invokevirtual 336	android/content/ContentValues:put	(Ljava/lang/String;Ljava/lang/Long;)V
    //   1714: aload_0
    //   1715: getfield 25	com/gtp/go/weather/sharephoto/c/n:b	Landroid/content/Context;
    //   1718: aload 8
    //   1720: ldc_w 343
    //   1723: iconst_1
    //   1724: anewarray 137	java/lang/String
    //   1727: dup
    //   1728: iconst_0
    //   1729: lload 4
    //   1731: invokestatic 141	java/lang/String:valueOf	(J)Ljava/lang/String;
    //   1734: aastore
    //   1735: invokestatic 348	com/gtp/go/weather/sharephoto/b/a/d:a	(Landroid/content/Context;Landroid/content/ContentValues;Ljava/lang/String;[Ljava/lang/String;)I
    //   1738: pop
    //   1739: invokestatic 211	com/gtp/a/a/b/c:a	()Z
    //   1742: ifeq -1732 -> 10
    //   1745: ldc_w 350
    //   1748: astore 9
    //   1750: aload 9
    //   1752: astore 8
    //   1754: aload_0
    //   1755: getfield 179	com/gtp/go/weather/sharephoto/c/n:d	Lcom/gtp/go/weather/sharephoto/b/l;
    //   1758: ifnull +19 -> 1777
    //   1761: aload_0
    //   1762: getfield 179	com/gtp/go/weather/sharephoto/c/n:d	Lcom/gtp/go/weather/sharephoto/b/l;
    //   1765: getfield 182	com/gtp/go/weather/sharephoto/b/l:a	I
    //   1768: iconst_1
    //   1769: if_icmpne +182 -> 1951
    //   1772: ldc_w 352
    //   1775: astore 8
    //   1777: ldc -13
    //   1779: new 68	java/lang/StringBuilder
    //   1782: dup
    //   1783: invokespecial 69	java/lang/StringBuilder:<init>	()V
    //   1786: ldc_w 354
    //   1789: invokevirtual 75	java/lang/StringBuilder:append	(Ljava/lang/String;)Ljava/lang/StringBuilder;
    //   1792: aload 8
    //   1794: invokevirtual 75	java/lang/StringBuilder:append	(Ljava/lang/String;)Ljava/lang/StringBuilder;
    //   1797: invokevirtual 87	java/lang/StringBuilder:toString	()Ljava/lang/String;
    //   1800: invokestatic 251	com/gtp/a/a/b/c:a	(Ljava/lang/String;Ljava/lang/String;)V
    //   1803: aload_0
    //   1804: getfield 61	com/gtp/go/weather/sharephoto/c/n:c	Lcom/jiubang/goweather/b/f;
    //   1807: invokevirtual 356	com/jiubang/goweather/b/f:m	()Ljava/lang/String;
    //   1810: astore 9
    //   1812: ldc -13
    //   1814: new 68	java/lang/StringBuilder
    //   1817: dup
    //   1818: invokespecial 69	java/lang/StringBuilder:<init>	()V
    //   1821: ldc_w 358
    //   1824: invokevirtual 75	java/lang/StringBuilder:append	(Ljava/lang/String;)Ljava/lang/StringBuilder;
    //   1827: aload 9
    //   1829: invokevirtual 75	java/lang/StringBuilder:append	(Ljava/lang/String;)Ljava/lang/StringBuilder;
    //   1832: invokevirtual 87	java/lang/StringBuilder:toString	()Ljava/lang/String;
    //   1835: invokestatic 251	com/gtp/a/a/b/c:a	(Ljava/lang/String;Ljava/lang/String;)V
    //   1838: invokestatic 66	com/gtp/a/a/a/a:a	()Lcom/gtp/a/a/a/a;
    //   1841: new 68	java/lang/StringBuilder
    //   1844: dup
    //   1845: invokespecial 69	java/lang/StringBuilder:<init>	()V
    //   1848: ldc_w 360
    //   1851: invokevirtual 75	java/lang/StringBuilder:append	(Ljava/lang/String;)Ljava/lang/StringBuilder;
    //   1854: aload 8
    //   1856: invokevirtual 75	java/lang/StringBuilder:append	(Ljava/lang/String;)Ljava/lang/StringBuilder;
    //   1859: invokevirtual 87	java/lang/StringBuilder:toString	()Ljava/lang/String;
    //   1862: ldc 89
    //   1864: invokevirtual 92	com/gtp/a/a/a/a:a	(Ljava/lang/String;Ljava/lang/String;)V
    //   1867: invokestatic 66	com/gtp/a/a/a/a:a	()Lcom/gtp/a/a/a/a;
    //   1870: new 68	java/lang/StringBuilder
    //   1873: dup
    //   1874: invokespecial 69	java/lang/StringBuilder:<init>	()V
    //   1877: ldc_w 362
    //   1880: invokevirtual 75	java/lang/StringBuilder:append	(Ljava/lang/String;)Ljava/lang/StringBuilder;
    //   1883: aload 9
    //   1885: invokevirtual 75	java/lang/StringBuilder:append	(Ljava/lang/String;)Ljava/lang/StringBuilder;
    //   1888: invokevirtual 87	java/lang/StringBuilder:toString	()Ljava/lang/String;
    //   1891: ldc 89
    //   1893: invokevirtual 92	com/gtp/a/a/a/a:a	(Ljava/lang/String;Ljava/lang/String;)V
    //   1896: return
    //   1897: astore 8
    //   1899: invokestatic 211	com/gtp/a/a/b/c:a	()Z
    //   1902: ifeq -1892 -> 10
    //   1905: aload 8
    //   1907: invokevirtual 214	java/io/UnsupportedEncodingException:printStackTrace	()V
    //   1910: return
    //   1911: astore 16
    //   1913: aload 12
    //   1915: astore 11
    //   1917: invokestatic 211	com/gtp/a/a/b/c:a	()Z
    //   1920: ifeq -470 -> 1450
    //   1923: aload 16
    //   1925: invokevirtual 214	java/io/UnsupportedEncodingException:printStackTrace	()V
    //   1928: aload 12
    //   1930: astore 11
    //   1932: goto -482 -> 1450
    //   1935: astore 8
    //   1937: invokestatic 211	com/gtp/a/a/b/c:a	()Z
    //   1940: ifeq -344 -> 1596
    //   1943: aload 8
    //   1945: invokevirtual 252	org/json/JSONException:printStackTrace	()V
    //   1948: goto -352 -> 1596
    //   1951: aload 9
    //   1953: astore 8
    //   1955: aload_0
    //   1956: getfield 179	com/gtp/go/weather/sharephoto/c/n:d	Lcom/gtp/go/weather/sharephoto/b/l;
    //   1959: getfield 182	com/gtp/go/weather/sharephoto/b/l:a	I
    //   1962: bipush 11
    //   1964: if_icmpne -187 -> 1777
    //   1967: ldc_w 364
    //   1970: astore 8
    //   1972: goto -195 -> 1777
    //   1975: goto -1216 -> 759
    //   1978: iload_1
    //   1979: istore_3
    //   1980: iload_2
    //   1981: istore_1
    //   1982: iload_3
    //   1983: istore_2
    //   1984: goto -1591 -> 393
    //   1987: aconst_null
    //   1988: astore 10
    //   1990: goto -1917 -> 73
    // Local variable table:
    //   start	length	slot	name	signature
    //   0	1993	0	this	n
    //   342	1640	1	i	int
    //   344	1640	2	j	int
    //   381	1602	3	k	int
    //   645	1085	4	l1	long
    //   653	309	6	l2	long
    //   158	676	8	localObject1	Object
    //   846	9	8	localJSONException1	org.json.JSONException
    //   860	995	8	localObject2	Object
    //   1897	9	8	localUnsupportedEncodingException1	java.io.UnsupportedEncodingException
    //   1935	9	8	localJSONException2	org.json.JSONException
    //   1953	18	8	localObject3	Object
    //   241	1711	9	localObject4	Object
    //   71	1918	10	localFile1	java.io.File
    //   131	1800	11	localObject5	Object
    //   170	1759	12	str	String
    //   45	1586	13	localFile2	java.io.File
    //   238	1229	14	localc	com.jiubang.goweather.b.c
    //   402	13	15	localUnsupportedEncodingException2	java.io.UnsupportedEncodingException
    //   553	918	15	localObject6	Object
    //   1911	13	16	localUnsupportedEncodingException3	java.io.UnsupportedEncodingException
    // Exception table:
    //   from	to	target	type
    //   243	250	402	java/io/UnsupportedEncodingException
    //   293	341	846	org/json/JSONException
    //   345	354	846	org/json/JSONException
    //   354	382	846	org/json/JSONException
    //   426	435	846	org/json/JSONException
    //   448	479	846	org/json/JSONException
    //   483	514	846	org/json/JSONException
    //   762	843	846	org/json/JSONException
    //   1116	1237	1897	java/io/UnsupportedEncodingException
    //   1443	1450	1911	java/io/UnsupportedEncodingException
    //   1575	1596	1935	org/json/JSONException
  }
  
  public e c()
  {
    return this.a;
  }
}


/* Location:              /Users/amaurremi/uw/stringoid/static-dynamic-comparison/apps/go weather ex/com.gau.go.launcherex.gowidget.weatherwidget-124-dex2jar.jar!/com/gtp/go/weather/sharephoto/c/n.class
 * Java compiler version: 6 (50.0)
 * JD-Core Version:       0.7.1
 */