package com.google.android.gms.maps.internal;

import android.os.IBinder;

class ar
  implements m
{
  private IBinder a;
  
  ar(IBinder paramIBinder)
  {
    this.a = paramIBinder;
  }
  
  public IBinder asBinder()
  {
    return this.a;
  }
  
  /* Error */
  public void b(com.google.android.gms.maps.model.internal.f paramf)
  {
    // Byte code:
    //   0: invokestatic 26	android/os/Parcel:obtain	()Landroid/os/Parcel;
    //   3: astore_2
    //   4: invokestatic 26	android/os/Parcel:obtain	()Landroid/os/Parcel;
    //   7: astore_3
    //   8: aload_2
    //   9: ldc 28
    //   11: invokevirtual 32	android/os/Parcel:writeInterfaceToken	(Ljava/lang/String;)V
    //   14: aload_1
    //   15: ifnull +42 -> 57
    //   18: aload_1
    //   19: invokeinterface 36 1 0
    //   24: astore_1
    //   25: aload_2
    //   26: aload_1
    //   27: invokevirtual 39	android/os/Parcel:writeStrongBinder	(Landroid/os/IBinder;)V
    //   30: aload_0
    //   31: getfield 15	com/google/android/gms/maps/internal/ar:a	Landroid/os/IBinder;
    //   34: iconst_1
    //   35: aload_2
    //   36: aload_3
    //   37: iconst_0
    //   38: invokeinterface 45 5 0
    //   43: pop
    //   44: aload_3
    //   45: invokevirtual 48	android/os/Parcel:readException	()V
    //   48: aload_3
    //   49: invokevirtual 51	android/os/Parcel:recycle	()V
    //   52: aload_2
    //   53: invokevirtual 51	android/os/Parcel:recycle	()V
    //   56: return
    //   57: aconst_null
    //   58: astore_1
    //   59: goto -34 -> 25
    //   62: astore_1
    //   63: aload_3
    //   64: invokevirtual 51	android/os/Parcel:recycle	()V
    //   67: aload_2
    //   68: invokevirtual 51	android/os/Parcel:recycle	()V
    //   71: aload_1
    //   72: athrow
    // Local variable table:
    //   start	length	slot	name	signature
    //   0	73	0	this	ar
    //   0	73	1	paramf	com.google.android.gms.maps.model.internal.f
    //   3	65	2	localParcel1	android.os.Parcel
    //   7	57	3	localParcel2	android.os.Parcel
    // Exception table:
    //   from	to	target	type
    //   8	14	62	finally
    //   18	25	62	finally
    //   25	48	62	finally
  }
  
  /* Error */
  public void c(com.google.android.gms.maps.model.internal.f paramf)
  {
    // Byte code:
    //   0: invokestatic 26	android/os/Parcel:obtain	()Landroid/os/Parcel;
    //   3: astore_2
    //   4: invokestatic 26	android/os/Parcel:obtain	()Landroid/os/Parcel;
    //   7: astore_3
    //   8: aload_2
    //   9: ldc 28
    //   11: invokevirtual 32	android/os/Parcel:writeInterfaceToken	(Ljava/lang/String;)V
    //   14: aload_1
    //   15: ifnull +42 -> 57
    //   18: aload_1
    //   19: invokeinterface 36 1 0
    //   24: astore_1
    //   25: aload_2
    //   26: aload_1
    //   27: invokevirtual 39	android/os/Parcel:writeStrongBinder	(Landroid/os/IBinder;)V
    //   30: aload_0
    //   31: getfield 15	com/google/android/gms/maps/internal/ar:a	Landroid/os/IBinder;
    //   34: iconst_3
    //   35: aload_2
    //   36: aload_3
    //   37: iconst_0
    //   38: invokeinterface 45 5 0
    //   43: pop
    //   44: aload_3
    //   45: invokevirtual 48	android/os/Parcel:readException	()V
    //   48: aload_3
    //   49: invokevirtual 51	android/os/Parcel:recycle	()V
    //   52: aload_2
    //   53: invokevirtual 51	android/os/Parcel:recycle	()V
    //   56: return
    //   57: aconst_null
    //   58: astore_1
    //   59: goto -34 -> 25
    //   62: astore_1
    //   63: aload_3
    //   64: invokevirtual 51	android/os/Parcel:recycle	()V
    //   67: aload_2
    //   68: invokevirtual 51	android/os/Parcel:recycle	()V
    //   71: aload_1
    //   72: athrow
    // Local variable table:
    //   start	length	slot	name	signature
    //   0	73	0	this	ar
    //   0	73	1	paramf	com.google.android.gms.maps.model.internal.f
    //   3	65	2	localParcel1	android.os.Parcel
    //   7	57	3	localParcel2	android.os.Parcel
    // Exception table:
    //   from	to	target	type
    //   8	14	62	finally
    //   18	25	62	finally
    //   25	48	62	finally
  }
  
  /* Error */
  public void d(com.google.android.gms.maps.model.internal.f paramf)
  {
    // Byte code:
    //   0: invokestatic 26	android/os/Parcel:obtain	()Landroid/os/Parcel;
    //   3: astore_2
    //   4: invokestatic 26	android/os/Parcel:obtain	()Landroid/os/Parcel;
    //   7: astore_3
    //   8: aload_2
    //   9: ldc 28
    //   11: invokevirtual 32	android/os/Parcel:writeInterfaceToken	(Ljava/lang/String;)V
    //   14: aload_1
    //   15: ifnull +42 -> 57
    //   18: aload_1
    //   19: invokeinterface 36 1 0
    //   24: astore_1
    //   25: aload_2
    //   26: aload_1
    //   27: invokevirtual 39	android/os/Parcel:writeStrongBinder	(Landroid/os/IBinder;)V
    //   30: aload_0
    //   31: getfield 15	com/google/android/gms/maps/internal/ar:a	Landroid/os/IBinder;
    //   34: iconst_2
    //   35: aload_2
    //   36: aload_3
    //   37: iconst_0
    //   38: invokeinterface 45 5 0
    //   43: pop
    //   44: aload_3
    //   45: invokevirtual 48	android/os/Parcel:readException	()V
    //   48: aload_3
    //   49: invokevirtual 51	android/os/Parcel:recycle	()V
    //   52: aload_2
    //   53: invokevirtual 51	android/os/Parcel:recycle	()V
    //   56: return
    //   57: aconst_null
    //   58: astore_1
    //   59: goto -34 -> 25
    //   62: astore_1
    //   63: aload_3
    //   64: invokevirtual 51	android/os/Parcel:recycle	()V
    //   67: aload_2
    //   68: invokevirtual 51	android/os/Parcel:recycle	()V
    //   71: aload_1
    //   72: athrow
    // Local variable table:
    //   start	length	slot	name	signature
    //   0	73	0	this	ar
    //   0	73	1	paramf	com.google.android.gms.maps.model.internal.f
    //   3	65	2	localParcel1	android.os.Parcel
    //   7	57	3	localParcel2	android.os.Parcel
    // Exception table:
    //   from	to	target	type
    //   8	14	62	finally
    //   18	25	62	finally
    //   25	48	62	finally
  }
}


/* Location:              /Users/amaurremi/uw/stringoid/static-dynamic-comparison/apps/retrica/com.venticake.retrica-21-dex2jar.jar!/com/google/android/gms/maps/internal/ar.class
 * Java compiler version: 6 (50.0)
 * JD-Core Version:       0.7.1
 */