package com.google.android.gms.wearable.internal;

import android.os.Binder;
import android.os.IBinder;
import android.os.IInterface;
import android.os.Parcel;
import android.os.Parcelable.Creator;
import android.os.RemoteException;
import com.google.android.gms.common.data.DataHolder;
import com.google.android.gms.common.data.f;

public abstract interface ac
  extends IInterface
{
  public abstract void Y(DataHolder paramDataHolder)
    throws RemoteException;
  
  public abstract void a(af paramaf)
    throws RemoteException;
  
  public abstract void a(ai paramai)
    throws RemoteException;
  
  public abstract void b(ai paramai)
    throws RemoteException;
  
  public static abstract class a
    extends Binder
    implements ac
  {
    public a()
    {
      attachInterface(this, "com.google.android.gms.wearable.internal.IWearableListener");
    }
    
    public static ac bx(IBinder paramIBinder)
    {
      if (paramIBinder == null) {
        return null;
      }
      IInterface localIInterface = paramIBinder.queryLocalInterface("com.google.android.gms.wearable.internal.IWearableListener");
      if ((localIInterface != null) && ((localIInterface instanceof ac))) {
        return (ac)localIInterface;
      }
      return new a(paramIBinder);
    }
    
    public IBinder asBinder()
    {
      return this;
    }
    
    public boolean onTransact(int paramInt1, Parcel paramParcel1, Parcel paramParcel2, int paramInt2)
      throws RemoteException
    {
      Object localObject2 = null;
      Object localObject3 = null;
      Object localObject4 = null;
      Object localObject1 = null;
      switch (paramInt1)
      {
      default: 
        return super.onTransact(paramInt1, paramParcel1, paramParcel2, paramInt2);
      case 1598968902: 
        paramParcel2.writeString("com.google.android.gms.wearable.internal.IWearableListener");
        return true;
      case 1: 
        paramParcel1.enforceInterface("com.google.android.gms.wearable.internal.IWearableListener");
        paramParcel2 = (Parcel)localObject1;
        if (paramParcel1.readInt() != 0) {
          paramParcel2 = DataHolder.CREATOR.x(paramParcel1);
        }
        Y(paramParcel2);
        return true;
      case 2: 
        paramParcel1.enforceInterface("com.google.android.gms.wearable.internal.IWearableListener");
        paramParcel2 = (Parcel)localObject2;
        if (paramParcel1.readInt() != 0) {
          paramParcel2 = (af)af.CREATOR.createFromParcel(paramParcel1);
        }
        a(paramParcel2);
        return true;
      case 3: 
        paramParcel1.enforceInterface("com.google.android.gms.wearable.internal.IWearableListener");
        paramParcel2 = (Parcel)localObject3;
        if (paramParcel1.readInt() != 0) {
          paramParcel2 = (ai)ai.CREATOR.createFromParcel(paramParcel1);
        }
        a(paramParcel2);
        return true;
      }
      paramParcel1.enforceInterface("com.google.android.gms.wearable.internal.IWearableListener");
      paramParcel2 = (Parcel)localObject4;
      if (paramParcel1.readInt() != 0) {
        paramParcel2 = (ai)ai.CREATOR.createFromParcel(paramParcel1);
      }
      b(paramParcel2);
      return true;
    }
    
    private static class a
      implements ac
    {
      private IBinder ko;
      
      a(IBinder paramIBinder)
      {
        this.ko = paramIBinder;
      }
      
      /* Error */
      public void Y(DataHolder paramDataHolder)
        throws RemoteException
      {
        // Byte code:
        //   0: invokestatic 29	android/os/Parcel:obtain	()Landroid/os/Parcel;
        //   3: astore_2
        //   4: aload_2
        //   5: ldc 31
        //   7: invokevirtual 35	android/os/Parcel:writeInterfaceToken	(Ljava/lang/String;)V
        //   10: aload_1
        //   11: ifnull +33 -> 44
        //   14: aload_2
        //   15: iconst_1
        //   16: invokevirtual 39	android/os/Parcel:writeInt	(I)V
        //   19: aload_1
        //   20: aload_2
        //   21: iconst_0
        //   22: invokevirtual 45	com/google/android/gms/common/data/DataHolder:writeToParcel	(Landroid/os/Parcel;I)V
        //   25: aload_0
        //   26: getfield 18	com/google/android/gms/wearable/internal/ac$a$a:ko	Landroid/os/IBinder;
        //   29: iconst_1
        //   30: aload_2
        //   31: aconst_null
        //   32: iconst_1
        //   33: invokeinterface 51 5 0
        //   38: pop
        //   39: aload_2
        //   40: invokevirtual 54	android/os/Parcel:recycle	()V
        //   43: return
        //   44: aload_2
        //   45: iconst_0
        //   46: invokevirtual 39	android/os/Parcel:writeInt	(I)V
        //   49: goto -24 -> 25
        //   52: astore_1
        //   53: aload_2
        //   54: invokevirtual 54	android/os/Parcel:recycle	()V
        //   57: aload_1
        //   58: athrow
        // Local variable table:
        //   start	length	slot	name	signature
        //   0	59	0	this	a
        //   0	59	1	paramDataHolder	DataHolder
        //   3	51	2	localParcel	Parcel
        // Exception table:
        //   from	to	target	type
        //   4	10	52	finally
        //   14	25	52	finally
        //   25	39	52	finally
        //   44	49	52	finally
      }
      
      /* Error */
      public void a(af paramaf)
        throws RemoteException
      {
        // Byte code:
        //   0: invokestatic 29	android/os/Parcel:obtain	()Landroid/os/Parcel;
        //   3: astore_2
        //   4: aload_2
        //   5: ldc 31
        //   7: invokevirtual 35	android/os/Parcel:writeInterfaceToken	(Ljava/lang/String;)V
        //   10: aload_1
        //   11: ifnull +33 -> 44
        //   14: aload_2
        //   15: iconst_1
        //   16: invokevirtual 39	android/os/Parcel:writeInt	(I)V
        //   19: aload_1
        //   20: aload_2
        //   21: iconst_0
        //   22: invokevirtual 59	com/google/android/gms/wearable/internal/af:writeToParcel	(Landroid/os/Parcel;I)V
        //   25: aload_0
        //   26: getfield 18	com/google/android/gms/wearable/internal/ac$a$a:ko	Landroid/os/IBinder;
        //   29: iconst_2
        //   30: aload_2
        //   31: aconst_null
        //   32: iconst_1
        //   33: invokeinterface 51 5 0
        //   38: pop
        //   39: aload_2
        //   40: invokevirtual 54	android/os/Parcel:recycle	()V
        //   43: return
        //   44: aload_2
        //   45: iconst_0
        //   46: invokevirtual 39	android/os/Parcel:writeInt	(I)V
        //   49: goto -24 -> 25
        //   52: astore_1
        //   53: aload_2
        //   54: invokevirtual 54	android/os/Parcel:recycle	()V
        //   57: aload_1
        //   58: athrow
        // Local variable table:
        //   start	length	slot	name	signature
        //   0	59	0	this	a
        //   0	59	1	paramaf	af
        //   3	51	2	localParcel	Parcel
        // Exception table:
        //   from	to	target	type
        //   4	10	52	finally
        //   14	25	52	finally
        //   25	39	52	finally
        //   44	49	52	finally
      }
      
      /* Error */
      public void a(ai paramai)
        throws RemoteException
      {
        // Byte code:
        //   0: invokestatic 29	android/os/Parcel:obtain	()Landroid/os/Parcel;
        //   3: astore_2
        //   4: aload_2
        //   5: ldc 31
        //   7: invokevirtual 35	android/os/Parcel:writeInterfaceToken	(Ljava/lang/String;)V
        //   10: aload_1
        //   11: ifnull +33 -> 44
        //   14: aload_2
        //   15: iconst_1
        //   16: invokevirtual 39	android/os/Parcel:writeInt	(I)V
        //   19: aload_1
        //   20: aload_2
        //   21: iconst_0
        //   22: invokevirtual 63	com/google/android/gms/wearable/internal/ai:writeToParcel	(Landroid/os/Parcel;I)V
        //   25: aload_0
        //   26: getfield 18	com/google/android/gms/wearable/internal/ac$a$a:ko	Landroid/os/IBinder;
        //   29: iconst_3
        //   30: aload_2
        //   31: aconst_null
        //   32: iconst_1
        //   33: invokeinterface 51 5 0
        //   38: pop
        //   39: aload_2
        //   40: invokevirtual 54	android/os/Parcel:recycle	()V
        //   43: return
        //   44: aload_2
        //   45: iconst_0
        //   46: invokevirtual 39	android/os/Parcel:writeInt	(I)V
        //   49: goto -24 -> 25
        //   52: astore_1
        //   53: aload_2
        //   54: invokevirtual 54	android/os/Parcel:recycle	()V
        //   57: aload_1
        //   58: athrow
        // Local variable table:
        //   start	length	slot	name	signature
        //   0	59	0	this	a
        //   0	59	1	paramai	ai
        //   3	51	2	localParcel	Parcel
        // Exception table:
        //   from	to	target	type
        //   4	10	52	finally
        //   14	25	52	finally
        //   25	39	52	finally
        //   44	49	52	finally
      }
      
      public IBinder asBinder()
      {
        return this.ko;
      }
      
      /* Error */
      public void b(ai paramai)
        throws RemoteException
      {
        // Byte code:
        //   0: invokestatic 29	android/os/Parcel:obtain	()Landroid/os/Parcel;
        //   3: astore_2
        //   4: aload_2
        //   5: ldc 31
        //   7: invokevirtual 35	android/os/Parcel:writeInterfaceToken	(Ljava/lang/String;)V
        //   10: aload_1
        //   11: ifnull +33 -> 44
        //   14: aload_2
        //   15: iconst_1
        //   16: invokevirtual 39	android/os/Parcel:writeInt	(I)V
        //   19: aload_1
        //   20: aload_2
        //   21: iconst_0
        //   22: invokevirtual 63	com/google/android/gms/wearable/internal/ai:writeToParcel	(Landroid/os/Parcel;I)V
        //   25: aload_0
        //   26: getfield 18	com/google/android/gms/wearable/internal/ac$a$a:ko	Landroid/os/IBinder;
        //   29: iconst_4
        //   30: aload_2
        //   31: aconst_null
        //   32: iconst_1
        //   33: invokeinterface 51 5 0
        //   38: pop
        //   39: aload_2
        //   40: invokevirtual 54	android/os/Parcel:recycle	()V
        //   43: return
        //   44: aload_2
        //   45: iconst_0
        //   46: invokevirtual 39	android/os/Parcel:writeInt	(I)V
        //   49: goto -24 -> 25
        //   52: astore_1
        //   53: aload_2
        //   54: invokevirtual 54	android/os/Parcel:recycle	()V
        //   57: aload_1
        //   58: athrow
        // Local variable table:
        //   start	length	slot	name	signature
        //   0	59	0	this	a
        //   0	59	1	paramai	ai
        //   3	51	2	localParcel	Parcel
        // Exception table:
        //   from	to	target	type
        //   4	10	52	finally
        //   14	25	52	finally
        //   25	39	52	finally
        //   44	49	52	finally
      }
    }
  }
}


/* Location:              /Users/amaurremi/uw/stringoid/static-dynamic-comparison/apps/broken screen/mobi.borken.android.brokenscreen-20-dex2jar.jar!/com/google/android/gms/wearable/internal/ac.class
 * Java compiler version: 6 (50.0)
 * JD-Core Version:       0.7.1
 */