package cmn;

import java.util.HashMap;
import java.util.Map;

public final class ae
{
  private ak a = null;
  private Map b = new HashMap();
  
  /* Error */
  public final void a(String paramString, ai paramai)
  {
    // Byte code:
    //   0: aload_0
    //   1: getfield 19	cmn/ae:b	Ljava/util/Map;
    //   4: astore 4
    //   6: aload 4
    //   8: monitorenter
    //   9: aload_2
    //   10: ifnull +94 -> 104
    //   13: aload_0
    //   14: getfield 19	cmn/ae:b	Ljava/util/Map;
    //   17: aload_1
    //   18: invokeinterface 29 2 0
    //   23: checkcast 31	java/util/List
    //   26: astore 5
    //   28: aload 5
    //   30: ifnull +43 -> 73
    //   33: aload 5
    //   35: aload_2
    //   36: invokeinterface 35 2 0
    //   41: pop
    //   42: iconst_1
    //   43: istore_3
    //   44: iload_3
    //   45: ifne +24 -> 69
    //   48: new 37	cmn/af
    //   51: dup
    //   52: aload_0
    //   53: aload_1
    //   54: invokespecial 40	cmn/af:<init>	(Lcmn/ae;Ljava/lang/String;)V
    //   57: iconst_1
    //   58: anewarray 42	java/lang/Void
    //   61: dup
    //   62: iconst_0
    //   63: aconst_null
    //   64: aastore
    //   65: invokevirtual 45	cmn/af:a	([Ljava/lang/Object;)Lcmn/g;
    //   68: pop
    //   69: aload 4
    //   71: monitorexit
    //   72: return
    //   73: new 47	java/util/ArrayList
    //   76: dup
    //   77: invokespecial 48	java/util/ArrayList:<init>	()V
    //   80: astore 5
    //   82: aload 5
    //   84: aload_2
    //   85: invokeinterface 35 2 0
    //   90: pop
    //   91: aload_0
    //   92: getfield 19	cmn/ae:b	Ljava/util/Map;
    //   95: aload_1
    //   96: aload 5
    //   98: invokeinterface 52 3 0
    //   103: pop
    //   104: iconst_0
    //   105: istore_3
    //   106: goto -62 -> 44
    //   109: astore_1
    //   110: aload 4
    //   112: monitorexit
    //   113: aload_1
    //   114: athrow
    // Local variable table:
    //   start	length	slot	name	signature
    //   0	115	0	this	ae
    //   0	115	1	paramString	String
    //   0	115	2	paramai	ai
    //   43	63	3	i	int
    //   4	107	4	localMap	Map
    //   26	71	5	localObject	Object
    // Exception table:
    //   from	to	target	type
    //   13	28	109	finally
    //   33	42	109	finally
    //   48	69	109	finally
    //   69	72	109	finally
    //   73	104	109	finally
  }
}


/* Location:              /Users/amaurremi/uw/stringoid/static-dynamic-comparison/apps/xperia z/com.androidwasabi.livewallpaper.xperiaz-13-dex2jar.jar!/cmn/ae.class
 * Java compiler version: 6 (50.0)
 * JD-Core Version:       0.7.1
 */