package cmn;

final class al
  implements Runnable
{
  al(ak paramak, Object paramObject, ai paramai) {}
  
  /* Error */
  public final void run()
  {
    // Byte code:
    //   0: new 29	java/io/ObjectInputStream
    //   3: dup
    //   4: new 31	java/io/FileInputStream
    //   7: dup
    //   8: aload_0
    //   9: getfield 16	cmn/al:c	Lcmn/ak;
    //   12: aload_0
    //   13: getfield 18	cmn/al:a	Ljava/lang/Object;
    //   16: invokevirtual 36	cmn/ak:a	(Ljava/lang/Object;)Ljava/lang/String;
    //   19: invokespecial 39	java/io/FileInputStream:<init>	(Ljava/lang/String;)V
    //   22: invokespecial 42	java/io/ObjectInputStream:<init>	(Ljava/io/InputStream;)V
    //   25: astore_3
    //   26: aload_3
    //   27: invokevirtual 46	java/io/ObjectInputStream:readObject	()Ljava/lang/Object;
    //   30: aload_0
    //   31: getfield 18	cmn/al:a	Ljava/lang/Object;
    //   34: invokevirtual 50	java/lang/Object:equals	(Ljava/lang/Object;)Z
    //   37: ifne +18 -> 55
    //   40: aload_0
    //   41: getfield 20	cmn/al:b	Lcmn/ai;
    //   44: aconst_null
    //   45: invokeinterface 55 2 0
    //   50: aload_3
    //   51: invokevirtual 58	java/io/ObjectInputStream:close	()V
    //   54: return
    //   55: aload_3
    //   56: invokevirtual 62	java/io/ObjectInputStream:readLong	()J
    //   59: lstore_1
    //   60: aload_0
    //   61: getfield 16	cmn/al:c	Lcmn/ak;
    //   64: invokestatic 65	cmn/ak:a	(Lcmn/ak;)I
    //   67: ifle +62 -> 129
    //   70: lload_1
    //   71: invokestatic 70	java/lang/System:currentTimeMillis	()J
    //   74: ldc2_w 71
    //   77: aload_0
    //   78: getfield 16	cmn/al:c	Lcmn/ak;
    //   81: invokestatic 65	cmn/ak:a	(Lcmn/ak;)I
    //   84: i2l
    //   85: lmul
    //   86: lsub
    //   87: lcmp
    //   88: ifge +41 -> 129
    //   91: aload_0
    //   92: getfield 16	cmn/al:c	Lcmn/ak;
    //   95: aload_0
    //   96: getfield 18	cmn/al:a	Ljava/lang/Object;
    //   99: invokevirtual 74	cmn/ak:b	(Ljava/lang/Object;)V
    //   102: aload_0
    //   103: getfield 20	cmn/al:b	Lcmn/ai;
    //   106: aconst_null
    //   107: invokeinterface 55 2 0
    //   112: aload_3
    //   113: invokevirtual 58	java/io/ObjectInputStream:close	()V
    //   116: return
    //   117: astore_3
    //   118: aload_0
    //   119: getfield 20	cmn/al:b	Lcmn/ai;
    //   122: aconst_null
    //   123: invokeinterface 55 2 0
    //   128: return
    //   129: aload_3
    //   130: invokevirtual 46	java/io/ObjectInputStream:readObject	()Ljava/lang/Object;
    //   133: astore 4
    //   135: new 76	java/lang/StringBuilder
    //   138: dup
    //   139: ldc 78
    //   141: invokespecial 79	java/lang/StringBuilder:<init>	(Ljava/lang/String;)V
    //   144: new 81	java/io/File
    //   147: dup
    //   148: aload_0
    //   149: getfield 16	cmn/al:c	Lcmn/ak;
    //   152: aload_0
    //   153: getfield 18	cmn/al:a	Ljava/lang/Object;
    //   156: invokevirtual 36	cmn/ak:a	(Ljava/lang/Object;)Ljava/lang/String;
    //   159: invokespecial 82	java/io/File:<init>	(Ljava/lang/String;)V
    //   162: invokevirtual 85	java/io/File:length	()J
    //   165: invokevirtual 89	java/lang/StringBuilder:append	(J)Ljava/lang/StringBuilder;
    //   168: ldc 91
    //   170: invokevirtual 94	java/lang/StringBuilder:append	(Ljava/lang/String;)Ljava/lang/StringBuilder;
    //   173: aload_0
    //   174: getfield 18	cmn/al:a	Ljava/lang/Object;
    //   177: invokevirtual 97	java/lang/StringBuilder:append	(Ljava/lang/Object;)Ljava/lang/StringBuilder;
    //   180: invokevirtual 101	java/lang/StringBuilder:toString	()Ljava/lang/String;
    //   183: pop
    //   184: aload_0
    //   185: getfield 20	cmn/al:b	Lcmn/ai;
    //   188: aload 4
    //   190: invokeinterface 55 2 0
    //   195: aload_3
    //   196: invokevirtual 58	java/io/ObjectInputStream:close	()V
    //   199: return
    //   200: astore 4
    //   202: aload_3
    //   203: invokevirtual 58	java/io/ObjectInputStream:close	()V
    //   206: aload 4
    //   208: athrow
    // Local variable table:
    //   start	length	slot	name	signature
    //   0	209	0	this	al
    //   59	12	1	l	long
    //   25	88	3	localObjectInputStream	java.io.ObjectInputStream
    //   117	86	3	localException	Exception
    //   133	56	4	localObject1	Object
    //   200	7	4	localObject2	Object
    // Exception table:
    //   from	to	target	type
    //   0	26	117	java/lang/Exception
    //   50	54	117	java/lang/Exception
    //   112	116	117	java/lang/Exception
    //   195	199	117	java/lang/Exception
    //   202	209	117	java/lang/Exception
    //   26	50	200	finally
    //   55	112	200	finally
    //   129	195	200	finally
  }
}


/* Location:              /Users/amaurremi/uw/stringoid/static-dynamic-comparison/apps/xperia z/com.androidwasabi.livewallpaper.xperiaz-13-dex2jar.jar!/cmn/al.class
 * Java compiler version: 6 (50.0)
 * JD-Core Version:       0.7.1
 */