package com.gau.go.launcherex.gowidget.statistics;

import android.content.Context;

class l
  implements Runnable
{
  private final String b;
  private final String c;
  private final Context d;
  
  public l(j paramj, String paramString1, String paramString2, Context paramContext)
  {
    this.b = paramString1;
    this.c = paramString2;
    this.d = paramContext;
  }
  
  /* Error */
  public void run()
  {
    // Byte code:
    //   0: aconst_null
    //   1: astore 6
    //   3: aconst_null
    //   4: astore 7
    //   6: aconst_null
    //   7: astore 4
    //   9: aconst_null
    //   10: astore_2
    //   11: aconst_null
    //   12: astore 5
    //   14: bipush 19
    //   16: invokestatic 40	android/os/Process:setThreadPriority	(I)V
    //   19: aload_0
    //   20: getfield 26	com/gau/go/launcherex/gowidget/statistics/l:d	Landroid/content/Context;
    //   23: aload_0
    //   24: getfield 24	com/gau/go/launcherex/gowidget/statistics/l:c	Ljava/lang/String;
    //   27: invokevirtual 46	android/content/Context:getFileStreamPath	(Ljava/lang/String;)Ljava/io/File;
    //   30: astore_1
    //   31: aload_1
    //   32: invokevirtual 52	java/io/File:exists	()Z
    //   35: ifne +8 -> 43
    //   38: aload_1
    //   39: invokevirtual 55	java/io/File:createNewFile	()Z
    //   42: pop
    //   43: aload_1
    //   44: invokevirtual 52	java/io/File:exists	()Z
    //   47: ifeq +347 -> 394
    //   50: aload_0
    //   51: getfield 26	com/gau/go/launcherex/gowidget/statistics/l:d	Landroid/content/Context;
    //   54: aload_0
    //   55: getfield 24	com/gau/go/launcherex/gowidget/statistics/l:c	Ljava/lang/String;
    //   58: ldc 56
    //   60: invokevirtual 60	android/content/Context:openFileOutput	(Ljava/lang/String;I)Ljava/io/FileOutputStream;
    //   63: astore_1
    //   64: aload_2
    //   65: astore 4
    //   67: aload_1
    //   68: astore_3
    //   69: new 62	java/io/OutputStreamWriter
    //   72: dup
    //   73: aload_1
    //   74: ldc 64
    //   76: invokespecial 67	java/io/OutputStreamWriter:<init>	(Ljava/io/OutputStream;Ljava/lang/String;)V
    //   79: astore_2
    //   80: aload_2
    //   81: new 69	java/lang/StringBuilder
    //   84: dup
    //   85: invokespecial 70	java/lang/StringBuilder:<init>	()V
    //   88: aload_0
    //   89: getfield 22	com/gau/go/launcherex/gowidget/statistics/l:b	Ljava/lang/String;
    //   92: invokevirtual 74	java/lang/StringBuilder:append	(Ljava/lang/String;)Ljava/lang/StringBuilder;
    //   95: ldc 76
    //   97: invokevirtual 74	java/lang/StringBuilder:append	(Ljava/lang/String;)Ljava/lang/StringBuilder;
    //   100: invokevirtual 80	java/lang/StringBuilder:toString	()Ljava/lang/String;
    //   103: invokevirtual 84	java/io/OutputStreamWriter:write	(Ljava/lang/String;)V
    //   106: aload_2
    //   107: invokevirtual 87	java/io/OutputStreamWriter:flush	()V
    //   110: aload_2
    //   111: ifnull +7 -> 118
    //   114: aload_2
    //   115: invokevirtual 90	java/io/OutputStreamWriter:close	()V
    //   118: aload_1
    //   119: ifnull +7 -> 126
    //   122: aload_1
    //   123: invokevirtual 93	java/io/FileOutputStream:close	()V
    //   126: return
    //   127: astore_2
    //   128: aload_2
    //   129: invokevirtual 96	java/io/IOException:printStackTrace	()V
    //   132: goto -14 -> 118
    //   135: astore_1
    //   136: aload_1
    //   137: invokevirtual 96	java/io/IOException:printStackTrace	()V
    //   140: return
    //   141: astore_2
    //   142: aconst_null
    //   143: astore_1
    //   144: aload 5
    //   146: astore 4
    //   148: aload_2
    //   149: invokevirtual 97	java/io/FileNotFoundException:printStackTrace	()V
    //   152: aload 4
    //   154: ifnull +8 -> 162
    //   157: aload 4
    //   159: invokevirtual 90	java/io/OutputStreamWriter:close	()V
    //   162: aload_1
    //   163: ifnull -37 -> 126
    //   166: aload_1
    //   167: invokevirtual 93	java/io/FileOutputStream:close	()V
    //   170: return
    //   171: astore_1
    //   172: aload_1
    //   173: invokevirtual 96	java/io/IOException:printStackTrace	()V
    //   176: return
    //   177: astore_2
    //   178: aload_2
    //   179: invokevirtual 96	java/io/IOException:printStackTrace	()V
    //   182: goto -20 -> 162
    //   185: astore_2
    //   186: aconst_null
    //   187: astore_1
    //   188: aload 6
    //   190: astore 5
    //   192: aload 5
    //   194: astore 4
    //   196: aload_1
    //   197: astore_3
    //   198: aload_2
    //   199: invokevirtual 98	java/io/UnsupportedEncodingException:printStackTrace	()V
    //   202: aload 5
    //   204: ifnull +8 -> 212
    //   207: aload 5
    //   209: invokevirtual 90	java/io/OutputStreamWriter:close	()V
    //   212: aload_1
    //   213: ifnull -87 -> 126
    //   216: aload_1
    //   217: invokevirtual 93	java/io/FileOutputStream:close	()V
    //   220: return
    //   221: astore_1
    //   222: aload_1
    //   223: invokevirtual 96	java/io/IOException:printStackTrace	()V
    //   226: return
    //   227: astore_2
    //   228: aload_2
    //   229: invokevirtual 96	java/io/IOException:printStackTrace	()V
    //   232: goto -20 -> 212
    //   235: astore_2
    //   236: aconst_null
    //   237: astore_1
    //   238: aload 7
    //   240: astore 5
    //   242: aload 5
    //   244: astore 4
    //   246: aload_1
    //   247: astore_3
    //   248: aload_2
    //   249: invokevirtual 96	java/io/IOException:printStackTrace	()V
    //   252: aload 5
    //   254: ifnull +8 -> 262
    //   257: aload 5
    //   259: invokevirtual 90	java/io/OutputStreamWriter:close	()V
    //   262: aload_1
    //   263: ifnull -137 -> 126
    //   266: aload_1
    //   267: invokevirtual 93	java/io/FileOutputStream:close	()V
    //   270: return
    //   271: astore_1
    //   272: aload_1
    //   273: invokevirtual 96	java/io/IOException:printStackTrace	()V
    //   276: return
    //   277: astore_2
    //   278: aload_2
    //   279: invokevirtual 96	java/io/IOException:printStackTrace	()V
    //   282: goto -20 -> 262
    //   285: astore_2
    //   286: aconst_null
    //   287: astore_1
    //   288: aload 4
    //   290: ifnull +8 -> 298
    //   293: aload 4
    //   295: invokevirtual 90	java/io/OutputStreamWriter:close	()V
    //   298: aload_1
    //   299: ifnull +7 -> 306
    //   302: aload_1
    //   303: invokevirtual 93	java/io/FileOutputStream:close	()V
    //   306: aload_2
    //   307: athrow
    //   308: astore_3
    //   309: aload_3
    //   310: invokevirtual 96	java/io/IOException:printStackTrace	()V
    //   313: goto -15 -> 298
    //   316: astore_1
    //   317: aload_1
    //   318: invokevirtual 96	java/io/IOException:printStackTrace	()V
    //   321: goto -15 -> 306
    //   324: astore_2
    //   325: aload_3
    //   326: astore_1
    //   327: goto -39 -> 288
    //   330: astore_3
    //   331: aload_2
    //   332: astore 4
    //   334: aload_3
    //   335: astore_2
    //   336: goto -48 -> 288
    //   339: astore_2
    //   340: goto -52 -> 288
    //   343: astore_2
    //   344: aload 7
    //   346: astore 5
    //   348: goto -106 -> 242
    //   351: astore_3
    //   352: aload_2
    //   353: astore 5
    //   355: aload_3
    //   356: astore_2
    //   357: goto -115 -> 242
    //   360: astore_2
    //   361: aload 6
    //   363: astore 5
    //   365: goto -173 -> 192
    //   368: astore_3
    //   369: aload_2
    //   370: astore 5
    //   372: aload_3
    //   373: astore_2
    //   374: goto -182 -> 192
    //   377: astore_2
    //   378: aload 5
    //   380: astore 4
    //   382: goto -234 -> 148
    //   385: astore_3
    //   386: aload_2
    //   387: astore 4
    //   389: aload_3
    //   390: astore_2
    //   391: goto -243 -> 148
    //   394: aconst_null
    //   395: astore_2
    //   396: aconst_null
    //   397: astore_1
    //   398: goto -288 -> 110
    // Local variable table:
    //   start	length	slot	name	signature
    //   0	401	0	this	l
    //   30	93	1	localObject1	Object
    //   135	2	1	localIOException1	java.io.IOException
    //   143	24	1	localObject2	Object
    //   171	2	1	localIOException2	java.io.IOException
    //   187	30	1	localObject3	Object
    //   221	2	1	localIOException3	java.io.IOException
    //   237	30	1	localObject4	Object
    //   271	2	1	localIOException4	java.io.IOException
    //   287	16	1	localObject5	Object
    //   316	2	1	localIOException5	java.io.IOException
    //   326	72	1	localObject6	Object
    //   10	105	2	localOutputStreamWriter	java.io.OutputStreamWriter
    //   127	2	2	localIOException6	java.io.IOException
    //   141	8	2	localFileNotFoundException1	java.io.FileNotFoundException
    //   177	2	2	localIOException7	java.io.IOException
    //   185	14	2	localUnsupportedEncodingException1	java.io.UnsupportedEncodingException
    //   227	2	2	localIOException8	java.io.IOException
    //   235	14	2	localIOException9	java.io.IOException
    //   277	2	2	localIOException10	java.io.IOException
    //   285	22	2	localObject7	Object
    //   324	8	2	localObject8	Object
    //   335	1	2	localObject9	Object
    //   339	1	2	localObject10	Object
    //   343	10	2	localIOException11	java.io.IOException
    //   356	1	2	localObject11	Object
    //   360	10	2	localUnsupportedEncodingException2	java.io.UnsupportedEncodingException
    //   373	1	2	localObject12	Object
    //   377	10	2	localFileNotFoundException2	java.io.FileNotFoundException
    //   390	6	2	localObject13	Object
    //   68	180	3	localObject14	Object
    //   308	18	3	localIOException12	java.io.IOException
    //   330	5	3	localObject15	Object
    //   351	5	3	localIOException13	java.io.IOException
    //   368	5	3	localUnsupportedEncodingException3	java.io.UnsupportedEncodingException
    //   385	5	3	localFileNotFoundException3	java.io.FileNotFoundException
    //   7	381	4	localObject16	Object
    //   12	367	5	localObject17	Object
    //   1	361	6	localObject18	Object
    //   4	341	7	localObject19	Object
    // Exception table:
    //   from	to	target	type
    //   114	118	127	java/io/IOException
    //   122	126	135	java/io/IOException
    //   19	43	141	java/io/FileNotFoundException
    //   43	64	141	java/io/FileNotFoundException
    //   166	170	171	java/io/IOException
    //   157	162	177	java/io/IOException
    //   19	43	185	java/io/UnsupportedEncodingException
    //   43	64	185	java/io/UnsupportedEncodingException
    //   216	220	221	java/io/IOException
    //   207	212	227	java/io/IOException
    //   19	43	235	java/io/IOException
    //   43	64	235	java/io/IOException
    //   266	270	271	java/io/IOException
    //   257	262	277	java/io/IOException
    //   19	43	285	finally
    //   43	64	285	finally
    //   293	298	308	java/io/IOException
    //   302	306	316	java/io/IOException
    //   69	80	324	finally
    //   198	202	324	finally
    //   248	252	324	finally
    //   80	110	330	finally
    //   148	152	339	finally
    //   69	80	343	java/io/IOException
    //   80	110	351	java/io/IOException
    //   69	80	360	java/io/UnsupportedEncodingException
    //   80	110	368	java/io/UnsupportedEncodingException
    //   69	80	377	java/io/FileNotFoundException
    //   80	110	385	java/io/FileNotFoundException
  }
}


/* Location:              /Users/amaurremi/uw/stringoid/static-dynamic-comparison/apps/go weather ex/com.gau.go.launcherex.gowidget.weatherwidget-124-dex2jar.jar!/com/gau/go/launcherex/gowidget/statistics/l.class
 * Java compiler version: 6 (50.0)
 * JD-Core Version:       0.7.1
 */