package com.gtp.nextlauncher.widget.weatherwidget;

import android.os.Handler;

class a
  extends Handler
{
  a(Base paramBase) {}
  
  /* Error */
  public void handleMessage(android.os.Message paramMessage)
  {
    // Byte code:
    //   0: aload_0
    //   1: monitorenter
    //   2: aload_0
    //   3: getfield 10	com/gtp/nextlauncher/widget/weatherwidget/a:a	Lcom/gtp/nextlauncher/widget/weatherwidget/Base;
    //   6: iconst_1
    //   7: invokestatic 22	com/gtp/nextlauncher/widget/weatherwidget/Base:access$002	(Lcom/gtp/nextlauncher/widget/weatherwidget/Base;Z)Z
    //   10: pop
    //   11: aload_0
    //   12: getfield 10	com/gtp/nextlauncher/widget/weatherwidget/a:a	Lcom/gtp/nextlauncher/widget/weatherwidget/Base;
    //   15: invokestatic 26	com/gtp/nextlauncher/widget/weatherwidget/Base:access$100	(Lcom/gtp/nextlauncher/widget/weatherwidget/Base;)Z
    //   18: ifeq +22 -> 40
    //   21: aload_0
    //   22: getfield 10	com/gtp/nextlauncher/widget/weatherwidget/a:a	Lcom/gtp/nextlauncher/widget/weatherwidget/Base;
    //   25: invokestatic 29	com/gtp/nextlauncher/widget/weatherwidget/Base:access$200	(Lcom/gtp/nextlauncher/widget/weatherwidget/Base;)V
    //   28: aload_0
    //   29: getfield 10	com/gtp/nextlauncher/widget/weatherwidget/a:a	Lcom/gtp/nextlauncher/widget/weatherwidget/Base;
    //   32: iconst_0
    //   33: invokestatic 22	com/gtp/nextlauncher/widget/weatherwidget/Base:access$002	(Lcom/gtp/nextlauncher/widget/weatherwidget/Base;Z)Z
    //   36: pop
    //   37: aload_0
    //   38: monitorexit
    //   39: return
    //   40: aload_0
    //   41: getfield 10	com/gtp/nextlauncher/widget/weatherwidget/a:a	Lcom/gtp/nextlauncher/widget/weatherwidget/Base;
    //   44: invokestatic 32	com/gtp/nextlauncher/widget/weatherwidget/Base:access$300	(Lcom/gtp/nextlauncher/widget/weatherwidget/Base;)V
    //   47: goto -19 -> 28
    //   50: astore_1
    //   51: aload_0
    //   52: monitorexit
    //   53: aload_1
    //   54: athrow
    // Local variable table:
    //   start	length	slot	name	signature
    //   0	55	0	this	a
    //   0	55	1	paramMessage	android.os.Message
    // Exception table:
    //   from	to	target	type
    //   2	28	50	finally
    //   28	39	50	finally
    //   40	47	50	finally
    //   51	53	50	finally
  }
}


/* Location:              /Users/amaurremi/uw/stringoid/static-dynamic-comparison/apps/go weather ex/com.gau.go.launcherex.gowidget.weatherwidget-124-dex2jar.jar!/com/gtp/nextlauncher/widget/weatherwidget/a.class
 * Java compiler version: 6 (50.0)
 * JD-Core Version:       0.7.1
 */