package com.google.android.gms.plus.internal;

import android.os.Bundle;
import android.os.IBinder;
import android.os.Parcel;
import android.os.ParcelFileDescriptor;
import com.google.android.gms.internal.ie;

class k
  implements b
{
  private IBinder a;
  
  k(IBinder paramIBinder)
  {
    this.a = paramIBinder;
  }
  
  public void a(int paramInt, Bundle paramBundle1, Bundle paramBundle2)
  {
    Parcel localParcel1 = Parcel.obtain();
    Parcel localParcel2 = Parcel.obtain();
    for (;;)
    {
      try
      {
        localParcel1.writeInterfaceToken("com.google.android.gms.plus.internal.IPlusCallbacks");
        localParcel1.writeInt(paramInt);
        if (paramBundle1 != null)
        {
          localParcel1.writeInt(1);
          paramBundle1.writeToParcel(localParcel1, 0);
          if (paramBundle2 != null)
          {
            localParcel1.writeInt(1);
            paramBundle2.writeToParcel(localParcel1, 0);
            this.a.transact(1, localParcel1, localParcel2, 0);
            localParcel2.readException();
          }
        }
        else
        {
          localParcel1.writeInt(0);
          continue;
        }
        localParcel1.writeInt(0);
      }
      finally
      {
        localParcel2.recycle();
        localParcel1.recycle();
      }
    }
  }
  
  public void a(int paramInt, Bundle paramBundle, ParcelFileDescriptor paramParcelFileDescriptor)
  {
    Parcel localParcel1 = Parcel.obtain();
    Parcel localParcel2 = Parcel.obtain();
    for (;;)
    {
      try
      {
        localParcel1.writeInterfaceToken("com.google.android.gms.plus.internal.IPlusCallbacks");
        localParcel1.writeInt(paramInt);
        if (paramBundle != null)
        {
          localParcel1.writeInt(1);
          paramBundle.writeToParcel(localParcel1, 0);
          if (paramParcelFileDescriptor != null)
          {
            localParcel1.writeInt(1);
            paramParcelFileDescriptor.writeToParcel(localParcel1, 0);
            this.a.transact(2, localParcel1, localParcel2, 0);
            localParcel2.readException();
          }
        }
        else
        {
          localParcel1.writeInt(0);
          continue;
        }
        localParcel1.writeInt(0);
      }
      finally
      {
        localParcel2.recycle();
        localParcel1.recycle();
      }
    }
  }
  
  public void a(int paramInt, Bundle paramBundle, ie paramie)
  {
    Parcel localParcel1 = Parcel.obtain();
    Parcel localParcel2 = Parcel.obtain();
    for (;;)
    {
      try
      {
        localParcel1.writeInterfaceToken("com.google.android.gms.plus.internal.IPlusCallbacks");
        localParcel1.writeInt(paramInt);
        if (paramBundle != null)
        {
          localParcel1.writeInt(1);
          paramBundle.writeToParcel(localParcel1, 0);
          if (paramie != null)
          {
            localParcel1.writeInt(1);
            paramie.writeToParcel(localParcel1, 0);
            this.a.transact(5, localParcel1, localParcel2, 0);
            localParcel2.readException();
          }
        }
        else
        {
          localParcel1.writeInt(0);
          continue;
        }
        localParcel1.writeInt(0);
      }
      finally
      {
        localParcel2.recycle();
        localParcel1.recycle();
      }
    }
  }
  
  /* Error */
  public void a(int paramInt, com.google.android.gms.internal.ks paramks)
  {
    // Byte code:
    //   0: invokestatic 23	android/os/Parcel:obtain	()Landroid/os/Parcel;
    //   3: astore_3
    //   4: invokestatic 23	android/os/Parcel:obtain	()Landroid/os/Parcel;
    //   7: astore 4
    //   9: aload_3
    //   10: ldc 25
    //   12: invokevirtual 29	android/os/Parcel:writeInterfaceToken	(Ljava/lang/String;)V
    //   15: aload_3
    //   16: iload_1
    //   17: invokevirtual 33	android/os/Parcel:writeInt	(I)V
    //   20: aload_2
    //   21: ifnull +45 -> 66
    //   24: aload_3
    //   25: iconst_1
    //   26: invokevirtual 33	android/os/Parcel:writeInt	(I)V
    //   29: aload_2
    //   30: aload_3
    //   31: iconst_0
    //   32: invokevirtual 63	com/google/android/gms/internal/ks:writeToParcel	(Landroid/os/Parcel;I)V
    //   35: aload_0
    //   36: getfield 15	com/google/android/gms/plus/internal/k:a	Landroid/os/IBinder;
    //   39: bipush 9
    //   41: aload_3
    //   42: aload 4
    //   44: iconst_0
    //   45: invokeinterface 45 5 0
    //   50: pop
    //   51: aload 4
    //   53: invokevirtual 48	android/os/Parcel:readException	()V
    //   56: aload 4
    //   58: invokevirtual 51	android/os/Parcel:recycle	()V
    //   61: aload_3
    //   62: invokevirtual 51	android/os/Parcel:recycle	()V
    //   65: return
    //   66: aload_3
    //   67: iconst_0
    //   68: invokevirtual 33	android/os/Parcel:writeInt	(I)V
    //   71: goto -36 -> 35
    //   74: astore_2
    //   75: aload 4
    //   77: invokevirtual 51	android/os/Parcel:recycle	()V
    //   80: aload_3
    //   81: invokevirtual 51	android/os/Parcel:recycle	()V
    //   84: aload_2
    //   85: athrow
    // Local variable table:
    //   start	length	slot	name	signature
    //   0	86	0	this	k
    //   0	86	1	paramInt	int
    //   0	86	2	paramks	com.google.android.gms.internal.ks
    //   3	78	3	localParcel1	Parcel
    //   7	69	4	localParcel2	Parcel
    // Exception table:
    //   from	to	target	type
    //   9	20	74	finally
    //   24	35	74	finally
    //   35	56	74	finally
    //   66	71	74	finally
  }
  
  /* Error */
  public void a(com.google.android.gms.common.data.DataHolder paramDataHolder, String paramString)
  {
    // Byte code:
    //   0: invokestatic 23	android/os/Parcel:obtain	()Landroid/os/Parcel;
    //   3: astore_3
    //   4: invokestatic 23	android/os/Parcel:obtain	()Landroid/os/Parcel;
    //   7: astore 4
    //   9: aload_3
    //   10: ldc 25
    //   12: invokevirtual 29	android/os/Parcel:writeInterfaceToken	(Ljava/lang/String;)V
    //   15: aload_1
    //   16: ifnull +49 -> 65
    //   19: aload_3
    //   20: iconst_1
    //   21: invokevirtual 33	android/os/Parcel:writeInt	(I)V
    //   24: aload_1
    //   25: aload_3
    //   26: iconst_0
    //   27: invokevirtual 67	com/google/android/gms/common/data/DataHolder:writeToParcel	(Landroid/os/Parcel;I)V
    //   30: aload_3
    //   31: aload_2
    //   32: invokevirtual 70	android/os/Parcel:writeString	(Ljava/lang/String;)V
    //   35: aload_0
    //   36: getfield 15	com/google/android/gms/plus/internal/k:a	Landroid/os/IBinder;
    //   39: iconst_4
    //   40: aload_3
    //   41: aload 4
    //   43: iconst_0
    //   44: invokeinterface 45 5 0
    //   49: pop
    //   50: aload 4
    //   52: invokevirtual 48	android/os/Parcel:readException	()V
    //   55: aload 4
    //   57: invokevirtual 51	android/os/Parcel:recycle	()V
    //   60: aload_3
    //   61: invokevirtual 51	android/os/Parcel:recycle	()V
    //   64: return
    //   65: aload_3
    //   66: iconst_0
    //   67: invokevirtual 33	android/os/Parcel:writeInt	(I)V
    //   70: goto -40 -> 30
    //   73: astore_1
    //   74: aload 4
    //   76: invokevirtual 51	android/os/Parcel:recycle	()V
    //   79: aload_3
    //   80: invokevirtual 51	android/os/Parcel:recycle	()V
    //   83: aload_1
    //   84: athrow
    // Local variable table:
    //   start	length	slot	name	signature
    //   0	85	0	this	k
    //   0	85	1	paramDataHolder	com.google.android.gms.common.data.DataHolder
    //   0	85	2	paramString	String
    //   3	77	3	localParcel1	Parcel
    //   7	68	4	localParcel2	Parcel
    // Exception table:
    //   from	to	target	type
    //   9	15	73	finally
    //   19	30	73	finally
    //   30	55	73	finally
    //   65	70	73	finally
  }
  
  /* Error */
  public void a(com.google.android.gms.common.data.DataHolder paramDataHolder, String paramString1, String paramString2)
  {
    // Byte code:
    //   0: invokestatic 23	android/os/Parcel:obtain	()Landroid/os/Parcel;
    //   3: astore 4
    //   5: invokestatic 23	android/os/Parcel:obtain	()Landroid/os/Parcel;
    //   8: astore 5
    //   10: aload 4
    //   12: ldc 25
    //   14: invokevirtual 29	android/os/Parcel:writeInterfaceToken	(Ljava/lang/String;)V
    //   17: aload_1
    //   18: ifnull +61 -> 79
    //   21: aload 4
    //   23: iconst_1
    //   24: invokevirtual 33	android/os/Parcel:writeInt	(I)V
    //   27: aload_1
    //   28: aload 4
    //   30: iconst_0
    //   31: invokevirtual 67	com/google/android/gms/common/data/DataHolder:writeToParcel	(Landroid/os/Parcel;I)V
    //   34: aload 4
    //   36: aload_2
    //   37: invokevirtual 70	android/os/Parcel:writeString	(Ljava/lang/String;)V
    //   40: aload 4
    //   42: aload_3
    //   43: invokevirtual 70	android/os/Parcel:writeString	(Ljava/lang/String;)V
    //   46: aload_0
    //   47: getfield 15	com/google/android/gms/plus/internal/k:a	Landroid/os/IBinder;
    //   50: bipush 6
    //   52: aload 4
    //   54: aload 5
    //   56: iconst_0
    //   57: invokeinterface 45 5 0
    //   62: pop
    //   63: aload 5
    //   65: invokevirtual 48	android/os/Parcel:readException	()V
    //   68: aload 5
    //   70: invokevirtual 51	android/os/Parcel:recycle	()V
    //   73: aload 4
    //   75: invokevirtual 51	android/os/Parcel:recycle	()V
    //   78: return
    //   79: aload 4
    //   81: iconst_0
    //   82: invokevirtual 33	android/os/Parcel:writeInt	(I)V
    //   85: goto -51 -> 34
    //   88: astore_1
    //   89: aload 5
    //   91: invokevirtual 51	android/os/Parcel:recycle	()V
    //   94: aload 4
    //   96: invokevirtual 51	android/os/Parcel:recycle	()V
    //   99: aload_1
    //   100: athrow
    // Local variable table:
    //   start	length	slot	name	signature
    //   0	101	0	this	k
    //   0	101	1	paramDataHolder	com.google.android.gms.common.data.DataHolder
    //   0	101	2	paramString1	String
    //   0	101	3	paramString2	String
    //   3	92	4	localParcel1	Parcel
    //   8	82	5	localParcel2	Parcel
    // Exception table:
    //   from	to	target	type
    //   10	17	88	finally
    //   21	34	88	finally
    //   34	68	88	finally
    //   79	85	88	finally
  }
  
  /* Error */
  public void am(com.google.android.gms.common.api.Status paramStatus)
  {
    // Byte code:
    //   0: invokestatic 23	android/os/Parcel:obtain	()Landroid/os/Parcel;
    //   3: astore_2
    //   4: invokestatic 23	android/os/Parcel:obtain	()Landroid/os/Parcel;
    //   7: astore_3
    //   8: aload_2
    //   9: ldc 25
    //   11: invokevirtual 29	android/os/Parcel:writeInterfaceToken	(Ljava/lang/String;)V
    //   14: aload_1
    //   15: ifnull +42 -> 57
    //   18: aload_2
    //   19: iconst_1
    //   20: invokevirtual 33	android/os/Parcel:writeInt	(I)V
    //   23: aload_1
    //   24: aload_2
    //   25: iconst_0
    //   26: invokevirtual 76	com/google/android/gms/common/api/Status:writeToParcel	(Landroid/os/Parcel;I)V
    //   29: aload_0
    //   30: getfield 15	com/google/android/gms/plus/internal/k:a	Landroid/os/IBinder;
    //   33: bipush 10
    //   35: aload_2
    //   36: aload_3
    //   37: iconst_0
    //   38: invokeinterface 45 5 0
    //   43: pop
    //   44: aload_3
    //   45: invokevirtual 48	android/os/Parcel:readException	()V
    //   48: aload_3
    //   49: invokevirtual 51	android/os/Parcel:recycle	()V
    //   52: aload_2
    //   53: invokevirtual 51	android/os/Parcel:recycle	()V
    //   56: return
    //   57: aload_2
    //   58: iconst_0
    //   59: invokevirtual 33	android/os/Parcel:writeInt	(I)V
    //   62: goto -33 -> 29
    //   65: astore_1
    //   66: aload_3
    //   67: invokevirtual 51	android/os/Parcel:recycle	()V
    //   70: aload_2
    //   71: invokevirtual 51	android/os/Parcel:recycle	()V
    //   74: aload_1
    //   75: athrow
    // Local variable table:
    //   start	length	slot	name	signature
    //   0	76	0	this	k
    //   0	76	1	paramStatus	com.google.android.gms.common.api.Status
    //   3	68	2	localParcel1	Parcel
    //   7	60	3	localParcel2	Parcel
    // Exception table:
    //   from	to	target	type
    //   8	14	65	finally
    //   18	29	65	finally
    //   29	48	65	finally
    //   57	62	65	finally
  }
  
  public IBinder asBinder()
  {
    return this.a;
  }
  
  public void bw(String paramString)
  {
    Parcel localParcel1 = Parcel.obtain();
    Parcel localParcel2 = Parcel.obtain();
    try
    {
      localParcel1.writeInterfaceToken("com.google.android.gms.plus.internal.IPlusCallbacks");
      localParcel1.writeString(paramString);
      this.a.transact(3, localParcel1, localParcel2, 0);
      localParcel2.readException();
      return;
    }
    finally
    {
      localParcel2.recycle();
      localParcel1.recycle();
    }
  }
  
  public void bx(String paramString)
  {
    Parcel localParcel1 = Parcel.obtain();
    Parcel localParcel2 = Parcel.obtain();
    try
    {
      localParcel1.writeInterfaceToken("com.google.android.gms.plus.internal.IPlusCallbacks");
      localParcel1.writeString(paramString);
      this.a.transact(8, localParcel1, localParcel2, 0);
      localParcel2.readException();
      return;
    }
    finally
    {
      localParcel2.recycle();
      localParcel1.recycle();
    }
  }
  
  /* Error */
  public void h(int paramInt, Bundle paramBundle)
  {
    // Byte code:
    //   0: invokestatic 23	android/os/Parcel:obtain	()Landroid/os/Parcel;
    //   3: astore_3
    //   4: invokestatic 23	android/os/Parcel:obtain	()Landroid/os/Parcel;
    //   7: astore 4
    //   9: aload_3
    //   10: ldc 25
    //   12: invokevirtual 29	android/os/Parcel:writeInterfaceToken	(Ljava/lang/String;)V
    //   15: aload_3
    //   16: iload_1
    //   17: invokevirtual 33	android/os/Parcel:writeInt	(I)V
    //   20: aload_2
    //   21: ifnull +45 -> 66
    //   24: aload_3
    //   25: iconst_1
    //   26: invokevirtual 33	android/os/Parcel:writeInt	(I)V
    //   29: aload_2
    //   30: aload_3
    //   31: iconst_0
    //   32: invokevirtual 39	android/os/Bundle:writeToParcel	(Landroid/os/Parcel;I)V
    //   35: aload_0
    //   36: getfield 15	com/google/android/gms/plus/internal/k:a	Landroid/os/IBinder;
    //   39: bipush 7
    //   41: aload_3
    //   42: aload 4
    //   44: iconst_0
    //   45: invokeinterface 45 5 0
    //   50: pop
    //   51: aload 4
    //   53: invokevirtual 48	android/os/Parcel:readException	()V
    //   56: aload 4
    //   58: invokevirtual 51	android/os/Parcel:recycle	()V
    //   61: aload_3
    //   62: invokevirtual 51	android/os/Parcel:recycle	()V
    //   65: return
    //   66: aload_3
    //   67: iconst_0
    //   68: invokevirtual 33	android/os/Parcel:writeInt	(I)V
    //   71: goto -36 -> 35
    //   74: astore_2
    //   75: aload 4
    //   77: invokevirtual 51	android/os/Parcel:recycle	()V
    //   80: aload_3
    //   81: invokevirtual 51	android/os/Parcel:recycle	()V
    //   84: aload_2
    //   85: athrow
    // Local variable table:
    //   start	length	slot	name	signature
    //   0	86	0	this	k
    //   0	86	1	paramInt	int
    //   0	86	2	paramBundle	Bundle
    //   3	78	3	localParcel1	Parcel
    //   7	69	4	localParcel2	Parcel
    // Exception table:
    //   from	to	target	type
    //   9	20	74	finally
    //   24	35	74	finally
    //   35	56	74	finally
    //   66	71	74	finally
  }
}


/* Location:              /Users/amaurremi/uw/stringoid/static-dynamic-comparison/apps/retrica/com.venticake.retrica-21-dex2jar.jar!/com/google/android/gms/plus/internal/k.class
 * Java compiler version: 6 (50.0)
 * JD-Core Version:       0.7.1
 */