package com.jiubang.goweather.c;

public class r
{
  /* Error */
  public static java.util.List a(android.content.Context paramContext, String paramString, int paramInt)
  {
    // Byte code:
    //   0: aconst_null
    //   1: astore 4
    //   3: new 10	java/util/ArrayList
    //   6: dup
    //   7: invokespecial 14	java/util/ArrayList:<init>	()V
    //   10: astore 6
    //   12: aload_0
    //   13: iload_2
    //   14: invokestatic 19	com/jiubang/goweather/c/f:a	(Landroid/content/Context;I)Landroid/database/sqlite/SQLiteDatabase;
    //   17: astore_0
    //   18: aload_0
    //   19: ifnull +297 -> 316
    //   22: aload_0
    //   23: ldc 21
    //   25: iconst_2
    //   26: anewarray 23	java/lang/String
    //   29: dup
    //   30: iconst_0
    //   31: new 25	java/lang/StringBuilder
    //   34: dup
    //   35: invokespecial 26	java/lang/StringBuilder:<init>	()V
    //   38: aload_1
    //   39: invokevirtual 30	java/lang/StringBuilder:append	(Ljava/lang/String;)Ljava/lang/StringBuilder;
    //   42: ldc 32
    //   44: invokevirtual 30	java/lang/StringBuilder:append	(Ljava/lang/String;)Ljava/lang/StringBuilder;
    //   47: invokevirtual 36	java/lang/StringBuilder:toString	()Ljava/lang/String;
    //   50: aastore
    //   51: dup
    //   52: iconst_1
    //   53: new 25	java/lang/StringBuilder
    //   56: dup
    //   57: invokespecial 26	java/lang/StringBuilder:<init>	()V
    //   60: aload_1
    //   61: invokevirtual 30	java/lang/StringBuilder:append	(Ljava/lang/String;)Ljava/lang/StringBuilder;
    //   64: ldc 32
    //   66: invokevirtual 30	java/lang/StringBuilder:append	(Ljava/lang/String;)Ljava/lang/StringBuilder;
    //   69: invokevirtual 36	java/lang/StringBuilder:toString	()Ljava/lang/String;
    //   72: aastore
    //   73: invokevirtual 42	android/database/sqlite/SQLiteDatabase:rawQuery	(Ljava/lang/String;[Ljava/lang/String;)Landroid/database/Cursor;
    //   76: astore_1
    //   77: aload_1
    //   78: astore_3
    //   79: aload_1
    //   80: ifnull +238 -> 318
    //   83: aload_1
    //   84: astore_3
    //   85: aload_1
    //   86: invokeinterface 48 1 0
    //   91: ifeq +227 -> 318
    //   94: aload_1
    //   95: aload_1
    //   96: ldc 50
    //   98: invokeinterface 54 2 0
    //   103: invokeinterface 58 2 0
    //   108: astore 7
    //   110: aload_1
    //   111: aload_1
    //   112: ldc 60
    //   114: invokeinterface 54 2 0
    //   119: invokeinterface 58 2 0
    //   124: astore 8
    //   126: aload_1
    //   127: aload_1
    //   128: ldc 62
    //   130: invokeinterface 54 2 0
    //   135: invokeinterface 58 2 0
    //   140: astore 5
    //   142: aload_1
    //   143: aload_1
    //   144: ldc 64
    //   146: invokeinterface 54 2 0
    //   151: invokeinterface 58 2 0
    //   156: astore_3
    //   157: aload_1
    //   158: aload_1
    //   159: ldc 66
    //   161: invokeinterface 54 2 0
    //   166: invokeinterface 58 2 0
    //   171: astore 9
    //   173: aload_1
    //   174: aload_1
    //   175: ldc 68
    //   177: invokeinterface 54 2 0
    //   182: invokeinterface 58 2 0
    //   187: invokestatic 73	java/lang/Integer:parseInt	(Ljava/lang/String;)I
    //   190: sipush 5000
    //   193: if_icmpgt +182 -> 375
    //   196: ldc 75
    //   198: astore 4
    //   200: aload 6
    //   202: new 77	com/gau/go/launcherex/gowidget/weather/model/b
    //   205: dup
    //   206: aload 8
    //   208: aload 7
    //   210: aload_3
    //   211: aload 4
    //   213: aload 9
    //   215: new 25	java/lang/StringBuilder
    //   218: dup
    //   219: invokespecial 26	java/lang/StringBuilder:<init>	()V
    //   222: aload 7
    //   224: invokevirtual 30	java/lang/StringBuilder:append	(Ljava/lang/String;)Ljava/lang/StringBuilder;
    //   227: ldc 79
    //   229: invokevirtual 30	java/lang/StringBuilder:append	(Ljava/lang/String;)Ljava/lang/StringBuilder;
    //   232: aload_3
    //   233: invokevirtual 30	java/lang/StringBuilder:append	(Ljava/lang/String;)Ljava/lang/StringBuilder;
    //   236: invokevirtual 36	java/lang/StringBuilder:toString	()Ljava/lang/String;
    //   239: invokespecial 82	com/gau/go/launcherex/gowidget/weather/model/b:<init>	(Ljava/lang/String;Ljava/lang/String;Ljava/lang/String;Ljava/lang/String;Ljava/lang/String;Ljava/lang/String;)V
    //   242: invokeinterface 88 2 0
    //   247: pop
    //   248: goto -165 -> 83
    //   251: astore_3
    //   252: aload_3
    //   253: invokevirtual 91	java/lang/Exception:printStackTrace	()V
    //   256: aload_1
    //   257: ifnull +9 -> 266
    //   260: aload_1
    //   261: invokeinterface 94 1 0
    //   266: aload_0
    //   267: ifnull +14 -> 281
    //   270: aload_0
    //   271: invokevirtual 97	android/database/sqlite/SQLiteDatabase:isOpen	()Z
    //   274: ifeq +7 -> 281
    //   277: aload_0
    //   278: invokevirtual 98	android/database/sqlite/SQLiteDatabase:close	()V
    //   281: aload 6
    //   283: areturn
    //   284: astore_3
    //   285: aconst_null
    //   286: astore_0
    //   287: aconst_null
    //   288: astore_1
    //   289: aload_1
    //   290: ifnull +9 -> 299
    //   293: aload_1
    //   294: invokeinterface 94 1 0
    //   299: aload_0
    //   300: ifnull +14 -> 314
    //   303: aload_0
    //   304: invokevirtual 97	android/database/sqlite/SQLiteDatabase:isOpen	()Z
    //   307: ifeq +7 -> 314
    //   310: aload_0
    //   311: invokevirtual 98	android/database/sqlite/SQLiteDatabase:close	()V
    //   314: aload_3
    //   315: athrow
    //   316: aconst_null
    //   317: astore_3
    //   318: aload_3
    //   319: ifnull +9 -> 328
    //   322: aload_3
    //   323: invokeinterface 94 1 0
    //   328: aload_0
    //   329: ifnull -48 -> 281
    //   332: aload_0
    //   333: invokevirtual 97	android/database/sqlite/SQLiteDatabase:isOpen	()Z
    //   336: ifeq -55 -> 281
    //   339: aload_0
    //   340: invokevirtual 98	android/database/sqlite/SQLiteDatabase:close	()V
    //   343: aload 6
    //   345: areturn
    //   346: astore_3
    //   347: aconst_null
    //   348: astore_1
    //   349: goto -60 -> 289
    //   352: astore_3
    //   353: goto -64 -> 289
    //   356: astore_3
    //   357: goto -68 -> 289
    //   360: astore_3
    //   361: aconst_null
    //   362: astore_1
    //   363: aload 4
    //   365: astore_0
    //   366: goto -114 -> 252
    //   369: astore_3
    //   370: aconst_null
    //   371: astore_1
    //   372: goto -120 -> 252
    //   375: aload_3
    //   376: astore 4
    //   378: aload 5
    //   380: astore_3
    //   381: goto -181 -> 200
    // Local variable table:
    //   start	length	slot	name	signature
    //   0	384	0	paramContext	android.content.Context
    //   0	384	1	paramString	String
    //   0	384	2	paramInt	int
    //   78	155	3	str1	String
    //   251	2	3	localException1	Exception
    //   284	31	3	localObject1	Object
    //   317	6	3	localObject2	Object
    //   346	1	3	localObject3	Object
    //   352	1	3	localObject4	Object
    //   356	1	3	localObject5	Object
    //   360	1	3	localException2	Exception
    //   369	7	3	localException3	Exception
    //   380	1	3	localObject6	Object
    //   1	376	4	localObject7	Object
    //   140	239	5	str2	String
    //   10	334	6	localArrayList	java.util.ArrayList
    //   108	115	7	str3	String
    //   124	83	8	str4	String
    //   171	43	9	str5	String
    // Exception table:
    //   from	to	target	type
    //   85	196	251	java/lang/Exception
    //   200	248	251	java/lang/Exception
    //   12	18	284	finally
    //   22	77	346	finally
    //   85	196	352	finally
    //   200	248	352	finally
    //   252	256	356	finally
    //   12	18	360	java/lang/Exception
    //   22	77	369	java/lang/Exception
  }
  
  /* Error */
  public static java.util.List a(android.content.Context paramContext, String paramString, int paramInt, java.util.List paramList)
  {
    // Byte code:
    //   0: aconst_null
    //   1: astore 5
    //   3: aload_3
    //   4: ifnonnull +262 -> 266
    //   7: new 10	java/util/ArrayList
    //   10: dup
    //   11: invokespecial 14	java/util/ArrayList:<init>	()V
    //   14: astore 4
    //   16: aload_0
    //   17: iload_2
    //   18: invokestatic 19	com/jiubang/goweather/c/f:a	(Landroid/content/Context;I)Landroid/database/sqlite/SQLiteDatabase;
    //   21: astore_0
    //   22: aload_0
    //   23: ifnull +287 -> 310
    //   26: aload_0
    //   27: ldc 102
    //   29: iconst_1
    //   30: anewarray 23	java/lang/String
    //   33: dup
    //   34: iconst_0
    //   35: new 25	java/lang/StringBuilder
    //   38: dup
    //   39: invokespecial 26	java/lang/StringBuilder:<init>	()V
    //   42: aload_1
    //   43: invokevirtual 30	java/lang/StringBuilder:append	(Ljava/lang/String;)Ljava/lang/StringBuilder;
    //   46: ldc 32
    //   48: invokevirtual 30	java/lang/StringBuilder:append	(Ljava/lang/String;)Ljava/lang/StringBuilder;
    //   51: invokevirtual 36	java/lang/StringBuilder:toString	()Ljava/lang/String;
    //   54: aastore
    //   55: invokevirtual 42	android/database/sqlite/SQLiteDatabase:rawQuery	(Ljava/lang/String;[Ljava/lang/String;)Landroid/database/Cursor;
    //   58: astore_1
    //   59: aload_1
    //   60: astore_3
    //   61: aload_1
    //   62: ifnull +250 -> 312
    //   65: aload_1
    //   66: astore_3
    //   67: aload_1
    //   68: invokeinterface 48 1 0
    //   73: ifeq +239 -> 312
    //   76: aload_1
    //   77: aload_1
    //   78: ldc 50
    //   80: invokeinterface 54 2 0
    //   85: invokeinterface 58 2 0
    //   90: astore 7
    //   92: aload_1
    //   93: aload_1
    //   94: ldc 60
    //   96: invokeinterface 54 2 0
    //   101: invokeinterface 58 2 0
    //   106: astore 8
    //   108: aload_1
    //   109: aload_1
    //   110: ldc 62
    //   112: invokeinterface 54 2 0
    //   117: invokeinterface 58 2 0
    //   122: astore 6
    //   124: aload_1
    //   125: aload_1
    //   126: ldc 64
    //   128: invokeinterface 54 2 0
    //   133: invokeinterface 58 2 0
    //   138: astore_3
    //   139: aload_1
    //   140: aload_1
    //   141: ldc 66
    //   143: invokeinterface 54 2 0
    //   148: invokeinterface 58 2 0
    //   153: astore 9
    //   155: aload_1
    //   156: aload_1
    //   157: ldc 68
    //   159: invokeinterface 54 2 0
    //   164: invokeinterface 58 2 0
    //   169: invokestatic 73	java/lang/Integer:parseInt	(Ljava/lang/String;)I
    //   172: sipush 5000
    //   175: if_icmpgt +194 -> 369
    //   178: ldc 75
    //   180: astore 5
    //   182: aload 4
    //   184: new 77	com/gau/go/launcherex/gowidget/weather/model/b
    //   187: dup
    //   188: aload 8
    //   190: aload 7
    //   192: aload_3
    //   193: aload 5
    //   195: aload 9
    //   197: new 25	java/lang/StringBuilder
    //   200: dup
    //   201: invokespecial 26	java/lang/StringBuilder:<init>	()V
    //   204: aload 7
    //   206: invokevirtual 30	java/lang/StringBuilder:append	(Ljava/lang/String;)Ljava/lang/StringBuilder;
    //   209: ldc 79
    //   211: invokevirtual 30	java/lang/StringBuilder:append	(Ljava/lang/String;)Ljava/lang/StringBuilder;
    //   214: aload_3
    //   215: invokevirtual 30	java/lang/StringBuilder:append	(Ljava/lang/String;)Ljava/lang/StringBuilder;
    //   218: invokevirtual 36	java/lang/StringBuilder:toString	()Ljava/lang/String;
    //   221: invokespecial 82	com/gau/go/launcherex/gowidget/weather/model/b:<init>	(Ljava/lang/String;Ljava/lang/String;Ljava/lang/String;Ljava/lang/String;Ljava/lang/String;Ljava/lang/String;)V
    //   224: invokeinterface 88 2 0
    //   229: pop
    //   230: goto -165 -> 65
    //   233: astore_3
    //   234: aload_3
    //   235: invokevirtual 91	java/lang/Exception:printStackTrace	()V
    //   238: aload_1
    //   239: ifnull +9 -> 248
    //   242: aload_1
    //   243: invokeinterface 94 1 0
    //   248: aload_0
    //   249: ifnull +14 -> 263
    //   252: aload_0
    //   253: invokevirtual 97	android/database/sqlite/SQLiteDatabase:isOpen	()Z
    //   256: ifeq +7 -> 263
    //   259: aload_0
    //   260: invokevirtual 98	android/database/sqlite/SQLiteDatabase:close	()V
    //   263: aload 4
    //   265: areturn
    //   266: aload_3
    //   267: invokeinterface 105 1 0
    //   272: aload_3
    //   273: astore 4
    //   275: goto -259 -> 16
    //   278: astore_3
    //   279: aconst_null
    //   280: astore_0
    //   281: aconst_null
    //   282: astore_1
    //   283: aload_1
    //   284: ifnull +9 -> 293
    //   287: aload_1
    //   288: invokeinterface 94 1 0
    //   293: aload_0
    //   294: ifnull +14 -> 308
    //   297: aload_0
    //   298: invokevirtual 97	android/database/sqlite/SQLiteDatabase:isOpen	()Z
    //   301: ifeq +7 -> 308
    //   304: aload_0
    //   305: invokevirtual 98	android/database/sqlite/SQLiteDatabase:close	()V
    //   308: aload_3
    //   309: athrow
    //   310: aconst_null
    //   311: astore_3
    //   312: aload_3
    //   313: ifnull +9 -> 322
    //   316: aload_3
    //   317: invokeinterface 94 1 0
    //   322: aload_0
    //   323: ifnull -60 -> 263
    //   326: aload_0
    //   327: invokevirtual 97	android/database/sqlite/SQLiteDatabase:isOpen	()Z
    //   330: ifeq -67 -> 263
    //   333: aload_0
    //   334: invokevirtual 98	android/database/sqlite/SQLiteDatabase:close	()V
    //   337: aload 4
    //   339: areturn
    //   340: astore_3
    //   341: aconst_null
    //   342: astore_1
    //   343: goto -60 -> 283
    //   346: astore_3
    //   347: goto -64 -> 283
    //   350: astore_3
    //   351: goto -68 -> 283
    //   354: astore_3
    //   355: aconst_null
    //   356: astore_1
    //   357: aload 5
    //   359: astore_0
    //   360: goto -126 -> 234
    //   363: astore_3
    //   364: aconst_null
    //   365: astore_1
    //   366: goto -132 -> 234
    //   369: aload_3
    //   370: astore 5
    //   372: aload 6
    //   374: astore_3
    //   375: goto -193 -> 182
    // Local variable table:
    //   start	length	slot	name	signature
    //   0	378	0	paramContext	android.content.Context
    //   0	378	1	paramString	String
    //   0	378	2	paramInt	int
    //   0	378	3	paramList	java.util.List
    //   14	324	4	localObject1	Object
    //   1	370	5	localObject2	Object
    //   122	251	6	str1	String
    //   90	115	7	str2	String
    //   106	83	8	str3	String
    //   153	43	9	str4	String
    // Exception table:
    //   from	to	target	type
    //   67	178	233	java/lang/Exception
    //   182	230	233	java/lang/Exception
    //   16	22	278	finally
    //   26	59	340	finally
    //   67	178	346	finally
    //   182	230	346	finally
    //   234	238	350	finally
    //   16	22	354	java/lang/Exception
    //   26	59	363	java/lang/Exception
  }
}


/* Location:              /Users/amaurremi/uw/stringoid/static-dynamic-comparison/apps/go weather ex/com.gau.go.launcherex.gowidget.weatherwidget-124-dex2jar.jar!/com/jiubang/goweather/c/r.class
 * Java compiler version: 6 (50.0)
 * JD-Core Version:       0.7.1
 */