package com.google.android.gms.drive.internal;

import android.os.Binder;
import android.os.IBinder;
import android.os.IInterface;
import android.os.Parcel;
import android.os.Parcelable.Creator;
import com.google.android.gms.common.api.Status;
import com.google.android.gms.common.api.i;

public abstract interface ai
  extends IInterface
{
  public abstract void a(OnContentsResponse paramOnContentsResponse);
  
  public abstract void a(OnDownloadProgressResponse paramOnDownloadProgressResponse);
  
  public abstract void a(OnDriveIdResponse paramOnDriveIdResponse);
  
  public abstract void a(OnListEntriesResponse paramOnListEntriesResponse);
  
  public abstract void a(OnListParentsResponse paramOnListParentsResponse);
  
  public abstract void a(OnMetadataResponse paramOnMetadataResponse);
  
  public abstract void c(Status paramStatus);
  
  public abstract void onSuccess();
  
  public static abstract class a
    extends Binder
    implements ai
  {
    public a()
    {
      attachInterface(this, "com.google.android.gms.drive.internal.IDriveServiceCallbacks");
    }
    
    public static ai f(IBinder paramIBinder)
    {
      if (paramIBinder == null) {
        return null;
      }
      IInterface localIInterface = paramIBinder.queryLocalInterface("com.google.android.gms.drive.internal.IDriveServiceCallbacks");
      if ((localIInterface != null) && ((localIInterface instanceof ai))) {
        return (ai)localIInterface;
      }
      return new a(paramIBinder);
    }
    
    public IBinder asBinder()
    {
      return this;
    }
    
    public boolean onTransact(int paramInt1, Parcel paramParcel1, Parcel paramParcel2, int paramInt2)
    {
      Object localObject2 = null;
      Object localObject3 = null;
      Object localObject4 = null;
      Object localObject5 = null;
      Object localObject6 = null;
      Object localObject7 = null;
      Object localObject1 = null;
      switch (paramInt1)
      {
      default: 
        return super.onTransact(paramInt1, paramParcel1, paramParcel2, paramInt2);
      case 1598968902: 
        paramParcel2.writeString("com.google.android.gms.drive.internal.IDriveServiceCallbacks");
        return true;
      case 1: 
        paramParcel1.enforceInterface("com.google.android.gms.drive.internal.IDriveServiceCallbacks");
        if (paramParcel1.readInt() != 0) {
          localObject1 = (OnDownloadProgressResponse)OnDownloadProgressResponse.CREATOR.createFromParcel(paramParcel1);
        }
        a((OnDownloadProgressResponse)localObject1);
        paramParcel2.writeNoException();
        return true;
      case 2: 
        paramParcel1.enforceInterface("com.google.android.gms.drive.internal.IDriveServiceCallbacks");
        localObject1 = localObject2;
        if (paramParcel1.readInt() != 0) {
          localObject1 = (OnListEntriesResponse)OnListEntriesResponse.CREATOR.createFromParcel(paramParcel1);
        }
        a((OnListEntriesResponse)localObject1);
        paramParcel2.writeNoException();
        return true;
      case 3: 
        paramParcel1.enforceInterface("com.google.android.gms.drive.internal.IDriveServiceCallbacks");
        localObject1 = localObject3;
        if (paramParcel1.readInt() != 0) {
          localObject1 = (OnDriveIdResponse)OnDriveIdResponse.CREATOR.createFromParcel(paramParcel1);
        }
        a((OnDriveIdResponse)localObject1);
        paramParcel2.writeNoException();
        return true;
      case 4: 
        paramParcel1.enforceInterface("com.google.android.gms.drive.internal.IDriveServiceCallbacks");
        localObject1 = localObject4;
        if (paramParcel1.readInt() != 0) {
          localObject1 = (OnMetadataResponse)OnMetadataResponse.CREATOR.createFromParcel(paramParcel1);
        }
        a((OnMetadataResponse)localObject1);
        paramParcel2.writeNoException();
        return true;
      case 5: 
        paramParcel1.enforceInterface("com.google.android.gms.drive.internal.IDriveServiceCallbacks");
        localObject1 = localObject5;
        if (paramParcel1.readInt() != 0) {
          localObject1 = (OnContentsResponse)OnContentsResponse.CREATOR.createFromParcel(paramParcel1);
        }
        a((OnContentsResponse)localObject1);
        paramParcel2.writeNoException();
        return true;
      case 6: 
        paramParcel1.enforceInterface("com.google.android.gms.drive.internal.IDriveServiceCallbacks");
        localObject1 = localObject6;
        if (paramParcel1.readInt() != 0) {
          localObject1 = Status.rf.f(paramParcel1);
        }
        c((Status)localObject1);
        paramParcel2.writeNoException();
        return true;
      case 7: 
        paramParcel1.enforceInterface("com.google.android.gms.drive.internal.IDriveServiceCallbacks");
        onSuccess();
        paramParcel2.writeNoException();
        return true;
      }
      paramParcel1.enforceInterface("com.google.android.gms.drive.internal.IDriveServiceCallbacks");
      localObject1 = localObject7;
      if (paramParcel1.readInt() != 0) {
        localObject1 = (OnListParentsResponse)OnListParentsResponse.CREATOR.createFromParcel(paramParcel1);
      }
      a((OnListParentsResponse)localObject1);
      paramParcel2.writeNoException();
      return true;
    }
    
    private static class a
      implements ai
    {
      private IBinder tS;
      
      a(IBinder paramIBinder)
      {
        this.tS = paramIBinder;
      }
      
      /* Error */
      public void a(OnContentsResponse paramOnContentsResponse)
      {
        // Byte code:
        //   0: invokestatic 26	android/os/Parcel:obtain	()Landroid/os/Parcel;
        //   3: astore_2
        //   4: invokestatic 26	android/os/Parcel:obtain	()Landroid/os/Parcel;
        //   7: astore_3
        //   8: aload_2
        //   9: ldc 28
        //   11: invokevirtual 32	android/os/Parcel:writeInterfaceToken	(Ljava/lang/String;)V
        //   14: aload_1
        //   15: ifnull +41 -> 56
        //   18: aload_2
        //   19: iconst_1
        //   20: invokevirtual 36	android/os/Parcel:writeInt	(I)V
        //   23: aload_1
        //   24: aload_2
        //   25: iconst_0
        //   26: invokevirtual 42	com/google/android/gms/drive/internal/OnContentsResponse:writeToParcel	(Landroid/os/Parcel;I)V
        //   29: aload_0
        //   30: getfield 18	com/google/android/gms/drive/internal/ai$a$a:tS	Landroid/os/IBinder;
        //   33: iconst_5
        //   34: aload_2
        //   35: aload_3
        //   36: iconst_0
        //   37: invokeinterface 48 5 0
        //   42: pop
        //   43: aload_3
        //   44: invokevirtual 51	android/os/Parcel:readException	()V
        //   47: aload_3
        //   48: invokevirtual 54	android/os/Parcel:recycle	()V
        //   51: aload_2
        //   52: invokevirtual 54	android/os/Parcel:recycle	()V
        //   55: return
        //   56: aload_2
        //   57: iconst_0
        //   58: invokevirtual 36	android/os/Parcel:writeInt	(I)V
        //   61: goto -32 -> 29
        //   64: astore_1
        //   65: aload_3
        //   66: invokevirtual 54	android/os/Parcel:recycle	()V
        //   69: aload_2
        //   70: invokevirtual 54	android/os/Parcel:recycle	()V
        //   73: aload_1
        //   74: athrow
        // Local variable table:
        //   start	length	slot	name	signature
        //   0	75	0	this	a
        //   0	75	1	paramOnContentsResponse	OnContentsResponse
        //   3	67	2	localParcel1	Parcel
        //   7	59	3	localParcel2	Parcel
        // Exception table:
        //   from	to	target	type
        //   8	14	64	finally
        //   18	29	64	finally
        //   29	47	64	finally
        //   56	61	64	finally
      }
      
      /* Error */
      public void a(OnDownloadProgressResponse paramOnDownloadProgressResponse)
      {
        // Byte code:
        //   0: invokestatic 26	android/os/Parcel:obtain	()Landroid/os/Parcel;
        //   3: astore_2
        //   4: invokestatic 26	android/os/Parcel:obtain	()Landroid/os/Parcel;
        //   7: astore_3
        //   8: aload_2
        //   9: ldc 28
        //   11: invokevirtual 32	android/os/Parcel:writeInterfaceToken	(Ljava/lang/String;)V
        //   14: aload_1
        //   15: ifnull +41 -> 56
        //   18: aload_2
        //   19: iconst_1
        //   20: invokevirtual 36	android/os/Parcel:writeInt	(I)V
        //   23: aload_1
        //   24: aload_2
        //   25: iconst_0
        //   26: invokevirtual 58	com/google/android/gms/drive/internal/OnDownloadProgressResponse:writeToParcel	(Landroid/os/Parcel;I)V
        //   29: aload_0
        //   30: getfield 18	com/google/android/gms/drive/internal/ai$a$a:tS	Landroid/os/IBinder;
        //   33: iconst_1
        //   34: aload_2
        //   35: aload_3
        //   36: iconst_0
        //   37: invokeinterface 48 5 0
        //   42: pop
        //   43: aload_3
        //   44: invokevirtual 51	android/os/Parcel:readException	()V
        //   47: aload_3
        //   48: invokevirtual 54	android/os/Parcel:recycle	()V
        //   51: aload_2
        //   52: invokevirtual 54	android/os/Parcel:recycle	()V
        //   55: return
        //   56: aload_2
        //   57: iconst_0
        //   58: invokevirtual 36	android/os/Parcel:writeInt	(I)V
        //   61: goto -32 -> 29
        //   64: astore_1
        //   65: aload_3
        //   66: invokevirtual 54	android/os/Parcel:recycle	()V
        //   69: aload_2
        //   70: invokevirtual 54	android/os/Parcel:recycle	()V
        //   73: aload_1
        //   74: athrow
        // Local variable table:
        //   start	length	slot	name	signature
        //   0	75	0	this	a
        //   0	75	1	paramOnDownloadProgressResponse	OnDownloadProgressResponse
        //   3	67	2	localParcel1	Parcel
        //   7	59	3	localParcel2	Parcel
        // Exception table:
        //   from	to	target	type
        //   8	14	64	finally
        //   18	29	64	finally
        //   29	47	64	finally
        //   56	61	64	finally
      }
      
      /* Error */
      public void a(OnDriveIdResponse paramOnDriveIdResponse)
      {
        // Byte code:
        //   0: invokestatic 26	android/os/Parcel:obtain	()Landroid/os/Parcel;
        //   3: astore_2
        //   4: invokestatic 26	android/os/Parcel:obtain	()Landroid/os/Parcel;
        //   7: astore_3
        //   8: aload_2
        //   9: ldc 28
        //   11: invokevirtual 32	android/os/Parcel:writeInterfaceToken	(Ljava/lang/String;)V
        //   14: aload_1
        //   15: ifnull +41 -> 56
        //   18: aload_2
        //   19: iconst_1
        //   20: invokevirtual 36	android/os/Parcel:writeInt	(I)V
        //   23: aload_1
        //   24: aload_2
        //   25: iconst_0
        //   26: invokevirtual 62	com/google/android/gms/drive/internal/OnDriveIdResponse:writeToParcel	(Landroid/os/Parcel;I)V
        //   29: aload_0
        //   30: getfield 18	com/google/android/gms/drive/internal/ai$a$a:tS	Landroid/os/IBinder;
        //   33: iconst_3
        //   34: aload_2
        //   35: aload_3
        //   36: iconst_0
        //   37: invokeinterface 48 5 0
        //   42: pop
        //   43: aload_3
        //   44: invokevirtual 51	android/os/Parcel:readException	()V
        //   47: aload_3
        //   48: invokevirtual 54	android/os/Parcel:recycle	()V
        //   51: aload_2
        //   52: invokevirtual 54	android/os/Parcel:recycle	()V
        //   55: return
        //   56: aload_2
        //   57: iconst_0
        //   58: invokevirtual 36	android/os/Parcel:writeInt	(I)V
        //   61: goto -32 -> 29
        //   64: astore_1
        //   65: aload_3
        //   66: invokevirtual 54	android/os/Parcel:recycle	()V
        //   69: aload_2
        //   70: invokevirtual 54	android/os/Parcel:recycle	()V
        //   73: aload_1
        //   74: athrow
        // Local variable table:
        //   start	length	slot	name	signature
        //   0	75	0	this	a
        //   0	75	1	paramOnDriveIdResponse	OnDriveIdResponse
        //   3	67	2	localParcel1	Parcel
        //   7	59	3	localParcel2	Parcel
        // Exception table:
        //   from	to	target	type
        //   8	14	64	finally
        //   18	29	64	finally
        //   29	47	64	finally
        //   56	61	64	finally
      }
      
      /* Error */
      public void a(OnListEntriesResponse paramOnListEntriesResponse)
      {
        // Byte code:
        //   0: invokestatic 26	android/os/Parcel:obtain	()Landroid/os/Parcel;
        //   3: astore_2
        //   4: invokestatic 26	android/os/Parcel:obtain	()Landroid/os/Parcel;
        //   7: astore_3
        //   8: aload_2
        //   9: ldc 28
        //   11: invokevirtual 32	android/os/Parcel:writeInterfaceToken	(Ljava/lang/String;)V
        //   14: aload_1
        //   15: ifnull +41 -> 56
        //   18: aload_2
        //   19: iconst_1
        //   20: invokevirtual 36	android/os/Parcel:writeInt	(I)V
        //   23: aload_1
        //   24: aload_2
        //   25: iconst_0
        //   26: invokevirtual 66	com/google/android/gms/drive/internal/OnListEntriesResponse:writeToParcel	(Landroid/os/Parcel;I)V
        //   29: aload_0
        //   30: getfield 18	com/google/android/gms/drive/internal/ai$a$a:tS	Landroid/os/IBinder;
        //   33: iconst_2
        //   34: aload_2
        //   35: aload_3
        //   36: iconst_0
        //   37: invokeinterface 48 5 0
        //   42: pop
        //   43: aload_3
        //   44: invokevirtual 51	android/os/Parcel:readException	()V
        //   47: aload_3
        //   48: invokevirtual 54	android/os/Parcel:recycle	()V
        //   51: aload_2
        //   52: invokevirtual 54	android/os/Parcel:recycle	()V
        //   55: return
        //   56: aload_2
        //   57: iconst_0
        //   58: invokevirtual 36	android/os/Parcel:writeInt	(I)V
        //   61: goto -32 -> 29
        //   64: astore_1
        //   65: aload_3
        //   66: invokevirtual 54	android/os/Parcel:recycle	()V
        //   69: aload_2
        //   70: invokevirtual 54	android/os/Parcel:recycle	()V
        //   73: aload_1
        //   74: athrow
        // Local variable table:
        //   start	length	slot	name	signature
        //   0	75	0	this	a
        //   0	75	1	paramOnListEntriesResponse	OnListEntriesResponse
        //   3	67	2	localParcel1	Parcel
        //   7	59	3	localParcel2	Parcel
        // Exception table:
        //   from	to	target	type
        //   8	14	64	finally
        //   18	29	64	finally
        //   29	47	64	finally
        //   56	61	64	finally
      }
      
      /* Error */
      public void a(OnListParentsResponse paramOnListParentsResponse)
      {
        // Byte code:
        //   0: invokestatic 26	android/os/Parcel:obtain	()Landroid/os/Parcel;
        //   3: astore_2
        //   4: invokestatic 26	android/os/Parcel:obtain	()Landroid/os/Parcel;
        //   7: astore_3
        //   8: aload_2
        //   9: ldc 28
        //   11: invokevirtual 32	android/os/Parcel:writeInterfaceToken	(Ljava/lang/String;)V
        //   14: aload_1
        //   15: ifnull +42 -> 57
        //   18: aload_2
        //   19: iconst_1
        //   20: invokevirtual 36	android/os/Parcel:writeInt	(I)V
        //   23: aload_1
        //   24: aload_2
        //   25: iconst_0
        //   26: invokevirtual 70	com/google/android/gms/drive/internal/OnListParentsResponse:writeToParcel	(Landroid/os/Parcel;I)V
        //   29: aload_0
        //   30: getfield 18	com/google/android/gms/drive/internal/ai$a$a:tS	Landroid/os/IBinder;
        //   33: bipush 8
        //   35: aload_2
        //   36: aload_3
        //   37: iconst_0
        //   38: invokeinterface 48 5 0
        //   43: pop
        //   44: aload_3
        //   45: invokevirtual 51	android/os/Parcel:readException	()V
        //   48: aload_3
        //   49: invokevirtual 54	android/os/Parcel:recycle	()V
        //   52: aload_2
        //   53: invokevirtual 54	android/os/Parcel:recycle	()V
        //   56: return
        //   57: aload_2
        //   58: iconst_0
        //   59: invokevirtual 36	android/os/Parcel:writeInt	(I)V
        //   62: goto -33 -> 29
        //   65: astore_1
        //   66: aload_3
        //   67: invokevirtual 54	android/os/Parcel:recycle	()V
        //   70: aload_2
        //   71: invokevirtual 54	android/os/Parcel:recycle	()V
        //   74: aload_1
        //   75: athrow
        // Local variable table:
        //   start	length	slot	name	signature
        //   0	76	0	this	a
        //   0	76	1	paramOnListParentsResponse	OnListParentsResponse
        //   3	68	2	localParcel1	Parcel
        //   7	60	3	localParcel2	Parcel
        // Exception table:
        //   from	to	target	type
        //   8	14	65	finally
        //   18	29	65	finally
        //   29	48	65	finally
        //   57	62	65	finally
      }
      
      /* Error */
      public void a(OnMetadataResponse paramOnMetadataResponse)
      {
        // Byte code:
        //   0: invokestatic 26	android/os/Parcel:obtain	()Landroid/os/Parcel;
        //   3: astore_2
        //   4: invokestatic 26	android/os/Parcel:obtain	()Landroid/os/Parcel;
        //   7: astore_3
        //   8: aload_2
        //   9: ldc 28
        //   11: invokevirtual 32	android/os/Parcel:writeInterfaceToken	(Ljava/lang/String;)V
        //   14: aload_1
        //   15: ifnull +41 -> 56
        //   18: aload_2
        //   19: iconst_1
        //   20: invokevirtual 36	android/os/Parcel:writeInt	(I)V
        //   23: aload_1
        //   24: aload_2
        //   25: iconst_0
        //   26: invokevirtual 74	com/google/android/gms/drive/internal/OnMetadataResponse:writeToParcel	(Landroid/os/Parcel;I)V
        //   29: aload_0
        //   30: getfield 18	com/google/android/gms/drive/internal/ai$a$a:tS	Landroid/os/IBinder;
        //   33: iconst_4
        //   34: aload_2
        //   35: aload_3
        //   36: iconst_0
        //   37: invokeinterface 48 5 0
        //   42: pop
        //   43: aload_3
        //   44: invokevirtual 51	android/os/Parcel:readException	()V
        //   47: aload_3
        //   48: invokevirtual 54	android/os/Parcel:recycle	()V
        //   51: aload_2
        //   52: invokevirtual 54	android/os/Parcel:recycle	()V
        //   55: return
        //   56: aload_2
        //   57: iconst_0
        //   58: invokevirtual 36	android/os/Parcel:writeInt	(I)V
        //   61: goto -32 -> 29
        //   64: astore_1
        //   65: aload_3
        //   66: invokevirtual 54	android/os/Parcel:recycle	()V
        //   69: aload_2
        //   70: invokevirtual 54	android/os/Parcel:recycle	()V
        //   73: aload_1
        //   74: athrow
        // Local variable table:
        //   start	length	slot	name	signature
        //   0	75	0	this	a
        //   0	75	1	paramOnMetadataResponse	OnMetadataResponse
        //   3	67	2	localParcel1	Parcel
        //   7	59	3	localParcel2	Parcel
        // Exception table:
        //   from	to	target	type
        //   8	14	64	finally
        //   18	29	64	finally
        //   29	47	64	finally
        //   56	61	64	finally
      }
      
      public IBinder asBinder()
      {
        return this.tS;
      }
      
      /* Error */
      public void c(Status paramStatus)
      {
        // Byte code:
        //   0: invokestatic 26	android/os/Parcel:obtain	()Landroid/os/Parcel;
        //   3: astore_2
        //   4: invokestatic 26	android/os/Parcel:obtain	()Landroid/os/Parcel;
        //   7: astore_3
        //   8: aload_2
        //   9: ldc 28
        //   11: invokevirtual 32	android/os/Parcel:writeInterfaceToken	(Ljava/lang/String;)V
        //   14: aload_1
        //   15: ifnull +42 -> 57
        //   18: aload_2
        //   19: iconst_1
        //   20: invokevirtual 36	android/os/Parcel:writeInt	(I)V
        //   23: aload_1
        //   24: aload_2
        //   25: iconst_0
        //   26: invokevirtual 81	com/google/android/gms/common/api/Status:writeToParcel	(Landroid/os/Parcel;I)V
        //   29: aload_0
        //   30: getfield 18	com/google/android/gms/drive/internal/ai$a$a:tS	Landroid/os/IBinder;
        //   33: bipush 6
        //   35: aload_2
        //   36: aload_3
        //   37: iconst_0
        //   38: invokeinterface 48 5 0
        //   43: pop
        //   44: aload_3
        //   45: invokevirtual 51	android/os/Parcel:readException	()V
        //   48: aload_3
        //   49: invokevirtual 54	android/os/Parcel:recycle	()V
        //   52: aload_2
        //   53: invokevirtual 54	android/os/Parcel:recycle	()V
        //   56: return
        //   57: aload_2
        //   58: iconst_0
        //   59: invokevirtual 36	android/os/Parcel:writeInt	(I)V
        //   62: goto -33 -> 29
        //   65: astore_1
        //   66: aload_3
        //   67: invokevirtual 54	android/os/Parcel:recycle	()V
        //   70: aload_2
        //   71: invokevirtual 54	android/os/Parcel:recycle	()V
        //   74: aload_1
        //   75: athrow
        // Local variable table:
        //   start	length	slot	name	signature
        //   0	76	0	this	a
        //   0	76	1	paramStatus	Status
        //   3	68	2	localParcel1	Parcel
        //   7	60	3	localParcel2	Parcel
        // Exception table:
        //   from	to	target	type
        //   8	14	65	finally
        //   18	29	65	finally
        //   29	48	65	finally
        //   57	62	65	finally
      }
      
      public void onSuccess()
      {
        Parcel localParcel1 = Parcel.obtain();
        Parcel localParcel2 = Parcel.obtain();
        try
        {
          localParcel1.writeInterfaceToken("com.google.android.gms.drive.internal.IDriveServiceCallbacks");
          this.tS.transact(7, localParcel1, localParcel2, 0);
          localParcel2.readException();
          return;
        }
        finally
        {
          localParcel2.recycle();
          localParcel1.recycle();
        }
      }
    }
  }
}


/* Location:              /Users/amaurremi/uw/stringoid/static-dynamic-comparison/apps/quick pdf scanner/com.mobisystems.mobiscanner-213-dex2jar.jar!/com/google/android/gms/drive/internal/ai.class
 * Java compiler version: 6 (50.0)
 * JD-Core Version:       0.7.1
 */