package com.inmobi.re.controller;

class JSUtilityController$f
        extends Thread {
    JSUtilityController$f(JSUtilityController paramJSUtilityController, String paramString) {
    }

    /* Error */
    public void run() {
        // Byte code:
        //   0: aconst_null
        //   1: astore_2
        //   2: aconst_null
        //   3: astore_3
        //   4: aload_2
        //   5: astore_1
        //   6: aload_0
        //   7: getfield 14	com/inmobi/re/controller/JSUtilityController$f:a	Ljava/lang/String;
        //   10: ldc 23
        //   12: ldc 25
        //   14: invokevirtual 31	java/lang/String:replaceAll	(Ljava/lang/String;Ljava/lang/String;)Ljava/lang/String;
        //   17: astore 4
        //   19: aload_2
        //   20: astore_1
        //   21: ldc 33
        //   23: new 35	java/lang/StringBuilder
        //   26: dup
        //   27: invokespecial 36	java/lang/StringBuilder:<init>	()V
        //   30: ldc 38
        //   32: invokevirtual 42	java/lang/StringBuilder:append	(Ljava/lang/String;)Ljava/lang/StringBuilder;
        //   35: aload 4
        //   37: invokevirtual 42	java/lang/StringBuilder:append	(Ljava/lang/String;)Ljava/lang/StringBuilder;
        //   40: invokevirtual 46	java/lang/StringBuilder:toString	()Ljava/lang/String;
        //   43: invokestatic 52	com/inmobi/commons/internal/Log:debug	(Ljava/lang/String;Ljava/lang/String;)V
        //   46: aload_2
        //   47: astore_1
        //   48: new 54	java/net/URL
        //   51: dup
        //   52: aload 4
        //   54: invokespecial 57	java/net/URL:<init>	(Ljava/lang/String;)V
        //   57: invokevirtual 61	java/net/URL:openConnection	()Ljava/net/URLConnection;
        //   60: checkcast 63	java/net/HttpURLConnection
        //   63: astore_2
        //   64: aload_2
        //   65: sipush 20000
        //   68: invokevirtual 67	java/net/HttpURLConnection:setConnectTimeout	(I)V
        //   71: aload_2
        //   72: ldc 69
        //   74: invokevirtual 72	java/net/HttpURLConnection:setRequestMethod	(Ljava/lang/String;)V
        //   77: aload_2
        //   78: ldc 74
        //   80: invokestatic 79	com/inmobi/commons/internal/InternalSDKUtil:getUserAgent	()Ljava/lang/String;
        //   83: invokevirtual 82	java/net/HttpURLConnection:setRequestProperty	(Ljava/lang/String;Ljava/lang/String;)V
        //   86: ldc 33
        //   88: new 35	java/lang/StringBuilder
        //   91: dup
        //   92: invokespecial 36	java/lang/StringBuilder:<init>	()V
        //   95: ldc 84
        //   97: invokevirtual 42	java/lang/StringBuilder:append	(Ljava/lang/String;)Ljava/lang/StringBuilder;
        //   100: aload_2
        //   101: invokevirtual 88	java/net/HttpURLConnection:getResponseCode	()I
        //   104: invokevirtual 91	java/lang/StringBuilder:append	(I)Ljava/lang/StringBuilder;
        //   107: invokevirtual 46	java/lang/StringBuilder:toString	()Ljava/lang/String;
        //   110: invokestatic 52	com/inmobi/commons/internal/Log:debug	(Ljava/lang/String;Ljava/lang/String;)V
        //   113: aload_2
        //   114: ifnull +7 -> 121
        //   117: aload_2
        //   118: invokevirtual 94	java/net/HttpURLConnection:disconnect	()V
        //   121: return
        //   122: astore_1
        //   123: aload_3
        //   124: astore_2
        //   125: aload_1
        //   126: astore_3
        //   127: aload_2
        //   128: astore_1
        //   129: ldc 33
        //   131: ldc 96
        //   133: aload_3
        //   134: invokestatic 99	com/inmobi/commons/internal/Log:debug	(Ljava/lang/String;Ljava/lang/String;Ljava/lang/Throwable;)V
        //   137: aload_2
        //   138: ifnull -17 -> 121
        //   141: aload_2
        //   142: invokevirtual 94	java/net/HttpURLConnection:disconnect	()V
        //   145: return
        //   146: astore_3
        //   147: aload_1
        //   148: astore_2
        //   149: aload_3
        //   150: astore_1
        //   151: aload_2
        //   152: ifnull +7 -> 159
        //   155: aload_2
        //   156: invokevirtual 94	java/net/HttpURLConnection:disconnect	()V
        //   159: aload_1
        //   160: athrow
        //   161: astore_1
        //   162: goto -11 -> 151
        //   165: astore_3
        //   166: goto -39 -> 127
        // Local variable table:
        //   start	length	slot	name	signature
        //   0	169	0	this	f
        //   5	43	1	localObject1	Object
        //   122	4	1	localException1	Exception
        //   128	32	1	localObject2	Object
        //   161	1	1	localObject3	Object
        //   1	155	2	localObject4	Object
        //   3	131	3	localObject5	Object
        //   146	4	3	localObject6	Object
        //   165	1	3	localException2	Exception
        //   17	36	4	str	String
        // Exception table:
        //   from	to	target	type
        //   6	19	122	java/lang/Exception
        //   21	46	122	java/lang/Exception
        //   48	64	122	java/lang/Exception
        //   6	19	146	finally
        //   21	46	146	finally
        //   48	64	146	finally
        //   129	137	146	finally
        //   64	113	161	finally
        //   64	113	165	java/lang/Exception
    }
}


/* Location:              /Users/amaurremi/uw/stringoid stuff/static vs dynamic/ifunny/mobi.ifunny-2447-dex2jar.jar!/com/inmobi/re/controller/JSUtilityController$f.class
 * Java compiler version: 6 (50.0)
 * JD-Core Version:       0.7.1
 */