package com.inmobi.re.controller;

import com.inmobi.re.controller.util.StartActivityForResultCallback;

class JSUtilityController$a
        implements StartActivityForResultCallback {
    JSUtilityController$a(JSUtilityController paramJSUtilityController, String paramString1, String paramString2, String paramString3) {
    }

    /* Error */
    public void onActivityResult(int paramInt, android.content.Intent paramIntent) {
        // Byte code:
        //   0: aload_0
        //   1: getfield 16	com/inmobi/re/controller/JSUtilityController$a:d	Lcom/inmobi/re/controller/JSUtilityController;
        //   4: ldc 34
        //   6: invokevirtual 39	com/inmobi/re/controller/JSUtilityController:a	(Ljava/lang/String;)Z
        //   9: ifeq +424 -> 433
        //   12: aload_0
        //   13: getfield 16	com/inmobi/re/controller/JSUtilityController$a:d	Lcom/inmobi/re/controller/JSUtilityController;
        //   16: ldc 41
        //   18: invokevirtual 39	com/inmobi/re/controller/JSUtilityController:a	(Ljava/lang/String;)Z
        //   21: ifeq +412 -> 433
        //   24: aload_0
        //   25: getfield 16	com/inmobi/re/controller/JSUtilityController$a:d	Lcom/inmobi/re/controller/JSUtilityController;
        //   28: invokestatic 44	com/inmobi/re/controller/JSUtilityController:a	(Lcom/inmobi/re/controller/JSUtilityController;)I
        //   31: istore_1
        //   32: aload_0
        //   33: getfield 16	com/inmobi/re/controller/JSUtilityController$a:d	Lcom/inmobi/re/controller/JSUtilityController;
        //   36: getfield 47	com/inmobi/re/controller/JSUtilityController:c	I
        //   39: iload_1
        //   40: if_icmpne +11 -> 51
        //   43: ldc 49
        //   45: ldc 51
        //   47: invokestatic 57	com/inmobi/commons/internal/Log:internal	(Ljava/lang/String;Ljava/lang/String;)V
        //   50: return
        //   51: getstatic 62	android/os/Build$VERSION:SDK_INT	I
        //   54: bipush 8
        //   56: if_icmplt +143 -> 199
        //   59: ldc 64
        //   61: invokestatic 70	android/net/Uri:parse	(Ljava/lang/String;)Landroid/net/Uri;
        //   64: astore_2
        //   65: aload_0
        //   66: getfield 16	com/inmobi/re/controller/JSUtilityController$a:d	Lcom/inmobi/re/controller/JSUtilityController;
        //   69: getfield 74	com/inmobi/re/controller/JSUtilityController:imWebView	Lcom/inmobi/re/container/IMWebView;
        //   72: invokevirtual 80	com/inmobi/re/container/IMWebView:getActivity	()Landroid/app/Activity;
        //   75: invokevirtual 86	android/app/Activity:getContentResolver	()Landroid/content/ContentResolver;
        //   78: astore 4
        //   80: new 88	android/content/ContentValues
        //   83: dup
        //   84: invokespecial 89	android/content/ContentValues:<init>	()V
        //   87: astore 5
        //   89: aload_0
        //   90: getfield 18	com/inmobi/re/controller/JSUtilityController$a:a	Ljava/lang/String;
        //   93: ldc 91
        //   95: invokevirtual 97	java/lang/String:equals	(Ljava/lang/Object;)Z
        //   98: ifeq +110 -> 208
        //   101: aload 5
        //   103: ldc 99
        //   105: iconst_0
        //   106: invokestatic 105	java/lang/Integer:valueOf	(I)Ljava/lang/Integer;
        //   109: invokevirtual 109	android/content/ContentValues:put	(Ljava/lang/String;Ljava/lang/Integer;)V
        //   112: aload 4
        //   114: aload_2
        //   115: aload_0
        //   116: getfield 16	com/inmobi/re/controller/JSUtilityController$a:d	Lcom/inmobi/re/controller/JSUtilityController;
        //   119: invokestatic 44	com/inmobi/re/controller/JSUtilityController:a	(Lcom/inmobi/re/controller/JSUtilityController;)I
        //   122: i2l
        //   123: invokestatic 115	android/content/ContentUris:withAppendedId	(Landroid/net/Uri;J)Landroid/net/Uri;
        //   126: aload 5
        //   128: aconst_null
        //   129: aconst_null
        //   130: invokevirtual 121	android/content/ContentResolver:update	(Landroid/net/Uri;Landroid/content/ContentValues;Ljava/lang/String;[Ljava/lang/String;)I
        //   133: pop
        //   134: aload_0
        //   135: getfield 20	com/inmobi/re/controller/JSUtilityController$a:b	Ljava/lang/String;
        //   138: ifnull +295 -> 433
        //   141: ldc 123
        //   143: aload_0
        //   144: getfield 20	com/inmobi/re/controller/JSUtilityController$a:b	Ljava/lang/String;
        //   147: invokevirtual 97	java/lang/String:equals	(Ljava/lang/Object;)Z
        //   150: istore_3
        //   151: iload_3
        //   152: ifne +281 -> 433
        //   155: aload_0
        //   156: getfield 20	com/inmobi/re/controller/JSUtilityController$a:b	Ljava/lang/String;
        //   159: invokestatic 127	java/lang/Integer:parseInt	(Ljava/lang/String;)I
        //   162: ldc -128
        //   164: idiv
        //   165: istore_1
        //   166: iload_1
        //   167: ifle +140 -> 307
        //   170: aload_0
        //   171: getfield 16	com/inmobi/re/controller/JSUtilityController$a:d	Lcom/inmobi/re/controller/JSUtilityController;
        //   174: getfield 74	com/inmobi/re/controller/JSUtilityController:imWebView	Lcom/inmobi/re/container/IMWebView;
        //   177: ldc -126
        //   179: ldc -124
        //   181: invokevirtual 135	com/inmobi/re/container/IMWebView:raiseError	(Ljava/lang/String;Ljava/lang/String;)V
        //   184: return
        //   185: astore_2
        //   186: aload_2
        //   187: invokevirtual 138	java/lang/Exception:printStackTrace	()V
        //   190: ldc 49
        //   192: ldc -116
        //   194: aload_2
        //   195: invokestatic 143	com/inmobi/commons/internal/Log:internal	(Ljava/lang/String;Ljava/lang/String;Ljava/lang/Throwable;)V
        //   198: return
        //   199: ldc -111
        //   201: invokestatic 70	android/net/Uri:parse	(Ljava/lang/String;)Landroid/net/Uri;
        //   204: astore_2
        //   205: goto -140 -> 65
        //   208: aload_0
        //   209: getfield 18	com/inmobi/re/controller/JSUtilityController$a:a	Ljava/lang/String;
        //   212: ldc -109
        //   214: invokevirtual 97	java/lang/String:equals	(Ljava/lang/Object;)Z
        //   217: ifeq +17 -> 234
        //   220: aload 5
        //   222: ldc 99
        //   224: iconst_1
        //   225: invokestatic 105	java/lang/Integer:valueOf	(I)Ljava/lang/Integer;
        //   228: invokevirtual 109	android/content/ContentValues:put	(Ljava/lang/String;Ljava/lang/Integer;)V
        //   231: goto -119 -> 112
        //   234: aload_0
        //   235: getfield 18	com/inmobi/re/controller/JSUtilityController$a:a	Ljava/lang/String;
        //   238: ldc -107
        //   240: invokevirtual 97	java/lang/String:equals	(Ljava/lang/Object;)Z
        //   243: ifeq -131 -> 112
        //   246: aload 5
        //   248: ldc 99
        //   250: iconst_2
        //   251: invokestatic 105	java/lang/Integer:valueOf	(I)Ljava/lang/Integer;
        //   254: invokevirtual 109	android/content/ContentValues:put	(Ljava/lang/String;Ljava/lang/Integer;)V
        //   257: goto -145 -> 112
        //   260: astore 5
        //   262: aload_0
        //   263: getfield 20	com/inmobi/re/controller/JSUtilityController$a:b	Ljava/lang/String;
        //   266: invokestatic 153	com/inmobi/re/controller/JSUtilityController:convertDateString	(Ljava/lang/String;)Ljava/util/GregorianCalendar;
        //   269: invokevirtual 159	java/util/GregorianCalendar:getTimeInMillis	()J
        //   272: aload_0
        //   273: getfield 22	com/inmobi/re/controller/JSUtilityController$a:c	Ljava/lang/String;
        //   276: invokestatic 153	com/inmobi/re/controller/JSUtilityController:convertDateString	(Ljava/lang/String;)Ljava/util/GregorianCalendar;
        //   279: invokevirtual 159	java/util/GregorianCalendar:getTimeInMillis	()J
        //   282: lsub
        //   283: l2i
        //   284: ldc -128
        //   286: idiv
        //   287: istore_1
        //   288: goto -122 -> 166
        //   291: astore_2
        //   292: aload_0
        //   293: getfield 16	com/inmobi/re/controller/JSUtilityController$a:d	Lcom/inmobi/re/controller/JSUtilityController;
        //   296: getfield 74	com/inmobi/re/controller/JSUtilityController:imWebView	Lcom/inmobi/re/container/IMWebView;
        //   299: ldc -95
        //   301: ldc -124
        //   303: invokevirtual 135	com/inmobi/re/container/IMWebView:raiseError	(Ljava/lang/String;Ljava/lang/String;)V
        //   306: return
        //   307: iload_1
        //   308: ineg
        //   309: istore_1
        //   310: new 88	android/content/ContentValues
        //   313: dup
        //   314: invokespecial 89	android/content/ContentValues:<init>	()V
        //   317: astore 5
        //   319: aload 5
        //   321: ldc -93
        //   323: iconst_1
        //   324: invokestatic 105	java/lang/Integer:valueOf	(I)Ljava/lang/Integer;
        //   327: invokevirtual 109	android/content/ContentValues:put	(Ljava/lang/String;Ljava/lang/Integer;)V
        //   330: aload 4
        //   332: aload_2
        //   333: aload_0
        //   334: getfield 16	com/inmobi/re/controller/JSUtilityController$a:d	Lcom/inmobi/re/controller/JSUtilityController;
        //   337: invokestatic 44	com/inmobi/re/controller/JSUtilityController:a	(Lcom/inmobi/re/controller/JSUtilityController;)I
        //   340: i2l
        //   341: invokestatic 115	android/content/ContentUris:withAppendedId	(Landroid/net/Uri;J)Landroid/net/Uri;
        //   344: aload 5
        //   346: aconst_null
        //   347: aconst_null
        //   348: invokevirtual 121	android/content/ContentResolver:update	(Landroid/net/Uri;Landroid/content/ContentValues;Ljava/lang/String;[Ljava/lang/String;)I
        //   351: pop
        //   352: getstatic 62	android/os/Build$VERSION:SDK_INT	I
        //   355: bipush 8
        //   357: if_icmplt +67 -> 424
        //   360: ldc -91
        //   362: invokestatic 70	android/net/Uri:parse	(Ljava/lang/String;)Landroid/net/Uri;
        //   365: astore_2
        //   366: new 88	android/content/ContentValues
        //   369: dup
        //   370: invokespecial 89	android/content/ContentValues:<init>	()V
        //   373: astore 5
        //   375: aload 5
        //   377: ldc -89
        //   379: aload_0
        //   380: getfield 16	com/inmobi/re/controller/JSUtilityController$a:d	Lcom/inmobi/re/controller/JSUtilityController;
        //   383: invokestatic 44	com/inmobi/re/controller/JSUtilityController:a	(Lcom/inmobi/re/controller/JSUtilityController;)I
        //   386: invokestatic 105	java/lang/Integer:valueOf	(I)Ljava/lang/Integer;
        //   389: invokevirtual 109	android/content/ContentValues:put	(Ljava/lang/String;Ljava/lang/Integer;)V
        //   392: aload 5
        //   394: ldc -87
        //   396: iconst_1
        //   397: invokestatic 105	java/lang/Integer:valueOf	(I)Ljava/lang/Integer;
        //   400: invokevirtual 109	android/content/ContentValues:put	(Ljava/lang/String;Ljava/lang/Integer;)V
        //   403: aload 5
        //   405: ldc -85
        //   407: iload_1
        //   408: invokestatic 105	java/lang/Integer:valueOf	(I)Ljava/lang/Integer;
        //   411: invokevirtual 109	android/content/ContentValues:put	(Ljava/lang/String;Ljava/lang/Integer;)V
        //   414: aload 4
        //   416: aload_2
        //   417: aload 5
        //   419: invokevirtual 175	android/content/ContentResolver:insert	(Landroid/net/Uri;Landroid/content/ContentValues;)Landroid/net/Uri;
        //   422: pop
        //   423: return
        //   424: ldc -79
        //   426: invokestatic 70	android/net/Uri:parse	(Ljava/lang/String;)Landroid/net/Uri;
        //   429: astore_2
        //   430: goto -64 -> 366
        //   433: return
        // Local variable table:
        //   start	length	slot	name	signature
        //   0	434	0	this	a
        //   0	434	1	paramInt	int
        //   0	434	2	paramIntent	android.content.Intent
        //   150	2	3	bool	boolean
        //   78	337	4	localContentResolver	android.content.ContentResolver
        //   87	160	5	localContentValues1	android.content.ContentValues
        //   260	1	5	localNumberFormatException	NumberFormatException
        //   317	101	5	localContentValues2	android.content.ContentValues
        // Exception table:
        //   from	to	target	type
        //   0	50	185	java/lang/Exception
        //   51	65	185	java/lang/Exception
        //   65	112	185	java/lang/Exception
        //   112	151	185	java/lang/Exception
        //   155	166	185	java/lang/Exception
        //   170	184	185	java/lang/Exception
        //   199	205	185	java/lang/Exception
        //   208	231	185	java/lang/Exception
        //   234	257	185	java/lang/Exception
        //   292	306	185	java/lang/Exception
        //   310	366	185	java/lang/Exception
        //   366	423	185	java/lang/Exception
        //   424	430	185	java/lang/Exception
        //   155	166	260	java/lang/NumberFormatException
        //   262	288	291	java/lang/Exception
    }
}


/* Location:              /Users/amaurremi/uw/stringoid stuff/static vs dynamic/ifunny/mobi.ifunny-2447-dex2jar.jar!/com/inmobi/re/controller/JSUtilityController$a.class
 * Java compiler version: 6 (50.0)
 * JD-Core Version:       0.7.1
 */