package com.millennialmedia.android;

class HandShake$1
        implements Runnable {
    HandShake$1(HandShake paramHandShake, boolean paramBoolean) {
    }

    /* Error */
    public void run() {
        // Byte code:
        //   0: aload_0
        //   1: getfield 14	com/millennialmedia/android/HandShake$1:b	Lcom/millennialmedia/android/HandShake;
        //   4: invokestatic 30	com/millennialmedia/android/HandShake:a	(Lcom/millennialmedia/android/HandShake;)Ljava/lang/ref/WeakReference;
        //   7: invokevirtual 36	java/lang/ref/WeakReference:get	()Ljava/lang/Object;
        //   10: checkcast 38	android/content/Context
        //   13: astore 6
        //   15: aload 6
        //   17: ifnonnull +770 -> 787
        //   20: aload_0
        //   21: getfield 14	com/millennialmedia/android/HandShake$1:b	Lcom/millennialmedia/android/HandShake;
        //   24: invokestatic 40	com/millennialmedia/android/HandShake:b	(Lcom/millennialmedia/android/HandShake;)Ljava/lang/ref/WeakReference;
        //   27: invokevirtual 36	java/lang/ref/WeakReference:get	()Ljava/lang/Object;
        //   30: checkcast 38	android/content/Context
        //   33: astore 6
        //   35: aload 6
        //   37: ifnonnull +4 -> 41
        //   40: return
        //   41: new 42	java/lang/StringBuilder
        //   44: dup
        //   45: invokespecial 43	java/lang/StringBuilder:<init>	()V
        //   48: astore 7
        //   50: new 45	java/util/TreeMap
        //   53: dup
        //   54: invokespecial 46	java/util/TreeMap:<init>	()V
        //   57: astore 4
        //   59: aload 4
        //   61: ldc 48
        //   63: new 42	java/lang/StringBuilder
        //   66: dup
        //   67: invokespecial 43	java/lang/StringBuilder:<init>	()V
        //   70: ldc 50
        //   72: invokevirtual 54	java/lang/StringBuilder:append	(Ljava/lang/String;)Ljava/lang/StringBuilder;
        //   75: getstatic 60	android/os/Build:MODEL	Ljava/lang/String;
        //   78: invokevirtual 54	java/lang/StringBuilder:append	(Ljava/lang/String;)Ljava/lang/StringBuilder;
        //   81: invokevirtual 64	java/lang/StringBuilder:toString	()Ljava/lang/String;
        //   84: invokeinterface 70 3 0
        //   89: pop
        //   90: aload_0
        //   91: getfield 14	com/millennialmedia/android/HandShake$1:b	Lcom/millennialmedia/android/HandShake;
        //   94: aload 6
        //   96: invokestatic 73	com/millennialmedia/android/HandShake:a	(Lcom/millennialmedia/android/HandShake;Landroid/content/Context;)Z
        //   99: istore_2
        //   100: iload_2
        //   101: ifeq +17 -> 118
        //   104: iload_2
        //   105: istore_3
        //   106: aload 4
        //   108: ldc 75
        //   110: ldc 77
        //   112: invokeinterface 70 3 0
        //   117: pop
        //   118: iload_2
        //   119: istore_3
        //   120: aload_0
        //   121: getfield 16	com/millennialmedia/android/HandShake$1:a	Z
        //   124: ifeq +17 -> 141
        //   127: iload_2
        //   128: istore_3
        //   129: aload 4
        //   131: ldc 79
        //   133: ldc 77
        //   135: invokeinterface 70 3 0
        //   140: pop
        //   141: iload_2
        //   142: istore_3
        //   143: aload 6
        //   145: aload 4
        //   147: invokestatic 84	com/millennialmedia/android/MMSDK:a	(Landroid/content/Context;Ljava/util/Map;)V
        //   150: iload_2
        //   151: istore_3
        //   152: aload 4
        //   154: invokeinterface 88 1 0
        //   159: invokeinterface 94 1 0
        //   164: astore 4
        //   166: iload_2
        //   167: istore_3
        //   168: aload 4
        //   170: invokeinterface 100 1 0
        //   175: ifeq +97 -> 272
        //   178: iload_2
        //   179: istore_3
        //   180: aload 4
        //   182: invokeinterface 103 1 0
        //   187: checkcast 105	java/util/Map$Entry
        //   190: astore 5
        //   192: iload_2
        //   193: istore_3
        //   194: aload 7
        //   196: ldc 107
        //   198: iconst_2
        //   199: anewarray 4	java/lang/Object
        //   202: dup
        //   203: iconst_0
        //   204: aload 5
        //   206: invokeinterface 110 1 0
        //   211: aastore
        //   212: dup
        //   213: iconst_1
        //   214: aload 5
        //   216: invokeinterface 113 1 0
        //   221: checkcast 115	java/lang/String
        //   224: ldc 117
        //   226: invokestatic 123	java/net/URLEncoder:encode	(Ljava/lang/String;Ljava/lang/String;)Ljava/lang/String;
        //   229: aastore
        //   230: invokestatic 127	java/lang/String:format	(Ljava/lang/String;[Ljava/lang/Object;)Ljava/lang/String;
        //   233: invokevirtual 54	java/lang/StringBuilder:append	(Ljava/lang/String;)Ljava/lang/StringBuilder;
        //   236: pop
        //   237: goto -71 -> 166
        //   240: astore 4
        //   242: iload_2
        //   243: istore_3
        //   244: ldc -127
        //   246: ldc -125
        //   248: aload 4
        //   250: invokestatic 136	com/millennialmedia/android/MMLog:a	(Ljava/lang/String;Ljava/lang/String;Ljava/lang/Throwable;)V
        //   253: return
        //   254: astore 4
        //   256: iload_3
        //   257: ifeq +12 -> 269
        //   260: aload_0
        //   261: getfield 14	com/millennialmedia/android/HandShake$1:b	Lcom/millennialmedia/android/HandShake;
        //   264: aload 6
        //   266: invokestatic 140	com/millennialmedia/android/HandShake:c	(Lcom/millennialmedia/android/HandShake;Landroid/content/Context;)V
        //   269: aload 4
        //   271: athrow
        //   272: iload_2
        //   273: istore_3
        //   274: new 42	java/lang/StringBuilder
        //   277: dup
        //   278: invokespecial 43	java/lang/StringBuilder:<init>	()V
        //   281: invokestatic 143	com/millennialmedia/android/HandShake:d	()Ljava/lang/String;
        //   284: invokevirtual 54	java/lang/StringBuilder:append	(Ljava/lang/String;)Ljava/lang/StringBuilder;
        //   287: getstatic 145	com/millennialmedia/android/HandShake:a	Ljava/lang/String;
        //   290: invokevirtual 54	java/lang/StringBuilder:append	(Ljava/lang/String;)Ljava/lang/StringBuilder;
        //   293: aload 7
        //   295: invokevirtual 64	java/lang/StringBuilder:toString	()Ljava/lang/String;
        //   298: invokevirtual 54	java/lang/StringBuilder:append	(Ljava/lang/String;)Ljava/lang/StringBuilder;
        //   301: invokevirtual 64	java/lang/StringBuilder:toString	()Ljava/lang/String;
        //   304: astore 5
        //   306: iload_2
        //   307: istore_3
        //   308: ldc -127
        //   310: ldc -109
        //   312: iconst_1
        //   313: anewarray 4	java/lang/Object
        //   316: dup
        //   317: iconst_0
        //   318: aload 5
        //   320: aastore
        //   321: invokestatic 127	java/lang/String:format	(Ljava/lang/String;[Ljava/lang/Object;)Ljava/lang/String;
        //   324: invokestatic 150	com/millennialmedia/android/MMLog:a	(Ljava/lang/String;Ljava/lang/String;)V
        //   327: aconst_null
        //   328: astore 4
        //   330: iload_2
        //   331: istore_3
        //   332: new 152	com/millennialmedia/android/HttpGetRequest
        //   335: dup
        //   336: sipush 3000
        //   339: invokespecial 155	com/millennialmedia/android/HttpGetRequest:<init>	(I)V
        //   342: aload 5
        //   344: invokevirtual 158	com/millennialmedia/android/HttpGetRequest:a	(Ljava/lang/String;)Lorg/apache/http/HttpResponse;
        //   347: astore 5
        //   349: aload 5
        //   351: astore 4
        //   353: aload 4
        //   355: ifnull +29 -> 384
        //   358: iload_2
        //   359: istore_3
        //   360: aload 4
        //   362: invokeinterface 164 1 0
        //   367: invokeinterface 170 1 0
        //   372: istore_1
        //   373: aload 4
        //   375: astore 5
        //   377: iload_1
        //   378: sipush 200
        //   381: if_icmpeq +90 -> 471
        //   384: iload_2
        //   385: istore_3
        //   386: invokestatic 143	com/millennialmedia/android/HandShake:d	()Ljava/lang/String;
        //   389: ldc -84
        //   391: ldc -82
        //   393: invokevirtual 177	java/lang/String:replaceFirst	(Ljava/lang/String;Ljava/lang/String;)Ljava/lang/String;
        //   396: invokestatic 181	com/millennialmedia/android/HandShake:f	(Ljava/lang/String;)Ljava/lang/String;
        //   399: pop
        //   400: iload_2
        //   401: istore_3
        //   402: new 42	java/lang/StringBuilder
        //   405: dup
        //   406: invokespecial 43	java/lang/StringBuilder:<init>	()V
        //   409: invokestatic 143	com/millennialmedia/android/HandShake:d	()Ljava/lang/String;
        //   412: invokevirtual 54	java/lang/StringBuilder:append	(Ljava/lang/String;)Ljava/lang/StringBuilder;
        //   415: getstatic 145	com/millennialmedia/android/HandShake:a	Ljava/lang/String;
        //   418: invokevirtual 54	java/lang/StringBuilder:append	(Ljava/lang/String;)Ljava/lang/StringBuilder;
        //   421: aload 7
        //   423: invokevirtual 64	java/lang/StringBuilder:toString	()Ljava/lang/String;
        //   426: invokevirtual 54	java/lang/StringBuilder:append	(Ljava/lang/String;)Ljava/lang/StringBuilder;
        //   429: invokevirtual 64	java/lang/StringBuilder:toString	()Ljava/lang/String;
        //   432: astore 5
        //   434: iload_2
        //   435: istore_3
        //   436: ldc -127
        //   438: ldc -73
        //   440: iconst_1
        //   441: anewarray 4	java/lang/Object
        //   444: dup
        //   445: iconst_0
        //   446: aload 5
        //   448: aastore
        //   449: invokestatic 127	java/lang/String:format	(Ljava/lang/String;[Ljava/lang/Object;)Ljava/lang/String;
        //   452: invokestatic 150	com/millennialmedia/android/MMLog:a	(Ljava/lang/String;Ljava/lang/String;)V
        //   455: iload_2
        //   456: istore_3
        //   457: new 152	com/millennialmedia/android/HttpGetRequest
        //   460: dup
        //   461: invokespecial 184	com/millennialmedia/android/HttpGetRequest:<init>	()V
        //   464: aload 5
        //   466: invokevirtual 158	com/millennialmedia/android/HttpGetRequest:a	(Ljava/lang/String;)Lorg/apache/http/HttpResponse;
        //   469: astore 5
        //   471: aload 5
        //   473: ifnull +25 -> 498
        //   476: iload_2
        //   477: istore_3
        //   478: aload 5
        //   480: invokeinterface 164 1 0
        //   485: invokeinterface 170 1 0
        //   490: istore_1
        //   491: iload_1
        //   492: sipush 200
        //   495: if_icmpeq +259 -> 754
        //   498: iload_2
        //   499: istore_3
        //   500: new 42	java/lang/StringBuilder
        //   503: dup
        //   504: invokespecial 43	java/lang/StringBuilder:<init>	()V
        //   507: ldc -70
        //   509: invokevirtual 54	java/lang/StringBuilder:append	(Ljava/lang/String;)Ljava/lang/StringBuilder;
        //   512: getstatic 145	com/millennialmedia/android/HandShake:a	Ljava/lang/String;
        //   515: invokevirtual 54	java/lang/StringBuilder:append	(Ljava/lang/String;)Ljava/lang/StringBuilder;
        //   518: aload 7
        //   520: invokevirtual 64	java/lang/StringBuilder:toString	()Ljava/lang/String;
        //   523: invokevirtual 54	java/lang/StringBuilder:append	(Ljava/lang/String;)Ljava/lang/StringBuilder;
        //   526: invokevirtual 64	java/lang/StringBuilder:toString	()Ljava/lang/String;
        //   529: astore 4
        //   531: iload_2
        //   532: istore_3
        //   533: ldc -127
        //   535: new 42	java/lang/StringBuilder
        //   538: dup
        //   539: invokespecial 43	java/lang/StringBuilder:<init>	()V
        //   542: ldc -68
        //   544: invokevirtual 54	java/lang/StringBuilder:append	(Ljava/lang/String;)Ljava/lang/StringBuilder;
        //   547: aload 4
        //   549: invokevirtual 54	java/lang/StringBuilder:append	(Ljava/lang/String;)Ljava/lang/StringBuilder;
        //   552: invokevirtual 64	java/lang/StringBuilder:toString	()Ljava/lang/String;
        //   555: invokestatic 150	com/millennialmedia/android/MMLog:a	(Ljava/lang/String;Ljava/lang/String;)V
        //   558: iload_2
        //   559: istore_3
        //   560: new 152	com/millennialmedia/android/HttpGetRequest
        //   563: dup
        //   564: invokespecial 184	com/millennialmedia/android/HttpGetRequest:<init>	()V
        //   567: aload 4
        //   569: invokevirtual 158	com/millennialmedia/android/HttpGetRequest:a	(Ljava/lang/String;)Lorg/apache/http/HttpResponse;
        //   572: astore 4
        //   574: aload 4
        //   576: ifnull +185 -> 761
        //   579: iload_2
        //   580: istore_3
        //   581: aload 4
        //   583: invokeinterface 164 1 0
        //   588: invokeinterface 170 1 0
        //   593: sipush 200
        //   596: if_icmpne +165 -> 761
        //   599: iload_2
        //   600: istore_3
        //   601: aload_0
        //   602: getfield 14	com/millennialmedia/android/HandShake$1:b	Lcom/millennialmedia/android/HandShake;
        //   605: aload_0
        //   606: getfield 14	com/millennialmedia/android/HandShake$1:b	Lcom/millennialmedia/android/HandShake;
        //   609: aload 4
        //   611: invokeinterface 192 1 0
        //   616: invokeinterface 198 1 0
        //   621: invokestatic 201	com/millennialmedia/android/HttpGetRequest:a	(Ljava/io/InputStream;)Ljava/lang/String;
        //   624: invokestatic 204	com/millennialmedia/android/HandShake:a	(Lcom/millennialmedia/android/HandShake;Ljava/lang/String;)Lorg/json/JSONObject;
        //   627: invokestatic 207	com/millennialmedia/android/HandShake:a	(Lcom/millennialmedia/android/HandShake;Lorg/json/JSONObject;)V
        //   630: iload_2
        //   631: istore_3
        //   632: aload_0
        //   633: getfield 14	com/millennialmedia/android/HandShake$1:b	Lcom/millennialmedia/android/HandShake;
        //   636: aload 6
        //   638: invokestatic 209	com/millennialmedia/android/HandShake:b	(Lcom/millennialmedia/android/HandShake;Landroid/content/Context;)V
        //   641: iload_2
        //   642: istore_3
        //   643: aload_0
        //   644: getfield 14	com/millennialmedia/android/HandShake$1:b	Lcom/millennialmedia/android/HandShake;
        //   647: invokestatic 213	com/millennialmedia/android/HandShake:e	(Lcom/millennialmedia/android/HandShake;)Landroid/os/Handler;
        //   650: aload_0
        //   651: getfield 14	com/millennialmedia/android/HandShake$1:b	Lcom/millennialmedia/android/HandShake;
        //   654: invokestatic 216	com/millennialmedia/android/HandShake:c	(Lcom/millennialmedia/android/HandShake;)Ljava/lang/Runnable;
        //   657: aload_0
        //   658: getfield 14	com/millennialmedia/android/HandShake$1:b	Lcom/millennialmedia/android/HandShake;
        //   661: invokestatic 219	com/millennialmedia/android/HandShake:d	(Lcom/millennialmedia/android/HandShake;)J
        //   664: invokevirtual 225	android/os/Handler:postDelayed	(Ljava/lang/Runnable;J)Z
        //   667: pop
        //   668: iload_2
        //   669: istore_3
        //   670: ldc -127
        //   672: ldc -29
        //   674: invokestatic 150	com/millennialmedia/android/MMLog:a	(Ljava/lang/String;Ljava/lang/String;)V
        //   677: iload_2
        //   678: ifeq -638 -> 40
        //   681: aload_0
        //   682: getfield 14	com/millennialmedia/android/HandShake$1:b	Lcom/millennialmedia/android/HandShake;
        //   685: aload 6
        //   687: invokestatic 140	com/millennialmedia/android/HandShake:c	(Lcom/millennialmedia/android/HandShake;Landroid/content/Context;)V
        //   690: return
        //   691: astore 5
        //   693: iload_2
        //   694: istore_3
        //   695: ldc -127
        //   697: ldc -125
        //   699: aload 5
        //   701: invokestatic 136	com/millennialmedia/android/MMLog:a	(Ljava/lang/String;Ljava/lang/String;Ljava/lang/Throwable;)V
        //   704: goto -351 -> 353
        //   707: astore 4
        //   709: iload_2
        //   710: istore_3
        //   711: ldc -127
        //   713: ldc -125
        //   715: aload 4
        //   717: invokestatic 136	com/millennialmedia/android/MMLog:a	(Ljava/lang/String;Ljava/lang/String;Ljava/lang/Throwable;)V
        //   720: return
        //   721: astore 5
        //   723: iload_2
        //   724: istore_3
        //   725: ldc -127
        //   727: ldc -125
        //   729: aload 5
        //   731: invokestatic 136	com/millennialmedia/android/MMLog:a	(Ljava/lang/String;Ljava/lang/String;Ljava/lang/Throwable;)V
        //   734: aload 4
        //   736: astore 5
        //   738: goto -267 -> 471
        //   741: astore 4
        //   743: iload_2
        //   744: istore_3
        //   745: ldc -127
        //   747: ldc -125
        //   749: aload 4
        //   751: invokestatic 136	com/millennialmedia/android/MMLog:a	(Ljava/lang/String;Ljava/lang/String;Ljava/lang/Throwable;)V
        //   754: aload 5
        //   756: astore 4
        //   758: goto -184 -> 574
        //   761: iconst_0
        //   762: istore_2
        //   763: goto -86 -> 677
        //   766: astore 4
        //   768: iconst_0
        //   769: istore_3
        //   770: goto -514 -> 256
        //   773: astore 4
        //   775: iconst_0
        //   776: istore_2
        //   777: goto -68 -> 709
        //   780: astore 4
        //   782: iconst_0
        //   783: istore_2
        //   784: goto -542 -> 242
        //   787: goto -752 -> 35
        // Local variable table:
        //   start	length	slot	name	signature
        //   0	790	0	this	1
        //   372	124	1	i	int
        //   99	685	2	bool1	boolean
        //   105	665	3	bool2	boolean
        //   57	124	4	localObject1	Object
        //   240	9	4	localIOException1	java.io.IOException
        //   254	16	4	localObject2	Object
        //   328	282	4	localObject3	Object
        //   707	28	4	localException1	Exception
        //   741	9	4	localIOException2	java.io.IOException
        //   756	1	4	localObject4	Object
        //   766	1	4	localObject5	Object
        //   773	1	4	localException2	Exception
        //   780	1	4	localIOException3	java.io.IOException
        //   190	289	5	localObject6	Object
        //   691	9	5	localIOException4	java.io.IOException
        //   721	9	5	localIOException5	java.io.IOException
        //   736	19	5	localException3	Exception
        //   13	673	6	localContext	android.content.Context
        //   48	471	7	localStringBuilder	StringBuilder
        // Exception table:
        //   from	to	target	type
        //   106	118	240	java/io/IOException
        //   120	127	240	java/io/IOException
        //   129	141	240	java/io/IOException
        //   143	150	240	java/io/IOException
        //   152	166	240	java/io/IOException
        //   168	178	240	java/io/IOException
        //   180	192	240	java/io/IOException
        //   194	237	240	java/io/IOException
        //   274	306	240	java/io/IOException
        //   308	327	240	java/io/IOException
        //   360	373	240	java/io/IOException
        //   478	491	240	java/io/IOException
        //   581	599	240	java/io/IOException
        //   601	630	240	java/io/IOException
        //   632	641	240	java/io/IOException
        //   643	668	240	java/io/IOException
        //   670	677	240	java/io/IOException
        //   695	704	240	java/io/IOException
        //   725	734	240	java/io/IOException
        //   745	754	240	java/io/IOException
        //   106	118	254	finally
        //   120	127	254	finally
        //   129	141	254	finally
        //   143	150	254	finally
        //   152	166	254	finally
        //   168	178	254	finally
        //   180	192	254	finally
        //   194	237	254	finally
        //   244	253	254	finally
        //   274	306	254	finally
        //   308	327	254	finally
        //   332	349	254	finally
        //   360	373	254	finally
        //   386	400	254	finally
        //   402	434	254	finally
        //   436	455	254	finally
        //   457	471	254	finally
        //   478	491	254	finally
        //   500	531	254	finally
        //   533	558	254	finally
        //   560	574	254	finally
        //   581	599	254	finally
        //   601	630	254	finally
        //   632	641	254	finally
        //   643	668	254	finally
        //   670	677	254	finally
        //   695	704	254	finally
        //   711	720	254	finally
        //   725	734	254	finally
        //   745	754	254	finally
        //   332	349	691	java/io/IOException
        //   106	118	707	java/lang/Exception
        //   120	127	707	java/lang/Exception
        //   129	141	707	java/lang/Exception
        //   143	150	707	java/lang/Exception
        //   152	166	707	java/lang/Exception
        //   168	178	707	java/lang/Exception
        //   180	192	707	java/lang/Exception
        //   194	237	707	java/lang/Exception
        //   274	306	707	java/lang/Exception
        //   308	327	707	java/lang/Exception
        //   332	349	707	java/lang/Exception
        //   360	373	707	java/lang/Exception
        //   386	400	707	java/lang/Exception
        //   402	434	707	java/lang/Exception
        //   436	455	707	java/lang/Exception
        //   457	471	707	java/lang/Exception
        //   478	491	707	java/lang/Exception
        //   500	531	707	java/lang/Exception
        //   533	558	707	java/lang/Exception
        //   560	574	707	java/lang/Exception
        //   581	599	707	java/lang/Exception
        //   601	630	707	java/lang/Exception
        //   632	641	707	java/lang/Exception
        //   643	668	707	java/lang/Exception
        //   670	677	707	java/lang/Exception
        //   695	704	707	java/lang/Exception
        //   725	734	707	java/lang/Exception
        //   745	754	707	java/lang/Exception
        //   386	400	721	java/io/IOException
        //   402	434	721	java/io/IOException
        //   436	455	721	java/io/IOException
        //   457	471	721	java/io/IOException
        //   500	531	741	java/io/IOException
        //   533	558	741	java/io/IOException
        //   560	574	741	java/io/IOException
        //   41	100	766	finally
        //   41	100	773	java/lang/Exception
        //   41	100	780	java/io/IOException
    }
}


/* Location:              /Users/amaurremi/uw/stringoid stuff/static vs dynamic/ifunny/mobi.ifunny-2447-dex2jar.jar!/com/millennialmedia/android/HandShake$1.class
 * Java compiler version: 6 (50.0)
 * JD-Core Version:       0.7.1
 */