package com.google.android.gms.maps.model.a;

import android.os.Binder;
import android.os.IBinder;
import android.os.IInterface;
import android.os.Parcel;
import com.google.android.gms.dynamic.c;
import com.google.android.gms.dynamic.c.a;
import com.google.android.gms.maps.model.LatLng;
import com.google.android.gms.maps.model.LatLngBounds;
import com.google.android.gms.maps.model.f;
import com.google.android.gms.maps.model.g;

public abstract interface d
  extends IInterface
{
  public abstract void a(LatLngBounds paramLatLngBounds);
  
  public abstract boolean a(d paramd);
  
  public abstract void d(float paramFloat1, float paramFloat2);
  
  public abstract void g(LatLng paramLatLng);
  
  public abstract float getBearing();
  
  public abstract float getHeight();
  
  public abstract String getId();
  
  public abstract float getWidth();
  
  public abstract boolean isVisible();
  
  public abstract void k(c paramc);
  
  public abstract void o(float paramFloat);
  
  public abstract void q(float paramFloat);
  
  public abstract void r(float paramFloat);
  
  public abstract void remove();
  
  public abstract void setBearing(float paramFloat);
  
  public abstract void setVisible(boolean paramBoolean);
  
  public abstract float uS();
  
  public abstract LatLngBounds uV();
  
  public abstract float uW();
  
  public abstract LatLng va();
  
  public abstract int vl();
  
  public static abstract class a
    extends Binder
    implements d
  {
    public static d ah(IBinder paramIBinder)
    {
      if (paramIBinder == null) {
        return null;
      }
      IInterface localIInterface = paramIBinder.queryLocalInterface("com.google.android.gms.maps.model.internal.IGroundOverlayDelegate");
      if ((localIInterface != null) && ((localIInterface instanceof d))) {
        return (d)localIInterface;
      }
      return new a(paramIBinder);
    }
    
    public boolean onTransact(int paramInt1, Parcel paramParcel1, Parcel paramParcel2, int paramInt2)
    {
      Object localObject2 = null;
      Object localObject1 = null;
      int j = 0;
      int i = 0;
      float f;
      boolean bool;
      switch (paramInt1)
      {
      default: 
        return super.onTransact(paramInt1, paramParcel1, paramParcel2, paramInt2);
      case 1598968902: 
        paramParcel2.writeString("com.google.android.gms.maps.model.internal.IGroundOverlayDelegate");
        return true;
      case 1: 
        paramParcel1.enforceInterface("com.google.android.gms.maps.model.internal.IGroundOverlayDelegate");
        remove();
        paramParcel2.writeNoException();
        return true;
      case 2: 
        paramParcel1.enforceInterface("com.google.android.gms.maps.model.internal.IGroundOverlayDelegate");
        paramParcel1 = getId();
        paramParcel2.writeNoException();
        paramParcel2.writeString(paramParcel1);
        return true;
      case 3: 
        paramParcel1.enforceInterface("com.google.android.gms.maps.model.internal.IGroundOverlayDelegate");
        if (paramParcel1.readInt() != 0) {
          localObject1 = LatLng.Vo.bo(paramParcel1);
        }
        g((LatLng)localObject1);
        paramParcel2.writeNoException();
        return true;
      case 4: 
        paramParcel1.enforceInterface("com.google.android.gms.maps.model.internal.IGroundOverlayDelegate");
        paramParcel1 = va();
        paramParcel2.writeNoException();
        if (paramParcel1 != null)
        {
          paramParcel2.writeInt(1);
          paramParcel1.writeToParcel(paramParcel2, 1);
          return true;
        }
        paramParcel2.writeInt(0);
        return true;
      case 5: 
        paramParcel1.enforceInterface("com.google.android.gms.maps.model.internal.IGroundOverlayDelegate");
        q(paramParcel1.readFloat());
        paramParcel2.writeNoException();
        return true;
      case 6: 
        paramParcel1.enforceInterface("com.google.android.gms.maps.model.internal.IGroundOverlayDelegate");
        d(paramParcel1.readFloat(), paramParcel1.readFloat());
        paramParcel2.writeNoException();
        return true;
      case 7: 
        paramParcel1.enforceInterface("com.google.android.gms.maps.model.internal.IGroundOverlayDelegate");
        f = getWidth();
        paramParcel2.writeNoException();
        paramParcel2.writeFloat(f);
        return true;
      case 8: 
        paramParcel1.enforceInterface("com.google.android.gms.maps.model.internal.IGroundOverlayDelegate");
        f = getHeight();
        paramParcel2.writeNoException();
        paramParcel2.writeFloat(f);
        return true;
      case 9: 
        paramParcel1.enforceInterface("com.google.android.gms.maps.model.internal.IGroundOverlayDelegate");
        localObject1 = localObject2;
        if (paramParcel1.readInt() != 0) {
          localObject1 = LatLngBounds.Vr.bn(paramParcel1);
        }
        a((LatLngBounds)localObject1);
        paramParcel2.writeNoException();
        return true;
      case 10: 
        paramParcel1.enforceInterface("com.google.android.gms.maps.model.internal.IGroundOverlayDelegate");
        paramParcel1 = uV();
        paramParcel2.writeNoException();
        if (paramParcel1 != null)
        {
          paramParcel2.writeInt(1);
          paramParcel1.writeToParcel(paramParcel2, 1);
          return true;
        }
        paramParcel2.writeInt(0);
        return true;
      case 11: 
        paramParcel1.enforceInterface("com.google.android.gms.maps.model.internal.IGroundOverlayDelegate");
        setBearing(paramParcel1.readFloat());
        paramParcel2.writeNoException();
        return true;
      case 12: 
        paramParcel1.enforceInterface("com.google.android.gms.maps.model.internal.IGroundOverlayDelegate");
        f = getBearing();
        paramParcel2.writeNoException();
        paramParcel2.writeFloat(f);
        return true;
      case 13: 
        paramParcel1.enforceInterface("com.google.android.gms.maps.model.internal.IGroundOverlayDelegate");
        o(paramParcel1.readFloat());
        paramParcel2.writeNoException();
        return true;
      case 14: 
        paramParcel1.enforceInterface("com.google.android.gms.maps.model.internal.IGroundOverlayDelegate");
        f = uS();
        paramParcel2.writeNoException();
        paramParcel2.writeFloat(f);
        return true;
      case 15: 
        paramParcel1.enforceInterface("com.google.android.gms.maps.model.internal.IGroundOverlayDelegate");
        if (paramParcel1.readInt() != 0) {}
        for (bool = true;; bool = false)
        {
          setVisible(bool);
          paramParcel2.writeNoException();
          return true;
        }
      case 16: 
        paramParcel1.enforceInterface("com.google.android.gms.maps.model.internal.IGroundOverlayDelegate");
        bool = isVisible();
        paramParcel2.writeNoException();
        paramInt1 = i;
        if (bool) {
          paramInt1 = 1;
        }
        paramParcel2.writeInt(paramInt1);
        return true;
      case 17: 
        paramParcel1.enforceInterface("com.google.android.gms.maps.model.internal.IGroundOverlayDelegate");
        r(paramParcel1.readFloat());
        paramParcel2.writeNoException();
        return true;
      case 18: 
        paramParcel1.enforceInterface("com.google.android.gms.maps.model.internal.IGroundOverlayDelegate");
        f = uW();
        paramParcel2.writeNoException();
        paramParcel2.writeFloat(f);
        return true;
      case 19: 
        paramParcel1.enforceInterface("com.google.android.gms.maps.model.internal.IGroundOverlayDelegate");
        bool = a(ah(paramParcel1.readStrongBinder()));
        paramParcel2.writeNoException();
        paramInt1 = j;
        if (bool) {
          paramInt1 = 1;
        }
        paramParcel2.writeInt(paramInt1);
        return true;
      case 20: 
        paramParcel1.enforceInterface("com.google.android.gms.maps.model.internal.IGroundOverlayDelegate");
        paramInt1 = vl();
        paramParcel2.writeNoException();
        paramParcel2.writeInt(paramInt1);
        return true;
      }
      paramParcel1.enforceInterface("com.google.android.gms.maps.model.internal.IGroundOverlayDelegate");
      k(c.a.h(paramParcel1.readStrongBinder()));
      paramParcel2.writeNoException();
      return true;
    }
    
    private static class a
      implements d
    {
      private IBinder tS;
      
      a(IBinder paramIBinder)
      {
        this.tS = paramIBinder;
      }
      
      /* Error */
      public void a(LatLngBounds paramLatLngBounds)
      {
        // Byte code:
        //   0: invokestatic 26	android/os/Parcel:obtain	()Landroid/os/Parcel;
        //   3: astore_2
        //   4: invokestatic 26	android/os/Parcel:obtain	()Landroid/os/Parcel;
        //   7: astore_3
        //   8: aload_2
        //   9: ldc 28
        //   11: invokevirtual 32	android/os/Parcel:writeInterfaceToken	(Ljava/lang/String;)V
        //   14: aload_1
        //   15: ifnull +42 -> 57
        //   18: aload_2
        //   19: iconst_1
        //   20: invokevirtual 36	android/os/Parcel:writeInt	(I)V
        //   23: aload_1
        //   24: aload_2
        //   25: iconst_0
        //   26: invokevirtual 42	com/google/android/gms/maps/model/LatLngBounds:writeToParcel	(Landroid/os/Parcel;I)V
        //   29: aload_0
        //   30: getfield 18	com/google/android/gms/maps/model/a/d$a$a:tS	Landroid/os/IBinder;
        //   33: bipush 9
        //   35: aload_2
        //   36: aload_3
        //   37: iconst_0
        //   38: invokeinterface 48 5 0
        //   43: pop
        //   44: aload_3
        //   45: invokevirtual 51	android/os/Parcel:readException	()V
        //   48: aload_3
        //   49: invokevirtual 54	android/os/Parcel:recycle	()V
        //   52: aload_2
        //   53: invokevirtual 54	android/os/Parcel:recycle	()V
        //   56: return
        //   57: aload_2
        //   58: iconst_0
        //   59: invokevirtual 36	android/os/Parcel:writeInt	(I)V
        //   62: goto -33 -> 29
        //   65: astore_1
        //   66: aload_3
        //   67: invokevirtual 54	android/os/Parcel:recycle	()V
        //   70: aload_2
        //   71: invokevirtual 54	android/os/Parcel:recycle	()V
        //   74: aload_1
        //   75: athrow
        // Local variable table:
        //   start	length	slot	name	signature
        //   0	76	0	this	a
        //   0	76	1	paramLatLngBounds	LatLngBounds
        //   3	68	2	localParcel1	Parcel
        //   7	60	3	localParcel2	Parcel
        // Exception table:
        //   from	to	target	type
        //   8	14	65	finally
        //   18	29	65	finally
        //   29	48	65	finally
        //   57	62	65	finally
      }
      
      /* Error */
      public boolean a(d paramd)
      {
        // Byte code:
        //   0: iconst_0
        //   1: istore_3
        //   2: invokestatic 26	android/os/Parcel:obtain	()Landroid/os/Parcel;
        //   5: astore 4
        //   7: invokestatic 26	android/os/Parcel:obtain	()Landroid/os/Parcel;
        //   10: astore 5
        //   12: aload 4
        //   14: ldc 28
        //   16: invokevirtual 32	android/os/Parcel:writeInterfaceToken	(Ljava/lang/String;)V
        //   19: aload_1
        //   20: ifnull +62 -> 82
        //   23: aload_1
        //   24: invokeinterface 59 1 0
        //   29: astore_1
        //   30: aload 4
        //   32: aload_1
        //   33: invokevirtual 62	android/os/Parcel:writeStrongBinder	(Landroid/os/IBinder;)V
        //   36: aload_0
        //   37: getfield 18	com/google/android/gms/maps/model/a/d$a$a:tS	Landroid/os/IBinder;
        //   40: bipush 19
        //   42: aload 4
        //   44: aload 5
        //   46: iconst_0
        //   47: invokeinterface 48 5 0
        //   52: pop
        //   53: aload 5
        //   55: invokevirtual 51	android/os/Parcel:readException	()V
        //   58: aload 5
        //   60: invokevirtual 66	android/os/Parcel:readInt	()I
        //   63: istore_2
        //   64: iload_2
        //   65: ifeq +5 -> 70
        //   68: iconst_1
        //   69: istore_3
        //   70: aload 5
        //   72: invokevirtual 54	android/os/Parcel:recycle	()V
        //   75: aload 4
        //   77: invokevirtual 54	android/os/Parcel:recycle	()V
        //   80: iload_3
        //   81: ireturn
        //   82: aconst_null
        //   83: astore_1
        //   84: goto -54 -> 30
        //   87: astore_1
        //   88: aload 5
        //   90: invokevirtual 54	android/os/Parcel:recycle	()V
        //   93: aload 4
        //   95: invokevirtual 54	android/os/Parcel:recycle	()V
        //   98: aload_1
        //   99: athrow
        // Local variable table:
        //   start	length	slot	name	signature
        //   0	100	0	this	a
        //   0	100	1	paramd	d
        //   63	2	2	i	int
        //   1	80	3	bool	boolean
        //   5	89	4	localParcel1	Parcel
        //   10	79	5	localParcel2	Parcel
        // Exception table:
        //   from	to	target	type
        //   12	19	87	finally
        //   23	30	87	finally
        //   30	64	87	finally
      }
      
      public IBinder asBinder()
      {
        return this.tS;
      }
      
      public void d(float paramFloat1, float paramFloat2)
      {
        Parcel localParcel1 = Parcel.obtain();
        Parcel localParcel2 = Parcel.obtain();
        try
        {
          localParcel1.writeInterfaceToken("com.google.android.gms.maps.model.internal.IGroundOverlayDelegate");
          localParcel1.writeFloat(paramFloat1);
          localParcel1.writeFloat(paramFloat2);
          this.tS.transact(6, localParcel1, localParcel2, 0);
          localParcel2.readException();
          return;
        }
        finally
        {
          localParcel2.recycle();
          localParcel1.recycle();
        }
      }
      
      /* Error */
      public void g(LatLng paramLatLng)
      {
        // Byte code:
        //   0: invokestatic 26	android/os/Parcel:obtain	()Landroid/os/Parcel;
        //   3: astore_2
        //   4: invokestatic 26	android/os/Parcel:obtain	()Landroid/os/Parcel;
        //   7: astore_3
        //   8: aload_2
        //   9: ldc 28
        //   11: invokevirtual 32	android/os/Parcel:writeInterfaceToken	(Ljava/lang/String;)V
        //   14: aload_1
        //   15: ifnull +41 -> 56
        //   18: aload_2
        //   19: iconst_1
        //   20: invokevirtual 36	android/os/Parcel:writeInt	(I)V
        //   23: aload_1
        //   24: aload_2
        //   25: iconst_0
        //   26: invokevirtual 77	com/google/android/gms/maps/model/LatLng:writeToParcel	(Landroid/os/Parcel;I)V
        //   29: aload_0
        //   30: getfield 18	com/google/android/gms/maps/model/a/d$a$a:tS	Landroid/os/IBinder;
        //   33: iconst_3
        //   34: aload_2
        //   35: aload_3
        //   36: iconst_0
        //   37: invokeinterface 48 5 0
        //   42: pop
        //   43: aload_3
        //   44: invokevirtual 51	android/os/Parcel:readException	()V
        //   47: aload_3
        //   48: invokevirtual 54	android/os/Parcel:recycle	()V
        //   51: aload_2
        //   52: invokevirtual 54	android/os/Parcel:recycle	()V
        //   55: return
        //   56: aload_2
        //   57: iconst_0
        //   58: invokevirtual 36	android/os/Parcel:writeInt	(I)V
        //   61: goto -32 -> 29
        //   64: astore_1
        //   65: aload_3
        //   66: invokevirtual 54	android/os/Parcel:recycle	()V
        //   69: aload_2
        //   70: invokevirtual 54	android/os/Parcel:recycle	()V
        //   73: aload_1
        //   74: athrow
        // Local variable table:
        //   start	length	slot	name	signature
        //   0	75	0	this	a
        //   0	75	1	paramLatLng	LatLng
        //   3	67	2	localParcel1	Parcel
        //   7	59	3	localParcel2	Parcel
        // Exception table:
        //   from	to	target	type
        //   8	14	64	finally
        //   18	29	64	finally
        //   29	47	64	finally
        //   56	61	64	finally
      }
      
      public float getBearing()
      {
        Parcel localParcel1 = Parcel.obtain();
        Parcel localParcel2 = Parcel.obtain();
        try
        {
          localParcel1.writeInterfaceToken("com.google.android.gms.maps.model.internal.IGroundOverlayDelegate");
          this.tS.transact(12, localParcel1, localParcel2, 0);
          localParcel2.readException();
          float f = localParcel2.readFloat();
          return f;
        }
        finally
        {
          localParcel2.recycle();
          localParcel1.recycle();
        }
      }
      
      public float getHeight()
      {
        Parcel localParcel1 = Parcel.obtain();
        Parcel localParcel2 = Parcel.obtain();
        try
        {
          localParcel1.writeInterfaceToken("com.google.android.gms.maps.model.internal.IGroundOverlayDelegate");
          this.tS.transact(8, localParcel1, localParcel2, 0);
          localParcel2.readException();
          float f = localParcel2.readFloat();
          return f;
        }
        finally
        {
          localParcel2.recycle();
          localParcel1.recycle();
        }
      }
      
      public String getId()
      {
        Parcel localParcel1 = Parcel.obtain();
        Parcel localParcel2 = Parcel.obtain();
        try
        {
          localParcel1.writeInterfaceToken("com.google.android.gms.maps.model.internal.IGroundOverlayDelegate");
          this.tS.transact(2, localParcel1, localParcel2, 0);
          localParcel2.readException();
          String str = localParcel2.readString();
          return str;
        }
        finally
        {
          localParcel2.recycle();
          localParcel1.recycle();
        }
      }
      
      public float getWidth()
      {
        Parcel localParcel1 = Parcel.obtain();
        Parcel localParcel2 = Parcel.obtain();
        try
        {
          localParcel1.writeInterfaceToken("com.google.android.gms.maps.model.internal.IGroundOverlayDelegate");
          this.tS.transact(7, localParcel1, localParcel2, 0);
          localParcel2.readException();
          float f = localParcel2.readFloat();
          return f;
        }
        finally
        {
          localParcel2.recycle();
          localParcel1.recycle();
        }
      }
      
      public boolean isVisible()
      {
        boolean bool = false;
        Parcel localParcel1 = Parcel.obtain();
        Parcel localParcel2 = Parcel.obtain();
        try
        {
          localParcel1.writeInterfaceToken("com.google.android.gms.maps.model.internal.IGroundOverlayDelegate");
          this.tS.transact(16, localParcel1, localParcel2, 0);
          localParcel2.readException();
          int i = localParcel2.readInt();
          if (i != 0) {
            bool = true;
          }
          return bool;
        }
        finally
        {
          localParcel2.recycle();
          localParcel1.recycle();
        }
      }
      
      /* Error */
      public void k(c paramc)
      {
        // Byte code:
        //   0: invokestatic 26	android/os/Parcel:obtain	()Landroid/os/Parcel;
        //   3: astore_2
        //   4: invokestatic 26	android/os/Parcel:obtain	()Landroid/os/Parcel;
        //   7: astore_3
        //   8: aload_2
        //   9: ldc 28
        //   11: invokevirtual 32	android/os/Parcel:writeInterfaceToken	(Ljava/lang/String;)V
        //   14: aload_1
        //   15: ifnull +43 -> 58
        //   18: aload_1
        //   19: invokeinterface 96 1 0
        //   24: astore_1
        //   25: aload_2
        //   26: aload_1
        //   27: invokevirtual 62	android/os/Parcel:writeStrongBinder	(Landroid/os/IBinder;)V
        //   30: aload_0
        //   31: getfield 18	com/google/android/gms/maps/model/a/d$a$a:tS	Landroid/os/IBinder;
        //   34: bipush 21
        //   36: aload_2
        //   37: aload_3
        //   38: iconst_0
        //   39: invokeinterface 48 5 0
        //   44: pop
        //   45: aload_3
        //   46: invokevirtual 51	android/os/Parcel:readException	()V
        //   49: aload_3
        //   50: invokevirtual 54	android/os/Parcel:recycle	()V
        //   53: aload_2
        //   54: invokevirtual 54	android/os/Parcel:recycle	()V
        //   57: return
        //   58: aconst_null
        //   59: astore_1
        //   60: goto -35 -> 25
        //   63: astore_1
        //   64: aload_3
        //   65: invokevirtual 54	android/os/Parcel:recycle	()V
        //   68: aload_2
        //   69: invokevirtual 54	android/os/Parcel:recycle	()V
        //   72: aload_1
        //   73: athrow
        // Local variable table:
        //   start	length	slot	name	signature
        //   0	74	0	this	a
        //   0	74	1	paramc	c
        //   3	66	2	localParcel1	Parcel
        //   7	58	3	localParcel2	Parcel
        // Exception table:
        //   from	to	target	type
        //   8	14	63	finally
        //   18	25	63	finally
        //   25	49	63	finally
      }
      
      public void o(float paramFloat)
      {
        Parcel localParcel1 = Parcel.obtain();
        Parcel localParcel2 = Parcel.obtain();
        try
        {
          localParcel1.writeInterfaceToken("com.google.android.gms.maps.model.internal.IGroundOverlayDelegate");
          localParcel1.writeFloat(paramFloat);
          this.tS.transact(13, localParcel1, localParcel2, 0);
          localParcel2.readException();
          return;
        }
        finally
        {
          localParcel2.recycle();
          localParcel1.recycle();
        }
      }
      
      public void q(float paramFloat)
      {
        Parcel localParcel1 = Parcel.obtain();
        Parcel localParcel2 = Parcel.obtain();
        try
        {
          localParcel1.writeInterfaceToken("com.google.android.gms.maps.model.internal.IGroundOverlayDelegate");
          localParcel1.writeFloat(paramFloat);
          this.tS.transact(5, localParcel1, localParcel2, 0);
          localParcel2.readException();
          return;
        }
        finally
        {
          localParcel2.recycle();
          localParcel1.recycle();
        }
      }
      
      public void r(float paramFloat)
      {
        Parcel localParcel1 = Parcel.obtain();
        Parcel localParcel2 = Parcel.obtain();
        try
        {
          localParcel1.writeInterfaceToken("com.google.android.gms.maps.model.internal.IGroundOverlayDelegate");
          localParcel1.writeFloat(paramFloat);
          this.tS.transact(17, localParcel1, localParcel2, 0);
          localParcel2.readException();
          return;
        }
        finally
        {
          localParcel2.recycle();
          localParcel1.recycle();
        }
      }
      
      public void remove()
      {
        Parcel localParcel1 = Parcel.obtain();
        Parcel localParcel2 = Parcel.obtain();
        try
        {
          localParcel1.writeInterfaceToken("com.google.android.gms.maps.model.internal.IGroundOverlayDelegate");
          this.tS.transact(1, localParcel1, localParcel2, 0);
          localParcel2.readException();
          return;
        }
        finally
        {
          localParcel2.recycle();
          localParcel1.recycle();
        }
      }
      
      public void setBearing(float paramFloat)
      {
        Parcel localParcel1 = Parcel.obtain();
        Parcel localParcel2 = Parcel.obtain();
        try
        {
          localParcel1.writeInterfaceToken("com.google.android.gms.maps.model.internal.IGroundOverlayDelegate");
          localParcel1.writeFloat(paramFloat);
          this.tS.transact(11, localParcel1, localParcel2, 0);
          localParcel2.readException();
          return;
        }
        finally
        {
          localParcel2.recycle();
          localParcel1.recycle();
        }
      }
      
      public void setVisible(boolean paramBoolean)
      {
        int i = 0;
        Parcel localParcel1 = Parcel.obtain();
        Parcel localParcel2 = Parcel.obtain();
        try
        {
          localParcel1.writeInterfaceToken("com.google.android.gms.maps.model.internal.IGroundOverlayDelegate");
          if (paramBoolean) {
            i = 1;
          }
          localParcel1.writeInt(i);
          this.tS.transact(15, localParcel1, localParcel2, 0);
          localParcel2.readException();
          return;
        }
        finally
        {
          localParcel2.recycle();
          localParcel1.recycle();
        }
      }
      
      public float uS()
      {
        Parcel localParcel1 = Parcel.obtain();
        Parcel localParcel2 = Parcel.obtain();
        try
        {
          localParcel1.writeInterfaceToken("com.google.android.gms.maps.model.internal.IGroundOverlayDelegate");
          this.tS.transact(14, localParcel1, localParcel2, 0);
          localParcel2.readException();
          float f = localParcel2.readFloat();
          return f;
        }
        finally
        {
          localParcel2.recycle();
          localParcel1.recycle();
        }
      }
      
      /* Error */
      public LatLngBounds uV()
      {
        // Byte code:
        //   0: invokestatic 26	android/os/Parcel:obtain	()Landroid/os/Parcel;
        //   3: astore_2
        //   4: invokestatic 26	android/os/Parcel:obtain	()Landroid/os/Parcel;
        //   7: astore_3
        //   8: aload_2
        //   9: ldc 28
        //   11: invokevirtual 32	android/os/Parcel:writeInterfaceToken	(Ljava/lang/String;)V
        //   14: aload_0
        //   15: getfield 18	com/google/android/gms/maps/model/a/d$a$a:tS	Landroid/os/IBinder;
        //   18: bipush 10
        //   20: aload_2
        //   21: aload_3
        //   22: iconst_0
        //   23: invokeinterface 48 5 0
        //   28: pop
        //   29: aload_3
        //   30: invokevirtual 51	android/os/Parcel:readException	()V
        //   33: aload_3
        //   34: invokevirtual 66	android/os/Parcel:readInt	()I
        //   37: ifeq +21 -> 58
        //   40: getstatic 110	com/google/android/gms/maps/model/LatLngBounds:Vr	Lcom/google/android/gms/maps/model/f;
        //   43: aload_3
        //   44: invokevirtual 116	com/google/android/gms/maps/model/f:bn	(Landroid/os/Parcel;)Lcom/google/android/gms/maps/model/LatLngBounds;
        //   47: astore_1
        //   48: aload_3
        //   49: invokevirtual 54	android/os/Parcel:recycle	()V
        //   52: aload_2
        //   53: invokevirtual 54	android/os/Parcel:recycle	()V
        //   56: aload_1
        //   57: areturn
        //   58: aconst_null
        //   59: astore_1
        //   60: goto -12 -> 48
        //   63: astore_1
        //   64: aload_3
        //   65: invokevirtual 54	android/os/Parcel:recycle	()V
        //   68: aload_2
        //   69: invokevirtual 54	android/os/Parcel:recycle	()V
        //   72: aload_1
        //   73: athrow
        // Local variable table:
        //   start	length	slot	name	signature
        //   0	74	0	this	a
        //   47	13	1	localLatLngBounds	LatLngBounds
        //   63	10	1	localObject	Object
        //   3	66	2	localParcel1	Parcel
        //   7	58	3	localParcel2	Parcel
        // Exception table:
        //   from	to	target	type
        //   8	48	63	finally
      }
      
      public float uW()
      {
        Parcel localParcel1 = Parcel.obtain();
        Parcel localParcel2 = Parcel.obtain();
        try
        {
          localParcel1.writeInterfaceToken("com.google.android.gms.maps.model.internal.IGroundOverlayDelegate");
          this.tS.transact(18, localParcel1, localParcel2, 0);
          localParcel2.readException();
          float f = localParcel2.readFloat();
          return f;
        }
        finally
        {
          localParcel2.recycle();
          localParcel1.recycle();
        }
      }
      
      /* Error */
      public LatLng va()
      {
        // Byte code:
        //   0: invokestatic 26	android/os/Parcel:obtain	()Landroid/os/Parcel;
        //   3: astore_2
        //   4: invokestatic 26	android/os/Parcel:obtain	()Landroid/os/Parcel;
        //   7: astore_3
        //   8: aload_2
        //   9: ldc 28
        //   11: invokevirtual 32	android/os/Parcel:writeInterfaceToken	(Ljava/lang/String;)V
        //   14: aload_0
        //   15: getfield 18	com/google/android/gms/maps/model/a/d$a$a:tS	Landroid/os/IBinder;
        //   18: iconst_4
        //   19: aload_2
        //   20: aload_3
        //   21: iconst_0
        //   22: invokeinterface 48 5 0
        //   27: pop
        //   28: aload_3
        //   29: invokevirtual 51	android/os/Parcel:readException	()V
        //   32: aload_3
        //   33: invokevirtual 66	android/os/Parcel:readInt	()I
        //   36: ifeq +21 -> 57
        //   39: getstatic 123	com/google/android/gms/maps/model/LatLng:Vo	Lcom/google/android/gms/maps/model/g;
        //   42: aload_3
        //   43: invokevirtual 129	com/google/android/gms/maps/model/g:bo	(Landroid/os/Parcel;)Lcom/google/android/gms/maps/model/LatLng;
        //   46: astore_1
        //   47: aload_3
        //   48: invokevirtual 54	android/os/Parcel:recycle	()V
        //   51: aload_2
        //   52: invokevirtual 54	android/os/Parcel:recycle	()V
        //   55: aload_1
        //   56: areturn
        //   57: aconst_null
        //   58: astore_1
        //   59: goto -12 -> 47
        //   62: astore_1
        //   63: aload_3
        //   64: invokevirtual 54	android/os/Parcel:recycle	()V
        //   67: aload_2
        //   68: invokevirtual 54	android/os/Parcel:recycle	()V
        //   71: aload_1
        //   72: athrow
        // Local variable table:
        //   start	length	slot	name	signature
        //   0	73	0	this	a
        //   46	13	1	localLatLng	LatLng
        //   62	10	1	localObject	Object
        //   3	65	2	localParcel1	Parcel
        //   7	57	3	localParcel2	Parcel
        // Exception table:
        //   from	to	target	type
        //   8	47	62	finally
      }
      
      public int vl()
      {
        Parcel localParcel1 = Parcel.obtain();
        Parcel localParcel2 = Parcel.obtain();
        try
        {
          localParcel1.writeInterfaceToken("com.google.android.gms.maps.model.internal.IGroundOverlayDelegate");
          this.tS.transact(20, localParcel1, localParcel2, 0);
          localParcel2.readException();
          int i = localParcel2.readInt();
          return i;
        }
        finally
        {
          localParcel2.recycle();
          localParcel1.recycle();
        }
      }
    }
  }
}


/* Location:              /Users/amaurremi/uw/stringoid/static-dynamic-comparison/apps/quick pdf scanner/com.mobisystems.mobiscanner-213-dex2jar.jar!/com/google/android/gms/maps/model/a/d.class
 * Java compiler version: 6 (50.0)
 * JD-Core Version:       0.7.1
 */