package com.mobileapptracker;

import java.util.Date;

public class c
        implements Runnable {
    private String b = null;
    private String c = null;
    private String d = null;
    private double e = 0.0D;
    private String f = null;
    private String g = null;
    private String h = null;
    private String i = null;
    private String j = null;
    private String k = null;
    private String l = null;
    private String m = null;
    private String n = null;
    private boolean o = false;
    private Date p = null;

    protected c(b paramb, String paramString1, String paramString2, String paramString3, double paramDouble, String paramString4, String paramString5, String paramString6, String paramString7, String paramString8, String paramString9, String paramString10, String paramString11, String paramString12, boolean paramBoolean, Date paramDate) {
        this.b = paramString1;
        this.c = paramString2;
        this.d = paramString3;
        this.e = paramDouble;
        this.f = paramString4;
        this.g = paramString5;
        this.h = paramString6;
        this.i = paramString7;
        this.j = paramString8;
        this.k = paramString9;
        this.l = paramString10;
        this.m = paramString11;
        this.n = paramString12;
        this.o = paramBoolean;
        this.p = paramDate;
    }

    /* Error */
    public void run() {
        // Byte code:
        //   0: aload_0
        //   1: getfield 31	com/mobileapptracker/c:a	Lcom/mobileapptracker/b;
        //   4: invokestatic 75	com/mobileapptracker/b:a	(Lcom/mobileapptracker/b;)Ljava/util/concurrent/Semaphore;
        //   7: invokevirtual 80	java/util/concurrent/Semaphore:acquire	()V
        //   10: new 82	org/json/JSONObject
        //   13: dup
        //   14: invokespecial 83	org/json/JSONObject:<init>	()V
        //   17: astore_2
        //   18: aload_2
        //   19: ldc 85
        //   21: aload_0
        //   22: getfield 36	com/mobileapptracker/c:b	Ljava/lang/String;
        //   25: invokevirtual 89	org/json/JSONObject:put	(Ljava/lang/String;Ljava/lang/Object;)Lorg/json/JSONObject;
        //   28: pop
        //   29: aload_0
        //   30: getfield 38	com/mobileapptracker/c:c	Ljava/lang/String;
        //   33: ifnull +14 -> 47
        //   36: aload_2
        //   37: ldc 91
        //   39: aload_0
        //   40: getfield 38	com/mobileapptracker/c:c	Ljava/lang/String;
        //   43: invokevirtual 89	org/json/JSONObject:put	(Ljava/lang/String;Ljava/lang/Object;)Lorg/json/JSONObject;
        //   46: pop
        //   47: aload_2
        //   48: ldc 93
        //   50: aload_0
        //   51: getfield 40	com/mobileapptracker/c:d	Ljava/lang/String;
        //   54: invokevirtual 89	org/json/JSONObject:put	(Ljava/lang/String;Ljava/lang/Object;)Lorg/json/JSONObject;
        //   57: pop
        //   58: aload_2
        //   59: ldc 95
        //   61: aload_0
        //   62: getfield 42	com/mobileapptracker/c:e	D
        //   65: invokevirtual 98	org/json/JSONObject:put	(Ljava/lang/String;D)Lorg/json/JSONObject;
        //   68: pop
        //   69: aload_0
        //   70: getfield 44	com/mobileapptracker/c:f	Ljava/lang/String;
        //   73: ifnonnull +9 -> 82
        //   76: aload_0
        //   77: ldc 100
        //   79: putfield 44	com/mobileapptracker/c:f	Ljava/lang/String;
        //   82: aload_2
        //   83: ldc 102
        //   85: aload_0
        //   86: getfield 44	com/mobileapptracker/c:f	Ljava/lang/String;
        //   89: invokevirtual 89	org/json/JSONObject:put	(Ljava/lang/String;Ljava/lang/Object;)Lorg/json/JSONObject;
        //   92: pop
        //   93: aload_0
        //   94: getfield 46	com/mobileapptracker/c:g	Ljava/lang/String;
        //   97: ifnull +14 -> 111
        //   100: aload_2
        //   101: ldc 104
        //   103: aload_0
        //   104: getfield 46	com/mobileapptracker/c:g	Ljava/lang/String;
        //   107: invokevirtual 89	org/json/JSONObject:put	(Ljava/lang/String;Ljava/lang/Object;)Lorg/json/JSONObject;
        //   110: pop
        //   111: aload_0
        //   112: getfield 52	com/mobileapptracker/c:j	Ljava/lang/String;
        //   115: ifnull +14 -> 129
        //   118: aload_2
        //   119: ldc 106
        //   121: aload_0
        //   122: getfield 52	com/mobileapptracker/c:j	Ljava/lang/String;
        //   125: invokevirtual 89	org/json/JSONObject:put	(Ljava/lang/String;Ljava/lang/Object;)Lorg/json/JSONObject;
        //   128: pop
        //   129: aload_0
        //   130: getfield 54	com/mobileapptracker/c:k	Ljava/lang/String;
        //   133: ifnull +14 -> 147
        //   136: aload_2
        //   137: ldc 108
        //   139: aload_0
        //   140: getfield 54	com/mobileapptracker/c:k	Ljava/lang/String;
        //   143: invokevirtual 89	org/json/JSONObject:put	(Ljava/lang/String;Ljava/lang/Object;)Lorg/json/JSONObject;
        //   146: pop
        //   147: aload_0
        //   148: getfield 56	com/mobileapptracker/c:l	Ljava/lang/String;
        //   151: ifnull +14 -> 165
        //   154: aload_2
        //   155: ldc 110
        //   157: aload_0
        //   158: getfield 56	com/mobileapptracker/c:l	Ljava/lang/String;
        //   161: invokevirtual 89	org/json/JSONObject:put	(Ljava/lang/String;Ljava/lang/Object;)Lorg/json/JSONObject;
        //   164: pop
        //   165: aload_0
        //   166: getfield 58	com/mobileapptracker/c:m	Ljava/lang/String;
        //   169: ifnull +14 -> 183
        //   172: aload_2
        //   173: ldc 112
        //   175: aload_0
        //   176: getfield 58	com/mobileapptracker/c:m	Ljava/lang/String;
        //   179: invokevirtual 89	org/json/JSONObject:put	(Ljava/lang/String;Ljava/lang/Object;)Lorg/json/JSONObject;
        //   182: pop
        //   183: aload_0
        //   184: getfield 60	com/mobileapptracker/c:n	Ljava/lang/String;
        //   187: ifnull +14 -> 201
        //   190: aload_2
        //   191: ldc 114
        //   193: aload_0
        //   194: getfield 60	com/mobileapptracker/c:n	Ljava/lang/String;
        //   197: invokevirtual 89	org/json/JSONObject:put	(Ljava/lang/String;Ljava/lang/Object;)Lorg/json/JSONObject;
        //   200: pop
        //   201: aload_0
        //   202: getfield 48	com/mobileapptracker/c:h	Ljava/lang/String;
        //   205: ifnull +14 -> 219
        //   208: aload_2
        //   209: ldc 116
        //   211: aload_0
        //   212: getfield 48	com/mobileapptracker/c:h	Ljava/lang/String;
        //   215: invokevirtual 89	org/json/JSONObject:put	(Ljava/lang/String;Ljava/lang/Object;)Lorg/json/JSONObject;
        //   218: pop
        //   219: aload_0
        //   220: getfield 50	com/mobileapptracker/c:i	Ljava/lang/String;
        //   223: ifnull +14 -> 237
        //   226: aload_2
        //   227: ldc 118
        //   229: aload_0
        //   230: getfield 50	com/mobileapptracker/c:i	Ljava/lang/String;
        //   233: invokevirtual 89	org/json/JSONObject:put	(Ljava/lang/String;Ljava/lang/Object;)Lorg/json/JSONObject;
        //   236: pop
        //   237: aload_2
        //   238: ldc 120
        //   240: aload_0
        //   241: getfield 62	com/mobileapptracker/c:o	Z
        //   244: invokevirtual 123	org/json/JSONObject:put	(Ljava/lang/String;Z)Lorg/json/JSONObject;
        //   247: pop
        //   248: aload_2
        //   249: ldc 125
        //   251: aload_0
        //   252: getfield 64	com/mobileapptracker/c:p	Ljava/util/Date;
        //   255: invokevirtual 131	java/util/Date:getTime	()J
        //   258: invokevirtual 134	org/json/JSONObject:put	(Ljava/lang/String;J)Lorg/json/JSONObject;
        //   261: pop
        //   262: aload_0
        //   263: getfield 31	com/mobileapptracker/c:a	Lcom/mobileapptracker/b;
        //   266: invokestatic 137	com/mobileapptracker/b:b	(Lcom/mobileapptracker/b;)Landroid/content/SharedPreferences;
        //   269: invokeinterface 143 1 0
        //   274: astore_3
        //   275: aload_0
        //   276: getfield 31	com/mobileapptracker/c:a	Lcom/mobileapptracker/b;
        //   279: invokevirtual 146	com/mobileapptracker/b:a	()I
        //   282: iconst_1
        //   283: iadd
        //   284: istore_1
        //   285: aload_0
        //   286: getfield 31	com/mobileapptracker/c:a	Lcom/mobileapptracker/b;
        //   289: iload_1
        //   290: invokevirtual 149	com/mobileapptracker/b:a	(I)V
        //   293: aload_3
        //   294: iload_1
        //   295: invokestatic 155	java/lang/Integer:toString	(I)Ljava/lang/String;
        //   298: aload_2
        //   299: invokevirtual 158	org/json/JSONObject:toString	()Ljava/lang/String;
        //   302: invokeinterface 164 3 0
        //   307: pop
        //   308: aload_3
        //   309: invokeinterface 168 1 0
        //   314: pop
        //   315: aload_0
        //   316: getfield 31	com/mobileapptracker/c:a	Lcom/mobileapptracker/b;
        //   319: invokestatic 75	com/mobileapptracker/b:a	(Lcom/mobileapptracker/b;)Ljava/util/concurrent/Semaphore;
        //   322: invokevirtual 171	java/util/concurrent/Semaphore:release	()V
        //   325: return
        //   326: astore_2
        //   327: aload_0
        //   328: getfield 31	com/mobileapptracker/c:a	Lcom/mobileapptracker/b;
        //   331: invokestatic 75	com/mobileapptracker/b:a	(Lcom/mobileapptracker/b;)Ljava/util/concurrent/Semaphore;
        //   334: invokevirtual 171	java/util/concurrent/Semaphore:release	()V
        //   337: return
        //   338: astore_2
        //   339: aload_2
        //   340: invokevirtual 174	java/lang/InterruptedException:printStackTrace	()V
        //   343: aload_0
        //   344: getfield 31	com/mobileapptracker/c:a	Lcom/mobileapptracker/b;
        //   347: invokestatic 75	com/mobileapptracker/b:a	(Lcom/mobileapptracker/b;)Ljava/util/concurrent/Semaphore;
        //   350: invokevirtual 171	java/util/concurrent/Semaphore:release	()V
        //   353: return
        //   354: astore_2
        //   355: aload_0
        //   356: getfield 31	com/mobileapptracker/c:a	Lcom/mobileapptracker/b;
        //   359: invokestatic 75	com/mobileapptracker/b:a	(Lcom/mobileapptracker/b;)Ljava/util/concurrent/Semaphore;
        //   362: invokevirtual 171	java/util/concurrent/Semaphore:release	()V
        //   365: aload_2
        //   366: athrow
        // Local variable table:
        //   start	length	slot	name	signature
        //   0	367	0	this	c
        //   284	11	1	i1	int
        //   17	282	2	localJSONObject	org.json.JSONObject
        //   326	1	2	localJSONException	org.json.JSONException
        //   338	2	2	localInterruptedException	InterruptedException
        //   354	12	2	localObject	Object
        //   274	35	3	localEditor	android.content.SharedPreferences.Editor
        // Exception table:
        //   from	to	target	type
        //   18	47	326	org/json/JSONException
        //   47	82	326	org/json/JSONException
        //   82	111	326	org/json/JSONException
        //   111	129	326	org/json/JSONException
        //   129	147	326	org/json/JSONException
        //   147	165	326	org/json/JSONException
        //   165	183	326	org/json/JSONException
        //   183	201	326	org/json/JSONException
        //   201	219	326	org/json/JSONException
        //   219	237	326	org/json/JSONException
        //   237	262	326	org/json/JSONException
        //   0	18	338	java/lang/InterruptedException
        //   18	47	338	java/lang/InterruptedException
        //   47	82	338	java/lang/InterruptedException
        //   82	111	338	java/lang/InterruptedException
        //   111	129	338	java/lang/InterruptedException
        //   129	147	338	java/lang/InterruptedException
        //   147	165	338	java/lang/InterruptedException
        //   165	183	338	java/lang/InterruptedException
        //   183	201	338	java/lang/InterruptedException
        //   201	219	338	java/lang/InterruptedException
        //   219	237	338	java/lang/InterruptedException
        //   237	262	338	java/lang/InterruptedException
        //   262	315	338	java/lang/InterruptedException
        //   0	18	354	finally
        //   18	47	354	finally
        //   47	82	354	finally
        //   82	111	354	finally
        //   111	129	354	finally
        //   129	147	354	finally
        //   147	165	354	finally
        //   165	183	354	finally
        //   183	201	354	finally
        //   201	219	354	finally
        //   219	237	354	finally
        //   237	262	354	finally
        //   262	315	354	finally
        //   339	343	354	finally
    }
}


/* Location:              /Users/amaurremi/uw/stringoid stuff/static vs dynamic/ifunny/mobi.ifunny-2447-dex2jar.jar!/com/mobileapptracker/c.class
 * Java compiler version: 6 (50.0)
 * JD-Core Version:       0.7.1
 */