package com.flurry.android;

import java.util.Map;

final class t
  implements Runnable
{
  t(InstallReceiver paramInstallReceiver, Map paramMap) {}
  
  /* Error */
  public final void run()
  {
    // Byte code:
    //   0: aconst_null
    //   1: astore_3
    //   2: aconst_null
    //   3: astore 5
    //   5: aload_3
    //   6: astore_2
    //   7: aload_0
    //   8: getfield 14	com/flurry/android/t:b	Lcom/flurry/android/InstallReceiver;
    //   11: invokestatic 28	com/flurry/android/InstallReceiver:a	(Lcom/flurry/android/InstallReceiver;)Ljava/io/File;
    //   14: invokevirtual 34	java/io/File:getParentFile	()Ljava/io/File;
    //   17: astore 4
    //   19: aload_3
    //   20: astore_2
    //   21: aload 4
    //   23: invokevirtual 38	java/io/File:mkdirs	()Z
    //   26: ifne +46 -> 72
    //   29: aload_3
    //   30: astore_2
    //   31: aload 4
    //   33: invokevirtual 41	java/io/File:exists	()Z
    //   36: ifne +36 -> 72
    //   39: aload_3
    //   40: astore_2
    //   41: ldc 43
    //   43: new 45	java/lang/StringBuilder
    //   46: dup
    //   47: invokespecial 46	java/lang/StringBuilder:<init>	()V
    //   50: ldc 48
    //   52: invokevirtual 52	java/lang/StringBuilder:append	(Ljava/lang/String;)Ljava/lang/StringBuilder;
    //   55: aload 4
    //   57: invokevirtual 55	java/lang/StringBuilder:append	(Ljava/lang/Object;)Ljava/lang/StringBuilder;
    //   60: invokevirtual 59	java/lang/StringBuilder:toString	()Ljava/lang/String;
    //   63: invokestatic 64	com/flurry/android/ah:b	(Ljava/lang/String;Ljava/lang/String;)I
    //   66: pop
    //   67: aconst_null
    //   68: invokestatic 69	com/flurry/android/r:a	(Ljava/io/Closeable;)V
    //   71: return
    //   72: aload_3
    //   73: astore_2
    //   74: new 71	java/io/DataOutputStream
    //   77: dup
    //   78: new 73	java/io/FileOutputStream
    //   81: dup
    //   82: aload_0
    //   83: getfield 14	com/flurry/android/t:b	Lcom/flurry/android/InstallReceiver;
    //   86: invokestatic 28	com/flurry/android/InstallReceiver:a	(Lcom/flurry/android/InstallReceiver;)Ljava/io/File;
    //   89: invokespecial 76	java/io/FileOutputStream:<init>	(Ljava/io/File;)V
    //   92: invokespecial 79	java/io/DataOutputStream:<init>	(Ljava/io/OutputStream;)V
    //   95: astore_3
    //   96: aload_0
    //   97: getfield 16	com/flurry/android/t:a	Ljava/util/Map;
    //   100: invokeinterface 85 1 0
    //   105: invokeinterface 91 1 0
    //   110: astore_2
    //   111: iconst_1
    //   112: istore_1
    //   113: aload_2
    //   114: invokeinterface 96 1 0
    //   119: ifeq +99 -> 218
    //   122: aload_2
    //   123: invokeinterface 100 1 0
    //   128: checkcast 102	java/util/Map$Entry
    //   131: astore 4
    //   133: iload_1
    //   134: iconst_1
    //   135: if_icmpne +61 -> 196
    //   138: iconst_0
    //   139: istore_1
    //   140: aload_3
    //   141: aload 4
    //   143: invokeinterface 105 1 0
    //   148: checkcast 107	java/lang/String
    //   151: invokevirtual 111	java/io/DataOutputStream:writeUTF	(Ljava/lang/String;)V
    //   154: aload_3
    //   155: ldc 113
    //   157: invokevirtual 111	java/io/DataOutputStream:writeUTF	(Ljava/lang/String;)V
    //   160: aload_3
    //   161: aload 4
    //   163: invokeinterface 116 1 0
    //   168: checkcast 107	java/lang/String
    //   171: invokevirtual 111	java/io/DataOutputStream:writeUTF	(Ljava/lang/String;)V
    //   174: goto -61 -> 113
    //   177: astore 4
    //   179: aload_3
    //   180: astore_2
    //   181: ldc 43
    //   183: ldc 118
    //   185: aload 4
    //   187: invokestatic 121	com/flurry/android/ah:b	(Ljava/lang/String;Ljava/lang/String;Ljava/lang/Throwable;)I
    //   190: pop
    //   191: aload_3
    //   192: invokestatic 69	com/flurry/android/r:a	(Ljava/io/Closeable;)V
    //   195: return
    //   196: aload_3
    //   197: ldc 123
    //   199: invokevirtual 111	java/io/DataOutputStream:writeUTF	(Ljava/lang/String;)V
    //   202: goto -62 -> 140
    //   205: astore 4
    //   207: aload_3
    //   208: astore_2
    //   209: aload 4
    //   211: astore_3
    //   212: aload_2
    //   213: invokestatic 69	com/flurry/android/r:a	(Ljava/io/Closeable;)V
    //   216: aload_3
    //   217: athrow
    //   218: aload_3
    //   219: iconst_0
    //   220: invokevirtual 127	java/io/DataOutputStream:writeShort	(I)V
    //   223: aload_3
    //   224: invokestatic 69	com/flurry/android/r:a	(Ljava/io/Closeable;)V
    //   227: return
    //   228: astore_3
    //   229: goto -17 -> 212
    //   232: astore 4
    //   234: aload 5
    //   236: astore_3
    //   237: goto -58 -> 179
    // Local variable table:
    //   start	length	slot	name	signature
    //   0	240	0	this	t
    //   112	28	1	i	int
    //   6	207	2	localObject1	Object
    //   1	223	3	localObject2	Object
    //   228	1	3	localObject3	Object
    //   236	1	3	localObject4	Object
    //   17	145	4	localObject5	Object
    //   177	9	4	localThrowable1	Throwable
    //   205	5	4	localObject6	Object
    //   232	1	4	localThrowable2	Throwable
    //   3	232	5	localObject7	Object
    // Exception table:
    //   from	to	target	type
    //   96	111	177	java/lang/Throwable
    //   113	133	177	java/lang/Throwable
    //   140	174	177	java/lang/Throwable
    //   196	202	177	java/lang/Throwable
    //   218	223	177	java/lang/Throwable
    //   96	111	205	finally
    //   113	133	205	finally
    //   140	174	205	finally
    //   196	202	205	finally
    //   218	223	205	finally
    //   7	19	228	finally
    //   21	29	228	finally
    //   31	39	228	finally
    //   41	67	228	finally
    //   74	96	228	finally
    //   181	191	228	finally
    //   7	19	232	java/lang/Throwable
    //   21	29	232	java/lang/Throwable
    //   31	39	232	java/lang/Throwable
    //   41	67	232	java/lang/Throwable
    //   74	96	232	java/lang/Throwable
  }
}


/* Location:              /Users/amaurremi/uw/stringoid/static-dynamic-comparison/apps/paper toss/com.bfs.papertoss-7005-dex2jar.jar!/com/flurry/android/t.class
 * Java compiler version: 6 (50.0)
 * JD-Core Version:       0.7.1
 */