package com.google.android.gms.wearable.internal;

import android.os.IBinder;

class d
  implements ab
{
  private IBinder a;
  
  d(IBinder paramIBinder)
  {
    this.a = paramIBinder;
  }
  
  /* Error */
  public void Z(com.google.android.gms.common.data.DataHolder paramDataHolder)
  {
    // Byte code:
    //   0: invokestatic 24	android/os/Parcel:obtain	()Landroid/os/Parcel;
    //   3: astore_2
    //   4: invokestatic 24	android/os/Parcel:obtain	()Landroid/os/Parcel;
    //   7: astore_3
    //   8: aload_2
    //   9: ldc 26
    //   11: invokevirtual 30	android/os/Parcel:writeInterfaceToken	(Ljava/lang/String;)V
    //   14: aload_1
    //   15: ifnull +41 -> 56
    //   18: aload_2
    //   19: iconst_1
    //   20: invokevirtual 34	android/os/Parcel:writeInt	(I)V
    //   23: aload_1
    //   24: aload_2
    //   25: iconst_0
    //   26: invokevirtual 40	com/google/android/gms/common/data/DataHolder:writeToParcel	(Landroid/os/Parcel;I)V
    //   29: aload_0
    //   30: getfield 15	com/google/android/gms/wearable/internal/d:a	Landroid/os/IBinder;
    //   33: iconst_5
    //   34: aload_2
    //   35: aload_3
    //   36: iconst_0
    //   37: invokeinterface 46 5 0
    //   42: pop
    //   43: aload_3
    //   44: invokevirtual 49	android/os/Parcel:readException	()V
    //   47: aload_3
    //   48: invokevirtual 52	android/os/Parcel:recycle	()V
    //   51: aload_2
    //   52: invokevirtual 52	android/os/Parcel:recycle	()V
    //   55: return
    //   56: aload_2
    //   57: iconst_0
    //   58: invokevirtual 34	android/os/Parcel:writeInt	(I)V
    //   61: goto -32 -> 29
    //   64: astore_1
    //   65: aload_3
    //   66: invokevirtual 52	android/os/Parcel:recycle	()V
    //   69: aload_2
    //   70: invokevirtual 52	android/os/Parcel:recycle	()V
    //   73: aload_1
    //   74: athrow
    // Local variable table:
    //   start	length	slot	name	signature
    //   0	75	0	this	d
    //   0	75	1	paramDataHolder	com.google.android.gms.common.data.DataHolder
    //   3	67	2	localParcel1	android.os.Parcel
    //   7	59	3	localParcel2	android.os.Parcel
    // Exception table:
    //   from	to	target	type
    //   8	14	64	finally
    //   18	29	64	finally
    //   29	47	64	finally
    //   56	61	64	finally
  }
  
  /* Error */
  public void a(com.google.android.gms.common.api.Status paramStatus)
  {
    // Byte code:
    //   0: invokestatic 24	android/os/Parcel:obtain	()Landroid/os/Parcel;
    //   3: astore_2
    //   4: invokestatic 24	android/os/Parcel:obtain	()Landroid/os/Parcel;
    //   7: astore_3
    //   8: aload_2
    //   9: ldc 26
    //   11: invokevirtual 30	android/os/Parcel:writeInterfaceToken	(Ljava/lang/String;)V
    //   14: aload_1
    //   15: ifnull +42 -> 57
    //   18: aload_2
    //   19: iconst_1
    //   20: invokevirtual 34	android/os/Parcel:writeInt	(I)V
    //   23: aload_1
    //   24: aload_2
    //   25: iconst_0
    //   26: invokevirtual 56	com/google/android/gms/common/api/Status:writeToParcel	(Landroid/os/Parcel;I)V
    //   29: aload_0
    //   30: getfield 15	com/google/android/gms/wearable/internal/d:a	Landroid/os/IBinder;
    //   33: bipush 11
    //   35: aload_2
    //   36: aload_3
    //   37: iconst_0
    //   38: invokeinterface 46 5 0
    //   43: pop
    //   44: aload_3
    //   45: invokevirtual 49	android/os/Parcel:readException	()V
    //   48: aload_3
    //   49: invokevirtual 52	android/os/Parcel:recycle	()V
    //   52: aload_2
    //   53: invokevirtual 52	android/os/Parcel:recycle	()V
    //   56: return
    //   57: aload_2
    //   58: iconst_0
    //   59: invokevirtual 34	android/os/Parcel:writeInt	(I)V
    //   62: goto -33 -> 29
    //   65: astore_1
    //   66: aload_3
    //   67: invokevirtual 52	android/os/Parcel:recycle	()V
    //   70: aload_2
    //   71: invokevirtual 52	android/os/Parcel:recycle	()V
    //   74: aload_1
    //   75: athrow
    // Local variable table:
    //   start	length	slot	name	signature
    //   0	76	0	this	d
    //   0	76	1	paramStatus	com.google.android.gms.common.api.Status
    //   3	68	2	localParcel1	android.os.Parcel
    //   7	60	3	localParcel2	android.os.Parcel
    // Exception table:
    //   from	to	target	type
    //   8	14	65	finally
    //   18	29	65	finally
    //   29	48	65	finally
    //   57	62	65	finally
  }
  
  /* Error */
  public void a(am paramam)
  {
    // Byte code:
    //   0: invokestatic 24	android/os/Parcel:obtain	()Landroid/os/Parcel;
    //   3: astore_2
    //   4: invokestatic 24	android/os/Parcel:obtain	()Landroid/os/Parcel;
    //   7: astore_3
    //   8: aload_2
    //   9: ldc 26
    //   11: invokevirtual 30	android/os/Parcel:writeInterfaceToken	(Ljava/lang/String;)V
    //   14: aload_1
    //   15: ifnull +41 -> 56
    //   18: aload_2
    //   19: iconst_1
    //   20: invokevirtual 34	android/os/Parcel:writeInt	(I)V
    //   23: aload_1
    //   24: aload_2
    //   25: iconst_0
    //   26: invokevirtual 60	com/google/android/gms/wearable/internal/am:writeToParcel	(Landroid/os/Parcel;I)V
    //   29: aload_0
    //   30: getfield 15	com/google/android/gms/wearable/internal/d:a	Landroid/os/IBinder;
    //   33: iconst_3
    //   34: aload_2
    //   35: aload_3
    //   36: iconst_0
    //   37: invokeinterface 46 5 0
    //   42: pop
    //   43: aload_3
    //   44: invokevirtual 49	android/os/Parcel:readException	()V
    //   47: aload_3
    //   48: invokevirtual 52	android/os/Parcel:recycle	()V
    //   51: aload_2
    //   52: invokevirtual 52	android/os/Parcel:recycle	()V
    //   55: return
    //   56: aload_2
    //   57: iconst_0
    //   58: invokevirtual 34	android/os/Parcel:writeInt	(I)V
    //   61: goto -32 -> 29
    //   64: astore_1
    //   65: aload_3
    //   66: invokevirtual 52	android/os/Parcel:recycle	()V
    //   69: aload_2
    //   70: invokevirtual 52	android/os/Parcel:recycle	()V
    //   73: aload_1
    //   74: athrow
    // Local variable table:
    //   start	length	slot	name	signature
    //   0	75	0	this	d
    //   0	75	1	paramam	am
    //   3	67	2	localParcel1	android.os.Parcel
    //   7	59	3	localParcel2	android.os.Parcel
    // Exception table:
    //   from	to	target	type
    //   8	14	64	finally
    //   18	29	64	finally
    //   29	47	64	finally
    //   56	61	64	finally
  }
  
  /* Error */
  public void a(aq paramaq)
  {
    // Byte code:
    //   0: invokestatic 24	android/os/Parcel:obtain	()Landroid/os/Parcel;
    //   3: astore_2
    //   4: invokestatic 24	android/os/Parcel:obtain	()Landroid/os/Parcel;
    //   7: astore_3
    //   8: aload_2
    //   9: ldc 26
    //   11: invokevirtual 30	android/os/Parcel:writeInterfaceToken	(Ljava/lang/String;)V
    //   14: aload_1
    //   15: ifnull +42 -> 57
    //   18: aload_2
    //   19: iconst_1
    //   20: invokevirtual 34	android/os/Parcel:writeInt	(I)V
    //   23: aload_1
    //   24: aload_2
    //   25: iconst_0
    //   26: invokevirtual 64	com/google/android/gms/wearable/internal/aq:writeToParcel	(Landroid/os/Parcel;I)V
    //   29: aload_0
    //   30: getfield 15	com/google/android/gms/wearable/internal/d:a	Landroid/os/IBinder;
    //   33: bipush 7
    //   35: aload_2
    //   36: aload_3
    //   37: iconst_0
    //   38: invokeinterface 46 5 0
    //   43: pop
    //   44: aload_3
    //   45: invokevirtual 49	android/os/Parcel:readException	()V
    //   48: aload_3
    //   49: invokevirtual 52	android/os/Parcel:recycle	()V
    //   52: aload_2
    //   53: invokevirtual 52	android/os/Parcel:recycle	()V
    //   56: return
    //   57: aload_2
    //   58: iconst_0
    //   59: invokevirtual 34	android/os/Parcel:writeInt	(I)V
    //   62: goto -33 -> 29
    //   65: astore_1
    //   66: aload_3
    //   67: invokevirtual 52	android/os/Parcel:recycle	()V
    //   70: aload_2
    //   71: invokevirtual 52	android/os/Parcel:recycle	()V
    //   74: aload_1
    //   75: athrow
    // Local variable table:
    //   start	length	slot	name	signature
    //   0	76	0	this	d
    //   0	76	1	paramaq	aq
    //   3	68	2	localParcel1	android.os.Parcel
    //   7	60	3	localParcel2	android.os.Parcel
    // Exception table:
    //   from	to	target	type
    //   8	14	65	finally
    //   18	29	65	finally
    //   29	48	65	finally
    //   57	62	65	finally
  }
  
  /* Error */
  public void a(as paramas)
  {
    // Byte code:
    //   0: invokestatic 24	android/os/Parcel:obtain	()Landroid/os/Parcel;
    //   3: astore_2
    //   4: invokestatic 24	android/os/Parcel:obtain	()Landroid/os/Parcel;
    //   7: astore_3
    //   8: aload_2
    //   9: ldc 26
    //   11: invokevirtual 30	android/os/Parcel:writeInterfaceToken	(Ljava/lang/String;)V
    //   14: aload_1
    //   15: ifnull +42 -> 57
    //   18: aload_2
    //   19: iconst_1
    //   20: invokevirtual 34	android/os/Parcel:writeInt	(I)V
    //   23: aload_1
    //   24: aload_2
    //   25: iconst_0
    //   26: invokevirtual 68	com/google/android/gms/wearable/internal/as:writeToParcel	(Landroid/os/Parcel;I)V
    //   29: aload_0
    //   30: getfield 15	com/google/android/gms/wearable/internal/d:a	Landroid/os/IBinder;
    //   33: bipush 12
    //   35: aload_2
    //   36: aload_3
    //   37: iconst_0
    //   38: invokeinterface 46 5 0
    //   43: pop
    //   44: aload_3
    //   45: invokevirtual 49	android/os/Parcel:readException	()V
    //   48: aload_3
    //   49: invokevirtual 52	android/os/Parcel:recycle	()V
    //   52: aload_2
    //   53: invokevirtual 52	android/os/Parcel:recycle	()V
    //   56: return
    //   57: aload_2
    //   58: iconst_0
    //   59: invokevirtual 34	android/os/Parcel:writeInt	(I)V
    //   62: goto -33 -> 29
    //   65: astore_1
    //   66: aload_3
    //   67: invokevirtual 52	android/os/Parcel:recycle	()V
    //   70: aload_2
    //   71: invokevirtual 52	android/os/Parcel:recycle	()V
    //   74: aload_1
    //   75: athrow
    // Local variable table:
    //   start	length	slot	name	signature
    //   0	76	0	this	d
    //   0	76	1	paramas	as
    //   3	68	2	localParcel1	android.os.Parcel
    //   7	60	3	localParcel2	android.os.Parcel
    // Exception table:
    //   from	to	target	type
    //   8	14	65	finally
    //   18	29	65	finally
    //   29	48	65	finally
    //   57	62	65	finally
  }
  
  /* Error */
  public void a(p paramp)
  {
    // Byte code:
    //   0: invokestatic 24	android/os/Parcel:obtain	()Landroid/os/Parcel;
    //   3: astore_2
    //   4: invokestatic 24	android/os/Parcel:obtain	()Landroid/os/Parcel;
    //   7: astore_3
    //   8: aload_2
    //   9: ldc 26
    //   11: invokevirtual 30	android/os/Parcel:writeInterfaceToken	(Ljava/lang/String;)V
    //   14: aload_1
    //   15: ifnull +42 -> 57
    //   18: aload_2
    //   19: iconst_1
    //   20: invokevirtual 34	android/os/Parcel:writeInt	(I)V
    //   23: aload_1
    //   24: aload_2
    //   25: iconst_0
    //   26: invokevirtual 72	com/google/android/gms/wearable/internal/p:writeToParcel	(Landroid/os/Parcel;I)V
    //   29: aload_0
    //   30: getfield 15	com/google/android/gms/wearable/internal/d:a	Landroid/os/IBinder;
    //   33: bipush 6
    //   35: aload_2
    //   36: aload_3
    //   37: iconst_0
    //   38: invokeinterface 46 5 0
    //   43: pop
    //   44: aload_3
    //   45: invokevirtual 49	android/os/Parcel:readException	()V
    //   48: aload_3
    //   49: invokevirtual 52	android/os/Parcel:recycle	()V
    //   52: aload_2
    //   53: invokevirtual 52	android/os/Parcel:recycle	()V
    //   56: return
    //   57: aload_2
    //   58: iconst_0
    //   59: invokevirtual 34	android/os/Parcel:writeInt	(I)V
    //   62: goto -33 -> 29
    //   65: astore_1
    //   66: aload_3
    //   67: invokevirtual 52	android/os/Parcel:recycle	()V
    //   70: aload_2
    //   71: invokevirtual 52	android/os/Parcel:recycle	()V
    //   74: aload_1
    //   75: athrow
    // Local variable table:
    //   start	length	slot	name	signature
    //   0	76	0	this	d
    //   0	76	1	paramp	p
    //   3	68	2	localParcel1	android.os.Parcel
    //   7	60	3	localParcel2	android.os.Parcel
    // Exception table:
    //   from	to	target	type
    //   8	14	65	finally
    //   18	29	65	finally
    //   29	48	65	finally
    //   57	62	65	finally
  }
  
  /* Error */
  public void a(r paramr)
  {
    // Byte code:
    //   0: invokestatic 24	android/os/Parcel:obtain	()Landroid/os/Parcel;
    //   3: astore_2
    //   4: invokestatic 24	android/os/Parcel:obtain	()Landroid/os/Parcel;
    //   7: astore_3
    //   8: aload_2
    //   9: ldc 26
    //   11: invokevirtual 30	android/os/Parcel:writeInterfaceToken	(Ljava/lang/String;)V
    //   14: aload_1
    //   15: ifnull +41 -> 56
    //   18: aload_2
    //   19: iconst_1
    //   20: invokevirtual 34	android/os/Parcel:writeInt	(I)V
    //   23: aload_1
    //   24: aload_2
    //   25: iconst_0
    //   26: invokevirtual 76	com/google/android/gms/wearable/internal/r:writeToParcel	(Landroid/os/Parcel;I)V
    //   29: aload_0
    //   30: getfield 15	com/google/android/gms/wearable/internal/d:a	Landroid/os/IBinder;
    //   33: iconst_2
    //   34: aload_2
    //   35: aload_3
    //   36: iconst_0
    //   37: invokeinterface 46 5 0
    //   42: pop
    //   43: aload_3
    //   44: invokevirtual 49	android/os/Parcel:readException	()V
    //   47: aload_3
    //   48: invokevirtual 52	android/os/Parcel:recycle	()V
    //   51: aload_2
    //   52: invokevirtual 52	android/os/Parcel:recycle	()V
    //   55: return
    //   56: aload_2
    //   57: iconst_0
    //   58: invokevirtual 34	android/os/Parcel:writeInt	(I)V
    //   61: goto -32 -> 29
    //   64: astore_1
    //   65: aload_3
    //   66: invokevirtual 52	android/os/Parcel:recycle	()V
    //   69: aload_2
    //   70: invokevirtual 52	android/os/Parcel:recycle	()V
    //   73: aload_1
    //   74: athrow
    // Local variable table:
    //   start	length	slot	name	signature
    //   0	75	0	this	d
    //   0	75	1	paramr	r
    //   3	67	2	localParcel1	android.os.Parcel
    //   7	59	3	localParcel2	android.os.Parcel
    // Exception table:
    //   from	to	target	type
    //   8	14	64	finally
    //   18	29	64	finally
    //   29	47	64	finally
    //   56	61	64	finally
  }
  
  /* Error */
  public void a(t paramt)
  {
    // Byte code:
    //   0: invokestatic 24	android/os/Parcel:obtain	()Landroid/os/Parcel;
    //   3: astore_2
    //   4: invokestatic 24	android/os/Parcel:obtain	()Landroid/os/Parcel;
    //   7: astore_3
    //   8: aload_2
    //   9: ldc 26
    //   11: invokevirtual 30	android/os/Parcel:writeInterfaceToken	(Ljava/lang/String;)V
    //   14: aload_1
    //   15: ifnull +42 -> 57
    //   18: aload_2
    //   19: iconst_1
    //   20: invokevirtual 34	android/os/Parcel:writeInt	(I)V
    //   23: aload_1
    //   24: aload_2
    //   25: iconst_0
    //   26: invokevirtual 80	com/google/android/gms/wearable/internal/t:writeToParcel	(Landroid/os/Parcel;I)V
    //   29: aload_0
    //   30: getfield 15	com/google/android/gms/wearable/internal/d:a	Landroid/os/IBinder;
    //   33: bipush 10
    //   35: aload_2
    //   36: aload_3
    //   37: iconst_0
    //   38: invokeinterface 46 5 0
    //   43: pop
    //   44: aload_3
    //   45: invokevirtual 49	android/os/Parcel:readException	()V
    //   48: aload_3
    //   49: invokevirtual 52	android/os/Parcel:recycle	()V
    //   52: aload_2
    //   53: invokevirtual 52	android/os/Parcel:recycle	()V
    //   56: return
    //   57: aload_2
    //   58: iconst_0
    //   59: invokevirtual 34	android/os/Parcel:writeInt	(I)V
    //   62: goto -33 -> 29
    //   65: astore_1
    //   66: aload_3
    //   67: invokevirtual 52	android/os/Parcel:recycle	()V
    //   70: aload_2
    //   71: invokevirtual 52	android/os/Parcel:recycle	()V
    //   74: aload_1
    //   75: athrow
    // Local variable table:
    //   start	length	slot	name	signature
    //   0	76	0	this	d
    //   0	76	1	paramt	t
    //   3	68	2	localParcel1	android.os.Parcel
    //   7	60	3	localParcel2	android.os.Parcel
    // Exception table:
    //   from	to	target	type
    //   8	14	65	finally
    //   18	29	65	finally
    //   29	48	65	finally
    //   57	62	65	finally
  }
  
  /* Error */
  public void a(v paramv)
  {
    // Byte code:
    //   0: invokestatic 24	android/os/Parcel:obtain	()Landroid/os/Parcel;
    //   3: astore_2
    //   4: invokestatic 24	android/os/Parcel:obtain	()Landroid/os/Parcel;
    //   7: astore_3
    //   8: aload_2
    //   9: ldc 26
    //   11: invokevirtual 30	android/os/Parcel:writeInterfaceToken	(Ljava/lang/String;)V
    //   14: aload_1
    //   15: ifnull +41 -> 56
    //   18: aload_2
    //   19: iconst_1
    //   20: invokevirtual 34	android/os/Parcel:writeInt	(I)V
    //   23: aload_1
    //   24: aload_2
    //   25: iconst_0
    //   26: invokevirtual 84	com/google/android/gms/wearable/internal/v:writeToParcel	(Landroid/os/Parcel;I)V
    //   29: aload_0
    //   30: getfield 15	com/google/android/gms/wearable/internal/d:a	Landroid/os/IBinder;
    //   33: iconst_4
    //   34: aload_2
    //   35: aload_3
    //   36: iconst_0
    //   37: invokeinterface 46 5 0
    //   42: pop
    //   43: aload_3
    //   44: invokevirtual 49	android/os/Parcel:readException	()V
    //   47: aload_3
    //   48: invokevirtual 52	android/os/Parcel:recycle	()V
    //   51: aload_2
    //   52: invokevirtual 52	android/os/Parcel:recycle	()V
    //   55: return
    //   56: aload_2
    //   57: iconst_0
    //   58: invokevirtual 34	android/os/Parcel:writeInt	(I)V
    //   61: goto -32 -> 29
    //   64: astore_1
    //   65: aload_3
    //   66: invokevirtual 52	android/os/Parcel:recycle	()V
    //   69: aload_2
    //   70: invokevirtual 52	android/os/Parcel:recycle	()V
    //   73: aload_1
    //   74: athrow
    // Local variable table:
    //   start	length	slot	name	signature
    //   0	75	0	this	d
    //   0	75	1	paramv	v
    //   3	67	2	localParcel1	android.os.Parcel
    //   7	59	3	localParcel2	android.os.Parcel
    // Exception table:
    //   from	to	target	type
    //   8	14	64	finally
    //   18	29	64	finally
    //   29	47	64	finally
    //   56	61	64	finally
  }
  
  /* Error */
  public void a(x paramx)
  {
    // Byte code:
    //   0: invokestatic 24	android/os/Parcel:obtain	()Landroid/os/Parcel;
    //   3: astore_2
    //   4: invokestatic 24	android/os/Parcel:obtain	()Landroid/os/Parcel;
    //   7: astore_3
    //   8: aload_2
    //   9: ldc 26
    //   11: invokevirtual 30	android/os/Parcel:writeInterfaceToken	(Ljava/lang/String;)V
    //   14: aload_1
    //   15: ifnull +42 -> 57
    //   18: aload_2
    //   19: iconst_1
    //   20: invokevirtual 34	android/os/Parcel:writeInt	(I)V
    //   23: aload_1
    //   24: aload_2
    //   25: iconst_0
    //   26: invokevirtual 88	com/google/android/gms/wearable/internal/x:writeToParcel	(Landroid/os/Parcel;I)V
    //   29: aload_0
    //   30: getfield 15	com/google/android/gms/wearable/internal/d:a	Landroid/os/IBinder;
    //   33: bipush 8
    //   35: aload_2
    //   36: aload_3
    //   37: iconst_0
    //   38: invokeinterface 46 5 0
    //   43: pop
    //   44: aload_3
    //   45: invokevirtual 49	android/os/Parcel:readException	()V
    //   48: aload_3
    //   49: invokevirtual 52	android/os/Parcel:recycle	()V
    //   52: aload_2
    //   53: invokevirtual 52	android/os/Parcel:recycle	()V
    //   56: return
    //   57: aload_2
    //   58: iconst_0
    //   59: invokevirtual 34	android/os/Parcel:writeInt	(I)V
    //   62: goto -33 -> 29
    //   65: astore_1
    //   66: aload_3
    //   67: invokevirtual 52	android/os/Parcel:recycle	()V
    //   70: aload_2
    //   71: invokevirtual 52	android/os/Parcel:recycle	()V
    //   74: aload_1
    //   75: athrow
    // Local variable table:
    //   start	length	slot	name	signature
    //   0	76	0	this	d
    //   0	76	1	paramx	x
    //   3	68	2	localParcel1	android.os.Parcel
    //   7	60	3	localParcel2	android.os.Parcel
    // Exception table:
    //   from	to	target	type
    //   8	14	65	finally
    //   18	29	65	finally
    //   29	48	65	finally
    //   57	62	65	finally
  }
  
  /* Error */
  public void a(z paramz)
  {
    // Byte code:
    //   0: invokestatic 24	android/os/Parcel:obtain	()Landroid/os/Parcel;
    //   3: astore_2
    //   4: invokestatic 24	android/os/Parcel:obtain	()Landroid/os/Parcel;
    //   7: astore_3
    //   8: aload_2
    //   9: ldc 26
    //   11: invokevirtual 30	android/os/Parcel:writeInterfaceToken	(Ljava/lang/String;)V
    //   14: aload_1
    //   15: ifnull +42 -> 57
    //   18: aload_2
    //   19: iconst_1
    //   20: invokevirtual 34	android/os/Parcel:writeInt	(I)V
    //   23: aload_1
    //   24: aload_2
    //   25: iconst_0
    //   26: invokevirtual 92	com/google/android/gms/wearable/internal/z:writeToParcel	(Landroid/os/Parcel;I)V
    //   29: aload_0
    //   30: getfield 15	com/google/android/gms/wearable/internal/d:a	Landroid/os/IBinder;
    //   33: bipush 9
    //   35: aload_2
    //   36: aload_3
    //   37: iconst_0
    //   38: invokeinterface 46 5 0
    //   43: pop
    //   44: aload_3
    //   45: invokevirtual 49	android/os/Parcel:readException	()V
    //   48: aload_3
    //   49: invokevirtual 52	android/os/Parcel:recycle	()V
    //   52: aload_2
    //   53: invokevirtual 52	android/os/Parcel:recycle	()V
    //   56: return
    //   57: aload_2
    //   58: iconst_0
    //   59: invokevirtual 34	android/os/Parcel:writeInt	(I)V
    //   62: goto -33 -> 29
    //   65: astore_1
    //   66: aload_3
    //   67: invokevirtual 52	android/os/Parcel:recycle	()V
    //   70: aload_2
    //   71: invokevirtual 52	android/os/Parcel:recycle	()V
    //   74: aload_1
    //   75: athrow
    // Local variable table:
    //   start	length	slot	name	signature
    //   0	76	0	this	d
    //   0	76	1	paramz	z
    //   3	68	2	localParcel1	android.os.Parcel
    //   7	60	3	localParcel2	android.os.Parcel
    // Exception table:
    //   from	to	target	type
    //   8	14	65	finally
    //   18	29	65	finally
    //   29	48	65	finally
    //   57	62	65	finally
  }
  
  public IBinder asBinder()
  {
    return this.a;
  }
}


/* Location:              /Users/amaurremi/uw/stringoid/static-dynamic-comparison/apps/retrica/com.venticake.retrica-21-dex2jar.jar!/com/google/android/gms/wearable/internal/d.class
 * Java compiler version: 6 (50.0)
 * JD-Core Version:       0.7.1
 */