package com.flurry.android;

import android.os.AsyncTask;

final class co
  extends AsyncTask<Void, Void, Void>
{
  co(FlurryAds paramFlurryAds) {}
  
  /* Error */
  private Void ar()
  {
    // Byte code:
    //   0: aload_0
    //   1: getfield 11	com/flurry/android/co:ee	Lcom/flurry/android/FlurryAds;
    //   4: invokestatic 25	com/flurry/android/FlurryAds:c	(Lcom/flurry/android/FlurryAds;)Ljava/io/File;
    //   7: invokevirtual 31	java/io/File:exists	()Z
    //   10: istore_1
    //   11: iload_1
    //   12: ifeq +64 -> 76
    //   15: new 33	java/io/DataInputStream
    //   18: dup
    //   19: new 35	java/io/FileInputStream
    //   22: dup
    //   23: aload_0
    //   24: getfield 11	com/flurry/android/co:ee	Lcom/flurry/android/FlurryAds;
    //   27: invokestatic 25	com/flurry/android/FlurryAds:c	(Lcom/flurry/android/FlurryAds;)Ljava/io/File;
    //   30: invokespecial 38	java/io/FileInputStream:<init>	(Ljava/io/File;)V
    //   33: invokespecial 41	java/io/DataInputStream:<init>	(Ljava/io/InputStream;)V
    //   36: astore_3
    //   37: aload_3
    //   38: astore_2
    //   39: aload_0
    //   40: getfield 11	com/flurry/android/co:ee	Lcom/flurry/android/FlurryAds;
    //   43: aload_3
    //   44: invokevirtual 44	com/flurry/android/FlurryAds:c	(Ljava/io/DataInputStream;)V
    //   47: aload_3
    //   48: invokestatic 50	com/flurry/android/bd:a	(Ljava/io/Closeable;)V
    //   51: aload_0
    //   52: getfield 11	com/flurry/android/co:ee	Lcom/flurry/android/FlurryAds;
    //   55: invokestatic 54	com/flurry/android/FlurryAds:d	(Lcom/flurry/android/FlurryAds;)Z
    //   58: ifne +59 -> 117
    //   61: aload_0
    //   62: getfield 11	com/flurry/android/co:ee	Lcom/flurry/android/FlurryAds;
    //   65: invokestatic 25	com/flurry/android/FlurryAds:c	(Lcom/flurry/android/FlurryAds;)Ljava/io/File;
    //   68: invokevirtual 57	java/io/File:delete	()Z
    //   71: istore_1
    //   72: iload_1
    //   73: ifne +3 -> 76
    //   76: aconst_null
    //   77: areturn
    //   78: astore 4
    //   80: aconst_null
    //   81: astore_3
    //   82: aload_3
    //   83: astore_2
    //   84: getstatic 60	com/flurry/android/FlurryAds:d	Ljava/lang/String;
    //   87: ldc 62
    //   89: aload 4
    //   91: invokestatic 68	com/flurry/android/db:b	(Ljava/lang/String;Ljava/lang/String;Ljava/lang/Throwable;)V
    //   94: aload_3
    //   95: invokestatic 50	com/flurry/android/bd:a	(Ljava/io/Closeable;)V
    //   98: goto -47 -> 51
    //   101: astore_2
    //   102: aload_2
    //   103: invokevirtual 71	java/lang/Throwable:printStackTrace	()V
    //   106: aconst_null
    //   107: areturn
    //   108: astore_3
    //   109: aconst_null
    //   110: astore_2
    //   111: aload_2
    //   112: invokestatic 50	com/flurry/android/bd:a	(Ljava/io/Closeable;)V
    //   115: aload_3
    //   116: athrow
    //   117: aload_0
    //   118: getfield 11	com/flurry/android/co:ee	Lcom/flurry/android/FlurryAds;
    //   121: getfield 75	com/flurry/android/FlurryAds:cM	Lcom/flurry/android/FlurryFreqCapManager;
    //   124: invokevirtual 80	com/flurry/android/FlurryFreqCapManager:ap	()V
    //   127: aconst_null
    //   128: areturn
    //   129: astore_2
    //   130: getstatic 60	com/flurry/android/FlurryAds:d	Ljava/lang/String;
    //   133: ldc 82
    //   135: aload_2
    //   136: invokestatic 68	com/flurry/android/db:b	(Ljava/lang/String;Ljava/lang/String;Ljava/lang/Throwable;)V
    //   139: aconst_null
    //   140: areturn
    //   141: astore_3
    //   142: goto -31 -> 111
    //   145: astore 4
    //   147: goto -65 -> 82
    // Local variable table:
    //   start	length	slot	name	signature
    //   0	150	0	this	co
    //   10	63	1	bool	boolean
    //   38	46	2	localDataInputStream1	java.io.DataInputStream
    //   101	2	2	localThrowable1	Throwable
    //   110	2	2	localCloseable	java.io.Closeable
    //   129	7	2	localThrowable2	Throwable
    //   36	59	3	localDataInputStream2	java.io.DataInputStream
    //   108	8	3	localObject1	Object
    //   141	1	3	localObject2	Object
    //   78	12	4	localThrowable3	Throwable
    //   145	1	4	localThrowable4	Throwable
    // Exception table:
    //   from	to	target	type
    //   15	37	78	java/lang/Throwable
    //   0	11	101	java/lang/Throwable
    //   47	51	101	java/lang/Throwable
    //   94	98	101	java/lang/Throwable
    //   111	117	101	java/lang/Throwable
    //   130	139	101	java/lang/Throwable
    //   15	37	108	finally
    //   51	72	129	java/lang/Throwable
    //   117	127	129	java/lang/Throwable
    //   39	47	141	finally
    //   84	94	141	finally
    //   39	47	145	java/lang/Throwable
  }
}


/* Location:              /Users/amaurremi/uw/stringoid/static-dynamic-comparison/apps/randomchat/com.pioong-93-dex2jar.jar!/com/flurry/android/co.class
 * Java compiler version: 6 (50.0)
 * JD-Core Version:       0.7.1
 */