package com.google.android.gms.maps.model.internal;

import android.graphics.Bitmap;
import android.os.Binder;
import android.os.IBinder;
import android.os.IInterface;
import android.os.Parcel;
import android.os.Parcelable.Creator;
import android.os.RemoteException;
import com.google.android.gms.dynamic.b;
import com.google.android.gms.dynamic.b.a;

public abstract interface a
  extends IInterface
{
  public abstract b a(Bitmap paramBitmap)
    throws RemoteException;
  
  public abstract b at(String paramString)
    throws RemoteException;
  
  public abstract b au(String paramString)
    throws RemoteException;
  
  public abstract b av(String paramString)
    throws RemoteException;
  
  public abstract b bh(int paramInt)
    throws RemoteException;
  
  public abstract b c(float paramFloat)
    throws RemoteException;
  
  public abstract b eJ()
    throws RemoteException;
  
  public static abstract class a
    extends Binder
    implements a
  {
    public static a aj(IBinder paramIBinder)
    {
      if (paramIBinder == null) {
        return null;
      }
      IInterface localIInterface = paramIBinder.queryLocalInterface("com.google.android.gms.maps.model.internal.IBitmapDescriptorFactoryDelegate");
      if ((localIInterface != null) && ((localIInterface instanceof a))) {
        return (a)localIInterface;
      }
      return new a(paramIBinder);
    }
    
    public boolean onTransact(int paramInt1, Parcel paramParcel1, Parcel paramParcel2, int paramInt2)
      throws RemoteException
    {
      Object localObject1 = null;
      Object localObject2 = null;
      Object localObject3 = null;
      b localb1 = null;
      Object localObject4 = null;
      b localb2 = null;
      switch (paramInt1)
      {
      default: 
        return super.onTransact(paramInt1, paramParcel1, paramParcel2, paramInt2);
      case 1598968902: 
        paramParcel2.writeString("com.google.android.gms.maps.model.internal.IBitmapDescriptorFactoryDelegate");
        return true;
      case 1: 
        paramParcel1.enforceInterface("com.google.android.gms.maps.model.internal.IBitmapDescriptorFactoryDelegate");
        paramParcel1 = bh(paramParcel1.readInt());
        paramParcel2.writeNoException();
        if (paramParcel1 != null) {}
        for (paramParcel1 = paramParcel1.asBinder();; paramParcel1 = null)
        {
          paramParcel2.writeStrongBinder(paramParcel1);
          return true;
        }
      case 2: 
        paramParcel1.enforceInterface("com.google.android.gms.maps.model.internal.IBitmapDescriptorFactoryDelegate");
        localb1 = at(paramParcel1.readString());
        paramParcel2.writeNoException();
        paramParcel1 = localb2;
        if (localb1 != null) {
          paramParcel1 = localb1.asBinder();
        }
        paramParcel2.writeStrongBinder(paramParcel1);
        return true;
      case 3: 
        paramParcel1.enforceInterface("com.google.android.gms.maps.model.internal.IBitmapDescriptorFactoryDelegate");
        localb1 = au(paramParcel1.readString());
        paramParcel2.writeNoException();
        paramParcel1 = (Parcel)localObject1;
        if (localb1 != null) {
          paramParcel1 = localb1.asBinder();
        }
        paramParcel2.writeStrongBinder(paramParcel1);
        return true;
      case 4: 
        paramParcel1.enforceInterface("com.google.android.gms.maps.model.internal.IBitmapDescriptorFactoryDelegate");
        localb1 = eJ();
        paramParcel2.writeNoException();
        paramParcel1 = (Parcel)localObject2;
        if (localb1 != null) {
          paramParcel1 = localb1.asBinder();
        }
        paramParcel2.writeStrongBinder(paramParcel1);
        return true;
      case 5: 
        paramParcel1.enforceInterface("com.google.android.gms.maps.model.internal.IBitmapDescriptorFactoryDelegate");
        localb1 = c(paramParcel1.readFloat());
        paramParcel2.writeNoException();
        paramParcel1 = (Parcel)localObject3;
        if (localb1 != null) {
          paramParcel1 = localb1.asBinder();
        }
        paramParcel2.writeStrongBinder(paramParcel1);
        return true;
      case 6: 
        paramParcel1.enforceInterface("com.google.android.gms.maps.model.internal.IBitmapDescriptorFactoryDelegate");
        if (paramParcel1.readInt() != 0) {}
        for (paramParcel1 = (Bitmap)Bitmap.CREATOR.createFromParcel(paramParcel1);; paramParcel1 = null)
        {
          localb2 = a(paramParcel1);
          paramParcel2.writeNoException();
          paramParcel1 = localb1;
          if (localb2 != null) {
            paramParcel1 = localb2.asBinder();
          }
          paramParcel2.writeStrongBinder(paramParcel1);
          return true;
        }
      }
      paramParcel1.enforceInterface("com.google.android.gms.maps.model.internal.IBitmapDescriptorFactoryDelegate");
      localb1 = av(paramParcel1.readString());
      paramParcel2.writeNoException();
      paramParcel1 = (Parcel)localObject4;
      if (localb1 != null) {
        paramParcel1 = localb1.asBinder();
      }
      paramParcel2.writeStrongBinder(paramParcel1);
      return true;
    }
    
    private static class a
      implements a
    {
      private IBinder dU;
      
      a(IBinder paramIBinder)
      {
        this.dU = paramIBinder;
      }
      
      /* Error */
      public b a(Bitmap paramBitmap)
        throws RemoteException
      {
        // Byte code:
        //   0: invokestatic 28	android/os/Parcel:obtain	()Landroid/os/Parcel;
        //   3: astore_2
        //   4: invokestatic 28	android/os/Parcel:obtain	()Landroid/os/Parcel;
        //   7: astore_3
        //   8: aload_2
        //   9: ldc 30
        //   11: invokevirtual 34	android/os/Parcel:writeInterfaceToken	(Ljava/lang/String;)V
        //   14: aload_1
        //   15: ifnull +51 -> 66
        //   18: aload_2
        //   19: iconst_1
        //   20: invokevirtual 38	android/os/Parcel:writeInt	(I)V
        //   23: aload_1
        //   24: aload_2
        //   25: iconst_0
        //   26: invokevirtual 44	android/graphics/Bitmap:writeToParcel	(Landroid/os/Parcel;I)V
        //   29: aload_0
        //   30: getfield 18	com/google/android/gms/maps/model/internal/a$a$a:dU	Landroid/os/IBinder;
        //   33: bipush 6
        //   35: aload_2
        //   36: aload_3
        //   37: iconst_0
        //   38: invokeinterface 50 5 0
        //   43: pop
        //   44: aload_3
        //   45: invokevirtual 53	android/os/Parcel:readException	()V
        //   48: aload_3
        //   49: invokevirtual 57	android/os/Parcel:readStrongBinder	()Landroid/os/IBinder;
        //   52: invokestatic 63	com/google/android/gms/dynamic/b$a:E	(Landroid/os/IBinder;)Lcom/google/android/gms/dynamic/b;
        //   55: astore_1
        //   56: aload_3
        //   57: invokevirtual 66	android/os/Parcel:recycle	()V
        //   60: aload_2
        //   61: invokevirtual 66	android/os/Parcel:recycle	()V
        //   64: aload_1
        //   65: areturn
        //   66: aload_2
        //   67: iconst_0
        //   68: invokevirtual 38	android/os/Parcel:writeInt	(I)V
        //   71: goto -42 -> 29
        //   74: astore_1
        //   75: aload_3
        //   76: invokevirtual 66	android/os/Parcel:recycle	()V
        //   79: aload_2
        //   80: invokevirtual 66	android/os/Parcel:recycle	()V
        //   83: aload_1
        //   84: athrow
        // Local variable table:
        //   start	length	slot	name	signature
        //   0	85	0	this	a
        //   0	85	1	paramBitmap	Bitmap
        //   3	77	2	localParcel1	Parcel
        //   7	69	3	localParcel2	Parcel
        // Exception table:
        //   from	to	target	type
        //   8	14	74	finally
        //   18	29	74	finally
        //   29	56	74	finally
        //   66	71	74	finally
      }
      
      public IBinder asBinder()
      {
        return this.dU;
      }
      
      public b at(String paramString)
        throws RemoteException
      {
        Parcel localParcel1 = Parcel.obtain();
        Parcel localParcel2 = Parcel.obtain();
        try
        {
          localParcel1.writeInterfaceToken("com.google.android.gms.maps.model.internal.IBitmapDescriptorFactoryDelegate");
          localParcel1.writeString(paramString);
          this.dU.transact(2, localParcel1, localParcel2, 0);
          localParcel2.readException();
          paramString = b.a.E(localParcel2.readStrongBinder());
          return paramString;
        }
        finally
        {
          localParcel2.recycle();
          localParcel1.recycle();
        }
      }
      
      public b au(String paramString)
        throws RemoteException
      {
        Parcel localParcel1 = Parcel.obtain();
        Parcel localParcel2 = Parcel.obtain();
        try
        {
          localParcel1.writeInterfaceToken("com.google.android.gms.maps.model.internal.IBitmapDescriptorFactoryDelegate");
          localParcel1.writeString(paramString);
          this.dU.transact(3, localParcel1, localParcel2, 0);
          localParcel2.readException();
          paramString = b.a.E(localParcel2.readStrongBinder());
          return paramString;
        }
        finally
        {
          localParcel2.recycle();
          localParcel1.recycle();
        }
      }
      
      public b av(String paramString)
        throws RemoteException
      {
        Parcel localParcel1 = Parcel.obtain();
        Parcel localParcel2 = Parcel.obtain();
        try
        {
          localParcel1.writeInterfaceToken("com.google.android.gms.maps.model.internal.IBitmapDescriptorFactoryDelegate");
          localParcel1.writeString(paramString);
          this.dU.transact(7, localParcel1, localParcel2, 0);
          localParcel2.readException();
          paramString = b.a.E(localParcel2.readStrongBinder());
          return paramString;
        }
        finally
        {
          localParcel2.recycle();
          localParcel1.recycle();
        }
      }
      
      public b bh(int paramInt)
        throws RemoteException
      {
        Parcel localParcel1 = Parcel.obtain();
        Parcel localParcel2 = Parcel.obtain();
        try
        {
          localParcel1.writeInterfaceToken("com.google.android.gms.maps.model.internal.IBitmapDescriptorFactoryDelegate");
          localParcel1.writeInt(paramInt);
          this.dU.transact(1, localParcel1, localParcel2, 0);
          localParcel2.readException();
          b localb = b.a.E(localParcel2.readStrongBinder());
          return localb;
        }
        finally
        {
          localParcel2.recycle();
          localParcel1.recycle();
        }
      }
      
      public b c(float paramFloat)
        throws RemoteException
      {
        Parcel localParcel1 = Parcel.obtain();
        Parcel localParcel2 = Parcel.obtain();
        try
        {
          localParcel1.writeInterfaceToken("com.google.android.gms.maps.model.internal.IBitmapDescriptorFactoryDelegate");
          localParcel1.writeFloat(paramFloat);
          this.dU.transact(5, localParcel1, localParcel2, 0);
          localParcel2.readException();
          b localb = b.a.E(localParcel2.readStrongBinder());
          return localb;
        }
        finally
        {
          localParcel2.recycle();
          localParcel1.recycle();
        }
      }
      
      public b eJ()
        throws RemoteException
      {
        Parcel localParcel1 = Parcel.obtain();
        Parcel localParcel2 = Parcel.obtain();
        try
        {
          localParcel1.writeInterfaceToken("com.google.android.gms.maps.model.internal.IBitmapDescriptorFactoryDelegate");
          this.dU.transact(4, localParcel1, localParcel2, 0);
          localParcel2.readException();
          b localb = b.a.E(localParcel2.readStrongBinder());
          return localb;
        }
        finally
        {
          localParcel2.recycle();
          localParcel1.recycle();
        }
      }
    }
  }
}


/* Location:              /Users/amaurremi/uw/stringoid/static-dynamic-comparison/apps/beyondpod/mobi.beyondpod-3368-dex2jar.jar!/com/google/android/gms/maps/model/internal/a.class
 * Java compiler version: 6 (50.0)
 * JD-Core Version:       0.7.1
 */