package com.parse;

import android.content.Context;
import android.content.Intent;
import java.io.BufferedReader;
import java.io.OutputStreamWriter;
import java.net.Socket;

class PushConnection
{
  static final String TAG = "com.parse.push.connection";
  static int connectTimeout;
  static long generalTimeout;
  private ConnectivityNotifier.ConnectivityListener listener = new ConnectivityNotifier.ConnectivityListener()
  {
    public void networkConnectivityStatusChanged(Intent paramAnonymousIntent)
    {
      PushConnection.this.close();
    }
  };
  private int port;
  private BufferedReader reader = null;
  private Thread readerThread = null;
  private String server;
  private Socket socket;
  private Object socketLock = new Object();
  private OutputStreamWriter writer = null;
  
  static
  {
    if (!PushConnection.class.desiredAssertionStatus()) {}
    for (boolean bool = true;; bool = false)
    {
      $assertionsDisabled = bool;
      generalTimeout = 1800000L;
      connectTimeout = 40000;
      return;
    }
  }
  
  public PushConnection(Context paramContext)
  {
    ConnectivityNotifier.getNotifier().addListener(this.listener, paramContext);
  }
  
  /* Error */
  public void close()
  {
    // Byte code:
    //   0: invokestatic 71	com/parse/ConnectivityNotifier:getNotifier	()Lcom/parse/ConnectivityNotifier;
    //   3: aload_0
    //   4: getfield 63	com/parse/PushConnection:listener	Lcom/parse/ConnectivityNotifier$ConnectivityListener;
    //   7: invokevirtual 82	com/parse/ConnectivityNotifier:removeListener	(Lcom/parse/ConnectivityNotifier$ConnectivityListener;)V
    //   10: aload_0
    //   11: getfield 65	com/parse/PushConnection:socketLock	Ljava/lang/Object;
    //   14: astore_1
    //   15: aload_1
    //   16: monitorenter
    //   17: aload_0
    //   18: getfield 54	com/parse/PushConnection:reader	Ljava/io/BufferedReader;
    //   21: astore_2
    //   22: aload_0
    //   23: getfield 56	com/parse/PushConnection:writer	Ljava/io/OutputStreamWriter;
    //   26: astore_3
    //   27: aload_0
    //   28: getfield 84	com/parse/PushConnection:socket	Ljava/net/Socket;
    //   31: astore 4
    //   33: aload_0
    //   34: getfield 58	com/parse/PushConnection:readerThread	Ljava/lang/Thread;
    //   37: ifnull +17 -> 54
    //   40: ldc 12
    //   42: ldc 86
    //   44: invokestatic 92	com/parse/Parse:logV	(Ljava/lang/String;Ljava/lang/String;)V
    //   47: aload_0
    //   48: getfield 58	com/parse/PushConnection:readerThread	Ljava/lang/Thread;
    //   51: invokevirtual 97	java/lang/Thread:interrupt	()V
    //   54: aload_0
    //   55: aconst_null
    //   56: putfield 54	com/parse/PushConnection:reader	Ljava/io/BufferedReader;
    //   59: aload_0
    //   60: aconst_null
    //   61: putfield 56	com/parse/PushConnection:writer	Ljava/io/OutputStreamWriter;
    //   64: aload_0
    //   65: aconst_null
    //   66: putfield 84	com/parse/PushConnection:socket	Ljava/net/Socket;
    //   69: aload_1
    //   70: monitorexit
    //   71: invokestatic 103	android/os/Looper:myLooper	()Landroid/os/Looper;
    //   74: invokestatic 106	android/os/Looper:getMainLooper	()Landroid/os/Looper;
    //   77: if_acmpne +9 -> 86
    //   80: return
    //   81: astore_2
    //   82: aload_1
    //   83: monitorexit
    //   84: aload_2
    //   85: athrow
    //   86: aload_2
    //   87: ifnull +11 -> 98
    //   90: aload_2
    //   91: monitorenter
    //   92: aload_2
    //   93: invokevirtual 110	java/io/BufferedReader:close	()V
    //   96: aload_2
    //   97: monitorexit
    //   98: aload_3
    //   99: ifnull +11 -> 110
    //   102: aload_3
    //   103: monitorenter
    //   104: aload_3
    //   105: invokevirtual 113	java/io/OutputStreamWriter:close	()V
    //   108: aload_3
    //   109: monitorexit
    //   110: aload 4
    //   112: ifnull -32 -> 80
    //   115: aload 4
    //   117: monitorenter
    //   118: aload 4
    //   120: invokevirtual 116	java/net/Socket:close	()V
    //   123: aload 4
    //   125: monitorexit
    //   126: return
    //   127: astore_1
    //   128: aload 4
    //   130: monitorexit
    //   131: aload_1
    //   132: athrow
    //   133: astore_1
    //   134: ldc 12
    //   136: ldc 118
    //   138: aload_1
    //   139: invokestatic 121	com/parse/Parse:logV	(Ljava/lang/String;Ljava/lang/String;Ljava/lang/Throwable;)V
    //   142: return
    //   143: astore_1
    //   144: aload_2
    //   145: monitorexit
    //   146: aload_1
    //   147: athrow
    //   148: astore_1
    //   149: aload_3
    //   150: monitorexit
    //   151: aload_1
    //   152: athrow
    // Local variable table:
    //   start	length	slot	name	signature
    //   0	153	0	this	PushConnection
    //   14	69	1	localObject1	Object
    //   127	5	1	localObject2	Object
    //   133	6	1	localIOException	java.io.IOException
    //   143	4	1	localObject3	Object
    //   148	4	1	localObject4	Object
    //   21	1	2	localBufferedReader	BufferedReader
    //   81	64	2	localObject5	Object
    //   26	124	3	localOutputStreamWriter	OutputStreamWriter
    //   31	98	4	localSocket	Socket
    // Exception table:
    //   from	to	target	type
    //   17	54	81	finally
    //   54	71	81	finally
    //   82	84	81	finally
    //   118	126	127	finally
    //   128	131	127	finally
    //   90	92	133	java/io/IOException
    //   102	104	133	java/io/IOException
    //   115	118	133	java/io/IOException
    //   131	133	133	java/io/IOException
    //   146	148	133	java/io/IOException
    //   151	153	133	java/io/IOException
    //   92	98	143	finally
    //   144	146	143	finally
    //   104	110	148	finally
    //   149	151	148	finally
  }
  
  /* Error */
  public void connect(String paramString, int paramInt, boolean paramBoolean)
  {
    // Byte code:
    //   0: aconst_null
    //   1: astore 5
    //   3: iload_3
    //   4: istore 4
    //   6: iload_3
    //   7: ifne +59 -> 66
    //   10: aload_0
    //   11: getfield 65	com/parse/PushConnection:socketLock	Ljava/lang/Object;
    //   14: astore 6
    //   16: aload 6
    //   18: monitorenter
    //   19: aload_0
    //   20: getfield 84	com/parse/PushConnection:socket	Ljava/net/Socket;
    //   23: ifnull +166 -> 189
    //   26: aload_0
    //   27: getfield 84	com/parse/PushConnection:socket	Ljava/net/Socket;
    //   30: invokevirtual 128	java/net/Socket:isClosed	()Z
    //   33: ifne +156 -> 189
    //   36: aload_0
    //   37: getfield 130	com/parse/PushConnection:server	Ljava/lang/String;
    //   40: aload_1
    //   41: if_acmpne +148 -> 189
    //   44: aload_0
    //   45: getfield 132	com/parse/PushConnection:port	I
    //   48: iload_2
    //   49: if_icmpne +140 -> 189
    //   52: iconst_0
    //   53: istore_3
    //   54: aload_0
    //   55: getfield 84	com/parse/PushConnection:socket	Ljava/net/Socket;
    //   58: astore 5
    //   60: aload 6
    //   62: monitorexit
    //   63: iload_3
    //   64: istore 4
    //   66: iload 4
    //   68: ifeq +120 -> 188
    //   71: ldc 12
    //   73: new 134	java/lang/StringBuilder
    //   76: dup
    //   77: ldc -120
    //   79: invokespecial 139	java/lang/StringBuilder:<init>	(Ljava/lang/String;)V
    //   82: aload_1
    //   83: invokevirtual 143	java/lang/StringBuilder:append	(Ljava/lang/String;)Ljava/lang/StringBuilder;
    //   86: ldc -111
    //   88: invokevirtual 143	java/lang/StringBuilder:append	(Ljava/lang/String;)Ljava/lang/StringBuilder;
    //   91: iload_2
    //   92: invokevirtual 148	java/lang/StringBuilder:append	(I)Ljava/lang/StringBuilder;
    //   95: invokevirtual 152	java/lang/StringBuilder:toString	()Ljava/lang/String;
    //   98: invokestatic 92	com/parse/Parse:logV	(Ljava/lang/String;Ljava/lang/String;)V
    //   101: new 154	java/net/InetSocketAddress
    //   104: dup
    //   105: aload_1
    //   106: iload_2
    //   107: invokespecial 157	java/net/InetSocketAddress:<init>	(Ljava/lang/String;I)V
    //   110: astore 7
    //   112: new 115	java/net/Socket
    //   115: dup
    //   116: invokespecial 158	java/net/Socket:<init>	()V
    //   119: astore 6
    //   121: aload 6
    //   123: iconst_1
    //   124: invokevirtual 162	java/net/Socket:setKeepAlive	(Z)V
    //   127: aload 6
    //   129: aload 7
    //   131: getstatic 47	com/parse/PushConnection:connectTimeout	I
    //   134: invokevirtual 165	java/net/Socket:connect	(Ljava/net/SocketAddress;I)V
    //   137: getstatic 40	com/parse/PushConnection:$assertionsDisabled	Z
    //   140: ifne +90 -> 230
    //   143: aload 6
    //   145: invokevirtual 128	java/net/Socket:isClosed	()Z
    //   148: ifeq +82 -> 230
    //   151: new 167	java/lang/AssertionError
    //   154: dup
    //   155: invokespecial 168	java/lang/AssertionError:<init>	()V
    //   158: athrow
    //   159: astore_1
    //   160: ldc 12
    //   162: new 134	java/lang/StringBuilder
    //   165: dup
    //   166: ldc -86
    //   168: invokespecial 139	java/lang/StringBuilder:<init>	(Ljava/lang/String;)V
    //   171: aload_1
    //   172: invokevirtual 171	java/net/UnknownHostException:toString	()Ljava/lang/String;
    //   175: invokevirtual 143	java/lang/StringBuilder:append	(Ljava/lang/String;)Ljava/lang/StringBuilder;
    //   178: invokevirtual 152	java/lang/StringBuilder:toString	()Ljava/lang/String;
    //   181: invokestatic 92	com/parse/Parse:logV	(Ljava/lang/String;Ljava/lang/String;)V
    //   184: aload_0
    //   185: invokevirtual 172	com/parse/PushConnection:close	()V
    //   188: return
    //   189: iconst_1
    //   190: istore_3
    //   191: goto -137 -> 54
    //   194: astore_1
    //   195: aload 6
    //   197: monitorexit
    //   198: aload_1
    //   199: athrow
    //   200: astore_1
    //   201: ldc 12
    //   203: new 134	java/lang/StringBuilder
    //   206: dup
    //   207: ldc -82
    //   209: invokespecial 139	java/lang/StringBuilder:<init>	(Ljava/lang/String;)V
    //   212: aload_1
    //   213: invokevirtual 175	java/io/IOException:toString	()Ljava/lang/String;
    //   216: invokevirtual 143	java/lang/StringBuilder:append	(Ljava/lang/String;)Ljava/lang/StringBuilder;
    //   219: invokevirtual 152	java/lang/StringBuilder:toString	()Ljava/lang/String;
    //   222: invokestatic 92	com/parse/Parse:logV	(Ljava/lang/String;Ljava/lang/String;)V
    //   225: aload_0
    //   226: invokevirtual 172	com/parse/PushConnection:close	()V
    //   229: return
    //   230: aload_0
    //   231: getfield 65	com/parse/PushConnection:socketLock	Ljava/lang/Object;
    //   234: astore 7
    //   236: aload 7
    //   238: monitorenter
    //   239: aload_0
    //   240: getfield 84	com/parse/PushConnection:socket	Ljava/net/Socket;
    //   243: aload 5
    //   245: if_acmpeq +13 -> 258
    //   248: aload 7
    //   250: monitorexit
    //   251: return
    //   252: astore_1
    //   253: aload 7
    //   255: monitorexit
    //   256: aload_1
    //   257: athrow
    //   258: aload_0
    //   259: invokevirtual 172	com/parse/PushConnection:close	()V
    //   262: aload_0
    //   263: aload 6
    //   265: putfield 84	com/parse/PushConnection:socket	Ljava/net/Socket;
    //   268: aload_0
    //   269: aload_1
    //   270: putfield 130	com/parse/PushConnection:server	Ljava/lang/String;
    //   273: aload_0
    //   274: iload_2
    //   275: putfield 132	com/parse/PushConnection:port	I
    //   278: aload 7
    //   280: monitorexit
    //   281: return
    //   282: astore_1
    //   283: goto -82 -> 201
    //   286: astore_1
    //   287: goto -127 -> 160
    // Local variable table:
    //   start	length	slot	name	signature
    //   0	290	0	this	PushConnection
    //   0	290	1	paramString	String
    //   0	290	2	paramInt	int
    //   0	290	3	paramBoolean	boolean
    //   4	63	4	bool	boolean
    //   1	243	5	localSocket	Socket
    //   14	250	6	localObject1	Object
    // Exception table:
    //   from	to	target	type
    //   121	159	159	java/net/UnknownHostException
    //   19	52	194	finally
    //   54	63	194	finally
    //   195	198	194	finally
    //   71	121	200	java/io/IOException
    //   239	251	252	finally
    //   253	256	252	finally
    //   258	281	252	finally
    //   121	159	282	java/io/IOException
    //   71	121	286	java/net/UnknownHostException
  }
  
  /* Error */
  public String readLine()
    throws java.io.IOException
  {
    // Byte code:
    //   0: aload_0
    //   1: getfield 65	com/parse/PushConnection:socketLock	Ljava/lang/Object;
    //   4: astore_2
    //   5: aload_2
    //   6: monitorenter
    //   7: aload_0
    //   8: getfield 84	com/parse/PushConnection:socket	Ljava/net/Socket;
    //   11: ifnull +13 -> 24
    //   14: aload_0
    //   15: getfield 84	com/parse/PushConnection:socket	Ljava/net/Socket;
    //   18: invokevirtual 128	java/net/Socket:isClosed	()Z
    //   21: ifeq +7 -> 28
    //   24: aload_2
    //   25: monitorexit
    //   26: aconst_null
    //   27: areturn
    //   28: aload_0
    //   29: getfield 54	com/parse/PushConnection:reader	Ljava/io/BufferedReader;
    //   32: ifnonnull +35 -> 67
    //   35: ldc 12
    //   37: ldc -78
    //   39: invokestatic 92	com/parse/Parse:logV	(Ljava/lang/String;Ljava/lang/String;)V
    //   42: aload_0
    //   43: new 108	java/io/BufferedReader
    //   46: dup
    //   47: new 180	java/io/InputStreamReader
    //   50: dup
    //   51: aload_0
    //   52: getfield 84	com/parse/PushConnection:socket	Ljava/net/Socket;
    //   55: invokevirtual 184	java/net/Socket:getInputStream	()Ljava/io/InputStream;
    //   58: invokespecial 187	java/io/InputStreamReader:<init>	(Ljava/io/InputStream;)V
    //   61: invokespecial 190	java/io/BufferedReader:<init>	(Ljava/io/Reader;)V
    //   64: putfield 54	com/parse/PushConnection:reader	Ljava/io/BufferedReader;
    //   67: aload_0
    //   68: getfield 54	com/parse/PushConnection:reader	Ljava/io/BufferedReader;
    //   71: astore_1
    //   72: getstatic 40	com/parse/PushConnection:$assertionsDisabled	Z
    //   75: ifne +23 -> 98
    //   78: aload_0
    //   79: getfield 58	com/parse/PushConnection:readerThread	Ljava/lang/Thread;
    //   82: ifnull +16 -> 98
    //   85: new 167	java/lang/AssertionError
    //   88: dup
    //   89: invokespecial 168	java/lang/AssertionError:<init>	()V
    //   92: athrow
    //   93: astore_1
    //   94: aload_2
    //   95: monitorexit
    //   96: aload_1
    //   97: athrow
    //   98: aload_0
    //   99: invokestatic 194	java/lang/Thread:currentThread	()Ljava/lang/Thread;
    //   102: putfield 58	com/parse/PushConnection:readerThread	Ljava/lang/Thread;
    //   105: aload_2
    //   106: monitorexit
    //   107: aload_1
    //   108: monitorenter
    //   109: aload_1
    //   110: invokevirtual 196	java/io/BufferedReader:readLine	()Ljava/lang/String;
    //   113: astore_3
    //   114: aload_0
    //   115: getfield 65	com/parse/PushConnection:socketLock	Ljava/lang/Object;
    //   118: astore_2
    //   119: aload_2
    //   120: monitorenter
    //   121: aload_0
    //   122: aconst_null
    //   123: putfield 58	com/parse/PushConnection:readerThread	Ljava/lang/Thread;
    //   126: aload_2
    //   127: monitorexit
    //   128: aload_1
    //   129: monitorexit
    //   130: aload_3
    //   131: areturn
    //   132: astore_2
    //   133: aload_1
    //   134: monitorexit
    //   135: aload_2
    //   136: athrow
    //   137: astore_3
    //   138: aload_2
    //   139: monitorexit
    //   140: aload_3
    //   141: athrow
    //   142: astore_2
    //   143: ldc 12
    //   145: new 134	java/lang/StringBuilder
    //   148: dup
    //   149: ldc -58
    //   151: invokespecial 139	java/lang/StringBuilder:<init>	(Ljava/lang/String;)V
    //   154: aload_2
    //   155: invokevirtual 175	java/io/IOException:toString	()Ljava/lang/String;
    //   158: invokevirtual 143	java/lang/StringBuilder:append	(Ljava/lang/String;)Ljava/lang/StringBuilder;
    //   161: invokevirtual 152	java/lang/StringBuilder:toString	()Ljava/lang/String;
    //   164: invokestatic 92	com/parse/Parse:logV	(Ljava/lang/String;Ljava/lang/String;)V
    //   167: aload_0
    //   168: getfield 65	com/parse/PushConnection:socketLock	Ljava/lang/Object;
    //   171: astore_2
    //   172: aload_2
    //   173: monitorenter
    //   174: aload_0
    //   175: aconst_null
    //   176: putfield 58	com/parse/PushConnection:readerThread	Ljava/lang/Thread;
    //   179: aload_2
    //   180: monitorexit
    //   181: aload_1
    //   182: monitorexit
    //   183: aconst_null
    //   184: areturn
    //   185: astore_3
    //   186: aload_2
    //   187: monitorexit
    //   188: aload_3
    //   189: athrow
    //   190: astore_3
    //   191: aload_0
    //   192: getfield 65	com/parse/PushConnection:socketLock	Ljava/lang/Object;
    //   195: astore_2
    //   196: aload_2
    //   197: monitorenter
    //   198: aload_0
    //   199: aconst_null
    //   200: putfield 58	com/parse/PushConnection:readerThread	Ljava/lang/Thread;
    //   203: aload_2
    //   204: monitorexit
    //   205: aload_3
    //   206: athrow
    //   207: astore_3
    //   208: aload_2
    //   209: monitorexit
    //   210: aload_3
    //   211: athrow
    // Local variable table:
    //   start	length	slot	name	signature
    //   0	212	0	this	PushConnection
    //   71	1	1	localBufferedReader	BufferedReader
    //   93	89	1	localObject1	Object
    //   132	7	2	localObject3	Object
    //   142	13	2	localIOException	java.io.IOException
    //   113	18	3	str	String
    //   137	4	3	localObject5	Object
    //   185	4	3	localObject6	Object
    //   190	16	3	localObject7	Object
    //   207	4	3	localObject8	Object
    // Exception table:
    //   from	to	target	type
    //   7	24	93	finally
    //   24	26	93	finally
    //   28	67	93	finally
    //   67	93	93	finally
    //   94	96	93	finally
    //   98	107	93	finally
    //   114	121	132	finally
    //   128	130	132	finally
    //   133	135	132	finally
    //   140	142	132	finally
    //   167	174	132	finally
    //   181	183	132	finally
    //   188	190	132	finally
    //   191	198	132	finally
    //   205	207	132	finally
    //   210	212	132	finally
    //   121	128	137	finally
    //   138	140	137	finally
    //   109	114	142	java/io/IOException
    //   174	181	185	finally
    //   186	188	185	finally
    //   109	114	190	finally
    //   143	167	190	finally
    //   198	205	207	finally
    //   208	210	207	finally
  }
  
  /* Error */
  public boolean trySend(String paramString)
  {
    // Byte code:
    //   0: aload_0
    //   1: getfield 65	com/parse/PushConnection:socketLock	Ljava/lang/Object;
    //   4: astore_2
    //   5: aload_2
    //   6: monitorenter
    //   7: aload_0
    //   8: getfield 84	com/parse/PushConnection:socket	Ljava/net/Socket;
    //   11: ifnull +13 -> 24
    //   14: aload_0
    //   15: getfield 84	com/parse/PushConnection:socket	Ljava/net/Socket;
    //   18: invokevirtual 128	java/net/Socket:isClosed	()Z
    //   21: ifeq +7 -> 28
    //   24: aload_2
    //   25: monitorexit
    //   26: iconst_0
    //   27: ireturn
    //   28: aload_0
    //   29: getfield 56	com/parse/PushConnection:writer	Ljava/io/OutputStreamWriter;
    //   32: astore_3
    //   33: aload_3
    //   34: ifnonnull +23 -> 57
    //   37: aload_0
    //   38: new 112	java/io/OutputStreamWriter
    //   41: dup
    //   42: aload_0
    //   43: getfield 84	com/parse/PushConnection:socket	Ljava/net/Socket;
    //   46: invokevirtual 207	java/net/Socket:getOutputStream	()Ljava/io/OutputStream;
    //   49: ldc -47
    //   51: invokespecial 212	java/io/OutputStreamWriter:<init>	(Ljava/io/OutputStream;Ljava/lang/String;)V
    //   54: putfield 56	com/parse/PushConnection:writer	Ljava/io/OutputStreamWriter;
    //   57: aload_0
    //   58: getfield 56	com/parse/PushConnection:writer	Ljava/io/OutputStreamWriter;
    //   61: astore_3
    //   62: aload_2
    //   63: monitorexit
    //   64: aload_3
    //   65: monitorenter
    //   66: ldc 12
    //   68: new 134	java/lang/StringBuilder
    //   71: dup
    //   72: ldc -42
    //   74: invokespecial 139	java/lang/StringBuilder:<init>	(Ljava/lang/String;)V
    //   77: aload_1
    //   78: invokevirtual 143	java/lang/StringBuilder:append	(Ljava/lang/String;)Ljava/lang/StringBuilder;
    //   81: invokevirtual 152	java/lang/StringBuilder:toString	()Ljava/lang/String;
    //   84: invokestatic 92	com/parse/Parse:logV	(Ljava/lang/String;Ljava/lang/String;)V
    //   87: aload_3
    //   88: new 134	java/lang/StringBuilder
    //   91: dup
    //   92: aload_1
    //   93: invokestatic 220	java/lang/String:valueOf	(Ljava/lang/Object;)Ljava/lang/String;
    //   96: invokespecial 139	java/lang/StringBuilder:<init>	(Ljava/lang/String;)V
    //   99: ldc -34
    //   101: invokevirtual 143	java/lang/StringBuilder:append	(Ljava/lang/String;)Ljava/lang/StringBuilder;
    //   104: invokevirtual 152	java/lang/StringBuilder:toString	()Ljava/lang/String;
    //   107: invokevirtual 225	java/io/OutputStreamWriter:write	(Ljava/lang/String;)V
    //   110: aload_3
    //   111: invokevirtual 228	java/io/OutputStreamWriter:flush	()V
    //   114: aload_3
    //   115: monitorexit
    //   116: iconst_1
    //   117: ireturn
    //   118: astore_1
    //   119: ldc 12
    //   121: ldc -26
    //   123: aload_1
    //   124: invokestatic 233	com/parse/Parse:logE	(Ljava/lang/String;Ljava/lang/String;Ljava/lang/Throwable;)V
    //   127: aload_2
    //   128: monitorexit
    //   129: iconst_0
    //   130: ireturn
    //   131: astore_1
    //   132: aload_2
    //   133: monitorexit
    //   134: aload_1
    //   135: athrow
    //   136: astore_1
    //   137: ldc 12
    //   139: ldc -21
    //   141: aload_1
    //   142: invokestatic 233	com/parse/Parse:logE	(Ljava/lang/String;Ljava/lang/String;Ljava/lang/Throwable;)V
    //   145: aload_3
    //   146: monitorexit
    //   147: iconst_0
    //   148: ireturn
    //   149: astore_1
    //   150: aload_3
    //   151: monitorexit
    //   152: aload_1
    //   153: athrow
    //   154: astore_1
    //   155: ldc 12
    //   157: ldc -19
    //   159: aload_1
    //   160: invokestatic 233	com/parse/Parse:logE	(Ljava/lang/String;Ljava/lang/String;Ljava/lang/Throwable;)V
    //   163: aload_3
    //   164: monitorexit
    //   165: iconst_0
    //   166: ireturn
    // Local variable table:
    //   start	length	slot	name	signature
    //   0	167	0	this	PushConnection
    //   0	167	1	paramString	String
    //   4	129	2	localObject	Object
    //   32	132	3	localOutputStreamWriter	OutputStreamWriter
    // Exception table:
    //   from	to	target	type
    //   37	57	118	java/io/IOException
    //   7	24	131	finally
    //   24	26	131	finally
    //   28	33	131	finally
    //   37	57	131	finally
    //   57	64	131	finally
    //   119	129	131	finally
    //   132	134	131	finally
    //   66	114	136	java/io/UnsupportedEncodingException
    //   66	114	149	finally
    //   114	116	149	finally
    //   137	147	149	finally
    //   150	152	149	finally
    //   155	165	149	finally
    //   66	114	154	java/io/IOException
  }
}


/* Location:              /Users/amaurremi/uw/stringoid/static-dynamic-comparison/apps/randomchat/com.pioong-93-dex2jar.jar!/com/parse/PushConnection.class
 * Java compiler version: 6 (50.0)
 * JD-Core Version:       0.7.1
 */