package com.appbrain.e;

import com.appbrain.b.d;
import com.appbrain.b.h;
import com.appbrain.b.k;
import com.appbrain.b.w;

public final class aa
  extends k
  implements ac
{
  public static w a = new ad();
  private static final aa b;
  private long A;
  private int B;
  private int C;
  private int D;
  private int E;
  private int F;
  private int G;
  private int H;
  private Object I;
  private int J;
  private Object K;
  private d L;
  private d M;
  private int N;
  private int O;
  private long P;
  private byte Q = -1;
  private int R = -1;
  private int c;
  private int d;
  private long e;
  private long f;
  private Object g;
  private Object h;
  private Object i;
  private Object j;
  private Object k;
  private Object l;
  private Object m;
  private int n;
  private int o;
  private Object p;
  private Object q;
  private Object r;
  private Object s;
  private Object t;
  private Object u;
  private Object v;
  private int w;
  private Object x;
  private int y;
  private int z;
  
  static
  {
    aa localaa = new aa((byte)0);
    b = localaa;
    localaa.aG();
  }
  
  private aa()
  {
    super((byte)0);
  }
  
  private aa(byte paramByte) {}
  
  /* Error */
  private aa(com.appbrain.b.g paramg)
  {
    // Byte code:
    //   0: aload_0
    //   1: invokespecial 78	com/appbrain/b/k:<init>	()V
    //   4: aload_0
    //   5: iconst_m1
    //   6: putfield 75	com/appbrain/e/aa:Q	B
    //   9: aload_0
    //   10: iconst_m1
    //   11: putfield 77	com/appbrain/e/aa:R	I
    //   14: aload_0
    //   15: invokespecial 71	com/appbrain/e/aa:aG	()V
    //   18: iconst_0
    //   19: istore_2
    //   20: iload_2
    //   21: ifne +1209 -> 1230
    //   24: aload_1
    //   25: invokevirtual 90	com/appbrain/b/g:a	()I
    //   28: istore_3
    //   29: iload_3
    //   30: lookupswitch	default:+1201->1231, 0:+1204->1234, 8:+335->365, 16:+366->396, 26:+404->434, 34:+425->455, 42:+447->477, 50:+469->499, 58:+491->521, 66:+513->543, 74:+536->566, 80:+559->589, 88:+582->612, 106:+605->635, 114:+628->658, 122:+651->681, 130:+674->704, 162:+697->727, 170:+719->749, 178:+741->771, 184:+763->793, 202:+785->815, 208:+807->837, 216:+829->859, 224:+851->881, 232:+873->903, 240:+895->925, 248:+917->947, 256:+939->969, 264:+961->991, 272:+983->1013, 280:+1005->1035, 290:+1027->1057, 296:+1049->1079, 306:+1071->1101, 314:+1092->1122, 322:+1113->1143, 328:+1134->1164, 336:+1156->1186, 344:+1178->1208
    //   352: aload_1
    //   353: iload_3
    //   354: invokevirtual 93	com/appbrain/b/g:b	(I)Z
    //   357: ifne -337 -> 20
    //   360: iconst_1
    //   361: istore_2
    //   362: goto -342 -> 20
    //   365: aload_0
    //   366: aload_0
    //   367: getfield 95	com/appbrain/e/aa:c	I
    //   370: iconst_1
    //   371: ior
    //   372: putfield 95	com/appbrain/e/aa:c	I
    //   375: aload_0
    //   376: aload_1
    //   377: invokevirtual 98	com/appbrain/b/g:b	()J
    //   380: putfield 100	com/appbrain/e/aa:e	J
    //   383: goto -363 -> 20
    //   386: astore_1
    //   387: aload_1
    //   388: aload_0
    //   389: invokevirtual 103	com/appbrain/b/o:a	(Lcom/appbrain/b/t;)Lcom/appbrain/b/o;
    //   392: athrow
    //   393: astore_1
    //   394: aload_1
    //   395: athrow
    //   396: aload_0
    //   397: aload_0
    //   398: getfield 95	com/appbrain/e/aa:c	I
    //   401: iconst_2
    //   402: ior
    //   403: putfield 95	com/appbrain/e/aa:c	I
    //   406: aload_0
    //   407: aload_1
    //   408: invokevirtual 98	com/appbrain/b/g:b	()J
    //   411: putfield 105	com/appbrain/e/aa:f	J
    //   414: goto -394 -> 20
    //   417: astore_1
    //   418: new 83	com/appbrain/b/o
    //   421: dup
    //   422: aload_1
    //   423: invokevirtual 109	java/io/IOException:getMessage	()Ljava/lang/String;
    //   426: invokespecial 112	com/appbrain/b/o:<init>	(Ljava/lang/String;)V
    //   429: aload_0
    //   430: invokevirtual 103	com/appbrain/b/o:a	(Lcom/appbrain/b/t;)Lcom/appbrain/b/o;
    //   433: athrow
    //   434: aload_0
    //   435: aload_0
    //   436: getfield 95	com/appbrain/e/aa:c	I
    //   439: iconst_4
    //   440: ior
    //   441: putfield 95	com/appbrain/e/aa:c	I
    //   444: aload_0
    //   445: aload_1
    //   446: invokevirtual 115	com/appbrain/b/g:e	()Lcom/appbrain/b/d;
    //   449: putfield 117	com/appbrain/e/aa:g	Ljava/lang/Object;
    //   452: goto -432 -> 20
    //   455: aload_0
    //   456: aload_0
    //   457: getfield 95	com/appbrain/e/aa:c	I
    //   460: bipush 8
    //   462: ior
    //   463: putfield 95	com/appbrain/e/aa:c	I
    //   466: aload_0
    //   467: aload_1
    //   468: invokevirtual 115	com/appbrain/b/g:e	()Lcom/appbrain/b/d;
    //   471: putfield 119	com/appbrain/e/aa:h	Ljava/lang/Object;
    //   474: goto -454 -> 20
    //   477: aload_0
    //   478: aload_0
    //   479: getfield 95	com/appbrain/e/aa:c	I
    //   482: bipush 16
    //   484: ior
    //   485: putfield 95	com/appbrain/e/aa:c	I
    //   488: aload_0
    //   489: aload_1
    //   490: invokevirtual 115	com/appbrain/b/g:e	()Lcom/appbrain/b/d;
    //   493: putfield 121	com/appbrain/e/aa:i	Ljava/lang/Object;
    //   496: goto -476 -> 20
    //   499: aload_0
    //   500: aload_0
    //   501: getfield 95	com/appbrain/e/aa:c	I
    //   504: bipush 32
    //   506: ior
    //   507: putfield 95	com/appbrain/e/aa:c	I
    //   510: aload_0
    //   511: aload_1
    //   512: invokevirtual 115	com/appbrain/b/g:e	()Lcom/appbrain/b/d;
    //   515: putfield 123	com/appbrain/e/aa:j	Ljava/lang/Object;
    //   518: goto -498 -> 20
    //   521: aload_0
    //   522: aload_0
    //   523: getfield 95	com/appbrain/e/aa:c	I
    //   526: bipush 64
    //   528: ior
    //   529: putfield 95	com/appbrain/e/aa:c	I
    //   532: aload_0
    //   533: aload_1
    //   534: invokevirtual 115	com/appbrain/b/g:e	()Lcom/appbrain/b/d;
    //   537: putfield 125	com/appbrain/e/aa:k	Ljava/lang/Object;
    //   540: goto -520 -> 20
    //   543: aload_0
    //   544: aload_0
    //   545: getfield 95	com/appbrain/e/aa:c	I
    //   548: sipush 128
    //   551: ior
    //   552: putfield 95	com/appbrain/e/aa:c	I
    //   555: aload_0
    //   556: aload_1
    //   557: invokevirtual 115	com/appbrain/b/g:e	()Lcom/appbrain/b/d;
    //   560: putfield 127	com/appbrain/e/aa:l	Ljava/lang/Object;
    //   563: goto -543 -> 20
    //   566: aload_0
    //   567: aload_0
    //   568: getfield 95	com/appbrain/e/aa:c	I
    //   571: sipush 256
    //   574: ior
    //   575: putfield 95	com/appbrain/e/aa:c	I
    //   578: aload_0
    //   579: aload_1
    //   580: invokevirtual 115	com/appbrain/b/g:e	()Lcom/appbrain/b/d;
    //   583: putfield 129	com/appbrain/e/aa:m	Ljava/lang/Object;
    //   586: goto -566 -> 20
    //   589: aload_0
    //   590: aload_0
    //   591: getfield 95	com/appbrain/e/aa:c	I
    //   594: sipush 512
    //   597: ior
    //   598: putfield 95	com/appbrain/e/aa:c	I
    //   601: aload_0
    //   602: aload_1
    //   603: invokevirtual 131	com/appbrain/b/g:c	()I
    //   606: putfield 133	com/appbrain/e/aa:n	I
    //   609: goto -589 -> 20
    //   612: aload_0
    //   613: aload_0
    //   614: getfield 95	com/appbrain/e/aa:c	I
    //   617: sipush 1024
    //   620: ior
    //   621: putfield 95	com/appbrain/e/aa:c	I
    //   624: aload_0
    //   625: aload_1
    //   626: invokevirtual 131	com/appbrain/b/g:c	()I
    //   629: putfield 135	com/appbrain/e/aa:o	I
    //   632: goto -612 -> 20
    //   635: aload_0
    //   636: aload_0
    //   637: getfield 95	com/appbrain/e/aa:c	I
    //   640: sipush 2048
    //   643: ior
    //   644: putfield 95	com/appbrain/e/aa:c	I
    //   647: aload_0
    //   648: aload_1
    //   649: invokevirtual 115	com/appbrain/b/g:e	()Lcom/appbrain/b/d;
    //   652: putfield 137	com/appbrain/e/aa:p	Ljava/lang/Object;
    //   655: goto -635 -> 20
    //   658: aload_0
    //   659: aload_0
    //   660: getfield 95	com/appbrain/e/aa:c	I
    //   663: sipush 4096
    //   666: ior
    //   667: putfield 95	com/appbrain/e/aa:c	I
    //   670: aload_0
    //   671: aload_1
    //   672: invokevirtual 115	com/appbrain/b/g:e	()Lcom/appbrain/b/d;
    //   675: putfield 139	com/appbrain/e/aa:q	Ljava/lang/Object;
    //   678: goto -658 -> 20
    //   681: aload_0
    //   682: aload_0
    //   683: getfield 95	com/appbrain/e/aa:c	I
    //   686: sipush 8192
    //   689: ior
    //   690: putfield 95	com/appbrain/e/aa:c	I
    //   693: aload_0
    //   694: aload_1
    //   695: invokevirtual 115	com/appbrain/b/g:e	()Lcom/appbrain/b/d;
    //   698: putfield 141	com/appbrain/e/aa:r	Ljava/lang/Object;
    //   701: goto -681 -> 20
    //   704: aload_0
    //   705: aload_0
    //   706: getfield 95	com/appbrain/e/aa:c	I
    //   709: sipush 16384
    //   712: ior
    //   713: putfield 95	com/appbrain/e/aa:c	I
    //   716: aload_0
    //   717: aload_1
    //   718: invokevirtual 115	com/appbrain/b/g:e	()Lcom/appbrain/b/d;
    //   721: putfield 143	com/appbrain/e/aa:s	Ljava/lang/Object;
    //   724: goto -704 -> 20
    //   727: aload_0
    //   728: aload_0
    //   729: getfield 95	com/appbrain/e/aa:c	I
    //   732: ldc -112
    //   734: ior
    //   735: putfield 95	com/appbrain/e/aa:c	I
    //   738: aload_0
    //   739: aload_1
    //   740: invokevirtual 115	com/appbrain/b/g:e	()Lcom/appbrain/b/d;
    //   743: putfield 146	com/appbrain/e/aa:t	Ljava/lang/Object;
    //   746: goto -726 -> 20
    //   749: aload_0
    //   750: aload_0
    //   751: getfield 95	com/appbrain/e/aa:c	I
    //   754: ldc -109
    //   756: ior
    //   757: putfield 95	com/appbrain/e/aa:c	I
    //   760: aload_0
    //   761: aload_1
    //   762: invokevirtual 115	com/appbrain/b/g:e	()Lcom/appbrain/b/d;
    //   765: putfield 149	com/appbrain/e/aa:u	Ljava/lang/Object;
    //   768: goto -748 -> 20
    //   771: aload_0
    //   772: aload_0
    //   773: getfield 95	com/appbrain/e/aa:c	I
    //   776: ldc -106
    //   778: ior
    //   779: putfield 95	com/appbrain/e/aa:c	I
    //   782: aload_0
    //   783: aload_1
    //   784: invokevirtual 115	com/appbrain/b/g:e	()Lcom/appbrain/b/d;
    //   787: putfield 152	com/appbrain/e/aa:v	Ljava/lang/Object;
    //   790: goto -770 -> 20
    //   793: aload_0
    //   794: aload_0
    //   795: getfield 95	com/appbrain/e/aa:c	I
    //   798: ldc -103
    //   800: ior
    //   801: putfield 95	com/appbrain/e/aa:c	I
    //   804: aload_0
    //   805: aload_1
    //   806: invokevirtual 131	com/appbrain/b/g:c	()I
    //   809: putfield 155	com/appbrain/e/aa:w	I
    //   812: goto -792 -> 20
    //   815: aload_0
    //   816: aload_0
    //   817: getfield 95	com/appbrain/e/aa:c	I
    //   820: ldc -100
    //   822: ior
    //   823: putfield 95	com/appbrain/e/aa:c	I
    //   826: aload_0
    //   827: aload_1
    //   828: invokevirtual 115	com/appbrain/b/g:e	()Lcom/appbrain/b/d;
    //   831: putfield 158	com/appbrain/e/aa:x	Ljava/lang/Object;
    //   834: goto -814 -> 20
    //   837: aload_0
    //   838: aload_0
    //   839: getfield 95	com/appbrain/e/aa:c	I
    //   842: ldc -97
    //   844: ior
    //   845: putfield 95	com/appbrain/e/aa:c	I
    //   848: aload_0
    //   849: aload_1
    //   850: invokevirtual 131	com/appbrain/b/g:c	()I
    //   853: putfield 161	com/appbrain/e/aa:y	I
    //   856: goto -836 -> 20
    //   859: aload_0
    //   860: aload_0
    //   861: getfield 95	com/appbrain/e/aa:c	I
    //   864: ldc -94
    //   866: ior
    //   867: putfield 95	com/appbrain/e/aa:c	I
    //   870: aload_0
    //   871: aload_1
    //   872: invokevirtual 131	com/appbrain/b/g:c	()I
    //   875: putfield 164	com/appbrain/e/aa:z	I
    //   878: goto -858 -> 20
    //   881: aload_0
    //   882: aload_0
    //   883: getfield 95	com/appbrain/e/aa:c	I
    //   886: ldc -91
    //   888: ior
    //   889: putfield 95	com/appbrain/e/aa:c	I
    //   892: aload_0
    //   893: aload_1
    //   894: invokevirtual 98	com/appbrain/b/g:b	()J
    //   897: putfield 167	com/appbrain/e/aa:A	J
    //   900: goto -880 -> 20
    //   903: aload_0
    //   904: aload_0
    //   905: getfield 95	com/appbrain/e/aa:c	I
    //   908: ldc -88
    //   910: ior
    //   911: putfield 95	com/appbrain/e/aa:c	I
    //   914: aload_0
    //   915: aload_1
    //   916: invokevirtual 131	com/appbrain/b/g:c	()I
    //   919: putfield 170	com/appbrain/e/aa:B	I
    //   922: goto -902 -> 20
    //   925: aload_0
    //   926: aload_0
    //   927: getfield 95	com/appbrain/e/aa:c	I
    //   930: ldc -85
    //   932: ior
    //   933: putfield 95	com/appbrain/e/aa:c	I
    //   936: aload_0
    //   937: aload_1
    //   938: invokevirtual 131	com/appbrain/b/g:c	()I
    //   941: putfield 173	com/appbrain/e/aa:C	I
    //   944: goto -924 -> 20
    //   947: aload_0
    //   948: aload_0
    //   949: getfield 95	com/appbrain/e/aa:c	I
    //   952: ldc -82
    //   954: ior
    //   955: putfield 95	com/appbrain/e/aa:c	I
    //   958: aload_0
    //   959: aload_1
    //   960: invokevirtual 131	com/appbrain/b/g:c	()I
    //   963: putfield 176	com/appbrain/e/aa:D	I
    //   966: goto -946 -> 20
    //   969: aload_0
    //   970: aload_0
    //   971: getfield 95	com/appbrain/e/aa:c	I
    //   974: ldc -79
    //   976: ior
    //   977: putfield 95	com/appbrain/e/aa:c	I
    //   980: aload_0
    //   981: aload_1
    //   982: invokevirtual 131	com/appbrain/b/g:c	()I
    //   985: putfield 179	com/appbrain/e/aa:E	I
    //   988: goto -968 -> 20
    //   991: aload_0
    //   992: aload_0
    //   993: getfield 95	com/appbrain/e/aa:c	I
    //   996: ldc -76
    //   998: ior
    //   999: putfield 95	com/appbrain/e/aa:c	I
    //   1002: aload_0
    //   1003: aload_1
    //   1004: invokevirtual 131	com/appbrain/b/g:c	()I
    //   1007: putfield 182	com/appbrain/e/aa:F	I
    //   1010: goto -990 -> 20
    //   1013: aload_0
    //   1014: aload_0
    //   1015: getfield 95	com/appbrain/e/aa:c	I
    //   1018: ldc -73
    //   1020: ior
    //   1021: putfield 95	com/appbrain/e/aa:c	I
    //   1024: aload_0
    //   1025: aload_1
    //   1026: invokevirtual 131	com/appbrain/b/g:c	()I
    //   1029: putfield 185	com/appbrain/e/aa:G	I
    //   1032: goto -1012 -> 20
    //   1035: aload_0
    //   1036: aload_0
    //   1037: getfield 95	com/appbrain/e/aa:c	I
    //   1040: ldc -70
    //   1042: ior
    //   1043: putfield 95	com/appbrain/e/aa:c	I
    //   1046: aload_0
    //   1047: aload_1
    //   1048: invokevirtual 131	com/appbrain/b/g:c	()I
    //   1051: putfield 188	com/appbrain/e/aa:H	I
    //   1054: goto -1034 -> 20
    //   1057: aload_0
    //   1058: aload_0
    //   1059: getfield 95	com/appbrain/e/aa:c	I
    //   1062: ldc -67
    //   1064: ior
    //   1065: putfield 95	com/appbrain/e/aa:c	I
    //   1068: aload_0
    //   1069: aload_1
    //   1070: invokevirtual 115	com/appbrain/b/g:e	()Lcom/appbrain/b/d;
    //   1073: putfield 191	com/appbrain/e/aa:I	Ljava/lang/Object;
    //   1076: goto -1056 -> 20
    //   1079: aload_0
    //   1080: aload_0
    //   1081: getfield 95	com/appbrain/e/aa:c	I
    //   1084: ldc -64
    //   1086: ior
    //   1087: putfield 95	com/appbrain/e/aa:c	I
    //   1090: aload_0
    //   1091: aload_1
    //   1092: invokevirtual 131	com/appbrain/b/g:c	()I
    //   1095: putfield 194	com/appbrain/e/aa:J	I
    //   1098: goto -1078 -> 20
    //   1101: aload_0
    //   1102: aload_0
    //   1103: getfield 196	com/appbrain/e/aa:d	I
    //   1106: iconst_1
    //   1107: ior
    //   1108: putfield 196	com/appbrain/e/aa:d	I
    //   1111: aload_0
    //   1112: aload_1
    //   1113: invokevirtual 115	com/appbrain/b/g:e	()Lcom/appbrain/b/d;
    //   1116: putfield 198	com/appbrain/e/aa:K	Ljava/lang/Object;
    //   1119: goto -1099 -> 20
    //   1122: aload_0
    //   1123: aload_0
    //   1124: getfield 196	com/appbrain/e/aa:d	I
    //   1127: iconst_2
    //   1128: ior
    //   1129: putfield 196	com/appbrain/e/aa:d	I
    //   1132: aload_0
    //   1133: aload_1
    //   1134: invokevirtual 115	com/appbrain/b/g:e	()Lcom/appbrain/b/d;
    //   1137: putfield 200	com/appbrain/e/aa:L	Lcom/appbrain/b/d;
    //   1140: goto -1120 -> 20
    //   1143: aload_0
    //   1144: aload_0
    //   1145: getfield 196	com/appbrain/e/aa:d	I
    //   1148: iconst_4
    //   1149: ior
    //   1150: putfield 196	com/appbrain/e/aa:d	I
    //   1153: aload_0
    //   1154: aload_1
    //   1155: invokevirtual 115	com/appbrain/b/g:e	()Lcom/appbrain/b/d;
    //   1158: putfield 202	com/appbrain/e/aa:M	Lcom/appbrain/b/d;
    //   1161: goto -1141 -> 20
    //   1164: aload_0
    //   1165: aload_0
    //   1166: getfield 196	com/appbrain/e/aa:d	I
    //   1169: bipush 8
    //   1171: ior
    //   1172: putfield 196	com/appbrain/e/aa:d	I
    //   1175: aload_0
    //   1176: aload_1
    //   1177: invokevirtual 131	com/appbrain/b/g:c	()I
    //   1180: putfield 204	com/appbrain/e/aa:N	I
    //   1183: goto -1163 -> 20
    //   1186: aload_0
    //   1187: aload_0
    //   1188: getfield 196	com/appbrain/e/aa:d	I
    //   1191: bipush 16
    //   1193: ior
    //   1194: putfield 196	com/appbrain/e/aa:d	I
    //   1197: aload_0
    //   1198: aload_1
    //   1199: invokevirtual 131	com/appbrain/b/g:c	()I
    //   1202: putfield 206	com/appbrain/e/aa:O	I
    //   1205: goto -1185 -> 20
    //   1208: aload_0
    //   1209: aload_0
    //   1210: getfield 196	com/appbrain/e/aa:d	I
    //   1213: bipush 32
    //   1215: ior
    //   1216: putfield 196	com/appbrain/e/aa:d	I
    //   1219: aload_0
    //   1220: aload_1
    //   1221: invokevirtual 98	com/appbrain/b/g:b	()J
    //   1224: putfield 208	com/appbrain/e/aa:P	J
    //   1227: goto -1207 -> 20
    //   1230: return
    //   1231: goto -879 -> 352
    //   1234: iconst_1
    //   1235: istore_2
    //   1236: goto -1216 -> 20
    // Local variable table:
    //   start	length	slot	name	signature
    //   0	1239	0	this	aa
    //   0	1239	1	paramg	com.appbrain.b.g
    //   19	1217	2	i1	int
    //   28	326	3	i2	int
    // Exception table:
    //   from	to	target	type
    //   24	29	386	com/appbrain/b/o
    //   352	360	386	com/appbrain/b/o
    //   365	383	386	com/appbrain/b/o
    //   396	414	386	com/appbrain/b/o
    //   434	452	386	com/appbrain/b/o
    //   455	474	386	com/appbrain/b/o
    //   477	496	386	com/appbrain/b/o
    //   499	518	386	com/appbrain/b/o
    //   521	540	386	com/appbrain/b/o
    //   543	563	386	com/appbrain/b/o
    //   566	586	386	com/appbrain/b/o
    //   589	609	386	com/appbrain/b/o
    //   612	632	386	com/appbrain/b/o
    //   635	655	386	com/appbrain/b/o
    //   658	678	386	com/appbrain/b/o
    //   681	701	386	com/appbrain/b/o
    //   704	724	386	com/appbrain/b/o
    //   727	746	386	com/appbrain/b/o
    //   749	768	386	com/appbrain/b/o
    //   771	790	386	com/appbrain/b/o
    //   793	812	386	com/appbrain/b/o
    //   815	834	386	com/appbrain/b/o
    //   837	856	386	com/appbrain/b/o
    //   859	878	386	com/appbrain/b/o
    //   881	900	386	com/appbrain/b/o
    //   903	922	386	com/appbrain/b/o
    //   925	944	386	com/appbrain/b/o
    //   947	966	386	com/appbrain/b/o
    //   969	988	386	com/appbrain/b/o
    //   991	1010	386	com/appbrain/b/o
    //   1013	1032	386	com/appbrain/b/o
    //   1035	1054	386	com/appbrain/b/o
    //   1057	1076	386	com/appbrain/b/o
    //   1079	1098	386	com/appbrain/b/o
    //   1101	1119	386	com/appbrain/b/o
    //   1122	1140	386	com/appbrain/b/o
    //   1143	1161	386	com/appbrain/b/o
    //   1164	1183	386	com/appbrain/b/o
    //   1186	1205	386	com/appbrain/b/o
    //   1208	1227	386	com/appbrain/b/o
    //   24	29	393	finally
    //   352	360	393	finally
    //   365	383	393	finally
    //   387	393	393	finally
    //   396	414	393	finally
    //   418	434	393	finally
    //   434	452	393	finally
    //   455	474	393	finally
    //   477	496	393	finally
    //   499	518	393	finally
    //   521	540	393	finally
    //   543	563	393	finally
    //   566	586	393	finally
    //   589	609	393	finally
    //   612	632	393	finally
    //   635	655	393	finally
    //   658	678	393	finally
    //   681	701	393	finally
    //   704	724	393	finally
    //   727	746	393	finally
    //   749	768	393	finally
    //   771	790	393	finally
    //   793	812	393	finally
    //   815	834	393	finally
    //   837	856	393	finally
    //   859	878	393	finally
    //   881	900	393	finally
    //   903	922	393	finally
    //   925	944	393	finally
    //   947	966	393	finally
    //   969	988	393	finally
    //   991	1010	393	finally
    //   1013	1032	393	finally
    //   1035	1054	393	finally
    //   1057	1076	393	finally
    //   1079	1098	393	finally
    //   1101	1119	393	finally
    //   1122	1140	393	finally
    //   1143	1161	393	finally
    //   1164	1183	393	finally
    //   1186	1205	393	finally
    //   1208	1227	393	finally
    //   24	29	417	java/io/IOException
    //   352	360	417	java/io/IOException
    //   365	383	417	java/io/IOException
    //   396	414	417	java/io/IOException
    //   434	452	417	java/io/IOException
    //   455	474	417	java/io/IOException
    //   477	496	417	java/io/IOException
    //   499	518	417	java/io/IOException
    //   521	540	417	java/io/IOException
    //   543	563	417	java/io/IOException
    //   566	586	417	java/io/IOException
    //   589	609	417	java/io/IOException
    //   612	632	417	java/io/IOException
    //   635	655	417	java/io/IOException
    //   658	678	417	java/io/IOException
    //   681	701	417	java/io/IOException
    //   704	724	417	java/io/IOException
    //   727	746	417	java/io/IOException
    //   749	768	417	java/io/IOException
    //   771	790	417	java/io/IOException
    //   793	812	417	java/io/IOException
    //   815	834	417	java/io/IOException
    //   837	856	417	java/io/IOException
    //   859	878	417	java/io/IOException
    //   881	900	417	java/io/IOException
    //   903	922	417	java/io/IOException
    //   925	944	417	java/io/IOException
    //   947	966	417	java/io/IOException
    //   969	988	417	java/io/IOException
    //   991	1010	417	java/io/IOException
    //   1013	1032	417	java/io/IOException
    //   1035	1054	417	java/io/IOException
    //   1057	1076	417	java/io/IOException
    //   1079	1098	417	java/io/IOException
    //   1101	1119	417	java/io/IOException
    //   1122	1140	417	java/io/IOException
    //   1143	1161	417	java/io/IOException
    //   1164	1183	417	java/io/IOException
    //   1186	1205	417	java/io/IOException
    //   1208	1227	417	java/io/IOException
  }
  
  public static ab a(aa paramaa)
  {
    return ab.g().a(paramaa);
  }
  
  private d aA()
  {
    Object localObject = this.t;
    if ((localObject instanceof String))
    {
      localObject = d.a((String)localObject);
      this.t = localObject;
      return (d)localObject;
    }
    return (d)localObject;
  }
  
  private d aB()
  {
    Object localObject = this.u;
    if ((localObject instanceof String))
    {
      localObject = d.a((String)localObject);
      this.u = localObject;
      return (d)localObject;
    }
    return (d)localObject;
  }
  
  private d aC()
  {
    Object localObject = this.v;
    if ((localObject instanceof String))
    {
      localObject = d.a((String)localObject);
      this.v = localObject;
      return (d)localObject;
    }
    return (d)localObject;
  }
  
  private d aD()
  {
    Object localObject = this.x;
    if ((localObject instanceof String))
    {
      localObject = d.a((String)localObject);
      this.x = localObject;
      return (d)localObject;
    }
    return (d)localObject;
  }
  
  private d aE()
  {
    Object localObject = this.I;
    if ((localObject instanceof String))
    {
      localObject = d.a((String)localObject);
      this.I = localObject;
      return (d)localObject;
    }
    return (d)localObject;
  }
  
  private d aF()
  {
    Object localObject = this.K;
    if ((localObject instanceof String))
    {
      localObject = d.a((String)localObject);
      this.K = localObject;
      return (d)localObject;
    }
    return (d)localObject;
  }
  
  private void aG()
  {
    this.e = 0L;
    this.f = 0L;
    this.g = "";
    this.h = "";
    this.i = "";
    this.j = "";
    this.k = "";
    this.l = "";
    this.m = "";
    this.n = 0;
    this.o = 0;
    this.p = "";
    this.q = "";
    this.r = "";
    this.s = "";
    this.t = "";
    this.u = "";
    this.v = "";
    this.w = 0;
    this.x = "";
    this.y = 0;
    this.z = 0;
    this.A = 0L;
    this.B = 0;
    this.C = 0;
    this.D = 0;
    this.E = 0;
    this.F = 0;
    this.G = 0;
    this.H = 0;
    this.I = "";
    this.J = 0;
    this.K = "";
    this.L = d.a;
    this.M = d.a;
    this.N = 0;
    this.O = 0;
    this.P = 0L;
  }
  
  public static ab an()
  {
    return ab.g();
  }
  
  private d ap()
  {
    Object localObject = this.g;
    if ((localObject instanceof String))
    {
      localObject = d.a((String)localObject);
      this.g = localObject;
      return (d)localObject;
    }
    return (d)localObject;
  }
  
  private d aq()
  {
    Object localObject = this.h;
    if ((localObject instanceof String))
    {
      localObject = d.a((String)localObject);
      this.h = localObject;
      return (d)localObject;
    }
    return (d)localObject;
  }
  
  private d ar()
  {
    Object localObject = this.i;
    if ((localObject instanceof String))
    {
      localObject = d.a((String)localObject);
      this.i = localObject;
      return (d)localObject;
    }
    return (d)localObject;
  }
  
  private d as()
  {
    Object localObject = this.j;
    if ((localObject instanceof String))
    {
      localObject = d.a((String)localObject);
      this.j = localObject;
      return (d)localObject;
    }
    return (d)localObject;
  }
  
  private d at()
  {
    Object localObject = this.k;
    if ((localObject instanceof String))
    {
      localObject = d.a((String)localObject);
      this.k = localObject;
      return (d)localObject;
    }
    return (d)localObject;
  }
  
  private d au()
  {
    Object localObject = this.l;
    if ((localObject instanceof String))
    {
      localObject = d.a((String)localObject);
      this.l = localObject;
      return (d)localObject;
    }
    return (d)localObject;
  }
  
  private d av()
  {
    Object localObject = this.m;
    if ((localObject instanceof String))
    {
      localObject = d.a((String)localObject);
      this.m = localObject;
      return (d)localObject;
    }
    return (d)localObject;
  }
  
  private d aw()
  {
    Object localObject = this.p;
    if ((localObject instanceof String))
    {
      localObject = d.a((String)localObject);
      this.p = localObject;
      return (d)localObject;
    }
    return (d)localObject;
  }
  
  private d ax()
  {
    Object localObject = this.q;
    if ((localObject instanceof String))
    {
      localObject = d.a((String)localObject);
      this.q = localObject;
      return (d)localObject;
    }
    return (d)localObject;
  }
  
  private d ay()
  {
    Object localObject = this.r;
    if ((localObject instanceof String))
    {
      localObject = d.a((String)localObject);
      this.r = localObject;
      return (d)localObject;
    }
    return (d)localObject;
  }
  
  private d az()
  {
    Object localObject = this.s;
    if ((localObject instanceof String))
    {
      localObject = d.a((String)localObject);
      this.s = localObject;
      return (d)localObject;
    }
    return (d)localObject;
  }
  
  public static aa f()
  {
    return b;
  }
  
  public final boolean A()
  {
    return (this.c & 0x10000) == 65536;
  }
  
  public final boolean B()
  {
    return (this.c & 0x20000) == 131072;
  }
  
  public final boolean C()
  {
    return (this.c & 0x40000) == 262144;
  }
  
  public final int D()
  {
    return this.w;
  }
  
  public final boolean E()
  {
    return (this.c & 0x80000) == 524288;
  }
  
  public final boolean F()
  {
    return (this.c & 0x100000) == 1048576;
  }
  
  public final int G()
  {
    return this.y;
  }
  
  public final boolean H()
  {
    return (this.c & 0x200000) == 2097152;
  }
  
  public final int I()
  {
    return this.z;
  }
  
  public final boolean J()
  {
    return (this.c & 0x400000) == 4194304;
  }
  
  public final long K()
  {
    return this.A;
  }
  
  public final boolean L()
  {
    return (this.c & 0x800000) == 8388608;
  }
  
  public final int M()
  {
    return this.B;
  }
  
  public final boolean N()
  {
    return (this.c & 0x1000000) == 16777216;
  }
  
  public final int O()
  {
    return this.C;
  }
  
  public final boolean P()
  {
    return (this.c & 0x2000000) == 33554432;
  }
  
  public final int Q()
  {
    return this.D;
  }
  
  public final boolean R()
  {
    return (this.c & 0x4000000) == 67108864;
  }
  
  public final int S()
  {
    return this.E;
  }
  
  public final boolean T()
  {
    return (this.c & 0x8000000) == 134217728;
  }
  
  public final int U()
  {
    return this.F;
  }
  
  public final boolean V()
  {
    return (this.c & 0x10000000) == 268435456;
  }
  
  public final int W()
  {
    return this.G;
  }
  
  public final boolean X()
  {
    return (this.c & 0x20000000) == 536870912;
  }
  
  public final int Y()
  {
    return this.H;
  }
  
  public final boolean Z()
  {
    return (this.c & 0x40000000) == 1073741824;
  }
  
  public final void a(h paramh)
  {
    c();
    if ((this.c & 0x1) == 1) {
      paramh.a(1, this.e);
    }
    if ((this.c & 0x2) == 2) {
      paramh.a(2, this.f);
    }
    if ((this.c & 0x4) == 4) {
      paramh.a(3, ap());
    }
    if ((this.c & 0x8) == 8) {
      paramh.a(4, aq());
    }
    if ((this.c & 0x10) == 16) {
      paramh.a(5, ar());
    }
    if ((this.c & 0x20) == 32) {
      paramh.a(6, as());
    }
    if ((this.c & 0x40) == 64) {
      paramh.a(7, at());
    }
    if ((this.c & 0x80) == 128) {
      paramh.a(8, au());
    }
    if ((this.c & 0x100) == 256) {
      paramh.a(9, av());
    }
    if ((this.c & 0x200) == 512) {
      paramh.a(10, this.n);
    }
    if ((this.c & 0x400) == 1024) {
      paramh.a(11, this.o);
    }
    if ((this.c & 0x800) == 2048) {
      paramh.a(13, aw());
    }
    if ((this.c & 0x1000) == 4096) {
      paramh.a(14, ax());
    }
    if ((this.c & 0x2000) == 8192) {
      paramh.a(15, ay());
    }
    if ((this.c & 0x4000) == 16384) {
      paramh.a(16, az());
    }
    if ((this.c & 0x8000) == 32768) {
      paramh.a(20, aA());
    }
    if ((this.c & 0x10000) == 65536) {
      paramh.a(21, aB());
    }
    if ((this.c & 0x20000) == 131072) {
      paramh.a(22, aC());
    }
    if ((this.c & 0x40000) == 262144) {
      paramh.a(23, this.w);
    }
    if ((this.c & 0x80000) == 524288) {
      paramh.a(25, aD());
    }
    if ((this.c & 0x100000) == 1048576) {
      paramh.a(26, this.y);
    }
    if ((this.c & 0x200000) == 2097152) {
      paramh.a(27, this.z);
    }
    if ((this.c & 0x400000) == 4194304) {
      paramh.a(28, this.A);
    }
    if ((this.c & 0x800000) == 8388608) {
      paramh.a(29, this.B);
    }
    if ((this.c & 0x1000000) == 16777216) {
      paramh.a(30, this.C);
    }
    if ((this.c & 0x2000000) == 33554432) {
      paramh.a(31, this.D);
    }
    if ((this.c & 0x4000000) == 67108864) {
      paramh.a(32, this.E);
    }
    if ((this.c & 0x8000000) == 134217728) {
      paramh.a(33, this.F);
    }
    if ((this.c & 0x10000000) == 268435456) {
      paramh.a(34, this.G);
    }
    if ((this.c & 0x20000000) == 536870912) {
      paramh.a(35, this.H);
    }
    if ((this.c & 0x40000000) == 1073741824) {
      paramh.a(36, aE());
    }
    if ((this.c & 0x80000000) == Integer.MIN_VALUE) {
      paramh.a(37, this.J);
    }
    if ((this.d & 0x1) == 1) {
      paramh.a(38, aF());
    }
    if ((this.d & 0x2) == 2) {
      paramh.a(39, this.L);
    }
    if ((this.d & 0x4) == 4) {
      paramh.a(40, this.M);
    }
    if ((this.d & 0x8) == 8) {
      paramh.a(41, this.N);
    }
    if ((this.d & 0x10) == 16) {
      paramh.a(42, this.O);
    }
    if ((this.d & 0x20) == 32) {
      paramh.a(43, this.P);
    }
  }
  
  public final boolean aa()
  {
    return (this.c & 0x80000000) == Integer.MIN_VALUE;
  }
  
  public final int ab()
  {
    return this.J;
  }
  
  public final boolean ac()
  {
    return (this.d & 0x1) == 1;
  }
  
  public final boolean ad()
  {
    return (this.d & 0x2) == 2;
  }
  
  public final d ae()
  {
    return this.L;
  }
  
  public final boolean af()
  {
    return (this.d & 0x4) == 4;
  }
  
  public final d ag()
  {
    return this.M;
  }
  
  public final boolean ah()
  {
    return (this.d & 0x8) == 8;
  }
  
  public final int ai()
  {
    return this.N;
  }
  
  public final boolean aj()
  {
    return (this.d & 0x10) == 16;
  }
  
  public final int ak()
  {
    return this.O;
  }
  
  public final boolean al()
  {
    return (this.d & 0x20) == 32;
  }
  
  public final long am()
  {
    return this.P;
  }
  
  public final ab ao()
  {
    return ab.g().a(this);
  }
  
  public final int c()
  {
    int i1 = this.R;
    if (i1 != -1) {
      return i1;
    }
    int i2 = 0;
    if ((this.c & 0x1) == 1) {
      i2 = h.b(1, this.e) + 0;
    }
    i1 = i2;
    if ((this.c & 0x2) == 2) {
      i1 = i2 + h.b(2, this.f);
    }
    i2 = i1;
    if ((this.c & 0x4) == 4) {
      i2 = i1 + h.b(3, ap());
    }
    i1 = i2;
    if ((this.c & 0x8) == 8) {
      i1 = i2 + h.b(4, aq());
    }
    i2 = i1;
    if ((this.c & 0x10) == 16) {
      i2 = i1 + h.b(5, ar());
    }
    i1 = i2;
    if ((this.c & 0x20) == 32) {
      i1 = i2 + h.b(6, as());
    }
    i2 = i1;
    if ((this.c & 0x40) == 64) {
      i2 = i1 + h.b(7, at());
    }
    i1 = i2;
    if ((this.c & 0x80) == 128) {
      i1 = i2 + h.b(8, au());
    }
    i2 = i1;
    if ((this.c & 0x100) == 256) {
      i2 = i1 + h.b(9, av());
    }
    i1 = i2;
    if ((this.c & 0x200) == 512) {
      i1 = i2 + h.c(10, this.n);
    }
    i2 = i1;
    if ((this.c & 0x400) == 1024) {
      i2 = i1 + h.c(11, this.o);
    }
    i1 = i2;
    if ((this.c & 0x800) == 2048) {
      i1 = i2 + h.b(13, aw());
    }
    i2 = i1;
    if ((this.c & 0x1000) == 4096) {
      i2 = i1 + h.b(14, ax());
    }
    i1 = i2;
    if ((this.c & 0x2000) == 8192) {
      i1 = i2 + h.b(15, ay());
    }
    i2 = i1;
    if ((this.c & 0x4000) == 16384) {
      i2 = i1 + h.b(16, az());
    }
    i1 = i2;
    if ((this.c & 0x8000) == 32768) {
      i1 = i2 + h.b(20, aA());
    }
    i2 = i1;
    if ((this.c & 0x10000) == 65536) {
      i2 = i1 + h.b(21, aB());
    }
    i1 = i2;
    if ((this.c & 0x20000) == 131072) {
      i1 = i2 + h.b(22, aC());
    }
    i2 = i1;
    if ((this.c & 0x40000) == 262144) {
      i2 = i1 + h.c(23, this.w);
    }
    i1 = i2;
    if ((this.c & 0x80000) == 524288) {
      i1 = i2 + h.b(25, aD());
    }
    i2 = i1;
    if ((this.c & 0x100000) == 1048576) {
      i2 = i1 + h.c(26, this.y);
    }
    i1 = i2;
    if ((this.c & 0x200000) == 2097152) {
      i1 = i2 + h.c(27, this.z);
    }
    i2 = i1;
    if ((this.c & 0x400000) == 4194304) {
      i2 = i1 + h.b(28, this.A);
    }
    i1 = i2;
    if ((this.c & 0x800000) == 8388608) {
      i1 = i2 + h.c(29, this.B);
    }
    i2 = i1;
    if ((this.c & 0x1000000) == 16777216) {
      i2 = i1 + h.c(30, this.C);
    }
    i1 = i2;
    if ((this.c & 0x2000000) == 33554432) {
      i1 = i2 + h.c(31, this.D);
    }
    i2 = i1;
    if ((this.c & 0x4000000) == 67108864) {
      i2 = i1 + h.c(32, this.E);
    }
    i1 = i2;
    if ((this.c & 0x8000000) == 134217728) {
      i1 = i2 + h.c(33, this.F);
    }
    i2 = i1;
    if ((this.c & 0x10000000) == 268435456) {
      i2 = i1 + h.c(34, this.G);
    }
    i1 = i2;
    if ((this.c & 0x20000000) == 536870912) {
      i1 = i2 + h.c(35, this.H);
    }
    i2 = i1;
    if ((this.c & 0x40000000) == 1073741824) {
      i2 = i1 + h.b(36, aE());
    }
    i1 = i2;
    if ((this.c & 0x80000000) == Integer.MIN_VALUE) {
      i1 = i2 + h.c(37, this.J);
    }
    i2 = i1;
    if ((this.d & 0x1) == 1) {
      i2 = i1 + h.b(38, aF());
    }
    i1 = i2;
    if ((this.d & 0x2) == 2) {
      i1 = i2 + h.b(39, this.L);
    }
    i2 = i1;
    if ((this.d & 0x4) == 4) {
      i2 = i1 + h.b(40, this.M);
    }
    i1 = i2;
    if ((this.d & 0x8) == 8) {
      i1 = i2 + h.c(41, this.N);
    }
    i2 = i1;
    if ((this.d & 0x10) == 16) {
      i2 = i1 + h.c(42, this.O);
    }
    i1 = i2;
    if ((this.d & 0x20) == 32) {
      i1 = i2 + h.b(43, this.P);
    }
    this.R = i1;
    return i1;
  }
  
  public final boolean e()
  {
    int i1 = this.Q;
    if (i1 != -1) {
      return i1 == 1;
    }
    this.Q = 1;
    return true;
  }
  
  public final boolean g()
  {
    return (this.c & 0x1) == 1;
  }
  
  public final long h()
  {
    return this.e;
  }
  
  public final boolean i()
  {
    return (this.c & 0x2) == 2;
  }
  
  public final long j()
  {
    return this.f;
  }
  
  public final boolean k()
  {
    return (this.c & 0x4) == 4;
  }
  
  public final boolean l()
  {
    return (this.c & 0x8) == 8;
  }
  
  public final boolean m()
  {
    return (this.c & 0x10) == 16;
  }
  
  public final boolean n()
  {
    return (this.c & 0x20) == 32;
  }
  
  public final boolean o()
  {
    return (this.c & 0x40) == 64;
  }
  
  public final boolean p()
  {
    return (this.c & 0x80) == 128;
  }
  
  public final boolean q()
  {
    return (this.c & 0x100) == 256;
  }
  
  public final boolean r()
  {
    return (this.c & 0x200) == 512;
  }
  
  public final int s()
  {
    return this.n;
  }
  
  public final boolean t()
  {
    return (this.c & 0x400) == 1024;
  }
  
  public final int u()
  {
    return this.o;
  }
  
  public final boolean v()
  {
    return (this.c & 0x800) == 2048;
  }
  
  public final boolean w()
  {
    return (this.c & 0x1000) == 4096;
  }
  
  public final boolean x()
  {
    return (this.c & 0x2000) == 8192;
  }
  
  public final boolean y()
  {
    return (this.c & 0x4000) == 16384;
  }
  
  public final boolean z()
  {
    return (this.c & 0x8000) == 32768;
  }
}


/* Location:              /Users/amaurremi/uw/stringoid/static-dynamic-comparison/apps/xperia z/com.androidwasabi.livewallpaper.xperiaz-13-dex2jar.jar!/com/appbrain/e/aa.class
 * Java compiler version: 6 (50.0)
 * JD-Core Version:       0.7.1
 */