package com.google.android.gms.maps.a;

import android.os.Binder;
import android.os.IBinder;
import android.os.IInterface;
import android.os.Parcel;
import com.google.android.gms.maps.model.a.e;
import com.google.android.gms.maps.model.a.e.a;

public abstract interface s
  extends IInterface
{
  public abstract void e(e parame);
  
  public abstract void f(e parame);
  
  public abstract void g(e parame);
  
  public static abstract class a
    extends Binder
    implements s
  {
    public static s aa(IBinder paramIBinder)
    {
      if (paramIBinder == null) {
        return null;
      }
      IInterface localIInterface = paramIBinder.queryLocalInterface("com.google.android.gms.maps.internal.IOnMarkerDragListener");
      if ((localIInterface != null) && ((localIInterface instanceof s))) {
        return (s)localIInterface;
      }
      return new a(paramIBinder);
    }
    
    public IBinder asBinder()
    {
      return this;
    }
    
    public boolean onTransact(int paramInt1, Parcel paramParcel1, Parcel paramParcel2, int paramInt2)
    {
      switch (paramInt1)
      {
      default: 
        return super.onTransact(paramInt1, paramParcel1, paramParcel2, paramInt2);
      case 1598968902: 
        paramParcel2.writeString("com.google.android.gms.maps.internal.IOnMarkerDragListener");
        return true;
      case 1: 
        paramParcel1.enforceInterface("com.google.android.gms.maps.internal.IOnMarkerDragListener");
        e(e.a.ai(paramParcel1.readStrongBinder()));
        paramParcel2.writeNoException();
        return true;
      case 2: 
        paramParcel1.enforceInterface("com.google.android.gms.maps.internal.IOnMarkerDragListener");
        f(e.a.ai(paramParcel1.readStrongBinder()));
        paramParcel2.writeNoException();
        return true;
      }
      paramParcel1.enforceInterface("com.google.android.gms.maps.internal.IOnMarkerDragListener");
      g(e.a.ai(paramParcel1.readStrongBinder()));
      paramParcel2.writeNoException();
      return true;
    }
    
    private static class a
      implements s
    {
      private IBinder tS;
      
      a(IBinder paramIBinder)
      {
        this.tS = paramIBinder;
      }
      
      public IBinder asBinder()
      {
        return this.tS;
      }
      
      /* Error */
      public void e(e parame)
      {
        // Byte code:
        //   0: invokestatic 29	android/os/Parcel:obtain	()Landroid/os/Parcel;
        //   3: astore_2
        //   4: invokestatic 29	android/os/Parcel:obtain	()Landroid/os/Parcel;
        //   7: astore_3
        //   8: aload_2
        //   9: ldc 31
        //   11: invokevirtual 35	android/os/Parcel:writeInterfaceToken	(Ljava/lang/String;)V
        //   14: aload_1
        //   15: ifnull +42 -> 57
        //   18: aload_1
        //   19: invokeinterface 39 1 0
        //   24: astore_1
        //   25: aload_2
        //   26: aload_1
        //   27: invokevirtual 42	android/os/Parcel:writeStrongBinder	(Landroid/os/IBinder;)V
        //   30: aload_0
        //   31: getfield 18	com/google/android/gms/maps/a/s$a$a:tS	Landroid/os/IBinder;
        //   34: iconst_1
        //   35: aload_2
        //   36: aload_3
        //   37: iconst_0
        //   38: invokeinterface 48 5 0
        //   43: pop
        //   44: aload_3
        //   45: invokevirtual 51	android/os/Parcel:readException	()V
        //   48: aload_3
        //   49: invokevirtual 54	android/os/Parcel:recycle	()V
        //   52: aload_2
        //   53: invokevirtual 54	android/os/Parcel:recycle	()V
        //   56: return
        //   57: aconst_null
        //   58: astore_1
        //   59: goto -34 -> 25
        //   62: astore_1
        //   63: aload_3
        //   64: invokevirtual 54	android/os/Parcel:recycle	()V
        //   67: aload_2
        //   68: invokevirtual 54	android/os/Parcel:recycle	()V
        //   71: aload_1
        //   72: athrow
        // Local variable table:
        //   start	length	slot	name	signature
        //   0	73	0	this	a
        //   0	73	1	parame	e
        //   3	65	2	localParcel1	Parcel
        //   7	57	3	localParcel2	Parcel
        // Exception table:
        //   from	to	target	type
        //   8	14	62	finally
        //   18	25	62	finally
        //   25	48	62	finally
      }
      
      /* Error */
      public void f(e parame)
      {
        // Byte code:
        //   0: invokestatic 29	android/os/Parcel:obtain	()Landroid/os/Parcel;
        //   3: astore_2
        //   4: invokestatic 29	android/os/Parcel:obtain	()Landroid/os/Parcel;
        //   7: astore_3
        //   8: aload_2
        //   9: ldc 31
        //   11: invokevirtual 35	android/os/Parcel:writeInterfaceToken	(Ljava/lang/String;)V
        //   14: aload_1
        //   15: ifnull +42 -> 57
        //   18: aload_1
        //   19: invokeinterface 39 1 0
        //   24: astore_1
        //   25: aload_2
        //   26: aload_1
        //   27: invokevirtual 42	android/os/Parcel:writeStrongBinder	(Landroid/os/IBinder;)V
        //   30: aload_0
        //   31: getfield 18	com/google/android/gms/maps/a/s$a$a:tS	Landroid/os/IBinder;
        //   34: iconst_2
        //   35: aload_2
        //   36: aload_3
        //   37: iconst_0
        //   38: invokeinterface 48 5 0
        //   43: pop
        //   44: aload_3
        //   45: invokevirtual 51	android/os/Parcel:readException	()V
        //   48: aload_3
        //   49: invokevirtual 54	android/os/Parcel:recycle	()V
        //   52: aload_2
        //   53: invokevirtual 54	android/os/Parcel:recycle	()V
        //   56: return
        //   57: aconst_null
        //   58: astore_1
        //   59: goto -34 -> 25
        //   62: astore_1
        //   63: aload_3
        //   64: invokevirtual 54	android/os/Parcel:recycle	()V
        //   67: aload_2
        //   68: invokevirtual 54	android/os/Parcel:recycle	()V
        //   71: aload_1
        //   72: athrow
        // Local variable table:
        //   start	length	slot	name	signature
        //   0	73	0	this	a
        //   0	73	1	parame	e
        //   3	65	2	localParcel1	Parcel
        //   7	57	3	localParcel2	Parcel
        // Exception table:
        //   from	to	target	type
        //   8	14	62	finally
        //   18	25	62	finally
        //   25	48	62	finally
      }
      
      /* Error */
      public void g(e parame)
      {
        // Byte code:
        //   0: invokestatic 29	android/os/Parcel:obtain	()Landroid/os/Parcel;
        //   3: astore_2
        //   4: invokestatic 29	android/os/Parcel:obtain	()Landroid/os/Parcel;
        //   7: astore_3
        //   8: aload_2
        //   9: ldc 31
        //   11: invokevirtual 35	android/os/Parcel:writeInterfaceToken	(Ljava/lang/String;)V
        //   14: aload_1
        //   15: ifnull +42 -> 57
        //   18: aload_1
        //   19: invokeinterface 39 1 0
        //   24: astore_1
        //   25: aload_2
        //   26: aload_1
        //   27: invokevirtual 42	android/os/Parcel:writeStrongBinder	(Landroid/os/IBinder;)V
        //   30: aload_0
        //   31: getfield 18	com/google/android/gms/maps/a/s$a$a:tS	Landroid/os/IBinder;
        //   34: iconst_3
        //   35: aload_2
        //   36: aload_3
        //   37: iconst_0
        //   38: invokeinterface 48 5 0
        //   43: pop
        //   44: aload_3
        //   45: invokevirtual 51	android/os/Parcel:readException	()V
        //   48: aload_3
        //   49: invokevirtual 54	android/os/Parcel:recycle	()V
        //   52: aload_2
        //   53: invokevirtual 54	android/os/Parcel:recycle	()V
        //   56: return
        //   57: aconst_null
        //   58: astore_1
        //   59: goto -34 -> 25
        //   62: astore_1
        //   63: aload_3
        //   64: invokevirtual 54	android/os/Parcel:recycle	()V
        //   67: aload_2
        //   68: invokevirtual 54	android/os/Parcel:recycle	()V
        //   71: aload_1
        //   72: athrow
        // Local variable table:
        //   start	length	slot	name	signature
        //   0	73	0	this	a
        //   0	73	1	parame	e
        //   3	65	2	localParcel1	Parcel
        //   7	57	3	localParcel2	Parcel
        // Exception table:
        //   from	to	target	type
        //   8	14	62	finally
        //   18	25	62	finally
        //   25	48	62	finally
      }
    }
  }
}


/* Location:              /Users/amaurremi/uw/stringoid/static-dynamic-comparison/apps/quick pdf scanner/com.mobisystems.mobiscanner-213-dex2jar.jar!/com/google/android/gms/maps/a/s.class
 * Java compiler version: 6 (50.0)
 * JD-Core Version:       0.7.1
 */