package com.google.android.gms.maps.a;

import android.os.Binder;
import android.os.Bundle;
import android.os.IBinder;
import android.os.IInterface;
import android.os.Parcel;
import android.os.Parcelable.Creator;
import com.google.android.gms.dynamic.c;
import com.google.android.gms.dynamic.c.a;

public abstract interface e
  extends IInterface
{
  public abstract void onCreate(Bundle paramBundle);
  
  public abstract void onDestroy();
  
  public abstract void onLowMemory();
  
  public abstract void onPause();
  
  public abstract void onResume();
  
  public abstract void onSaveInstanceState(Bundle paramBundle);
  
  public abstract c pi();
  
  public abstract b uw();
  
  public static abstract class a
    extends Binder
    implements e
  {
    public static e N(IBinder paramIBinder)
    {
      if (paramIBinder == null) {
        return null;
      }
      IInterface localIInterface = paramIBinder.queryLocalInterface("com.google.android.gms.maps.internal.IMapViewDelegate");
      if ((localIInterface != null) && ((localIInterface instanceof e))) {
        return (e)localIInterface;
      }
      return new a(paramIBinder);
    }
    
    public boolean onTransact(int paramInt1, Parcel paramParcel1, Parcel paramParcel2, int paramInt2)
    {
      Object localObject2 = null;
      Object localObject3 = null;
      b localb = null;
      Object localObject1 = null;
      switch (paramInt1)
      {
      default: 
        return super.onTransact(paramInt1, paramParcel1, paramParcel2, paramInt2);
      case 1598968902: 
        paramParcel2.writeString("com.google.android.gms.maps.internal.IMapViewDelegate");
        return true;
      case 1: 
        paramParcel1.enforceInterface("com.google.android.gms.maps.internal.IMapViewDelegate");
        localb = uw();
        paramParcel2.writeNoException();
        paramParcel1 = (Parcel)localObject1;
        if (localb != null) {
          paramParcel1 = localb.asBinder();
        }
        paramParcel2.writeStrongBinder(paramParcel1);
        return true;
      case 2: 
        paramParcel1.enforceInterface("com.google.android.gms.maps.internal.IMapViewDelegate");
        localObject1 = localObject2;
        if (paramParcel1.readInt() != 0) {
          localObject1 = (Bundle)Bundle.CREATOR.createFromParcel(paramParcel1);
        }
        onCreate((Bundle)localObject1);
        paramParcel2.writeNoException();
        return true;
      case 3: 
        paramParcel1.enforceInterface("com.google.android.gms.maps.internal.IMapViewDelegate");
        onResume();
        paramParcel2.writeNoException();
        return true;
      case 4: 
        paramParcel1.enforceInterface("com.google.android.gms.maps.internal.IMapViewDelegate");
        onPause();
        paramParcel2.writeNoException();
        return true;
      case 5: 
        paramParcel1.enforceInterface("com.google.android.gms.maps.internal.IMapViewDelegate");
        onDestroy();
        paramParcel2.writeNoException();
        return true;
      case 6: 
        paramParcel1.enforceInterface("com.google.android.gms.maps.internal.IMapViewDelegate");
        onLowMemory();
        paramParcel2.writeNoException();
        return true;
      case 7: 
        paramParcel1.enforceInterface("com.google.android.gms.maps.internal.IMapViewDelegate");
        localObject1 = localObject3;
        if (paramParcel1.readInt() != 0) {
          localObject1 = (Bundle)Bundle.CREATOR.createFromParcel(paramParcel1);
        }
        onSaveInstanceState((Bundle)localObject1);
        paramParcel2.writeNoException();
        if (localObject1 != null)
        {
          paramParcel2.writeInt(1);
          ((Bundle)localObject1).writeToParcel(paramParcel2, 1);
        }
        for (;;)
        {
          return true;
          paramParcel2.writeInt(0);
        }
      }
      paramParcel1.enforceInterface("com.google.android.gms.maps.internal.IMapViewDelegate");
      localObject1 = pi();
      paramParcel2.writeNoException();
      paramParcel1 = localb;
      if (localObject1 != null) {
        paramParcel1 = ((c)localObject1).asBinder();
      }
      paramParcel2.writeStrongBinder(paramParcel1);
      return true;
    }
    
    private static class a
      implements e
    {
      private IBinder tS;
      
      a(IBinder paramIBinder)
      {
        this.tS = paramIBinder;
      }
      
      public IBinder asBinder()
      {
        return this.tS;
      }
      
      /* Error */
      public void onCreate(Bundle paramBundle)
      {
        // Byte code:
        //   0: invokestatic 29	android/os/Parcel:obtain	()Landroid/os/Parcel;
        //   3: astore_2
        //   4: invokestatic 29	android/os/Parcel:obtain	()Landroid/os/Parcel;
        //   7: astore_3
        //   8: aload_2
        //   9: ldc 31
        //   11: invokevirtual 35	android/os/Parcel:writeInterfaceToken	(Ljava/lang/String;)V
        //   14: aload_1
        //   15: ifnull +41 -> 56
        //   18: aload_2
        //   19: iconst_1
        //   20: invokevirtual 39	android/os/Parcel:writeInt	(I)V
        //   23: aload_1
        //   24: aload_2
        //   25: iconst_0
        //   26: invokevirtual 45	android/os/Bundle:writeToParcel	(Landroid/os/Parcel;I)V
        //   29: aload_0
        //   30: getfield 18	com/google/android/gms/maps/a/e$a$a:tS	Landroid/os/IBinder;
        //   33: iconst_2
        //   34: aload_2
        //   35: aload_3
        //   36: iconst_0
        //   37: invokeinterface 51 5 0
        //   42: pop
        //   43: aload_3
        //   44: invokevirtual 54	android/os/Parcel:readException	()V
        //   47: aload_3
        //   48: invokevirtual 57	android/os/Parcel:recycle	()V
        //   51: aload_2
        //   52: invokevirtual 57	android/os/Parcel:recycle	()V
        //   55: return
        //   56: aload_2
        //   57: iconst_0
        //   58: invokevirtual 39	android/os/Parcel:writeInt	(I)V
        //   61: goto -32 -> 29
        //   64: astore_1
        //   65: aload_3
        //   66: invokevirtual 57	android/os/Parcel:recycle	()V
        //   69: aload_2
        //   70: invokevirtual 57	android/os/Parcel:recycle	()V
        //   73: aload_1
        //   74: athrow
        // Local variable table:
        //   start	length	slot	name	signature
        //   0	75	0	this	a
        //   0	75	1	paramBundle	Bundle
        //   3	67	2	localParcel1	Parcel
        //   7	59	3	localParcel2	Parcel
        // Exception table:
        //   from	to	target	type
        //   8	14	64	finally
        //   18	29	64	finally
        //   29	47	64	finally
        //   56	61	64	finally
      }
      
      public void onDestroy()
      {
        Parcel localParcel1 = Parcel.obtain();
        Parcel localParcel2 = Parcel.obtain();
        try
        {
          localParcel1.writeInterfaceToken("com.google.android.gms.maps.internal.IMapViewDelegate");
          this.tS.transact(5, localParcel1, localParcel2, 0);
          localParcel2.readException();
          return;
        }
        finally
        {
          localParcel2.recycle();
          localParcel1.recycle();
        }
      }
      
      public void onLowMemory()
      {
        Parcel localParcel1 = Parcel.obtain();
        Parcel localParcel2 = Parcel.obtain();
        try
        {
          localParcel1.writeInterfaceToken("com.google.android.gms.maps.internal.IMapViewDelegate");
          this.tS.transact(6, localParcel1, localParcel2, 0);
          localParcel2.readException();
          return;
        }
        finally
        {
          localParcel2.recycle();
          localParcel1.recycle();
        }
      }
      
      public void onPause()
      {
        Parcel localParcel1 = Parcel.obtain();
        Parcel localParcel2 = Parcel.obtain();
        try
        {
          localParcel1.writeInterfaceToken("com.google.android.gms.maps.internal.IMapViewDelegate");
          this.tS.transact(4, localParcel1, localParcel2, 0);
          localParcel2.readException();
          return;
        }
        finally
        {
          localParcel2.recycle();
          localParcel1.recycle();
        }
      }
      
      public void onResume()
      {
        Parcel localParcel1 = Parcel.obtain();
        Parcel localParcel2 = Parcel.obtain();
        try
        {
          localParcel1.writeInterfaceToken("com.google.android.gms.maps.internal.IMapViewDelegate");
          this.tS.transact(3, localParcel1, localParcel2, 0);
          localParcel2.readException();
          return;
        }
        finally
        {
          localParcel2.recycle();
          localParcel1.recycle();
        }
      }
      
      /* Error */
      public void onSaveInstanceState(Bundle paramBundle)
      {
        // Byte code:
        //   0: invokestatic 29	android/os/Parcel:obtain	()Landroid/os/Parcel;
        //   3: astore_2
        //   4: invokestatic 29	android/os/Parcel:obtain	()Landroid/os/Parcel;
        //   7: astore_3
        //   8: aload_2
        //   9: ldc 31
        //   11: invokevirtual 35	android/os/Parcel:writeInterfaceToken	(Ljava/lang/String;)V
        //   14: aload_1
        //   15: ifnull +54 -> 69
        //   18: aload_2
        //   19: iconst_1
        //   20: invokevirtual 39	android/os/Parcel:writeInt	(I)V
        //   23: aload_1
        //   24: aload_2
        //   25: iconst_0
        //   26: invokevirtual 45	android/os/Bundle:writeToParcel	(Landroid/os/Parcel;I)V
        //   29: aload_0
        //   30: getfield 18	com/google/android/gms/maps/a/e$a$a:tS	Landroid/os/IBinder;
        //   33: bipush 7
        //   35: aload_2
        //   36: aload_3
        //   37: iconst_0
        //   38: invokeinterface 51 5 0
        //   43: pop
        //   44: aload_3
        //   45: invokevirtual 54	android/os/Parcel:readException	()V
        //   48: aload_3
        //   49: invokevirtual 66	android/os/Parcel:readInt	()I
        //   52: ifeq +8 -> 60
        //   55: aload_1
        //   56: aload_3
        //   57: invokevirtual 70	android/os/Bundle:readFromParcel	(Landroid/os/Parcel;)V
        //   60: aload_3
        //   61: invokevirtual 57	android/os/Parcel:recycle	()V
        //   64: aload_2
        //   65: invokevirtual 57	android/os/Parcel:recycle	()V
        //   68: return
        //   69: aload_2
        //   70: iconst_0
        //   71: invokevirtual 39	android/os/Parcel:writeInt	(I)V
        //   74: goto -45 -> 29
        //   77: astore_1
        //   78: aload_3
        //   79: invokevirtual 57	android/os/Parcel:recycle	()V
        //   82: aload_2
        //   83: invokevirtual 57	android/os/Parcel:recycle	()V
        //   86: aload_1
        //   87: athrow
        // Local variable table:
        //   start	length	slot	name	signature
        //   0	88	0	this	a
        //   0	88	1	paramBundle	Bundle
        //   3	80	2	localParcel1	Parcel
        //   7	72	3	localParcel2	Parcel
        // Exception table:
        //   from	to	target	type
        //   8	14	77	finally
        //   18	29	77	finally
        //   29	60	77	finally
        //   69	74	77	finally
      }
      
      public c pi()
      {
        Parcel localParcel1 = Parcel.obtain();
        Parcel localParcel2 = Parcel.obtain();
        try
        {
          localParcel1.writeInterfaceToken("com.google.android.gms.maps.internal.IMapViewDelegate");
          this.tS.transact(8, localParcel1, localParcel2, 0);
          localParcel2.readException();
          c localc = c.a.h(localParcel2.readStrongBinder());
          return localc;
        }
        finally
        {
          localParcel2.recycle();
          localParcel1.recycle();
        }
      }
      
      public b uw()
      {
        Parcel localParcel1 = Parcel.obtain();
        Parcel localParcel2 = Parcel.obtain();
        try
        {
          localParcel1.writeInterfaceToken("com.google.android.gms.maps.internal.IMapViewDelegate");
          this.tS.transact(1, localParcel1, localParcel2, 0);
          localParcel2.readException();
          b localb = b.a.K(localParcel2.readStrongBinder());
          return localb;
        }
        finally
        {
          localParcel2.recycle();
          localParcel1.recycle();
        }
      }
    }
  }
}


/* Location:              /Users/amaurremi/uw/stringoid/static-dynamic-comparison/apps/quick pdf scanner/com.mobisystems.mobiscanner-213-dex2jar.jar!/com/google/android/gms/maps/a/e.class
 * Java compiler version: 6 (50.0)
 * JD-Core Version:       0.7.1
 */