package com.google.android.gms.internal;

import android.content.Context;
import android.util.DisplayMetrics;
import android.view.MotionEvent;
import java.io.UnsupportedEncodingException;
import java.lang.reflect.InvocationTargetException;
import java.lang.reflect.Method;
import java.nio.ByteBuffer;
import java.util.ArrayList;

public abstract class dd
  extends dc
{
  private static Method d;
  private static Method e;
  private static Method f;
  private static Method g;
  private static Method h;
  private static Method i;
  private static String j;
  private static long k = 0L;
  private static dp l;
  private static boolean m = false;
  
  protected dd(Context paramContext, dn paramdn, do paramdo)
  {
    super(paramContext, paramdn, paramdo);
  }
  
  private static String a()
  {
    if (j == null) {
      throw new de();
    }
    return j;
  }
  
  private static String a(Context paramContext, dn paramdn)
  {
    if (f == null) {
      throw new de();
    }
    try
    {
      paramContext = (ByteBuffer)f.invoke(null, new Object[] { paramContext });
      if (paramContext == null) {
        throw new de();
      }
    }
    catch (IllegalAccessException paramContext)
    {
      throw new de(paramContext);
      paramContext = paramdn.a(paramContext.array(), true);
      return paramContext;
    }
    catch (InvocationTargetException paramContext)
    {
      throw new de(paramContext);
    }
  }
  
  private static String a(byte[] paramArrayOfByte, String paramString)
  {
    try
    {
      paramArrayOfByte = new String(l.a(paramArrayOfByte, paramString), "UTF-8");
      return paramArrayOfByte;
    }
    catch (dq paramArrayOfByte)
    {
      throw new de(paramArrayOfByte);
    }
    catch (UnsupportedEncodingException paramArrayOfByte)
    {
      throw new de(paramArrayOfByte);
    }
  }
  
  private static ArrayList a(MotionEvent paramMotionEvent, DisplayMetrics paramDisplayMetrics)
  {
    if ((g == null) || (paramMotionEvent == null)) {
      throw new de();
    }
    try
    {
      paramMotionEvent = (ArrayList)g.invoke(null, new Object[] { paramMotionEvent, paramDisplayMetrics });
      return paramMotionEvent;
    }
    catch (IllegalAccessException paramMotionEvent)
    {
      throw new de(paramMotionEvent);
    }
    catch (InvocationTargetException paramMotionEvent)
    {
      throw new de(paramMotionEvent);
    }
  }
  
  /* Error */
  protected static void a(String paramString, Context paramContext, dn paramdn)
  {
    // Byte code:
    //   0: ldc 2
    //   2: monitorenter
    //   3: getstatic 25	com/google/android/gms/internal/dd:m	Z
    //   6: istore_3
    //   7: iload_3
    //   8: ifne +85 -> 93
    //   11: new 78	com/google/android/gms/internal/dp
    //   14: dup
    //   15: aload_2
    //   16: aconst_null
    //   17: invokespecial 107	com/google/android/gms/internal/dp:<init>	(Lcom/google/android/gms/internal/dn;Ljava/security/SecureRandom;)V
    //   20: putstatic 76	com/google/android/gms/internal/dd:l	Lcom/google/android/gms/internal/dp;
    //   23: aload_0
    //   24: putstatic 34	com/google/android/gms/internal/dd:j	Ljava/lang/String;
    //   27: getstatic 76	com/google/android/gms/internal/dd:l	Lcom/google/android/gms/internal/dp;
    //   30: ldc 109
    //   32: invokevirtual 112	com/google/android/gms/internal/dp:a	(Ljava/lang/String;)[B
    //   35: astore 4
    //   37: getstatic 76	com/google/android/gms/internal/dd:l	Lcom/google/android/gms/internal/dp;
    //   40: aload 4
    //   42: ldc 114
    //   44: invokevirtual 81	com/google/android/gms/internal/dp:a	([BLjava/lang/String;)[B
    //   47: astore 5
    //   49: aload_1
    //   50: invokevirtual 120	android/content/Context:getCacheDir	()Ljava/io/File;
    //   53: astore_2
    //   54: aload_2
    //   55: astore_0
    //   56: aload_2
    //   57: ifnonnull +40 -> 97
    //   60: aload_1
    //   61: ldc 122
    //   63: iconst_0
    //   64: invokevirtual 126	android/content/Context:getDir	(Ljava/lang/String;I)Ljava/io/File;
    //   67: astore_2
    //   68: aload_2
    //   69: astore_0
    //   70: aload_2
    //   71: ifnonnull +26 -> 97
    //   74: new 36	com/google/android/gms/internal/de
    //   77: dup
    //   78: invokespecial 38	com/google/android/gms/internal/de:<init>	()V
    //   81: athrow
    //   82: astore_0
    //   83: new 36	com/google/android/gms/internal/de
    //   86: dup
    //   87: aload_0
    //   88: invokespecial 58	com/google/android/gms/internal/de:<init>	(Ljava/lang/Throwable;)V
    //   91: athrow
    //   92: astore_0
    //   93: ldc 2
    //   95: monitorexit
    //   96: return
    //   97: ldc -128
    //   99: ldc -126
    //   101: aload_0
    //   102: invokestatic 136	java/io/File:createTempFile	(Ljava/lang/String;Ljava/lang/String;Ljava/io/File;)Ljava/io/File;
    //   105: astore_2
    //   106: new 138	java/io/FileOutputStream
    //   109: dup
    //   110: aload_2
    //   111: invokespecial 141	java/io/FileOutputStream:<init>	(Ljava/io/File;)V
    //   114: astore 6
    //   116: aload 6
    //   118: aload 5
    //   120: iconst_0
    //   121: aload 5
    //   123: arraylength
    //   124: invokevirtual 145	java/io/FileOutputStream:write	([BII)V
    //   127: aload 6
    //   129: invokevirtual 148	java/io/FileOutputStream:close	()V
    //   132: new 150	dalvik/system/DexClassLoader
    //   135: dup
    //   136: aload_2
    //   137: invokevirtual 153	java/io/File:getAbsolutePath	()Ljava/lang/String;
    //   140: aload_0
    //   141: invokevirtual 153	java/io/File:getAbsolutePath	()Ljava/lang/String;
    //   144: aconst_null
    //   145: aload_1
    //   146: invokevirtual 157	android/content/Context:getClassLoader	()Ljava/lang/ClassLoader;
    //   149: invokespecial 160	dalvik/system/DexClassLoader:<init>	(Ljava/lang/String;Ljava/lang/String;Ljava/lang/String;Ljava/lang/ClassLoader;)V
    //   152: astore 9
    //   154: aload 9
    //   156: aload 4
    //   158: ldc -94
    //   160: invokestatic 164	com/google/android/gms/internal/dd:a	([BLjava/lang/String;)Ljava/lang/String;
    //   163: invokevirtual 168	dalvik/system/DexClassLoader:loadClass	(Ljava/lang/String;)Ljava/lang/Class;
    //   166: astore_1
    //   167: aload 9
    //   169: aload 4
    //   171: ldc -86
    //   173: invokestatic 164	com/google/android/gms/internal/dd:a	([BLjava/lang/String;)Ljava/lang/String;
    //   176: invokevirtual 168	dalvik/system/DexClassLoader:loadClass	(Ljava/lang/String;)Ljava/lang/Class;
    //   179: astore 5
    //   181: aload 9
    //   183: aload 4
    //   185: ldc -84
    //   187: invokestatic 164	com/google/android/gms/internal/dd:a	([BLjava/lang/String;)Ljava/lang/String;
    //   190: invokevirtual 168	dalvik/system/DexClassLoader:loadClass	(Ljava/lang/String;)Ljava/lang/Class;
    //   193: astore 6
    //   195: aload 9
    //   197: aload 4
    //   199: ldc -82
    //   201: invokestatic 164	com/google/android/gms/internal/dd:a	([BLjava/lang/String;)Ljava/lang/String;
    //   204: invokevirtual 168	dalvik/system/DexClassLoader:loadClass	(Ljava/lang/String;)Ljava/lang/Class;
    //   207: astore 7
    //   209: aload 9
    //   211: aload 4
    //   213: ldc -80
    //   215: invokestatic 164	com/google/android/gms/internal/dd:a	([BLjava/lang/String;)Ljava/lang/String;
    //   218: invokevirtual 168	dalvik/system/DexClassLoader:loadClass	(Ljava/lang/String;)Ljava/lang/Class;
    //   221: astore 8
    //   223: aload 9
    //   225: aload 4
    //   227: ldc -78
    //   229: invokestatic 164	com/google/android/gms/internal/dd:a	([BLjava/lang/String;)Ljava/lang/String;
    //   232: invokevirtual 168	dalvik/system/DexClassLoader:loadClass	(Ljava/lang/String;)Ljava/lang/Class;
    //   235: astore 9
    //   237: aload_1
    //   238: aload 4
    //   240: ldc -76
    //   242: invokestatic 164	com/google/android/gms/internal/dd:a	([BLjava/lang/String;)Ljava/lang/String;
    //   245: iconst_0
    //   246: anewarray 182	java/lang/Class
    //   249: invokevirtual 186	java/lang/Class:getMethod	(Ljava/lang/String;[Ljava/lang/Class;)Ljava/lang/reflect/Method;
    //   252: putstatic 188	com/google/android/gms/internal/dd:d	Ljava/lang/reflect/Method;
    //   255: aload 5
    //   257: aload 4
    //   259: ldc -66
    //   261: invokestatic 164	com/google/android/gms/internal/dd:a	([BLjava/lang/String;)Ljava/lang/String;
    //   264: iconst_0
    //   265: anewarray 182	java/lang/Class
    //   268: invokevirtual 186	java/lang/Class:getMethod	(Ljava/lang/String;[Ljava/lang/Class;)Ljava/lang/reflect/Method;
    //   271: putstatic 192	com/google/android/gms/internal/dd:e	Ljava/lang/reflect/Method;
    //   274: aload 6
    //   276: aload 4
    //   278: ldc -62
    //   280: invokestatic 164	com/google/android/gms/internal/dd:a	([BLjava/lang/String;)Ljava/lang/String;
    //   283: iconst_1
    //   284: anewarray 182	java/lang/Class
    //   287: dup
    //   288: iconst_0
    //   289: ldc 116
    //   291: aastore
    //   292: invokevirtual 186	java/lang/Class:getMethod	(Ljava/lang/String;[Ljava/lang/Class;)Ljava/lang/reflect/Method;
    //   295: putstatic 45	com/google/android/gms/internal/dd:f	Ljava/lang/reflect/Method;
    //   298: aload 7
    //   300: aload 4
    //   302: ldc -60
    //   304: invokestatic 164	com/google/android/gms/internal/dd:a	([BLjava/lang/String;)Ljava/lang/String;
    //   307: iconst_2
    //   308: anewarray 182	java/lang/Class
    //   311: dup
    //   312: iconst_0
    //   313: ldc -58
    //   315: aastore
    //   316: dup
    //   317: iconst_1
    //   318: ldc -56
    //   320: aastore
    //   321: invokevirtual 186	java/lang/Class:getMethod	(Ljava/lang/String;[Ljava/lang/Class;)Ljava/lang/reflect/Method;
    //   324: putstatic 89	com/google/android/gms/internal/dd:g	Ljava/lang/reflect/Method;
    //   327: aload 8
    //   329: aload 4
    //   331: ldc -54
    //   333: invokestatic 164	com/google/android/gms/internal/dd:a	([BLjava/lang/String;)Ljava/lang/String;
    //   336: iconst_1
    //   337: anewarray 182	java/lang/Class
    //   340: dup
    //   341: iconst_0
    //   342: ldc 116
    //   344: aastore
    //   345: invokevirtual 186	java/lang/Class:getMethod	(Ljava/lang/String;[Ljava/lang/Class;)Ljava/lang/reflect/Method;
    //   348: putstatic 204	com/google/android/gms/internal/dd:h	Ljava/lang/reflect/Method;
    //   351: aload 9
    //   353: aload 4
    //   355: ldc -50
    //   357: invokestatic 164	com/google/android/gms/internal/dd:a	([BLjava/lang/String;)Ljava/lang/String;
    //   360: iconst_1
    //   361: anewarray 182	java/lang/Class
    //   364: dup
    //   365: iconst_0
    //   366: ldc 116
    //   368: aastore
    //   369: invokevirtual 186	java/lang/Class:getMethod	(Ljava/lang/String;[Ljava/lang/Class;)Ljava/lang/reflect/Method;
    //   372: putstatic 208	com/google/android/gms/internal/dd:i	Ljava/lang/reflect/Method;
    //   375: aload_2
    //   376: invokevirtual 211	java/io/File:getName	()Ljava/lang/String;
    //   379: astore_1
    //   380: aload_2
    //   381: invokevirtual 215	java/io/File:delete	()Z
    //   384: pop
    //   385: new 132	java/io/File
    //   388: dup
    //   389: aload_0
    //   390: aload_1
    //   391: ldc -126
    //   393: ldc -39
    //   395: invokevirtual 221	java/lang/String:replace	(Ljava/lang/CharSequence;Ljava/lang/CharSequence;)Ljava/lang/String;
    //   398: invokespecial 224	java/io/File:<init>	(Ljava/io/File;Ljava/lang/String;)V
    //   401: invokevirtual 215	java/io/File:delete	()Z
    //   404: pop
    //   405: invokestatic 228	com/google/android/gms/internal/dd:b	()Ljava/lang/Long;
    //   408: invokevirtual 234	java/lang/Long:longValue	()J
    //   411: putstatic 23	com/google/android/gms/internal/dd:k	J
    //   414: iconst_1
    //   415: putstatic 25	com/google/android/gms/internal/dd:m	Z
    //   418: goto -325 -> 93
    //   421: astore_0
    //   422: new 36	com/google/android/gms/internal/de
    //   425: dup
    //   426: aload_0
    //   427: invokespecial 58	com/google/android/gms/internal/de:<init>	(Ljava/lang/Throwable;)V
    //   430: athrow
    //   431: astore_0
    //   432: ldc 2
    //   434: monitorexit
    //   435: aload_0
    //   436: athrow
    //   437: astore_0
    //   438: new 36	com/google/android/gms/internal/de
    //   441: dup
    //   442: aload_0
    //   443: invokespecial 58	com/google/android/gms/internal/de:<init>	(Ljava/lang/Throwable;)V
    //   446: athrow
    //   447: astore_0
    //   448: new 36	com/google/android/gms/internal/de
    //   451: dup
    //   452: aload_0
    //   453: invokespecial 58	com/google/android/gms/internal/de:<init>	(Ljava/lang/Throwable;)V
    //   456: athrow
    //   457: astore_0
    //   458: new 36	com/google/android/gms/internal/de
    //   461: dup
    //   462: aload_0
    //   463: invokespecial 58	com/google/android/gms/internal/de:<init>	(Ljava/lang/Throwable;)V
    //   466: athrow
    //   467: astore_0
    //   468: new 36	com/google/android/gms/internal/de
    //   471: dup
    //   472: aload_0
    //   473: invokespecial 58	com/google/android/gms/internal/de:<init>	(Ljava/lang/Throwable;)V
    //   476: athrow
    //   477: astore_0
    //   478: goto -385 -> 93
    // Local variable table:
    //   start	length	slot	name	signature
    //   0	481	0	paramString	String
    //   0	481	1	paramContext	Context
    //   0	481	2	paramdn	dn
    //   6	2	3	bool	boolean
    //   35	319	4	arrayOfByte	byte[]
    //   47	209	5	localObject1	Object
    //   114	161	6	localObject2	Object
    //   207	92	7	localClass1	Class
    //   221	107	8	localClass2	Class
    //   152	200	9	localObject3	Object
    // Exception table:
    //   from	to	target	type
    //   27	54	82	java/io/FileNotFoundException
    //   60	68	82	java/io/FileNotFoundException
    //   74	82	82	java/io/FileNotFoundException
    //   97	405	82	java/io/FileNotFoundException
    //   11	27	92	com/google/android/gms/internal/de
    //   27	54	92	com/google/android/gms/internal/de
    //   60	68	92	com/google/android/gms/internal/de
    //   74	82	92	com/google/android/gms/internal/de
    //   83	92	92	com/google/android/gms/internal/de
    //   97	405	92	com/google/android/gms/internal/de
    //   405	418	92	com/google/android/gms/internal/de
    //   422	431	92	com/google/android/gms/internal/de
    //   438	447	92	com/google/android/gms/internal/de
    //   448	457	92	com/google/android/gms/internal/de
    //   458	467	92	com/google/android/gms/internal/de
    //   468	477	92	com/google/android/gms/internal/de
    //   27	54	421	java/io/IOException
    //   60	68	421	java/io/IOException
    //   74	82	421	java/io/IOException
    //   97	405	421	java/io/IOException
    //   3	7	431	finally
    //   11	27	431	finally
    //   27	54	431	finally
    //   60	68	431	finally
    //   74	82	431	finally
    //   83	92	431	finally
    //   97	405	431	finally
    //   405	418	431	finally
    //   422	431	431	finally
    //   438	447	431	finally
    //   448	457	431	finally
    //   458	467	431	finally
    //   468	477	431	finally
    //   27	54	437	java/lang/ClassNotFoundException
    //   60	68	437	java/lang/ClassNotFoundException
    //   74	82	437	java/lang/ClassNotFoundException
    //   97	405	437	java/lang/ClassNotFoundException
    //   27	54	447	com/google/android/gms/internal/dq
    //   60	68	447	com/google/android/gms/internal/dq
    //   74	82	447	com/google/android/gms/internal/dq
    //   97	405	447	com/google/android/gms/internal/dq
    //   27	54	457	java/lang/NoSuchMethodException
    //   60	68	457	java/lang/NoSuchMethodException
    //   74	82	457	java/lang/NoSuchMethodException
    //   97	405	457	java/lang/NoSuchMethodException
    //   27	54	467	java/lang/NullPointerException
    //   60	68	467	java/lang/NullPointerException
    //   74	82	467	java/lang/NullPointerException
    //   97	405	467	java/lang/NullPointerException
    //   11	27	477	java/lang/UnsupportedOperationException
    //   27	54	477	java/lang/UnsupportedOperationException
    //   60	68	477	java/lang/UnsupportedOperationException
    //   74	82	477	java/lang/UnsupportedOperationException
    //   83	92	477	java/lang/UnsupportedOperationException
    //   97	405	477	java/lang/UnsupportedOperationException
    //   405	418	477	java/lang/UnsupportedOperationException
    //   422	431	477	java/lang/UnsupportedOperationException
    //   438	447	477	java/lang/UnsupportedOperationException
    //   448	457	477	java/lang/UnsupportedOperationException
    //   458	467	477	java/lang/UnsupportedOperationException
    //   468	477	477	java/lang/UnsupportedOperationException
  }
  
  private static Long b()
  {
    if (d == null) {
      throw new de();
    }
    try
    {
      Long localLong = (Long)d.invoke(null, new Object[0]);
      return localLong;
    }
    catch (IllegalAccessException localIllegalAccessException)
    {
      throw new de(localIllegalAccessException);
    }
    catch (InvocationTargetException localInvocationTargetException)
    {
      throw new de(localInvocationTargetException);
    }
  }
  
  private static String b(Context paramContext, dn paramdn)
  {
    if (i == null) {
      throw new de();
    }
    try
    {
      paramContext = (ByteBuffer)i.invoke(null, new Object[] { paramContext });
      if (paramContext == null) {
        throw new de();
      }
    }
    catch (IllegalAccessException paramContext)
    {
      throw new de(paramContext);
      paramContext = paramdn.a(paramContext.array(), true);
      return paramContext;
    }
    catch (InvocationTargetException paramContext)
    {
      throw new de(paramContext);
    }
  }
  
  private static String c()
  {
    if (e == null) {
      throw new de();
    }
    try
    {
      String str = (String)e.invoke(null, new Object[0]);
      return str;
    }
    catch (IllegalAccessException localIllegalAccessException)
    {
      throw new de(localIllegalAccessException);
    }
    catch (InvocationTargetException localInvocationTargetException)
    {
      throw new de(localInvocationTargetException);
    }
  }
  
  private static String d(Context paramContext)
  {
    if (h == null) {
      throw new de();
    }
    try
    {
      paramContext = (String)h.invoke(null, new Object[] { paramContext });
      if (paramContext == null) {
        throw new de();
      }
    }
    catch (IllegalAccessException paramContext)
    {
      throw new de(paramContext);
    }
    catch (InvocationTargetException paramContext)
    {
      throw new de(paramContext);
    }
    return paramContext;
  }
  
  /* Error */
  protected void b(Context paramContext)
  {
    // Byte code:
    //   0: aload_0
    //   1: iconst_1
    //   2: invokestatic 239	com/google/android/gms/internal/dd:c	()Ljava/lang/String;
    //   5: invokevirtual 242	com/google/android/gms/internal/dd:a	(ILjava/lang/String;)V
    //   8: aload_0
    //   9: iconst_2
    //   10: invokestatic 244	com/google/android/gms/internal/dd:a	()Ljava/lang/String;
    //   13: invokevirtual 242	com/google/android/gms/internal/dd:a	(ILjava/lang/String;)V
    //   16: aload_0
    //   17: bipush 25
    //   19: invokestatic 228	com/google/android/gms/internal/dd:b	()Ljava/lang/Long;
    //   22: invokevirtual 234	java/lang/Long:longValue	()J
    //   25: invokevirtual 247	com/google/android/gms/internal/dd:a	(IJ)V
    //   28: aload_0
    //   29: bipush 24
    //   31: aload_1
    //   32: invokestatic 249	com/google/android/gms/internal/dd:d	(Landroid/content/Context;)Ljava/lang/String;
    //   35: invokevirtual 242	com/google/android/gms/internal/dd:a	(ILjava/lang/String;)V
    //   38: return
    //   39: astore_1
    //   40: return
    //   41: astore_1
    //   42: return
    //   43: astore_2
    //   44: goto -16 -> 28
    //   47: astore_2
    //   48: goto -32 -> 16
    //   51: astore_2
    //   52: goto -44 -> 8
    // Local variable table:
    //   start	length	slot	name	signature
    //   0	55	0	this	dd
    //   0	55	1	paramContext	Context
    //   43	1	2	localde1	de
    //   47	1	2	localde2	de
    //   51	1	2	localde3	de
    // Exception table:
    //   from	to	target	type
    //   0	8	39	java/io/IOException
    //   8	16	39	java/io/IOException
    //   16	28	39	java/io/IOException
    //   28	38	39	java/io/IOException
    //   28	38	41	com/google/android/gms/internal/de
    //   16	28	43	com/google/android/gms/internal/de
    //   8	16	47	com/google/android/gms/internal/de
    //   0	8	51	com/google/android/gms/internal/de
  }
  
  /* Error */
  protected final void c(Context paramContext)
  {
    // Byte code:
    //   0: aload_0
    //   1: iconst_2
    //   2: invokestatic 244	com/google/android/gms/internal/dd:a	()Ljava/lang/String;
    //   5: invokevirtual 242	com/google/android/gms/internal/dd:a	(ILjava/lang/String;)V
    //   8: aload_0
    //   9: iconst_1
    //   10: invokestatic 239	com/google/android/gms/internal/dd:c	()Ljava/lang/String;
    //   13: invokevirtual 242	com/google/android/gms/internal/dd:a	(ILjava/lang/String;)V
    //   16: invokestatic 228	com/google/android/gms/internal/dd:b	()Ljava/lang/Long;
    //   19: invokevirtual 234	java/lang/Long:longValue	()J
    //   22: lstore_2
    //   23: aload_0
    //   24: bipush 25
    //   26: lload_2
    //   27: invokevirtual 247	com/google/android/gms/internal/dd:a	(IJ)V
    //   30: getstatic 23	com/google/android/gms/internal/dd:k	J
    //   33: lconst_0
    //   34: lcmp
    //   35: ifeq +23 -> 58
    //   38: aload_0
    //   39: bipush 17
    //   41: lload_2
    //   42: getstatic 23	com/google/android/gms/internal/dd:k	J
    //   45: lsub
    //   46: invokevirtual 247	com/google/android/gms/internal/dd:a	(IJ)V
    //   49: aload_0
    //   50: bipush 23
    //   52: getstatic 23	com/google/android/gms/internal/dd:k	J
    //   55: invokevirtual 247	com/google/android/gms/internal/dd:a	(IJ)V
    //   58: aload_0
    //   59: getfield 252	com/google/android/gms/internal/dd:a	Landroid/view/MotionEvent;
    //   62: aload_0
    //   63: getfield 255	com/google/android/gms/internal/dd:b	Landroid/util/DisplayMetrics;
    //   66: invokestatic 257	com/google/android/gms/internal/dd:a	(Landroid/view/MotionEvent;Landroid/util/DisplayMetrics;)Ljava/util/ArrayList;
    //   69: astore 4
    //   71: aload_0
    //   72: bipush 14
    //   74: aload 4
    //   76: iconst_0
    //   77: invokevirtual 261	java/util/ArrayList:get	(I)Ljava/lang/Object;
    //   80: checkcast 230	java/lang/Long
    //   83: invokevirtual 234	java/lang/Long:longValue	()J
    //   86: invokevirtual 247	com/google/android/gms/internal/dd:a	(IJ)V
    //   89: aload_0
    //   90: bipush 15
    //   92: aload 4
    //   94: iconst_1
    //   95: invokevirtual 261	java/util/ArrayList:get	(I)Ljava/lang/Object;
    //   98: checkcast 230	java/lang/Long
    //   101: invokevirtual 234	java/lang/Long:longValue	()J
    //   104: invokevirtual 247	com/google/android/gms/internal/dd:a	(IJ)V
    //   107: aload 4
    //   109: invokevirtual 265	java/util/ArrayList:size	()I
    //   112: iconst_3
    //   113: if_icmplt +21 -> 134
    //   116: aload_0
    //   117: bipush 16
    //   119: aload 4
    //   121: iconst_2
    //   122: invokevirtual 261	java/util/ArrayList:get	(I)Ljava/lang/Object;
    //   125: checkcast 230	java/lang/Long
    //   128: invokevirtual 234	java/lang/Long:longValue	()J
    //   131: invokevirtual 247	com/google/android/gms/internal/dd:a	(IJ)V
    //   134: aload_0
    //   135: bipush 27
    //   137: aload_1
    //   138: aload_0
    //   139: getfield 268	com/google/android/gms/internal/dd:c	Lcom/google/android/gms/internal/dn;
    //   142: invokestatic 270	com/google/android/gms/internal/dd:a	(Landroid/content/Context;Lcom/google/android/gms/internal/dn;)Ljava/lang/String;
    //   145: invokevirtual 242	com/google/android/gms/internal/dd:a	(ILjava/lang/String;)V
    //   148: aload_0
    //   149: bipush 29
    //   151: aload_1
    //   152: aload_0
    //   153: getfield 268	com/google/android/gms/internal/dd:c	Lcom/google/android/gms/internal/dn;
    //   156: invokestatic 272	com/google/android/gms/internal/dd:b	(Landroid/content/Context;Lcom/google/android/gms/internal/dn;)Ljava/lang/String;
    //   159: invokevirtual 242	com/google/android/gms/internal/dd:a	(ILjava/lang/String;)V
    //   162: return
    //   163: astore_1
    //   164: return
    //   165: astore_1
    //   166: return
    //   167: astore 4
    //   169: goto -21 -> 148
    //   172: astore 4
    //   174: goto -40 -> 134
    //   177: astore 4
    //   179: goto -121 -> 58
    //   182: astore 4
    //   184: goto -168 -> 16
    //   187: astore 4
    //   189: goto -181 -> 8
    // Local variable table:
    //   start	length	slot	name	signature
    //   0	192	0	this	dd
    //   0	192	1	paramContext	Context
    //   22	20	2	l1	long
    //   69	51	4	localArrayList	ArrayList
    //   167	1	4	localde1	de
    //   172	1	4	localde2	de
    //   177	1	4	localde3	de
    //   182	1	4	localde4	de
    //   187	1	4	localde5	de
    // Exception table:
    //   from	to	target	type
    //   0	8	163	java/io/IOException
    //   8	16	163	java/io/IOException
    //   16	58	163	java/io/IOException
    //   58	134	163	java/io/IOException
    //   134	148	163	java/io/IOException
    //   148	162	163	java/io/IOException
    //   148	162	165	com/google/android/gms/internal/de
    //   134	148	167	com/google/android/gms/internal/de
    //   58	134	172	com/google/android/gms/internal/de
    //   16	58	177	com/google/android/gms/internal/de
    //   8	16	182	com/google/android/gms/internal/de
    //   0	8	187	com/google/android/gms/internal/de
  }
}


/* Location:              /Users/amaurremi/uw/stringoid/static-dynamic-comparison/apps/mp3 cutter/com.atomic.apps.ringtone.cutter-100007-dex2jar.jar!/com/google/android/gms/internal/dd.class
 * Java compiler version: 6 (50.0)
 * JD-Core Version:       0.7.1
 */