package com.google.android.gms.drive.internal;

import android.os.IBinder;
import android.os.Parcel;
import com.google.android.gms.drive.realtime.internal.m;

class az
  implements ab
{
  private IBinder a;
  
  az(IBinder paramIBinder)
  {
    this.a = paramIBinder;
  }
  
  /* Error */
  public void a(OnContentsResponse paramOnContentsResponse)
  {
    // Byte code:
    //   0: invokestatic 23	android/os/Parcel:obtain	()Landroid/os/Parcel;
    //   3: astore_2
    //   4: invokestatic 23	android/os/Parcel:obtain	()Landroid/os/Parcel;
    //   7: astore_3
    //   8: aload_2
    //   9: ldc 25
    //   11: invokevirtual 29	android/os/Parcel:writeInterfaceToken	(Ljava/lang/String;)V
    //   14: aload_1
    //   15: ifnull +41 -> 56
    //   18: aload_2
    //   19: iconst_1
    //   20: invokevirtual 33	android/os/Parcel:writeInt	(I)V
    //   23: aload_1
    //   24: aload_2
    //   25: iconst_0
    //   26: invokevirtual 39	com/google/android/gms/drive/internal/OnContentsResponse:writeToParcel	(Landroid/os/Parcel;I)V
    //   29: aload_0
    //   30: getfield 15	com/google/android/gms/drive/internal/az:a	Landroid/os/IBinder;
    //   33: iconst_5
    //   34: aload_2
    //   35: aload_3
    //   36: iconst_0
    //   37: invokeinterface 45 5 0
    //   42: pop
    //   43: aload_3
    //   44: invokevirtual 48	android/os/Parcel:readException	()V
    //   47: aload_3
    //   48: invokevirtual 51	android/os/Parcel:recycle	()V
    //   51: aload_2
    //   52: invokevirtual 51	android/os/Parcel:recycle	()V
    //   55: return
    //   56: aload_2
    //   57: iconst_0
    //   58: invokevirtual 33	android/os/Parcel:writeInt	(I)V
    //   61: goto -32 -> 29
    //   64: astore_1
    //   65: aload_3
    //   66: invokevirtual 51	android/os/Parcel:recycle	()V
    //   69: aload_2
    //   70: invokevirtual 51	android/os/Parcel:recycle	()V
    //   73: aload_1
    //   74: athrow
    // Local variable table:
    //   start	length	slot	name	signature
    //   0	75	0	this	az
    //   0	75	1	paramOnContentsResponse	OnContentsResponse
    //   3	67	2	localParcel1	Parcel
    //   7	59	3	localParcel2	Parcel
    // Exception table:
    //   from	to	target	type
    //   8	14	64	finally
    //   18	29	64	finally
    //   29	47	64	finally
    //   56	61	64	finally
  }
  
  /* Error */
  public void a(OnDownloadProgressResponse paramOnDownloadProgressResponse)
  {
    // Byte code:
    //   0: invokestatic 23	android/os/Parcel:obtain	()Landroid/os/Parcel;
    //   3: astore_2
    //   4: invokestatic 23	android/os/Parcel:obtain	()Landroid/os/Parcel;
    //   7: astore_3
    //   8: aload_2
    //   9: ldc 25
    //   11: invokevirtual 29	android/os/Parcel:writeInterfaceToken	(Ljava/lang/String;)V
    //   14: aload_1
    //   15: ifnull +41 -> 56
    //   18: aload_2
    //   19: iconst_1
    //   20: invokevirtual 33	android/os/Parcel:writeInt	(I)V
    //   23: aload_1
    //   24: aload_2
    //   25: iconst_0
    //   26: invokevirtual 55	com/google/android/gms/drive/internal/OnDownloadProgressResponse:writeToParcel	(Landroid/os/Parcel;I)V
    //   29: aload_0
    //   30: getfield 15	com/google/android/gms/drive/internal/az:a	Landroid/os/IBinder;
    //   33: iconst_1
    //   34: aload_2
    //   35: aload_3
    //   36: iconst_0
    //   37: invokeinterface 45 5 0
    //   42: pop
    //   43: aload_3
    //   44: invokevirtual 48	android/os/Parcel:readException	()V
    //   47: aload_3
    //   48: invokevirtual 51	android/os/Parcel:recycle	()V
    //   51: aload_2
    //   52: invokevirtual 51	android/os/Parcel:recycle	()V
    //   55: return
    //   56: aload_2
    //   57: iconst_0
    //   58: invokevirtual 33	android/os/Parcel:writeInt	(I)V
    //   61: goto -32 -> 29
    //   64: astore_1
    //   65: aload_3
    //   66: invokevirtual 51	android/os/Parcel:recycle	()V
    //   69: aload_2
    //   70: invokevirtual 51	android/os/Parcel:recycle	()V
    //   73: aload_1
    //   74: athrow
    // Local variable table:
    //   start	length	slot	name	signature
    //   0	75	0	this	az
    //   0	75	1	paramOnDownloadProgressResponse	OnDownloadProgressResponse
    //   3	67	2	localParcel1	Parcel
    //   7	59	3	localParcel2	Parcel
    // Exception table:
    //   from	to	target	type
    //   8	14	64	finally
    //   18	29	64	finally
    //   29	47	64	finally
    //   56	61	64	finally
  }
  
  /* Error */
  public void a(OnDriveIdResponse paramOnDriveIdResponse)
  {
    // Byte code:
    //   0: invokestatic 23	android/os/Parcel:obtain	()Landroid/os/Parcel;
    //   3: astore_2
    //   4: invokestatic 23	android/os/Parcel:obtain	()Landroid/os/Parcel;
    //   7: astore_3
    //   8: aload_2
    //   9: ldc 25
    //   11: invokevirtual 29	android/os/Parcel:writeInterfaceToken	(Ljava/lang/String;)V
    //   14: aload_1
    //   15: ifnull +41 -> 56
    //   18: aload_2
    //   19: iconst_1
    //   20: invokevirtual 33	android/os/Parcel:writeInt	(I)V
    //   23: aload_1
    //   24: aload_2
    //   25: iconst_0
    //   26: invokevirtual 59	com/google/android/gms/drive/internal/OnDriveIdResponse:writeToParcel	(Landroid/os/Parcel;I)V
    //   29: aload_0
    //   30: getfield 15	com/google/android/gms/drive/internal/az:a	Landroid/os/IBinder;
    //   33: iconst_3
    //   34: aload_2
    //   35: aload_3
    //   36: iconst_0
    //   37: invokeinterface 45 5 0
    //   42: pop
    //   43: aload_3
    //   44: invokevirtual 48	android/os/Parcel:readException	()V
    //   47: aload_3
    //   48: invokevirtual 51	android/os/Parcel:recycle	()V
    //   51: aload_2
    //   52: invokevirtual 51	android/os/Parcel:recycle	()V
    //   55: return
    //   56: aload_2
    //   57: iconst_0
    //   58: invokevirtual 33	android/os/Parcel:writeInt	(I)V
    //   61: goto -32 -> 29
    //   64: astore_1
    //   65: aload_3
    //   66: invokevirtual 51	android/os/Parcel:recycle	()V
    //   69: aload_2
    //   70: invokevirtual 51	android/os/Parcel:recycle	()V
    //   73: aload_1
    //   74: athrow
    // Local variable table:
    //   start	length	slot	name	signature
    //   0	75	0	this	az
    //   0	75	1	paramOnDriveIdResponse	OnDriveIdResponse
    //   3	67	2	localParcel1	Parcel
    //   7	59	3	localParcel2	Parcel
    // Exception table:
    //   from	to	target	type
    //   8	14	64	finally
    //   18	29	64	finally
    //   29	47	64	finally
    //   56	61	64	finally
  }
  
  /* Error */
  public void a(OnListEntriesResponse paramOnListEntriesResponse)
  {
    // Byte code:
    //   0: invokestatic 23	android/os/Parcel:obtain	()Landroid/os/Parcel;
    //   3: astore_2
    //   4: invokestatic 23	android/os/Parcel:obtain	()Landroid/os/Parcel;
    //   7: astore_3
    //   8: aload_2
    //   9: ldc 25
    //   11: invokevirtual 29	android/os/Parcel:writeInterfaceToken	(Ljava/lang/String;)V
    //   14: aload_1
    //   15: ifnull +41 -> 56
    //   18: aload_2
    //   19: iconst_1
    //   20: invokevirtual 33	android/os/Parcel:writeInt	(I)V
    //   23: aload_1
    //   24: aload_2
    //   25: iconst_0
    //   26: invokevirtual 63	com/google/android/gms/drive/internal/OnListEntriesResponse:writeToParcel	(Landroid/os/Parcel;I)V
    //   29: aload_0
    //   30: getfield 15	com/google/android/gms/drive/internal/az:a	Landroid/os/IBinder;
    //   33: iconst_2
    //   34: aload_2
    //   35: aload_3
    //   36: iconst_0
    //   37: invokeinterface 45 5 0
    //   42: pop
    //   43: aload_3
    //   44: invokevirtual 48	android/os/Parcel:readException	()V
    //   47: aload_3
    //   48: invokevirtual 51	android/os/Parcel:recycle	()V
    //   51: aload_2
    //   52: invokevirtual 51	android/os/Parcel:recycle	()V
    //   55: return
    //   56: aload_2
    //   57: iconst_0
    //   58: invokevirtual 33	android/os/Parcel:writeInt	(I)V
    //   61: goto -32 -> 29
    //   64: astore_1
    //   65: aload_3
    //   66: invokevirtual 51	android/os/Parcel:recycle	()V
    //   69: aload_2
    //   70: invokevirtual 51	android/os/Parcel:recycle	()V
    //   73: aload_1
    //   74: athrow
    // Local variable table:
    //   start	length	slot	name	signature
    //   0	75	0	this	az
    //   0	75	1	paramOnListEntriesResponse	OnListEntriesResponse
    //   3	67	2	localParcel1	Parcel
    //   7	59	3	localParcel2	Parcel
    // Exception table:
    //   from	to	target	type
    //   8	14	64	finally
    //   18	29	64	finally
    //   29	47	64	finally
    //   56	61	64	finally
  }
  
  /* Error */
  public void a(OnListParentsResponse paramOnListParentsResponse)
  {
    // Byte code:
    //   0: invokestatic 23	android/os/Parcel:obtain	()Landroid/os/Parcel;
    //   3: astore_2
    //   4: invokestatic 23	android/os/Parcel:obtain	()Landroid/os/Parcel;
    //   7: astore_3
    //   8: aload_2
    //   9: ldc 25
    //   11: invokevirtual 29	android/os/Parcel:writeInterfaceToken	(Ljava/lang/String;)V
    //   14: aload_1
    //   15: ifnull +42 -> 57
    //   18: aload_2
    //   19: iconst_1
    //   20: invokevirtual 33	android/os/Parcel:writeInt	(I)V
    //   23: aload_1
    //   24: aload_2
    //   25: iconst_0
    //   26: invokevirtual 67	com/google/android/gms/drive/internal/OnListParentsResponse:writeToParcel	(Landroid/os/Parcel;I)V
    //   29: aload_0
    //   30: getfield 15	com/google/android/gms/drive/internal/az:a	Landroid/os/IBinder;
    //   33: bipush 8
    //   35: aload_2
    //   36: aload_3
    //   37: iconst_0
    //   38: invokeinterface 45 5 0
    //   43: pop
    //   44: aload_3
    //   45: invokevirtual 48	android/os/Parcel:readException	()V
    //   48: aload_3
    //   49: invokevirtual 51	android/os/Parcel:recycle	()V
    //   52: aload_2
    //   53: invokevirtual 51	android/os/Parcel:recycle	()V
    //   56: return
    //   57: aload_2
    //   58: iconst_0
    //   59: invokevirtual 33	android/os/Parcel:writeInt	(I)V
    //   62: goto -33 -> 29
    //   65: astore_1
    //   66: aload_3
    //   67: invokevirtual 51	android/os/Parcel:recycle	()V
    //   70: aload_2
    //   71: invokevirtual 51	android/os/Parcel:recycle	()V
    //   74: aload_1
    //   75: athrow
    // Local variable table:
    //   start	length	slot	name	signature
    //   0	76	0	this	az
    //   0	76	1	paramOnListParentsResponse	OnListParentsResponse
    //   3	68	2	localParcel1	Parcel
    //   7	60	3	localParcel2	Parcel
    // Exception table:
    //   from	to	target	type
    //   8	14	65	finally
    //   18	29	65	finally
    //   29	48	65	finally
    //   57	62	65	finally
  }
  
  public void a(OnLoadRealtimeResponse paramOnLoadRealtimeResponse, m paramm)
  {
    Parcel localParcel1 = Parcel.obtain();
    Parcel localParcel2 = Parcel.obtain();
    for (;;)
    {
      try
      {
        localParcel1.writeInterfaceToken("com.google.android.gms.drive.internal.IDriveServiceCallbacks");
        if (paramOnLoadRealtimeResponse != null)
        {
          localParcel1.writeInt(1);
          paramOnLoadRealtimeResponse.writeToParcel(localParcel1, 0);
          if (paramm != null)
          {
            paramOnLoadRealtimeResponse = paramm.asBinder();
            localParcel1.writeStrongBinder(paramOnLoadRealtimeResponse);
            this.a.transact(11, localParcel1, localParcel2, 0);
            localParcel2.readException();
          }
        }
        else
        {
          localParcel1.writeInt(0);
          continue;
        }
        paramOnLoadRealtimeResponse = null;
      }
      finally
      {
        localParcel2.recycle();
        localParcel1.recycle();
      }
    }
  }
  
  /* Error */
  public void a(OnMetadataResponse paramOnMetadataResponse)
  {
    // Byte code:
    //   0: invokestatic 23	android/os/Parcel:obtain	()Landroid/os/Parcel;
    //   3: astore_2
    //   4: invokestatic 23	android/os/Parcel:obtain	()Landroid/os/Parcel;
    //   7: astore_3
    //   8: aload_2
    //   9: ldc 25
    //   11: invokevirtual 29	android/os/Parcel:writeInterfaceToken	(Ljava/lang/String;)V
    //   14: aload_1
    //   15: ifnull +41 -> 56
    //   18: aload_2
    //   19: iconst_1
    //   20: invokevirtual 33	android/os/Parcel:writeInt	(I)V
    //   23: aload_1
    //   24: aload_2
    //   25: iconst_0
    //   26: invokevirtual 84	com/google/android/gms/drive/internal/OnMetadataResponse:writeToParcel	(Landroid/os/Parcel;I)V
    //   29: aload_0
    //   30: getfield 15	com/google/android/gms/drive/internal/az:a	Landroid/os/IBinder;
    //   33: iconst_4
    //   34: aload_2
    //   35: aload_3
    //   36: iconst_0
    //   37: invokeinterface 45 5 0
    //   42: pop
    //   43: aload_3
    //   44: invokevirtual 48	android/os/Parcel:readException	()V
    //   47: aload_3
    //   48: invokevirtual 51	android/os/Parcel:recycle	()V
    //   51: aload_2
    //   52: invokevirtual 51	android/os/Parcel:recycle	()V
    //   55: return
    //   56: aload_2
    //   57: iconst_0
    //   58: invokevirtual 33	android/os/Parcel:writeInt	(I)V
    //   61: goto -32 -> 29
    //   64: astore_1
    //   65: aload_3
    //   66: invokevirtual 51	android/os/Parcel:recycle	()V
    //   69: aload_2
    //   70: invokevirtual 51	android/os/Parcel:recycle	()V
    //   73: aload_1
    //   74: athrow
    // Local variable table:
    //   start	length	slot	name	signature
    //   0	75	0	this	az
    //   0	75	1	paramOnMetadataResponse	OnMetadataResponse
    //   3	67	2	localParcel1	Parcel
    //   7	59	3	localParcel2	Parcel
    // Exception table:
    //   from	to	target	type
    //   8	14	64	finally
    //   18	29	64	finally
    //   29	47	64	finally
    //   56	61	64	finally
  }
  
  /* Error */
  public void a(OnResourceIdSetResponse paramOnResourceIdSetResponse)
  {
    // Byte code:
    //   0: invokestatic 23	android/os/Parcel:obtain	()Landroid/os/Parcel;
    //   3: astore_2
    //   4: invokestatic 23	android/os/Parcel:obtain	()Landroid/os/Parcel;
    //   7: astore_3
    //   8: aload_2
    //   9: ldc 25
    //   11: invokevirtual 29	android/os/Parcel:writeInterfaceToken	(Ljava/lang/String;)V
    //   14: aload_1
    //   15: ifnull +42 -> 57
    //   18: aload_2
    //   19: iconst_1
    //   20: invokevirtual 33	android/os/Parcel:writeInt	(I)V
    //   23: aload_1
    //   24: aload_2
    //   25: iconst_0
    //   26: invokevirtual 88	com/google/android/gms/drive/internal/OnResourceIdSetResponse:writeToParcel	(Landroid/os/Parcel;I)V
    //   29: aload_0
    //   30: getfield 15	com/google/android/gms/drive/internal/az:a	Landroid/os/IBinder;
    //   33: bipush 12
    //   35: aload_2
    //   36: aload_3
    //   37: iconst_0
    //   38: invokeinterface 45 5 0
    //   43: pop
    //   44: aload_3
    //   45: invokevirtual 48	android/os/Parcel:readException	()V
    //   48: aload_3
    //   49: invokevirtual 51	android/os/Parcel:recycle	()V
    //   52: aload_2
    //   53: invokevirtual 51	android/os/Parcel:recycle	()V
    //   56: return
    //   57: aload_2
    //   58: iconst_0
    //   59: invokevirtual 33	android/os/Parcel:writeInt	(I)V
    //   62: goto -33 -> 29
    //   65: astore_1
    //   66: aload_3
    //   67: invokevirtual 51	android/os/Parcel:recycle	()V
    //   70: aload_2
    //   71: invokevirtual 51	android/os/Parcel:recycle	()V
    //   74: aload_1
    //   75: athrow
    // Local variable table:
    //   start	length	slot	name	signature
    //   0	76	0	this	az
    //   0	76	1	paramOnResourceIdSetResponse	OnResourceIdSetResponse
    //   3	68	2	localParcel1	Parcel
    //   7	60	3	localParcel2	Parcel
    // Exception table:
    //   from	to	target	type
    //   8	14	65	finally
    //   18	29	65	finally
    //   29	48	65	finally
    //   57	62	65	finally
  }
  
  /* Error */
  public void a(OnStorageStatsResponse paramOnStorageStatsResponse)
  {
    // Byte code:
    //   0: invokestatic 23	android/os/Parcel:obtain	()Landroid/os/Parcel;
    //   3: astore_2
    //   4: invokestatic 23	android/os/Parcel:obtain	()Landroid/os/Parcel;
    //   7: astore_3
    //   8: aload_2
    //   9: ldc 25
    //   11: invokevirtual 29	android/os/Parcel:writeInterfaceToken	(Ljava/lang/String;)V
    //   14: aload_1
    //   15: ifnull +42 -> 57
    //   18: aload_2
    //   19: iconst_1
    //   20: invokevirtual 33	android/os/Parcel:writeInt	(I)V
    //   23: aload_1
    //   24: aload_2
    //   25: iconst_0
    //   26: invokevirtual 92	com/google/android/gms/drive/internal/OnStorageStatsResponse:writeToParcel	(Landroid/os/Parcel;I)V
    //   29: aload_0
    //   30: getfield 15	com/google/android/gms/drive/internal/az:a	Landroid/os/IBinder;
    //   33: bipush 10
    //   35: aload_2
    //   36: aload_3
    //   37: iconst_0
    //   38: invokeinterface 45 5 0
    //   43: pop
    //   44: aload_3
    //   45: invokevirtual 48	android/os/Parcel:readException	()V
    //   48: aload_3
    //   49: invokevirtual 51	android/os/Parcel:recycle	()V
    //   52: aload_2
    //   53: invokevirtual 51	android/os/Parcel:recycle	()V
    //   56: return
    //   57: aload_2
    //   58: iconst_0
    //   59: invokevirtual 33	android/os/Parcel:writeInt	(I)V
    //   62: goto -33 -> 29
    //   65: astore_1
    //   66: aload_3
    //   67: invokevirtual 51	android/os/Parcel:recycle	()V
    //   70: aload_2
    //   71: invokevirtual 51	android/os/Parcel:recycle	()V
    //   74: aload_1
    //   75: athrow
    // Local variable table:
    //   start	length	slot	name	signature
    //   0	76	0	this	az
    //   0	76	1	paramOnStorageStatsResponse	OnStorageStatsResponse
    //   3	68	2	localParcel1	Parcel
    //   7	60	3	localParcel2	Parcel
    // Exception table:
    //   from	to	target	type
    //   8	14	65	finally
    //   18	29	65	finally
    //   29	48	65	finally
    //   57	62	65	finally
  }
  
  /* Error */
  public void a(OnSyncMoreResponse paramOnSyncMoreResponse)
  {
    // Byte code:
    //   0: invokestatic 23	android/os/Parcel:obtain	()Landroid/os/Parcel;
    //   3: astore_2
    //   4: invokestatic 23	android/os/Parcel:obtain	()Landroid/os/Parcel;
    //   7: astore_3
    //   8: aload_2
    //   9: ldc 25
    //   11: invokevirtual 29	android/os/Parcel:writeInterfaceToken	(Ljava/lang/String;)V
    //   14: aload_1
    //   15: ifnull +42 -> 57
    //   18: aload_2
    //   19: iconst_1
    //   20: invokevirtual 33	android/os/Parcel:writeInt	(I)V
    //   23: aload_1
    //   24: aload_2
    //   25: iconst_0
    //   26: invokevirtual 96	com/google/android/gms/drive/internal/OnSyncMoreResponse:writeToParcel	(Landroid/os/Parcel;I)V
    //   29: aload_0
    //   30: getfield 15	com/google/android/gms/drive/internal/az:a	Landroid/os/IBinder;
    //   33: bipush 9
    //   35: aload_2
    //   36: aload_3
    //   37: iconst_0
    //   38: invokeinterface 45 5 0
    //   43: pop
    //   44: aload_3
    //   45: invokevirtual 48	android/os/Parcel:readException	()V
    //   48: aload_3
    //   49: invokevirtual 51	android/os/Parcel:recycle	()V
    //   52: aload_2
    //   53: invokevirtual 51	android/os/Parcel:recycle	()V
    //   56: return
    //   57: aload_2
    //   58: iconst_0
    //   59: invokevirtual 33	android/os/Parcel:writeInt	(I)V
    //   62: goto -33 -> 29
    //   65: astore_1
    //   66: aload_3
    //   67: invokevirtual 51	android/os/Parcel:recycle	()V
    //   70: aload_2
    //   71: invokevirtual 51	android/os/Parcel:recycle	()V
    //   74: aload_1
    //   75: athrow
    // Local variable table:
    //   start	length	slot	name	signature
    //   0	76	0	this	az
    //   0	76	1	paramOnSyncMoreResponse	OnSyncMoreResponse
    //   3	68	2	localParcel1	Parcel
    //   7	60	3	localParcel2	Parcel
    // Exception table:
    //   from	to	target	type
    //   8	14	65	finally
    //   18	29	65	finally
    //   29	48	65	finally
    //   57	62	65	finally
  }
  
  public IBinder asBinder()
  {
    return this.a;
  }
  
  /* Error */
  public void o(com.google.android.gms.common.api.Status paramStatus)
  {
    // Byte code:
    //   0: invokestatic 23	android/os/Parcel:obtain	()Landroid/os/Parcel;
    //   3: astore_2
    //   4: invokestatic 23	android/os/Parcel:obtain	()Landroid/os/Parcel;
    //   7: astore_3
    //   8: aload_2
    //   9: ldc 25
    //   11: invokevirtual 29	android/os/Parcel:writeInterfaceToken	(Ljava/lang/String;)V
    //   14: aload_1
    //   15: ifnull +42 -> 57
    //   18: aload_2
    //   19: iconst_1
    //   20: invokevirtual 33	android/os/Parcel:writeInt	(I)V
    //   23: aload_1
    //   24: aload_2
    //   25: iconst_0
    //   26: invokevirtual 101	com/google/android/gms/common/api/Status:writeToParcel	(Landroid/os/Parcel;I)V
    //   29: aload_0
    //   30: getfield 15	com/google/android/gms/drive/internal/az:a	Landroid/os/IBinder;
    //   33: bipush 6
    //   35: aload_2
    //   36: aload_3
    //   37: iconst_0
    //   38: invokeinterface 45 5 0
    //   43: pop
    //   44: aload_3
    //   45: invokevirtual 48	android/os/Parcel:readException	()V
    //   48: aload_3
    //   49: invokevirtual 51	android/os/Parcel:recycle	()V
    //   52: aload_2
    //   53: invokevirtual 51	android/os/Parcel:recycle	()V
    //   56: return
    //   57: aload_2
    //   58: iconst_0
    //   59: invokevirtual 33	android/os/Parcel:writeInt	(I)V
    //   62: goto -33 -> 29
    //   65: astore_1
    //   66: aload_3
    //   67: invokevirtual 51	android/os/Parcel:recycle	()V
    //   70: aload_2
    //   71: invokevirtual 51	android/os/Parcel:recycle	()V
    //   74: aload_1
    //   75: athrow
    // Local variable table:
    //   start	length	slot	name	signature
    //   0	76	0	this	az
    //   0	76	1	paramStatus	com.google.android.gms.common.api.Status
    //   3	68	2	localParcel1	Parcel
    //   7	60	3	localParcel2	Parcel
    // Exception table:
    //   from	to	target	type
    //   8	14	65	finally
    //   18	29	65	finally
    //   29	48	65	finally
    //   57	62	65	finally
  }
  
  public void onSuccess()
  {
    Parcel localParcel1 = Parcel.obtain();
    Parcel localParcel2 = Parcel.obtain();
    try
    {
      localParcel1.writeInterfaceToken("com.google.android.gms.drive.internal.IDriveServiceCallbacks");
      this.a.transact(7, localParcel1, localParcel2, 0);
      localParcel2.readException();
      return;
    }
    finally
    {
      localParcel2.recycle();
      localParcel1.recycle();
    }
  }
}


/* Location:              /Users/amaurremi/uw/stringoid/static-dynamic-comparison/apps/retrica/com.venticake.retrica-21-dex2jar.jar!/com/google/android/gms/drive/internal/az.class
 * Java compiler version: 6 (50.0)
 * JD-Core Version:       0.7.1
 */