package com.gau.go.launcherex.gowidget.statistics;

class m
  implements Runnable
{
  m(j paramj) {}
  
  /* Error */
  public void run()
  {
    // Byte code:
    //   0: ldc2_w 26
    //   3: lstore_1
    //   4: invokestatic 33	java/lang/System:currentTimeMillis	()J
    //   7: lstore 5
    //   9: aload_0
    //   10: getfield 12	com/gau/go/launcherex/gowidget/statistics/m:a	Lcom/gau/go/launcherex/gowidget/statistics/j;
    //   13: invokestatic 39	com/gau/go/launcherex/gowidget/statistics/j:e	(Lcom/gau/go/launcherex/gowidget/statistics/j;)J
    //   16: lstore_3
    //   17: lload_3
    //   18: lconst_0
    //   19: lcmp
    //   20: ifeq +23 -> 43
    //   23: lload 5
    //   25: lload_3
    //   26: lsub
    //   27: ldc2_w 26
    //   30: lcmp
    //   31: ifge +12 -> 43
    //   34: lload 5
    //   36: lload_3
    //   37: lsub
    //   38: lconst_0
    //   39: lcmp
    //   40: ifgt +731 -> 771
    //   43: invokestatic 44	com/gtp/a/a/a/a:a	()Lcom/gtp/a/a/a/a;
    //   46: ldc 46
    //   48: ldc 48
    //   50: invokevirtual 51	com/gtp/a/a/a/a:a	(Ljava/lang/String;Ljava/lang/String;)V
    //   53: aload_0
    //   54: getfield 12	com/gau/go/launcherex/gowidget/statistics/m:a	Lcom/gau/go/launcherex/gowidget/statistics/j;
    //   57: invokestatic 55	com/gau/go/launcherex/gowidget/statistics/j:b	(Lcom/gau/go/launcherex/gowidget/statistics/j;)Landroid/content/Context;
    //   60: ldc 57
    //   62: invokevirtual 63	android/content/Context:openFileInput	(Ljava/lang/String;)Ljava/io/FileInputStream;
    //   65: astore 8
    //   67: new 65	java/io/InputStreamReader
    //   70: dup
    //   71: aload 8
    //   73: ldc 67
    //   75: invokespecial 70	java/io/InputStreamReader:<init>	(Ljava/io/InputStream;Ljava/lang/String;)V
    //   78: astore 9
    //   80: new 72	java/io/BufferedReader
    //   83: dup
    //   84: aload 9
    //   86: invokespecial 75	java/io/BufferedReader:<init>	(Ljava/io/Reader;)V
    //   89: astore 13
    //   91: aload 13
    //   93: astore 12
    //   95: aload 9
    //   97: astore 11
    //   99: aload 8
    //   101: astore 10
    //   103: new 77	java/lang/StringBuilder
    //   106: dup
    //   107: invokespecial 78	java/lang/StringBuilder:<init>	()V
    //   110: astore 14
    //   112: aload 13
    //   114: astore 12
    //   116: aload 9
    //   118: astore 11
    //   120: aload 8
    //   122: astore 10
    //   124: aload 13
    //   126: invokevirtual 82	java/io/BufferedReader:readLine	()Ljava/lang/String;
    //   129: astore 15
    //   131: aload 15
    //   133: ifnull +161 -> 294
    //   136: aload 13
    //   138: astore 12
    //   140: aload 9
    //   142: astore 11
    //   144: aload 8
    //   146: astore 10
    //   148: aload 14
    //   150: new 77	java/lang/StringBuilder
    //   153: dup
    //   154: invokespecial 78	java/lang/StringBuilder:<init>	()V
    //   157: aload 15
    //   159: invokevirtual 86	java/lang/StringBuilder:append	(Ljava/lang/String;)Ljava/lang/StringBuilder;
    //   162: ldc 88
    //   164: invokevirtual 86	java/lang/StringBuilder:append	(Ljava/lang/String;)Ljava/lang/StringBuilder;
    //   167: invokevirtual 91	java/lang/StringBuilder:toString	()Ljava/lang/String;
    //   170: invokevirtual 86	java/lang/StringBuilder:append	(Ljava/lang/String;)Ljava/lang/StringBuilder;
    //   173: pop
    //   174: goto -62 -> 112
    //   177: astore 14
    //   179: aload 13
    //   181: astore 12
    //   183: aload 9
    //   185: astore 11
    //   187: aload 8
    //   189: astore 10
    //   191: aload 14
    //   193: invokevirtual 94	java/io/UnsupportedEncodingException:printStackTrace	()V
    //   196: aload 13
    //   198: ifnull +8 -> 206
    //   201: aload 13
    //   203: invokevirtual 97	java/io/BufferedReader:close	()V
    //   206: aload 9
    //   208: ifnull +8 -> 216
    //   211: aload 9
    //   213: invokevirtual 98	java/io/InputStreamReader:close	()V
    //   216: aload 8
    //   218: ifnull +8 -> 226
    //   221: aload 8
    //   223: invokevirtual 101	java/io/FileInputStream:close	()V
    //   226: iconst_0
    //   227: istore 7
    //   229: iload 7
    //   231: ifeq +516 -> 747
    //   234: invokestatic 44	com/gtp/a/a/a/a:a	()Lcom/gtp/a/a/a/a;
    //   237: ldc 103
    //   239: ldc 48
    //   241: invokevirtual 51	com/gtp/a/a/a/a:a	(Ljava/lang/String;Ljava/lang/String;)V
    //   244: ldc 105
    //   246: ldc 103
    //   248: invokestatic 108	com/gtp/a/a/b/c:a	(Ljava/lang/String;Ljava/lang/String;)V
    //   251: aload_0
    //   252: getfield 12	com/gau/go/launcherex/gowidget/statistics/m:a	Lcom/gau/go/launcherex/gowidget/statistics/j;
    //   255: invokestatic 55	com/gau/go/launcherex/gowidget/statistics/j:b	(Lcom/gau/go/launcherex/gowidget/statistics/j;)Landroid/content/Context;
    //   258: ldc 57
    //   260: iconst_0
    //   261: invokevirtual 112	android/content/Context:openFileOutput	(Ljava/lang/String;I)Ljava/io/FileOutputStream;
    //   264: astore 8
    //   266: aload 8
    //   268: ifnull +8 -> 276
    //   271: aload 8
    //   273: invokevirtual 115	java/io/FileOutputStream:close	()V
    //   276: aload_0
    //   277: getfield 12	com/gau/go/launcherex/gowidget/statistics/m:a	Lcom/gau/go/launcherex/gowidget/statistics/j;
    //   280: lload 5
    //   282: invokestatic 118	com/gau/go/launcherex/gowidget/statistics/j:a	(Lcom/gau/go/launcherex/gowidget/statistics/j;J)V
    //   285: aload_0
    //   286: getfield 12	com/gau/go/launcherex/gowidget/statistics/m:a	Lcom/gau/go/launcherex/gowidget/statistics/j;
    //   289: lload_1
    //   290: invokestatic 120	com/gau/go/launcherex/gowidget/statistics/j:b	(Lcom/gau/go/launcherex/gowidget/statistics/j;J)V
    //   293: return
    //   294: aload 13
    //   296: astore 12
    //   298: aload 9
    //   300: astore 11
    //   302: aload 8
    //   304: astore 10
    //   306: aload 14
    //   308: invokevirtual 91	java/lang/StringBuilder:toString	()Ljava/lang/String;
    //   311: astore 14
    //   313: aload 13
    //   315: astore 12
    //   317: aload 9
    //   319: astore 11
    //   321: aload 8
    //   323: astore 10
    //   325: aload 14
    //   327: ldc 67
    //   329: invokestatic 126	java/net/URLEncoder:encode	(Ljava/lang/String;Ljava/lang/String;)Ljava/lang/String;
    //   332: astore 15
    //   334: aload 15
    //   336: astore 14
    //   338: aload 14
    //   340: astore 15
    //   342: aload 14
    //   344: ifnull +24 -> 368
    //   347: aload 13
    //   349: astore 12
    //   351: aload 9
    //   353: astore 11
    //   355: aload 8
    //   357: astore 10
    //   359: aload 14
    //   361: ldc -128
    //   363: invokestatic 132	com/gau/go/launcherex/gowidget/statistics/c:a	(Ljava/lang/String;Ljava/lang/String;)Ljava/lang/String;
    //   366: astore 15
    //   368: aload 13
    //   370: astore 12
    //   372: aload 9
    //   374: astore 11
    //   376: aload 8
    //   378: astore 10
    //   380: aload 15
    //   382: aload_0
    //   383: getfield 12	com/gau/go/launcherex/gowidget/statistics/m:a	Lcom/gau/go/launcherex/gowidget/statistics/j;
    //   386: invokestatic 55	com/gau/go/launcherex/gowidget/statistics/j:b	(Lcom/gau/go/launcherex/gowidget/statistics/j;)Landroid/content/Context;
    //   389: iconst_1
    //   390: invokestatic 137	com/gau/go/launcherex/gowidget/statistics/i:a	(Ljava/lang/String;Landroid/content/Context;Z)Z
    //   393: istore 7
    //   395: aload 13
    //   397: ifnull +8 -> 405
    //   400: aload 13
    //   402: invokevirtual 97	java/io/BufferedReader:close	()V
    //   405: aload 9
    //   407: ifnull +8 -> 415
    //   410: aload 9
    //   412: invokevirtual 98	java/io/InputStreamReader:close	()V
    //   415: aload 8
    //   417: ifnull +8 -> 425
    //   420: aload 8
    //   422: invokevirtual 101	java/io/FileInputStream:close	()V
    //   425: goto -196 -> 229
    //   428: astore 15
    //   430: aload 13
    //   432: astore 12
    //   434: aload 9
    //   436: astore 11
    //   438: aload 8
    //   440: astore 10
    //   442: aload 15
    //   444: invokevirtual 138	java/lang/Exception:printStackTrace	()V
    //   447: goto -109 -> 338
    //   450: astore 8
    //   452: aload 8
    //   454: invokevirtual 139	java/io/IOException:printStackTrace	()V
    //   457: goto -228 -> 229
    //   460: astore 8
    //   462: aload 8
    //   464: invokevirtual 139	java/io/IOException:printStackTrace	()V
    //   467: iconst_0
    //   468: istore 7
    //   470: goto -241 -> 229
    //   473: astore 14
    //   475: aconst_null
    //   476: astore 13
    //   478: aconst_null
    //   479: astore 9
    //   481: aconst_null
    //   482: astore 8
    //   484: aload 13
    //   486: astore 12
    //   488: aload 9
    //   490: astore 11
    //   492: aload 8
    //   494: astore 10
    //   496: aload 14
    //   498: invokevirtual 140	java/io/FileNotFoundException:printStackTrace	()V
    //   501: aload 13
    //   503: ifnull +8 -> 511
    //   506: aload 13
    //   508: invokevirtual 97	java/io/BufferedReader:close	()V
    //   511: aload 9
    //   513: ifnull +8 -> 521
    //   516: aload 9
    //   518: invokevirtual 98	java/io/InputStreamReader:close	()V
    //   521: aload 8
    //   523: ifnull +8 -> 531
    //   526: aload 8
    //   528: invokevirtual 101	java/io/FileInputStream:close	()V
    //   531: iconst_0
    //   532: istore 7
    //   534: goto -305 -> 229
    //   537: astore 8
    //   539: aload 8
    //   541: invokevirtual 139	java/io/IOException:printStackTrace	()V
    //   544: iconst_0
    //   545: istore 7
    //   547: goto -318 -> 229
    //   550: astore 14
    //   552: aconst_null
    //   553: astore 13
    //   555: aconst_null
    //   556: astore 9
    //   558: aconst_null
    //   559: astore 8
    //   561: aload 13
    //   563: astore 12
    //   565: aload 9
    //   567: astore 11
    //   569: aload 8
    //   571: astore 10
    //   573: aload 14
    //   575: invokevirtual 139	java/io/IOException:printStackTrace	()V
    //   578: aload 13
    //   580: ifnull +8 -> 588
    //   583: aload 13
    //   585: invokevirtual 97	java/io/BufferedReader:close	()V
    //   588: aload 9
    //   590: ifnull +8 -> 598
    //   593: aload 9
    //   595: invokevirtual 98	java/io/InputStreamReader:close	()V
    //   598: aload 8
    //   600: ifnull +8 -> 608
    //   603: aload 8
    //   605: invokevirtual 101	java/io/FileInputStream:close	()V
    //   608: iconst_0
    //   609: istore 7
    //   611: goto -382 -> 229
    //   614: astore 8
    //   616: aload 8
    //   618: invokevirtual 139	java/io/IOException:printStackTrace	()V
    //   621: iconst_0
    //   622: istore 7
    //   624: goto -395 -> 229
    //   627: astore 13
    //   629: aconst_null
    //   630: astore 12
    //   632: aconst_null
    //   633: astore 9
    //   635: aconst_null
    //   636: astore 8
    //   638: aload 12
    //   640: ifnull +8 -> 648
    //   643: aload 12
    //   645: invokevirtual 97	java/io/BufferedReader:close	()V
    //   648: aload 9
    //   650: ifnull +8 -> 658
    //   653: aload 9
    //   655: invokevirtual 98	java/io/InputStreamReader:close	()V
    //   658: aload 8
    //   660: ifnull +8 -> 668
    //   663: aload 8
    //   665: invokevirtual 101	java/io/FileInputStream:close	()V
    //   668: aload 13
    //   670: athrow
    //   671: astore 8
    //   673: aload 8
    //   675: invokevirtual 139	java/io/IOException:printStackTrace	()V
    //   678: goto -10 -> 668
    //   681: astore 8
    //   683: aload 8
    //   685: invokevirtual 138	java/lang/Exception:printStackTrace	()V
    //   688: goto -412 -> 276
    //   691: astore 8
    //   693: aload 8
    //   695: invokevirtual 140	java/io/FileNotFoundException:printStackTrace	()V
    //   698: iconst_0
    //   699: ifeq -423 -> 276
    //   702: new 142	java/lang/NullPointerException
    //   705: dup
    //   706: invokespecial 143	java/lang/NullPointerException:<init>	()V
    //   709: athrow
    //   710: astore 8
    //   712: aload 8
    //   714: invokevirtual 138	java/lang/Exception:printStackTrace	()V
    //   717: goto -441 -> 276
    //   720: astore 9
    //   722: iconst_0
    //   723: ifeq +11 -> 734
    //   726: new 142	java/lang/NullPointerException
    //   729: dup
    //   730: invokespecial 143	java/lang/NullPointerException:<init>	()V
    //   733: athrow
    //   734: aload 9
    //   736: athrow
    //   737: astore 8
    //   739: aload 8
    //   741: invokevirtual 138	java/lang/Exception:printStackTrace	()V
    //   744: goto -10 -> 734
    //   747: invokestatic 44	com/gtp/a/a/a/a:a	()Lcom/gtp/a/a/a/a;
    //   750: ldc -111
    //   752: ldc 48
    //   754: invokevirtual 51	com/gtp/a/a/a/a:a	(Ljava/lang/String;Ljava/lang/String;)V
    //   757: ldc 105
    //   759: ldc -111
    //   761: invokestatic 108	com/gtp/a/a/b/c:a	(Ljava/lang/String;Ljava/lang/String;)V
    //   764: ldc2_w 146
    //   767: lstore_1
    //   768: goto -483 -> 285
    //   771: ldc2_w 26
    //   774: lload 5
    //   776: lload_3
    //   777: lsub
    //   778: lsub
    //   779: lstore_1
    //   780: goto -495 -> 285
    //   783: astore 13
    //   785: aconst_null
    //   786: astore 12
    //   788: aconst_null
    //   789: astore 9
    //   791: goto -153 -> 638
    //   794: astore 13
    //   796: aconst_null
    //   797: astore 12
    //   799: goto -161 -> 638
    //   802: astore 13
    //   804: aload 11
    //   806: astore 9
    //   808: aload 10
    //   810: astore 8
    //   812: goto -174 -> 638
    //   815: astore 14
    //   817: aconst_null
    //   818: astore 13
    //   820: aconst_null
    //   821: astore 9
    //   823: goto -262 -> 561
    //   826: astore 14
    //   828: aconst_null
    //   829: astore 13
    //   831: goto -270 -> 561
    //   834: astore 14
    //   836: goto -275 -> 561
    //   839: astore 14
    //   841: aconst_null
    //   842: astore 13
    //   844: aconst_null
    //   845: astore 9
    //   847: goto -363 -> 484
    //   850: astore 14
    //   852: aconst_null
    //   853: astore 13
    //   855: goto -371 -> 484
    //   858: astore 14
    //   860: goto -376 -> 484
    //   863: astore 14
    //   865: aconst_null
    //   866: astore 13
    //   868: aconst_null
    //   869: astore 9
    //   871: aconst_null
    //   872: astore 8
    //   874: goto -695 -> 179
    //   877: astore 14
    //   879: aconst_null
    //   880: astore 13
    //   882: aconst_null
    //   883: astore 9
    //   885: goto -706 -> 179
    //   888: astore 14
    //   890: aconst_null
    //   891: astore 13
    //   893: goto -714 -> 179
    // Local variable table:
    //   start	length	slot	name	signature
    //   0	896	0	this	m
    //   3	777	1	l1	long
    //   16	761	3	l2	long
    //   7	768	5	l3	long
    //   227	396	7	bool	boolean
    //   65	374	8	localObject1	Object
    //   450	3	8	localIOException1	java.io.IOException
    //   460	3	8	localIOException2	java.io.IOException
    //   482	45	8	localObject2	Object
    //   537	3	8	localIOException3	java.io.IOException
    //   559	45	8	localObject3	Object
    //   614	3	8	localIOException4	java.io.IOException
    //   636	28	8	localObject4	Object
    //   671	3	8	localIOException5	java.io.IOException
    //   681	3	8	localException1	Exception
    //   691	3	8	localFileNotFoundException1	java.io.FileNotFoundException
    //   710	3	8	localException2	Exception
    //   737	3	8	localException3	Exception
    //   810	63	8	localObject5	Object
    //   78	576	9	localInputStreamReader1	java.io.InputStreamReader
    //   720	15	9	localObject6	Object
    //   789	95	9	localObject7	Object
    //   101	708	10	localObject8	Object
    //   97	708	11	localInputStreamReader2	java.io.InputStreamReader
    //   93	705	12	localBufferedReader1	java.io.BufferedReader
    //   89	495	13	localBufferedReader2	java.io.BufferedReader
    //   627	42	13	localObject9	Object
    //   783	1	13	localObject10	Object
    //   794	1	13	localObject11	Object
    //   802	1	13	localObject12	Object
    //   818	74	13	localObject13	Object
    //   110	39	14	localStringBuilder	StringBuilder
    //   177	130	14	localUnsupportedEncodingException1	java.io.UnsupportedEncodingException
    //   311	49	14	localObject14	Object
    //   473	24	14	localFileNotFoundException2	java.io.FileNotFoundException
    //   550	24	14	localIOException6	java.io.IOException
    //   815	1	14	localIOException7	java.io.IOException
    //   826	1	14	localIOException8	java.io.IOException
    //   834	1	14	localIOException9	java.io.IOException
    //   839	1	14	localFileNotFoundException3	java.io.FileNotFoundException
    //   850	1	14	localFileNotFoundException4	java.io.FileNotFoundException
    //   858	1	14	localFileNotFoundException5	java.io.FileNotFoundException
    //   863	1	14	localUnsupportedEncodingException2	java.io.UnsupportedEncodingException
    //   877	1	14	localUnsupportedEncodingException3	java.io.UnsupportedEncodingException
    //   888	1	14	localUnsupportedEncodingException4	java.io.UnsupportedEncodingException
    //   129	252	15	localObject15	Object
    //   428	15	15	localException4	Exception
    // Exception table:
    //   from	to	target	type
    //   103	112	177	java/io/UnsupportedEncodingException
    //   124	131	177	java/io/UnsupportedEncodingException
    //   148	174	177	java/io/UnsupportedEncodingException
    //   306	313	177	java/io/UnsupportedEncodingException
    //   325	334	177	java/io/UnsupportedEncodingException
    //   359	368	177	java/io/UnsupportedEncodingException
    //   380	395	177	java/io/UnsupportedEncodingException
    //   442	447	177	java/io/UnsupportedEncodingException
    //   325	334	428	java/lang/Exception
    //   400	405	450	java/io/IOException
    //   410	415	450	java/io/IOException
    //   420	425	450	java/io/IOException
    //   201	206	460	java/io/IOException
    //   211	216	460	java/io/IOException
    //   221	226	460	java/io/IOException
    //   53	67	473	java/io/FileNotFoundException
    //   506	511	537	java/io/IOException
    //   516	521	537	java/io/IOException
    //   526	531	537	java/io/IOException
    //   53	67	550	java/io/IOException
    //   583	588	614	java/io/IOException
    //   593	598	614	java/io/IOException
    //   603	608	614	java/io/IOException
    //   53	67	627	finally
    //   643	648	671	java/io/IOException
    //   653	658	671	java/io/IOException
    //   663	668	671	java/io/IOException
    //   271	276	681	java/lang/Exception
    //   251	266	691	java/io/FileNotFoundException
    //   702	710	710	java/lang/Exception
    //   251	266	720	finally
    //   693	698	720	finally
    //   726	734	737	java/lang/Exception
    //   67	80	783	finally
    //   80	91	794	finally
    //   103	112	802	finally
    //   124	131	802	finally
    //   148	174	802	finally
    //   191	196	802	finally
    //   306	313	802	finally
    //   325	334	802	finally
    //   359	368	802	finally
    //   380	395	802	finally
    //   442	447	802	finally
    //   496	501	802	finally
    //   573	578	802	finally
    //   67	80	815	java/io/IOException
    //   80	91	826	java/io/IOException
    //   103	112	834	java/io/IOException
    //   124	131	834	java/io/IOException
    //   148	174	834	java/io/IOException
    //   306	313	834	java/io/IOException
    //   325	334	834	java/io/IOException
    //   359	368	834	java/io/IOException
    //   380	395	834	java/io/IOException
    //   442	447	834	java/io/IOException
    //   67	80	839	java/io/FileNotFoundException
    //   80	91	850	java/io/FileNotFoundException
    //   103	112	858	java/io/FileNotFoundException
    //   124	131	858	java/io/FileNotFoundException
    //   148	174	858	java/io/FileNotFoundException
    //   306	313	858	java/io/FileNotFoundException
    //   325	334	858	java/io/FileNotFoundException
    //   359	368	858	java/io/FileNotFoundException
    //   380	395	858	java/io/FileNotFoundException
    //   442	447	858	java/io/FileNotFoundException
    //   53	67	863	java/io/UnsupportedEncodingException
    //   67	80	877	java/io/UnsupportedEncodingException
    //   80	91	888	java/io/UnsupportedEncodingException
  }
}


/* Location:              /Users/amaurremi/uw/stringoid/static-dynamic-comparison/apps/go weather ex/com.gau.go.launcherex.gowidget.weatherwidget-124-dex2jar.jar!/com/gau/go/launcherex/gowidget/statistics/m.class
 * Java compiler version: 6 (50.0)
 * JD-Core Version:       0.7.1
 */