package com.quoord.tapatalkpro.tabwidget.manager;

import android.content.BroadcastReceiver;

public class WidgetReciver
        extends BroadcastReceiver {
    /* Error */
    public void onReceive(android.content.Context paramContext, android.content.Intent paramIntent) {
        // Byte code:
        //   0: aload_1
        //   1: ldc 15
        //   3: iconst_0
        //   4: invokevirtual 21	android/content/Context:getSharedPreferences	(Ljava/lang/String;I)Landroid/content/SharedPreferences;
        //   7: invokeinterface 27 1 0
        //   12: checkcast 29	java/util/HashMap
        //   15: astore 4
        //   17: aload 4
        //   19: invokevirtual 33	java/util/HashMap:keySet	()Ljava/util/Set;
        //   22: invokeinterface 39 1 0
        //   27: astore_2
        //   28: aload 4
        //   30: invokevirtual 33	java/util/HashMap:keySet	()Ljava/util/Set;
        //   33: invokeinterface 43 1 0
        //   38: newarray <illegal type>
        //   40: astore 4
        //   42: iconst_0
        //   43: istore_3
        //   44: aload_2
        //   45: invokeinterface 49 1 0
        //   50: ifne +137 -> 187
        //   53: invokestatic 55	com/quoord/tapatalkpro/tabwidget/manager/PMWidgetManager:getInstance	()Lcom/quoord/tapatalkpro/tabwidget/manager/PMWidgetManager;
        //   56: aload_1
        //   57: aload 4
        //   59: invokevirtual 59	com/quoord/tapatalkpro/tabwidget/manager/PMWidgetManager:updateWidgets	(Landroid/content/Context;[I)V
        //   62: aload_1
        //   63: ldc 61
        //   65: iconst_0
        //   66: invokevirtual 21	android/content/Context:getSharedPreferences	(Ljava/lang/String;I)Landroid/content/SharedPreferences;
        //   69: invokeinterface 27 1 0
        //   74: checkcast 29	java/util/HashMap
        //   77: astore 4
        //   79: aload 4
        //   81: invokevirtual 33	java/util/HashMap:keySet	()Ljava/util/Set;
        //   84: invokeinterface 39 1 0
        //   89: astore_2
        //   90: aload 4
        //   92: invokevirtual 33	java/util/HashMap:keySet	()Ljava/util/Set;
        //   95: invokeinterface 43 1 0
        //   100: newarray <illegal type>
        //   102: astore 4
        //   104: iconst_0
        //   105: istore_3
        //   106: aload_2
        //   107: invokeinterface 49 1 0
        //   112: ifne +122 -> 234
        //   115: invokestatic 66	com/quoord/tapatalkpro/tabwidget/manager/FavForumWidgetManager:getInstance	()Lcom/quoord/tapatalkpro/tabwidget/manager/FavForumWidgetManager;
        //   118: aload_1
        //   119: aload 4
        //   121: invokevirtual 67	com/quoord/tapatalkpro/tabwidget/manager/FavForumWidgetManager:updateWidgets	(Landroid/content/Context;[I)V
        //   124: aload_1
        //   125: ldc 69
        //   127: iconst_0
        //   128: invokevirtual 21	android/content/Context:getSharedPreferences	(Ljava/lang/String;I)Landroid/content/SharedPreferences;
        //   131: invokeinterface 27 1 0
        //   136: checkcast 29	java/util/HashMap
        //   139: astore 4
        //   141: aload 4
        //   143: invokevirtual 33	java/util/HashMap:keySet	()Ljava/util/Set;
        //   146: invokeinterface 39 1 0
        //   151: astore_2
        //   152: aload 4
        //   154: invokevirtual 33	java/util/HashMap:keySet	()Ljava/util/Set;
        //   157: invokeinterface 43 1 0
        //   162: newarray <illegal type>
        //   164: astore 4
        //   166: iconst_0
        //   167: istore_3
        //   168: aload_2
        //   169: invokeinterface 49 1 0
        //   174: ifne +107 -> 281
        //   177: invokestatic 74	com/quoord/tapatalkpro/tabwidget/manager/FavTopicsWidgetManager:getInstance	()Lcom/quoord/tapatalkpro/tabwidget/manager/FavTopicsWidgetManager;
        //   180: aload_1
        //   181: aload 4
        //   183: invokevirtual 75	com/quoord/tapatalkpro/tabwidget/manager/FavTopicsWidgetManager:updateWidgets	(Landroid/content/Context;[I)V
        //   186: return
        //   187: aload_2
        //   188: invokeinterface 79 1 0
        //   193: checkcast 81	java/lang/String
        //   196: astore 5
        //   198: aload 4
        //   200: iload_3
        //   201: aload 5
        //   203: aload 5
        //   205: ldc 83
        //   207: invokevirtual 87	java/lang/String:indexOf	(Ljava/lang/String;)I
        //   210: iconst_1
        //   211: iadd
        //   212: aload 5
        //   214: invokevirtual 90	java/lang/String:length	()I
        //   217: invokevirtual 94	java/lang/String:substring	(II)Ljava/lang/String;
        //   220: invokestatic 100	java/lang/Integer:valueOf	(Ljava/lang/String;)Ljava/lang/Integer;
        //   223: invokevirtual 103	java/lang/Integer:intValue	()I
        //   226: iastore
        //   227: iload_3
        //   228: iconst_1
        //   229: iadd
        //   230: istore_3
        //   231: goto -187 -> 44
        //   234: aload_2
        //   235: invokeinterface 79 1 0
        //   240: checkcast 81	java/lang/String
        //   243: astore 5
        //   245: aload 4
        //   247: iload_3
        //   248: aload 5
        //   250: aload 5
        //   252: ldc 83
        //   254: invokevirtual 87	java/lang/String:indexOf	(Ljava/lang/String;)I
        //   257: iconst_1
        //   258: iadd
        //   259: aload 5
        //   261: invokevirtual 90	java/lang/String:length	()I
        //   264: invokevirtual 94	java/lang/String:substring	(II)Ljava/lang/String;
        //   267: invokestatic 100	java/lang/Integer:valueOf	(Ljava/lang/String;)Ljava/lang/Integer;
        //   270: invokevirtual 103	java/lang/Integer:intValue	()I
        //   273: iastore
        //   274: iload_3
        //   275: iconst_1
        //   276: iadd
        //   277: istore_3
        //   278: goto -172 -> 106
        //   281: aload_2
        //   282: invokeinterface 79 1 0
        //   287: checkcast 81	java/lang/String
        //   290: astore 5
        //   292: aload 4
        //   294: iload_3
        //   295: aload 5
        //   297: aload 5
        //   299: ldc 83
        //   301: invokevirtual 87	java/lang/String:indexOf	(Ljava/lang/String;)I
        //   304: iconst_1
        //   305: iadd
        //   306: aload 5
        //   308: invokevirtual 90	java/lang/String:length	()I
        //   311: invokevirtual 94	java/lang/String:substring	(II)Ljava/lang/String;
        //   314: invokestatic 100	java/lang/Integer:valueOf	(Ljava/lang/String;)Ljava/lang/Integer;
        //   317: invokevirtual 103	java/lang/Integer:intValue	()I
        //   320: iastore
        //   321: iload_3
        //   322: iconst_1
        //   323: iadd
        //   324: istore_3
        //   325: goto -157 -> 168
        //   328: astore_1
        //   329: return
        //   330: astore_2
        //   331: goto -207 -> 124
        //   334: astore_2
        //   335: goto -273 -> 62
        // Local variable table:
        //   start	length	slot	name	signature
        //   0	338	0	this	WidgetReciver
        //   0	338	1	paramContext	android.content.Context
        //   0	338	2	paramIntent	android.content.Intent
        //   43	282	3	i	int
        //   15	278	4	localObject	Object
        //   196	111	5	str	String
        // Exception table:
        //   from	to	target	type
        //   124	166	328	java/lang/Exception
        //   168	186	328	java/lang/Exception
        //   281	321	328	java/lang/Exception
        //   62	104	330	java/lang/Exception
        //   106	124	330	java/lang/Exception
        //   234	274	330	java/lang/Exception
        //   0	42	334	java/lang/Exception
        //   44	62	334	java/lang/Exception
        //   187	227	334	java/lang/Exception
    }
}


/* Location:              /Users/amaurremi/uw/stringoid stuff/static vs dynamic/tapatalk/com.quoord.tapatalkpro.activity-453-dex2jar.jar!/com/quoord/tapatalkpro/tabwidget/manager/WidgetReciver.class
 * Java compiler version: 6 (50.0)
 * JD-Core Version:       0.7.1
 */