package com.vungle.publisher;

import java.io.File;

public final class bl
{
  /* Error */
  public static void a(File paramFile1, File paramFile2, a... paramVarArgs)
    throws java.io.IOException
  {
    // Byte code:
    //   0: ldc 12
    //   2: new 14	java/lang/StringBuilder
    //   5: dup
    //   6: ldc 16
    //   8: invokespecial 20	java/lang/StringBuilder:<init>	(Ljava/lang/String;)V
    //   11: aload_0
    //   12: invokevirtual 24	java/lang/StringBuilder:append	(Ljava/lang/Object;)Ljava/lang/StringBuilder;
    //   15: ldc 26
    //   17: invokevirtual 29	java/lang/StringBuilder:append	(Ljava/lang/String;)Ljava/lang/StringBuilder;
    //   20: aload_1
    //   21: invokevirtual 24	java/lang/StringBuilder:append	(Ljava/lang/Object;)Ljava/lang/StringBuilder;
    //   24: invokevirtual 33	java/lang/StringBuilder:toString	()Ljava/lang/String;
    //   27: invokestatic 39	com/vungle/publisher/log/Logger:d	(Ljava/lang/String;Ljava/lang/String;)V
    //   30: aload_1
    //   31: invokevirtual 45	java/io/File:isDirectory	()Z
    //   34: ifne +34 -> 68
    //   37: aload_1
    //   38: invokevirtual 48	java/io/File:mkdirs	()Z
    //   41: ifne +27 -> 68
    //   44: new 10	java/io/IOException
    //   47: dup
    //   48: new 14	java/lang/StringBuilder
    //   51: dup
    //   52: ldc 50
    //   54: invokespecial 20	java/lang/StringBuilder:<init>	(Ljava/lang/String;)V
    //   57: aload_1
    //   58: invokevirtual 24	java/lang/StringBuilder:append	(Ljava/lang/Object;)Ljava/lang/StringBuilder;
    //   61: invokevirtual 33	java/lang/StringBuilder:toString	()Ljava/lang/String;
    //   64: invokespecial 51	java/io/IOException:<init>	(Ljava/lang/String;)V
    //   67: athrow
    //   68: new 53	java/util/zip/ZipInputStream
    //   71: dup
    //   72: new 55	java/io/BufferedInputStream
    //   75: dup
    //   76: new 57	java/io/FileInputStream
    //   79: dup
    //   80: aload_0
    //   81: invokespecial 60	java/io/FileInputStream:<init>	(Ljava/io/File;)V
    //   84: invokespecial 63	java/io/BufferedInputStream:<init>	(Ljava/io/InputStream;)V
    //   87: invokespecial 64	java/util/zip/ZipInputStream:<init>	(Ljava/io/InputStream;)V
    //   90: astore 6
    //   92: sipush 8192
    //   95: newarray <illegal type>
    //   97: astore 7
    //   99: aload 6
    //   101: invokevirtual 68	java/util/zip/ZipInputStream:getNextEntry	()Ljava/util/zip/ZipEntry;
    //   104: astore 8
    //   106: aload 8
    //   108: ifnull +186 -> 294
    //   111: new 41	java/io/File
    //   114: dup
    //   115: aload_1
    //   116: aload 8
    //   118: invokevirtual 73	java/util/zip/ZipEntry:getName	()Ljava/lang/String;
    //   121: invokespecial 76	java/io/File:<init>	(Ljava/io/File;Ljava/lang/String;)V
    //   124: astore 9
    //   126: ldc 12
    //   128: new 14	java/lang/StringBuilder
    //   131: dup
    //   132: ldc 16
    //   134: invokespecial 20	java/lang/StringBuilder:<init>	(Ljava/lang/String;)V
    //   137: aload 9
    //   139: invokevirtual 24	java/lang/StringBuilder:append	(Ljava/lang/Object;)Ljava/lang/StringBuilder;
    //   142: invokevirtual 33	java/lang/StringBuilder:toString	()Ljava/lang/String;
    //   145: invokestatic 79	com/vungle/publisher/log/Logger:v	(Ljava/lang/String;Ljava/lang/String;)V
    //   148: new 81	java/io/FileOutputStream
    //   151: dup
    //   152: aload 9
    //   154: invokespecial 82	java/io/FileOutputStream:<init>	(Ljava/io/File;)V
    //   157: astore 8
    //   159: lconst_0
    //   160: lstore 4
    //   162: aload 6
    //   164: aload 7
    //   166: invokevirtual 86	java/util/zip/ZipInputStream:read	([B)I
    //   169: istore_3
    //   170: iload_3
    //   171: ifle +38 -> 209
    //   174: lload 4
    //   176: iload_3
    //   177: i2l
    //   178: ladd
    //   179: lstore 4
    //   181: aload 8
    //   183: aload 7
    //   185: iconst_0
    //   186: iload_3
    //   187: invokevirtual 92	java/io/OutputStream:write	([BII)V
    //   190: goto -28 -> 162
    //   193: astore_2
    //   194: aload 8
    //   196: invokevirtual 96	java/io/OutputStream:close	()V
    //   199: aload_2
    //   200: athrow
    //   201: astore_1
    //   202: aload 6
    //   204: invokevirtual 97	java/util/zip/ZipInputStream:close	()V
    //   207: aload_1
    //   208: athrow
    //   209: iconst_0
    //   210: istore_3
    //   211: iload_3
    //   212: ifgt +22 -> 234
    //   215: aload_2
    //   216: iload_3
    //   217: aaload
    //   218: aload 9
    //   220: lload 4
    //   222: invokeinterface 100 4 0
    //   227: iload_3
    //   228: iconst_1
    //   229: iadd
    //   230: istore_3
    //   231: goto -20 -> 211
    //   234: aload 8
    //   236: invokevirtual 96	java/io/OutputStream:close	()V
    //   239: goto -140 -> 99
    //   242: astore 8
    //   244: ldc 12
    //   246: new 14	java/lang/StringBuilder
    //   249: dup
    //   250: ldc 102
    //   252: invokespecial 20	java/lang/StringBuilder:<init>	(Ljava/lang/String;)V
    //   255: aload_1
    //   256: invokevirtual 24	java/lang/StringBuilder:append	(Ljava/lang/Object;)Ljava/lang/StringBuilder;
    //   259: invokevirtual 33	java/lang/StringBuilder:toString	()Ljava/lang/String;
    //   262: invokestatic 105	com/vungle/publisher/log/Logger:w	(Ljava/lang/String;Ljava/lang/String;)V
    //   265: goto -166 -> 99
    //   268: astore 7
    //   270: ldc 12
    //   272: new 14	java/lang/StringBuilder
    //   275: dup
    //   276: ldc 102
    //   278: invokespecial 20	java/lang/StringBuilder:<init>	(Ljava/lang/String;)V
    //   281: aload_1
    //   282: invokevirtual 24	java/lang/StringBuilder:append	(Ljava/lang/Object;)Ljava/lang/StringBuilder;
    //   285: invokevirtual 33	java/lang/StringBuilder:toString	()Ljava/lang/String;
    //   288: invokestatic 105	com/vungle/publisher/log/Logger:w	(Ljava/lang/String;Ljava/lang/String;)V
    //   291: goto -92 -> 199
    //   294: aload 6
    //   296: invokevirtual 97	java/util/zip/ZipInputStream:close	()V
    //   299: return
    //   300: astore_1
    //   301: ldc 12
    //   303: new 14	java/lang/StringBuilder
    //   306: dup
    //   307: ldc 107
    //   309: invokespecial 20	java/lang/StringBuilder:<init>	(Ljava/lang/String;)V
    //   312: aload_0
    //   313: invokevirtual 24	java/lang/StringBuilder:append	(Ljava/lang/Object;)Ljava/lang/StringBuilder;
    //   316: invokevirtual 33	java/lang/StringBuilder:toString	()Ljava/lang/String;
    //   319: invokestatic 105	com/vungle/publisher/log/Logger:w	(Ljava/lang/String;Ljava/lang/String;)V
    //   322: return
    //   323: astore_2
    //   324: ldc 12
    //   326: new 14	java/lang/StringBuilder
    //   329: dup
    //   330: ldc 107
    //   332: invokespecial 20	java/lang/StringBuilder:<init>	(Ljava/lang/String;)V
    //   335: aload_0
    //   336: invokevirtual 24	java/lang/StringBuilder:append	(Ljava/lang/Object;)Ljava/lang/StringBuilder;
    //   339: invokevirtual 33	java/lang/StringBuilder:toString	()Ljava/lang/String;
    //   342: invokestatic 105	com/vungle/publisher/log/Logger:w	(Ljava/lang/String;Ljava/lang/String;)V
    //   345: goto -138 -> 207
    // Local variable table:
    //   start	length	slot	name	signature
    //   0	348	0	paramFile1	File
    //   0	348	1	paramFile2	File
    //   0	348	2	paramVarArgs	a[]
    //   169	62	3	i	int
    //   160	61	4	l	long
    //   90	205	6	localZipInputStream	java.util.zip.ZipInputStream
    //   97	87	7	arrayOfByte	byte[]
    //   268	1	7	localIOException1	java.io.IOException
    //   104	131	8	localObject	Object
    //   242	1	8	localIOException2	java.io.IOException
    //   124	95	9	localFile	File
    // Exception table:
    //   from	to	target	type
    //   162	170	193	finally
    //   181	190	193	finally
    //   215	227	193	finally
    //   92	99	201	finally
    //   99	106	201	finally
    //   111	159	201	finally
    //   194	199	201	finally
    //   199	201	201	finally
    //   234	239	201	finally
    //   244	265	201	finally
    //   270	291	201	finally
    //   234	239	242	java/io/IOException
    //   194	199	268	java/io/IOException
    //   294	299	300	java/io/IOException
    //   202	207	323	java/io/IOException
  }
  
  public static abstract interface a
  {
    public abstract void a(File paramFile, long paramLong);
  }
}


/* Location:              /Users/amaurremi/uw/stringoid/static-dynamic-comparison/apps/broken screen/mobi.borken.android.brokenscreen-20-dex2jar.jar!/com/vungle/publisher/bl.class
 * Java compiler version: 6 (50.0)
 * JD-Core Version:       0.7.1
 */