package com.google.android.gms.wearable.internal;

import android.os.IBinder;

class ax
  implements ad
{
  private IBinder a;
  
  ax(IBinder paramIBinder)
  {
    this.a = paramIBinder;
  }
  
  /* Error */
  public void a(ab paramab)
  {
    // Byte code:
    //   0: invokestatic 23	android/os/Parcel:obtain	()Landroid/os/Parcel;
    //   3: astore_2
    //   4: invokestatic 23	android/os/Parcel:obtain	()Landroid/os/Parcel;
    //   7: astore_3
    //   8: aload_2
    //   9: ldc 25
    //   11: invokevirtual 29	android/os/Parcel:writeInterfaceToken	(Ljava/lang/String;)V
    //   14: aload_1
    //   15: ifnull +42 -> 57
    //   18: aload_1
    //   19: invokeinterface 35 1 0
    //   24: astore_1
    //   25: aload_2
    //   26: aload_1
    //   27: invokevirtual 38	android/os/Parcel:writeStrongBinder	(Landroid/os/IBinder;)V
    //   30: aload_0
    //   31: getfield 15	com/google/android/gms/wearable/internal/ax:a	Landroid/os/IBinder;
    //   34: iconst_3
    //   35: aload_2
    //   36: aload_3
    //   37: iconst_0
    //   38: invokeinterface 44 5 0
    //   43: pop
    //   44: aload_3
    //   45: invokevirtual 47	android/os/Parcel:readException	()V
    //   48: aload_3
    //   49: invokevirtual 50	android/os/Parcel:recycle	()V
    //   52: aload_2
    //   53: invokevirtual 50	android/os/Parcel:recycle	()V
    //   56: return
    //   57: aconst_null
    //   58: astore_1
    //   59: goto -34 -> 25
    //   62: astore_1
    //   63: aload_3
    //   64: invokevirtual 50	android/os/Parcel:recycle	()V
    //   67: aload_2
    //   68: invokevirtual 50	android/os/Parcel:recycle	()V
    //   71: aload_1
    //   72: athrow
    // Local variable table:
    //   start	length	slot	name	signature
    //   0	73	0	this	ax
    //   0	73	1	paramab	ab
    //   3	65	2	localParcel1	android.os.Parcel
    //   7	57	3	localParcel2	android.os.Parcel
    // Exception table:
    //   from	to	target	type
    //   8	14	62	finally
    //   18	25	62	finally
    //   25	48	62	finally
  }
  
  /* Error */
  public void a(ab paramab, android.net.Uri paramUri)
  {
    // Byte code:
    //   0: invokestatic 23	android/os/Parcel:obtain	()Landroid/os/Parcel;
    //   3: astore_3
    //   4: invokestatic 23	android/os/Parcel:obtain	()Landroid/os/Parcel;
    //   7: astore 4
    //   9: aload_3
    //   10: ldc 25
    //   12: invokevirtual 29	android/os/Parcel:writeInterfaceToken	(Ljava/lang/String;)V
    //   15: aload_1
    //   16: ifnull +61 -> 77
    //   19: aload_1
    //   20: invokeinterface 35 1 0
    //   25: astore_1
    //   26: aload_3
    //   27: aload_1
    //   28: invokevirtual 38	android/os/Parcel:writeStrongBinder	(Landroid/os/IBinder;)V
    //   31: aload_2
    //   32: ifnull +50 -> 82
    //   35: aload_3
    //   36: iconst_1
    //   37: invokevirtual 55	android/os/Parcel:writeInt	(I)V
    //   40: aload_2
    //   41: aload_3
    //   42: iconst_0
    //   43: invokevirtual 61	android/net/Uri:writeToParcel	(Landroid/os/Parcel;I)V
    //   46: aload_0
    //   47: getfield 15	com/google/android/gms/wearable/internal/ax:a	Landroid/os/IBinder;
    //   50: bipush 7
    //   52: aload_3
    //   53: aload 4
    //   55: iconst_0
    //   56: invokeinterface 44 5 0
    //   61: pop
    //   62: aload 4
    //   64: invokevirtual 47	android/os/Parcel:readException	()V
    //   67: aload 4
    //   69: invokevirtual 50	android/os/Parcel:recycle	()V
    //   72: aload_3
    //   73: invokevirtual 50	android/os/Parcel:recycle	()V
    //   76: return
    //   77: aconst_null
    //   78: astore_1
    //   79: goto -53 -> 26
    //   82: aload_3
    //   83: iconst_0
    //   84: invokevirtual 55	android/os/Parcel:writeInt	(I)V
    //   87: goto -41 -> 46
    //   90: astore_1
    //   91: aload 4
    //   93: invokevirtual 50	android/os/Parcel:recycle	()V
    //   96: aload_3
    //   97: invokevirtual 50	android/os/Parcel:recycle	()V
    //   100: aload_1
    //   101: athrow
    // Local variable table:
    //   start	length	slot	name	signature
    //   0	102	0	this	ax
    //   0	102	1	paramab	ab
    //   0	102	2	paramUri	android.net.Uri
    //   3	94	3	localParcel1	android.os.Parcel
    //   7	85	4	localParcel2	android.os.Parcel
    // Exception table:
    //   from	to	target	type
    //   9	15	90	finally
    //   19	26	90	finally
    //   26	31	90	finally
    //   35	46	90	finally
    //   46	67	90	finally
    //   82	87	90	finally
  }
  
  /* Error */
  public void a(ab paramab, com.google.android.gms.wearable.Asset paramAsset)
  {
    // Byte code:
    //   0: invokestatic 23	android/os/Parcel:obtain	()Landroid/os/Parcel;
    //   3: astore_3
    //   4: invokestatic 23	android/os/Parcel:obtain	()Landroid/os/Parcel;
    //   7: astore 4
    //   9: aload_3
    //   10: ldc 25
    //   12: invokevirtual 29	android/os/Parcel:writeInterfaceToken	(Ljava/lang/String;)V
    //   15: aload_1
    //   16: ifnull +61 -> 77
    //   19: aload_1
    //   20: invokeinterface 35 1 0
    //   25: astore_1
    //   26: aload_3
    //   27: aload_1
    //   28: invokevirtual 38	android/os/Parcel:writeStrongBinder	(Landroid/os/IBinder;)V
    //   31: aload_2
    //   32: ifnull +50 -> 82
    //   35: aload_3
    //   36: iconst_1
    //   37: invokevirtual 55	android/os/Parcel:writeInt	(I)V
    //   40: aload_2
    //   41: aload_3
    //   42: iconst_0
    //   43: invokevirtual 65	com/google/android/gms/wearable/Asset:writeToParcel	(Landroid/os/Parcel;I)V
    //   46: aload_0
    //   47: getfield 15	com/google/android/gms/wearable/internal/ax:a	Landroid/os/IBinder;
    //   50: bipush 13
    //   52: aload_3
    //   53: aload 4
    //   55: iconst_0
    //   56: invokeinterface 44 5 0
    //   61: pop
    //   62: aload 4
    //   64: invokevirtual 47	android/os/Parcel:readException	()V
    //   67: aload 4
    //   69: invokevirtual 50	android/os/Parcel:recycle	()V
    //   72: aload_3
    //   73: invokevirtual 50	android/os/Parcel:recycle	()V
    //   76: return
    //   77: aconst_null
    //   78: astore_1
    //   79: goto -53 -> 26
    //   82: aload_3
    //   83: iconst_0
    //   84: invokevirtual 55	android/os/Parcel:writeInt	(I)V
    //   87: goto -41 -> 46
    //   90: astore_1
    //   91: aload 4
    //   93: invokevirtual 50	android/os/Parcel:recycle	()V
    //   96: aload_3
    //   97: invokevirtual 50	android/os/Parcel:recycle	()V
    //   100: aload_1
    //   101: athrow
    // Local variable table:
    //   start	length	slot	name	signature
    //   0	102	0	this	ax
    //   0	102	1	paramab	ab
    //   0	102	2	paramAsset	com.google.android.gms.wearable.Asset
    //   3	94	3	localParcel1	android.os.Parcel
    //   7	85	4	localParcel2	android.os.Parcel
    // Exception table:
    //   from	to	target	type
    //   9	15	90	finally
    //   19	26	90	finally
    //   26	31	90	finally
    //   35	46	90	finally
    //   46	67	90	finally
    //   82	87	90	finally
  }
  
  /* Error */
  public void a(ab paramab, com.google.android.gms.wearable.PutDataRequest paramPutDataRequest)
  {
    // Byte code:
    //   0: invokestatic 23	android/os/Parcel:obtain	()Landroid/os/Parcel;
    //   3: astore_3
    //   4: invokestatic 23	android/os/Parcel:obtain	()Landroid/os/Parcel;
    //   7: astore 4
    //   9: aload_3
    //   10: ldc 25
    //   12: invokevirtual 29	android/os/Parcel:writeInterfaceToken	(Ljava/lang/String;)V
    //   15: aload_1
    //   16: ifnull +61 -> 77
    //   19: aload_1
    //   20: invokeinterface 35 1 0
    //   25: astore_1
    //   26: aload_3
    //   27: aload_1
    //   28: invokevirtual 38	android/os/Parcel:writeStrongBinder	(Landroid/os/IBinder;)V
    //   31: aload_2
    //   32: ifnull +50 -> 82
    //   35: aload_3
    //   36: iconst_1
    //   37: invokevirtual 55	android/os/Parcel:writeInt	(I)V
    //   40: aload_2
    //   41: aload_3
    //   42: iconst_0
    //   43: invokevirtual 69	com/google/android/gms/wearable/PutDataRequest:writeToParcel	(Landroid/os/Parcel;I)V
    //   46: aload_0
    //   47: getfield 15	com/google/android/gms/wearable/internal/ax:a	Landroid/os/IBinder;
    //   50: bipush 6
    //   52: aload_3
    //   53: aload 4
    //   55: iconst_0
    //   56: invokeinterface 44 5 0
    //   61: pop
    //   62: aload 4
    //   64: invokevirtual 47	android/os/Parcel:readException	()V
    //   67: aload 4
    //   69: invokevirtual 50	android/os/Parcel:recycle	()V
    //   72: aload_3
    //   73: invokevirtual 50	android/os/Parcel:recycle	()V
    //   76: return
    //   77: aconst_null
    //   78: astore_1
    //   79: goto -53 -> 26
    //   82: aload_3
    //   83: iconst_0
    //   84: invokevirtual 55	android/os/Parcel:writeInt	(I)V
    //   87: goto -41 -> 46
    //   90: astore_1
    //   91: aload 4
    //   93: invokevirtual 50	android/os/Parcel:recycle	()V
    //   96: aload_3
    //   97: invokevirtual 50	android/os/Parcel:recycle	()V
    //   100: aload_1
    //   101: athrow
    // Local variable table:
    //   start	length	slot	name	signature
    //   0	102	0	this	ax
    //   0	102	1	paramab	ab
    //   0	102	2	paramPutDataRequest	com.google.android.gms.wearable.PutDataRequest
    //   3	94	3	localParcel1	android.os.Parcel
    //   7	85	4	localParcel2	android.os.Parcel
    // Exception table:
    //   from	to	target	type
    //   9	15	90	finally
    //   19	26	90	finally
    //   26	31	90	finally
    //   35	46	90	finally
    //   46	67	90	finally
    //   82	87	90	finally
  }
  
  /* Error */
  public void a(ab paramab, com.google.android.gms.wearable.c paramc)
  {
    // Byte code:
    //   0: invokestatic 23	android/os/Parcel:obtain	()Landroid/os/Parcel;
    //   3: astore_3
    //   4: invokestatic 23	android/os/Parcel:obtain	()Landroid/os/Parcel;
    //   7: astore 4
    //   9: aload_3
    //   10: ldc 25
    //   12: invokevirtual 29	android/os/Parcel:writeInterfaceToken	(Ljava/lang/String;)V
    //   15: aload_1
    //   16: ifnull +60 -> 76
    //   19: aload_1
    //   20: invokeinterface 35 1 0
    //   25: astore_1
    //   26: aload_3
    //   27: aload_1
    //   28: invokevirtual 38	android/os/Parcel:writeStrongBinder	(Landroid/os/IBinder;)V
    //   31: aload_2
    //   32: ifnull +49 -> 81
    //   35: aload_3
    //   36: iconst_1
    //   37: invokevirtual 55	android/os/Parcel:writeInt	(I)V
    //   40: aload_2
    //   41: aload_3
    //   42: iconst_0
    //   43: invokevirtual 73	com/google/android/gms/wearable/c:writeToParcel	(Landroid/os/Parcel;I)V
    //   46: aload_0
    //   47: getfield 15	com/google/android/gms/wearable/internal/ax:a	Landroid/os/IBinder;
    //   50: iconst_2
    //   51: aload_3
    //   52: aload 4
    //   54: iconst_0
    //   55: invokeinterface 44 5 0
    //   60: pop
    //   61: aload 4
    //   63: invokevirtual 47	android/os/Parcel:readException	()V
    //   66: aload 4
    //   68: invokevirtual 50	android/os/Parcel:recycle	()V
    //   71: aload_3
    //   72: invokevirtual 50	android/os/Parcel:recycle	()V
    //   75: return
    //   76: aconst_null
    //   77: astore_1
    //   78: goto -52 -> 26
    //   81: aload_3
    //   82: iconst_0
    //   83: invokevirtual 55	android/os/Parcel:writeInt	(I)V
    //   86: goto -40 -> 46
    //   89: astore_1
    //   90: aload 4
    //   92: invokevirtual 50	android/os/Parcel:recycle	()V
    //   95: aload_3
    //   96: invokevirtual 50	android/os/Parcel:recycle	()V
    //   99: aload_1
    //   100: athrow
    // Local variable table:
    //   start	length	slot	name	signature
    //   0	101	0	this	ax
    //   0	101	1	paramab	ab
    //   0	101	2	paramc	com.google.android.gms.wearable.c
    //   3	93	3	localParcel1	android.os.Parcel
    //   7	84	4	localParcel2	android.os.Parcel
    // Exception table:
    //   from	to	target	type
    //   9	15	89	finally
    //   19	26	89	finally
    //   26	31	89	finally
    //   35	46	89	finally
    //   46	66	89	finally
    //   81	86	89	finally
  }
  
  /* Error */
  public void a(ab paramab, ao paramao)
  {
    // Byte code:
    //   0: invokestatic 23	android/os/Parcel:obtain	()Landroid/os/Parcel;
    //   3: astore_3
    //   4: invokestatic 23	android/os/Parcel:obtain	()Landroid/os/Parcel;
    //   7: astore 4
    //   9: aload_3
    //   10: ldc 25
    //   12: invokevirtual 29	android/os/Parcel:writeInterfaceToken	(Ljava/lang/String;)V
    //   15: aload_1
    //   16: ifnull +61 -> 77
    //   19: aload_1
    //   20: invokeinterface 35 1 0
    //   25: astore_1
    //   26: aload_3
    //   27: aload_1
    //   28: invokevirtual 38	android/os/Parcel:writeStrongBinder	(Landroid/os/IBinder;)V
    //   31: aload_2
    //   32: ifnull +50 -> 82
    //   35: aload_3
    //   36: iconst_1
    //   37: invokevirtual 55	android/os/Parcel:writeInt	(I)V
    //   40: aload_2
    //   41: aload_3
    //   42: iconst_0
    //   43: invokevirtual 77	com/google/android/gms/wearable/internal/ao:writeToParcel	(Landroid/os/Parcel;I)V
    //   46: aload_0
    //   47: getfield 15	com/google/android/gms/wearable/internal/ax:a	Landroid/os/IBinder;
    //   50: bipush 17
    //   52: aload_3
    //   53: aload 4
    //   55: iconst_0
    //   56: invokeinterface 44 5 0
    //   61: pop
    //   62: aload 4
    //   64: invokevirtual 47	android/os/Parcel:readException	()V
    //   67: aload 4
    //   69: invokevirtual 50	android/os/Parcel:recycle	()V
    //   72: aload_3
    //   73: invokevirtual 50	android/os/Parcel:recycle	()V
    //   76: return
    //   77: aconst_null
    //   78: astore_1
    //   79: goto -53 -> 26
    //   82: aload_3
    //   83: iconst_0
    //   84: invokevirtual 55	android/os/Parcel:writeInt	(I)V
    //   87: goto -41 -> 46
    //   90: astore_1
    //   91: aload 4
    //   93: invokevirtual 50	android/os/Parcel:recycle	()V
    //   96: aload_3
    //   97: invokevirtual 50	android/os/Parcel:recycle	()V
    //   100: aload_1
    //   101: athrow
    // Local variable table:
    //   start	length	slot	name	signature
    //   0	102	0	this	ax
    //   0	102	1	paramab	ab
    //   0	102	2	paramao	ao
    //   3	94	3	localParcel1	android.os.Parcel
    //   7	85	4	localParcel2	android.os.Parcel
    // Exception table:
    //   from	to	target	type
    //   9	15	90	finally
    //   19	26	90	finally
    //   26	31	90	finally
    //   35	46	90	finally
    //   46	67	90	finally
    //   82	87	90	finally
  }
  
  /* Error */
  public void a(ab paramab, b paramb)
  {
    // Byte code:
    //   0: invokestatic 23	android/os/Parcel:obtain	()Landroid/os/Parcel;
    //   3: astore_3
    //   4: invokestatic 23	android/os/Parcel:obtain	()Landroid/os/Parcel;
    //   7: astore 4
    //   9: aload_3
    //   10: ldc 25
    //   12: invokevirtual 29	android/os/Parcel:writeInterfaceToken	(Ljava/lang/String;)V
    //   15: aload_1
    //   16: ifnull +61 -> 77
    //   19: aload_1
    //   20: invokeinterface 35 1 0
    //   25: astore_1
    //   26: aload_3
    //   27: aload_1
    //   28: invokevirtual 38	android/os/Parcel:writeStrongBinder	(Landroid/os/IBinder;)V
    //   31: aload_2
    //   32: ifnull +50 -> 82
    //   35: aload_3
    //   36: iconst_1
    //   37: invokevirtual 55	android/os/Parcel:writeInt	(I)V
    //   40: aload_2
    //   41: aload_3
    //   42: iconst_0
    //   43: invokevirtual 81	com/google/android/gms/wearable/internal/b:writeToParcel	(Landroid/os/Parcel;I)V
    //   46: aload_0
    //   47: getfield 15	com/google/android/gms/wearable/internal/ax:a	Landroid/os/IBinder;
    //   50: bipush 16
    //   52: aload_3
    //   53: aload 4
    //   55: iconst_0
    //   56: invokeinterface 44 5 0
    //   61: pop
    //   62: aload 4
    //   64: invokevirtual 47	android/os/Parcel:readException	()V
    //   67: aload 4
    //   69: invokevirtual 50	android/os/Parcel:recycle	()V
    //   72: aload_3
    //   73: invokevirtual 50	android/os/Parcel:recycle	()V
    //   76: return
    //   77: aconst_null
    //   78: astore_1
    //   79: goto -53 -> 26
    //   82: aload_3
    //   83: iconst_0
    //   84: invokevirtual 55	android/os/Parcel:writeInt	(I)V
    //   87: goto -41 -> 46
    //   90: astore_1
    //   91: aload 4
    //   93: invokevirtual 50	android/os/Parcel:recycle	()V
    //   96: aload_3
    //   97: invokevirtual 50	android/os/Parcel:recycle	()V
    //   100: aload_1
    //   101: athrow
    // Local variable table:
    //   start	length	slot	name	signature
    //   0	102	0	this	ax
    //   0	102	1	paramab	ab
    //   0	102	2	paramb	b
    //   3	94	3	localParcel1	android.os.Parcel
    //   7	85	4	localParcel2	android.os.Parcel
    // Exception table:
    //   from	to	target	type
    //   9	15	90	finally
    //   19	26	90	finally
    //   26	31	90	finally
    //   35	46	90	finally
    //   46	67	90	finally
    //   82	87	90	finally
  }
  
  /* Error */
  public void a(ab paramab, String paramString1, String paramString2, byte[] paramArrayOfByte)
  {
    // Byte code:
    //   0: invokestatic 23	android/os/Parcel:obtain	()Landroid/os/Parcel;
    //   3: astore 5
    //   5: invokestatic 23	android/os/Parcel:obtain	()Landroid/os/Parcel;
    //   8: astore 6
    //   10: aload 5
    //   12: ldc 25
    //   14: invokevirtual 29	android/os/Parcel:writeInterfaceToken	(Ljava/lang/String;)V
    //   17: aload_1
    //   18: ifnull +68 -> 86
    //   21: aload_1
    //   22: invokeinterface 35 1 0
    //   27: astore_1
    //   28: aload 5
    //   30: aload_1
    //   31: invokevirtual 38	android/os/Parcel:writeStrongBinder	(Landroid/os/IBinder;)V
    //   34: aload 5
    //   36: aload_2
    //   37: invokevirtual 85	android/os/Parcel:writeString	(Ljava/lang/String;)V
    //   40: aload 5
    //   42: aload_3
    //   43: invokevirtual 85	android/os/Parcel:writeString	(Ljava/lang/String;)V
    //   46: aload 5
    //   48: aload 4
    //   50: invokevirtual 89	android/os/Parcel:writeByteArray	([B)V
    //   53: aload_0
    //   54: getfield 15	com/google/android/gms/wearable/internal/ax:a	Landroid/os/IBinder;
    //   57: bipush 12
    //   59: aload 5
    //   61: aload 6
    //   63: iconst_0
    //   64: invokeinterface 44 5 0
    //   69: pop
    //   70: aload 6
    //   72: invokevirtual 47	android/os/Parcel:readException	()V
    //   75: aload 6
    //   77: invokevirtual 50	android/os/Parcel:recycle	()V
    //   80: aload 5
    //   82: invokevirtual 50	android/os/Parcel:recycle	()V
    //   85: return
    //   86: aconst_null
    //   87: astore_1
    //   88: goto -60 -> 28
    //   91: astore_1
    //   92: aload 6
    //   94: invokevirtual 50	android/os/Parcel:recycle	()V
    //   97: aload 5
    //   99: invokevirtual 50	android/os/Parcel:recycle	()V
    //   102: aload_1
    //   103: athrow
    // Local variable table:
    //   start	length	slot	name	signature
    //   0	104	0	this	ax
    //   0	104	1	paramab	ab
    //   0	104	2	paramString1	String
    //   0	104	3	paramString2	String
    //   0	104	4	paramArrayOfByte	byte[]
    //   3	95	5	localParcel1	android.os.Parcel
    //   8	85	6	localParcel2	android.os.Parcel
    // Exception table:
    //   from	to	target	type
    //   10	17	91	finally
    //   21	28	91	finally
    //   28	75	91	finally
  }
  
  public IBinder asBinder()
  {
    return this.a;
  }
  
  /* Error */
  public void b(ab paramab)
  {
    // Byte code:
    //   0: invokestatic 23	android/os/Parcel:obtain	()Landroid/os/Parcel;
    //   3: astore_2
    //   4: invokestatic 23	android/os/Parcel:obtain	()Landroid/os/Parcel;
    //   7: astore_3
    //   8: aload_2
    //   9: ldc 25
    //   11: invokevirtual 29	android/os/Parcel:writeInterfaceToken	(Ljava/lang/String;)V
    //   14: aload_1
    //   15: ifnull +42 -> 57
    //   18: aload_1
    //   19: invokeinterface 35 1 0
    //   24: astore_1
    //   25: aload_2
    //   26: aload_1
    //   27: invokevirtual 38	android/os/Parcel:writeStrongBinder	(Landroid/os/IBinder;)V
    //   30: aload_0
    //   31: getfield 15	com/google/android/gms/wearable/internal/ax:a	Landroid/os/IBinder;
    //   34: iconst_4
    //   35: aload_2
    //   36: aload_3
    //   37: iconst_0
    //   38: invokeinterface 44 5 0
    //   43: pop
    //   44: aload_3
    //   45: invokevirtual 47	android/os/Parcel:readException	()V
    //   48: aload_3
    //   49: invokevirtual 50	android/os/Parcel:recycle	()V
    //   52: aload_2
    //   53: invokevirtual 50	android/os/Parcel:recycle	()V
    //   56: return
    //   57: aconst_null
    //   58: astore_1
    //   59: goto -34 -> 25
    //   62: astore_1
    //   63: aload_3
    //   64: invokevirtual 50	android/os/Parcel:recycle	()V
    //   67: aload_2
    //   68: invokevirtual 50	android/os/Parcel:recycle	()V
    //   71: aload_1
    //   72: athrow
    // Local variable table:
    //   start	length	slot	name	signature
    //   0	73	0	this	ax
    //   0	73	1	paramab	ab
    //   3	65	2	localParcel1	android.os.Parcel
    //   7	57	3	localParcel2	android.os.Parcel
    // Exception table:
    //   from	to	target	type
    //   8	14	62	finally
    //   18	25	62	finally
    //   25	48	62	finally
  }
  
  /* Error */
  public void b(ab paramab, android.net.Uri paramUri)
  {
    // Byte code:
    //   0: invokestatic 23	android/os/Parcel:obtain	()Landroid/os/Parcel;
    //   3: astore_3
    //   4: invokestatic 23	android/os/Parcel:obtain	()Landroid/os/Parcel;
    //   7: astore 4
    //   9: aload_3
    //   10: ldc 25
    //   12: invokevirtual 29	android/os/Parcel:writeInterfaceToken	(Ljava/lang/String;)V
    //   15: aload_1
    //   16: ifnull +61 -> 77
    //   19: aload_1
    //   20: invokeinterface 35 1 0
    //   25: astore_1
    //   26: aload_3
    //   27: aload_1
    //   28: invokevirtual 38	android/os/Parcel:writeStrongBinder	(Landroid/os/IBinder;)V
    //   31: aload_2
    //   32: ifnull +50 -> 82
    //   35: aload_3
    //   36: iconst_1
    //   37: invokevirtual 55	android/os/Parcel:writeInt	(I)V
    //   40: aload_2
    //   41: aload_3
    //   42: iconst_0
    //   43: invokevirtual 61	android/net/Uri:writeToParcel	(Landroid/os/Parcel;I)V
    //   46: aload_0
    //   47: getfield 15	com/google/android/gms/wearable/internal/ax:a	Landroid/os/IBinder;
    //   50: bipush 9
    //   52: aload_3
    //   53: aload 4
    //   55: iconst_0
    //   56: invokeinterface 44 5 0
    //   61: pop
    //   62: aload 4
    //   64: invokevirtual 47	android/os/Parcel:readException	()V
    //   67: aload 4
    //   69: invokevirtual 50	android/os/Parcel:recycle	()V
    //   72: aload_3
    //   73: invokevirtual 50	android/os/Parcel:recycle	()V
    //   76: return
    //   77: aconst_null
    //   78: astore_1
    //   79: goto -53 -> 26
    //   82: aload_3
    //   83: iconst_0
    //   84: invokevirtual 55	android/os/Parcel:writeInt	(I)V
    //   87: goto -41 -> 46
    //   90: astore_1
    //   91: aload 4
    //   93: invokevirtual 50	android/os/Parcel:recycle	()V
    //   96: aload_3
    //   97: invokevirtual 50	android/os/Parcel:recycle	()V
    //   100: aload_1
    //   101: athrow
    // Local variable table:
    //   start	length	slot	name	signature
    //   0	102	0	this	ax
    //   0	102	1	paramab	ab
    //   0	102	2	paramUri	android.net.Uri
    //   3	94	3	localParcel1	android.os.Parcel
    //   7	85	4	localParcel2	android.os.Parcel
    // Exception table:
    //   from	to	target	type
    //   9	15	90	finally
    //   19	26	90	finally
    //   26	31	90	finally
    //   35	46	90	finally
    //   46	67	90	finally
    //   82	87	90	finally
  }
  
  /* Error */
  public void c(ab paramab)
  {
    // Byte code:
    //   0: invokestatic 23	android/os/Parcel:obtain	()Landroid/os/Parcel;
    //   3: astore_2
    //   4: invokestatic 23	android/os/Parcel:obtain	()Landroid/os/Parcel;
    //   7: astore_3
    //   8: aload_2
    //   9: ldc 25
    //   11: invokevirtual 29	android/os/Parcel:writeInterfaceToken	(Ljava/lang/String;)V
    //   14: aload_1
    //   15: ifnull +42 -> 57
    //   18: aload_1
    //   19: invokeinterface 35 1 0
    //   24: astore_1
    //   25: aload_2
    //   26: aload_1
    //   27: invokevirtual 38	android/os/Parcel:writeStrongBinder	(Landroid/os/IBinder;)V
    //   30: aload_0
    //   31: getfield 15	com/google/android/gms/wearable/internal/ax:a	Landroid/os/IBinder;
    //   34: iconst_5
    //   35: aload_2
    //   36: aload_3
    //   37: iconst_0
    //   38: invokeinterface 44 5 0
    //   43: pop
    //   44: aload_3
    //   45: invokevirtual 47	android/os/Parcel:readException	()V
    //   48: aload_3
    //   49: invokevirtual 50	android/os/Parcel:recycle	()V
    //   52: aload_2
    //   53: invokevirtual 50	android/os/Parcel:recycle	()V
    //   56: return
    //   57: aconst_null
    //   58: astore_1
    //   59: goto -34 -> 25
    //   62: astore_1
    //   63: aload_3
    //   64: invokevirtual 50	android/os/Parcel:recycle	()V
    //   67: aload_2
    //   68: invokevirtual 50	android/os/Parcel:recycle	()V
    //   71: aload_1
    //   72: athrow
    // Local variable table:
    //   start	length	slot	name	signature
    //   0	73	0	this	ax
    //   0	73	1	paramab	ab
    //   3	65	2	localParcel1	android.os.Parcel
    //   7	57	3	localParcel2	android.os.Parcel
    // Exception table:
    //   from	to	target	type
    //   8	14	62	finally
    //   18	25	62	finally
    //   25	48	62	finally
  }
  
  /* Error */
  public void c(ab paramab, android.net.Uri paramUri)
  {
    // Byte code:
    //   0: invokestatic 23	android/os/Parcel:obtain	()Landroid/os/Parcel;
    //   3: astore_3
    //   4: invokestatic 23	android/os/Parcel:obtain	()Landroid/os/Parcel;
    //   7: astore 4
    //   9: aload_3
    //   10: ldc 25
    //   12: invokevirtual 29	android/os/Parcel:writeInterfaceToken	(Ljava/lang/String;)V
    //   15: aload_1
    //   16: ifnull +61 -> 77
    //   19: aload_1
    //   20: invokeinterface 35 1 0
    //   25: astore_1
    //   26: aload_3
    //   27: aload_1
    //   28: invokevirtual 38	android/os/Parcel:writeStrongBinder	(Landroid/os/IBinder;)V
    //   31: aload_2
    //   32: ifnull +50 -> 82
    //   35: aload_3
    //   36: iconst_1
    //   37: invokevirtual 55	android/os/Parcel:writeInt	(I)V
    //   40: aload_2
    //   41: aload_3
    //   42: iconst_0
    //   43: invokevirtual 61	android/net/Uri:writeToParcel	(Landroid/os/Parcel;I)V
    //   46: aload_0
    //   47: getfield 15	com/google/android/gms/wearable/internal/ax:a	Landroid/os/IBinder;
    //   50: bipush 11
    //   52: aload_3
    //   53: aload 4
    //   55: iconst_0
    //   56: invokeinterface 44 5 0
    //   61: pop
    //   62: aload 4
    //   64: invokevirtual 47	android/os/Parcel:readException	()V
    //   67: aload 4
    //   69: invokevirtual 50	android/os/Parcel:recycle	()V
    //   72: aload_3
    //   73: invokevirtual 50	android/os/Parcel:recycle	()V
    //   76: return
    //   77: aconst_null
    //   78: astore_1
    //   79: goto -53 -> 26
    //   82: aload_3
    //   83: iconst_0
    //   84: invokevirtual 55	android/os/Parcel:writeInt	(I)V
    //   87: goto -41 -> 46
    //   90: astore_1
    //   91: aload 4
    //   93: invokevirtual 50	android/os/Parcel:recycle	()V
    //   96: aload_3
    //   97: invokevirtual 50	android/os/Parcel:recycle	()V
    //   100: aload_1
    //   101: athrow
    // Local variable table:
    //   start	length	slot	name	signature
    //   0	102	0	this	ax
    //   0	102	1	paramab	ab
    //   0	102	2	paramUri	android.net.Uri
    //   3	94	3	localParcel1	android.os.Parcel
    //   7	85	4	localParcel2	android.os.Parcel
    // Exception table:
    //   from	to	target	type
    //   9	15	90	finally
    //   19	26	90	finally
    //   26	31	90	finally
    //   35	46	90	finally
    //   46	67	90	finally
    //   82	87	90	finally
  }
  
  /* Error */
  public void d(ab paramab)
  {
    // Byte code:
    //   0: invokestatic 23	android/os/Parcel:obtain	()Landroid/os/Parcel;
    //   3: astore_2
    //   4: invokestatic 23	android/os/Parcel:obtain	()Landroid/os/Parcel;
    //   7: astore_3
    //   8: aload_2
    //   9: ldc 25
    //   11: invokevirtual 29	android/os/Parcel:writeInterfaceToken	(Ljava/lang/String;)V
    //   14: aload_1
    //   15: ifnull +43 -> 58
    //   18: aload_1
    //   19: invokeinterface 35 1 0
    //   24: astore_1
    //   25: aload_2
    //   26: aload_1
    //   27: invokevirtual 38	android/os/Parcel:writeStrongBinder	(Landroid/os/IBinder;)V
    //   30: aload_0
    //   31: getfield 15	com/google/android/gms/wearable/internal/ax:a	Landroid/os/IBinder;
    //   34: bipush 8
    //   36: aload_2
    //   37: aload_3
    //   38: iconst_0
    //   39: invokeinterface 44 5 0
    //   44: pop
    //   45: aload_3
    //   46: invokevirtual 47	android/os/Parcel:readException	()V
    //   49: aload_3
    //   50: invokevirtual 50	android/os/Parcel:recycle	()V
    //   53: aload_2
    //   54: invokevirtual 50	android/os/Parcel:recycle	()V
    //   57: return
    //   58: aconst_null
    //   59: astore_1
    //   60: goto -35 -> 25
    //   63: astore_1
    //   64: aload_3
    //   65: invokevirtual 50	android/os/Parcel:recycle	()V
    //   68: aload_2
    //   69: invokevirtual 50	android/os/Parcel:recycle	()V
    //   72: aload_1
    //   73: athrow
    // Local variable table:
    //   start	length	slot	name	signature
    //   0	74	0	this	ax
    //   0	74	1	paramab	ab
    //   3	66	2	localParcel1	android.os.Parcel
    //   7	58	3	localParcel2	android.os.Parcel
    // Exception table:
    //   from	to	target	type
    //   8	14	63	finally
    //   18	25	63	finally
    //   25	49	63	finally
  }
  
  /* Error */
  public void e(ab paramab)
  {
    // Byte code:
    //   0: invokestatic 23	android/os/Parcel:obtain	()Landroid/os/Parcel;
    //   3: astore_2
    //   4: invokestatic 23	android/os/Parcel:obtain	()Landroid/os/Parcel;
    //   7: astore_3
    //   8: aload_2
    //   9: ldc 25
    //   11: invokevirtual 29	android/os/Parcel:writeInterfaceToken	(Ljava/lang/String;)V
    //   14: aload_1
    //   15: ifnull +43 -> 58
    //   18: aload_1
    //   19: invokeinterface 35 1 0
    //   24: astore_1
    //   25: aload_2
    //   26: aload_1
    //   27: invokevirtual 38	android/os/Parcel:writeStrongBinder	(Landroid/os/IBinder;)V
    //   30: aload_0
    //   31: getfield 15	com/google/android/gms/wearable/internal/ax:a	Landroid/os/IBinder;
    //   34: bipush 14
    //   36: aload_2
    //   37: aload_3
    //   38: iconst_0
    //   39: invokeinterface 44 5 0
    //   44: pop
    //   45: aload_3
    //   46: invokevirtual 47	android/os/Parcel:readException	()V
    //   49: aload_3
    //   50: invokevirtual 50	android/os/Parcel:recycle	()V
    //   53: aload_2
    //   54: invokevirtual 50	android/os/Parcel:recycle	()V
    //   57: return
    //   58: aconst_null
    //   59: astore_1
    //   60: goto -35 -> 25
    //   63: astore_1
    //   64: aload_3
    //   65: invokevirtual 50	android/os/Parcel:recycle	()V
    //   68: aload_2
    //   69: invokevirtual 50	android/os/Parcel:recycle	()V
    //   72: aload_1
    //   73: athrow
    // Local variable table:
    //   start	length	slot	name	signature
    //   0	74	0	this	ax
    //   0	74	1	paramab	ab
    //   3	66	2	localParcel1	android.os.Parcel
    //   7	58	3	localParcel2	android.os.Parcel
    // Exception table:
    //   from	to	target	type
    //   8	14	63	finally
    //   18	25	63	finally
    //   25	49	63	finally
  }
  
  /* Error */
  public void f(ab paramab)
  {
    // Byte code:
    //   0: invokestatic 23	android/os/Parcel:obtain	()Landroid/os/Parcel;
    //   3: astore_2
    //   4: invokestatic 23	android/os/Parcel:obtain	()Landroid/os/Parcel;
    //   7: astore_3
    //   8: aload_2
    //   9: ldc 25
    //   11: invokevirtual 29	android/os/Parcel:writeInterfaceToken	(Ljava/lang/String;)V
    //   14: aload_1
    //   15: ifnull +43 -> 58
    //   18: aload_1
    //   19: invokeinterface 35 1 0
    //   24: astore_1
    //   25: aload_2
    //   26: aload_1
    //   27: invokevirtual 38	android/os/Parcel:writeStrongBinder	(Landroid/os/IBinder;)V
    //   30: aload_0
    //   31: getfield 15	com/google/android/gms/wearable/internal/ax:a	Landroid/os/IBinder;
    //   34: bipush 15
    //   36: aload_2
    //   37: aload_3
    //   38: iconst_0
    //   39: invokeinterface 44 5 0
    //   44: pop
    //   45: aload_3
    //   46: invokevirtual 47	android/os/Parcel:readException	()V
    //   49: aload_3
    //   50: invokevirtual 50	android/os/Parcel:recycle	()V
    //   53: aload_2
    //   54: invokevirtual 50	android/os/Parcel:recycle	()V
    //   57: return
    //   58: aconst_null
    //   59: astore_1
    //   60: goto -35 -> 25
    //   63: astore_1
    //   64: aload_3
    //   65: invokevirtual 50	android/os/Parcel:recycle	()V
    //   68: aload_2
    //   69: invokevirtual 50	android/os/Parcel:recycle	()V
    //   72: aload_1
    //   73: athrow
    // Local variable table:
    //   start	length	slot	name	signature
    //   0	74	0	this	ax
    //   0	74	1	paramab	ab
    //   3	66	2	localParcel1	android.os.Parcel
    //   7	58	3	localParcel2	android.os.Parcel
    // Exception table:
    //   from	to	target	type
    //   8	14	63	finally
    //   18	25	63	finally
    //   25	49	63	finally
  }
  
  /* Error */
  public void g(ab paramab)
  {
    // Byte code:
    //   0: invokestatic 23	android/os/Parcel:obtain	()Landroid/os/Parcel;
    //   3: astore_2
    //   4: invokestatic 23	android/os/Parcel:obtain	()Landroid/os/Parcel;
    //   7: astore_3
    //   8: aload_2
    //   9: ldc 25
    //   11: invokevirtual 29	android/os/Parcel:writeInterfaceToken	(Ljava/lang/String;)V
    //   14: aload_1
    //   15: ifnull +43 -> 58
    //   18: aload_1
    //   19: invokeinterface 35 1 0
    //   24: astore_1
    //   25: aload_2
    //   26: aload_1
    //   27: invokevirtual 38	android/os/Parcel:writeStrongBinder	(Landroid/os/IBinder;)V
    //   30: aload_0
    //   31: getfield 15	com/google/android/gms/wearable/internal/ax:a	Landroid/os/IBinder;
    //   34: bipush 18
    //   36: aload_2
    //   37: aload_3
    //   38: iconst_0
    //   39: invokeinterface 44 5 0
    //   44: pop
    //   45: aload_3
    //   46: invokevirtual 47	android/os/Parcel:readException	()V
    //   49: aload_3
    //   50: invokevirtual 50	android/os/Parcel:recycle	()V
    //   53: aload_2
    //   54: invokevirtual 50	android/os/Parcel:recycle	()V
    //   57: return
    //   58: aconst_null
    //   59: astore_1
    //   60: goto -35 -> 25
    //   63: astore_1
    //   64: aload_3
    //   65: invokevirtual 50	android/os/Parcel:recycle	()V
    //   68: aload_2
    //   69: invokevirtual 50	android/os/Parcel:recycle	()V
    //   72: aload_1
    //   73: athrow
    // Local variable table:
    //   start	length	slot	name	signature
    //   0	74	0	this	ax
    //   0	74	1	paramab	ab
    //   3	66	2	localParcel1	android.os.Parcel
    //   7	58	3	localParcel2	android.os.Parcel
    // Exception table:
    //   from	to	target	type
    //   8	14	63	finally
    //   18	25	63	finally
    //   25	49	63	finally
  }
  
  /* Error */
  public void h(ab paramab)
  {
    // Byte code:
    //   0: invokestatic 23	android/os/Parcel:obtain	()Landroid/os/Parcel;
    //   3: astore_2
    //   4: invokestatic 23	android/os/Parcel:obtain	()Landroid/os/Parcel;
    //   7: astore_3
    //   8: aload_2
    //   9: ldc 25
    //   11: invokevirtual 29	android/os/Parcel:writeInterfaceToken	(Ljava/lang/String;)V
    //   14: aload_1
    //   15: ifnull +43 -> 58
    //   18: aload_1
    //   19: invokeinterface 35 1 0
    //   24: astore_1
    //   25: aload_2
    //   26: aload_1
    //   27: invokevirtual 38	android/os/Parcel:writeStrongBinder	(Landroid/os/IBinder;)V
    //   30: aload_0
    //   31: getfield 15	com/google/android/gms/wearable/internal/ax:a	Landroid/os/IBinder;
    //   34: bipush 19
    //   36: aload_2
    //   37: aload_3
    //   38: iconst_0
    //   39: invokeinterface 44 5 0
    //   44: pop
    //   45: aload_3
    //   46: invokevirtual 47	android/os/Parcel:readException	()V
    //   49: aload_3
    //   50: invokevirtual 50	android/os/Parcel:recycle	()V
    //   53: aload_2
    //   54: invokevirtual 50	android/os/Parcel:recycle	()V
    //   57: return
    //   58: aconst_null
    //   59: astore_1
    //   60: goto -35 -> 25
    //   63: astore_1
    //   64: aload_3
    //   65: invokevirtual 50	android/os/Parcel:recycle	()V
    //   68: aload_2
    //   69: invokevirtual 50	android/os/Parcel:recycle	()V
    //   72: aload_1
    //   73: athrow
    // Local variable table:
    //   start	length	slot	name	signature
    //   0	74	0	this	ax
    //   0	74	1	paramab	ab
    //   3	66	2	localParcel1	android.os.Parcel
    //   7	58	3	localParcel2	android.os.Parcel
    // Exception table:
    //   from	to	target	type
    //   8	14	63	finally
    //   18	25	63	finally
    //   25	49	63	finally
  }
}


/* Location:              /Users/amaurremi/uw/stringoid/static-dynamic-comparison/apps/retrica/com.venticake.retrica-21-dex2jar.jar!/com/google/android/gms/wearable/internal/ax.class
 * Java compiler version: 6 (50.0)
 * JD-Core Version:       0.7.1
 */