package com.google.analytics.midtier.proto.containertag;

import com.google.tagmanager.protobuf.CodedOutputStream;
import com.google.tagmanager.protobuf.GeneratedMessageLite.ExtendableMessage;
import com.google.tagmanager.protobuf.GeneratedMessageLite.ExtendableMessage.a;
import com.google.tagmanager.protobuf.GeneratedMessageLite.b;
import com.google.tagmanager.protobuf.GeneratedMessageLite.c;
import com.google.tagmanager.protobuf.c;
import com.google.tagmanager.protobuf.e;
import com.google.tagmanager.protobuf.f;
import com.google.tagmanager.protobuf.g;
import com.google.tagmanager.protobuf.i;
import com.google.tagmanager.protobuf.i.a;
import com.google.tagmanager.protobuf.i.b;
import com.google.tagmanager.protobuf.n;
import com.google.tagmanager.protobuf.p;
import com.google.tagmanager.protobuf.q;
import java.util.ArrayList;
import java.util.Collections;
import java.util.List;

public final class TypeSystem
{
  public static final class Value
    extends GeneratedMessageLite.ExtendableMessage<Value>
    implements TypeSystem.a
  {
    public static q<Value> gW = new c()
    {
      public TypeSystem.Value n(f paramAnonymousf, g paramAnonymousg)
      {
        return new TypeSystem.Value(paramAnonymousf, paramAnonymousg, null);
      }
    };
    private static volatile p gX = null;
    private static final Value hh = new Value(true);
    private static final long serialVersionUID = 0L;
    private int bitField0_;
    private boolean boolean_;
    private boolean containsReferences_;
    private List<Escaping> escaping_;
    private Object functionId_;
    private long integer_;
    private List<Value> listItem_;
    private Object macroReference_;
    private List<Value> mapKey_;
    private List<Value> mapValue_;
    private byte memoizedIsInitialized = -1;
    private int memoizedSerializedSize = -1;
    private Object string_;
    private List<Value> templateToken_;
    private Type type_;
    private final e unknownFields;
    
    static
    {
      hh.fH();
    }
    
    private Value(GeneratedMessageLite.b<Value, ?> paramb)
    {
      super();
      this.unknownFields = paramb.BE();
    }
    
    /* Error */
    private Value(f paramf, g paramg)
    {
      // Byte code:
      //   0: aload_0
      //   1: invokespecial 104	com/google/tagmanager/protobuf/GeneratedMessageLite$ExtendableMessage:<init>	()V
      //   4: aload_0
      //   5: iconst_m1
      //   6: putfield 84	com/google/analytics/midtier/proto/containertag/TypeSystem$Value:memoizedIsInitialized	B
      //   9: aload_0
      //   10: iconst_m1
      //   11: putfield 86	com/google/analytics/midtier/proto/containertag/TypeSystem$Value:memoizedSerializedSize	I
      //   14: aload_0
      //   15: invokespecial 78	com/google/analytics/midtier/proto/containertag/TypeSystem$Value:fH	()V
      //   18: iconst_0
      //   19: istore_3
      //   20: invokestatic 110	com/google/tagmanager/protobuf/e:AN	()Lcom/google/tagmanager/protobuf/e$b;
      //   23: astore 11
      //   25: aload 11
      //   27: invokestatic 115	com/google/tagmanager/protobuf/CodedOutputStream:a	(Ljava/io/OutputStream;)Lcom/google/tagmanager/protobuf/CodedOutputStream;
      //   30: astore 12
      //   32: iconst_0
      //   33: istore 4
      //   35: iload 4
      //   37: ifne +1273 -> 1310
      //   40: iload_3
      //   41: istore 5
      //   43: aload_1
      //   44: invokevirtual 121	com/google/tagmanager/protobuf/f:AT	()I
      //   47: istore 9
      //   49: iload 9
      //   51: lookupswitch	default:+1476->1527, 0:+1492->1543, 8:+149->200, 18:+241->292, 26:+285->336, 34:+350->401, 42:+418->469, 50:+486->537, 58:+530->581, 64:+575->626, 72:+613->664, 80:+651->702, 82:+773->824, 90:+1150->1201, 96:+1221->1272
      //   172: iload_3
      //   173: istore 5
      //   175: aload_0
      //   176: aload_1
      //   177: aload 12
      //   179: aload_2
      //   180: iload 9
      //   182: invokevirtual 124	com/google/analytics/midtier/proto/containertag/TypeSystem$Value:a	(Lcom/google/tagmanager/protobuf/f;Lcom/google/tagmanager/protobuf/CodedOutputStream;Lcom/google/tagmanager/protobuf/g;I)Z
      //   185: ifne +1112 -> 1297
      //   188: iconst_1
      //   189: istore 5
      //   191: iload_3
      //   192: istore 4
      //   194: iload 5
      //   196: istore_3
      //   197: goto +1333 -> 1530
      //   200: iload_3
      //   201: istore 5
      //   203: aload_1
      //   204: invokevirtual 127	com/google/tagmanager/protobuf/f:Bd	()I
      //   207: istore 6
      //   209: iload_3
      //   210: istore 5
      //   212: iload 6
      //   214: invokestatic 131	com/google/analytics/midtier/proto/containertag/TypeSystem$Value$Type:aV	(I)Lcom/google/analytics/midtier/proto/containertag/TypeSystem$Value$Type;
      //   217: astore 13
      //   219: aload 13
      //   221: ifnonnull +36 -> 257
      //   224: iload_3
      //   225: istore 5
      //   227: aload 12
      //   229: iload 9
      //   231: invokevirtual 135	com/google/tagmanager/protobuf/CodedOutputStream:fn	(I)V
      //   234: iload_3
      //   235: istore 5
      //   237: aload 12
      //   239: iload 6
      //   241: invokevirtual 135	com/google/tagmanager/protobuf/CodedOutputStream:fn	(I)V
      //   244: iload_3
      //   245: istore 5
      //   247: iload 4
      //   249: istore_3
      //   250: iload 5
      //   252: istore 4
      //   254: goto +1276 -> 1530
      //   257: iload_3
      //   258: istore 5
      //   260: aload_0
      //   261: aload_0
      //   262: getfield 137	com/google/analytics/midtier/proto/containertag/TypeSystem$Value:bitField0_	I
      //   265: iconst_1
      //   266: ior
      //   267: putfield 137	com/google/analytics/midtier/proto/containertag/TypeSystem$Value:bitField0_	I
      //   270: iload_3
      //   271: istore 5
      //   273: aload_0
      //   274: aload 13
      //   276: putfield 139	com/google/analytics/midtier/proto/containertag/TypeSystem$Value:type_	Lcom/google/analytics/midtier/proto/containertag/TypeSystem$Value$Type;
      //   279: iload_3
      //   280: istore 5
      //   282: iload 4
      //   284: istore_3
      //   285: iload 5
      //   287: istore 4
      //   289: goto +1241 -> 1530
      //   292: iload_3
      //   293: istore 5
      //   295: aload_1
      //   296: invokevirtual 142	com/google/tagmanager/protobuf/f:Bb	()Lcom/google/tagmanager/protobuf/e;
      //   299: astore 13
      //   301: iload_3
      //   302: istore 5
      //   304: aload_0
      //   305: aload_0
      //   306: getfield 137	com/google/analytics/midtier/proto/containertag/TypeSystem$Value:bitField0_	I
      //   309: iconst_2
      //   310: ior
      //   311: putfield 137	com/google/analytics/midtier/proto/containertag/TypeSystem$Value:bitField0_	I
      //   314: iload_3
      //   315: istore 5
      //   317: aload_0
      //   318: aload 13
      //   320: putfield 144	com/google/analytics/midtier/proto/containertag/TypeSystem$Value:string_	Ljava/lang/Object;
      //   323: iload_3
      //   324: istore 5
      //   326: iload 4
      //   328: istore_3
      //   329: iload 5
      //   331: istore 4
      //   333: goto +1197 -> 1530
      //   336: iload_3
      //   337: iconst_4
      //   338: iand
      //   339: iconst_4
      //   340: if_icmpeq +1181 -> 1521
      //   343: iload_3
      //   344: istore 5
      //   346: aload_0
      //   347: new 146	java/util/ArrayList
      //   350: dup
      //   351: invokespecial 147	java/util/ArrayList:<init>	()V
      //   354: putfield 149	com/google/analytics/midtier/proto/containertag/TypeSystem$Value:listItem_	Ljava/util/List;
      //   357: iload_3
      //   358: iconst_4
      //   359: ior
      //   360: istore 7
      //   362: iload 7
      //   364: istore_3
      //   365: iload 7
      //   367: istore 5
      //   369: iload 7
      //   371: istore 6
      //   373: aload_0
      //   374: getfield 149	com/google/analytics/midtier/proto/containertag/TypeSystem$Value:listItem_	Ljava/util/List;
      //   377: aload_1
      //   378: getstatic 68	com/google/analytics/midtier/proto/containertag/TypeSystem$Value:gW	Lcom/google/tagmanager/protobuf/q;
      //   381: aload_2
      //   382: invokevirtual 152	com/google/tagmanager/protobuf/f:a	(Lcom/google/tagmanager/protobuf/q;Lcom/google/tagmanager/protobuf/g;)Lcom/google/tagmanager/protobuf/n;
      //   385: invokeinterface 158 2 0
      //   390: pop
      //   391: iload 4
      //   393: istore_3
      //   394: iload 7
      //   396: istore 4
      //   398: goto +1132 -> 1530
      //   401: iload_3
      //   402: bipush 8
      //   404: iand
      //   405: bipush 8
      //   407: if_icmpeq +1108 -> 1515
      //   410: iload_3
      //   411: istore 5
      //   413: aload_0
      //   414: new 146	java/util/ArrayList
      //   417: dup
      //   418: invokespecial 147	java/util/ArrayList:<init>	()V
      //   421: putfield 160	com/google/analytics/midtier/proto/containertag/TypeSystem$Value:mapKey_	Ljava/util/List;
      //   424: iload_3
      //   425: bipush 8
      //   427: ior
      //   428: istore 7
      //   430: iload 7
      //   432: istore_3
      //   433: iload 7
      //   435: istore 5
      //   437: iload 7
      //   439: istore 6
      //   441: aload_0
      //   442: getfield 160	com/google/analytics/midtier/proto/containertag/TypeSystem$Value:mapKey_	Ljava/util/List;
      //   445: aload_1
      //   446: getstatic 68	com/google/analytics/midtier/proto/containertag/TypeSystem$Value:gW	Lcom/google/tagmanager/protobuf/q;
      //   449: aload_2
      //   450: invokevirtual 152	com/google/tagmanager/protobuf/f:a	(Lcom/google/tagmanager/protobuf/q;Lcom/google/tagmanager/protobuf/g;)Lcom/google/tagmanager/protobuf/n;
      //   453: invokeinterface 158 2 0
      //   458: pop
      //   459: iload 4
      //   461: istore_3
      //   462: iload 7
      //   464: istore 4
      //   466: goto +1064 -> 1530
      //   469: iload_3
      //   470: bipush 16
      //   472: iand
      //   473: bipush 16
      //   475: if_icmpeq +1034 -> 1509
      //   478: iload_3
      //   479: istore 5
      //   481: aload_0
      //   482: new 146	java/util/ArrayList
      //   485: dup
      //   486: invokespecial 147	java/util/ArrayList:<init>	()V
      //   489: putfield 162	com/google/analytics/midtier/proto/containertag/TypeSystem$Value:mapValue_	Ljava/util/List;
      //   492: iload_3
      //   493: bipush 16
      //   495: ior
      //   496: istore 7
      //   498: iload 7
      //   500: istore_3
      //   501: iload 7
      //   503: istore 5
      //   505: iload 7
      //   507: istore 6
      //   509: aload_0
      //   510: getfield 162	com/google/analytics/midtier/proto/containertag/TypeSystem$Value:mapValue_	Ljava/util/List;
      //   513: aload_1
      //   514: getstatic 68	com/google/analytics/midtier/proto/containertag/TypeSystem$Value:gW	Lcom/google/tagmanager/protobuf/q;
      //   517: aload_2
      //   518: invokevirtual 152	com/google/tagmanager/protobuf/f:a	(Lcom/google/tagmanager/protobuf/q;Lcom/google/tagmanager/protobuf/g;)Lcom/google/tagmanager/protobuf/n;
      //   521: invokeinterface 158 2 0
      //   526: pop
      //   527: iload 4
      //   529: istore_3
      //   530: iload 7
      //   532: istore 4
      //   534: goto +996 -> 1530
      //   537: iload_3
      //   538: istore 5
      //   540: aload_1
      //   541: invokevirtual 142	com/google/tagmanager/protobuf/f:Bb	()Lcom/google/tagmanager/protobuf/e;
      //   544: astore 13
      //   546: iload_3
      //   547: istore 5
      //   549: aload_0
      //   550: aload_0
      //   551: getfield 137	com/google/analytics/midtier/proto/containertag/TypeSystem$Value:bitField0_	I
      //   554: iconst_4
      //   555: ior
      //   556: putfield 137	com/google/analytics/midtier/proto/containertag/TypeSystem$Value:bitField0_	I
      //   559: iload_3
      //   560: istore 5
      //   562: aload_0
      //   563: aload 13
      //   565: putfield 164	com/google/analytics/midtier/proto/containertag/TypeSystem$Value:macroReference_	Ljava/lang/Object;
      //   568: iload_3
      //   569: istore 5
      //   571: iload 4
      //   573: istore_3
      //   574: iload 5
      //   576: istore 4
      //   578: goto +952 -> 1530
      //   581: iload_3
      //   582: istore 5
      //   584: aload_1
      //   585: invokevirtual 142	com/google/tagmanager/protobuf/f:Bb	()Lcom/google/tagmanager/protobuf/e;
      //   588: astore 13
      //   590: iload_3
      //   591: istore 5
      //   593: aload_0
      //   594: aload_0
      //   595: getfield 137	com/google/analytics/midtier/proto/containertag/TypeSystem$Value:bitField0_	I
      //   598: bipush 8
      //   600: ior
      //   601: putfield 137	com/google/analytics/midtier/proto/containertag/TypeSystem$Value:bitField0_	I
      //   604: iload_3
      //   605: istore 5
      //   607: aload_0
      //   608: aload 13
      //   610: putfield 166	com/google/analytics/midtier/proto/containertag/TypeSystem$Value:functionId_	Ljava/lang/Object;
      //   613: iload_3
      //   614: istore 5
      //   616: iload 4
      //   618: istore_3
      //   619: iload 5
      //   621: istore 4
      //   623: goto +907 -> 1530
      //   626: iload_3
      //   627: istore 5
      //   629: aload_0
      //   630: aload_0
      //   631: getfield 137	com/google/analytics/midtier/proto/containertag/TypeSystem$Value:bitField0_	I
      //   634: bipush 16
      //   636: ior
      //   637: putfield 137	com/google/analytics/midtier/proto/containertag/TypeSystem$Value:bitField0_	I
      //   640: iload_3
      //   641: istore 5
      //   643: aload_0
      //   644: aload_1
      //   645: invokevirtual 170	com/google/tagmanager/protobuf/f:AV	()J
      //   648: putfield 172	com/google/analytics/midtier/proto/containertag/TypeSystem$Value:integer_	J
      //   651: iload_3
      //   652: istore 5
      //   654: iload 4
      //   656: istore_3
      //   657: iload 5
      //   659: istore 4
      //   661: goto +869 -> 1530
      //   664: iload_3
      //   665: istore 5
      //   667: aload_0
      //   668: aload_0
      //   669: getfield 137	com/google/analytics/midtier/proto/containertag/TypeSystem$Value:bitField0_	I
      //   672: bipush 64
      //   674: ior
      //   675: putfield 137	com/google/analytics/midtier/proto/containertag/TypeSystem$Value:bitField0_	I
      //   678: iload_3
      //   679: istore 5
      //   681: aload_0
      //   682: aload_1
      //   683: invokevirtual 176	com/google/tagmanager/protobuf/f:AZ	()Z
      //   686: putfield 178	com/google/analytics/midtier/proto/containertag/TypeSystem$Value:containsReferences_	Z
      //   689: iload_3
      //   690: istore 5
      //   692: iload 4
      //   694: istore_3
      //   695: iload 5
      //   697: istore 4
      //   699: goto +831 -> 1530
      //   702: iload_3
      //   703: istore 5
      //   705: aload_1
      //   706: invokevirtual 127	com/google/tagmanager/protobuf/f:Bd	()I
      //   709: istore 6
      //   711: iload_3
      //   712: istore 5
      //   714: iload 6
      //   716: invokestatic 182	com/google/analytics/midtier/proto/containertag/TypeSystem$Value$Escaping:aT	(I)Lcom/google/analytics/midtier/proto/containertag/TypeSystem$Value$Escaping;
      //   719: astore 13
      //   721: aload 13
      //   723: ifnonnull +36 -> 759
      //   726: iload_3
      //   727: istore 5
      //   729: aload 12
      //   731: iload 9
      //   733: invokevirtual 135	com/google/tagmanager/protobuf/CodedOutputStream:fn	(I)V
      //   736: iload_3
      //   737: istore 5
      //   739: aload 12
      //   741: iload 6
      //   743: invokevirtual 135	com/google/tagmanager/protobuf/CodedOutputStream:fn	(I)V
      //   746: iload_3
      //   747: istore 5
      //   749: iload 4
      //   751: istore_3
      //   752: iload 5
      //   754: istore 4
      //   756: goto +774 -> 1530
      //   759: iload_3
      //   760: sipush 1024
      //   763: iand
      //   764: sipush 1024
      //   767: if_icmpeq +736 -> 1503
      //   770: iload_3
      //   771: istore 5
      //   773: aload_0
      //   774: new 146	java/util/ArrayList
      //   777: dup
      //   778: invokespecial 147	java/util/ArrayList:<init>	()V
      //   781: putfield 184	com/google/analytics/midtier/proto/containertag/TypeSystem$Value:escaping_	Ljava/util/List;
      //   784: iload_3
      //   785: sipush 1024
      //   788: ior
      //   789: istore 7
      //   791: iload 7
      //   793: istore_3
      //   794: iload 7
      //   796: istore 5
      //   798: iload 7
      //   800: istore 6
      //   802: aload_0
      //   803: getfield 184	com/google/analytics/midtier/proto/containertag/TypeSystem$Value:escaping_	Ljava/util/List;
      //   806: aload 13
      //   808: invokeinterface 158 2 0
      //   813: pop
      //   814: iload 4
      //   816: istore_3
      //   817: iload 7
      //   819: istore 4
      //   821: goto +709 -> 1530
      //   824: iload_3
      //   825: istore 5
      //   827: aload_1
      //   828: aload_1
      //   829: invokevirtual 187	com/google/tagmanager/protobuf/f:Bi	()I
      //   832: invokevirtual 191	com/google/tagmanager/protobuf/f:eV	(I)I
      //   835: istore 10
      //   837: iload_3
      //   838: istore 7
      //   840: iload 7
      //   842: istore_3
      //   843: iload 7
      //   845: istore 5
      //   847: iload 7
      //   849: istore 6
      //   851: aload_1
      //   852: invokevirtual 194	com/google/tagmanager/protobuf/f:Bn	()I
      //   855: ifle +319 -> 1174
      //   858: iload 7
      //   860: istore_3
      //   861: iload 7
      //   863: istore 5
      //   865: iload 7
      //   867: istore 6
      //   869: aload_1
      //   870: invokevirtual 127	com/google/tagmanager/protobuf/f:Bd	()I
      //   873: istore 8
      //   875: iload 7
      //   877: istore_3
      //   878: iload 7
      //   880: istore 5
      //   882: iload 7
      //   884: istore 6
      //   886: iload 8
      //   888: invokestatic 182	com/google/analytics/midtier/proto/containertag/TypeSystem$Value$Escaping:aT	(I)Lcom/google/analytics/midtier/proto/containertag/TypeSystem$Value$Escaping;
      //   891: astore 13
      //   893: aload 13
      //   895: ifnonnull +180 -> 1075
      //   898: iload 7
      //   900: istore_3
      //   901: iload 7
      //   903: istore 5
      //   905: iload 7
      //   907: istore 6
      //   909: aload 12
      //   911: iload 9
      //   913: invokevirtual 135	com/google/tagmanager/protobuf/CodedOutputStream:fn	(I)V
      //   916: iload 7
      //   918: istore_3
      //   919: iload 7
      //   921: istore 5
      //   923: iload 7
      //   925: istore 6
      //   927: aload 12
      //   929: iload 8
      //   931: invokevirtual 135	com/google/tagmanager/protobuf/CodedOutputStream:fn	(I)V
      //   934: goto -94 -> 840
      //   937: astore_1
      //   938: iload_3
      //   939: istore 5
      //   941: aload_1
      //   942: aload_0
      //   943: invokevirtual 198	com/google/tagmanager/protobuf/InvalidProtocolBufferException:h	(Lcom/google/tagmanager/protobuf/n;)Lcom/google/tagmanager/protobuf/InvalidProtocolBufferException;
      //   946: athrow
      //   947: astore_1
      //   948: iload 5
      //   950: iconst_4
      //   951: iand
      //   952: iconst_4
      //   953: if_icmpne +14 -> 967
      //   956: aload_0
      //   957: aload_0
      //   958: getfield 149	com/google/analytics/midtier/proto/containertag/TypeSystem$Value:listItem_	Ljava/util/List;
      //   961: invokestatic 204	java/util/Collections:unmodifiableList	(Ljava/util/List;)Ljava/util/List;
      //   964: putfield 149	com/google/analytics/midtier/proto/containertag/TypeSystem$Value:listItem_	Ljava/util/List;
      //   967: iload 5
      //   969: bipush 8
      //   971: iand
      //   972: bipush 8
      //   974: if_icmpne +14 -> 988
      //   977: aload_0
      //   978: aload_0
      //   979: getfield 160	com/google/analytics/midtier/proto/containertag/TypeSystem$Value:mapKey_	Ljava/util/List;
      //   982: invokestatic 204	java/util/Collections:unmodifiableList	(Ljava/util/List;)Ljava/util/List;
      //   985: putfield 160	com/google/analytics/midtier/proto/containertag/TypeSystem$Value:mapKey_	Ljava/util/List;
      //   988: iload 5
      //   990: bipush 16
      //   992: iand
      //   993: bipush 16
      //   995: if_icmpne +14 -> 1009
      //   998: aload_0
      //   999: aload_0
      //   1000: getfield 162	com/google/analytics/midtier/proto/containertag/TypeSystem$Value:mapValue_	Ljava/util/List;
      //   1003: invokestatic 204	java/util/Collections:unmodifiableList	(Ljava/util/List;)Ljava/util/List;
      //   1006: putfield 162	com/google/analytics/midtier/proto/containertag/TypeSystem$Value:mapValue_	Ljava/util/List;
      //   1009: iload 5
      //   1011: sipush 1024
      //   1014: iand
      //   1015: sipush 1024
      //   1018: if_icmpne +14 -> 1032
      //   1021: aload_0
      //   1022: aload_0
      //   1023: getfield 184	com/google/analytics/midtier/proto/containertag/TypeSystem$Value:escaping_	Ljava/util/List;
      //   1026: invokestatic 204	java/util/Collections:unmodifiableList	(Ljava/util/List;)Ljava/util/List;
      //   1029: putfield 184	com/google/analytics/midtier/proto/containertag/TypeSystem$Value:escaping_	Ljava/util/List;
      //   1032: iload 5
      //   1034: sipush 512
      //   1037: iand
      //   1038: sipush 512
      //   1041: if_icmpne +14 -> 1055
      //   1044: aload_0
      //   1045: aload_0
      //   1046: getfield 206	com/google/analytics/midtier/proto/containertag/TypeSystem$Value:templateToken_	Ljava/util/List;
      //   1049: invokestatic 204	java/util/Collections:unmodifiableList	(Ljava/util/List;)Ljava/util/List;
      //   1052: putfield 206	com/google/analytics/midtier/proto/containertag/TypeSystem$Value:templateToken_	Ljava/util/List;
      //   1055: aload 12
      //   1057: invokevirtual 209	com/google/tagmanager/protobuf/CodedOutputStream:flush	()V
      //   1060: aload_0
      //   1061: aload 11
      //   1063: invokevirtual 214	com/google/tagmanager/protobuf/e$b:AR	()Lcom/google/tagmanager/protobuf/e;
      //   1066: putfield 94	com/google/analytics/midtier/proto/containertag/TypeSystem$Value:unknownFields	Lcom/google/tagmanager/protobuf/e;
      //   1069: aload_0
      //   1070: invokevirtual 217	com/google/analytics/midtier/proto/containertag/TypeSystem$Value:BD	()V
      //   1073: aload_1
      //   1074: athrow
      //   1075: iload 7
      //   1077: istore 8
      //   1079: iload 7
      //   1081: sipush 1024
      //   1084: iand
      //   1085: sipush 1024
      //   1088: if_icmpeq +33 -> 1121
      //   1091: iload 7
      //   1093: istore_3
      //   1094: iload 7
      //   1096: istore 5
      //   1098: iload 7
      //   1100: istore 6
      //   1102: aload_0
      //   1103: new 146	java/util/ArrayList
      //   1106: dup
      //   1107: invokespecial 147	java/util/ArrayList:<init>	()V
      //   1110: putfield 184	com/google/analytics/midtier/proto/containertag/TypeSystem$Value:escaping_	Ljava/util/List;
      //   1113: iload 7
      //   1115: sipush 1024
      //   1118: ior
      //   1119: istore 8
      //   1121: iload 8
      //   1123: istore_3
      //   1124: iload 8
      //   1126: istore 5
      //   1128: iload 8
      //   1130: istore 6
      //   1132: aload_0
      //   1133: getfield 184	com/google/analytics/midtier/proto/containertag/TypeSystem$Value:escaping_	Ljava/util/List;
      //   1136: aload 13
      //   1138: invokeinterface 158 2 0
      //   1143: pop
      //   1144: iload 8
      //   1146: istore 7
      //   1148: goto -308 -> 840
      //   1151: astore_1
      //   1152: iload 5
      //   1154: istore_3
      //   1155: iload_3
      //   1156: istore 5
      //   1158: new 101	com/google/tagmanager/protobuf/InvalidProtocolBufferException
      //   1161: dup
      //   1162: aload_1
      //   1163: invokevirtual 221	java/io/IOException:getMessage	()Ljava/lang/String;
      //   1166: invokespecial 224	com/google/tagmanager/protobuf/InvalidProtocolBufferException:<init>	(Ljava/lang/String;)V
      //   1169: aload_0
      //   1170: invokevirtual 198	com/google/tagmanager/protobuf/InvalidProtocolBufferException:h	(Lcom/google/tagmanager/protobuf/n;)Lcom/google/tagmanager/protobuf/InvalidProtocolBufferException;
      //   1173: athrow
      //   1174: iload 7
      //   1176: istore_3
      //   1177: iload 7
      //   1179: istore 5
      //   1181: iload 7
      //   1183: istore 6
      //   1185: aload_1
      //   1186: iload 10
      //   1188: invokevirtual 227	com/google/tagmanager/protobuf/f:eW	(I)V
      //   1191: iload 4
      //   1193: istore_3
      //   1194: iload 7
      //   1196: istore 4
      //   1198: goto +332 -> 1530
      //   1201: iload_3
      //   1202: sipush 512
      //   1205: iand
      //   1206: sipush 512
      //   1209: if_icmpeq +288 -> 1497
      //   1212: iload_3
      //   1213: istore 5
      //   1215: aload_0
      //   1216: new 146	java/util/ArrayList
      //   1219: dup
      //   1220: invokespecial 147	java/util/ArrayList:<init>	()V
      //   1223: putfield 206	com/google/analytics/midtier/proto/containertag/TypeSystem$Value:templateToken_	Ljava/util/List;
      //   1226: iload_3
      //   1227: sipush 512
      //   1230: ior
      //   1231: istore 7
      //   1233: iload 7
      //   1235: istore_3
      //   1236: iload 7
      //   1238: istore 5
      //   1240: iload 7
      //   1242: istore 6
      //   1244: aload_0
      //   1245: getfield 206	com/google/analytics/midtier/proto/containertag/TypeSystem$Value:templateToken_	Ljava/util/List;
      //   1248: aload_1
      //   1249: getstatic 68	com/google/analytics/midtier/proto/containertag/TypeSystem$Value:gW	Lcom/google/tagmanager/protobuf/q;
      //   1252: aload_2
      //   1253: invokevirtual 152	com/google/tagmanager/protobuf/f:a	(Lcom/google/tagmanager/protobuf/q;Lcom/google/tagmanager/protobuf/g;)Lcom/google/tagmanager/protobuf/n;
      //   1256: invokeinterface 158 2 0
      //   1261: pop
      //   1262: iload 4
      //   1264: istore_3
      //   1265: iload 7
      //   1267: istore 4
      //   1269: goto +261 -> 1530
      //   1272: iload_3
      //   1273: istore 5
      //   1275: aload_0
      //   1276: aload_0
      //   1277: getfield 137	com/google/analytics/midtier/proto/containertag/TypeSystem$Value:bitField0_	I
      //   1280: bipush 32
      //   1282: ior
      //   1283: putfield 137	com/google/analytics/midtier/proto/containertag/TypeSystem$Value:bitField0_	I
      //   1286: iload_3
      //   1287: istore 5
      //   1289: aload_0
      //   1290: aload_1
      //   1291: invokevirtual 176	com/google/tagmanager/protobuf/f:AZ	()Z
      //   1294: putfield 229	com/google/analytics/midtier/proto/containertag/TypeSystem$Value:boolean_	Z
      //   1297: iload_3
      //   1298: istore 5
      //   1300: iload 4
      //   1302: istore_3
      //   1303: iload 5
      //   1305: istore 4
      //   1307: goto +223 -> 1530
      //   1310: iload_3
      //   1311: iconst_4
      //   1312: iand
      //   1313: iconst_4
      //   1314: if_icmpne +14 -> 1328
      //   1317: aload_0
      //   1318: aload_0
      //   1319: getfield 149	com/google/analytics/midtier/proto/containertag/TypeSystem$Value:listItem_	Ljava/util/List;
      //   1322: invokestatic 204	java/util/Collections:unmodifiableList	(Ljava/util/List;)Ljava/util/List;
      //   1325: putfield 149	com/google/analytics/midtier/proto/containertag/TypeSystem$Value:listItem_	Ljava/util/List;
      //   1328: iload_3
      //   1329: bipush 8
      //   1331: iand
      //   1332: bipush 8
      //   1334: if_icmpne +14 -> 1348
      //   1337: aload_0
      //   1338: aload_0
      //   1339: getfield 160	com/google/analytics/midtier/proto/containertag/TypeSystem$Value:mapKey_	Ljava/util/List;
      //   1342: invokestatic 204	java/util/Collections:unmodifiableList	(Ljava/util/List;)Ljava/util/List;
      //   1345: putfield 160	com/google/analytics/midtier/proto/containertag/TypeSystem$Value:mapKey_	Ljava/util/List;
      //   1348: iload_3
      //   1349: bipush 16
      //   1351: iand
      //   1352: bipush 16
      //   1354: if_icmpne +14 -> 1368
      //   1357: aload_0
      //   1358: aload_0
      //   1359: getfield 162	com/google/analytics/midtier/proto/containertag/TypeSystem$Value:mapValue_	Ljava/util/List;
      //   1362: invokestatic 204	java/util/Collections:unmodifiableList	(Ljava/util/List;)Ljava/util/List;
      //   1365: putfield 162	com/google/analytics/midtier/proto/containertag/TypeSystem$Value:mapValue_	Ljava/util/List;
      //   1368: iload_3
      //   1369: sipush 1024
      //   1372: iand
      //   1373: sipush 1024
      //   1376: if_icmpne +14 -> 1390
      //   1379: aload_0
      //   1380: aload_0
      //   1381: getfield 184	com/google/analytics/midtier/proto/containertag/TypeSystem$Value:escaping_	Ljava/util/List;
      //   1384: invokestatic 204	java/util/Collections:unmodifiableList	(Ljava/util/List;)Ljava/util/List;
      //   1387: putfield 184	com/google/analytics/midtier/proto/containertag/TypeSystem$Value:escaping_	Ljava/util/List;
      //   1390: iload_3
      //   1391: sipush 512
      //   1394: iand
      //   1395: sipush 512
      //   1398: if_icmpne +14 -> 1412
      //   1401: aload_0
      //   1402: aload_0
      //   1403: getfield 206	com/google/analytics/midtier/proto/containertag/TypeSystem$Value:templateToken_	Ljava/util/List;
      //   1406: invokestatic 204	java/util/Collections:unmodifiableList	(Ljava/util/List;)Ljava/util/List;
      //   1409: putfield 206	com/google/analytics/midtier/proto/containertag/TypeSystem$Value:templateToken_	Ljava/util/List;
      //   1412: aload 12
      //   1414: invokevirtual 209	com/google/tagmanager/protobuf/CodedOutputStream:flush	()V
      //   1417: aload_0
      //   1418: aload 11
      //   1420: invokevirtual 214	com/google/tagmanager/protobuf/e$b:AR	()Lcom/google/tagmanager/protobuf/e;
      //   1423: putfield 94	com/google/analytics/midtier/proto/containertag/TypeSystem$Value:unknownFields	Lcom/google/tagmanager/protobuf/e;
      //   1426: aload_0
      //   1427: invokevirtual 217	com/google/analytics/midtier/proto/containertag/TypeSystem$Value:BD	()V
      //   1430: return
      //   1431: astore_1
      //   1432: aload_0
      //   1433: aload 11
      //   1435: invokevirtual 214	com/google/tagmanager/protobuf/e$b:AR	()Lcom/google/tagmanager/protobuf/e;
      //   1438: putfield 94	com/google/analytics/midtier/proto/containertag/TypeSystem$Value:unknownFields	Lcom/google/tagmanager/protobuf/e;
      //   1441: goto -15 -> 1426
      //   1444: astore_1
      //   1445: aload_0
      //   1446: aload 11
      //   1448: invokevirtual 214	com/google/tagmanager/protobuf/e$b:AR	()Lcom/google/tagmanager/protobuf/e;
      //   1451: putfield 94	com/google/analytics/midtier/proto/containertag/TypeSystem$Value:unknownFields	Lcom/google/tagmanager/protobuf/e;
      //   1454: aload_1
      //   1455: athrow
      //   1456: astore_2
      //   1457: aload_0
      //   1458: aload 11
      //   1460: invokevirtual 214	com/google/tagmanager/protobuf/e$b:AR	()Lcom/google/tagmanager/protobuf/e;
      //   1463: putfield 94	com/google/analytics/midtier/proto/containertag/TypeSystem$Value:unknownFields	Lcom/google/tagmanager/protobuf/e;
      //   1466: goto -397 -> 1069
      //   1469: astore_1
      //   1470: aload_0
      //   1471: aload 11
      //   1473: invokevirtual 214	com/google/tagmanager/protobuf/e$b:AR	()Lcom/google/tagmanager/protobuf/e;
      //   1476: putfield 94	com/google/analytics/midtier/proto/containertag/TypeSystem$Value:unknownFields	Lcom/google/tagmanager/protobuf/e;
      //   1479: aload_1
      //   1480: athrow
      //   1481: astore_1
      //   1482: iload 6
      //   1484: istore 5
      //   1486: goto -538 -> 948
      //   1489: astore_1
      //   1490: goto -335 -> 1155
      //   1493: astore_1
      //   1494: goto -556 -> 938
      //   1497: iload_3
      //   1498: istore 7
      //   1500: goto -267 -> 1233
      //   1503: iload_3
      //   1504: istore 7
      //   1506: goto -715 -> 791
      //   1509: iload_3
      //   1510: istore 7
      //   1512: goto -1014 -> 498
      //   1515: iload_3
      //   1516: istore 7
      //   1518: goto -1088 -> 430
      //   1521: iload_3
      //   1522: istore 7
      //   1524: goto -1162 -> 362
      //   1527: goto -1355 -> 172
      //   1530: iload 4
      //   1532: istore 5
      //   1534: iload_3
      //   1535: istore 4
      //   1537: iload 5
      //   1539: istore_3
      //   1540: goto -1505 -> 35
      //   1543: iconst_1
      //   1544: istore 5
      //   1546: iload_3
      //   1547: istore 4
      //   1549: iload 5
      //   1551: istore_3
      //   1552: goto -22 -> 1530
      // Local variable table:
      //   start	length	slot	name	signature
      //   0	1555	0	this	Value
      //   0	1555	1	paramf	f
      //   0	1555	2	paramg	g
      //   19	1533	3	i	int
      //   33	1515	4	j	int
      //   41	1509	5	k	int
      //   207	1276	6	m	int
      //   360	1163	7	n	int
      //   873	272	8	i1	int
      //   47	865	9	i2	int
      //   835	352	10	i3	int
      //   23	1449	11	localb	com.google.tagmanager.protobuf.e.b
      //   30	1383	12	localCodedOutputStream	CodedOutputStream
      //   217	920	13	localObject	Object
      // Exception table:
      //   from	to	target	type
      //   373	391	937	com/google/tagmanager/protobuf/InvalidProtocolBufferException
      //   441	459	937	com/google/tagmanager/protobuf/InvalidProtocolBufferException
      //   509	527	937	com/google/tagmanager/protobuf/InvalidProtocolBufferException
      //   802	814	937	com/google/tagmanager/protobuf/InvalidProtocolBufferException
      //   851	858	937	com/google/tagmanager/protobuf/InvalidProtocolBufferException
      //   869	875	937	com/google/tagmanager/protobuf/InvalidProtocolBufferException
      //   886	893	937	com/google/tagmanager/protobuf/InvalidProtocolBufferException
      //   909	916	937	com/google/tagmanager/protobuf/InvalidProtocolBufferException
      //   927	934	937	com/google/tagmanager/protobuf/InvalidProtocolBufferException
      //   1102	1113	937	com/google/tagmanager/protobuf/InvalidProtocolBufferException
      //   1132	1144	937	com/google/tagmanager/protobuf/InvalidProtocolBufferException
      //   1185	1191	937	com/google/tagmanager/protobuf/InvalidProtocolBufferException
      //   1244	1262	937	com/google/tagmanager/protobuf/InvalidProtocolBufferException
      //   43	49	947	finally
      //   175	188	947	finally
      //   203	209	947	finally
      //   212	219	947	finally
      //   227	234	947	finally
      //   237	244	947	finally
      //   260	270	947	finally
      //   273	279	947	finally
      //   295	301	947	finally
      //   304	314	947	finally
      //   317	323	947	finally
      //   346	357	947	finally
      //   413	424	947	finally
      //   481	492	947	finally
      //   540	546	947	finally
      //   549	559	947	finally
      //   562	568	947	finally
      //   584	590	947	finally
      //   593	604	947	finally
      //   607	613	947	finally
      //   629	640	947	finally
      //   643	651	947	finally
      //   667	678	947	finally
      //   681	689	947	finally
      //   705	711	947	finally
      //   714	721	947	finally
      //   729	736	947	finally
      //   739	746	947	finally
      //   773	784	947	finally
      //   827	837	947	finally
      //   941	947	947	finally
      //   1158	1174	947	finally
      //   1215	1226	947	finally
      //   1275	1286	947	finally
      //   1289	1297	947	finally
      //   373	391	1151	java/io/IOException
      //   441	459	1151	java/io/IOException
      //   509	527	1151	java/io/IOException
      //   802	814	1151	java/io/IOException
      //   851	858	1151	java/io/IOException
      //   869	875	1151	java/io/IOException
      //   886	893	1151	java/io/IOException
      //   909	916	1151	java/io/IOException
      //   927	934	1151	java/io/IOException
      //   1102	1113	1151	java/io/IOException
      //   1132	1144	1151	java/io/IOException
      //   1185	1191	1151	java/io/IOException
      //   1244	1262	1151	java/io/IOException
      //   1412	1417	1431	java/io/IOException
      //   1412	1417	1444	finally
      //   1055	1060	1456	java/io/IOException
      //   1055	1060	1469	finally
      //   373	391	1481	finally
      //   441	459	1481	finally
      //   509	527	1481	finally
      //   802	814	1481	finally
      //   851	858	1481	finally
      //   869	875	1481	finally
      //   886	893	1481	finally
      //   909	916	1481	finally
      //   927	934	1481	finally
      //   1102	1113	1481	finally
      //   1132	1144	1481	finally
      //   1185	1191	1481	finally
      //   1244	1262	1481	finally
      //   43	49	1489	java/io/IOException
      //   175	188	1489	java/io/IOException
      //   203	209	1489	java/io/IOException
      //   212	219	1489	java/io/IOException
      //   227	234	1489	java/io/IOException
      //   237	244	1489	java/io/IOException
      //   260	270	1489	java/io/IOException
      //   273	279	1489	java/io/IOException
      //   295	301	1489	java/io/IOException
      //   304	314	1489	java/io/IOException
      //   317	323	1489	java/io/IOException
      //   346	357	1489	java/io/IOException
      //   413	424	1489	java/io/IOException
      //   481	492	1489	java/io/IOException
      //   540	546	1489	java/io/IOException
      //   549	559	1489	java/io/IOException
      //   562	568	1489	java/io/IOException
      //   584	590	1489	java/io/IOException
      //   593	604	1489	java/io/IOException
      //   607	613	1489	java/io/IOException
      //   629	640	1489	java/io/IOException
      //   643	651	1489	java/io/IOException
      //   667	678	1489	java/io/IOException
      //   681	689	1489	java/io/IOException
      //   705	711	1489	java/io/IOException
      //   714	721	1489	java/io/IOException
      //   729	736	1489	java/io/IOException
      //   739	746	1489	java/io/IOException
      //   773	784	1489	java/io/IOException
      //   827	837	1489	java/io/IOException
      //   1215	1226	1489	java/io/IOException
      //   1275	1286	1489	java/io/IOException
      //   1289	1297	1489	java/io/IOException
      //   43	49	1493	com/google/tagmanager/protobuf/InvalidProtocolBufferException
      //   175	188	1493	com/google/tagmanager/protobuf/InvalidProtocolBufferException
      //   203	209	1493	com/google/tagmanager/protobuf/InvalidProtocolBufferException
      //   212	219	1493	com/google/tagmanager/protobuf/InvalidProtocolBufferException
      //   227	234	1493	com/google/tagmanager/protobuf/InvalidProtocolBufferException
      //   237	244	1493	com/google/tagmanager/protobuf/InvalidProtocolBufferException
      //   260	270	1493	com/google/tagmanager/protobuf/InvalidProtocolBufferException
      //   273	279	1493	com/google/tagmanager/protobuf/InvalidProtocolBufferException
      //   295	301	1493	com/google/tagmanager/protobuf/InvalidProtocolBufferException
      //   304	314	1493	com/google/tagmanager/protobuf/InvalidProtocolBufferException
      //   317	323	1493	com/google/tagmanager/protobuf/InvalidProtocolBufferException
      //   346	357	1493	com/google/tagmanager/protobuf/InvalidProtocolBufferException
      //   413	424	1493	com/google/tagmanager/protobuf/InvalidProtocolBufferException
      //   481	492	1493	com/google/tagmanager/protobuf/InvalidProtocolBufferException
      //   540	546	1493	com/google/tagmanager/protobuf/InvalidProtocolBufferException
      //   549	559	1493	com/google/tagmanager/protobuf/InvalidProtocolBufferException
      //   562	568	1493	com/google/tagmanager/protobuf/InvalidProtocolBufferException
      //   584	590	1493	com/google/tagmanager/protobuf/InvalidProtocolBufferException
      //   593	604	1493	com/google/tagmanager/protobuf/InvalidProtocolBufferException
      //   607	613	1493	com/google/tagmanager/protobuf/InvalidProtocolBufferException
      //   629	640	1493	com/google/tagmanager/protobuf/InvalidProtocolBufferException
      //   643	651	1493	com/google/tagmanager/protobuf/InvalidProtocolBufferException
      //   667	678	1493	com/google/tagmanager/protobuf/InvalidProtocolBufferException
      //   681	689	1493	com/google/tagmanager/protobuf/InvalidProtocolBufferException
      //   705	711	1493	com/google/tagmanager/protobuf/InvalidProtocolBufferException
      //   714	721	1493	com/google/tagmanager/protobuf/InvalidProtocolBufferException
      //   729	736	1493	com/google/tagmanager/protobuf/InvalidProtocolBufferException
      //   739	746	1493	com/google/tagmanager/protobuf/InvalidProtocolBufferException
      //   773	784	1493	com/google/tagmanager/protobuf/InvalidProtocolBufferException
      //   827	837	1493	com/google/tagmanager/protobuf/InvalidProtocolBufferException
      //   1215	1226	1493	com/google/tagmanager/protobuf/InvalidProtocolBufferException
      //   1275	1286	1493	com/google/tagmanager/protobuf/InvalidProtocolBufferException
      //   1289	1297	1493	com/google/tagmanager/protobuf/InvalidProtocolBufferException
    }
    
    private Value(boolean paramBoolean)
    {
      this.unknownFields = e.ajf;
    }
    
    public static a a(Value paramValue)
    {
      return iU().k(paramValue);
    }
    
    private void fH()
    {
      this.type_ = Type.hA;
      this.string_ = "";
      this.listItem_ = Collections.emptyList();
      this.mapKey_ = Collections.emptyList();
      this.mapValue_ = Collections.emptyList();
      this.macroReference_ = "";
      this.functionId_ = "";
      this.integer_ = 0L;
      this.boolean_ = false;
      this.templateToken_ = Collections.emptyList();
      this.escaping_ = Collections.emptyList();
      this.containsReferences_ = false;
    }
    
    public static a iU()
    {
      return a.jh();
    }
    
    public static Value is()
    {
      return hh;
    }
    
    public void a(CodedOutputStream paramCodedOutputStream)
    {
      int k = 0;
      fI();
      GeneratedMessageLite.ExtendableMessage.a locala = BI();
      if ((this.bitField0_ & 0x1) == 1) {
        paramCodedOutputStream.y(1, this.type_.ga());
      }
      if ((this.bitField0_ & 0x2) == 2) {
        paramCodedOutputStream.a(2, ix());
      }
      int i = 0;
      while (i < this.listItem_.size())
      {
        paramCodedOutputStream.b(3, (n)this.listItem_.get(i));
        i += 1;
      }
      i = 0;
      while (i < this.mapKey_.size())
      {
        paramCodedOutputStream.b(4, (n)this.mapKey_.get(i));
        i += 1;
      }
      i = 0;
      while (i < this.mapValue_.size())
      {
        paramCodedOutputStream.b(5, (n)this.mapValue_.get(i));
        i += 1;
      }
      if ((this.bitField0_ & 0x4) == 4) {
        paramCodedOutputStream.a(6, iG());
      }
      if ((this.bitField0_ & 0x8) == 8) {
        paramCodedOutputStream.a(7, iJ());
      }
      if ((this.bitField0_ & 0x10) == 16) {
        paramCodedOutputStream.f(8, this.integer_);
      }
      if ((this.bitField0_ & 0x40) == 64) {
        paramCodedOutputStream.d(9, this.containsReferences_);
      }
      i = 0;
      int j;
      for (;;)
      {
        j = k;
        if (i >= this.escaping_.size()) {
          break;
        }
        paramCodedOutputStream.y(10, ((Escaping)this.escaping_.get(i)).ga());
        i += 1;
      }
      while (j < this.templateToken_.size())
      {
        paramCodedOutputStream.b(11, (n)this.templateToken_.get(j));
        j += 1;
      }
      if ((this.bitField0_ & 0x20) == 32) {
        paramCodedOutputStream.d(12, this.boolean_);
      }
      locala.b(536870912, paramCodedOutputStream);
      paramCodedOutputStream.d(this.unknownFields);
    }
    
    public Value aP(int paramInt)
    {
      return (Value)this.listItem_.get(paramInt);
    }
    
    public Value aQ(int paramInt)
    {
      return (Value)this.mapKey_.get(paramInt);
    }
    
    public Value aR(int paramInt)
    {
      return (Value)this.mapValue_.get(paramInt);
    }
    
    public Value aS(int paramInt)
    {
      return (Value)this.templateToken_.get(paramInt);
    }
    
    public boolean equals(Object paramObject)
    {
      if (paramObject == this) {
        return true;
      }
      if (!(paramObject instanceof Value)) {
        return super.equals(paramObject);
      }
      paramObject = (Value)paramObject;
      int i;
      label38:
      int j;
      if (iu() == ((Value)paramObject).iu())
      {
        i = 1;
        j = i;
        if (iu())
        {
          if ((i == 0) || (iv() != ((Value)paramObject).iv())) {
            break label447;
          }
          j = 1;
        }
        label64:
        if ((j == 0) || (iw() != ((Value)paramObject).iw())) {
          break label452;
        }
        i = 1;
        label81:
        j = i;
        if (iw())
        {
          if ((i == 0) || (!getString().equals(((Value)paramObject).getString()))) {
            break label457;
          }
          j = 1;
        }
        label110:
        if ((j == 0) || (!iy().equals(((Value)paramObject).iy()))) {
          break label462;
        }
        i = 1;
        label132:
        if ((i == 0) || (!iA().equals(((Value)paramObject).iA()))) {
          break label467;
        }
        i = 1;
        label154:
        if ((i == 0) || (!iC().equals(((Value)paramObject).iC()))) {
          break label472;
        }
        i = 1;
        label176:
        if ((i == 0) || (iE() != ((Value)paramObject).iE())) {
          break label477;
        }
        i = 1;
        label193:
        j = i;
        if (iE())
        {
          if ((i == 0) || (!iF().equals(((Value)paramObject).iF()))) {
            break label482;
          }
          j = 1;
        }
        label222:
        if ((j == 0) || (iH() != ((Value)paramObject).iH())) {
          break label487;
        }
        i = 1;
        label239:
        j = i;
        if (iH())
        {
          if ((i == 0) || (!iI().equals(((Value)paramObject).iI()))) {
            break label492;
          }
          j = 1;
        }
        label268:
        if ((j == 0) || (iK() != ((Value)paramObject).iK())) {
          break label497;
        }
        i = 1;
        label285:
        j = i;
        if (iK())
        {
          if ((i == 0) || (iL() != ((Value)paramObject).iL())) {
            break label502;
          }
          j = 1;
        }
        label312:
        if ((j == 0) || (iM() != ((Value)paramObject).iM())) {
          break label507;
        }
        i = 1;
        label329:
        j = i;
        if (iM())
        {
          if ((i == 0) || (iN() != ((Value)paramObject).iN())) {
            break label512;
          }
          j = 1;
        }
        label355:
        if ((j == 0) || (!iO().equals(((Value)paramObject).iO()))) {
          break label517;
        }
        i = 1;
        label377:
        if ((i == 0) || (!iQ().equals(((Value)paramObject).iQ()))) {
          break label522;
        }
        i = 1;
        label399:
        if ((i == 0) || (iS() != ((Value)paramObject).iS())) {
          break label527;
        }
      }
      label447:
      label452:
      label457:
      label462:
      label467:
      label472:
      label477:
      label482:
      label487:
      label492:
      label497:
      label502:
      label507:
      label512:
      label517:
      label522:
      label527:
      for (boolean bool = true;; bool = false)
      {
        if (!iS()) {
          break label533;
        }
        if ((bool) && (iT() == ((Value)paramObject).iT())) {
          break;
        }
        return false;
        i = 0;
        break label38;
        j = 0;
        break label64;
        i = 0;
        break label81;
        j = 0;
        break label110;
        i = 0;
        break label132;
        i = 0;
        break label154;
        i = 0;
        break label176;
        i = 0;
        break label193;
        j = 0;
        break label222;
        i = 0;
        break label239;
        j = 0;
        break label268;
        i = 0;
        break label285;
        j = 0;
        break label312;
        i = 0;
        break label329;
        j = 0;
        break label355;
        i = 0;
        break label377;
        i = 0;
        break label399;
      }
      label533:
      return bool;
    }
    
    public q<Value> fA()
    {
      return gW;
    }
    
    public int fI()
    {
      int m = 0;
      int i = this.memoizedSerializedSize;
      if (i != -1) {
        return i;
      }
      if ((this.bitField0_ & 0x1) == 1) {}
      for (int j = CodedOutputStream.A(1, this.type_.ga()) + 0;; j = 0)
      {
        i = j;
        if ((this.bitField0_ & 0x2) == 2) {
          i = j + CodedOutputStream.b(2, ix());
        }
        j = 0;
        while (j < this.listItem_.size())
        {
          i += CodedOutputStream.d(3, (n)this.listItem_.get(j));
          j += 1;
        }
        j = 0;
        while (j < this.mapKey_.size())
        {
          i += CodedOutputStream.d(4, (n)this.mapKey_.get(j));
          j += 1;
        }
        j = 0;
        while (j < this.mapValue_.size())
        {
          i += CodedOutputStream.d(5, (n)this.mapValue_.get(j));
          j += 1;
        }
        j = i;
        if ((this.bitField0_ & 0x4) == 4) {
          j = i + CodedOutputStream.b(6, iG());
        }
        i = j;
        if ((this.bitField0_ & 0x8) == 8) {
          i = j + CodedOutputStream.b(7, iJ());
        }
        j = i;
        if ((this.bitField0_ & 0x10) == 16) {
          j = i + CodedOutputStream.g(8, this.integer_);
        }
        i = j;
        if ((this.bitField0_ & 0x40) == 64) {
          i = j + CodedOutputStream.e(9, this.containsReferences_);
        }
        j = 0;
        int k = 0;
        while (j < this.escaping_.size())
        {
          k += CodedOutputStream.fi(((Escaping)this.escaping_.get(j)).ga());
          j += 1;
        }
        i = i + k + this.escaping_.size() * 1;
        j = m;
        while (j < this.templateToken_.size())
        {
          k = CodedOutputStream.d(11, (n)this.templateToken_.get(j));
          j += 1;
          i = k + i;
        }
        j = i;
        if ((this.bitField0_ & 0x20) == 32) {
          j = i + CodedOutputStream.e(12, this.boolean_);
        }
        i = BJ() + j + this.unknownFields.size();
        this.memoizedSerializedSize = i;
        return i;
      }
    }
    
    public String getString()
    {
      Object localObject = this.string_;
      if ((localObject instanceof String)) {
        return (String)localObject;
      }
      localObject = (e)localObject;
      String str = ((e)localObject).AK();
      if (((e)localObject).AL()) {
        this.string_ = str;
      }
      return str;
    }
    
    public int hashCode()
    {
      if (this.memoizedHashCode != 0) {
        return this.memoizedHashCode;
      }
      int j = Value.class.hashCode() + 779;
      int i = j;
      if (iu()) {
        i = (j * 37 + 1) * 53 + i.a(iv());
      }
      j = i;
      if (iw()) {
        j = (i * 37 + 2) * 53 + getString().hashCode();
      }
      i = j;
      if (iz() > 0) {
        i = (j * 37 + 3) * 53 + iy().hashCode();
      }
      j = i;
      if (iB() > 0) {
        j = (i * 37 + 4) * 53 + iA().hashCode();
      }
      i = j;
      if (iD() > 0) {
        i = (j * 37 + 5) * 53 + iC().hashCode();
      }
      j = i;
      if (iE()) {
        j = (i * 37 + 6) * 53 + iF().hashCode();
      }
      i = j;
      if (iH()) {
        i = (j * 37 + 7) * 53 + iI().hashCode();
      }
      j = i;
      if (iK()) {
        j = (i * 37 + 8) * 53 + i.T(iL());
      }
      i = j;
      if (iM()) {
        i = (j * 37 + 12) * 53 + i.aK(iN());
      }
      j = i;
      if (iP() > 0) {
        j = (i * 37 + 11) * 53 + iO().hashCode();
      }
      i = j;
      if (iR() > 0) {
        i = (j * 37 + 10) * 53 + i.j(iQ());
      }
      j = i;
      if (iS()) {
        j = (i * 37 + 9) * 53 + i.aK(iT());
      }
      i = j * 29 + this.unknownFields.hashCode();
      this.memoizedHashCode = i;
      return i;
    }
    
    public List<Value> iA()
    {
      return this.mapKey_;
    }
    
    public int iB()
    {
      return this.mapKey_.size();
    }
    
    public List<Value> iC()
    {
      return this.mapValue_;
    }
    
    public int iD()
    {
      return this.mapValue_.size();
    }
    
    public boolean iE()
    {
      return (this.bitField0_ & 0x4) == 4;
    }
    
    public String iF()
    {
      Object localObject = this.macroReference_;
      if ((localObject instanceof String)) {
        return (String)localObject;
      }
      localObject = (e)localObject;
      String str = ((e)localObject).AK();
      if (((e)localObject).AL()) {
        this.macroReference_ = str;
      }
      return str;
    }
    
    public e iG()
    {
      Object localObject = this.macroReference_;
      if ((localObject instanceof String))
      {
        localObject = e.cU((String)localObject);
        this.macroReference_ = localObject;
        return (e)localObject;
      }
      return (e)localObject;
    }
    
    public boolean iH()
    {
      return (this.bitField0_ & 0x8) == 8;
    }
    
    public String iI()
    {
      Object localObject = this.functionId_;
      if ((localObject instanceof String)) {
        return (String)localObject;
      }
      localObject = (e)localObject;
      String str = ((e)localObject).AK();
      if (((e)localObject).AL()) {
        this.functionId_ = str;
      }
      return str;
    }
    
    public e iJ()
    {
      Object localObject = this.functionId_;
      if ((localObject instanceof String))
      {
        localObject = e.cU((String)localObject);
        this.functionId_ = localObject;
        return (e)localObject;
      }
      return (e)localObject;
    }
    
    public boolean iK()
    {
      return (this.bitField0_ & 0x10) == 16;
    }
    
    public long iL()
    {
      return this.integer_;
    }
    
    public boolean iM()
    {
      return (this.bitField0_ & 0x20) == 32;
    }
    
    public boolean iN()
    {
      return this.boolean_;
    }
    
    public List<Value> iO()
    {
      return this.templateToken_;
    }
    
    public int iP()
    {
      return this.templateToken_.size();
    }
    
    public List<Escaping> iQ()
    {
      return this.escaping_;
    }
    
    public int iR()
    {
      return this.escaping_.size();
    }
    
    public boolean iS()
    {
      return (this.bitField0_ & 0x40) == 64;
    }
    
    public boolean iT()
    {
      return this.containsReferences_;
    }
    
    public a iV()
    {
      return iU();
    }
    
    public a iW()
    {
      return a(this);
    }
    
    public final boolean isInitialized()
    {
      boolean bool = true;
      int i = this.memoizedIsInitialized;
      if (i != -1)
      {
        if (i == 1) {}
        for (;;)
        {
          return bool;
          bool = false;
        }
      }
      if (!iu())
      {
        this.memoizedIsInitialized = 0;
        return false;
      }
      i = 0;
      while (i < iz())
      {
        if (!aP(i).isInitialized())
        {
          this.memoizedIsInitialized = 0;
          return false;
        }
        i += 1;
      }
      i = 0;
      while (i < iB())
      {
        if (!aQ(i).isInitialized())
        {
          this.memoizedIsInitialized = 0;
          return false;
        }
        i += 1;
      }
      i = 0;
      while (i < iD())
      {
        if (!aR(i).isInitialized())
        {
          this.memoizedIsInitialized = 0;
          return false;
        }
        i += 1;
      }
      i = 0;
      while (i < iP())
      {
        if (!aS(i).isInitialized())
        {
          this.memoizedIsInitialized = 0;
          return false;
        }
        i += 1;
      }
      if (!BH())
      {
        this.memoizedIsInitialized = 0;
        return false;
      }
      this.memoizedIsInitialized = 1;
      return true;
    }
    
    public Value it()
    {
      return hh;
    }
    
    public boolean iu()
    {
      return (this.bitField0_ & 0x1) == 1;
    }
    
    public Type iv()
    {
      return this.type_;
    }
    
    public boolean iw()
    {
      return (this.bitField0_ & 0x2) == 2;
    }
    
    public e ix()
    {
      Object localObject = this.string_;
      if ((localObject instanceof String))
      {
        localObject = e.cU((String)localObject);
        this.string_ = localObject;
        return (e)localObject;
      }
      return (e)localObject;
    }
    
    public List<Value> iy()
    {
      return this.listItem_;
    }
    
    public int iz()
    {
      return this.listItem_.size();
    }
    
    protected Object writeReplace()
    {
      return super.writeReplace();
    }
    
    public static enum Escaping
      implements i.a
    {
      private static i.b<Escaping> hb = new i.b()
      {
        public TypeSystem.Value.Escaping aU(int paramAnonymousInt)
        {
          return TypeSystem.Value.Escaping.aT(paramAnonymousInt);
        }
      };
      private final int value;
      
      private Escaping(int paramInt1, int paramInt2)
      {
        this.value = paramInt2;
      }
      
      public static Escaping aT(int paramInt)
      {
        switch (paramInt)
        {
        default: 
          return null;
        case 1: 
          return hi;
        case 2: 
          return hj;
        case 3: 
          return hk;
        case 4: 
          return hl;
        case 5: 
          return hm;
        case 6: 
          return hn;
        case 7: 
          return ho;
        case 8: 
          return hp;
        case 9: 
          return hq;
        case 10: 
          return hr;
        case 11: 
          return hs;
        case 12: 
          return ht;
        case 13: 
          return hu;
        case 14: 
          return hv;
        case 15: 
          return hw;
        case 17: 
          return hx;
        }
        return hy;
      }
      
      public final int ga()
      {
        return this.value;
      }
    }
    
    public static enum Type
      implements i.a
    {
      private static i.b<Type> hb = new i.b()
      {
        public TypeSystem.Value.Type aW(int paramAnonymousInt)
        {
          return TypeSystem.Value.Type.aV(paramAnonymousInt);
        }
      };
      private final int value;
      
      private Type(int paramInt1, int paramInt2)
      {
        this.value = paramInt2;
      }
      
      public static Type aV(int paramInt)
      {
        switch (paramInt)
        {
        default: 
          return null;
        case 1: 
          return hA;
        case 2: 
          return hB;
        case 3: 
          return hC;
        case 4: 
          return hD;
        case 5: 
          return hE;
        case 6: 
          return hF;
        case 7: 
          return hG;
        }
        return hH;
      }
      
      public final int ga()
      {
        return this.value;
      }
    }
    
    public static final class a
      extends GeneratedMessageLite.b<TypeSystem.Value, a>
      implements TypeSystem.a
    {
      private int bitField0_;
      private boolean boolean_;
      private boolean containsReferences_;
      private List<TypeSystem.Value.Escaping> escaping_ = Collections.emptyList();
      private Object functionId_ = "";
      private long integer_;
      private List<TypeSystem.Value> listItem_ = Collections.emptyList();
      private Object macroReference_ = "";
      private List<TypeSystem.Value> mapKey_ = Collections.emptyList();
      private List<TypeSystem.Value> mapValue_ = Collections.emptyList();
      private Object string_ = "";
      private List<TypeSystem.Value> templateToken_ = Collections.emptyList();
      private TypeSystem.Value.Type type_ = TypeSystem.Value.Type.hA;
      
      private a()
      {
        fP();
      }
      
      private void fP() {}
      
      private static a iX()
      {
        return new a();
      }
      
      private void jb()
      {
        if ((this.bitField0_ & 0x4) != 4)
        {
          this.listItem_ = new ArrayList(this.listItem_);
          this.bitField0_ |= 0x4;
        }
      }
      
      private void jc()
      {
        if ((this.bitField0_ & 0x8) != 8)
        {
          this.mapKey_ = new ArrayList(this.mapKey_);
          this.bitField0_ |= 0x8;
        }
      }
      
      private void jd()
      {
        if ((this.bitField0_ & 0x10) != 16)
        {
          this.mapValue_ = new ArrayList(this.mapValue_);
          this.bitField0_ |= 0x10;
        }
      }
      
      private void je()
      {
        if ((this.bitField0_ & 0x200) != 512)
        {
          this.templateToken_ = new ArrayList(this.templateToken_);
          this.bitField0_ |= 0x200;
        }
      }
      
      private void jf()
      {
        if ((this.bitField0_ & 0x400) != 1024)
        {
          this.escaping_ = new ArrayList(this.escaping_);
          this.bitField0_ |= 0x400;
        }
      }
      
      public a a(long paramLong)
      {
        this.bitField0_ |= 0x80;
        this.integer_ = paramLong;
        return this;
      }
      
      public a a(TypeSystem.Value.Type paramType)
      {
        if (paramType == null) {
          throw new NullPointerException();
        }
        this.bitField0_ |= 0x1;
        this.type_ = paramType;
        return this;
      }
      
      public TypeSystem.Value aP(int paramInt)
      {
        return (TypeSystem.Value)this.listItem_.get(paramInt);
      }
      
      public TypeSystem.Value aQ(int paramInt)
      {
        return (TypeSystem.Value)this.mapKey_.get(paramInt);
      }
      
      public TypeSystem.Value aR(int paramInt)
      {
        return (TypeSystem.Value)this.mapValue_.get(paramInt);
      }
      
      public TypeSystem.Value aS(int paramInt)
      {
        return (TypeSystem.Value)this.templateToken_.get(paramInt);
      }
      
      public int iB()
      {
        return this.mapKey_.size();
      }
      
      public int iD()
      {
        return this.mapValue_.size();
      }
      
      public int iP()
      {
        return this.templateToken_.size();
      }
      
      public a iY()
      {
        return iX().k(ja());
      }
      
      public TypeSystem.Value iZ()
      {
        TypeSystem.Value localValue = ja();
        if (!localValue.isInitialized()) {
          throw a(localValue);
        }
        return localValue;
      }
      
      public final boolean isInitialized()
      {
        if (!iu()) {}
        label37:
        label65:
        label93:
        label121:
        do
        {
          return false;
          int i = 0;
          for (;;)
          {
            if (i >= iz()) {
              break label37;
            }
            if (!aP(i).isInitialized()) {
              break;
            }
            i += 1;
          }
          i = 0;
          for (;;)
          {
            if (i >= iB()) {
              break label65;
            }
            if (!aQ(i).isInitialized()) {
              break;
            }
            i += 1;
          }
          i = 0;
          for (;;)
          {
            if (i >= iD()) {
              break label93;
            }
            if (!aR(i).isInitialized()) {
              break;
            }
            i += 1;
          }
          i = 0;
          for (;;)
          {
            if (i >= iP()) {
              break label121;
            }
            if (!aS(i).isInitialized()) {
              break;
            }
            i += 1;
          }
        } while (!BH());
        return true;
      }
      
      public TypeSystem.Value it()
      {
        return TypeSystem.Value.is();
      }
      
      public boolean iu()
      {
        return (this.bitField0_ & 0x1) == 1;
      }
      
      public int iz()
      {
        return this.listItem_.size();
      }
      
      public TypeSystem.Value ja()
      {
        int j = 1;
        TypeSystem.Value localValue = new TypeSystem.Value(this, null);
        int k = this.bitField0_;
        if ((k & 0x1) == 1) {}
        for (;;)
        {
          TypeSystem.Value.a(localValue, this.type_);
          int i = j;
          if ((k & 0x2) == 2) {
            i = j | 0x2;
          }
          TypeSystem.Value.a(localValue, this.string_);
          if ((this.bitField0_ & 0x4) == 4)
          {
            this.listItem_ = Collections.unmodifiableList(this.listItem_);
            this.bitField0_ &= 0xFFFFFFFB;
          }
          TypeSystem.Value.a(localValue, this.listItem_);
          if ((this.bitField0_ & 0x8) == 8)
          {
            this.mapKey_ = Collections.unmodifiableList(this.mapKey_);
            this.bitField0_ &= 0xFFFFFFF7;
          }
          TypeSystem.Value.b(localValue, this.mapKey_);
          if ((this.bitField0_ & 0x10) == 16)
          {
            this.mapValue_ = Collections.unmodifiableList(this.mapValue_);
            this.bitField0_ &= 0xFFFFFFEF;
          }
          TypeSystem.Value.c(localValue, this.mapValue_);
          j = i;
          if ((k & 0x20) == 32) {
            j = i | 0x4;
          }
          TypeSystem.Value.b(localValue, this.macroReference_);
          i = j;
          if ((k & 0x40) == 64) {
            i = j | 0x8;
          }
          TypeSystem.Value.c(localValue, this.functionId_);
          j = i;
          if ((k & 0x80) == 128) {
            j = i | 0x10;
          }
          TypeSystem.Value.a(localValue, this.integer_);
          i = j;
          if ((k & 0x100) == 256) {
            i = j | 0x20;
          }
          TypeSystem.Value.a(localValue, this.boolean_);
          if ((this.bitField0_ & 0x200) == 512)
          {
            this.templateToken_ = Collections.unmodifiableList(this.templateToken_);
            this.bitField0_ &= 0xFDFF;
          }
          TypeSystem.Value.d(localValue, this.templateToken_);
          if ((this.bitField0_ & 0x400) == 1024)
          {
            this.escaping_ = Collections.unmodifiableList(this.escaping_);
            this.bitField0_ &= 0xFBFF;
          }
          TypeSystem.Value.e(localValue, this.escaping_);
          j = i;
          if ((k & 0x800) == 2048) {
            j = i | 0x40;
          }
          TypeSystem.Value.b(localValue, this.containsReferences_);
          TypeSystem.Value.a(localValue, j);
          return localValue;
          j = 0;
        }
      }
      
      public a k(TypeSystem.Value paramValue)
      {
        if (paramValue == TypeSystem.Value.is()) {
          return this;
        }
        if (paramValue.iu()) {
          a(paramValue.iv());
        }
        if (paramValue.iw())
        {
          this.bitField0_ |= 0x2;
          this.string_ = TypeSystem.Value.b(paramValue);
        }
        if (!TypeSystem.Value.c(paramValue).isEmpty())
        {
          if (this.listItem_.isEmpty())
          {
            this.listItem_ = TypeSystem.Value.c(paramValue);
            this.bitField0_ &= 0xFFFFFFFB;
          }
        }
        else
        {
          if (!TypeSystem.Value.d(paramValue).isEmpty())
          {
            if (!this.mapKey_.isEmpty()) {
              break label411;
            }
            this.mapKey_ = TypeSystem.Value.d(paramValue);
            this.bitField0_ &= 0xFFFFFFF7;
          }
          label136:
          if (!TypeSystem.Value.e(paramValue).isEmpty())
          {
            if (!this.mapValue_.isEmpty()) {
              break label432;
            }
            this.mapValue_ = TypeSystem.Value.e(paramValue);
            this.bitField0_ &= 0xFFFFFFEF;
          }
          label179:
          if (paramValue.iE())
          {
            this.bitField0_ |= 0x20;
            this.macroReference_ = TypeSystem.Value.f(paramValue);
          }
          if (paramValue.iH())
          {
            this.bitField0_ |= 0x40;
            this.functionId_ = TypeSystem.Value.g(paramValue);
          }
          if (paramValue.iK()) {
            a(paramValue.iL());
          }
          if (paramValue.iM()) {
            k(paramValue.iN());
          }
          if (!TypeSystem.Value.h(paramValue).isEmpty())
          {
            if (!this.templateToken_.isEmpty()) {
              break label453;
            }
            this.templateToken_ = TypeSystem.Value.h(paramValue);
            this.bitField0_ &= 0xFDFF;
          }
          label307:
          if (!TypeSystem.Value.i(paramValue).isEmpty())
          {
            if (!this.escaping_.isEmpty()) {
              break label474;
            }
            this.escaping_ = TypeSystem.Value.i(paramValue);
            this.bitField0_ &= 0xFBFF;
          }
        }
        for (;;)
        {
          if (paramValue.iS()) {
            l(paramValue.iT());
          }
          a(paramValue);
          e(BE().a(TypeSystem.Value.j(paramValue)));
          return this;
          jb();
          this.listItem_.addAll(TypeSystem.Value.c(paramValue));
          break;
          label411:
          jc();
          this.mapKey_.addAll(TypeSystem.Value.d(paramValue));
          break label136;
          label432:
          jd();
          this.mapValue_.addAll(TypeSystem.Value.e(paramValue));
          break label179;
          label453:
          je();
          this.templateToken_.addAll(TypeSystem.Value.h(paramValue));
          break label307;
          label474:
          jf();
          this.escaping_.addAll(TypeSystem.Value.i(paramValue));
        }
      }
      
      public a k(boolean paramBoolean)
      {
        this.bitField0_ |= 0x100;
        this.boolean_ = paramBoolean;
        return this;
      }
      
      public a l(TypeSystem.Value paramValue)
      {
        if (paramValue == null) {
          throw new NullPointerException();
        }
        jb();
        this.listItem_.add(paramValue);
        return this;
      }
      
      public a l(boolean paramBoolean)
      {
        this.bitField0_ |= 0x800;
        this.containsReferences_ = paramBoolean;
        return this;
      }
      
      public a m(TypeSystem.Value paramValue)
      {
        if (paramValue == null) {
          throw new NullPointerException();
        }
        jc();
        this.mapKey_.add(paramValue);
        return this;
      }
      
      public a m(String paramString)
      {
        if (paramString == null) {
          throw new NullPointerException();
        }
        this.bitField0_ |= 0x2;
        this.string_ = paramString;
        return this;
      }
      
      public a n(TypeSystem.Value paramValue)
      {
        if (paramValue == null) {
          throw new NullPointerException();
        }
        jd();
        this.mapValue_.add(paramValue);
        return this;
      }
      
      /* Error */
      public a o(f paramf, g paramg)
      {
        // Byte code:
        //   0: getstatic 348	com/google/analytics/midtier/proto/containertag/TypeSystem$Value:gW	Lcom/google/tagmanager/protobuf/q;
        //   3: aload_1
        //   4: aload_2
        //   5: invokeinterface 353 3 0
        //   10: checkcast 9	com/google/analytics/midtier/proto/containertag/TypeSystem$Value
        //   13: astore_1
        //   14: aload_1
        //   15: ifnull +9 -> 24
        //   18: aload_0
        //   19: aload_1
        //   20: invokevirtual 103	com/google/analytics/midtier/proto/containertag/TypeSystem$Value$a:k	(Lcom/google/analytics/midtier/proto/containertag/TypeSystem$Value;)Lcom/google/analytics/midtier/proto/containertag/TypeSystem$Value$a;
        //   23: pop
        //   24: aload_0
        //   25: areturn
        //   26: astore_2
        //   27: aload_2
        //   28: invokevirtual 356	com/google/tagmanager/protobuf/InvalidProtocolBufferException:BN	()Lcom/google/tagmanager/protobuf/n;
        //   31: checkcast 9	com/google/analytics/midtier/proto/containertag/TypeSystem$Value
        //   34: astore_1
        //   35: aload_2
        //   36: athrow
        //   37: astore_2
        //   38: aload_1
        //   39: ifnull +9 -> 48
        //   42: aload_0
        //   43: aload_1
        //   44: invokevirtual 103	com/google/analytics/midtier/proto/containertag/TypeSystem$Value$a:k	(Lcom/google/analytics/midtier/proto/containertag/TypeSystem$Value;)Lcom/google/analytics/midtier/proto/containertag/TypeSystem$Value$a;
        //   47: pop
        //   48: aload_2
        //   49: athrow
        //   50: astore_2
        //   51: aconst_null
        //   52: astore_1
        //   53: goto -15 -> 38
        // Local variable table:
        //   start	length	slot	name	signature
        //   0	56	0	this	a
        //   0	56	1	paramf	f
        //   0	56	2	paramg	g
        // Exception table:
        //   from	to	target	type
        //   0	14	26	com/google/tagmanager/protobuf/InvalidProtocolBufferException
        //   35	37	37	finally
        //   0	14	50	finally
        //   27	35	50	finally
      }
    }
  }
  
  public static abstract interface a
    extends GeneratedMessageLite.c
  {}
}


/* Location:              /Users/amaurremi/uw/stringoid/static-dynamic-comparison/apps/quick pdf scanner/com.mobisystems.mobiscanner-213-dex2jar.jar!/com/google/analytics/midtier/proto/containertag/TypeSystem.class
 * Java compiler version: 6 (50.0)
 * JD-Core Version:       0.7.1
 */