package com.google.android.gms.internal;

import android.os.IBinder;
import android.os.Parcel;

class ga
        implements fy {
    private IBinder a;

    ga(IBinder paramIBinder) {
        this.a = paramIBinder;
    }

    /* Error */
    public void a(android.os.Bundle paramBundle) {
        // Byte code:
        //   0: invokestatic 23	android/os/Parcel:obtain	()Landroid/os/Parcel;
        //   3: astore_2
        //   4: invokestatic 23	android/os/Parcel:obtain	()Landroid/os/Parcel;
        //   7: astore_3
        //   8: aload_2
        //   9: ldc 25
        //   11: invokevirtual 29	android/os/Parcel:writeInterfaceToken	(Ljava/lang/String;)V
        //   14: aload_1
        //   15: ifnull +41 -> 56
        //   18: aload_2
        //   19: iconst_1
        //   20: invokevirtual 33	android/os/Parcel:writeInt	(I)V
        //   23: aload_1
        //   24: aload_2
        //   25: iconst_0
        //   26: invokevirtual 39	android/os/Bundle:writeToParcel	(Landroid/os/Parcel;I)V
        //   29: aload_0
        //   30: getfield 15	com/google/android/gms/internal/ga:a	Landroid/os/IBinder;
        //   33: iconst_1
        //   34: aload_2
        //   35: aload_3
        //   36: iconst_0
        //   37: invokeinterface 45 5 0
        //   42: pop
        //   43: aload_3
        //   44: invokevirtual 48	android/os/Parcel:readException	()V
        //   47: aload_3
        //   48: invokevirtual 51	android/os/Parcel:recycle	()V
        //   51: aload_2
        //   52: invokevirtual 51	android/os/Parcel:recycle	()V
        //   55: return
        //   56: aload_2
        //   57: iconst_0
        //   58: invokevirtual 33	android/os/Parcel:writeInt	(I)V
        //   61: goto -32 -> 29
        //   64: astore_1
        //   65: aload_3
        //   66: invokevirtual 51	android/os/Parcel:recycle	()V
        //   69: aload_2
        //   70: invokevirtual 51	android/os/Parcel:recycle	()V
        //   73: aload_1
        //   74: athrow
        // Local variable table:
        //   start	length	slot	name	signature
        //   0	75	0	this	ga
        //   0	75	1	paramBundle	android.os.Bundle
        //   3	67	2	localParcel1	Parcel
        //   7	59	3	localParcel2	Parcel
        // Exception table:
        //   from	to	target	type
        //   8	14	64	finally
        //   18	29	64	finally
        //   29	47	64	finally
        //   56	61	64	finally
    }

    public IBinder asBinder() {
        return this.a;
    }

    /* Error */
    public void b(android.os.Bundle paramBundle) {
        // Byte code:
        //   0: invokestatic 23	android/os/Parcel:obtain	()Landroid/os/Parcel;
        //   3: astore_2
        //   4: invokestatic 23	android/os/Parcel:obtain	()Landroid/os/Parcel;
        //   7: astore_3
        //   8: aload_2
        //   9: ldc 25
        //   11: invokevirtual 29	android/os/Parcel:writeInterfaceToken	(Ljava/lang/String;)V
        //   14: aload_1
        //   15: ifnull +54 -> 69
        //   18: aload_2
        //   19: iconst_1
        //   20: invokevirtual 33	android/os/Parcel:writeInt	(I)V
        //   23: aload_1
        //   24: aload_2
        //   25: iconst_0
        //   26: invokevirtual 39	android/os/Bundle:writeToParcel	(Landroid/os/Parcel;I)V
        //   29: aload_0
        //   30: getfield 15	com/google/android/gms/internal/ga:a	Landroid/os/IBinder;
        //   33: bipush 6
        //   35: aload_2
        //   36: aload_3
        //   37: iconst_0
        //   38: invokeinterface 45 5 0
        //   43: pop
        //   44: aload_3
        //   45: invokevirtual 48	android/os/Parcel:readException	()V
        //   48: aload_3
        //   49: invokevirtual 58	android/os/Parcel:readInt	()I
        //   52: ifeq +8 -> 60
        //   55: aload_1
        //   56: aload_3
        //   57: invokevirtual 62	android/os/Bundle:readFromParcel	(Landroid/os/Parcel;)V
        //   60: aload_3
        //   61: invokevirtual 51	android/os/Parcel:recycle	()V
        //   64: aload_2
        //   65: invokevirtual 51	android/os/Parcel:recycle	()V
        //   68: return
        //   69: aload_2
        //   70: iconst_0
        //   71: invokevirtual 33	android/os/Parcel:writeInt	(I)V
        //   74: goto -45 -> 29
        //   77: astore_1
        //   78: aload_3
        //   79: invokevirtual 51	android/os/Parcel:recycle	()V
        //   82: aload_2
        //   83: invokevirtual 51	android/os/Parcel:recycle	()V
        //   86: aload_1
        //   87: athrow
        // Local variable table:
        //   start	length	slot	name	signature
        //   0	88	0	this	ga
        //   0	88	1	paramBundle	android.os.Bundle
        //   3	80	2	localParcel1	Parcel
        //   7	72	3	localParcel2	Parcel
        // Exception table:
        //   from	to	target	type
        //   8	14	77	finally
        //   18	29	77	finally
        //   29	60	77	finally
        //   69	74	77	finally
    }

    public void d() {
        Parcel localParcel1 = Parcel.obtain();
        Parcel localParcel2 = Parcel.obtain();
        try {
            localParcel1.writeInterfaceToken("com.google.android.gms.ads.internal.overlay.client.IAdOverlay");
            this.a.transact(2, localParcel1, localParcel2, 0);
            localParcel2.readException();
            return;
        } finally {
            localParcel2.recycle();
            localParcel1.recycle();
        }
    }

    public void e() {
        Parcel localParcel1 = Parcel.obtain();
        Parcel localParcel2 = Parcel.obtain();
        try {
            localParcel1.writeInterfaceToken("com.google.android.gms.ads.internal.overlay.client.IAdOverlay");
            this.a.transact(3, localParcel1, localParcel2, 0);
            localParcel2.readException();
            return;
        } finally {
            localParcel2.recycle();
            localParcel1.recycle();
        }
    }

    public void f() {
        Parcel localParcel1 = Parcel.obtain();
        Parcel localParcel2 = Parcel.obtain();
        try {
            localParcel1.writeInterfaceToken("com.google.android.gms.ads.internal.overlay.client.IAdOverlay");
            this.a.transact(4, localParcel1, localParcel2, 0);
            localParcel2.readException();
            return;
        } finally {
            localParcel2.recycle();
            localParcel1.recycle();
        }
    }

    public void g() {
        Parcel localParcel1 = Parcel.obtain();
        Parcel localParcel2 = Parcel.obtain();
        try {
            localParcel1.writeInterfaceToken("com.google.android.gms.ads.internal.overlay.client.IAdOverlay");
            this.a.transact(5, localParcel1, localParcel2, 0);
            localParcel2.readException();
            return;
        } finally {
            localParcel2.recycle();
            localParcel1.recycle();
        }
    }

    public void h() {
        Parcel localParcel1 = Parcel.obtain();
        Parcel localParcel2 = Parcel.obtain();
        try {
            localParcel1.writeInterfaceToken("com.google.android.gms.ads.internal.overlay.client.IAdOverlay");
            this.a.transact(7, localParcel1, localParcel2, 0);
            localParcel2.readException();
            return;
        } finally {
            localParcel2.recycle();
            localParcel1.recycle();
        }
    }

    public void i() {
        Parcel localParcel1 = Parcel.obtain();
        Parcel localParcel2 = Parcel.obtain();
        try {
            localParcel1.writeInterfaceToken("com.google.android.gms.ads.internal.overlay.client.IAdOverlay");
            this.a.transact(8, localParcel1, localParcel2, 0);
            localParcel2.readException();
            return;
        } finally {
            localParcel2.recycle();
            localParcel1.recycle();
        }
    }

    public void j() {
        Parcel localParcel1 = Parcel.obtain();
        Parcel localParcel2 = Parcel.obtain();
        try {
            localParcel1.writeInterfaceToken("com.google.android.gms.ads.internal.overlay.client.IAdOverlay");
            this.a.transact(9, localParcel1, localParcel2, 0);
            localParcel2.readException();
            return;
        } finally {
            localParcel2.recycle();
            localParcel1.recycle();
        }
    }
}


/* Location:              /Users/amaurremi/uw/stringoid stuff/static vs dynamic/ifunny/mobi.ifunny-2447-dex2jar.jar!/com/google/android/gms/internal/ga.class
 * Java compiler version: 6 (50.0)
 * JD-Core Version:       0.7.1
 */