package com.google.android.gms.wearable.internal;

import android.net.Uri;
import android.os.Binder;
import android.os.IBinder;
import android.os.IInterface;
import android.os.Parcel;
import android.os.Parcelable.Creator;
import android.os.RemoteException;
import com.google.android.gms.wearable.Asset;
import com.google.android.gms.wearable.PutDataRequest;
import com.google.android.gms.wearable.c;

public abstract interface ad
  extends IInterface
{
  public abstract void a(ab paramab)
    throws RemoteException;
  
  public abstract void a(ab paramab, Uri paramUri)
    throws RemoteException;
  
  public abstract void a(ab paramab, Asset paramAsset)
    throws RemoteException;
  
  public abstract void a(ab paramab, PutDataRequest paramPutDataRequest)
    throws RemoteException;
  
  public abstract void a(ab paramab, c paramc)
    throws RemoteException;
  
  public abstract void a(ab paramab, ao paramao)
    throws RemoteException;
  
  public abstract void a(ab paramab, b paramb)
    throws RemoteException;
  
  public abstract void a(ab paramab, String paramString1, String paramString2, byte[] paramArrayOfByte)
    throws RemoteException;
  
  public abstract void b(ab paramab)
    throws RemoteException;
  
  public abstract void b(ab paramab, Uri paramUri)
    throws RemoteException;
  
  public abstract void c(ab paramab)
    throws RemoteException;
  
  public abstract void c(ab paramab, Uri paramUri)
    throws RemoteException;
  
  public abstract void d(ab paramab)
    throws RemoteException;
  
  public abstract void e(ab paramab)
    throws RemoteException;
  
  public abstract void f(ab paramab)
    throws RemoteException;
  
  public abstract void g(ab paramab)
    throws RemoteException;
  
  public abstract void h(ab paramab)
    throws RemoteException;
  
  public static abstract class a
    extends Binder
    implements ad
  {
    public static ad by(IBinder paramIBinder)
    {
      if (paramIBinder == null) {
        return null;
      }
      IInterface localIInterface = paramIBinder.queryLocalInterface("com.google.android.gms.wearable.internal.IWearableService");
      if ((localIInterface != null) && ((localIInterface instanceof ad))) {
        return (ad)localIInterface;
      }
      return new a(paramIBinder);
    }
    
    public boolean onTransact(int paramInt1, Parcel paramParcel1, Parcel paramParcel2, int paramInt2)
      throws RemoteException
    {
      ab localab1 = null;
      ab localab2 = null;
      Object localObject2 = null;
      Object localObject3 = null;
      Object localObject4 = null;
      Object localObject5 = null;
      Object localObject6 = null;
      Object localObject1 = null;
      switch (paramInt1)
      {
      default: 
        return super.onTransact(paramInt1, paramParcel1, paramParcel2, paramInt2);
      case 1598968902: 
        paramParcel2.writeString("com.google.android.gms.wearable.internal.IWearableService");
        return true;
      case 2: 
        paramParcel1.enforceInterface("com.google.android.gms.wearable.internal.IWearableService");
        localab1 = ab.a.bw(paramParcel1.readStrongBinder());
        if (paramParcel1.readInt() != 0) {
          localObject1 = (c)c.CREATOR.createFromParcel(paramParcel1);
        }
        a(localab1, (c)localObject1);
        paramParcel2.writeNoException();
        return true;
      case 3: 
        paramParcel1.enforceInterface("com.google.android.gms.wearable.internal.IWearableService");
        a(ab.a.bw(paramParcel1.readStrongBinder()));
        paramParcel2.writeNoException();
        return true;
      case 4: 
        paramParcel1.enforceInterface("com.google.android.gms.wearable.internal.IWearableService");
        b(ab.a.bw(paramParcel1.readStrongBinder()));
        paramParcel2.writeNoException();
        return true;
      case 5: 
        paramParcel1.enforceInterface("com.google.android.gms.wearable.internal.IWearableService");
        c(ab.a.bw(paramParcel1.readStrongBinder()));
        paramParcel2.writeNoException();
        return true;
      case 6: 
        paramParcel1.enforceInterface("com.google.android.gms.wearable.internal.IWearableService");
        localab2 = ab.a.bw(paramParcel1.readStrongBinder());
        localObject1 = localab1;
        if (paramParcel1.readInt() != 0) {
          localObject1 = (PutDataRequest)PutDataRequest.CREATOR.createFromParcel(paramParcel1);
        }
        a(localab2, (PutDataRequest)localObject1);
        paramParcel2.writeNoException();
        return true;
      case 7: 
        paramParcel1.enforceInterface("com.google.android.gms.wearable.internal.IWearableService");
        localab1 = ab.a.bw(paramParcel1.readStrongBinder());
        localObject1 = localab2;
        if (paramParcel1.readInt() != 0) {
          localObject1 = (Uri)Uri.CREATOR.createFromParcel(paramParcel1);
        }
        a(localab1, (Uri)localObject1);
        paramParcel2.writeNoException();
        return true;
      case 8: 
        paramParcel1.enforceInterface("com.google.android.gms.wearable.internal.IWearableService");
        d(ab.a.bw(paramParcel1.readStrongBinder()));
        paramParcel2.writeNoException();
        return true;
      case 9: 
        paramParcel1.enforceInterface("com.google.android.gms.wearable.internal.IWearableService");
        localab1 = ab.a.bw(paramParcel1.readStrongBinder());
        localObject1 = localObject2;
        if (paramParcel1.readInt() != 0) {
          localObject1 = (Uri)Uri.CREATOR.createFromParcel(paramParcel1);
        }
        b(localab1, (Uri)localObject1);
        paramParcel2.writeNoException();
        return true;
      case 11: 
        paramParcel1.enforceInterface("com.google.android.gms.wearable.internal.IWearableService");
        localab1 = ab.a.bw(paramParcel1.readStrongBinder());
        localObject1 = localObject3;
        if (paramParcel1.readInt() != 0) {
          localObject1 = (Uri)Uri.CREATOR.createFromParcel(paramParcel1);
        }
        c(localab1, (Uri)localObject1);
        paramParcel2.writeNoException();
        return true;
      case 12: 
        paramParcel1.enforceInterface("com.google.android.gms.wearable.internal.IWearableService");
        a(ab.a.bw(paramParcel1.readStrongBinder()), paramParcel1.readString(), paramParcel1.readString(), paramParcel1.createByteArray());
        paramParcel2.writeNoException();
        return true;
      case 13: 
        paramParcel1.enforceInterface("com.google.android.gms.wearable.internal.IWearableService");
        localab1 = ab.a.bw(paramParcel1.readStrongBinder());
        localObject1 = localObject4;
        if (paramParcel1.readInt() != 0) {
          localObject1 = (Asset)Asset.CREATOR.createFromParcel(paramParcel1);
        }
        a(localab1, (Asset)localObject1);
        paramParcel2.writeNoException();
        return true;
      case 14: 
        paramParcel1.enforceInterface("com.google.android.gms.wearable.internal.IWearableService");
        e(ab.a.bw(paramParcel1.readStrongBinder()));
        paramParcel2.writeNoException();
        return true;
      case 15: 
        paramParcel1.enforceInterface("com.google.android.gms.wearable.internal.IWearableService");
        f(ab.a.bw(paramParcel1.readStrongBinder()));
        paramParcel2.writeNoException();
        return true;
      case 16: 
        paramParcel1.enforceInterface("com.google.android.gms.wearable.internal.IWearableService");
        localab1 = ab.a.bw(paramParcel1.readStrongBinder());
        localObject1 = localObject5;
        if (paramParcel1.readInt() != 0) {
          localObject1 = (b)b.CREATOR.createFromParcel(paramParcel1);
        }
        a(localab1, (b)localObject1);
        paramParcel2.writeNoException();
        return true;
      case 17: 
        paramParcel1.enforceInterface("com.google.android.gms.wearable.internal.IWearableService");
        localab1 = ab.a.bw(paramParcel1.readStrongBinder());
        localObject1 = localObject6;
        if (paramParcel1.readInt() != 0) {
          localObject1 = (ao)ao.CREATOR.createFromParcel(paramParcel1);
        }
        a(localab1, (ao)localObject1);
        paramParcel2.writeNoException();
        return true;
      case 18: 
        paramParcel1.enforceInterface("com.google.android.gms.wearable.internal.IWearableService");
        g(ab.a.bw(paramParcel1.readStrongBinder()));
        paramParcel2.writeNoException();
        return true;
      }
      paramParcel1.enforceInterface("com.google.android.gms.wearable.internal.IWearableService");
      h(ab.a.bw(paramParcel1.readStrongBinder()));
      paramParcel2.writeNoException();
      return true;
    }
    
    private static class a
      implements ad
    {
      private IBinder ko;
      
      a(IBinder paramIBinder)
      {
        this.ko = paramIBinder;
      }
      
      /* Error */
      public void a(ab paramab)
        throws RemoteException
      {
        // Byte code:
        //   0: invokestatic 28	android/os/Parcel:obtain	()Landroid/os/Parcel;
        //   3: astore_2
        //   4: invokestatic 28	android/os/Parcel:obtain	()Landroid/os/Parcel;
        //   7: astore_3
        //   8: aload_2
        //   9: ldc 30
        //   11: invokevirtual 34	android/os/Parcel:writeInterfaceToken	(Ljava/lang/String;)V
        //   14: aload_1
        //   15: ifnull +42 -> 57
        //   18: aload_1
        //   19: invokeinterface 40 1 0
        //   24: astore_1
        //   25: aload_2
        //   26: aload_1
        //   27: invokevirtual 43	android/os/Parcel:writeStrongBinder	(Landroid/os/IBinder;)V
        //   30: aload_0
        //   31: getfield 18	com/google/android/gms/wearable/internal/ad$a$a:ko	Landroid/os/IBinder;
        //   34: iconst_3
        //   35: aload_2
        //   36: aload_3
        //   37: iconst_0
        //   38: invokeinterface 49 5 0
        //   43: pop
        //   44: aload_3
        //   45: invokevirtual 52	android/os/Parcel:readException	()V
        //   48: aload_3
        //   49: invokevirtual 55	android/os/Parcel:recycle	()V
        //   52: aload_2
        //   53: invokevirtual 55	android/os/Parcel:recycle	()V
        //   56: return
        //   57: aconst_null
        //   58: astore_1
        //   59: goto -34 -> 25
        //   62: astore_1
        //   63: aload_3
        //   64: invokevirtual 55	android/os/Parcel:recycle	()V
        //   67: aload_2
        //   68: invokevirtual 55	android/os/Parcel:recycle	()V
        //   71: aload_1
        //   72: athrow
        // Local variable table:
        //   start	length	slot	name	signature
        //   0	73	0	this	a
        //   0	73	1	paramab	ab
        //   3	65	2	localParcel1	Parcel
        //   7	57	3	localParcel2	Parcel
        // Exception table:
        //   from	to	target	type
        //   8	14	62	finally
        //   18	25	62	finally
        //   25	48	62	finally
      }
      
      /* Error */
      public void a(ab paramab, Uri paramUri)
        throws RemoteException
      {
        // Byte code:
        //   0: invokestatic 28	android/os/Parcel:obtain	()Landroid/os/Parcel;
        //   3: astore_3
        //   4: invokestatic 28	android/os/Parcel:obtain	()Landroid/os/Parcel;
        //   7: astore 4
        //   9: aload_3
        //   10: ldc 30
        //   12: invokevirtual 34	android/os/Parcel:writeInterfaceToken	(Ljava/lang/String;)V
        //   15: aload_1
        //   16: ifnull +61 -> 77
        //   19: aload_1
        //   20: invokeinterface 40 1 0
        //   25: astore_1
        //   26: aload_3
        //   27: aload_1
        //   28: invokevirtual 43	android/os/Parcel:writeStrongBinder	(Landroid/os/IBinder;)V
        //   31: aload_2
        //   32: ifnull +50 -> 82
        //   35: aload_3
        //   36: iconst_1
        //   37: invokevirtual 61	android/os/Parcel:writeInt	(I)V
        //   40: aload_2
        //   41: aload_3
        //   42: iconst_0
        //   43: invokevirtual 67	android/net/Uri:writeToParcel	(Landroid/os/Parcel;I)V
        //   46: aload_0
        //   47: getfield 18	com/google/android/gms/wearable/internal/ad$a$a:ko	Landroid/os/IBinder;
        //   50: bipush 7
        //   52: aload_3
        //   53: aload 4
        //   55: iconst_0
        //   56: invokeinterface 49 5 0
        //   61: pop
        //   62: aload 4
        //   64: invokevirtual 52	android/os/Parcel:readException	()V
        //   67: aload 4
        //   69: invokevirtual 55	android/os/Parcel:recycle	()V
        //   72: aload_3
        //   73: invokevirtual 55	android/os/Parcel:recycle	()V
        //   76: return
        //   77: aconst_null
        //   78: astore_1
        //   79: goto -53 -> 26
        //   82: aload_3
        //   83: iconst_0
        //   84: invokevirtual 61	android/os/Parcel:writeInt	(I)V
        //   87: goto -41 -> 46
        //   90: astore_1
        //   91: aload 4
        //   93: invokevirtual 55	android/os/Parcel:recycle	()V
        //   96: aload_3
        //   97: invokevirtual 55	android/os/Parcel:recycle	()V
        //   100: aload_1
        //   101: athrow
        // Local variable table:
        //   start	length	slot	name	signature
        //   0	102	0	this	a
        //   0	102	1	paramab	ab
        //   0	102	2	paramUri	Uri
        //   3	94	3	localParcel1	Parcel
        //   7	85	4	localParcel2	Parcel
        // Exception table:
        //   from	to	target	type
        //   9	15	90	finally
        //   19	26	90	finally
        //   26	31	90	finally
        //   35	46	90	finally
        //   46	67	90	finally
        //   82	87	90	finally
      }
      
      /* Error */
      public void a(ab paramab, Asset paramAsset)
        throws RemoteException
      {
        // Byte code:
        //   0: invokestatic 28	android/os/Parcel:obtain	()Landroid/os/Parcel;
        //   3: astore_3
        //   4: invokestatic 28	android/os/Parcel:obtain	()Landroid/os/Parcel;
        //   7: astore 4
        //   9: aload_3
        //   10: ldc 30
        //   12: invokevirtual 34	android/os/Parcel:writeInterfaceToken	(Ljava/lang/String;)V
        //   15: aload_1
        //   16: ifnull +61 -> 77
        //   19: aload_1
        //   20: invokeinterface 40 1 0
        //   25: astore_1
        //   26: aload_3
        //   27: aload_1
        //   28: invokevirtual 43	android/os/Parcel:writeStrongBinder	(Landroid/os/IBinder;)V
        //   31: aload_2
        //   32: ifnull +50 -> 82
        //   35: aload_3
        //   36: iconst_1
        //   37: invokevirtual 61	android/os/Parcel:writeInt	(I)V
        //   40: aload_2
        //   41: aload_3
        //   42: iconst_0
        //   43: invokevirtual 71	com/google/android/gms/wearable/Asset:writeToParcel	(Landroid/os/Parcel;I)V
        //   46: aload_0
        //   47: getfield 18	com/google/android/gms/wearable/internal/ad$a$a:ko	Landroid/os/IBinder;
        //   50: bipush 13
        //   52: aload_3
        //   53: aload 4
        //   55: iconst_0
        //   56: invokeinterface 49 5 0
        //   61: pop
        //   62: aload 4
        //   64: invokevirtual 52	android/os/Parcel:readException	()V
        //   67: aload 4
        //   69: invokevirtual 55	android/os/Parcel:recycle	()V
        //   72: aload_3
        //   73: invokevirtual 55	android/os/Parcel:recycle	()V
        //   76: return
        //   77: aconst_null
        //   78: astore_1
        //   79: goto -53 -> 26
        //   82: aload_3
        //   83: iconst_0
        //   84: invokevirtual 61	android/os/Parcel:writeInt	(I)V
        //   87: goto -41 -> 46
        //   90: astore_1
        //   91: aload 4
        //   93: invokevirtual 55	android/os/Parcel:recycle	()V
        //   96: aload_3
        //   97: invokevirtual 55	android/os/Parcel:recycle	()V
        //   100: aload_1
        //   101: athrow
        // Local variable table:
        //   start	length	slot	name	signature
        //   0	102	0	this	a
        //   0	102	1	paramab	ab
        //   0	102	2	paramAsset	Asset
        //   3	94	3	localParcel1	Parcel
        //   7	85	4	localParcel2	Parcel
        // Exception table:
        //   from	to	target	type
        //   9	15	90	finally
        //   19	26	90	finally
        //   26	31	90	finally
        //   35	46	90	finally
        //   46	67	90	finally
        //   82	87	90	finally
      }
      
      /* Error */
      public void a(ab paramab, PutDataRequest paramPutDataRequest)
        throws RemoteException
      {
        // Byte code:
        //   0: invokestatic 28	android/os/Parcel:obtain	()Landroid/os/Parcel;
        //   3: astore_3
        //   4: invokestatic 28	android/os/Parcel:obtain	()Landroid/os/Parcel;
        //   7: astore 4
        //   9: aload_3
        //   10: ldc 30
        //   12: invokevirtual 34	android/os/Parcel:writeInterfaceToken	(Ljava/lang/String;)V
        //   15: aload_1
        //   16: ifnull +61 -> 77
        //   19: aload_1
        //   20: invokeinterface 40 1 0
        //   25: astore_1
        //   26: aload_3
        //   27: aload_1
        //   28: invokevirtual 43	android/os/Parcel:writeStrongBinder	(Landroid/os/IBinder;)V
        //   31: aload_2
        //   32: ifnull +50 -> 82
        //   35: aload_3
        //   36: iconst_1
        //   37: invokevirtual 61	android/os/Parcel:writeInt	(I)V
        //   40: aload_2
        //   41: aload_3
        //   42: iconst_0
        //   43: invokevirtual 75	com/google/android/gms/wearable/PutDataRequest:writeToParcel	(Landroid/os/Parcel;I)V
        //   46: aload_0
        //   47: getfield 18	com/google/android/gms/wearable/internal/ad$a$a:ko	Landroid/os/IBinder;
        //   50: bipush 6
        //   52: aload_3
        //   53: aload 4
        //   55: iconst_0
        //   56: invokeinterface 49 5 0
        //   61: pop
        //   62: aload 4
        //   64: invokevirtual 52	android/os/Parcel:readException	()V
        //   67: aload 4
        //   69: invokevirtual 55	android/os/Parcel:recycle	()V
        //   72: aload_3
        //   73: invokevirtual 55	android/os/Parcel:recycle	()V
        //   76: return
        //   77: aconst_null
        //   78: astore_1
        //   79: goto -53 -> 26
        //   82: aload_3
        //   83: iconst_0
        //   84: invokevirtual 61	android/os/Parcel:writeInt	(I)V
        //   87: goto -41 -> 46
        //   90: astore_1
        //   91: aload 4
        //   93: invokevirtual 55	android/os/Parcel:recycle	()V
        //   96: aload_3
        //   97: invokevirtual 55	android/os/Parcel:recycle	()V
        //   100: aload_1
        //   101: athrow
        // Local variable table:
        //   start	length	slot	name	signature
        //   0	102	0	this	a
        //   0	102	1	paramab	ab
        //   0	102	2	paramPutDataRequest	PutDataRequest
        //   3	94	3	localParcel1	Parcel
        //   7	85	4	localParcel2	Parcel
        // Exception table:
        //   from	to	target	type
        //   9	15	90	finally
        //   19	26	90	finally
        //   26	31	90	finally
        //   35	46	90	finally
        //   46	67	90	finally
        //   82	87	90	finally
      }
      
      /* Error */
      public void a(ab paramab, c paramc)
        throws RemoteException
      {
        // Byte code:
        //   0: invokestatic 28	android/os/Parcel:obtain	()Landroid/os/Parcel;
        //   3: astore_3
        //   4: invokestatic 28	android/os/Parcel:obtain	()Landroid/os/Parcel;
        //   7: astore 4
        //   9: aload_3
        //   10: ldc 30
        //   12: invokevirtual 34	android/os/Parcel:writeInterfaceToken	(Ljava/lang/String;)V
        //   15: aload_1
        //   16: ifnull +60 -> 76
        //   19: aload_1
        //   20: invokeinterface 40 1 0
        //   25: astore_1
        //   26: aload_3
        //   27: aload_1
        //   28: invokevirtual 43	android/os/Parcel:writeStrongBinder	(Landroid/os/IBinder;)V
        //   31: aload_2
        //   32: ifnull +49 -> 81
        //   35: aload_3
        //   36: iconst_1
        //   37: invokevirtual 61	android/os/Parcel:writeInt	(I)V
        //   40: aload_2
        //   41: aload_3
        //   42: iconst_0
        //   43: invokevirtual 79	com/google/android/gms/wearable/c:writeToParcel	(Landroid/os/Parcel;I)V
        //   46: aload_0
        //   47: getfield 18	com/google/android/gms/wearable/internal/ad$a$a:ko	Landroid/os/IBinder;
        //   50: iconst_2
        //   51: aload_3
        //   52: aload 4
        //   54: iconst_0
        //   55: invokeinterface 49 5 0
        //   60: pop
        //   61: aload 4
        //   63: invokevirtual 52	android/os/Parcel:readException	()V
        //   66: aload 4
        //   68: invokevirtual 55	android/os/Parcel:recycle	()V
        //   71: aload_3
        //   72: invokevirtual 55	android/os/Parcel:recycle	()V
        //   75: return
        //   76: aconst_null
        //   77: astore_1
        //   78: goto -52 -> 26
        //   81: aload_3
        //   82: iconst_0
        //   83: invokevirtual 61	android/os/Parcel:writeInt	(I)V
        //   86: goto -40 -> 46
        //   89: astore_1
        //   90: aload 4
        //   92: invokevirtual 55	android/os/Parcel:recycle	()V
        //   95: aload_3
        //   96: invokevirtual 55	android/os/Parcel:recycle	()V
        //   99: aload_1
        //   100: athrow
        // Local variable table:
        //   start	length	slot	name	signature
        //   0	101	0	this	a
        //   0	101	1	paramab	ab
        //   0	101	2	paramc	c
        //   3	93	3	localParcel1	Parcel
        //   7	84	4	localParcel2	Parcel
        // Exception table:
        //   from	to	target	type
        //   9	15	89	finally
        //   19	26	89	finally
        //   26	31	89	finally
        //   35	46	89	finally
        //   46	66	89	finally
        //   81	86	89	finally
      }
      
      /* Error */
      public void a(ab paramab, ao paramao)
        throws RemoteException
      {
        // Byte code:
        //   0: invokestatic 28	android/os/Parcel:obtain	()Landroid/os/Parcel;
        //   3: astore_3
        //   4: invokestatic 28	android/os/Parcel:obtain	()Landroid/os/Parcel;
        //   7: astore 4
        //   9: aload_3
        //   10: ldc 30
        //   12: invokevirtual 34	android/os/Parcel:writeInterfaceToken	(Ljava/lang/String;)V
        //   15: aload_1
        //   16: ifnull +61 -> 77
        //   19: aload_1
        //   20: invokeinterface 40 1 0
        //   25: astore_1
        //   26: aload_3
        //   27: aload_1
        //   28: invokevirtual 43	android/os/Parcel:writeStrongBinder	(Landroid/os/IBinder;)V
        //   31: aload_2
        //   32: ifnull +50 -> 82
        //   35: aload_3
        //   36: iconst_1
        //   37: invokevirtual 61	android/os/Parcel:writeInt	(I)V
        //   40: aload_2
        //   41: aload_3
        //   42: iconst_0
        //   43: invokevirtual 83	com/google/android/gms/wearable/internal/ao:writeToParcel	(Landroid/os/Parcel;I)V
        //   46: aload_0
        //   47: getfield 18	com/google/android/gms/wearable/internal/ad$a$a:ko	Landroid/os/IBinder;
        //   50: bipush 17
        //   52: aload_3
        //   53: aload 4
        //   55: iconst_0
        //   56: invokeinterface 49 5 0
        //   61: pop
        //   62: aload 4
        //   64: invokevirtual 52	android/os/Parcel:readException	()V
        //   67: aload 4
        //   69: invokevirtual 55	android/os/Parcel:recycle	()V
        //   72: aload_3
        //   73: invokevirtual 55	android/os/Parcel:recycle	()V
        //   76: return
        //   77: aconst_null
        //   78: astore_1
        //   79: goto -53 -> 26
        //   82: aload_3
        //   83: iconst_0
        //   84: invokevirtual 61	android/os/Parcel:writeInt	(I)V
        //   87: goto -41 -> 46
        //   90: astore_1
        //   91: aload 4
        //   93: invokevirtual 55	android/os/Parcel:recycle	()V
        //   96: aload_3
        //   97: invokevirtual 55	android/os/Parcel:recycle	()V
        //   100: aload_1
        //   101: athrow
        // Local variable table:
        //   start	length	slot	name	signature
        //   0	102	0	this	a
        //   0	102	1	paramab	ab
        //   0	102	2	paramao	ao
        //   3	94	3	localParcel1	Parcel
        //   7	85	4	localParcel2	Parcel
        // Exception table:
        //   from	to	target	type
        //   9	15	90	finally
        //   19	26	90	finally
        //   26	31	90	finally
        //   35	46	90	finally
        //   46	67	90	finally
        //   82	87	90	finally
      }
      
      /* Error */
      public void a(ab paramab, b paramb)
        throws RemoteException
      {
        // Byte code:
        //   0: invokestatic 28	android/os/Parcel:obtain	()Landroid/os/Parcel;
        //   3: astore_3
        //   4: invokestatic 28	android/os/Parcel:obtain	()Landroid/os/Parcel;
        //   7: astore 4
        //   9: aload_3
        //   10: ldc 30
        //   12: invokevirtual 34	android/os/Parcel:writeInterfaceToken	(Ljava/lang/String;)V
        //   15: aload_1
        //   16: ifnull +61 -> 77
        //   19: aload_1
        //   20: invokeinterface 40 1 0
        //   25: astore_1
        //   26: aload_3
        //   27: aload_1
        //   28: invokevirtual 43	android/os/Parcel:writeStrongBinder	(Landroid/os/IBinder;)V
        //   31: aload_2
        //   32: ifnull +50 -> 82
        //   35: aload_3
        //   36: iconst_1
        //   37: invokevirtual 61	android/os/Parcel:writeInt	(I)V
        //   40: aload_2
        //   41: aload_3
        //   42: iconst_0
        //   43: invokevirtual 87	com/google/android/gms/wearable/internal/b:writeToParcel	(Landroid/os/Parcel;I)V
        //   46: aload_0
        //   47: getfield 18	com/google/android/gms/wearable/internal/ad$a$a:ko	Landroid/os/IBinder;
        //   50: bipush 16
        //   52: aload_3
        //   53: aload 4
        //   55: iconst_0
        //   56: invokeinterface 49 5 0
        //   61: pop
        //   62: aload 4
        //   64: invokevirtual 52	android/os/Parcel:readException	()V
        //   67: aload 4
        //   69: invokevirtual 55	android/os/Parcel:recycle	()V
        //   72: aload_3
        //   73: invokevirtual 55	android/os/Parcel:recycle	()V
        //   76: return
        //   77: aconst_null
        //   78: astore_1
        //   79: goto -53 -> 26
        //   82: aload_3
        //   83: iconst_0
        //   84: invokevirtual 61	android/os/Parcel:writeInt	(I)V
        //   87: goto -41 -> 46
        //   90: astore_1
        //   91: aload 4
        //   93: invokevirtual 55	android/os/Parcel:recycle	()V
        //   96: aload_3
        //   97: invokevirtual 55	android/os/Parcel:recycle	()V
        //   100: aload_1
        //   101: athrow
        // Local variable table:
        //   start	length	slot	name	signature
        //   0	102	0	this	a
        //   0	102	1	paramab	ab
        //   0	102	2	paramb	b
        //   3	94	3	localParcel1	Parcel
        //   7	85	4	localParcel2	Parcel
        // Exception table:
        //   from	to	target	type
        //   9	15	90	finally
        //   19	26	90	finally
        //   26	31	90	finally
        //   35	46	90	finally
        //   46	67	90	finally
        //   82	87	90	finally
      }
      
      /* Error */
      public void a(ab paramab, String paramString1, String paramString2, byte[] paramArrayOfByte)
        throws RemoteException
      {
        // Byte code:
        //   0: invokestatic 28	android/os/Parcel:obtain	()Landroid/os/Parcel;
        //   3: astore 5
        //   5: invokestatic 28	android/os/Parcel:obtain	()Landroid/os/Parcel;
        //   8: astore 6
        //   10: aload 5
        //   12: ldc 30
        //   14: invokevirtual 34	android/os/Parcel:writeInterfaceToken	(Ljava/lang/String;)V
        //   17: aload_1
        //   18: ifnull +68 -> 86
        //   21: aload_1
        //   22: invokeinterface 40 1 0
        //   27: astore_1
        //   28: aload 5
        //   30: aload_1
        //   31: invokevirtual 43	android/os/Parcel:writeStrongBinder	(Landroid/os/IBinder;)V
        //   34: aload 5
        //   36: aload_2
        //   37: invokevirtual 91	android/os/Parcel:writeString	(Ljava/lang/String;)V
        //   40: aload 5
        //   42: aload_3
        //   43: invokevirtual 91	android/os/Parcel:writeString	(Ljava/lang/String;)V
        //   46: aload 5
        //   48: aload 4
        //   50: invokevirtual 95	android/os/Parcel:writeByteArray	([B)V
        //   53: aload_0
        //   54: getfield 18	com/google/android/gms/wearable/internal/ad$a$a:ko	Landroid/os/IBinder;
        //   57: bipush 12
        //   59: aload 5
        //   61: aload 6
        //   63: iconst_0
        //   64: invokeinterface 49 5 0
        //   69: pop
        //   70: aload 6
        //   72: invokevirtual 52	android/os/Parcel:readException	()V
        //   75: aload 6
        //   77: invokevirtual 55	android/os/Parcel:recycle	()V
        //   80: aload 5
        //   82: invokevirtual 55	android/os/Parcel:recycle	()V
        //   85: return
        //   86: aconst_null
        //   87: astore_1
        //   88: goto -60 -> 28
        //   91: astore_1
        //   92: aload 6
        //   94: invokevirtual 55	android/os/Parcel:recycle	()V
        //   97: aload 5
        //   99: invokevirtual 55	android/os/Parcel:recycle	()V
        //   102: aload_1
        //   103: athrow
        // Local variable table:
        //   start	length	slot	name	signature
        //   0	104	0	this	a
        //   0	104	1	paramab	ab
        //   0	104	2	paramString1	String
        //   0	104	3	paramString2	String
        //   0	104	4	paramArrayOfByte	byte[]
        //   3	95	5	localParcel1	Parcel
        //   8	85	6	localParcel2	Parcel
        // Exception table:
        //   from	to	target	type
        //   10	17	91	finally
        //   21	28	91	finally
        //   28	75	91	finally
      }
      
      public IBinder asBinder()
      {
        return this.ko;
      }
      
      /* Error */
      public void b(ab paramab)
        throws RemoteException
      {
        // Byte code:
        //   0: invokestatic 28	android/os/Parcel:obtain	()Landroid/os/Parcel;
        //   3: astore_2
        //   4: invokestatic 28	android/os/Parcel:obtain	()Landroid/os/Parcel;
        //   7: astore_3
        //   8: aload_2
        //   9: ldc 30
        //   11: invokevirtual 34	android/os/Parcel:writeInterfaceToken	(Ljava/lang/String;)V
        //   14: aload_1
        //   15: ifnull +42 -> 57
        //   18: aload_1
        //   19: invokeinterface 40 1 0
        //   24: astore_1
        //   25: aload_2
        //   26: aload_1
        //   27: invokevirtual 43	android/os/Parcel:writeStrongBinder	(Landroid/os/IBinder;)V
        //   30: aload_0
        //   31: getfield 18	com/google/android/gms/wearable/internal/ad$a$a:ko	Landroid/os/IBinder;
        //   34: iconst_4
        //   35: aload_2
        //   36: aload_3
        //   37: iconst_0
        //   38: invokeinterface 49 5 0
        //   43: pop
        //   44: aload_3
        //   45: invokevirtual 52	android/os/Parcel:readException	()V
        //   48: aload_3
        //   49: invokevirtual 55	android/os/Parcel:recycle	()V
        //   52: aload_2
        //   53: invokevirtual 55	android/os/Parcel:recycle	()V
        //   56: return
        //   57: aconst_null
        //   58: astore_1
        //   59: goto -34 -> 25
        //   62: astore_1
        //   63: aload_3
        //   64: invokevirtual 55	android/os/Parcel:recycle	()V
        //   67: aload_2
        //   68: invokevirtual 55	android/os/Parcel:recycle	()V
        //   71: aload_1
        //   72: athrow
        // Local variable table:
        //   start	length	slot	name	signature
        //   0	73	0	this	a
        //   0	73	1	paramab	ab
        //   3	65	2	localParcel1	Parcel
        //   7	57	3	localParcel2	Parcel
        // Exception table:
        //   from	to	target	type
        //   8	14	62	finally
        //   18	25	62	finally
        //   25	48	62	finally
      }
      
      /* Error */
      public void b(ab paramab, Uri paramUri)
        throws RemoteException
      {
        // Byte code:
        //   0: invokestatic 28	android/os/Parcel:obtain	()Landroid/os/Parcel;
        //   3: astore_3
        //   4: invokestatic 28	android/os/Parcel:obtain	()Landroid/os/Parcel;
        //   7: astore 4
        //   9: aload_3
        //   10: ldc 30
        //   12: invokevirtual 34	android/os/Parcel:writeInterfaceToken	(Ljava/lang/String;)V
        //   15: aload_1
        //   16: ifnull +61 -> 77
        //   19: aload_1
        //   20: invokeinterface 40 1 0
        //   25: astore_1
        //   26: aload_3
        //   27: aload_1
        //   28: invokevirtual 43	android/os/Parcel:writeStrongBinder	(Landroid/os/IBinder;)V
        //   31: aload_2
        //   32: ifnull +50 -> 82
        //   35: aload_3
        //   36: iconst_1
        //   37: invokevirtual 61	android/os/Parcel:writeInt	(I)V
        //   40: aload_2
        //   41: aload_3
        //   42: iconst_0
        //   43: invokevirtual 67	android/net/Uri:writeToParcel	(Landroid/os/Parcel;I)V
        //   46: aload_0
        //   47: getfield 18	com/google/android/gms/wearable/internal/ad$a$a:ko	Landroid/os/IBinder;
        //   50: bipush 9
        //   52: aload_3
        //   53: aload 4
        //   55: iconst_0
        //   56: invokeinterface 49 5 0
        //   61: pop
        //   62: aload 4
        //   64: invokevirtual 52	android/os/Parcel:readException	()V
        //   67: aload 4
        //   69: invokevirtual 55	android/os/Parcel:recycle	()V
        //   72: aload_3
        //   73: invokevirtual 55	android/os/Parcel:recycle	()V
        //   76: return
        //   77: aconst_null
        //   78: astore_1
        //   79: goto -53 -> 26
        //   82: aload_3
        //   83: iconst_0
        //   84: invokevirtual 61	android/os/Parcel:writeInt	(I)V
        //   87: goto -41 -> 46
        //   90: astore_1
        //   91: aload 4
        //   93: invokevirtual 55	android/os/Parcel:recycle	()V
        //   96: aload_3
        //   97: invokevirtual 55	android/os/Parcel:recycle	()V
        //   100: aload_1
        //   101: athrow
        // Local variable table:
        //   start	length	slot	name	signature
        //   0	102	0	this	a
        //   0	102	1	paramab	ab
        //   0	102	2	paramUri	Uri
        //   3	94	3	localParcel1	Parcel
        //   7	85	4	localParcel2	Parcel
        // Exception table:
        //   from	to	target	type
        //   9	15	90	finally
        //   19	26	90	finally
        //   26	31	90	finally
        //   35	46	90	finally
        //   46	67	90	finally
        //   82	87	90	finally
      }
      
      /* Error */
      public void c(ab paramab)
        throws RemoteException
      {
        // Byte code:
        //   0: invokestatic 28	android/os/Parcel:obtain	()Landroid/os/Parcel;
        //   3: astore_2
        //   4: invokestatic 28	android/os/Parcel:obtain	()Landroid/os/Parcel;
        //   7: astore_3
        //   8: aload_2
        //   9: ldc 30
        //   11: invokevirtual 34	android/os/Parcel:writeInterfaceToken	(Ljava/lang/String;)V
        //   14: aload_1
        //   15: ifnull +42 -> 57
        //   18: aload_1
        //   19: invokeinterface 40 1 0
        //   24: astore_1
        //   25: aload_2
        //   26: aload_1
        //   27: invokevirtual 43	android/os/Parcel:writeStrongBinder	(Landroid/os/IBinder;)V
        //   30: aload_0
        //   31: getfield 18	com/google/android/gms/wearable/internal/ad$a$a:ko	Landroid/os/IBinder;
        //   34: iconst_5
        //   35: aload_2
        //   36: aload_3
        //   37: iconst_0
        //   38: invokeinterface 49 5 0
        //   43: pop
        //   44: aload_3
        //   45: invokevirtual 52	android/os/Parcel:readException	()V
        //   48: aload_3
        //   49: invokevirtual 55	android/os/Parcel:recycle	()V
        //   52: aload_2
        //   53: invokevirtual 55	android/os/Parcel:recycle	()V
        //   56: return
        //   57: aconst_null
        //   58: astore_1
        //   59: goto -34 -> 25
        //   62: astore_1
        //   63: aload_3
        //   64: invokevirtual 55	android/os/Parcel:recycle	()V
        //   67: aload_2
        //   68: invokevirtual 55	android/os/Parcel:recycle	()V
        //   71: aload_1
        //   72: athrow
        // Local variable table:
        //   start	length	slot	name	signature
        //   0	73	0	this	a
        //   0	73	1	paramab	ab
        //   3	65	2	localParcel1	Parcel
        //   7	57	3	localParcel2	Parcel
        // Exception table:
        //   from	to	target	type
        //   8	14	62	finally
        //   18	25	62	finally
        //   25	48	62	finally
      }
      
      /* Error */
      public void c(ab paramab, Uri paramUri)
        throws RemoteException
      {
        // Byte code:
        //   0: invokestatic 28	android/os/Parcel:obtain	()Landroid/os/Parcel;
        //   3: astore_3
        //   4: invokestatic 28	android/os/Parcel:obtain	()Landroid/os/Parcel;
        //   7: astore 4
        //   9: aload_3
        //   10: ldc 30
        //   12: invokevirtual 34	android/os/Parcel:writeInterfaceToken	(Ljava/lang/String;)V
        //   15: aload_1
        //   16: ifnull +61 -> 77
        //   19: aload_1
        //   20: invokeinterface 40 1 0
        //   25: astore_1
        //   26: aload_3
        //   27: aload_1
        //   28: invokevirtual 43	android/os/Parcel:writeStrongBinder	(Landroid/os/IBinder;)V
        //   31: aload_2
        //   32: ifnull +50 -> 82
        //   35: aload_3
        //   36: iconst_1
        //   37: invokevirtual 61	android/os/Parcel:writeInt	(I)V
        //   40: aload_2
        //   41: aload_3
        //   42: iconst_0
        //   43: invokevirtual 67	android/net/Uri:writeToParcel	(Landroid/os/Parcel;I)V
        //   46: aload_0
        //   47: getfield 18	com/google/android/gms/wearable/internal/ad$a$a:ko	Landroid/os/IBinder;
        //   50: bipush 11
        //   52: aload_3
        //   53: aload 4
        //   55: iconst_0
        //   56: invokeinterface 49 5 0
        //   61: pop
        //   62: aload 4
        //   64: invokevirtual 52	android/os/Parcel:readException	()V
        //   67: aload 4
        //   69: invokevirtual 55	android/os/Parcel:recycle	()V
        //   72: aload_3
        //   73: invokevirtual 55	android/os/Parcel:recycle	()V
        //   76: return
        //   77: aconst_null
        //   78: astore_1
        //   79: goto -53 -> 26
        //   82: aload_3
        //   83: iconst_0
        //   84: invokevirtual 61	android/os/Parcel:writeInt	(I)V
        //   87: goto -41 -> 46
        //   90: astore_1
        //   91: aload 4
        //   93: invokevirtual 55	android/os/Parcel:recycle	()V
        //   96: aload_3
        //   97: invokevirtual 55	android/os/Parcel:recycle	()V
        //   100: aload_1
        //   101: athrow
        // Local variable table:
        //   start	length	slot	name	signature
        //   0	102	0	this	a
        //   0	102	1	paramab	ab
        //   0	102	2	paramUri	Uri
        //   3	94	3	localParcel1	Parcel
        //   7	85	4	localParcel2	Parcel
        // Exception table:
        //   from	to	target	type
        //   9	15	90	finally
        //   19	26	90	finally
        //   26	31	90	finally
        //   35	46	90	finally
        //   46	67	90	finally
        //   82	87	90	finally
      }
      
      /* Error */
      public void d(ab paramab)
        throws RemoteException
      {
        // Byte code:
        //   0: invokestatic 28	android/os/Parcel:obtain	()Landroid/os/Parcel;
        //   3: astore_2
        //   4: invokestatic 28	android/os/Parcel:obtain	()Landroid/os/Parcel;
        //   7: astore_3
        //   8: aload_2
        //   9: ldc 30
        //   11: invokevirtual 34	android/os/Parcel:writeInterfaceToken	(Ljava/lang/String;)V
        //   14: aload_1
        //   15: ifnull +43 -> 58
        //   18: aload_1
        //   19: invokeinterface 40 1 0
        //   24: astore_1
        //   25: aload_2
        //   26: aload_1
        //   27: invokevirtual 43	android/os/Parcel:writeStrongBinder	(Landroid/os/IBinder;)V
        //   30: aload_0
        //   31: getfield 18	com/google/android/gms/wearable/internal/ad$a$a:ko	Landroid/os/IBinder;
        //   34: bipush 8
        //   36: aload_2
        //   37: aload_3
        //   38: iconst_0
        //   39: invokeinterface 49 5 0
        //   44: pop
        //   45: aload_3
        //   46: invokevirtual 52	android/os/Parcel:readException	()V
        //   49: aload_3
        //   50: invokevirtual 55	android/os/Parcel:recycle	()V
        //   53: aload_2
        //   54: invokevirtual 55	android/os/Parcel:recycle	()V
        //   57: return
        //   58: aconst_null
        //   59: astore_1
        //   60: goto -35 -> 25
        //   63: astore_1
        //   64: aload_3
        //   65: invokevirtual 55	android/os/Parcel:recycle	()V
        //   68: aload_2
        //   69: invokevirtual 55	android/os/Parcel:recycle	()V
        //   72: aload_1
        //   73: athrow
        // Local variable table:
        //   start	length	slot	name	signature
        //   0	74	0	this	a
        //   0	74	1	paramab	ab
        //   3	66	2	localParcel1	Parcel
        //   7	58	3	localParcel2	Parcel
        // Exception table:
        //   from	to	target	type
        //   8	14	63	finally
        //   18	25	63	finally
        //   25	49	63	finally
      }
      
      /* Error */
      public void e(ab paramab)
        throws RemoteException
      {
        // Byte code:
        //   0: invokestatic 28	android/os/Parcel:obtain	()Landroid/os/Parcel;
        //   3: astore_2
        //   4: invokestatic 28	android/os/Parcel:obtain	()Landroid/os/Parcel;
        //   7: astore_3
        //   8: aload_2
        //   9: ldc 30
        //   11: invokevirtual 34	android/os/Parcel:writeInterfaceToken	(Ljava/lang/String;)V
        //   14: aload_1
        //   15: ifnull +43 -> 58
        //   18: aload_1
        //   19: invokeinterface 40 1 0
        //   24: astore_1
        //   25: aload_2
        //   26: aload_1
        //   27: invokevirtual 43	android/os/Parcel:writeStrongBinder	(Landroid/os/IBinder;)V
        //   30: aload_0
        //   31: getfield 18	com/google/android/gms/wearable/internal/ad$a$a:ko	Landroid/os/IBinder;
        //   34: bipush 14
        //   36: aload_2
        //   37: aload_3
        //   38: iconst_0
        //   39: invokeinterface 49 5 0
        //   44: pop
        //   45: aload_3
        //   46: invokevirtual 52	android/os/Parcel:readException	()V
        //   49: aload_3
        //   50: invokevirtual 55	android/os/Parcel:recycle	()V
        //   53: aload_2
        //   54: invokevirtual 55	android/os/Parcel:recycle	()V
        //   57: return
        //   58: aconst_null
        //   59: astore_1
        //   60: goto -35 -> 25
        //   63: astore_1
        //   64: aload_3
        //   65: invokevirtual 55	android/os/Parcel:recycle	()V
        //   68: aload_2
        //   69: invokevirtual 55	android/os/Parcel:recycle	()V
        //   72: aload_1
        //   73: athrow
        // Local variable table:
        //   start	length	slot	name	signature
        //   0	74	0	this	a
        //   0	74	1	paramab	ab
        //   3	66	2	localParcel1	Parcel
        //   7	58	3	localParcel2	Parcel
        // Exception table:
        //   from	to	target	type
        //   8	14	63	finally
        //   18	25	63	finally
        //   25	49	63	finally
      }
      
      /* Error */
      public void f(ab paramab)
        throws RemoteException
      {
        // Byte code:
        //   0: invokestatic 28	android/os/Parcel:obtain	()Landroid/os/Parcel;
        //   3: astore_2
        //   4: invokestatic 28	android/os/Parcel:obtain	()Landroid/os/Parcel;
        //   7: astore_3
        //   8: aload_2
        //   9: ldc 30
        //   11: invokevirtual 34	android/os/Parcel:writeInterfaceToken	(Ljava/lang/String;)V
        //   14: aload_1
        //   15: ifnull +43 -> 58
        //   18: aload_1
        //   19: invokeinterface 40 1 0
        //   24: astore_1
        //   25: aload_2
        //   26: aload_1
        //   27: invokevirtual 43	android/os/Parcel:writeStrongBinder	(Landroid/os/IBinder;)V
        //   30: aload_0
        //   31: getfield 18	com/google/android/gms/wearable/internal/ad$a$a:ko	Landroid/os/IBinder;
        //   34: bipush 15
        //   36: aload_2
        //   37: aload_3
        //   38: iconst_0
        //   39: invokeinterface 49 5 0
        //   44: pop
        //   45: aload_3
        //   46: invokevirtual 52	android/os/Parcel:readException	()V
        //   49: aload_3
        //   50: invokevirtual 55	android/os/Parcel:recycle	()V
        //   53: aload_2
        //   54: invokevirtual 55	android/os/Parcel:recycle	()V
        //   57: return
        //   58: aconst_null
        //   59: astore_1
        //   60: goto -35 -> 25
        //   63: astore_1
        //   64: aload_3
        //   65: invokevirtual 55	android/os/Parcel:recycle	()V
        //   68: aload_2
        //   69: invokevirtual 55	android/os/Parcel:recycle	()V
        //   72: aload_1
        //   73: athrow
        // Local variable table:
        //   start	length	slot	name	signature
        //   0	74	0	this	a
        //   0	74	1	paramab	ab
        //   3	66	2	localParcel1	Parcel
        //   7	58	3	localParcel2	Parcel
        // Exception table:
        //   from	to	target	type
        //   8	14	63	finally
        //   18	25	63	finally
        //   25	49	63	finally
      }
      
      /* Error */
      public void g(ab paramab)
        throws RemoteException
      {
        // Byte code:
        //   0: invokestatic 28	android/os/Parcel:obtain	()Landroid/os/Parcel;
        //   3: astore_2
        //   4: invokestatic 28	android/os/Parcel:obtain	()Landroid/os/Parcel;
        //   7: astore_3
        //   8: aload_2
        //   9: ldc 30
        //   11: invokevirtual 34	android/os/Parcel:writeInterfaceToken	(Ljava/lang/String;)V
        //   14: aload_1
        //   15: ifnull +43 -> 58
        //   18: aload_1
        //   19: invokeinterface 40 1 0
        //   24: astore_1
        //   25: aload_2
        //   26: aload_1
        //   27: invokevirtual 43	android/os/Parcel:writeStrongBinder	(Landroid/os/IBinder;)V
        //   30: aload_0
        //   31: getfield 18	com/google/android/gms/wearable/internal/ad$a$a:ko	Landroid/os/IBinder;
        //   34: bipush 18
        //   36: aload_2
        //   37: aload_3
        //   38: iconst_0
        //   39: invokeinterface 49 5 0
        //   44: pop
        //   45: aload_3
        //   46: invokevirtual 52	android/os/Parcel:readException	()V
        //   49: aload_3
        //   50: invokevirtual 55	android/os/Parcel:recycle	()V
        //   53: aload_2
        //   54: invokevirtual 55	android/os/Parcel:recycle	()V
        //   57: return
        //   58: aconst_null
        //   59: astore_1
        //   60: goto -35 -> 25
        //   63: astore_1
        //   64: aload_3
        //   65: invokevirtual 55	android/os/Parcel:recycle	()V
        //   68: aload_2
        //   69: invokevirtual 55	android/os/Parcel:recycle	()V
        //   72: aload_1
        //   73: athrow
        // Local variable table:
        //   start	length	slot	name	signature
        //   0	74	0	this	a
        //   0	74	1	paramab	ab
        //   3	66	2	localParcel1	Parcel
        //   7	58	3	localParcel2	Parcel
        // Exception table:
        //   from	to	target	type
        //   8	14	63	finally
        //   18	25	63	finally
        //   25	49	63	finally
      }
      
      /* Error */
      public void h(ab paramab)
        throws RemoteException
      {
        // Byte code:
        //   0: invokestatic 28	android/os/Parcel:obtain	()Landroid/os/Parcel;
        //   3: astore_2
        //   4: invokestatic 28	android/os/Parcel:obtain	()Landroid/os/Parcel;
        //   7: astore_3
        //   8: aload_2
        //   9: ldc 30
        //   11: invokevirtual 34	android/os/Parcel:writeInterfaceToken	(Ljava/lang/String;)V
        //   14: aload_1
        //   15: ifnull +43 -> 58
        //   18: aload_1
        //   19: invokeinterface 40 1 0
        //   24: astore_1
        //   25: aload_2
        //   26: aload_1
        //   27: invokevirtual 43	android/os/Parcel:writeStrongBinder	(Landroid/os/IBinder;)V
        //   30: aload_0
        //   31: getfield 18	com/google/android/gms/wearable/internal/ad$a$a:ko	Landroid/os/IBinder;
        //   34: bipush 19
        //   36: aload_2
        //   37: aload_3
        //   38: iconst_0
        //   39: invokeinterface 49 5 0
        //   44: pop
        //   45: aload_3
        //   46: invokevirtual 52	android/os/Parcel:readException	()V
        //   49: aload_3
        //   50: invokevirtual 55	android/os/Parcel:recycle	()V
        //   53: aload_2
        //   54: invokevirtual 55	android/os/Parcel:recycle	()V
        //   57: return
        //   58: aconst_null
        //   59: astore_1
        //   60: goto -35 -> 25
        //   63: astore_1
        //   64: aload_3
        //   65: invokevirtual 55	android/os/Parcel:recycle	()V
        //   68: aload_2
        //   69: invokevirtual 55	android/os/Parcel:recycle	()V
        //   72: aload_1
        //   73: athrow
        // Local variable table:
        //   start	length	slot	name	signature
        //   0	74	0	this	a
        //   0	74	1	paramab	ab
        //   3	66	2	localParcel1	Parcel
        //   7	58	3	localParcel2	Parcel
        // Exception table:
        //   from	to	target	type
        //   8	14	63	finally
        //   18	25	63	finally
        //   25	49	63	finally
      }
    }
  }
}


/* Location:              /Users/amaurremi/uw/stringoid/static-dynamic-comparison/apps/broken screen/mobi.borken.android.brokenscreen-20-dex2jar.jar!/com/google/android/gms/wearable/internal/ad.class
 * Java compiler version: 6 (50.0)
 * JD-Core Version:       0.7.1
 */