package com.appbrain.e;

import com.appbrain.b.c;
import com.appbrain.b.e;
import com.appbrain.b.g;
import com.appbrain.b.g.a;
import com.appbrain.b.n;
import com.appbrain.b.o;
import com.appbrain.b.q;

public final class h
{
  public static final class a
    extends g
    implements h.b
  {
    public static o a = new i();
    private static final a b;
    private long A;
    private int B;
    private int C;
    private int D;
    private int E;
    private int F;
    private int G;
    private int H;
    private Object I;
    private int J;
    private Object K;
    private c L;
    private c M;
    private int N;
    private int O;
    private long P;
    private boolean Q;
    private Object R;
    private boolean S;
    private byte T = -1;
    private int U = -1;
    private int c;
    private int d;
    private long e;
    private long f;
    private Object g;
    private Object h;
    private Object i;
    private Object j;
    private Object k;
    private Object l;
    private Object m;
    private int n;
    private int o;
    private Object p;
    private Object q;
    private Object r;
    private Object s;
    private Object t;
    private Object u;
    private Object v;
    private int w;
    private Object x;
    private int y;
    private int z;
    
    static
    {
      a locala = new a((byte)0);
      b = locala;
      locala.aM();
    }
    
    private a()
    {
      super();
    }
    
    private a(byte paramByte) {}
    
    /* Error */
    private a(com.appbrain.b.d paramd)
    {
      // Byte code:
      //   0: aload_0
      //   1: invokespecial 86	com/appbrain/b/g:<init>	()V
      //   4: aload_0
      //   5: iconst_m1
      //   6: putfield 83	com/appbrain/e/h$a:T	B
      //   9: aload_0
      //   10: iconst_m1
      //   11: putfield 85	com/appbrain/e/h$a:U	I
      //   14: aload_0
      //   15: invokespecial 79	com/appbrain/e/h$a:aM	()V
      //   18: iconst_0
      //   19: istore_2
      //   20: iload_2
      //   21: ifne +1301 -> 1322
      //   24: aload_1
      //   25: invokevirtual 98	com/appbrain/b/d:a	()I
      //   28: istore_3
      //   29: iload_3
      //   30: lookupswitch	default:+1293->1323, 0:+1296->1326, 8:+359->389, 16:+390->420, 26:+428->458, 34:+449->479, 42:+471->501, 50:+493->523, 58:+515->545, 66:+537->567, 74:+560->590, 80:+583->613, 88:+606->636, 106:+629->659, 114:+652->682, 122:+675->705, 130:+698->728, 162:+721->751, 170:+743->773, 178:+765->795, 184:+787->817, 202:+809->839, 208:+831->861, 216:+853->883, 224:+875->905, 232:+897->927, 240:+919->949, 248:+941->971, 256:+963->993, 264:+985->1015, 272:+1007->1037, 280:+1029->1059, 290:+1051->1081, 296:+1073->1103, 306:+1095->1125, 314:+1116->1146, 322:+1137->1167, 328:+1158->1188, 336:+1180->1210, 344:+1202->1232, 352:+1224->1254, 362:+1246->1276, 368:+1269->1299
      //   376: aload_1
      //   377: iload_3
      //   378: invokevirtual 101	com/appbrain/b/d:b	(I)Z
      //   381: ifne -361 -> 20
      //   384: iconst_1
      //   385: istore_2
      //   386: goto -366 -> 20
      //   389: aload_0
      //   390: aload_0
      //   391: getfield 103	com/appbrain/e/h$a:c	I
      //   394: iconst_1
      //   395: ior
      //   396: putfield 103	com/appbrain/e/h$a:c	I
      //   399: aload_0
      //   400: aload_1
      //   401: invokevirtual 106	com/appbrain/b/d:b	()J
      //   404: putfield 108	com/appbrain/e/h$a:e	J
      //   407: goto -387 -> 20
      //   410: astore_1
      //   411: aload_1
      //   412: aload_0
      //   413: invokevirtual 111	com/appbrain/b/i:a	(Lcom/appbrain/b/m;)Lcom/appbrain/b/i;
      //   416: athrow
      //   417: astore_1
      //   418: aload_1
      //   419: athrow
      //   420: aload_0
      //   421: aload_0
      //   422: getfield 103	com/appbrain/e/h$a:c	I
      //   425: iconst_2
      //   426: ior
      //   427: putfield 103	com/appbrain/e/h$a:c	I
      //   430: aload_0
      //   431: aload_1
      //   432: invokevirtual 106	com/appbrain/b/d:b	()J
      //   435: putfield 113	com/appbrain/e/h$a:f	J
      //   438: goto -418 -> 20
      //   441: astore_1
      //   442: new 91	com/appbrain/b/i
      //   445: dup
      //   446: aload_1
      //   447: invokevirtual 117	java/io/IOException:getMessage	()Ljava/lang/String;
      //   450: invokespecial 120	com/appbrain/b/i:<init>	(Ljava/lang/String;)V
      //   453: aload_0
      //   454: invokevirtual 111	com/appbrain/b/i:a	(Lcom/appbrain/b/m;)Lcom/appbrain/b/i;
      //   457: athrow
      //   458: aload_0
      //   459: aload_0
      //   460: getfield 103	com/appbrain/e/h$a:c	I
      //   463: iconst_4
      //   464: ior
      //   465: putfield 103	com/appbrain/e/h$a:c	I
      //   468: aload_0
      //   469: aload_1
      //   470: invokevirtual 123	com/appbrain/b/d:e	()Lcom/appbrain/b/c;
      //   473: putfield 125	com/appbrain/e/h$a:g	Ljava/lang/Object;
      //   476: goto -456 -> 20
      //   479: aload_0
      //   480: aload_0
      //   481: getfield 103	com/appbrain/e/h$a:c	I
      //   484: bipush 8
      //   486: ior
      //   487: putfield 103	com/appbrain/e/h$a:c	I
      //   490: aload_0
      //   491: aload_1
      //   492: invokevirtual 123	com/appbrain/b/d:e	()Lcom/appbrain/b/c;
      //   495: putfield 127	com/appbrain/e/h$a:h	Ljava/lang/Object;
      //   498: goto -478 -> 20
      //   501: aload_0
      //   502: aload_0
      //   503: getfield 103	com/appbrain/e/h$a:c	I
      //   506: bipush 16
      //   508: ior
      //   509: putfield 103	com/appbrain/e/h$a:c	I
      //   512: aload_0
      //   513: aload_1
      //   514: invokevirtual 123	com/appbrain/b/d:e	()Lcom/appbrain/b/c;
      //   517: putfield 129	com/appbrain/e/h$a:i	Ljava/lang/Object;
      //   520: goto -500 -> 20
      //   523: aload_0
      //   524: aload_0
      //   525: getfield 103	com/appbrain/e/h$a:c	I
      //   528: bipush 32
      //   530: ior
      //   531: putfield 103	com/appbrain/e/h$a:c	I
      //   534: aload_0
      //   535: aload_1
      //   536: invokevirtual 123	com/appbrain/b/d:e	()Lcom/appbrain/b/c;
      //   539: putfield 131	com/appbrain/e/h$a:j	Ljava/lang/Object;
      //   542: goto -522 -> 20
      //   545: aload_0
      //   546: aload_0
      //   547: getfield 103	com/appbrain/e/h$a:c	I
      //   550: bipush 64
      //   552: ior
      //   553: putfield 103	com/appbrain/e/h$a:c	I
      //   556: aload_0
      //   557: aload_1
      //   558: invokevirtual 123	com/appbrain/b/d:e	()Lcom/appbrain/b/c;
      //   561: putfield 133	com/appbrain/e/h$a:k	Ljava/lang/Object;
      //   564: goto -544 -> 20
      //   567: aload_0
      //   568: aload_0
      //   569: getfield 103	com/appbrain/e/h$a:c	I
      //   572: sipush 128
      //   575: ior
      //   576: putfield 103	com/appbrain/e/h$a:c	I
      //   579: aload_0
      //   580: aload_1
      //   581: invokevirtual 123	com/appbrain/b/d:e	()Lcom/appbrain/b/c;
      //   584: putfield 135	com/appbrain/e/h$a:l	Ljava/lang/Object;
      //   587: goto -567 -> 20
      //   590: aload_0
      //   591: aload_0
      //   592: getfield 103	com/appbrain/e/h$a:c	I
      //   595: sipush 256
      //   598: ior
      //   599: putfield 103	com/appbrain/e/h$a:c	I
      //   602: aload_0
      //   603: aload_1
      //   604: invokevirtual 123	com/appbrain/b/d:e	()Lcom/appbrain/b/c;
      //   607: putfield 137	com/appbrain/e/h$a:m	Ljava/lang/Object;
      //   610: goto -590 -> 20
      //   613: aload_0
      //   614: aload_0
      //   615: getfield 103	com/appbrain/e/h$a:c	I
      //   618: sipush 512
      //   621: ior
      //   622: putfield 103	com/appbrain/e/h$a:c	I
      //   625: aload_0
      //   626: aload_1
      //   627: invokevirtual 139	com/appbrain/b/d:c	()I
      //   630: putfield 141	com/appbrain/e/h$a:n	I
      //   633: goto -613 -> 20
      //   636: aload_0
      //   637: aload_0
      //   638: getfield 103	com/appbrain/e/h$a:c	I
      //   641: sipush 1024
      //   644: ior
      //   645: putfield 103	com/appbrain/e/h$a:c	I
      //   648: aload_0
      //   649: aload_1
      //   650: invokevirtual 139	com/appbrain/b/d:c	()I
      //   653: putfield 143	com/appbrain/e/h$a:o	I
      //   656: goto -636 -> 20
      //   659: aload_0
      //   660: aload_0
      //   661: getfield 103	com/appbrain/e/h$a:c	I
      //   664: sipush 2048
      //   667: ior
      //   668: putfield 103	com/appbrain/e/h$a:c	I
      //   671: aload_0
      //   672: aload_1
      //   673: invokevirtual 123	com/appbrain/b/d:e	()Lcom/appbrain/b/c;
      //   676: putfield 145	com/appbrain/e/h$a:p	Ljava/lang/Object;
      //   679: goto -659 -> 20
      //   682: aload_0
      //   683: aload_0
      //   684: getfield 103	com/appbrain/e/h$a:c	I
      //   687: sipush 4096
      //   690: ior
      //   691: putfield 103	com/appbrain/e/h$a:c	I
      //   694: aload_0
      //   695: aload_1
      //   696: invokevirtual 123	com/appbrain/b/d:e	()Lcom/appbrain/b/c;
      //   699: putfield 147	com/appbrain/e/h$a:q	Ljava/lang/Object;
      //   702: goto -682 -> 20
      //   705: aload_0
      //   706: aload_0
      //   707: getfield 103	com/appbrain/e/h$a:c	I
      //   710: sipush 8192
      //   713: ior
      //   714: putfield 103	com/appbrain/e/h$a:c	I
      //   717: aload_0
      //   718: aload_1
      //   719: invokevirtual 123	com/appbrain/b/d:e	()Lcom/appbrain/b/c;
      //   722: putfield 149	com/appbrain/e/h$a:r	Ljava/lang/Object;
      //   725: goto -705 -> 20
      //   728: aload_0
      //   729: aload_0
      //   730: getfield 103	com/appbrain/e/h$a:c	I
      //   733: sipush 16384
      //   736: ior
      //   737: putfield 103	com/appbrain/e/h$a:c	I
      //   740: aload_0
      //   741: aload_1
      //   742: invokevirtual 123	com/appbrain/b/d:e	()Lcom/appbrain/b/c;
      //   745: putfield 151	com/appbrain/e/h$a:s	Ljava/lang/Object;
      //   748: goto -728 -> 20
      //   751: aload_0
      //   752: aload_0
      //   753: getfield 103	com/appbrain/e/h$a:c	I
      //   756: ldc -104
      //   758: ior
      //   759: putfield 103	com/appbrain/e/h$a:c	I
      //   762: aload_0
      //   763: aload_1
      //   764: invokevirtual 123	com/appbrain/b/d:e	()Lcom/appbrain/b/c;
      //   767: putfield 154	com/appbrain/e/h$a:t	Ljava/lang/Object;
      //   770: goto -750 -> 20
      //   773: aload_0
      //   774: aload_0
      //   775: getfield 103	com/appbrain/e/h$a:c	I
      //   778: ldc -101
      //   780: ior
      //   781: putfield 103	com/appbrain/e/h$a:c	I
      //   784: aload_0
      //   785: aload_1
      //   786: invokevirtual 123	com/appbrain/b/d:e	()Lcom/appbrain/b/c;
      //   789: putfield 157	com/appbrain/e/h$a:u	Ljava/lang/Object;
      //   792: goto -772 -> 20
      //   795: aload_0
      //   796: aload_0
      //   797: getfield 103	com/appbrain/e/h$a:c	I
      //   800: ldc -98
      //   802: ior
      //   803: putfield 103	com/appbrain/e/h$a:c	I
      //   806: aload_0
      //   807: aload_1
      //   808: invokevirtual 123	com/appbrain/b/d:e	()Lcom/appbrain/b/c;
      //   811: putfield 160	com/appbrain/e/h$a:v	Ljava/lang/Object;
      //   814: goto -794 -> 20
      //   817: aload_0
      //   818: aload_0
      //   819: getfield 103	com/appbrain/e/h$a:c	I
      //   822: ldc -95
      //   824: ior
      //   825: putfield 103	com/appbrain/e/h$a:c	I
      //   828: aload_0
      //   829: aload_1
      //   830: invokevirtual 139	com/appbrain/b/d:c	()I
      //   833: putfield 163	com/appbrain/e/h$a:w	I
      //   836: goto -816 -> 20
      //   839: aload_0
      //   840: aload_0
      //   841: getfield 103	com/appbrain/e/h$a:c	I
      //   844: ldc -92
      //   846: ior
      //   847: putfield 103	com/appbrain/e/h$a:c	I
      //   850: aload_0
      //   851: aload_1
      //   852: invokevirtual 123	com/appbrain/b/d:e	()Lcom/appbrain/b/c;
      //   855: putfield 166	com/appbrain/e/h$a:x	Ljava/lang/Object;
      //   858: goto -838 -> 20
      //   861: aload_0
      //   862: aload_0
      //   863: getfield 103	com/appbrain/e/h$a:c	I
      //   866: ldc -89
      //   868: ior
      //   869: putfield 103	com/appbrain/e/h$a:c	I
      //   872: aload_0
      //   873: aload_1
      //   874: invokevirtual 139	com/appbrain/b/d:c	()I
      //   877: putfield 169	com/appbrain/e/h$a:y	I
      //   880: goto -860 -> 20
      //   883: aload_0
      //   884: aload_0
      //   885: getfield 103	com/appbrain/e/h$a:c	I
      //   888: ldc -86
      //   890: ior
      //   891: putfield 103	com/appbrain/e/h$a:c	I
      //   894: aload_0
      //   895: aload_1
      //   896: invokevirtual 139	com/appbrain/b/d:c	()I
      //   899: putfield 172	com/appbrain/e/h$a:z	I
      //   902: goto -882 -> 20
      //   905: aload_0
      //   906: aload_0
      //   907: getfield 103	com/appbrain/e/h$a:c	I
      //   910: ldc -83
      //   912: ior
      //   913: putfield 103	com/appbrain/e/h$a:c	I
      //   916: aload_0
      //   917: aload_1
      //   918: invokevirtual 106	com/appbrain/b/d:b	()J
      //   921: putfield 175	com/appbrain/e/h$a:A	J
      //   924: goto -904 -> 20
      //   927: aload_0
      //   928: aload_0
      //   929: getfield 103	com/appbrain/e/h$a:c	I
      //   932: ldc -80
      //   934: ior
      //   935: putfield 103	com/appbrain/e/h$a:c	I
      //   938: aload_0
      //   939: aload_1
      //   940: invokevirtual 139	com/appbrain/b/d:c	()I
      //   943: putfield 178	com/appbrain/e/h$a:B	I
      //   946: goto -926 -> 20
      //   949: aload_0
      //   950: aload_0
      //   951: getfield 103	com/appbrain/e/h$a:c	I
      //   954: ldc -77
      //   956: ior
      //   957: putfield 103	com/appbrain/e/h$a:c	I
      //   960: aload_0
      //   961: aload_1
      //   962: invokevirtual 139	com/appbrain/b/d:c	()I
      //   965: putfield 181	com/appbrain/e/h$a:C	I
      //   968: goto -948 -> 20
      //   971: aload_0
      //   972: aload_0
      //   973: getfield 103	com/appbrain/e/h$a:c	I
      //   976: ldc -74
      //   978: ior
      //   979: putfield 103	com/appbrain/e/h$a:c	I
      //   982: aload_0
      //   983: aload_1
      //   984: invokevirtual 139	com/appbrain/b/d:c	()I
      //   987: putfield 184	com/appbrain/e/h$a:D	I
      //   990: goto -970 -> 20
      //   993: aload_0
      //   994: aload_0
      //   995: getfield 103	com/appbrain/e/h$a:c	I
      //   998: ldc -71
      //   1000: ior
      //   1001: putfield 103	com/appbrain/e/h$a:c	I
      //   1004: aload_0
      //   1005: aload_1
      //   1006: invokevirtual 139	com/appbrain/b/d:c	()I
      //   1009: putfield 187	com/appbrain/e/h$a:E	I
      //   1012: goto -992 -> 20
      //   1015: aload_0
      //   1016: aload_0
      //   1017: getfield 103	com/appbrain/e/h$a:c	I
      //   1020: ldc -68
      //   1022: ior
      //   1023: putfield 103	com/appbrain/e/h$a:c	I
      //   1026: aload_0
      //   1027: aload_1
      //   1028: invokevirtual 139	com/appbrain/b/d:c	()I
      //   1031: putfield 190	com/appbrain/e/h$a:F	I
      //   1034: goto -1014 -> 20
      //   1037: aload_0
      //   1038: aload_0
      //   1039: getfield 103	com/appbrain/e/h$a:c	I
      //   1042: ldc -65
      //   1044: ior
      //   1045: putfield 103	com/appbrain/e/h$a:c	I
      //   1048: aload_0
      //   1049: aload_1
      //   1050: invokevirtual 139	com/appbrain/b/d:c	()I
      //   1053: putfield 193	com/appbrain/e/h$a:G	I
      //   1056: goto -1036 -> 20
      //   1059: aload_0
      //   1060: aload_0
      //   1061: getfield 103	com/appbrain/e/h$a:c	I
      //   1064: ldc -62
      //   1066: ior
      //   1067: putfield 103	com/appbrain/e/h$a:c	I
      //   1070: aload_0
      //   1071: aload_1
      //   1072: invokevirtual 139	com/appbrain/b/d:c	()I
      //   1075: putfield 196	com/appbrain/e/h$a:H	I
      //   1078: goto -1058 -> 20
      //   1081: aload_0
      //   1082: aload_0
      //   1083: getfield 103	com/appbrain/e/h$a:c	I
      //   1086: ldc -59
      //   1088: ior
      //   1089: putfield 103	com/appbrain/e/h$a:c	I
      //   1092: aload_0
      //   1093: aload_1
      //   1094: invokevirtual 123	com/appbrain/b/d:e	()Lcom/appbrain/b/c;
      //   1097: putfield 199	com/appbrain/e/h$a:I	Ljava/lang/Object;
      //   1100: goto -1080 -> 20
      //   1103: aload_0
      //   1104: aload_0
      //   1105: getfield 103	com/appbrain/e/h$a:c	I
      //   1108: ldc -56
      //   1110: ior
      //   1111: putfield 103	com/appbrain/e/h$a:c	I
      //   1114: aload_0
      //   1115: aload_1
      //   1116: invokevirtual 139	com/appbrain/b/d:c	()I
      //   1119: putfield 202	com/appbrain/e/h$a:J	I
      //   1122: goto -1102 -> 20
      //   1125: aload_0
      //   1126: aload_0
      //   1127: getfield 204	com/appbrain/e/h$a:d	I
      //   1130: iconst_1
      //   1131: ior
      //   1132: putfield 204	com/appbrain/e/h$a:d	I
      //   1135: aload_0
      //   1136: aload_1
      //   1137: invokevirtual 123	com/appbrain/b/d:e	()Lcom/appbrain/b/c;
      //   1140: putfield 206	com/appbrain/e/h$a:K	Ljava/lang/Object;
      //   1143: goto -1123 -> 20
      //   1146: aload_0
      //   1147: aload_0
      //   1148: getfield 204	com/appbrain/e/h$a:d	I
      //   1151: iconst_2
      //   1152: ior
      //   1153: putfield 204	com/appbrain/e/h$a:d	I
      //   1156: aload_0
      //   1157: aload_1
      //   1158: invokevirtual 123	com/appbrain/b/d:e	()Lcom/appbrain/b/c;
      //   1161: putfield 208	com/appbrain/e/h$a:L	Lcom/appbrain/b/c;
      //   1164: goto -1144 -> 20
      //   1167: aload_0
      //   1168: aload_0
      //   1169: getfield 204	com/appbrain/e/h$a:d	I
      //   1172: iconst_4
      //   1173: ior
      //   1174: putfield 204	com/appbrain/e/h$a:d	I
      //   1177: aload_0
      //   1178: aload_1
      //   1179: invokevirtual 123	com/appbrain/b/d:e	()Lcom/appbrain/b/c;
      //   1182: putfield 210	com/appbrain/e/h$a:M	Lcom/appbrain/b/c;
      //   1185: goto -1165 -> 20
      //   1188: aload_0
      //   1189: aload_0
      //   1190: getfield 204	com/appbrain/e/h$a:d	I
      //   1193: bipush 8
      //   1195: ior
      //   1196: putfield 204	com/appbrain/e/h$a:d	I
      //   1199: aload_0
      //   1200: aload_1
      //   1201: invokevirtual 139	com/appbrain/b/d:c	()I
      //   1204: putfield 212	com/appbrain/e/h$a:N	I
      //   1207: goto -1187 -> 20
      //   1210: aload_0
      //   1211: aload_0
      //   1212: getfield 204	com/appbrain/e/h$a:d	I
      //   1215: bipush 16
      //   1217: ior
      //   1218: putfield 204	com/appbrain/e/h$a:d	I
      //   1221: aload_0
      //   1222: aload_1
      //   1223: invokevirtual 139	com/appbrain/b/d:c	()I
      //   1226: putfield 214	com/appbrain/e/h$a:O	I
      //   1229: goto -1209 -> 20
      //   1232: aload_0
      //   1233: aload_0
      //   1234: getfield 204	com/appbrain/e/h$a:d	I
      //   1237: bipush 32
      //   1239: ior
      //   1240: putfield 204	com/appbrain/e/h$a:d	I
      //   1243: aload_0
      //   1244: aload_1
      //   1245: invokevirtual 106	com/appbrain/b/d:b	()J
      //   1248: putfield 216	com/appbrain/e/h$a:P	J
      //   1251: goto -1231 -> 20
      //   1254: aload_0
      //   1255: aload_0
      //   1256: getfield 204	com/appbrain/e/h$a:d	I
      //   1259: bipush 64
      //   1261: ior
      //   1262: putfield 204	com/appbrain/e/h$a:d	I
      //   1265: aload_0
      //   1266: aload_1
      //   1267: invokevirtual 219	com/appbrain/b/d:d	()Z
      //   1270: putfield 221	com/appbrain/e/h$a:Q	Z
      //   1273: goto -1253 -> 20
      //   1276: aload_0
      //   1277: aload_0
      //   1278: getfield 204	com/appbrain/e/h$a:d	I
      //   1281: sipush 128
      //   1284: ior
      //   1285: putfield 204	com/appbrain/e/h$a:d	I
      //   1288: aload_0
      //   1289: aload_1
      //   1290: invokevirtual 123	com/appbrain/b/d:e	()Lcom/appbrain/b/c;
      //   1293: putfield 223	com/appbrain/e/h$a:R	Ljava/lang/Object;
      //   1296: goto -1276 -> 20
      //   1299: aload_0
      //   1300: aload_0
      //   1301: getfield 204	com/appbrain/e/h$a:d	I
      //   1304: sipush 256
      //   1307: ior
      //   1308: putfield 204	com/appbrain/e/h$a:d	I
      //   1311: aload_0
      //   1312: aload_1
      //   1313: invokevirtual 219	com/appbrain/b/d:d	()Z
      //   1316: putfield 225	com/appbrain/e/h$a:S	Z
      //   1319: goto -1299 -> 20
      //   1322: return
      //   1323: goto -947 -> 376
      //   1326: iconst_1
      //   1327: istore_2
      //   1328: goto -1308 -> 20
      // Local variable table:
      //   start	length	slot	name	signature
      //   0	1331	0	this	a
      //   0	1331	1	paramd	com.appbrain.b.d
      //   19	1309	2	i1	int
      //   28	350	3	i2	int
      // Exception table:
      //   from	to	target	type
      //   24	29	410	com/appbrain/b/i
      //   376	384	410	com/appbrain/b/i
      //   389	407	410	com/appbrain/b/i
      //   420	438	410	com/appbrain/b/i
      //   458	476	410	com/appbrain/b/i
      //   479	498	410	com/appbrain/b/i
      //   501	520	410	com/appbrain/b/i
      //   523	542	410	com/appbrain/b/i
      //   545	564	410	com/appbrain/b/i
      //   567	587	410	com/appbrain/b/i
      //   590	610	410	com/appbrain/b/i
      //   613	633	410	com/appbrain/b/i
      //   636	656	410	com/appbrain/b/i
      //   659	679	410	com/appbrain/b/i
      //   682	702	410	com/appbrain/b/i
      //   705	725	410	com/appbrain/b/i
      //   728	748	410	com/appbrain/b/i
      //   751	770	410	com/appbrain/b/i
      //   773	792	410	com/appbrain/b/i
      //   795	814	410	com/appbrain/b/i
      //   817	836	410	com/appbrain/b/i
      //   839	858	410	com/appbrain/b/i
      //   861	880	410	com/appbrain/b/i
      //   883	902	410	com/appbrain/b/i
      //   905	924	410	com/appbrain/b/i
      //   927	946	410	com/appbrain/b/i
      //   949	968	410	com/appbrain/b/i
      //   971	990	410	com/appbrain/b/i
      //   993	1012	410	com/appbrain/b/i
      //   1015	1034	410	com/appbrain/b/i
      //   1037	1056	410	com/appbrain/b/i
      //   1059	1078	410	com/appbrain/b/i
      //   1081	1100	410	com/appbrain/b/i
      //   1103	1122	410	com/appbrain/b/i
      //   1125	1143	410	com/appbrain/b/i
      //   1146	1164	410	com/appbrain/b/i
      //   1167	1185	410	com/appbrain/b/i
      //   1188	1207	410	com/appbrain/b/i
      //   1210	1229	410	com/appbrain/b/i
      //   1232	1251	410	com/appbrain/b/i
      //   1254	1273	410	com/appbrain/b/i
      //   1276	1296	410	com/appbrain/b/i
      //   1299	1319	410	com/appbrain/b/i
      //   24	29	417	finally
      //   376	384	417	finally
      //   389	407	417	finally
      //   411	417	417	finally
      //   420	438	417	finally
      //   442	458	417	finally
      //   458	476	417	finally
      //   479	498	417	finally
      //   501	520	417	finally
      //   523	542	417	finally
      //   545	564	417	finally
      //   567	587	417	finally
      //   590	610	417	finally
      //   613	633	417	finally
      //   636	656	417	finally
      //   659	679	417	finally
      //   682	702	417	finally
      //   705	725	417	finally
      //   728	748	417	finally
      //   751	770	417	finally
      //   773	792	417	finally
      //   795	814	417	finally
      //   817	836	417	finally
      //   839	858	417	finally
      //   861	880	417	finally
      //   883	902	417	finally
      //   905	924	417	finally
      //   927	946	417	finally
      //   949	968	417	finally
      //   971	990	417	finally
      //   993	1012	417	finally
      //   1015	1034	417	finally
      //   1037	1056	417	finally
      //   1059	1078	417	finally
      //   1081	1100	417	finally
      //   1103	1122	417	finally
      //   1125	1143	417	finally
      //   1146	1164	417	finally
      //   1167	1185	417	finally
      //   1188	1207	417	finally
      //   1210	1229	417	finally
      //   1232	1251	417	finally
      //   1254	1273	417	finally
      //   1276	1296	417	finally
      //   1299	1319	417	finally
      //   24	29	441	java/io/IOException
      //   376	384	441	java/io/IOException
      //   389	407	441	java/io/IOException
      //   420	438	441	java/io/IOException
      //   458	476	441	java/io/IOException
      //   479	498	441	java/io/IOException
      //   501	520	441	java/io/IOException
      //   523	542	441	java/io/IOException
      //   545	564	441	java/io/IOException
      //   567	587	441	java/io/IOException
      //   590	610	441	java/io/IOException
      //   613	633	441	java/io/IOException
      //   636	656	441	java/io/IOException
      //   659	679	441	java/io/IOException
      //   682	702	441	java/io/IOException
      //   705	725	441	java/io/IOException
      //   728	748	441	java/io/IOException
      //   751	770	441	java/io/IOException
      //   773	792	441	java/io/IOException
      //   795	814	441	java/io/IOException
      //   817	836	441	java/io/IOException
      //   839	858	441	java/io/IOException
      //   861	880	441	java/io/IOException
      //   883	902	441	java/io/IOException
      //   905	924	441	java/io/IOException
      //   927	946	441	java/io/IOException
      //   949	968	441	java/io/IOException
      //   971	990	441	java/io/IOException
      //   993	1012	441	java/io/IOException
      //   1015	1034	441	java/io/IOException
      //   1037	1056	441	java/io/IOException
      //   1059	1078	441	java/io/IOException
      //   1081	1100	441	java/io/IOException
      //   1103	1122	441	java/io/IOException
      //   1125	1143	441	java/io/IOException
      //   1146	1164	441	java/io/IOException
      //   1167	1185	441	java/io/IOException
      //   1188	1207	441	java/io/IOException
      //   1210	1229	441	java/io/IOException
      //   1232	1251	441	java/io/IOException
      //   1254	1273	441	java/io/IOException
      //   1276	1296	441	java/io/IOException
      //   1299	1319	441	java/io/IOException
    }
    
    public static a a(a parama)
    {
      return a.g().a(parama);
    }
    
    private c aA()
    {
      Object localObject = this.m;
      if ((localObject instanceof String))
      {
        localObject = c.a((String)localObject);
        this.m = localObject;
        return (c)localObject;
      }
      return (c)localObject;
    }
    
    private c aB()
    {
      Object localObject = this.p;
      if ((localObject instanceof String))
      {
        localObject = c.a((String)localObject);
        this.p = localObject;
        return (c)localObject;
      }
      return (c)localObject;
    }
    
    private c aC()
    {
      Object localObject = this.q;
      if ((localObject instanceof String))
      {
        localObject = c.a((String)localObject);
        this.q = localObject;
        return (c)localObject;
      }
      return (c)localObject;
    }
    
    private c aD()
    {
      Object localObject = this.r;
      if ((localObject instanceof String))
      {
        localObject = c.a((String)localObject);
        this.r = localObject;
        return (c)localObject;
      }
      return (c)localObject;
    }
    
    private c aE()
    {
      Object localObject = this.s;
      if ((localObject instanceof String))
      {
        localObject = c.a((String)localObject);
        this.s = localObject;
        return (c)localObject;
      }
      return (c)localObject;
    }
    
    private c aF()
    {
      Object localObject = this.t;
      if ((localObject instanceof String))
      {
        localObject = c.a((String)localObject);
        this.t = localObject;
        return (c)localObject;
      }
      return (c)localObject;
    }
    
    private c aG()
    {
      Object localObject = this.u;
      if ((localObject instanceof String))
      {
        localObject = c.a((String)localObject);
        this.u = localObject;
        return (c)localObject;
      }
      return (c)localObject;
    }
    
    private c aH()
    {
      Object localObject = this.v;
      if ((localObject instanceof String))
      {
        localObject = c.a((String)localObject);
        this.v = localObject;
        return (c)localObject;
      }
      return (c)localObject;
    }
    
    private c aI()
    {
      Object localObject = this.x;
      if ((localObject instanceof String))
      {
        localObject = c.a((String)localObject);
        this.x = localObject;
        return (c)localObject;
      }
      return (c)localObject;
    }
    
    private c aJ()
    {
      Object localObject = this.I;
      if ((localObject instanceof String))
      {
        localObject = c.a((String)localObject);
        this.I = localObject;
        return (c)localObject;
      }
      return (c)localObject;
    }
    
    private c aK()
    {
      Object localObject = this.K;
      if ((localObject instanceof String))
      {
        localObject = c.a((String)localObject);
        this.K = localObject;
        return (c)localObject;
      }
      return (c)localObject;
    }
    
    private c aL()
    {
      Object localObject = this.R;
      if ((localObject instanceof String))
      {
        localObject = c.a((String)localObject);
        this.R = localObject;
        return (c)localObject;
      }
      return (c)localObject;
    }
    
    private void aM()
    {
      this.e = 0L;
      this.f = 0L;
      this.g = "";
      this.h = "";
      this.i = "";
      this.j = "";
      this.k = "";
      this.l = "";
      this.m = "";
      this.n = 0;
      this.o = 0;
      this.p = "";
      this.q = "";
      this.r = "";
      this.s = "";
      this.t = "";
      this.u = "";
      this.v = "";
      this.w = 0;
      this.x = "";
      this.y = 0;
      this.z = 0;
      this.A = 0L;
      this.B = 0;
      this.C = 0;
      this.D = 0;
      this.E = 0;
      this.F = 0;
      this.G = 0;
      this.H = 0;
      this.I = "";
      this.J = 0;
      this.K = "";
      this.L = c.a;
      this.M = c.a;
      this.N = 0;
      this.O = 0;
      this.P = 0L;
      this.Q = false;
      this.R = "";
      this.S = false;
    }
    
    public static a as()
    {
      return a.g();
    }
    
    private c au()
    {
      Object localObject = this.g;
      if ((localObject instanceof String))
      {
        localObject = c.a((String)localObject);
        this.g = localObject;
        return (c)localObject;
      }
      return (c)localObject;
    }
    
    private c av()
    {
      Object localObject = this.h;
      if ((localObject instanceof String))
      {
        localObject = c.a((String)localObject);
        this.h = localObject;
        return (c)localObject;
      }
      return (c)localObject;
    }
    
    private c aw()
    {
      Object localObject = this.i;
      if ((localObject instanceof String))
      {
        localObject = c.a((String)localObject);
        this.i = localObject;
        return (c)localObject;
      }
      return (c)localObject;
    }
    
    private c ax()
    {
      Object localObject = this.j;
      if ((localObject instanceof String))
      {
        localObject = c.a((String)localObject);
        this.j = localObject;
        return (c)localObject;
      }
      return (c)localObject;
    }
    
    private c ay()
    {
      Object localObject = this.k;
      if ((localObject instanceof String))
      {
        localObject = c.a((String)localObject);
        this.k = localObject;
        return (c)localObject;
      }
      return (c)localObject;
    }
    
    private c az()
    {
      Object localObject = this.l;
      if ((localObject instanceof String))
      {
        localObject = c.a((String)localObject);
        this.l = localObject;
        return (c)localObject;
      }
      return (c)localObject;
    }
    
    public static a f()
    {
      return b;
    }
    
    public final boolean A()
    {
      return (this.c & 0x10000) == 65536;
    }
    
    public final boolean B()
    {
      return (this.c & 0x20000) == 131072;
    }
    
    public final boolean C()
    {
      return (this.c & 0x40000) == 262144;
    }
    
    public final int D()
    {
      return this.w;
    }
    
    public final boolean E()
    {
      return (this.c & 0x80000) == 524288;
    }
    
    public final boolean F()
    {
      return (this.c & 0x100000) == 1048576;
    }
    
    public final int G()
    {
      return this.y;
    }
    
    public final boolean H()
    {
      return (this.c & 0x200000) == 2097152;
    }
    
    public final int I()
    {
      return this.z;
    }
    
    public final boolean J()
    {
      return (this.c & 0x400000) == 4194304;
    }
    
    public final long K()
    {
      return this.A;
    }
    
    public final boolean L()
    {
      return (this.c & 0x800000) == 8388608;
    }
    
    public final int M()
    {
      return this.B;
    }
    
    public final boolean N()
    {
      return (this.c & 0x1000000) == 16777216;
    }
    
    public final int O()
    {
      return this.C;
    }
    
    public final boolean P()
    {
      return (this.c & 0x2000000) == 33554432;
    }
    
    public final int Q()
    {
      return this.D;
    }
    
    public final boolean R()
    {
      return (this.c & 0x4000000) == 67108864;
    }
    
    public final int S()
    {
      return this.E;
    }
    
    public final boolean T()
    {
      return (this.c & 0x8000000) == 134217728;
    }
    
    public final int U()
    {
      return this.F;
    }
    
    public final boolean V()
    {
      return (this.c & 0x10000000) == 268435456;
    }
    
    public final int W()
    {
      return this.G;
    }
    
    public final boolean X()
    {
      return (this.c & 0x20000000) == 536870912;
    }
    
    public final int Y()
    {
      return this.H;
    }
    
    public final boolean Z()
    {
      return (this.c & 0x40000000) == 1073741824;
    }
    
    public final void a(e parame)
    {
      c();
      if ((this.c & 0x1) == 1) {
        parame.a(1, this.e);
      }
      if ((this.c & 0x2) == 2) {
        parame.a(2, this.f);
      }
      if ((this.c & 0x4) == 4) {
        parame.a(3, au());
      }
      if ((this.c & 0x8) == 8) {
        parame.a(4, av());
      }
      if ((this.c & 0x10) == 16) {
        parame.a(5, aw());
      }
      if ((this.c & 0x20) == 32) {
        parame.a(6, ax());
      }
      if ((this.c & 0x40) == 64) {
        parame.a(7, ay());
      }
      if ((this.c & 0x80) == 128) {
        parame.a(8, az());
      }
      if ((this.c & 0x100) == 256) {
        parame.a(9, aA());
      }
      if ((this.c & 0x200) == 512) {
        parame.a(10, this.n);
      }
      if ((this.c & 0x400) == 1024) {
        parame.a(11, this.o);
      }
      if ((this.c & 0x800) == 2048) {
        parame.a(13, aB());
      }
      if ((this.c & 0x1000) == 4096) {
        parame.a(14, aC());
      }
      if ((this.c & 0x2000) == 8192) {
        parame.a(15, aD());
      }
      if ((this.c & 0x4000) == 16384) {
        parame.a(16, aE());
      }
      if ((this.c & 0x8000) == 32768) {
        parame.a(20, aF());
      }
      if ((this.c & 0x10000) == 65536) {
        parame.a(21, aG());
      }
      if ((this.c & 0x20000) == 131072) {
        parame.a(22, aH());
      }
      if ((this.c & 0x40000) == 262144) {
        parame.a(23, this.w);
      }
      if ((this.c & 0x80000) == 524288) {
        parame.a(25, aI());
      }
      if ((this.c & 0x100000) == 1048576) {
        parame.a(26, this.y);
      }
      if ((this.c & 0x200000) == 2097152) {
        parame.a(27, this.z);
      }
      if ((this.c & 0x400000) == 4194304) {
        parame.a(28, this.A);
      }
      if ((this.c & 0x800000) == 8388608) {
        parame.a(29, this.B);
      }
      if ((this.c & 0x1000000) == 16777216) {
        parame.a(30, this.C);
      }
      if ((this.c & 0x2000000) == 33554432) {
        parame.a(31, this.D);
      }
      if ((this.c & 0x4000000) == 67108864) {
        parame.a(32, this.E);
      }
      if ((this.c & 0x8000000) == 134217728) {
        parame.a(33, this.F);
      }
      if ((this.c & 0x10000000) == 268435456) {
        parame.a(34, this.G);
      }
      if ((this.c & 0x20000000) == 536870912) {
        parame.a(35, this.H);
      }
      if ((this.c & 0x40000000) == 1073741824) {
        parame.a(36, aJ());
      }
      if ((this.c & 0x80000000) == Integer.MIN_VALUE) {
        parame.a(37, this.J);
      }
      if ((this.d & 0x1) == 1) {
        parame.a(38, aK());
      }
      if ((this.d & 0x2) == 2) {
        parame.a(39, this.L);
      }
      if ((this.d & 0x4) == 4) {
        parame.a(40, this.M);
      }
      if ((this.d & 0x8) == 8) {
        parame.a(41, this.N);
      }
      if ((this.d & 0x10) == 16) {
        parame.a(42, this.O);
      }
      if ((this.d & 0x20) == 32) {
        parame.a(43, this.P);
      }
      if ((this.d & 0x40) == 64) {
        parame.a(44, this.Q);
      }
      if ((this.d & 0x80) == 128) {
        parame.a(45, aL());
      }
      if ((this.d & 0x100) == 256) {
        parame.a(46, this.S);
      }
    }
    
    public final boolean aa()
    {
      return (this.c & 0x80000000) == Integer.MIN_VALUE;
    }
    
    public final int ab()
    {
      return this.J;
    }
    
    public final boolean ac()
    {
      return (this.d & 0x1) == 1;
    }
    
    public final boolean ad()
    {
      return (this.d & 0x2) == 2;
    }
    
    public final c ae()
    {
      return this.L;
    }
    
    public final boolean af()
    {
      return (this.d & 0x4) == 4;
    }
    
    public final c ag()
    {
      return this.M;
    }
    
    public final boolean ah()
    {
      return (this.d & 0x8) == 8;
    }
    
    public final int ai()
    {
      return this.N;
    }
    
    public final boolean aj()
    {
      return (this.d & 0x10) == 16;
    }
    
    public final int ak()
    {
      return this.O;
    }
    
    public final boolean al()
    {
      return (this.d & 0x20) == 32;
    }
    
    public final long am()
    {
      return this.P;
    }
    
    public final boolean an()
    {
      return (this.d & 0x40) == 64;
    }
    
    public final boolean ao()
    {
      return this.Q;
    }
    
    public final boolean ap()
    {
      return (this.d & 0x80) == 128;
    }
    
    public final boolean aq()
    {
      return (this.d & 0x100) == 256;
    }
    
    public final boolean ar()
    {
      return this.S;
    }
    
    public final a at()
    {
      return a.g().a(this);
    }
    
    public final int c()
    {
      int i1 = this.U;
      if (i1 != -1) {
        return i1;
      }
      int i2 = 0;
      if ((this.c & 0x1) == 1) {
        i2 = e.b(1, this.e) + 0;
      }
      i1 = i2;
      if ((this.c & 0x2) == 2) {
        i1 = i2 + e.b(2, this.f);
      }
      i2 = i1;
      if ((this.c & 0x4) == 4) {
        i2 = i1 + e.b(3, au());
      }
      i1 = i2;
      if ((this.c & 0x8) == 8) {
        i1 = i2 + e.b(4, av());
      }
      i2 = i1;
      if ((this.c & 0x10) == 16) {
        i2 = i1 + e.b(5, aw());
      }
      i1 = i2;
      if ((this.c & 0x20) == 32) {
        i1 = i2 + e.b(6, ax());
      }
      i2 = i1;
      if ((this.c & 0x40) == 64) {
        i2 = i1 + e.b(7, ay());
      }
      i1 = i2;
      if ((this.c & 0x80) == 128) {
        i1 = i2 + e.b(8, az());
      }
      i2 = i1;
      if ((this.c & 0x100) == 256) {
        i2 = i1 + e.b(9, aA());
      }
      i1 = i2;
      if ((this.c & 0x200) == 512) {
        i1 = i2 + e.c(10, this.n);
      }
      i2 = i1;
      if ((this.c & 0x400) == 1024) {
        i2 = i1 + e.c(11, this.o);
      }
      i1 = i2;
      if ((this.c & 0x800) == 2048) {
        i1 = i2 + e.b(13, aB());
      }
      i2 = i1;
      if ((this.c & 0x1000) == 4096) {
        i2 = i1 + e.b(14, aC());
      }
      i1 = i2;
      if ((this.c & 0x2000) == 8192) {
        i1 = i2 + e.b(15, aD());
      }
      i2 = i1;
      if ((this.c & 0x4000) == 16384) {
        i2 = i1 + e.b(16, aE());
      }
      i1 = i2;
      if ((this.c & 0x8000) == 32768) {
        i1 = i2 + e.b(20, aF());
      }
      i2 = i1;
      if ((this.c & 0x10000) == 65536) {
        i2 = i1 + e.b(21, aG());
      }
      i1 = i2;
      if ((this.c & 0x20000) == 131072) {
        i1 = i2 + e.b(22, aH());
      }
      i2 = i1;
      if ((this.c & 0x40000) == 262144) {
        i2 = i1 + e.c(23, this.w);
      }
      i1 = i2;
      if ((this.c & 0x80000) == 524288) {
        i1 = i2 + e.b(25, aI());
      }
      i2 = i1;
      if ((this.c & 0x100000) == 1048576) {
        i2 = i1 + e.c(26, this.y);
      }
      i1 = i2;
      if ((this.c & 0x200000) == 2097152) {
        i1 = i2 + e.c(27, this.z);
      }
      i2 = i1;
      if ((this.c & 0x400000) == 4194304) {
        i2 = i1 + e.b(28, this.A);
      }
      i1 = i2;
      if ((this.c & 0x800000) == 8388608) {
        i1 = i2 + e.c(29, this.B);
      }
      i2 = i1;
      if ((this.c & 0x1000000) == 16777216) {
        i2 = i1 + e.c(30, this.C);
      }
      i1 = i2;
      if ((this.c & 0x2000000) == 33554432) {
        i1 = i2 + e.c(31, this.D);
      }
      i2 = i1;
      if ((this.c & 0x4000000) == 67108864) {
        i2 = i1 + e.c(32, this.E);
      }
      i1 = i2;
      if ((this.c & 0x8000000) == 134217728) {
        i1 = i2 + e.c(33, this.F);
      }
      i2 = i1;
      if ((this.c & 0x10000000) == 268435456) {
        i2 = i1 + e.c(34, this.G);
      }
      i1 = i2;
      if ((this.c & 0x20000000) == 536870912) {
        i1 = i2 + e.c(35, this.H);
      }
      i2 = i1;
      if ((this.c & 0x40000000) == 1073741824) {
        i2 = i1 + e.b(36, aJ());
      }
      i1 = i2;
      if ((this.c & 0x80000000) == Integer.MIN_VALUE) {
        i1 = i2 + e.c(37, this.J);
      }
      i2 = i1;
      if ((this.d & 0x1) == 1) {
        i2 = i1 + e.b(38, aK());
      }
      i1 = i2;
      if ((this.d & 0x2) == 2) {
        i1 = i2 + e.b(39, this.L);
      }
      i2 = i1;
      if ((this.d & 0x4) == 4) {
        i2 = i1 + e.b(40, this.M);
      }
      i1 = i2;
      if ((this.d & 0x8) == 8) {
        i1 = i2 + e.c(41, this.N);
      }
      i2 = i1;
      if ((this.d & 0x10) == 16) {
        i2 = i1 + e.c(42, this.O);
      }
      i1 = i2;
      if ((this.d & 0x20) == 32) {
        i1 = i2 + e.b(43, this.P);
      }
      i2 = i1;
      boolean bool;
      if ((this.d & 0x40) == 64)
      {
        bool = this.Q;
        i2 = i1 + e.a(44);
      }
      i1 = i2;
      if ((this.d & 0x80) == 128) {
        i1 = i2 + e.b(45, aL());
      }
      i2 = i1;
      if ((this.d & 0x100) == 256)
      {
        bool = this.S;
        i2 = i1 + e.a(46);
      }
      this.U = i2;
      return i2;
    }
    
    public final boolean e()
    {
      int i1 = this.T;
      if (i1 != -1) {
        return i1 == 1;
      }
      this.T = 1;
      return true;
    }
    
    public final boolean g()
    {
      return (this.c & 0x1) == 1;
    }
    
    public final long h()
    {
      return this.e;
    }
    
    public final boolean i()
    {
      return (this.c & 0x2) == 2;
    }
    
    public final long j()
    {
      return this.f;
    }
    
    public final boolean k()
    {
      return (this.c & 0x4) == 4;
    }
    
    public final boolean l()
    {
      return (this.c & 0x8) == 8;
    }
    
    public final boolean m()
    {
      return (this.c & 0x10) == 16;
    }
    
    public final boolean n()
    {
      return (this.c & 0x20) == 32;
    }
    
    public final boolean o()
    {
      return (this.c & 0x40) == 64;
    }
    
    public final boolean p()
    {
      return (this.c & 0x80) == 128;
    }
    
    public final boolean q()
    {
      return (this.c & 0x100) == 256;
    }
    
    public final boolean r()
    {
      return (this.c & 0x200) == 512;
    }
    
    public final int s()
    {
      return this.n;
    }
    
    public final boolean t()
    {
      return (this.c & 0x400) == 1024;
    }
    
    public final int u()
    {
      return this.o;
    }
    
    public final boolean v()
    {
      return (this.c & 0x800) == 2048;
    }
    
    public final boolean w()
    {
      return (this.c & 0x1000) == 4096;
    }
    
    public final boolean x()
    {
      return (this.c & 0x2000) == 8192;
    }
    
    public final boolean y()
    {
      return (this.c & 0x4000) == 16384;
    }
    
    public final boolean z()
    {
      return (this.c & 0x8000) == 32768;
    }
    
    public static final class a
      extends g.a
      implements h.b
    {
      private int A;
      private int B;
      private int C;
      private int D;
      private int E;
      private int F;
      private Object G = "";
      private int H;
      private Object I = "";
      private c J = c.a;
      private c K = c.a;
      private int L;
      private int M;
      private long N;
      private boolean O;
      private Object P = "";
      private boolean Q;
      private int a;
      private int b;
      private long c;
      private long d;
      private Object e = "";
      private Object f = "";
      private Object g = "";
      private Object h = "";
      private Object i = "";
      private Object j = "";
      private Object k = "";
      private int l;
      private int m;
      private Object n = "";
      private Object o = "";
      private Object p = "";
      private Object q = "";
      private Object r = "";
      private Object s = "";
      private Object t = "";
      private int u;
      private Object v = "";
      private int w;
      private int x;
      private long y;
      private int z;
      
      private a h()
      {
        return new a().a(f());
      }
      
      public final a a(int paramInt)
      {
        this.a |= 0x200;
        this.l = paramInt;
        return this;
      }
      
      public final a a(long paramLong)
      {
        this.a |= 0x1;
        this.c = paramLong;
        return this;
      }
      
      public final a a(c paramc)
      {
        if (paramc == null) {
          throw new NullPointerException();
        }
        this.b |= 0x2;
        this.J = paramc;
        return this;
      }
      
      public final a a(h.a parama)
      {
        if (parama == h.a.f()) {}
        do
        {
          return this;
          if (parama.g()) {
            a(parama.h());
          }
          if (parama.i()) {
            b(parama.j());
          }
          if (parama.k())
          {
            this.a |= 0x4;
            this.e = h.a.b(parama);
          }
          if (parama.l())
          {
            this.a |= 0x8;
            this.f = h.a.c(parama);
          }
          if (parama.m())
          {
            this.a |= 0x10;
            this.g = h.a.d(parama);
          }
          if (parama.n())
          {
            this.a |= 0x20;
            this.h = h.a.e(parama);
          }
          if (parama.o())
          {
            this.a |= 0x40;
            this.i = h.a.f(parama);
          }
          if (parama.p())
          {
            this.a |= 0x80;
            this.j = h.a.g(parama);
          }
          if (parama.q())
          {
            this.a |= 0x100;
            this.k = h.a.h(parama);
          }
          if (parama.r()) {
            a(parama.s());
          }
          if (parama.t()) {
            b(parama.u());
          }
          if (parama.v())
          {
            this.a |= 0x800;
            this.n = h.a.i(parama);
          }
          if (parama.w())
          {
            this.a |= 0x1000;
            this.o = h.a.j(parama);
          }
          if (parama.x())
          {
            this.a |= 0x2000;
            this.p = h.a.k(parama);
          }
          if (parama.y())
          {
            this.a |= 0x4000;
            this.q = h.a.l(parama);
          }
          if (parama.z())
          {
            this.a |= 0x8000;
            this.r = h.a.m(parama);
          }
          if (parama.A())
          {
            this.a |= 0x10000;
            this.s = h.a.n(parama);
          }
          if (parama.B())
          {
            this.a |= 0x20000;
            this.t = h.a.o(parama);
          }
          if (parama.C()) {
            c(parama.D());
          }
          if (parama.E())
          {
            this.a |= 0x80000;
            this.v = h.a.p(parama);
          }
          if (parama.F()) {
            d(parama.G());
          }
          if (parama.H()) {
            e(parama.I());
          }
          if (parama.J()) {
            c(parama.K());
          }
          if (parama.L()) {
            f(parama.M());
          }
          if (parama.N()) {
            g(parama.O());
          }
          if (parama.P()) {
            h(parama.Q());
          }
          if (parama.R()) {
            i(parama.S());
          }
          if (parama.T()) {
            j(parama.U());
          }
          if (parama.V()) {
            k(parama.W());
          }
          if (parama.X()) {
            l(parama.Y());
          }
          if (parama.Z())
          {
            this.a |= 0x40000000;
            this.G = h.a.q(parama);
          }
          if (parama.aa()) {
            m(parama.ab());
          }
          if (parama.ac())
          {
            this.b |= 0x1;
            this.I = h.a.r(parama);
          }
          if (parama.ad()) {
            a(parama.ae());
          }
          if (parama.af()) {
            b(parama.ag());
          }
          if (parama.ah()) {
            n(parama.ai());
          }
          if (parama.aj()) {
            o(parama.ak());
          }
          if (parama.al()) {
            d(parama.am());
          }
          if (parama.an()) {
            a(parama.ao());
          }
          if (parama.ap())
          {
            this.b |= 0x80;
            this.P = h.a.s(parama);
          }
        } while (!parama.aq());
        b(parama.ar());
        return this;
      }
      
      public final a a(String paramString)
      {
        if (paramString == null) {
          throw new NullPointerException();
        }
        this.a |= 0x4;
        this.e = paramString;
        return this;
      }
      
      public final a a(boolean paramBoolean)
      {
        this.b |= 0x40;
        this.O = paramBoolean;
        return this;
      }
      
      public final a b(int paramInt)
      {
        this.a |= 0x400;
        this.m = paramInt;
        return this;
      }
      
      public final a b(long paramLong)
      {
        this.a |= 0x2;
        this.d = paramLong;
        return this;
      }
      
      public final a b(c paramc)
      {
        if (paramc == null) {
          throw new NullPointerException();
        }
        this.b |= 0x4;
        this.K = paramc;
        return this;
      }
      
      public final a b(String paramString)
      {
        if (paramString == null) {
          throw new NullPointerException();
        }
        this.a |= 0x8;
        this.f = paramString;
        return this;
      }
      
      public final a b(boolean paramBoolean)
      {
        this.b |= 0x100;
        this.Q = paramBoolean;
        return this;
      }
      
      public final a c(int paramInt)
      {
        this.a |= 0x40000;
        this.u = paramInt;
        return this;
      }
      
      public final a c(long paramLong)
      {
        this.a |= 0x400000;
        this.y = paramLong;
        return this;
      }
      
      public final a c(String paramString)
      {
        if (paramString == null) {
          throw new NullPointerException();
        }
        this.a |= 0x10;
        this.g = paramString;
        return this;
      }
      
      public final a d(int paramInt)
      {
        this.a |= 0x100000;
        this.w = paramInt;
        return this;
      }
      
      public final a d(long paramLong)
      {
        this.b |= 0x20;
        this.N = paramLong;
        return this;
      }
      
      public final a d(String paramString)
      {
        if (paramString == null) {
          throw new NullPointerException();
        }
        this.a |= 0x20;
        this.h = paramString;
        return this;
      }
      
      public final h.a d()
      {
        h.a locala = f();
        if (!locala.e()) {
          throw new q();
        }
        return locala;
      }
      
      public final a e(int paramInt)
      {
        this.a |= 0x200000;
        this.x = paramInt;
        return this;
      }
      
      public final a e(String paramString)
      {
        if (paramString == null) {
          throw new NullPointerException();
        }
        this.a |= 0x40;
        this.i = paramString;
        return this;
      }
      
      public final boolean e()
      {
        return true;
      }
      
      public final a f(int paramInt)
      {
        this.a |= 0x800000;
        this.z = paramInt;
        return this;
      }
      
      public final a f(String paramString)
      {
        if (paramString == null) {
          throw new NullPointerException();
        }
        this.a |= 0x80;
        this.j = paramString;
        return this;
      }
      
      public final h.a f()
      {
        int i4 = 1;
        h.a locala = new h.a('\000');
        int i6 = this.a;
        int i5 = this.b;
        if ((i6 & 0x1) == 1) {}
        for (int i2 = 1;; i2 = 0)
        {
          h.a.a(locala, this.c);
          int i1 = i2;
          if ((i6 & 0x2) == 2) {
            i1 = i2 | 0x2;
          }
          h.a.b(locala, this.d);
          i2 = i1;
          if ((i6 & 0x4) == 4) {
            i2 = i1 | 0x4;
          }
          h.a.a(locala, this.e);
          i1 = i2;
          if ((i6 & 0x8) == 8) {
            i1 = i2 | 0x8;
          }
          h.a.b(locala, this.f);
          i2 = i1;
          if ((i6 & 0x10) == 16) {
            i2 = i1 | 0x10;
          }
          h.a.c(locala, this.g);
          i1 = i2;
          if ((i6 & 0x20) == 32) {
            i1 = i2 | 0x20;
          }
          h.a.d(locala, this.h);
          i2 = i1;
          if ((i6 & 0x40) == 64) {
            i2 = i1 | 0x40;
          }
          h.a.e(locala, this.i);
          i1 = i2;
          if ((i6 & 0x80) == 128) {
            i1 = i2 | 0x80;
          }
          h.a.f(locala, this.j);
          i2 = i1;
          if ((i6 & 0x100) == 256) {
            i2 = i1 | 0x100;
          }
          h.a.g(locala, this.k);
          i1 = i2;
          if ((i6 & 0x200) == 512) {
            i1 = i2 | 0x200;
          }
          h.a.a(locala, this.l);
          i2 = i1;
          if ((i6 & 0x400) == 1024) {
            i2 = i1 | 0x400;
          }
          h.a.b(locala, this.m);
          i1 = i2;
          if ((i6 & 0x800) == 2048) {
            i1 = i2 | 0x800;
          }
          h.a.h(locala, this.n);
          i2 = i1;
          if ((i6 & 0x1000) == 4096) {
            i2 = i1 | 0x1000;
          }
          h.a.i(locala, this.o);
          i1 = i2;
          if ((i6 & 0x2000) == 8192) {
            i1 = i2 | 0x2000;
          }
          h.a.j(locala, this.p);
          i2 = i1;
          if ((i6 & 0x4000) == 16384) {
            i2 = i1 | 0x4000;
          }
          h.a.k(locala, this.q);
          i1 = i2;
          if ((i6 & 0x8000) == 32768) {
            i1 = i2 | 0x8000;
          }
          h.a.l(locala, this.r);
          i2 = i1;
          if ((i6 & 0x10000) == 65536) {
            i2 = i1 | 0x10000;
          }
          h.a.m(locala, this.s);
          i1 = i2;
          if ((0x20000 & i6) == 131072) {
            i1 = i2 | 0x20000;
          }
          h.a.n(locala, this.t);
          i2 = i1;
          if ((0x40000 & i6) == 262144) {
            i2 = i1 | 0x40000;
          }
          h.a.c(locala, this.u);
          i1 = i2;
          if ((0x80000 & i6) == 524288) {
            i1 = i2 | 0x80000;
          }
          h.a.o(locala, this.v);
          i2 = i1;
          if ((0x100000 & i6) == 1048576) {
            i2 = i1 | 0x100000;
          }
          h.a.d(locala, this.w);
          i1 = i2;
          if ((0x200000 & i6) == 2097152) {
            i1 = i2 | 0x200000;
          }
          h.a.e(locala, this.x);
          i2 = i1;
          if ((0x400000 & i6) == 4194304) {
            i2 = i1 | 0x400000;
          }
          h.a.c(locala, this.y);
          i1 = i2;
          if ((0x800000 & i6) == 8388608) {
            i1 = i2 | 0x800000;
          }
          h.a.f(locala, this.z);
          i2 = i1;
          if ((0x1000000 & i6) == 16777216) {
            i2 = i1 | 0x1000000;
          }
          h.a.g(locala, this.A);
          i1 = i2;
          if ((0x2000000 & i6) == 33554432) {
            i1 = i2 | 0x2000000;
          }
          h.a.h(locala, this.B);
          i2 = i1;
          if ((0x4000000 & i6) == 67108864) {
            i2 = i1 | 0x4000000;
          }
          h.a.i(locala, this.C);
          i1 = i2;
          if ((0x8000000 & i6) == 134217728) {
            i1 = i2 | 0x8000000;
          }
          h.a.j(locala, this.D);
          i2 = i1;
          if ((0x10000000 & i6) == 268435456) {
            i2 = i1 | 0x10000000;
          }
          h.a.k(locala, this.E);
          i1 = i2;
          if ((0x20000000 & i6) == 536870912) {
            i1 = i2 | 0x20000000;
          }
          h.a.l(locala, this.F);
          i2 = i1;
          if ((0x40000000 & i6) == 1073741824) {
            i2 = i1 | 0x40000000;
          }
          h.a.p(locala, this.G);
          int i3 = i2;
          if ((i6 & 0x80000000) == Integer.MIN_VALUE) {
            i3 = i2 | 0x80000000;
          }
          h.a.m(locala, this.H);
          if ((i5 & 0x1) == 1) {}
          for (i2 = i4;; i2 = 0)
          {
            h.a.q(locala, this.I);
            i1 = i2;
            if ((i5 & 0x2) == 2) {
              i1 = i2 | 0x2;
            }
            h.a.a(locala, this.J);
            i2 = i1;
            if ((i5 & 0x4) == 4) {
              i2 = i1 | 0x4;
            }
            h.a.b(locala, this.K);
            i1 = i2;
            if ((i5 & 0x8) == 8) {
              i1 = i2 | 0x8;
            }
            h.a.n(locala, this.L);
            i2 = i1;
            if ((i5 & 0x10) == 16) {
              i2 = i1 | 0x10;
            }
            h.a.o(locala, this.M);
            i1 = i2;
            if ((i5 & 0x20) == 32) {
              i1 = i2 | 0x20;
            }
            h.a.d(locala, this.N);
            i2 = i1;
            if ((i5 & 0x40) == 64) {
              i2 = i1 | 0x40;
            }
            h.a.a(locala, this.O);
            i1 = i2;
            if ((i5 & 0x80) == 128) {
              i1 = i2 | 0x80;
            }
            h.a.r(locala, this.P);
            i2 = i1;
            if ((i5 & 0x100) == 256) {
              i2 = i1 | 0x100;
            }
            h.a.b(locala, this.Q);
            h.a.p(locala, i3);
            h.a.q(locala, i2);
            return locala;
          }
        }
      }
      
      public final a g(int paramInt)
      {
        this.a |= 0x1000000;
        this.A = paramInt;
        return this;
      }
      
      public final a g(String paramString)
      {
        if (paramString == null) {
          throw new NullPointerException();
        }
        this.a |= 0x100;
        this.k = paramString;
        return this;
      }
      
      public final a h(int paramInt)
      {
        this.a |= 0x2000000;
        this.B = paramInt;
        return this;
      }
      
      public final a h(String paramString)
      {
        if (paramString == null) {
          throw new NullPointerException();
        }
        this.a |= 0x1000;
        this.o = paramString;
        return this;
      }
      
      public final a i(int paramInt)
      {
        this.a |= 0x4000000;
        this.C = paramInt;
        return this;
      }
      
      public final a i(String paramString)
      {
        if (paramString == null) {
          throw new NullPointerException();
        }
        this.a |= 0x2000;
        this.p = paramString;
        return this;
      }
      
      public final a j(int paramInt)
      {
        this.a |= 0x8000000;
        this.D = paramInt;
        return this;
      }
      
      public final a j(String paramString)
      {
        if (paramString == null) {
          throw new NullPointerException();
        }
        this.a |= 0x4000;
        this.q = paramString;
        return this;
      }
      
      public final a k(int paramInt)
      {
        this.a |= 0x10000000;
        this.E = paramInt;
        return this;
      }
      
      public final a k(String paramString)
      {
        if (paramString == null) {
          throw new NullPointerException();
        }
        this.a |= 0x8000;
        this.r = paramString;
        return this;
      }
      
      public final a l(int paramInt)
      {
        this.a |= 0x20000000;
        this.F = paramInt;
        return this;
      }
      
      public final a l(String paramString)
      {
        if (paramString == null) {
          throw new NullPointerException();
        }
        this.a |= 0x10000;
        this.s = paramString;
        return this;
      }
      
      public final a m(int paramInt)
      {
        this.a |= 0x80000000;
        this.H = paramInt;
        return this;
      }
      
      public final a m(String paramString)
      {
        if (paramString == null) {
          throw new NullPointerException();
        }
        this.a |= 0x20000;
        this.t = paramString;
        return this;
      }
      
      public final a n(int paramInt)
      {
        this.b |= 0x8;
        this.L = paramInt;
        return this;
      }
      
      public final a n(String paramString)
      {
        if (paramString == null) {
          throw new NullPointerException();
        }
        this.a |= 0x80000;
        this.v = paramString;
        return this;
      }
      
      public final a o(int paramInt)
      {
        this.b |= 0x10;
        this.M = paramInt;
        return this;
      }
      
      public final a o(String paramString)
      {
        if (paramString == null) {
          throw new NullPointerException();
        }
        this.a |= 0x40000000;
        this.G = paramString;
        return this;
      }
      
      public final a p(String paramString)
      {
        if (paramString == null) {
          throw new NullPointerException();
        }
        this.b |= 0x1;
        this.I = paramString;
        return this;
      }
      
      public final a q(String paramString)
      {
        if (paramString == null) {
          throw new NullPointerException();
        }
        this.b |= 0x80;
        this.P = paramString;
        return this;
      }
    }
  }
  
  public static abstract interface b
    extends n
  {}
}


/* Location:              /Users/amaurremi/uw/stringoid/static-dynamic-comparison/apps/broken screen/mobi.borken.android.brokenscreen-20-dex2jar.jar!/com/appbrain/e/h.class
 * Java compiler version: 6 (50.0)
 * JD-Core Version:       0.7.1
 */